Workbook

Sheet Start
A2: The STR Ledger
A4: Escape the W2 Planner — Lite
A5: When the math says you can.
A7: STR-001 · v1.0 · LITE
A8: OPTIMISTIC QUIT DATE
A9: ='Quit Date Calculator'!C7
A11: CONSERVATIVE QUIT DATE
A12: ='Quit Date Calculator'!C8
A14: ="Spread: "&TEXT('Quit Date Calculator'!C9,"0.0")&" years between best- and worst-case."
A16: PROPS NEEDED | D16: CASH NEEDED AT QUIT | G16: HEALTHCARE BRIDGE | J16: Y1 PROJECTED NET
A17: ='Target State'!C20 | D17: ='Target State'!C22 | G17: ="(Full only)" | J17: ='Quit Date Calculator'!C19
A20: ="You're "&TEXT('Target State'!C20-'Current State'!C16,"0")&" properties and "&TEXT(MAX(0,'Target State'!C22-'Current State'!C18),"$#,##0")&" away from the target. Two paths get you there: "&TEXT('Quit Date Calculator'!C7,"mmm yyyy")&" optimistic, "&TEXT('Quit Date Calculator'!C8,"mmm yyyy")&" conservative. The biggest swing factor is acquisition pace. Re-run when you close on a property."
A24: =HYPERLINK("#'Current State'!A1", "Current State") | D24: =HYPERLINK("#'Target State'!A1", "Target State") | G24: =HYPERLINK("#'Quit Date Calculator'!A1", "Quit Date") | J24: =HYPERLINK("https://thestrledger.com/escape-w2", "Upgrade →")
A33: Need healthcare bridge math, partner risk-share, and the printable conversation doc? Upgrade to Full at thestrledger.com/escape-w2 — $47.
A36: Questions? hello@thestrledger.com
A37: STR-001 · v1.0 · LITE · Free updates forever

Sheet Current State
A2: =HYPERLINK("#'Start'!A1", "← BACK") | D2: CURRENT STATE | J2: =HYPERLINK("#'Target State'!A1", "NEXT →")
A4: Section 1 — what you have today: W2, partner income, STR portfolio, runway.
A6: PLAN ANCHOR
B7: Plan start date: | C7: 46143 | E7: Today's date — when you started this planning round
A9: HOUSEHOLD INCOME
B10: Your W2 gross ($/yr): | C10: 145000
B11: Your W2 net ($/yr): | C11: 98000 | E11: After taxes, 401k, benefits
B12: W2 benefits value ($/yr): | C12: 18000 | E12: Employer 401k match + health + life + disability
B13: Partner W2 net ($/yr): | C13: 72000 | E13: Zero if single-income household
A15: CURRENT STR PORTFOLIO
B16: # properties owned: | C16: 2
B17: Portfolio gross ($/yr): | C17: 58000 | E17: Total revenue across all properties YTD-annualized
B18: Portfolio net ($/yr): | C18: 19000 | E18: Schedule E line 26 — what hits your tax return
B19: Avg stab. net per prop ($/yr): | C19: 14000 | E19: Use a Y3 property — Y1/Y2 are depressed
A21: EXPENSES & RUNWAY
B22: Annual household expenses ($): | C22: 96000 | E22: All in — mortgage, food, kids, etc.
B23: Annual savings rate ($): | C23: 42000 | E23: What you actually deploy into properties each year
B24: Current liquid runway ($): | C24: 48000 | E24: Cash after closing on existing properties
A26: ROLLUP
B27: Total household income (net): | C27: =C11+C13+C18
B28: Income replaced by STR today: | C28: =IFERROR(C18/(C11+C12),0)
B29: Implied savings rate: | C29: =IFERROR(C23/(C11+C13+C18),0)
B30: Years runway covers expenses: | C30: =IFERROR(C24/C22,0)
A34: Questions? hello@thestrledger.com
A35: STR-001 · Current State

Sheet Target State
A2: =HYPERLINK("#'Current State'!A1", "← BACK") | D2: TARGET STATE | J2: =HYPERLINK("#'Quit Date Calculator'!A1", "NEXT →")
A4: Section 2 — what 'enough' looks like: replacement income, buffer, properties needed.
A6: REPLACEMENT INCOME
B7: Target replacement income ($/yr): | C7: 112000 | E7: Default = current W2 net + benefits cost + healthcare bridge
B8: Buffer multiple (×): | C8: 1.5 | E8: 1.5× = handle a bad year without panic
B9: Target liquid reserve at quit ($): | C9: 48000 | E9: Default 6 months of expenses
B10: Target stabilized net per prop ($/yr): | C10: 14000 | E10: Use the per-property economics you actually achieve
A12: WHAT THE MATH SAYS
B13: Buffered income required ($/yr): | C13: =C7*C8
B14: Less current STR portfolio net: | C14: ='Current State'!C18
B15: Net new STR income required: | C15: =MAX(0,C13-C14)
B16: Properties to add (rounded up): | C16: =IFERROR(CEILING(C15/C10,1),0)
B17: Total properties at quit: | C17: ='Current State'!C16+C16
A19: HEADLINE NUMBERS (referenced by Start tab)
B20: TOTAL PROPERTIES NEEDED: | C20: =C17
B21: Cash deployment per property ($): | C21: =95000
B22: TOTAL CASH NEEDED AT QUIT ($): | C22: =C16*C21+C9
A26: Questions? hello@thestrledger.com
A27: STR-001 · Target State

Sheet Quit Date Calculator
A2: =HYPERLINK("#'Target State'!A1", "← BACK") | D2: QUIT DATE CALCULATOR
A4: Section 3 — the math behind the headline date. Adjust assumptions below.
A6: QUIT DATES
B7: Optimistic quit date: | C7: =EDATE('Current State'!C7,(MAX(0,'Target State'!C16/3.0))*12)
B8: Conservative quit date: | C8: =EDATE('Current State'!C7,(MAX(0,'Target State'!C16/1.5)*1.15)*12)
B9: Spread (years): | C9: =(C8-C7)/365.25
A11: ASSUMPTIONS (edit to test scenarios)
B12: Optimistic props/year: | C12: 3 | E12: Lite: fixed assumption — upgrade for editable scenarios
B13: Conservative props/year: | C13: 1.5 | E13: Lite: fixed assumption — upgrade for editable scenarios
A17: HEADLINE NUMBERS (referenced by Start tab)
B18: Stabilized portfolio at quit ($/yr): | C18: ='Target State'!C17*'Target State'!C10
B19: Y1 PROJECTED NET ($/yr): | C19: =C18*0.65
A23: Questions? hello@thestrledger.com
A24: STR-001 · Quit Date Calculator
