Workbook

Sheet Start
A2: The STR Ledger
A4: Furniture / Setup Budget
A5: Every room, every item — what you'll spend before the first guest.
A7: ACQ-007 · v1.0 · BLANK
A11: WHAT THIS DOES
A12: Walks you room-by-room through every essential furnishing item with cost benchmarks. Tracks estimated vs actual spend, MACRS class per item (5-yr / 7-yr / Decor), and a 60-day operating reserve so you don't run dry the week you launch.
A17: BUDGET (EST) | D17: SPENT (ACTUAL) | G17: INSTALLED % | J17: $ TO FIRST STAY
A18: =SUM('Room Detail'!E6:E205) | D18: =SUM('Room Detail'!F6:F205) | G18: =IFERROR(COUNTIF('Room Detail'!H6:H205,"Installed")/COUNTA('Room Detail'!C6:C205),0) | J18: =SUM('Room Detail'!F6:F205)+'Operating Reserve'!C16
A23: =HYPERLINK("#'Room Detail'!A1", "Room Detail") | D23: =HYPERLINK("#'Per-Room Roll-up'!A1", "Per-Room Roll-up") | G23: =HYPERLINK("#'Operating Reserve'!A1", "Operating Reserve") | J23: =HYPERLINK("#'Settings'!A1", "Settings")
A27: =HYPERLINK("#'Room Detail'!B6", "→ ADD A NEW ITEM")
A32: HOW TO USE
A33: 1) On Settings — set property name + first-stay date. 2) On Room Detail — log every item: room, name, est cost, MACRS class. 3) As you buy: fill Actual cost + status. KPIs above and Roll-up update live.
A39: Questions? hello@thestrledger.com
A40: ACQ-007 · v1.0 · BLANK · Free updates forever

Sheet Room Detail
A2: =HYPERLINK("#'Start'!A1", "← BACK") | D2: ROOM DETAIL | J2: =HYPERLINK("#'Per-Room Roll-up'!A1", "NEXT →")
A4: Per-item register · 200 rows · yellow = edit · gray = formula · Status "Installed" counts toward completion %.
A5: # | B5: Room | C5: Item | D5: Description / brand | E5: Est cost | F5: Actual cost | G5: Vendor / source | H5: Status | I5: MACRS class | J5: Notes
A6: =IF(C6="","",ROW()-5)
A7: =IF(C7="","",ROW()-5)
A8: =IF(C8="","",ROW()-5)
A9: =IF(C9="","",ROW()-5)
A10: =IF(C10="","",ROW()-5)
A11: =IF(C11="","",ROW()-5)
A12: =IF(C12="","",ROW()-5)
A13: =IF(C13="","",ROW()-5)
A14: =IF(C14="","",ROW()-5)
A15: =IF(C15="","",ROW()-5)
A16: =IF(C16="","",ROW()-5)
A17: =IF(C17="","",ROW()-5)
... A205: =IF(C205="","",ROW()-5)

Sheet Per-Room Roll-up
A2: =HYPERLINK("#'Room Detail'!A1", "← BACK") | D2: PER-ROOM ROLL-UP | J2: =HYPERLINK("#'Operating Reserve'!A1", "NEXT →")
A4: Totals by room · bar chart "$ by room" anchored right of table.
A5: Room | B5: Est total | C5: Actual total | D5: Items | E5: Installed | F5: Completion %
A6: Living | B6: =SUMIF('Room Detail'!B6:B205,A6,'Room Detail'!E6:E205) | C6: =SUMIF('Room Detail'!B6:B205,A6,'Room Detail'!F6:F205) | D6: =COUNTIF('Room Detail'!B6:B205,A6) | E6: =COUNTIFS('Room Detail'!B6:B205,A6,'Room Detail'!H6:H205,"Installed") | F6: =IFERROR(E6/D6,0)
A7: Kitchen | B7: =SUMIF('Room Detail'!B6:B205,A7,'Room Detail'!E6:E205) | C7: =SUMIF('Room Detail'!B6:B205,A7,'Room Detail'!F6:F205) | D7: =COUNTIF('Room Detail'!B6:B205,A7) | E7: =COUNTIFS('Room Detail'!B6:B205,A7,'Room Detail'!H6:H205,"Installed") | F7: =IFERROR(E7/D7,0)
A8: Master BR | B8: =SUMIF('Room Detail'!B6:B205,A8,'Room Detail'!E6:E205) | C8: =SUMIF('Room Detail'!B6:B205,A8,'Room Detail'!F6:F205) | D8: =COUNTIF('Room Detail'!B6:B205,A8) | E8: =COUNTIFS('Room Detail'!B6:B205,A8,'Room Detail'!H6:H205,"Installed") | F8: =IFERROR(E8/D8,0)
A9: BR2 | B9: =SUMIF('Room Detail'!B6:B205,A9,'Room Detail'!E6:E205) | C9: =SUMIF('Room Detail'!B6:B205,A9,'Room Detail'!F6:F205) | D9: =COUNTIF('Room Detail'!B6:B205,A9) | E9: =COUNTIFS('Room Detail'!B6:B205,A9,'Room Detail'!H6:H205,"Installed") | F9: =IFERROR(E9/D9,0)
A10: BR3 | B10: =SUMIF('Room Detail'!B6:B205,A10,'Room Detail'!E6:E205) | C10: =SUMIF('Room Detail'!B6:B205,A10,'Room Detail'!F6:F205) | D10: =COUNTIF('Room Detail'!B6:B205,A10) | E10: =COUNTIFS('Room Detail'!B6:B205,A10,'Room Detail'!H6:H205,"Installed") | F10: =IFERROR(E10/D10,0)
A11: Master Bath | B11: =SUMIF('Room Detail'!B6:B205,A11,'Room Detail'!E6:E205) | C11: =SUMIF('Room Detail'!B6:B205,A11,'Room Detail'!F6:F205) | D11: =COUNTIF('Room Detail'!B6:B205,A11) | E11: =COUNTIFS('Room Detail'!B6:B205,A11,'Room Detail'!H6:H205,"Installed") | F11: =IFERROR(E11/D11,0)
A12: Bath2 | B12: =SUMIF('Room Detail'!B6:B205,A12,'Room Detail'!E6:E205) | C12: =SUMIF('Room Detail'!B6:B205,A12,'Room Detail'!F6:F205) | D12: =COUNTIF('Room Detail'!B6:B205,A12) | E12: =COUNTIFS('Room Detail'!B6:B205,A12,'Room Detail'!H6:H205,"Installed") | F12: =IFERROR(E12/D12,0)
A13: Patio/Outdoor | B13: =SUMIF('Room Detail'!B6:B205,A13,'Room Detail'!E6:E205) | C13: =SUMIF('Room Detail'!B6:B205,A13,'Room Detail'!F6:F205) | D13: =COUNTIF('Room Detail'!B6:B205,A13) | E13: =COUNTIFS('Room Detail'!B6:B205,A13,'Room Detail'!H6:H205,"Installed") | F13: =IFERROR(E13/D13,0)
A14: Laundry | B14: =SUMIF('Room Detail'!B6:B205,A14,'Room Detail'!E6:E205) | C14: =SUMIF('Room Detail'!B6:B205,A14,'Room Detail'!F6:F205) | D14: =COUNTIF('Room Detail'!B6:B205,A14) | E14: =COUNTIFS('Room Detail'!B6:B205,A14,'Room Detail'!H6:H205,"Installed") | F14: =IFERROR(E14/D14,0)
A15: Decor | B15: =SUMIF('Room Detail'!B6:B205,A15,'Room Detail'!E6:E205) | C15: =SUMIF('Room Detail'!B6:B205,A15,'Room Detail'!F6:F205) | D15: =COUNTIF('Room Detail'!B6:B205,A15) | E15: =COUNTIFS('Room Detail'!B6:B205,A15,'Room Detail'!H6:H205,"Installed") | F15: =IFERROR(E15/D15,0)
A16: Tech | B16: =SUMIF('Room Detail'!B6:B205,A16,'Room Detail'!E6:E205) | C16: =SUMIF('Room Detail'!B6:B205,A16,'Room Detail'!F6:F205) | D16: =COUNTIF('Room Detail'!B6:B205,A16) | E16: =COUNTIFS('Room Detail'!B6:B205,A16,'Room Detail'!H6:H205,"Installed") | F16: =IFERROR(E16/D16,0)
A17: TOTAL | B17: =SUM(B6:B16) | C17: =SUM(C6:C16) | D17: =SUM(D6:D16) | E17: =SUM(E6:E16) | F17: =IFERROR(E17/D17,0)
A22: Questions? hello@thestrledger.com
A23: ACQ-007 · Per-Room Roll-up

Sheet Operating Reserve
A2: =HYPERLINK("#'Per-Room Roll-up'!A1", "← BACK") | D2: OPERATING RESERVE | J2: =HYPERLINK("#'Settings'!A1", "NEXT →")
A4: 60-day setup-phase costs — fixed costs you'll pay BEFORE bookings stabilize. This is your "$ to first stay" reserve.
A6: SETUP-PHASE OPERATING COSTS
B7: Mortgage P&I × 60 days:
B8: Insurance (60-day proration):
B9: Utilities setup + 60 days:
B10: Property tax accrual (60 days):
B11: PMS / pricing software (60d):
B12: Marketing prep + listing photos:
B13: Cleaning + supplies stock-up:
B14: Contingency (5%):
B16: TOTAL OPERATING RESERVE | C16: =SUM(C7:C14)
A18: Why this matters: hosts who skip the operating reserve burn furniture money on month-1 cleaning + insurance + utilities, then can't replace the broken thing the first guest reports. Keep this segregated.
A23: Questions? hello@thestrledger.com
A24: ACQ-007 · Operating Reserve

Sheet Settings
A2: =HYPERLINK("#'Operating Reserve'!A1", "← BACK") | D2: SETTINGS
A4: Property meta · MACRS class options · year-end archive table
A5: PROPERTY
B7: Property name:
B9: Setup start date: | E9: Use ISO YYYY-MM-DD
B11: First-stay target: | E11: Drives "$ to first stay" countdown
B13: Operating reserve days: | E13: Default 60 — adjust if pre-bookings start sooner
B15: Active year: | E15: Used for date-filtered views and archive
A18: MACRS CLASS REFERENCE
B20: 5-yr | C20: Appliances, electronics, computers, smart-home devices
B21: 7-yr | C21: Furniture, mattresses, rugs, fixtures, outdoor durables
B22: Decor — expense | C22: Linens, art, plants, books, candles (de minimis: <$2,500/item)
A25: YEAR-END ARCHIVE
A26: Each January, copy the YTD totals from Start tab into one row below, then clear Room Detail to start the new property build clean.
B28: Year | C28: Total Budget | D28: Total Spent | E28: # Items | F28: Notes
B29: 2026
B30: 2027
B31: 2028
B32: 2029
B33: 2030
B34: 2031
B35: 2032
A39: Questions? hello@thestrledger.com
A40: ACQ-007 · Settings
