Workbook

Sheet Start
A2: The STR Ledger
A4: Cost-to-Launch Calculator
A5: The all-in number — including what you'd forget.
A7: ACQ-002 · v1.0 · DEMO
A9: Typical 2BR cabin: $32K-$58K mid finish · 1BR condo: $18K-$28K · 4BR luxury: $90K-$160K
A11: YOUR LAUNCH BUDGET
A12: ='Total + Y1 ROI'!C14
A15: 90-DAY RESERVE | E15: CASH INVESTED | I15: Y1 CASH-ON-CASH
A16: ='90-Day Reserve'!C16 | E16: ='Total + Y1 ROI'!C19 | I16: ='Total + Y1 ROI'!C28
A20: =HYPERLINK("#'Acquisition'!A1", "Acquisition") | D20: =HYPERLINK("#'Furnish & Setup'!A1", "Furnish & Setup") | G20: =HYPERLINK("#'Launch Costs'!A1", "Launch Costs") | J20: =HYPERLINK("#'90-Day Reserve'!A1", "90-Day Reserve")
A24: =HYPERLINK("#'Total + Y1 ROI'!A1", "→ Total + Y1 ROI")
A29: Validate the deal numbers before you sign? Get the STR Deal Analyzer (ACQ-001) at thestrledger.com — $47, includes stress test.
A31: Join the email list — first launch checklist + 47 deduction guide free.
A34: Questions? hello@thestrledger.com
A35: ACQ-002 · v1.0 · DEMO · Free updates forever

Sheet Acquisition
A2: =HYPERLINK("#'Start'!A1", "← BACK") | D2: ACQUISITION | J2: =HYPERLINK("#'Furnish & Setup'!A1", "NEXT →")
A4: Section 1 of 4 — what it costs to BUY the property
A6: PROPERTY
B7: Property name: | C7: Smokies Ridge Cabin
B8: City, State: | C8: Gatlinburg, TN
B9: Bedrooms: | C9: 2 | E9: Drives furnishing zone counts (manual — adjust on Furnish tab)
B10: Bathrooms: | C10: 2
A12: PURCHASE & FINANCING
B13: Purchase price ($): | C13: 385000
B14: Down payment (%): | C14: 0.25 | E14: 20-25% typical for STR
B15: Interest rate (%): | C15: 0.07
B16: Term (years): | C16: 30 | E16: 30 typical
A18: DUE DILIGENCE & CLOSING
B19: Closing costs ($): | C19: 9000 | E19: 2-3% of purchase typical
B20: Inspection ($): | C20: 400 | E20: $300-500 typical
B21: Appraisal ($): | C21: 650 | E21: $500-800 typical
B22: Title insurance ($): | C22: 1100 | E22: May be in closing — check
B23: Legal / attorney ($): | C23: 1200
B24: Loan origination fee ($): | C24: 1500 | E24: 0.5-1% of loan
B25: Other due diligence ($): | C25: 300 | E25: Survey, environmental, etc.
A27: DERIVED
B28: Down payment ($): | C28: =C13*C14
B29: Loan amount ($): | C29: =C13*(1-C14)
B30: Monthly P&I: | C30: =IFERROR(PMT(C15/12,C16*12,-C29),0)
B31: Acquisition cash needed: | C31: =C28+SUM(C19:C25)
A35: Questions? hello@thestrledger.com
A36: ACQ-002 · Acquisition

Sheet Furnish & Setup
A2: =HYPERLINK("#'Acquisition'!A1", "← BACK") | D2: FURNISH & SETUP | J2: =HYPERLINK("#'Launch Costs'!A1", "NEXT →")
A4: Section 2 of 4 — pre-populated room-by-room checklist. Per-item: Low / Mid / High prices are real Amazon-tier benchmarks. Selected column = your choice (default Mid).
A6: Zone | B6: Item | C6: Low $ | D6: Mid $ | E6: High $ | F6: Selected $ | G6: Qty | H6: Line Total | J6: DID YOU FORGET?
A7: BEDROOM 1 | J7: LLC formation? | K7: =IF('Launch Costs'!C12>0,"OK","missing")
A8: Bedroom 1 | B8: Queen mattress | C8: 250 | D8: 650 | E8: 1200 | F8: =D8 | G8: 1 | H8: =F8*G8
A9: Bedroom 1 | B9: Bed frame + slats | C9: 120 | D9: 280 | E9: 650 | F9: =D9 | G9: 1 | H9: =F9*G9 | J9: Insurance binder? | K9: =IF('Launch Costs'!C14>0,"OK","missing")
A10: Bedroom 1 | B10: Headboard | C10: 80 | D10: 200 | E10: 500 | F10: =D10 | G10: 1 | H10: =F10*G10
A11: Bedroom 1 | B11: Sheet sets (2 sets) | C11: 60 | D11: 140 | E11: 300 | F11: =D11 | G11: 1 | H11: =F11*G11 | J11: =HYPERLINK("#'Furnish & Setup'!B141", "Smoke detectors?") | K11: =IF(H141>0,"OK","missing")
A12: Bedroom 1 | B12: Comforter / duvet | C12: 60 | D12: 150 | E12: 400 | F12: =D12 | G12: 1 | H12: =F12*G12
A13: Bedroom 1 | B13: Pillows (4) | C13: 40 | D13: 100 | E13: 240 | F13: =D13 | G13: 1 | H13: =F13*G13 | J13: =HYPERLINK("#'Furnish & Setup'!B142", "CO detectors?") | K13: =IF(H142>0,"OK","missing")
A14: Bedroom 1 | B14: Bedside lamps (pair) | C14: 40 | D14: 120 | E14: 280 | F14: =D14 | G14: 1 | H14: =F14*G14
A15: Bedroom 1 | B15: Blackout curtains | C15: 40 | D15: 90 | E15: 220 | F15: =D15 | G15: 1 | H15: =F15*G15 | J15: =HYPERLINK("#'Furnish & Setup'!B143", "Fire extinguisher?") | K15: =IF(H143>0,"OK","missing")
A16: Bedroom 1 | B16: Dresser / chest | C16: 150 | D16: 380 | E16: 900 | F16: =D16 | G16: 1 | H16: =F16*G16
A17: Bedroom 1 | B17: Closet system / hangers | C17: 25 | D17: 75 | E17: 180 | F17: =D17 | G17: 1 | H17: =F17*G17 | J17: =HYPERLINK("#'Furnish & Setup'!B144", "First aid kit?") | K17: =IF(H144>0,"OK","missing")
A18: Bedroom 1 | B18: Mirror (full-length) | C18: 40 | D18: 95 | E18: 240 | F18: =D18 | G18: 1 | H18: =F18*G18
A19: Bedroom 1 | B19: Wall art (3-piece set) | C19: 50 | D19: 140 | E19: 400 | F19: =D19 | G19: 1 | H19: =F19*G19 | J19: Pro photos? | K19: =IF('Launch Costs'!C8>0,"OK","missing")
A20: Bedroom 1 | B20: Area rug | C20: 80 | D20: 220 | E20: 600 | F20: =D20 | G20: 1 | H20: =F20*G20
A21: Bedroom 1 | B21: Nightstand (pair) | C21: 90 | D21: 240 | E21: 600 | F21: =D21 | G21: 1 | H21: =F21*G21 | J21: =HYPERLINK("#'Furnish & Setup'!B148", "Exterior security cam?") | K21: =IF(H148>0,"OK","missing")
A22: Bedroom 1 | B22: Throw blanket + accent pillows | C22: 35 | D22: 90 | E22: 220 | F22: =D22 | G22: 1 | H22: =F22*G22
B23: Bedroom 1 subtotal | C23: =SUM(C8:C22) | D23: =SUM(D8:D22) | E23: =SUM(E8:E22) | F23: =SUM(F8:F22) | H23: =SUM(H8:H22) | J23: Permit / business license? | K23: =IF('Launch Costs'!C10>0,"OK","missing")
A25: BEDROOM 2 | J25: Click any label to jump to the row. "OK" = you've accounted for it. "missing" = double-check before launch.
A26: Bedroom 2 | B26: Queen mattress | C26: 250 | D26: 650 | E26: 1200 | F26: =D26 | G26: 1 | H26: =F26*G26
A27: Bedroom 2 | B27: Bed frame + slats | C27: 120 | D27: 280 | E27: 650 | F27: =D27 | G27: 1 | H27: =F27*G27
A28: Bedroom 2 | B28: Headboard | C28: 80 | D28: 200 | E28: 500 | F28: =D28 | G28: 1 | H28: =F28*G28
A29: Bedroom 2 | B29: Sheet sets (2 sets) | C29: 60 | D29: 140 | E29: 300 | F29: =D29 | G29: 1 | H29: =F29*G29
A30: Bedroom 2 | B30: Comforter / duvet | C30: 60 | D30: 150 | E30: 400 | F30: =D30 | G30: 1 | H30: =F30*G30
A31: Bedroom 2 | B31: Pillows (4) | C31: 40 | D31: 100 | E31: 240 | F31: =D31 | G31: 1 | H31: =F31*G31
A32: Bedroom 2 | B32: Bedside lamps (pair) | C32: 40 | D32: 120 | E32: 280 | F32: =D32 | G32: 1 | H32: =F32*G32
A33: Bedroom 2 | B33: Blackout curtains | C33: 40 | D33: 90 | E33: 220 | F33: =D33 | G33: 1 | H33: =F33*G33
A34: Bedroom 2 | B34: Dresser / chest | C34: 150 | D34: 380 | E34: 900 | F34: =D34 | G34: 1 | H34: =F34*G34
A35: Bedroom 2 | B35: Closet system / hangers | C35: 25 | D35: 75 | E35: 180 | F35: =D35 | G35: 1 | H35: =F35*G35
A36: Bedroom 2 | B36: Mirror (full-length) | C36: 40 | D36: 95 | E36: 240 | F36: =D36 | G36: 1 | H36: =F36*G36
A37: Bedroom 2 | B37: Wall art (3-piece set) | C37: 50 | D37: 140 | E37: 400 | F37: =D37 | G37: 1 | H37: =F37*G37
... A40: Bedroom 2 | B40: Throw blanket + accent pillows | C40: 35 | D40: 90 | E40: 220 | F40: =D40 | G40: 1 | H40: =F40*G40
B41: Bedroom 2 subtotal | C41: =SUM(C26:C40) | D41: =SUM(D26:D40) | E41: =SUM(E26:E40) | F41: =SUM(F26:F40) | H41: =SUM(H26:H40)
A43: BATHROOM 1
A44: Bathroom 1 | B44: Towel sets (4 hand + 4 bath) | C44: 60 | D44: 140 | E44: 320 | F44: =D44 | G44: 1 | H44: =F44*G44
A45: Bathroom 1 | B45: Bath mats (2) | C45: 25 | D45: 55 | E45: 140 | F45: =D45 | G45: 1 | H45: =F45*G45
A46: Bathroom 1 | B46: Shower curtain + liner | C46: 25 | D46: 60 | E46: 140 | F46: =D46 | G46: 1 | H46: =F46*G46
A47: Bathroom 1 | B47: Soap + lotion dispensers | C47: 20 | D47: 50 | E47: 120 | F47: =D47 | G47: 1 | H47: =F47*G47
A48: Bathroom 1 | B48: Trash bin (covered) | C48: 20 | D48: 45 | E48: 110 | F48: =D48 | G48: 1 | H48: =F48*G48
A49: Bathroom 1 | B49: Toilet brush + holder | C49: 15 | D49: 35 | E49: 80 | F49: =D49 | G49: 1 | H49: =F49*G49
A50: Bathroom 1 | B50: Plunger | C50: 12 | D50: 25 | E50: 50 | F50: =D50 | G50: 1 | H50: =F50*G50
A51: Bathroom 1 | B51: Toilet paper holder | C51: 15 | D51: 35 | E51: 80 | F51: =D51 | G51: 1 | H51: =F51*G51
A52: Bathroom 1 | B52: Wall hooks / robe hooks | C52: 15 | D52: 35 | E52: 90 | F52: =D52 | G52: 1 | H52: =F52*G52
A53: Bathroom 1 | B53: Wall art | C53: 30 | D53: 75 | E53: 200 | F53: =D53 | G53: 1 | H53: =F53*G53
A54: Bathroom 1 | B54: Bathroom scale | C54: 20 | D54: 45 | E54: 100 | F54: =D54 | G54: 1 | H54: =F54*G54
A55: Bathroom 1 | B55: Hairdryer | C55: 20 | D55: 55 | E55: 130 | F55: =D55 | G55: 1 | H55: =F55*G55
B56: Bathroom 1 subtotal | C56: =SUM(C44:C55) | D56: =SUM(D44:D55) | E56: =SUM(E44:E55) | F56: =SUM(F44:F55) | H56: =SUM(H44:H55)
A58: BATHROOM 2
A59: Bathroom 2 | B59: Towel sets (4 hand + 4 bath) | C59: 60 | D59: 140 | E59: 320 | F59: =D59 | G59: 1 | H59: =F59*G59
A60: Bathroom 2 | B60: Bath mats (2) | C60: 25 | D60: 55 | E60: 140 | F60: =D60 | G60: 1 | H60: =F60*G60
A61: Bathroom 2 | B61: Shower curtain + liner | C61: 25 | D61: 60 | E61: 140 | F61: =D61 | G61: 1 | H61: =F61*G61
A62: Bathroom 2 | B62: Soap + lotion dispensers | C62: 20 | D62: 50 | E62: 120 | F62: =D62 | G62: 1 | H62: =F62*G62
A63: Bathroom 2 | B63: Trash bin (covered) | C63: 20 | D63: 45 | E63: 110 | F63: =D63 | G63: 1 | H63: =F63*G63
A64: Bathroom 2 | B64: Toilet brush + holder | C64: 15 | D64: 35 | E64: 80 | F64: =D64 | G64: 1 | H64: =F64*G64
A65: Bathroom 2 | B65: Plunger | C65: 12 | D65: 25 | E65: 50 | F65: =D65 | G65: 1 | H65: =F65*G65
A66: Bathroom 2 | B66: Toilet paper holder | C66: 15 | D66: 35 | E66: 80 | F66: =D66 | G66: 1 | H66: =F66*G66
A67: Bathroom 2 | B67: Wall hooks / robe hooks | C67: 15 | D67: 35 | E67: 90 | F67: =D67 | G67: 1 | H67: =F67*G67
A68: Bathroom 2 | B68: Wall art | C68: 30 | D68: 75 | E68: 200 | F68: =D68 | G68: 1 | H68: =F68*G68
A69: Bathroom 2 | B69: Bathroom scale | C69: 20 | D69: 45 | E69: 100 | F69: =D69 | G69: 1 | H69: =F69*G69
A70: Bathroom 2 | B70: Hairdryer | C70: 20 | D70: 55 | E70: 130 | F70: =D70 | G70: 1 | H70: =F70*G70
B71: Bathroom 2 subtotal | C71: =SUM(C59:C70) | D71: =SUM(D59:D70) | E71: =SUM(E59:E70) | F71: =SUM(F59:F70) | H71: =SUM(H59:H70)
A73: KITCHEN
A74: Kitchen | B74: Dish set (service for 8) | C74: 60 | D74: 150 | E74: 400 | F74: =D74 | G74: 1 | H74: =F74*G74
A75: Kitchen | B75: Drinking glasses (set of 8) | C75: 25 | D75: 60 | E75: 150 | F75: =D75 | G75: 1 | H75: =F75*G75
A76: Kitchen | B76: Wine glasses (set of 6) | C76: 20 | D76: 50 | E76: 140 | F76: =D76 | G76: 1 | H76: =F76*G76
A77: Kitchen | B77: Coffee mugs (set of 8) | C77: 20 | D77: 45 | E77: 110 | F77: =D77 | G77: 1 | H77: =F77*G77
A78: Kitchen | B78: Silverware (service for 8) | C78: 30 | D78: 75 | E78: 200 | F78: =D78 | G78: 1 | H78: =F78*G78
A79: Kitchen | B79: Cookware (5-pc set) | C79: 80 | D79: 220 | E79: 650 | F79: =D79 | G79: 1 | H79: =F79*G79
A80: Kitchen | B80: Bakeware (3-pc set) | C80: 30 | D80: 75 | E80: 180 | F80: =D80 | G80: 1 | H80: =F80*G80
A81: Kitchen | B81: Knife block + 6 knives | C81: 45 | D81: 120 | E81: 350 | F81: =D81 | G81: 1 | H81: =F81*G81
A82: Kitchen | B82: Cutting boards (2) | C82: 20 | D82: 45 | E82: 110 | F82: =D82 | G82: 1 | H82: =F82*G82
A83: Kitchen | B83: Mixing bowls (3-pc set) | C83: 20 | D83: 45 | E83: 110 | F83: =D83 | G83: 1 | H83: =F83*G83
A84: Kitchen | B84: Measuring cups + spoons | C84: 15 | D84: 30 | E84: 65 | F84: =D84 | G84: 1 | H84: =F84*G84
A85: Kitchen | B85: Can opener + corkscrew + tools | C85: 20 | D85: 45 | E85: 110 | F85: =D85 | G85: 1 | H85: =F85*G85
... A98: Kitchen | B98: Welcome basket (coffee/snacks) | C98: 25 | D98: 50 | E98: 120 | F98: =D98 | G98: 1 | H98: =F98*G98
B99: Kitchen subtotal | C99: =SUM(C74:C98) | D99: =SUM(D74:D98) | E99: =SUM(E74:E98) | F99: =SUM(F74:F98) | H99: =SUM(H74:H98)
A101: LIVING
A102: Living | B102: Sofa (3-seat) | C102: 400 | D102: 900 | E102: 2400 | F102: =D102 | G102: 1 | H102: =F102*G102
A103: Living | B103: Accent chairs (pair) | C103: 200 | D103: 500 | E103: 1400 | F103: =D103 | G103: 1 | H103: =F103*G103
A104: Living | B104: Coffee table | C104: 80 | D104: 220 | E104: 600 | F104: =D104 | G104: 1 | H104: =F104*G104
A105: Living | B105: End tables (pair) | C105: 80 | D105: 200 | E105: 500 | F105: =D105 | G105: 1 | H105: =F105*G105
A106: Living | B106: Floor + table lamps (3) | C106: 80 | D106: 220 | E106: 550 | F106: =D106 | G106: 1 | H106: =F106*G106
A107: Living | B107: TV (55" smart) | C107: 280 | D107: 500 | E107: 1100 | F107: =D107 | G107: 1 | H107: =F107*G107
A108: Living | B108: TV stand / media console | C108: 90 | D108: 240 | E108: 650 | F108: =D108 | G108: 1 | H108: =F108*G108
A109: Living | B109: Throw blankets (3) | C109: 40 | D109: 95 | E109: 220 | F109: =D109 | G109: 1 | H109: =F109*G109
A110: Living | B110: Throw pillows (6) | C110: 50 | D110: 130 | E110: 320 | F110: =D110 | G110: 1 | H110: =F110*G110
A111: Living | B111: Wall art / gallery wall | C111: 100 | D111: 280 | E111: 800 | F111: =D111 | G111: 1 | H111: =F111*G111
A112: Living | B112: Area rug (8x10) | C112: 120 | D112: 340 | E112: 900 | F112: =D112 | G112: 1 | H112: =F112*G112
A113: Living | B113: Bookshelf + decor / books | C113: 80 | D113: 220 | E113: 550 | F113: =D113 | G113: 1 | H113: =F113*G113
... A116: Living | B116: Coat rack / entry bench | C116: 50 | D116: 120 | E116: 300 | F116: =D116 | G116: 1 | H116: =F116*G116
B117: Living subtotal | C117: =SUM(C102:C116) | D117: =SUM(D102:D116) | E117: =SUM(E102:E116) | F117: =SUM(F102:F116) | H117: =SUM(H102:H116)
A119: OUTDOOR
A120: Outdoor | B120: Patio dining set (table + 4-6) | C120: 220 | D120: 600 | E120: 1800 | F120: =D120 | G120: 1 | H120: =F120*G120
A121: Outdoor | B121: Patio umbrella + base | C121: 70 | D121: 180 | E121: 480 | F121: =D121 | G121: 1 | H121: =F121*G121
A122: Outdoor | B122: Grill (gas or charcoal) | C122: 150 | D122: 400 | E122: 950 | F122: =D122 | G122: 1 | H122: =F122*G122
A123: Outdoor | B123: Fire pit (if allowed) | C123: 100 | D123: 280 | E123: 700 | F123: =D123 | G123: 1 | H123: =F123*G123
A124: Outdoor | B124: Outdoor string lights | C124: 30 | D124: 75 | E124: 180 | F124: =D124 | G124: 1 | H124: =F124*G124
A125: Outdoor | B125: Adirondack / lounge chairs (2) | C125: 120 | D125: 300 | E125: 750 | F125: =D125 | G125: 1 | H125: =F125*G125
...

Sheet Launch Costs
A2: =HYPERLINK("#'Furnish & Setup'!A1", "← BACK") | D2: LAUNCH COSTS | J2: =HYPERLINK("#'90-Day Reserve'!A1", "NEXT →")
A4: Section 3 of 4 — costs to GO LIVE: photos, listings, permits, LLC, insurance, software.
A6: MARKETING & LISTING
B8: Professional photos ($): | C8: 1200 | E8: $800-1500 — non-negotiable for ranking
B9: Airbnb listing fee ($): | C9: 0 | E9: Typically $0 — free to list
A10: PERMITS & LEGAL ENTITY
B11: Permit / STR registration ($): | C11: 450 | E11: Varies by city — check local
B12: Business license ($): | C12: 150
B13: LLC formation ($): | C13: 400 | E13: $300-500 most states
B14: Insurance binder + Y1 ($): | C14: 1800 | E14: STR-specific; HO-3 won't cover
A16: SOFTWARE & TOOLS (Y1)
B17: PMS setup ($): | C17: 250 | E17: Hospitable / Hostfully / etc.
B18: Pricing tool setup ($): | C18: 150 | E18: PriceLabs / Wheelhouse setup
B19: Accounting software ($): | C19: 240 | E19: QBO / Stessa annual
A21: OTHER LAUNCH
B22: VRBO listing fee ($): | C22: 499 | E22: Annual subscription option
B23: Marketing / branding ($): | C23: 400 | E23: Logo, social, welcome book
B24: Signage ($): | C24: 180
B25: Lockbox / key codes ($): | C25: 85
A27: DERIVED
B28: Total launch costs: | C28: =SUM(C8:C9)+SUM(C11:C14)+SUM(C17:C19)+SUM(C22:C25)
A32: Questions? hello@thestrledger.com
A33: ACQ-002 · Launch Costs

Sheet 90-Day Reserve
A2: =HYPERLINK("#'Launch Costs'!A1", "← BACK") | D2: 90-DAY RESERVE | J2: =HYPERLINK("#'Total + Y1 ROI'!A1", "NEXT →")
A4: Section 4 of 4 — operating runway. The difference between "launched" and "sustained." Non-negotiable.
A6: 90-DAY OPERATING RESERVE
B7: Mortgage P&I × 3 mo: | C7: =Acquisition!C30*3 | E7: Auto-calculated from Acquisition tab P&I × 3 months
B8: Utilities × 3 mo ($): | C8: 900 | E8: $200-400/mo typical
B9: Insurance reserve ($): | C9: 450 | E9: Annual / 4 (3 mo)
B10: Cleaning reserve ($): | C10: 1500 | E10: Pre-bookings until cash flow normalizes
B11: Maintenance reserve ($): | C11: 1200 | E11: Surprise repairs in Y1
B12: Marketing reserve ($): | C12: 600 | E12: Boost listing first 90 days
B13: Software subscriptions × 3 mo: | C13: 210 | E13: PMS + pricing + accounting
B14: Other contingency ($): | C14: 500 | E14: HOA dues, surprises
A15: TOTAL RESERVE
B16: 90-day reserve: | C16: =SUM(C7:C14)
A18: Why this matters: The #1 reason new STR investors fail isn't a bad deal — it's running out of cash before bookings stabilize. Three months of fixed costs in reserve = the difference between launched and sustained. Don't skip this.
A23: Questions? hello@thestrledger.com
A24: ACQ-002 · 90-Day Reserve

Sheet Total + Y1 ROI
A2: =HYPERLINK("#'90-Day Reserve'!A1", "← BACK") | D2: TOTAL + Y1 ROI
A4: Your all-in budget + Y1 cash-on-cash return projection.
A6: ALL-IN BUDGET
B7: Acquisition (full, incl. purchase price): | C7: =Acquisition!C13+SUM(Acquisition!C19:C25)
B8: Furnish & Setup (selected total): | C8: ='Furnish & Setup'!H164
B9: Launch Costs: | C9: ='Launch Costs'!C28
B10: 90-Day Reserve: | C10: ='90-Day Reserve'!C16
B14: TOTAL ALL-IN: | C14: =SUM(C7:C10)
A16: CASH INVESTED (excludes mortgage principal)
B17: Down payment + DD/closing: | C17: =Acquisition!C31
B18: + Furnish + Launch + Reserve: | C18: =C8+C9+C10
B19: Cash invested (out of pocket): | C19: =C17+C18
A21: Y1 REVENUE PROJECTION (your inputs)
B22: Y1 ADR — avg nightly rate ($): | C22: 245 | E22: Pull from AirDNA / comps; haircut for Y1
B23: Y1 occupancy (%): | C23: 0.45 | E23: 40-50% typical for Y1; 65% stabilized
B24: Available nights/yr: | C24: 365 | E24: 365 default; less if owner-blocked
B25: Y1 operating costs ($): | C25: 22000 | E25: Excl. mortgage; rough projection
A26: Y1 OUTPUTS
B27: Y1 gross revenue: | C27: =C22*C23*C24
B28: Y1 cash-on-cash %: | C28: =IFERROR((C27-C25-Acquisition!C30*12)/C19,0)
B29: Y1 net cash flow: | C29: =C27-C25-Acquisition!C30*12
B30: Payback (months, if positive): | C30: =IFERROR(IF(C29>0,C19/(C29/12),0),0)
B31: Break-even occupancy: | C31: =IFERROR((C25+Acquisition!C30*12)/(C22*C24),0)
A35: Questions? hello@thestrledger.com
A36: ACQ-002 · Total + Y1 ROI
