Workbook

Sheet Start
A2: The STR Ledger
A4: STR Deal Analyzer
A5: Yes-or-no on a property in 10 minutes.
A7: ACQ-001 · v1.0 · DEMO
A11: =IF(Property!C7="","(enter property on Property tab)",Property!C7)
A13: VERDICT
A14: =Verdict!A17
A17: Y1 ANNUAL CASH FLOW | G17: STABILIZED CASH FLOW
A18: =Verdict!C10 | G18: =Verdict!D10
A21: =Verdict!A22
A24: =HYPERLINK("#'Property'!A1", "Property") | D24: =HYPERLINK("#'Market'!A1", "Market") | G24: =HYPERLINK("#'Costs'!A1", "Costs") | J24: =HYPERLINK("#'Finance'!A1", "Finance")
A28: =HYPERLINK("#'Verdict'!A1", "→ Verdict + Stress Test") | G28: =HYPERLINK("#'CPA Summary'!A1", "CPA / Partner Summary")
A33: 💡 Underwriting multiple properties? Get the 3-Property Side-by-Side at thestrledger.com — $67, or grab the Acquisition Bundle for $147.
A36: Questions? hello@thestrledger.com
A37: ACQ-001 · v1.0 · DEMO · Free updates forever

Sheet Property
A2: =HYPERLINK("#'Start'!A1", "← BACK") | D2: PROPERTY | J2: =HYPERLINK("#'Market'!A1", "NEXT →")
A4: Section 1 of 4 — what you're underwriting
A6: PROPERTY
B7: Property name: | C7: Smokies Ridge Cabin
B8: Street address: | C8: 123 Mountain Lane
B9: City, State, Zip: | C9: Gatlinburg, TN 37738
B10: Property type: | C10: Cabin | E10: Dropdown
B11: Bedrooms: | C11: 3
B12: Bathrooms: | C12: 2
B13: Square feet: | C13: 1850
B14: Year built: | C14: 2014
B15: Lot type: | C15: Rural | E15: Dropdown — drives ADR adjustment intuition
B17: Hot tub? | C17: Yes | E17: Yes/No
B18: View premium? | C18: Yes | E18: Yes/No
A22: Questions? hello@thestrledger.com
A23: ACQ-001 · Property

Sheet Market
A2: =HYPERLINK("#'Property'!A1", "← BACK") | D2: MARKET | J2: =HYPERLINK("#'Costs'!A1", "NEXT →")
A4: Section 2 of 4 — ADR, occupancy, comp benchmarks
A6: MARKET ASSUMPTIONS
B7: ADR — Avg nightly rate ($): | C7: 285 | E7: Paste from AirDNA / verify with comps
B8: Comp ADR (3-comp average, $): | C8: 268 | E8: Sanity check on your ADR assumption
B9: Stabilized occupancy (%): | C9: 0.68 | E9: Year 2-3 expected
B10: Year 1 occupancy (%): | C10: 0.44 | E10: Default ≈ 65% of stabilized (BiggerPockets consensus)
B11: Avg length of stay (nights): | C11: 3.4 | E11: 1.5-7 typical
B12: Platform commission (%): | C12: 0.15 | E12: Airbnb 15%, VRBO 8%, direct 0-3%
A14: 📋 PASTE FROM AIRDNA / RABBU / KEYDATA
A15: Pull market RevPAR, ADR, and occupancy from AirDNA Markets (or Rabbu / KeyData free comp). Look for the same beds/baths/lot type. Then haircut: if AirDNA shows median ADR, use the 25th-percentile ADR for Y1 here. AirDNA optimism is the #1 reason new STR investors get burned — the Verdict tab's stress test lives at AirDNA's 25th-percentile assumptions.
A21: Questions? hello@thestrledger.com
A22: ACQ-001 · Market

Sheet Costs
A2: =HYPERLINK("#'Market'!A1", "← BACK") | D2: COSTS | J2: =HYPERLINK("#'Finance'!A1", "NEXT →")
A4: Section 3 of 4 — operating costs (mirrors TAX-002 / FIN-002 structure)
A6: ANNUAL FIXED COSTS
B7: Property tax (annual, $): | C7: 5800
B8: Insurance (annual, $): | C8: 3400 | E8: STR rider included
B9: HOA / Condo (annual, $): | C9: 0
B10: Utilities (annual, $): | C10: 2400 | E10: Electric/gas/water/trash combined
B11: Internet (annual, $): | C11: 960
B12: Software / PMS (annual, $): | C12: 480
B13: Marketing (annual, $): | C13: 1200 | E13: Photos refresh, listing fees
A15: PER-TURNOVER VARIABLE
B16: Cleaning paid ($/turnover): | C16: 185
B17: Supplies ($/turnover): | C17: 35
A19: RESERVES & MGMT (% OF REVENUE)
B20: Management fee (%): | C20: 0 | E20: 0% if self-managed; 15-25% with a PM
B21: Maintenance reserve (%): | C21: 0.05 | E21: 5% typical
B22: CapEx reserve (%): | C22: 0.03 | E22: 3% typical
A26: Questions? hello@thestrledger.com
A27: ACQ-001 · Costs

Sheet Finance
A2: =HYPERLINK("#'Costs'!A1", "← BACK") | D2: FINANCE | J2: =HYPERLINK("#'Verdict'!A1", "NEXT →")
A4: Section 4 of 4 — purchase, loan, closing, rehab, furnishing
A6: FINANCING
B7: Purchase price ($): | C7: 485000
B8: Down payment (%): | C8: 0.25 | E8: 20-25% typical for STR
B9: Interest rate (%): | C9: 0.07
B10: Term (years): | C10: 30 | E10: 30 typical
B11: Closing costs ($): | C11: 9000 | E11: 2-3% of purchase typical
B12: Rehab budget ($): | C12: 35000
B13: Furnishing budget ($): | C13: 25000 | E13: Cross-reference ACQ-002
A15: DERIVED
B16: Loan amount: | C16: =C7*(1-C8)
B17: Monthly P&I: | C17: =IFERROR(PMT(C9/12,C10*12,-C16),0)
B18: Annual debt service (P&I): | C18: =C17*12
B19: Annual mortgage interest (Y1 approx): | C19: =C16*C9
B20: Total cash to close: | C20: =C7*C8+C11+C12+C13
A24: Questions? hello@thestrledger.com
A25: ACQ-001 · Finance

Sheet Verdict
A2: =HYPERLINK("#'Finance'!A1", "← BACK") | D2: VERDICT | J2: =HYPERLINK("#'CPA Summary'!A1", "NEXT →")
A4: Toggle Y1 vs Stabilized below. The Stress Test column compares your deal against AirDNA's pessimistic case.
B6: Metric | C6: Year 1 | D6: Stabilized | E6: Stress Test
B7: Gross revenue: | C7: =((Market!C7)*(Market!C10)*365*(1-Market!C12)) | D7: =((Market!C7)*(Market!C9)*365*(1-Market!C12)) | E7: =((Market!C7*0.9)*(Market!C9*0.85)*365*(1-Market!C12))
B8: NOI (operating profit): | C8: =(((Market!C7)*(Market!C10)*365*(1-Market!C12))-(SUM(Costs!C7:C13))-(((Market!C7)*(Market!C10)*365*(1-Market!C12))*(Costs!C20+Costs!C21+Costs!C22))-((Market!C10*365/Market!C11)*(Costs!C16+Costs!C17))) | D8: =(((Market!C7)*(Market!C9)*365*(1-Market!C12))-(SUM(Costs!C7:C13))-(((Market!C7)*(Market!C9)*365*(1-Market!C12))*(Costs!C20+Costs!C21+Costs!C22))-((Market!C9*365/Market!C11)*(Costs!C16+Costs!C17))) | E8: =(((Market!C7*0.9)*(Market!C9*0.85)*365*(1-Market!C12))-(SUM(Costs!C7:C13))*1.2-(((Market!C7*0.9)*(Market!C9*0.85)*365*(1-Market!C12))*(Costs!C20+Costs!C21+Costs!C22))-((Market!C9*0.85*365/Market!C11)*(Costs!C16+Costs!C17)*1.2))
B9: Annual debt service: | C9: =(Finance!C18) | D9: =(Finance!C18) | E9: =(Finance!C18)
B10: ANNUAL CASH FLOW: | C10: =((((Market!C7)*(Market!C10)*365*(1-Market!C12))-(SUM(Costs!C7:C13))-(((Market!C7)*(Market!C10)*365*(1-Market!C12))*(Costs!C20+Costs!C21+Costs!C22))-((Market!C10*365/Market!C11)*(Costs!C16+Costs!C17)))-(Finance!C18)) | D10: =((((Market!C7)*(Market!C9)*365*(1-Market!C12))-(SUM(Costs!C7:C13))-(((Market!C7)*(Market!C9)*365*(1-Market!C12))*(Costs!C20+Costs!C21+Costs!C22))-((Market!C9*365/Market!C11)*(Costs!C16+Costs!C17)))-(Finance!C18)) | E10: =((((Market!C7*0.9)*(Market!C9*0.85)*365*(1-Market!C12))-(SUM(Costs!C7:C13))*1.2-(((Market!C7*0.9)*(Market!C9*0.85)*365*(1-Market!C12))*(Costs!C20+Costs!C21+Costs!C22))-((Market!C9*0.85*365/Market!C11)*(Costs!C16+Costs!C17)*1.2))-(Finance!C18))
B11: Cash invested: | C11: =(Finance!C7*Finance!C8+Finance!C11+Finance!C12+Finance!C13) | D11: =(Finance!C7*Finance!C8+Finance!C11+Finance!C12+Finance!C13) | E11: =(Finance!C7*Finance!C8+Finance!C11+Finance!C12+Finance!C13)
B12: Cash-on-cash: | C12: =(((((Market!C7)*(Market!C10)*365*(1-Market!C12))-(SUM(Costs!C7:C13))-(((Market!C7)*(Market!C10)*365*(1-Market!C12))*(Costs!C20+Costs!C21+Costs!C22))-((Market!C10*365/Market!C11)*(Costs!C16+Costs!C17)))-(Finance!C18))/(Finance!C7*Finance!C8+Finance!C11+Finance!C12+Finance!C13)) | D12: =(((((Market!C7)*(Market!C9)*365*(1-Market!C12))-(SUM(Costs!C7:C13))-(((Market!C7)*(Market!C9)*365*(1-Market!C12))*(Costs!C20+Costs!C21+Costs!C22))-((Market!C9*365/Market!C11)*(Costs!C16+Costs!C17)))-(Finance!C18))/(Finance!C7*Finance!C8+Finance!C11+Finance!C12+Finance!C13)) | E12: =(((((Market!C7*0.9)*(Market!C9*0.85)*365*(1-Market!C12))-(SUM(Costs!C7:C13))*1.2-(((Market!C7*0.9)*(Market!C9*0.85)*365*(1-Market!C12))*(Costs!C20+Costs!C21+Costs!C22))-((Market!C9*0.85*365/Market!C11)*(Costs!C16+Costs!C17)*1.2))-(Finance!C18))/(Finance!C7*Finance!C8+Finance!C11+Finance!C12+Finance!C13))
B13: DSCR: | C13: =((((Market!C7)*(Market!C10)*365*(1-Market!C12))-(SUM(Costs!C7:C13))-(((Market!C7)*(Market!C10)*365*(1-Market!C12))*(Costs!C20+Costs!C21+Costs!C22))-((Market!C10*365/Market!C11)*(Costs!C16+Costs!C17)))/(Finance!C18)) | D13: =((((Market!C7)*(Market!C9)*365*(1-Market!C12))-(SUM(Costs!C7:C13))-(((Market!C7)*(Market!C9)*365*(1-Market!C12))*(Costs!C20+Costs!C21+Costs!C22))-((Market!C9*365/Market!C11)*(Costs!C16+Costs!C17)))/(Finance!C18)) | E13: =((((Market!C7*0.9)*(Market!C9*0.85)*365*(1-Market!C12))-(SUM(Costs!C7:C13))*1.2-(((Market!C7*0.9)*(Market!C9*0.85)*365*(1-Market!C12))*(Costs!C20+Costs!C21+Costs!C22))-((Market!C9*0.85*365/Market!C11)*(Costs!C16+Costs!C17)*1.2))/(Finance!C18))
B14: Cap rate: | C14: =((((Market!C7)*(Market!C10)*365*(1-Market!C12))-(SUM(Costs!C7:C13))-(((Market!C7)*(Market!C10)*365*(1-Market!C12))*(Costs!C20+Costs!C21+Costs!C22))-((Market!C10*365/Market!C11)*(Costs!C16+Costs!C17)))/Finance!C7) | D14: =((((Market!C7)*(Market!C9)*365*(1-Market!C12))-(SUM(Costs!C7:C13))-(((Market!C7)*(Market!C9)*365*(1-Market!C12))*(Costs!C20+Costs!C21+Costs!C22))-((Market!C9*365/Market!C11)*(Costs!C16+Costs!C17)))/Finance!C7) | E14: =((((Market!C7)*(Market!C9)*365*(1-Market!C12))-(SUM(Costs!C7:C13))-(((Market!C7)*(Market!C9)*365*(1-Market!C12))*(Costs!C20+Costs!C21+Costs!C22))-((Market!C9*365/Market!C11)*(Costs!C16+Costs!C17)))/Finance!C7)
A17: =IF(AND((((((Market!C7)*(Market!C9)*365*(1-Market!C12))-(SUM(Costs!C7:C13))-(((Market!C7)*(Market!C9)*365*(1-Market!C12))*(Costs!C20+Costs!C21+Costs!C22))-((Market!C9*365/Market!C11)*(Costs!C16+Costs!C17)))-(Finance!C18))/(Finance!C7*Finance!C8+Finance!C11+Finance!C12+Finance!C13))>0.08,((((Market!C7)*(Market!C9)*365*(1-Market!C12))-(SUM(Costs!C7:C13))-(((Market!C7)*(Market!C9)*365*(1-Market!C12))*(Costs!C20+Costs!C21+Costs!C22))-((Market!C9*365/Market!C11)*(Costs!C16+Costs!C17)))/(Finance!C18))>1.25),"✅ DEAL",IF(OR((((((Market!C7)*(Market!C9)*365*(1-Market!C12))-(SUM(Costs!C7:C13))-(((Market!C7)*(Market!C9)*365*(1-Market!C12))*(Costs!C20+Costs!C21+Costs!C22))-((Market!C9*365/Market!C11)*(Costs!C16+Costs!C17)))-(Finance!C18))/(Finance!C7*Finance!C8+Finance!C11+Finance!C12+Finance!C13))<0.04,((((Market!C7)*(Market!C9)*365*(1-Market!C12))-(SUM(Costs!C7:C13))-(((Market!C7)*(Market!C9)*365*(1-Market!C12))*(Costs!C20+Costs!C21+Costs!C22))-((Market!C9*365/Market!C11)*(Costs!C16+Costs!C17)))/(Finance!C18))<1.05),"❌ PASS","⚠ MARGINAL"))
A22: =IF(((((Market!C7*0.9)*(Market!C9*0.85)*365*(1-Market!C12))-(SUM(Costs!C7:C13))*1.2-(((Market!C7*0.9)*(Market!C9*0.85)*365*(1-Market!C12))*(Costs!C20+Costs!C21+Costs!C22))-((Market!C9*0.85*365/Market!C11)*(Costs!C16+Costs!C17)*1.2))-(Finance!C18))>0,"✅ Survives stress test ($"&TEXT(((((Market!C7*0.9)*(Market!C9*0.85)*365*(1-Market!C12))-(SUM(Costs!C7:C13))*1.2-(((Market!C7*0.9)*(Market!C9*0.85)*365*(1-Market!C12))*(Costs!C20+Costs!C21+Costs!C22))-((Market!C9*0.85*365/Market!C11)*(Costs!C16+Costs!C17)*1.2))-(Finance!C18)),"#,##0")&" CF)",IF(((((Market!C7*0.9)*(Market!C9*0.85)*365*(1-Market!C12))-(SUM(Costs!C7:C13))*1.2-(((Market!C7*0.9)*(Market!C9*0.85)*365*(1-Market!C12))*(Costs!C20+Costs!C21+Costs!C22))-((Market!C9*0.85*365/Market!C11)*(Costs!C16+Costs!C17)*1.2))-(Finance!C18))>-5000,"⚠ Marginal under stress (−$"&TEXT(ABS(((((Market!C7*0.9)*(Market!C9*0.85)*365*(1-Market!C12))-(SUM(Costs!C7:C13))*1.2-(((Market!C7*0.9)*(Market!C9*0.85)*365*(1-Market!C12))*(Costs!C20+Costs!C21+Costs!C22))-((Market!C9*0.85*365/Market!C11)*(Costs!C16+Costs!C17)*1.2))-(Finance!C18))),"#,##0")&")","❌ Fails under stress ($"&TEXT(((((Market!C7*0.9)*(Market!C9*0.85)*365*(1-Market!C12))-(SUM(Costs!C7:C13))*1.2-(((Market!C7*0.9)*(Market!C9*0.85)*365*(1-Market!C12))*(Costs!C20+Costs!C21+Costs!C22))-((Market!C9*0.85*365/Market!C11)*(Costs!C16+Costs!C17)*1.2))-(Finance!C18)),"#,##0")&")"))
A24: Stress test method: ADR -10%, occupancy haircut to 85% of stabilized, operating expenses +20%. Roughly equivalent to AirDNA's 25th-percentile projection — what real underwriters use. If your deal fails this stress, you're underwriting too aggressively or the property is marginal.
A29: Questions? hello@thestrledger.com
A30: ACQ-001 · Verdict

Sheet CPA Summary
A2: =HYPERLINK("#'Verdict'!A1", "← BACK") | D2: CPA / PARTNER SUMMARY
A4: Deal Underwriting Summary
A7: =Property!C7&" · "&Property!C9
A8: ="Analysis date: "&TEXT(TODAY(),"yyyy-mm-dd")
A10: KEY TERMS
B11: Purchase price: | C11: =Finance!C7
B12: Down payment: | C12: =Finance!C7*Finance!C8
B13: Loan amount: | C13: =Finance!C16
B14: Interest rate: | C14: =Finance!C9
B15: Term: | C15: =Finance!C10&" years"
B16: Total cash to close: | C16: =Finance!C20
A19: 5-YEAR PRO-FORMA (3% appreciation, stabilized after Y2)
C20: Year 1 | D20: Year 2 Stab | E20: Year 5 Stab
B21: Revenue (gross): | C21: =Market!C7*Market!C10*365 | D21: =Market!C7*Market!C9*365 | E21: =Market!C7*Market!C9*365*1.06
B22: Operating expenses: | C22: =SUM(Costs!C7:C13)+(Market!C7*Market!C10*365)*(Costs!C20+Costs!C21+Costs!C22)+(Market!C10*365/Market!C11)*(Costs!C16+Costs!C17) | D22: =SUM(Costs!C7:C13)+(Market!C7*Market!C9*365)*(Costs!C20+Costs!C21+Costs!C22)+(Market!C9*365/Market!C11)*(Costs!C16+Costs!C17) | E22: =SUM(Costs!C7:C13)*1.10+(Market!C7*Market!C9*365*1.06)*(Costs!C20+Costs!C21+Costs!C22)+(Market!C9*365/Market!C11)*(Costs!C16+Costs!C17)*1.10
B23: NOI: | C23: =C21-C22 | D23: =D21-D22 | E23: =E21-E22
B24: Debt service: | C24: =Finance!C18 | D24: =Finance!C18 | E24: =Finance!C18
B25: Cash flow: | C25: =C23-C24 | D25: =D23-D24 | E25: =E23-E24
B26: Cumulative cash: | C26: =C25 | D26: =C25+D25 | E26: =C25+D25+(D25*3)
A28: VERDICT + STRESS TEST
B29: =Verdict!A17
B30: =Verdict!A22
A32: UNDERWRITING NOTES
