Workbook

Sheet Start
A2: The STR Ledger
A4: BRRRR-to-STR Refi Math
A5: Did this BRRRR actually return all your cash?
A7: ACQ-009 · v1.0 · BLANK
A11: =IF(Settings!C5="","(enter property on Settings tab)",Settings!C5)
A13: % CAPITAL RETURNED AT REFI
A14: ='ARV + Refi'!C25
A17: =IF('ARV + Refi'!C25>=0.95,"✅ Full BRRRR — capital recycled",IF('ARV + Refi'!C25>=0.75,"⚠ Partial BRRRR — some cash trapped","❌ Cash-heavy deal — most equity stays in"))
A19: CASH INVESTED | E19: CASH RETURNED | I19: POST-REFI DSCR
A20: ='Acquisition + Rehab'!C18 | E20: ='ARV + Refi'!C23 | I20: ='Post-Refi Operating'!C13
A23: ="Cash left in deal: "&TEXT('ARV + Refi'!C24,"$#,##0") | G23: =IF('Post-Refi Operating'!C13>=1.20,"✅ Meets DSCR-loan minimum (1.20)","⚠ Below DSCR-loan minimum (1.20)")
A25: Note: BRRRR math here covers acquisition + rehab + holding cash, ARV estimate, refi cash-out, and post-refi DSCR/cash flow. It does NOT model rehab overruns, appraisal misses, or DSCR-loan seasoning windows. Re-run the moment any input changes — every $5K rehab overrun is real money.
A28: =HYPERLINK("#'Acquisition + Rehab'!A1", "Acquisition + Rehab") | D28: =HYPERLINK("#'ARV + Refi'!A1", "ARV + Refi") | G28: =HYPERLINK("#'Post-Refi Operating'!A1", "Post-Refi Operating") | J28: =HYPERLINK("#'Settings'!A1", "Settings")
A33: 💡 Stacking BRRRRs? Get the Acquisition Bundle at thestrledger.com — Deal Analyzer + Cost-to-Launch + BRRRR Math + more.
A36: Questions? hello@thestrledger.com
A37: ACQ-009 · v1.0 · BLANK · Free updates forever

Sheet Acquisition + Rehab
A2: =HYPERLINK("#'Start'!A1", "← BACK") | D2: ACQUISITION + REHAB | J2: =HYPERLINK("#'ARV + Refi'!A1", "NEXT →")
A4: Section 1 of 3 — every dollar that goes in before the refi
A6: PURCHASE
B7: Purchase price ($): | E7: Distressed/below-market is the BRRRR target
B8: Closing costs at purchase ($): | E8: Title, recording, lender fees — typically 2-3%
B9: Hard money / acquisition loan ($): | E9: 0 if all-cash. HML typically 80% of purchase + 100% rehab
B10: Down + closing in cash ($): | E10: Purchase − HML loan + closing costs paid out of pocket
A12: REHAB + HOLDING
B13: Rehab budget ($): | E13: Hard costs — labor, materials, permits
B14: Furniture budget ($): | E14: Often deferred to post-refi — toggle to $0 if so
B15: Holding period (months): | E15: Months from close to refi cash-out
B16: Holding cost per month ($): | E16: Insurance + utilities + tax + HML interest
A17: TOTAL CASH INVESTED — CALCULATED
B18: Total cash in (pre-refi): | C18: =C10+C13+C14+(C15*C16) | E18: Sum of all out-of-pocket dollars before refi
B20: Total holding costs: | C20: =C15*C16 | E20: Months × monthly carry
B21: Hard money outstanding (refi payoff): | C21: =C9 | E21: Pulled to ARV + Refi tab as loan payoff
A25: Questions? hello@thestrledger.com
A26: ACQ-009 · Acquisition + Rehab

Sheet ARV + Refi
A2: =HYPERLINK("#'Acquisition + Rehab'!A1", "← BACK") | D2: ARV + REFI | J2: =HYPERLINK("#'Post-Refi Operating'!A1", "NEXT →")
A4: Section 2 of 3 — what it appraises for and how much cash comes back
A6: ARV ESTIMATE — THREE METHODS
B7: ARV — Comp sales method ($): | E7: 3 nearby sold comps × adjusted $/sqft
B8: ARV — Cap rate × NOI method ($): | E8: Year-1 NOI ÷ market cap rate
B9: ARV — $/sq ft method ($): | E9: Renovated comp $/sqft × your sqft
B10: Average of three methods: | C10: =AVERAGE(C7:C9) | E10: Reality check on your selected ARV below
B12: Selected ARV ($): | E12: What you're underwriting — usually conservative
A14: REFINANCE
B15: Target LTV (from Settings): | C15: =Settings!C7 | E15: DSCR loans typically 70-75%
B16: Refi rate (from Settings): | C16: =Settings!C9 | E16: Current DSCR-loan rate
B17: Refi term in years (from Settings): | C17: =Settings!C11 | E17: 30 typical
B18: Max refi loan amount: | C18: =C12*C15 | E18: Selected ARV × target LTV
B19: Less: original loan payoff ($): | E19: HML principal paid off at refi (0 if all-cash purchase)
B20: Refi closing cost (% of refi loan): | E20: DSCR-loan closing typically 2-4%
B21: Refi closing cost ($): | C21: =C18*C20 | E21: Refi loan × refi closing %
B22: Cash out at refi (gross): | C22: =C18-C19 | E22: Refi proceeds after HML payoff (before closing)
B23: Net cash returned after refi: | C23: ='Acquisition + Rehab'!C18-MAX(0,'Acquisition + Rehab'!C18-(C18-C19-C21)) | E23: Cash returned to host — capped at total cash in
B24: Cash left in deal: | C24: =MAX(0,'Acquisition + Rehab'!C18-(C18-C19-C21)) | E24: Cash in − cash returned (never negative)
B25: % capital returned: | C25: =IFERROR(C23/'Acquisition + Rehab'!C18,0) | E25: Cash returned ÷ cash in (>=95% = full BRRRR)
A29: Questions? hello@thestrledger.com
A30: ACQ-009 · ARV + Refi

Sheet Post-Refi Operating
A2: =HYPERLINK("#'ARV + Refi'!A1", "← BACK") | D2: POST-REFI OPERATING | J2: =HYPERLINK("#'Settings'!A1", "NEXT →")
A4: Section 3 of 3 — does it cash flow with the new debt service?
A6: OPERATING — YEAR 1 STABILIZED
B7: Year-1 STR projected revenue ($): | E7: Net of platform commission
B8: Year-1 operating expenses ($): | E8: Excludes debt service (added below)
B9: NOI (Net Operating Income): | C9: =C7-C8 | E9: Revenue − operating expenses
A11: NEW DEBT SERVICE + DSCR
B12: Annual debt service (Excel PMT × 12): | C12: =IFERROR(PMT(Settings!C9/12,Settings!C11*12,-'ARV + Refi'!C18),0)*12 | E12: PMT(rate/12, term×12, -refi_loan) × 12
B13: DSCR (NOI ÷ debt service): | C13: =IFERROR(C9/C12,0) | E13: DSCR loans require ≥ 1.20
B14: Monthly P&I (post-refi): | C14: =IFERROR(PMT(Settings!C9/12,Settings!C11*12,-'ARV + Refi'!C18),0) | E14: Excel PMT — handy reference
A16: OUTPUTS
B17: Cash flow (NOI − debt service): | C17: =C9-C12 | E17: Annual cash flow after debt
B18: Cash-on-cash on cash-left-in: | C18: =IFERROR(C17/'ARV + Refi'!C24,0) | E18: Annual cash flow ÷ cash left in
A20: DSCR 1.20 is the standard floor for non-QM DSCR loans. Below that, your refi may not approve at the target LTV — lenders will haircut the loan amount or push you to a lower-LTV product. If DSCR is borderline, model a 70% LTV scenario in Settings.
A25: Questions? hello@thestrledger.com
A26: ACQ-009 · Post-Refi Operating

Sheet Settings
A2: =HYPERLINK("#'Post-Refi Operating'!A1", "← BACK") | D2: SETTINGS
A4: Property name + refi assumptions used across the workbook
B5: Property name: | E5: Shown on Start tab headline
B7: Target LTV (refi): | E7: 75% typical for DSCR; 70% conservative
B9: Refi rate (annual): | E9: Current DSCR-loan quote — verify with broker
B11: Refi term (years): | E11: 30 typical; 25 sometimes for DSCR
A14: These four settings drive Max-refi-loan, post-refi P&I, and DSCR. Re-quote your DSCR rate every 30 days while sourcing — STR DSCR rates have moved 100-200bp in single quarters since 2023. The ARV + Refi tab uses the LTV here. The Post-Refi Operating tab uses the rate + term here in the Excel PMT formula.
A20: Questions? hello@thestrledger.com
A21: ACQ-009 · Settings
