Workbook

Sheet Start
A2: The STR Ledger
A4: 3-Property Side-by-Side
A5: Compare 3 acquisition candidates head-to-head. Pick the winner.
A7: ACQ-004 · v1.0 · DEMO
A10: PROPERTY A | E10: PROPERTY B | I10: PROPERTY C
A12: =IF(Inputs!C7="","(unnamed)",Inputs!C7) | E12: =IF(Inputs!D7="","(unnamed)",Inputs!D7) | I12: =IF(Inputs!E7="","(unnamed)",Inputs!E7)
A14: Y1 CASH FLOW | E14: Y1 CASH FLOW | I14: Y1 CASH FLOW
A15: =Underwriting!C16 | E15: =Underwriting!D16 | I15: =Underwriting!E16
A18: CASH-ON-CASH | E18: CASH-ON-CASH | I18: CASH-ON-CASH
A19: =Underwriting!C12 | E19: =Underwriting!D12 | I19: =Underwriting!E12
A22: RECOMMENDATION
A23: ='Comparison Matrix'!A30
A26: =HYPERLINK("#'Inputs'!A1", "Inputs") | D26: =HYPERLINK("#'Underwriting'!A1", "Underwriting") | G26: =HYPERLINK("#'Comparison Matrix'!A1", "→ Compare") | J26: =HYPERLINK("#'Decision Notes'!A1", "Decision Notes")
A31: 💡 Need to compare more than 3? The Acquisition Bundle at thestrledger.com includes deal analyzer + cost-to-launch + arbitrage analyzer.
A34: Questions? hello@thestrledger.com
A35: ACQ-004 · v1.0 · DEMO · Free updates forever

Sheet Inputs
A2: =HYPERLINK("#'Start'!A1", "← BACK") | D2: INPUTS | J2: =HYPERLINK("#'Underwriting'!A1", "NEXT →")
A4: Three properties side-by-side. Fill A, B, C columns. Underwriting computes automatically.
C5: PROPERTY A | D5: PROPERTY B | E5: PROPERTY C
A6: PROPERTY
B7: Property name: | C7: Smokies Ridge Cabin | D7: Lakehouse Retreat | E7: Creek Side Cottage
B8: Address: | C8: 123 Mountain Lane, Gatlinburg TN | D8: 47 Shoreline Dr, Sevierville TN | E8: 9 Creekbed Rd, Pigeon Forge TN
B9: Bedrooms: | C9: 3 | D9: 4 | E9: 2
B10: Bathrooms: | C10: 2 | D10: 3 | E10: 2
B11: Sleeps: | C11: 8 | D11: 10 | E11: 6
A13: FINANCING
B14: Purchase price ($): | C14: 485000 | D14: 625000 | E14: 360000
B15: Down payment (%): | C15: 0.25 | D15: 0.25 | E15: 0.25
B16: Interest rate (%): | C16: 0.07 | D16: 0.07 | E16: 0.07
B17: Term (years): | C17: 30 | D17: 30 | E17: 30
B18: Rehab budget ($): | C18: 35000 | D18: 22000 | E18: 18000
B19: Furniture budget ($): | C19: 25000 | D19: 32000 | E19: 18000
B20: Reserves ($): | C20: 12000 | D20: 15000 | E20: 9000
A22: REVENUE
B23: Projected occupancy (%): | C23: 0.68 | D23: 0.62 | E23: 0.64
B24: ADR — nightly rate ($): | C24: 285 | D24: 340 | E24: 215
A26: OPERATING EXPENSES (ANNUAL)
B27: Insurance ($): | C27: 3400 | D27: 4100 | E27: 2700
B28: Property tax ($): | C28: 5800 | D28: 7200 | E28: 4200
B29: Utilities ($): | C29: 2400 | D29: 3000 | E29: 1800
B30: Management fee (%): | C30: 0 | D30: 0 | E30: 0
B31: Cleaning ($/yr): | C31: 6800 | D31: 8200 | E31: 5400
B32: Supplies ($/yr): | C32: 1400 | D32: 1700 | E32: 1100
A36: Questions? hello@thestrledger.com
A37: ACQ-004 · Inputs

Sheet Underwriting
A2: =HYPERLINK("#'Inputs'!A1", "← BACK") | D2: UNDERWRITING | J2: =HYPERLINK("#'Comparison Matrix'!A1", "NEXT →")
A4: Computed metrics. Don't edit — these flow from Inputs.
C5: PROPERTY A | D5: PROPERTY B | E5: PROPERTY C
A6: COMPUTED METRICS
B7: Total cash invested: | C7: =(Inputs!C14*Inputs!C15+Inputs!C18+Inputs!C19+Inputs!C20) | D7: =(Inputs!D14*Inputs!D15+Inputs!D18+Inputs!D19+Inputs!D20) | E7: =(Inputs!E14*Inputs!E15+Inputs!E18+Inputs!E19+Inputs!E20)
B8: Gross revenue (annual): | C8: =(Inputs!C23*365*Inputs!C24) | D8: =(Inputs!D23*365*Inputs!D24) | E8: =(Inputs!E23*365*Inputs!E24)
B9: Operating expenses: | C9: =(Inputs!C27+Inputs!C28+Inputs!C29+Inputs!C31+Inputs!C32+(Inputs!C23*365*Inputs!C24)*Inputs!C30) | D9: =(Inputs!D27+Inputs!D28+Inputs!D29+Inputs!D31+Inputs!D32+(Inputs!D23*365*Inputs!D24)*Inputs!D30) | E9: =(Inputs!E27+Inputs!E28+Inputs!E29+Inputs!E31+Inputs!E32+(Inputs!E23*365*Inputs!E24)*Inputs!E30)
B10: NOI (annual): | C10: =((Inputs!C23*365*Inputs!C24)-(Inputs!C27+Inputs!C28+Inputs!C29+Inputs!C31+Inputs!C32+(Inputs!C23*365*Inputs!C24)*Inputs!C30)) | D10: =((Inputs!D23*365*Inputs!D24)-(Inputs!D27+Inputs!D28+Inputs!D29+Inputs!D31+Inputs!D32+(Inputs!D23*365*Inputs!D24)*Inputs!D30)) | E10: =((Inputs!E23*365*Inputs!E24)-(Inputs!E27+Inputs!E28+Inputs!E29+Inputs!E31+Inputs!E32+(Inputs!E23*365*Inputs!E24)*Inputs!E30))
B11: Annual debt service: | C11: =(IFERROR(PMT(Inputs!C16/12,Inputs!C17*12,-(Inputs!C14*(1-Inputs!C15))),0)*12) | D11: =(IFERROR(PMT(Inputs!D16/12,Inputs!D17*12,-(Inputs!D14*(1-Inputs!D15))),0)*12) | E11: =(IFERROR(PMT(Inputs!E16/12,Inputs!E17*12,-(Inputs!E14*(1-Inputs!E15))),0)*12)
B12: Cash-on-cash: | C12: =((((Inputs!C23*365*Inputs!C24)-(Inputs!C27+Inputs!C28+Inputs!C29+Inputs!C31+Inputs!C32+(Inputs!C23*365*Inputs!C24)*Inputs!C30))-(IFERROR(PMT(Inputs!C16/12,Inputs!C17*12,-(Inputs!C14*(1-Inputs!C15))),0)*12))/(Inputs!C14*Inputs!C15+Inputs!C18+Inputs!C19+Inputs!C20)) | D12: =((((Inputs!D23*365*Inputs!D24)-(Inputs!D27+Inputs!D28+Inputs!D29+Inputs!D31+Inputs!D32+(Inputs!D23*365*Inputs!D24)*Inputs!D30))-(IFERROR(PMT(Inputs!D16/12,Inputs!D17*12,-(Inputs!D14*(1-Inputs!D15))),0)*12))/(Inputs!D14*Inputs!D15+Inputs!D18+Inputs!D19+Inputs!D20)) | E12: =((((Inputs!E23*365*Inputs!E24)-(Inputs!E27+Inputs!E28+Inputs!E29+Inputs!E31+Inputs!E32+(Inputs!E23*365*Inputs!E24)*Inputs!E30))-(IFERROR(PMT(Inputs!E16/12,Inputs!E17*12,-(Inputs!E14*(1-Inputs!E15))),0)*12))/(Inputs!E14*Inputs!E15+Inputs!E18+Inputs!E19+Inputs!E20))
B13: Cap rate: | C13: =(((Inputs!C23*365*Inputs!C24)-(Inputs!C27+Inputs!C28+Inputs!C29+Inputs!C31+Inputs!C32+(Inputs!C23*365*Inputs!C24)*Inputs!C30))/Inputs!C14) | D13: =(((Inputs!D23*365*Inputs!D24)-(Inputs!D27+Inputs!D28+Inputs!D29+Inputs!D31+Inputs!D32+(Inputs!D23*365*Inputs!D24)*Inputs!D30))/Inputs!D14) | E13: =(((Inputs!E23*365*Inputs!E24)-(Inputs!E27+Inputs!E28+Inputs!E29+Inputs!E31+Inputs!E32+(Inputs!E23*365*Inputs!E24)*Inputs!E30))/Inputs!E14)
B14: DSCR: | C14: =(((Inputs!C23*365*Inputs!C24)-(Inputs!C27+Inputs!C28+Inputs!C29+Inputs!C31+Inputs!C32+(Inputs!C23*365*Inputs!C24)*Inputs!C30))/(IFERROR(PMT(Inputs!C16/12,Inputs!C17*12,-(Inputs!C14*(1-Inputs!C15))),0)*12)) | D14: =(((Inputs!D23*365*Inputs!D24)-(Inputs!D27+Inputs!D28+Inputs!D29+Inputs!D31+Inputs!D32+(Inputs!D23*365*Inputs!D24)*Inputs!D30))/(IFERROR(PMT(Inputs!D16/12,Inputs!D17*12,-(Inputs!D14*(1-Inputs!D15))),0)*12)) | E14: =(((Inputs!E23*365*Inputs!E24)-(Inputs!E27+Inputs!E28+Inputs!E29+Inputs!E31+Inputs!E32+(Inputs!E23*365*Inputs!E24)*Inputs!E30))/(IFERROR(PMT(Inputs!E16/12,Inputs!E17*12,-(Inputs!E14*(1-Inputs!E15))),0)*12))
B15: Break-even occupancy: | C15: =(((Inputs!C27+Inputs!C28+Inputs!C29+Inputs!C31+Inputs!C32)+(IFERROR(PMT(Inputs!C16/12,Inputs!C17*12,-(Inputs!C14*(1-Inputs!C15))),0)*12))/(365*Inputs!C24*(1-Inputs!C30))) | D15: =(((Inputs!D27+Inputs!D28+Inputs!D29+Inputs!D31+Inputs!D32)+(IFERROR(PMT(Inputs!D16/12,Inputs!D17*12,-(Inputs!D14*(1-Inputs!D15))),0)*12))/(365*Inputs!D24*(1-Inputs!D30))) | E15: =(((Inputs!E27+Inputs!E28+Inputs!E29+Inputs!E31+Inputs!E32)+(IFERROR(PMT(Inputs!E16/12,Inputs!E17*12,-(Inputs!E14*(1-Inputs!E15))),0)*12))/(365*Inputs!E24*(1-Inputs!E30)))
B16: Annual cash flow (Y1): | C16: =(((Inputs!C23*365*Inputs!C24)-(Inputs!C27+Inputs!C28+Inputs!C29+Inputs!C31+Inputs!C32+(Inputs!C23*365*Inputs!C24)*Inputs!C30))-(IFERROR(PMT(Inputs!C16/12,Inputs!C17*12,-(Inputs!C14*(1-Inputs!C15))),0)*12)) | D16: =(((Inputs!D23*365*Inputs!D24)-(Inputs!D27+Inputs!D28+Inputs!D29+Inputs!D31+Inputs!D32+(Inputs!D23*365*Inputs!D24)*Inputs!D30))-(IFERROR(PMT(Inputs!D16/12,Inputs!D17*12,-(Inputs!D14*(1-Inputs!D15))),0)*12)) | E16: =(((Inputs!E23*365*Inputs!E24)-(Inputs!E27+Inputs!E28+Inputs!E29+Inputs!E31+Inputs!E32+(Inputs!E23*365*Inputs!E24)*Inputs!E30))-(IFERROR(PMT(Inputs!E16/12,Inputs!E17*12,-(Inputs!E14*(1-Inputs!E15))),0)*12))
B17: 5-yr IRR (proxy): | C17: =((((((Inputs!C23*365*Inputs!C24)-(Inputs!C27+Inputs!C28+Inputs!C29+Inputs!C31+Inputs!C32+(Inputs!C23*365*Inputs!C24)*Inputs!C30))-(IFERROR(PMT(Inputs!C16/12,Inputs!C17*12,-(Inputs!C14*(1-Inputs!C15))),0)*12))*5)+(Inputs!C14*0.16))/(Inputs!C14*Inputs!C15+Inputs!C18+Inputs!C19+Inputs!C20)/5) | D17: =((((((Inputs!D23*365*Inputs!D24)-(Inputs!D27+Inputs!D28+Inputs!D29+Inputs!D31+Inputs!D32+(Inputs!D23*365*Inputs!D24)*Inputs!D30))-(IFERROR(PMT(Inputs!D16/12,Inputs!D17*12,-(Inputs!D14*(1-Inputs!D15))),0)*12))*5)+(Inputs!D14*0.16))/(Inputs!D14*Inputs!D15+Inputs!D18+Inputs!D19+Inputs!D20)/5) | E17: =((((((Inputs!E23*365*Inputs!E24)-(Inputs!E27+Inputs!E28+Inputs!E29+Inputs!E31+Inputs!E32+(Inputs!E23*365*Inputs!E24)*Inputs!E30))-(IFERROR(PMT(Inputs!E16/12,Inputs!E17*12,-(Inputs!E14*(1-Inputs!E15))),0)*12))*5)+(Inputs!E14*0.16))/(Inputs!E14*Inputs!E15+Inputs!E18+Inputs!E19+Inputs!E20)/5)
A21: Questions? hello@thestrledger.com
A22: ACQ-004 · Underwriting

Sheet Comparison Matrix
A2: =HYPERLINK("#'Underwriting'!A1", "← BACK") | D2: COMPARISON MATRIX | J2: =HYPERLINK("#'Decision Notes'!A1", "NEXT →")
A4: Per-row winner highlighted in gold. Recommendation auto-computes if one wins ≥ 10/16 metrics.
B5: Metric | C5: Property A | D5: Property B | E5: Property C | F5: Direction
B6: Purchase price | C6: =Inputs!C14 | D6: =Inputs!D14 | E6: =Inputs!E14 | F6: ↓ lower wins
B7: Total cash invested | C7: =Underwriting!C7 | D7: =Underwriting!D7 | E7: =Underwriting!E7 | F7: ↓ lower wins
B8: Gross revenue (Y1) | C8: =Underwriting!C8 | D8: =Underwriting!D8 | E8: =Underwriting!E8 | F8: ↑ higher wins
B9: NOI | C9: =Underwriting!C10 | D9: =Underwriting!D10 | E9: =Underwriting!E10 | F9: ↑ higher wins
B10: Annual cash flow (Y1) | C10: =Underwriting!C16 | D10: =Underwriting!D16 | E10: =Underwriting!E16 | F10: ↑ higher wins
B11: Cash-on-cash | C11: =Underwriting!C12 | D11: =Underwriting!D12 | E11: =Underwriting!E12 | F11: ↑ higher wins
B12: Cap rate | C12: =Underwriting!C13 | D12: =Underwriting!D13 | E12: =Underwriting!E13 | F12: ↑ higher wins
B13: DSCR | C13: =Underwriting!C14 | D13: =Underwriting!D14 | E13: =Underwriting!E14 | F13: ↑ higher wins
B14: Break-even occupancy | C14: =Underwriting!C15 | D14: =Underwriting!D15 | E14: =Underwriting!E15 | F14: ↓ lower wins
B15: 5-yr IRR (proxy) | C15: =Underwriting!C17 | D15: =Underwriting!D17 | E15: =Underwriting!E17 | F15: ↑ higher wins
B16: Operating expenses | C16: =Underwriting!C9 | D16: =Underwriting!D9 | E16: =Underwriting!E9 | F16: ↓ lower wins
B17: Annual debt service | C17: =Underwriting!C11 | D17: =Underwriting!D11 | E17: =Underwriting!E11 | F17: ↓ lower wins
B18: ADR | C18: =Inputs!C24 | D18: =Inputs!D24 | E18: =Inputs!E24 | F18: ↑ higher wins
B19: Occupancy | C19: =Inputs!C23 | D19: =Inputs!D23 | E19: =Inputs!E23 | F19: ↑ higher wins
B20: Bedrooms | C20: =Inputs!C9 | D20: =Inputs!D9 | E20: =Inputs!E9 | F20: ↑ higher wins
B21: Sleeps | C21: =Inputs!C11 | D21: =Inputs!D11 | E21: =Inputs!E11 | F21: ↑ higher wins
B23: WINS PER PROPERTY | C23: =($C6=MIN($C6:$E6))+($C7=MIN($C7:$E7))+($C8=MAX($C8:$E8))+($C9=MAX($C9:$E9))+($C10=MAX($C10:$E10))+($C11=MAX($C11:$E11))+($C12=MAX($C12:$E12))+($C13=MAX($C13:$E13))+($C14=MIN($C14:$E14))+($C15=MAX($C15:$E15))+($C16=MIN($C16:$E16))+($C17=MIN($C17:$E17))+($C18=MAX($C18:$E18))+($C19=MAX($C19:$E19))+($C20=MAX($C20:$E20))+($C21=MAX($C21:$E21)) | D23: =($D6=MIN($C6:$E6))+($D7=MIN($C7:$E7))+($D8=MAX($C8:$E8))+($D9=MAX($C9:$E9))+($D10=MAX($C10:$E10))+($D11=MAX($C11:$E11))+($D12=MAX($C12:$E12))+($D13=MAX($C13:$E13))+($D14=MIN($C14:$E14))+($D15=MAX($C15:$E15))+($D16=MIN($C16:$E16))+($D17=MIN($C17:$E17))+($D18=MAX($C18:$E18))+($D19=MAX($C19:$E19))+($D20=MAX($C20:$E20))+($D21=MAX($C21:$E21)) | E23: =($E6=MIN($C6:$E6))+($E7=MIN($C7:$E7))+($E8=MAX($C8:$E8))+($E9=MAX($C9:$E9))+($E10=MAX($C10:$E10))+($E11=MAX($C11:$E11))+($E12=MAX($C12:$E12))+($E13=MAX($C13:$E13))+($E14=MIN($C14:$E14))+($E15=MAX($C15:$E15))+($E16=MIN($C16:$E16))+($E17=MIN($C17:$E17))+($E18=MAX($C18:$E18))+($E19=MAX($C19:$E19))+($E20=MAX($C20:$E20))+($E21=MAX($C21:$E21))
A30: =IF(MAX(C23:E23)>=10,"Recommendation: "&INDEX({"Property A","Property B","Property C"},MATCH(MAX(C23:E23),C23:E23,0))&" — wins "&MAX(C23:E23)&"/16 metrics","⚠ Close call — no clear winner. Review Decision Notes.")
A34: Questions? hello@thestrledger.com
A35: ACQ-004 · Comparison Matrix

Sheet Decision Notes
A2: =HYPERLINK("#'Comparison Matrix'!A1", "← BACK") | D2: DECISION NOTES
A4: Free-form notes per property. Pros/cons, gut feel, intel from showings.
C6: PROPERTY A | D6: PROPERTY B | E6: PROPERTY C
C7: =IF(Inputs!C7="","(unnamed)",Inputs!C7) | D7: =IF(Inputs!D7="","(unnamed)",Inputs!D7) | E7: =IF(Inputs!E7="","(unnamed)",Inputs!E7)
B9: PROS
C10: Best CoC return; strong amenity stack (hot tub + view). | D10: Highest ADR ceiling; lakefront premium. | E10: Lowest cash invested; lowest break-even occupancy.
B15: CONS
C16: Older HVAC; furnace replacement likely Y3. | D16: Highest cash invested; insurance bid still pending. | E16: Smaller (sleeps 6) caps revenue ceiling vs A/B.
B21: INTEL FROM SHOWING
C22: Seller motivated — relocation. Comp ADR $268 verified. | D22: Multiple offers expected. Seller wants 30-day close. | E22: Tenant occupied — vacancy on close not guaranteed.
B27: OFFER STRATEGY
C28: Offer $470K, request 2.5K closing credit. | D28: Pass unless price drops below $600K. | E28: Offer $345K with vacancy contingency.
A33: FINAL RECOMMENDATION
B34: ='Comparison Matrix'!A30
B35: Property A wins on cash-on-cash, NOI, and break-even. Lake (B) is overpriced for the revenue. Creek (C) has best entry price but smaller revenue ceiling. Going with A — submitting offer this week.
A41: Questions? hello@thestrledger.com
A42: ACQ-004 · Decision Notes
