Workbook

Sheet Start
A2: The STR Ledger
A4: Seller-Finance Offer Calculator
A5: What does this seller-finance deal really cost vs going to a bank?
A7: ACQ-010 · v1.0 · DEMO
A11: =IF(Settings!B5="","(set property name on Settings tab)",Settings!B5)
A13: MONTHLY P&I | D13: TOTAL COST OF LOAN | G13: VS-CONV SAVINGS | J13: CASH-ON-CASH
A14: ='Side-by-Side'!C12 | D14: ='Side-by-Side'!C16 | G14: ='Side-by-Side'!F18 | J14: ='Side-by-Side'!C19
A18: =IF('Side-by-Side'!F18>0,"✅ Seller finance saves $"&TEXT('Side-by-Side'!F18,"#,##0")&" cash up front · "&TEXT('Side-by-Side'!F19,"0.0%")&" CoC lift","⚠ Seller terms net more expensive than conventional — review Side-by-Side")
A21: =HYPERLINK("#'Term Inputs'!A1", "→ Term Inputs") | D21: =HYPERLINK("#'Side-by-Side'!A1", "Side-by-Side") | G21: =HYPERLINK("#'Term Sheet'!A1", "Term Sheet") | J21: =HYPERLINK("#'Settings'!A1", "Settings")
A26: 💡 Negotiating multiple seller-finance offers? Pair with the STR Deal Analyzer at thestrledger.com for full underwriting + DSCR stress test.
A29: Questions? hello@thestrledger.com
A30: ACQ-010 · v1.0 · DEMO · Free updates forever

Sheet Term Inputs
A2: =HYPERLINK("#'Start'!A1", "← BACK") | D2: TERM INPUTS | J2: =HYPERLINK("#'Side-by-Side'!A1", "NEXT →")
A4: The seller-finance offer terms you're modeling — edit yellow cells.
A6: PRICE & DOWN PAYMENT
B7: Purchase price ($): | C7: 485000
B8: Earnest money ($): | C8: 5000 | E8: Held in escrow at signing
B9: Seller-finance down (%): | C9: 0.1 | E9: Typical 5-15% for seller carry
B11: Seller note rate (%): | C11: 0.065 | E11: Fixed; often below market on motivated sellers
B12: Amortization (years): | C12: 30 | E12: 30-yr amortization standard
B13: Balloon (years): | C13: 7 | E13: 0 = fully amortizing; 5-7 typical balloon
B14: Interest-only period (months): | C14: 0 | E14: 0 = no IO; 6-24 months reduces Y1 cash burn
A16: PREPAYMENT & CLOSING
B17: Prepayment penalty terms: | C17: None after Year 3 (3-2-1 step-down) | E17: Free-text — pasted into Term Sheet
B18: Closing costs ($): | C18: 3500 | E18: Seller-finance often 1-2% (no lender fees)
B19: Target closing date: | C19: 2026-07-15 | E19: YYYY-MM-DD format
A21: DERIVED
B22: Down payment ($): | C22: =C7*C9
B23: Seller carry-back ($): | C23: =C7*(1-C9)
B24: Total cash to close ($): | C24: =C7*C9+C18
A28: Questions? hello@thestrledger.com
A29: ACQ-010 · Term Inputs

Sheet Side-by-Side
A2: =HYPERLINK("#'Term Inputs'!A1", "← BACK") | D2: SIDE-BY-SIDE | J2: =HYPERLINK("#'Term Sheet'!A1", "NEXT →")
A4: Seller finance vs conventional 25%-down DSCR loan — row-by-row deltas.
B6: Metric | C6: Seller Finance | D6: Conventional 25% | F6: Δ Cash Saved | G6: Δ Annual CF
B7: Down payment | C7: =('Term Inputs'!C7*'Term Inputs'!C9) | D7: =('Term Inputs'!C7*Settings!B11) | F7: =D7-C7
B8: Closing costs | C8: ='Term Inputs'!C18 | D8: =('Term Inputs'!C7*Settings!B13) | F8: =D8-C8
B9: Total cash in | C9: =(('Term Inputs'!C7*'Term Inputs'!C9)+'Term Inputs'!C18) | D9: =(('Term Inputs'!C7*Settings!B11)+('Term Inputs'!C7*Settings!B13)) | F9: =D9-C9
B10: Loan amount | C10: =('Term Inputs'!C7*(1-'Term Inputs'!C9)) | D10: =('Term Inputs'!C7*(1-Settings!B11))
B11: Interest rate | C11: ='Term Inputs'!C11 | D11: =Settings!B7
B12: Monthly P&I | C12: =IFERROR(PMT('Term Inputs'!C11/12,'Term Inputs'!C12*12,-('Term Inputs'!C7*(1-'Term Inputs'!C9))),0) | D12: =IFERROR(PMT(Settings!B7/12,Settings!B9*12,-('Term Inputs'!C7*(1-Settings!B11))),0) | G12: =(C12-D12)*12
B13: Annual debt service | C13: =(IFERROR(PMT('Term Inputs'!C11/12,'Term Inputs'!C12*12,-('Term Inputs'!C7*(1-'Term Inputs'!C9))),0)*12) | D13: =(IFERROR(PMT(Settings!B7/12,Settings!B9*12,-('Term Inputs'!C7*(1-Settings!B11))),0)*12) | G13: =C13-D13
B14: Term / Balloon (years) | C14: =IF('Term Inputs'!C13>0,'Term Inputs'!C13&"-yr balloon",'Term Inputs'!C12&"-yr fully amort") | D14: =Settings!B9&"-yr fully amort"
B15: Balloon balance owed | C15: =IFERROR(-FV('Term Inputs'!C11/12,IF('Term Inputs'!C13>0,'Term Inputs'!C13*12,'Term Inputs'!C12*12),IFERROR(PMT('Term Inputs'!C11/12,'Term Inputs'!C12*12,-('Term Inputs'!C7*(1-'Term Inputs'!C9))),0),('Term Inputs'!C7*(1-'Term Inputs'!C9))),0) | D15: =0
B16: Total cost of loan (life) | C16: =(IFERROR(PMT('Term Inputs'!C11/12,'Term Inputs'!C12*12,-('Term Inputs'!C7*(1-'Term Inputs'!C9))),0)*IF('Term Inputs'!C13>0,'Term Inputs'!C13*12,'Term Inputs'!C12*12)+IFERROR(-FV('Term Inputs'!C11/12,IF('Term Inputs'!C13>0,'Term Inputs'!C13*12,'Term Inputs'!C12*12),IFERROR(PMT('Term Inputs'!C11/12,'Term Inputs'!C12*12,-('Term Inputs'!C7*(1-'Term Inputs'!C9))),0),('Term Inputs'!C7*(1-'Term Inputs'!C9))),0)+('Term Inputs'!C7*'Term Inputs'!C9)+'Term Inputs'!C18) | D16: =(IFERROR(PMT(Settings!B7/12,Settings!B9*12,-('Term Inputs'!C7*(1-Settings!B11))),0)*(Settings!B9*12)+('Term Inputs'!C7*Settings!B11)+('Term Inputs'!C7*Settings!B13))
B17: Total interest paid | C17: =(IFERROR(PMT('Term Inputs'!C11/12,'Term Inputs'!C12*12,-('Term Inputs'!C7*(1-'Term Inputs'!C9))),0)*IF('Term Inputs'!C13>0,'Term Inputs'!C13*12,'Term Inputs'!C12*12)-(('Term Inputs'!C7*(1-'Term Inputs'!C9))-IFERROR(-FV('Term Inputs'!C11/12,IF('Term Inputs'!C13>0,'Term Inputs'!C13*12,'Term Inputs'!C12*12),IFERROR(PMT('Term Inputs'!C11/12,'Term Inputs'!C12*12,-('Term Inputs'!C7*(1-'Term Inputs'!C9))),0),('Term Inputs'!C7*(1-'Term Inputs'!C9))),0))) | D17: =(IFERROR(PMT(Settings!B7/12,Settings!B9*12,-('Term Inputs'!C7*(1-Settings!B11))),0)*(Settings!B9*12)-('Term Inputs'!C7*(1-Settings!B11)))
B18: Annual cash flow (NOI − DS) | C18: =(Settings!B15-(IFERROR(PMT('Term Inputs'!C11/12,'Term Inputs'!C12*12,-('Term Inputs'!C7*(1-'Term Inputs'!C9))),0)*12)) | D18: =(Settings!B15-(IFERROR(PMT(Settings!B7/12,Settings!B9*12,-('Term Inputs'!C7*(1-Settings!B11))),0)*12))
B19: Cash-on-cash | C19: =((Settings!B15-(IFERROR(PMT('Term Inputs'!C11/12,'Term Inputs'!C12*12,-('Term Inputs'!C7*(1-'Term Inputs'!C9))),0)*12))/(('Term Inputs'!C7*'Term Inputs'!C9)+'Term Inputs'!C18)) | D19: =((Settings!B15-(IFERROR(PMT(Settings!B7/12,Settings!B9*12,-('Term Inputs'!C7*(1-Settings!B11))),0)*12))/(('Term Inputs'!C7*Settings!B11)+('Term Inputs'!C7*Settings!B13)))
B21: =IF(F9>0,"Seller finance saves $"&TEXT(F9,"#,##0")&" cash up front. "&IF(C18>D18,"And nets +$"&TEXT(C18-D18,"#,##0")&" more annual cash flow.","But nets −$"&TEXT(D18-C18,"#,##0")&" less annual cash flow.")&" CoC: "&TEXT(C19,"0.0%")&" vs "&TEXT(D19,"0.0%")&".","Conventional is cheaper here — seller terms above market.")
B23: Effective cost note: if seller note rate exceeds market (Settings!B7), the absolute monthly P&I may be higher despite lower cash in. The CoC metric is the honest tiebreaker — cash flow earned per dollar invested. If you're cash-constrained, low-cash deals often win even with higher rate.
A28: Questions? hello@thestrledger.com
A29: ACQ-010 · Side-by-Side

Sheet Term Sheet
A2: =HYPERLINK("#'Side-by-Side'!A1", "← BACK") | D2: TERM SHEET | J2: =HYPERLINK("#'Settings'!A1", "NEXT →")
A4: Print-ready draft term sheet — generated from Term Inputs + Settings. Edit parties below.
A6: PARTIES (edit these — flow into the document below)
B7: Buyer name: | C7: Daniel Harrison
B8: Buyer entity: | C8: Smokies Ridge Holdings LLC
B9: Seller name(s): | C9: Robert & Mary Whitfield
A11: DRAFT TERM SHEET — copy/paste or print
B13: SELLER-FINANCED PURCHASE — TERM SHEET
B14: ="Drafted: "&TEXT(TODAY(),"mmmm d, yyyy")
B16: ="Property: "&Settings!B5&" — "&Settings!B17
B17: ="Buyer: "&C7&IF(C8="",""," (acting through "&C8&")")
B18: ="Seller: "&C9
B20: ="1. Purchase Price: $"&TEXT('Term Inputs'!C7,"#,##0")&" USD."
B21: ="2. Earnest Money: $"&TEXT('Term Inputs'!C8,"#,##0")&" deposited within three (3) business days of mutual execution, held in escrow and credited at Closing."
B22: ="3. Down Payment: $"&TEXT('Term Inputs'!C7*'Term Inputs'!C9,"#,##0")&" ("&TEXT('Term Inputs'!C9,"0.0%")&" of Purchase Price), payable at Closing."
B23: ="4. Seller Carry-Back Note: Principal of $"&TEXT('Term Inputs'!C7*(1-'Term Inputs'!C9),"#,##0")&" at "&TEXT('Term Inputs'!C11,"0.000%")&" fixed annual interest, amortized over "&'Term Inputs'!C12&" years, "&IF('Term Inputs'!C13>0,"with a balloon payment of all unpaid principal and accrued interest due at the end of Year "&'Term Inputs'!C13&".","fully amortizing with no balloon.")
B24: =IF('Term Inputs'!C14>0,"5. Interest-Only Period: First "&'Term Inputs'!C14&" months interest-only, then converting to fully amortizing payments per Section 4.","5. Payment Schedule: Standard amortizing monthly payments of approximately $"&TEXT(IFERROR(PMT('Term Inputs'!C11/12,'Term Inputs'!C12*12,-('Term Inputs'!C7*(1-'Term Inputs'!C9))),0),"#,##0.00")&" beginning the first day of the month following Closing.")
B25: ="6. Prepayment: "&'Term Inputs'!C17&". Buyer may prepay all or any portion of principal subject to the foregoing terms."
B26: ="7. Security: Note secured by a first-position Deed of Trust / Mortgage on the Property recorded at Closing."
B27: ="8. Closing Date: On or before "&'Term Inputs'!C19&", or such later date as the parties mutually agree in writing."
B28: ="9. Closing Costs: Each party bears their customary share. Buyer estimates total closing costs of $"&TEXT('Term Inputs'!C18,"#,##0")&"."
B29: ="10. Contingencies: This offer is contingent upon (a) Buyer's satisfactory inspection of the Property within fifteen (15) days, (b) clear and marketable title, (c) Buyer's confirmation of permitted short-term-rental use, and (d) any zoning, HOA, or insurance verifications customary in the jurisdiction."
B30: ="11. Assignment: Buyer may assign this agreement to a wholly-owned entity ("&IF(C8="","TBD",C8)&") prior to Closing without further consent."
B31: ="12. Default & Cure: Standard 30-day cure period; on uncured default, Seller's remedies are limited to those stated in the Note and Deed of Trust."
B32: ="13. This Term Sheet is non-binding and intended to summarize the principal economic terms. The parties shall execute a definitive Purchase & Sale Agreement and Promissory Note reflecting these terms."
B34: SIGNATURES
B36: Buyer: | C36: =C7
B37: Date:
B39: Seller: | C39: =C9
B40: Date:
A44: Questions? hello@thestrledger.com
A45: ACQ-010 · Term Sheet · NON-BINDING DRAFT

Sheet Settings
A2: =HYPERLINK("#'Term Sheet'!A1", "← BACK") | D2: SETTINGS
A4: Property identity + conventional-loan benchmarks for the Side-by-Side comparison.
B5: Smokies Ridge Cabin | D5: Property name:
B7: 0.0725 | D7: Conventional rate (%): | E7: Today's market DSCR rate (default 7.25%)
B9: 30 | D9: Conventional term (yrs): | E9: 30 standard
B11: 0.25 | D11: Conventional down (%): | E11: 25% standard for DSCR
B13: 0.03 | D13: Conventional closing (%): | E13: Approx 3% of purchase
B15: 42000 | D15: Annual NOI (after opex, $): | E15: From your operating P&L — drives CoC
B17: 123 Mountain Lane, Gatlinburg, TN 37738 | D17: Property address: | E17: Used in Term Sheet
A20: DEAL ARCHIVE — log each seller-finance offer outcome
B21: Year | C21: Property | D21: Outcome | E21: Final monthly P&I | F21: Notes
B22: 2026
B23: 2027
B24: 2028
B25: 2029
B26: 2030
A31: Questions? hello@thestrledger.com
A32: ACQ-010 · Settings
