Workbook

Sheet Start
A2: The STR Ledger
A4: STR vs LTR Yield Comparison
A5: Airbnb or 12-month lease — which actually pays you more?
A7: ACQ-012 · v1.0 · DEMO
A11: =IF(Settings!B5="","(enter property name on Settings tab)",Settings!B5)
A13: ='Side-by-Side'!C12 | D13: ='Side-by-Side'!E12 | G13: ='Side-by-Side'!G12 | J13: ='Side-by-Side'!G19
A18: STR NOI | D18: LTR NOI | G18: DIFFERENCE | J18: HRS/WK Δ
A20: =IF('Side-by-Side'!C12>='Side-by-Side'!E12,"STR wins NOI by "&TEXT('Side-by-Side'!G12,"$#,##0")&" — but "&TEXT('Side-by-Side'!G19,"0.0")&" more hrs/wk + reg risk "&'Side-by-Side'!C20&"/10","LTR wins NOI by "&TEXT(-'Side-by-Side'!G12,"$#,##0")&" with "&TEXT(-'Side-by-Side'!G19,"0.0")&" fewer hrs/wk")
A22: ="Effective $/hr — STR: "&TEXT('Side-by-Side'!C18,"$#,##0")&" | LTR: "&TEXT('Side-by-Side'!E18,"$#,##0")
A25: =HYPERLINK("#'Side-by-Side'!A1", "→ Open Side-by-Side") | G25: =HYPERLINK("#'Inputs'!A1", "Edit Inputs")
A29: =HYPERLINK("#'Decision Notes'!A1", "Decision Notes")
A33: Note: NOI excludes debt service. Cash flow / CoC factor it in. Regulatory risk is your subjective 1-10 — bump it if your city is actively debating an STR cap or registration regime.
A37: Questions? hello@thestrledger.com
A38: ACQ-012 · v1.0 · DEMO · Free updates forever

Sheet Inputs
A2: =HYPERLINK("#'Start'!A1", "← BACK") | D2: INPUTS | J2: =HYPERLINK("#'Side-by-Side'!A1", "NEXT →")
A4: Yellow = edit. STR column on the left, LTR on the right.
C5: STR | E5: LTR
A7: SHARED — APPLIES TO BOTH SCENARIOS
B8: Cash invested (down + closing + setup) ($): | C8: 121000 | E8: =C8 | G8: STR may need higher furnishing — adjust if comparing apples to apples
B9: Annual debt service ($): | C9: 28800 | E9: =C9 | G9: P+I — same loan, same payment, regardless of rental strategy
A11: REVENUE ASSUMPTIONS
B12: STR Occupancy (%): | C12: 0.62 | E12: — | G12: Year-2+ stabilized
B13: STR ADR — Avg nightly rate ($): | C13: 245 | E13: — | G13: Gross — commission applied below
B14: LTR Monthly rent ($): | C14: — | E14: 2800 | G14: Annual = monthly × 12
B15: LTR Vacancy (%): | C15: — | E15: 0.05 | G15: 5% typical for stable markets
A17: OPERATING EXPENSE ASSUMPTIONS
B18: STR Cleaning paid ($/turnover): | C18: 150 | E18: —
B19: STR Turnovers per year: | C19: 68 | E19: — | G19: =(occupancy × 365) ÷ avg LOS
B20: STR Supplies / consumables (annual, $): | C20: 1800 | E20: — | G20: Toiletries, paper, coffee
B21: STR Software / PMS (annual, $): | C21: 720 | E21: — | G21: Hospitable, OwnerRez, dynamic pricing
B22: Channel/PM fee (%): | C22: 0.03 | E22: 0 | G22: STR: Airbnb 3% or PM 20%. LTR: 0% self / 8% managed
B23: Insurance (annual, $): | C23: 2400 | E23: 1400 | G23: STR rider runs 30-100% higher than landlord policy
B24: STR Utilities (annual, $): | C24: 2160 | E24: — | G24: Host pays in STR; tenant typically pays in LTR
B25: Maintenance reserve (%): | C25: 0.05 | E25: 0.05 | G25: % of gross revenue set aside for repairs
B26: LTR Tenant turnover cost (annualized, $): | C26: — | E26: 500 | G26: Lease-up costs ÷ avg tenancy length
A28: TIME + REGULATORY RISK
B29: Host hours per week: | C29: 8 | E29: 0.5 | G29: Self-managed STR: 5-15. Self-managed LTR: 0.25-1
B30: Regulatory risk (1-10): | C30: 7 | E30: 1 | G30: Subjective — high if your city is debating an STR cap
A34: Questions? hello@thestrledger.com
A35: ACQ-012 · v1.0 · Inputs · DEMO

Sheet Side-by-Side
A2: =HYPERLINK("#'Inputs'!A1", "← BACK") | D2: SIDE-BY-SIDE | J2: =HYPERLINK("#'Decision Notes'!A1", "NEXT →")
A4: Per-row winner highlighted gold. All formulas reference the Inputs tab.
B6: Metric | C6: STR | E6: LTR | G6: Difference
B8: Annual gross revenue | C8: =Inputs!C13*Inputs!C12*365 | E8: =Inputs!E14*12 | G8: =C8-E8
B9: Cleaning (annual) | C9: =Inputs!C18*Inputs!C19 | E9: =Inputs!E26 | G9: =C9-E9
B10: Supplies + Software + Utilities | C10: =Inputs!C20+Inputs!C21+Inputs!C24 | E10: =0 | G10: =C10-E10
B11: Channel/PM fee + Insurance + Maintenance | C11: =(C8*Inputs!C22)+Inputs!C23+(C8*Inputs!C25) | E11: =(E8*(1-Inputs!E15)*Inputs!E22)+Inputs!E23+(E8*Inputs!E25) | G11: =C11-E11
B12: NOI (Net Operating Income) | C12: =C8-C9-C10-C11 | E12: =E8*(1-Inputs!E15)-E9-E10-E11 | G12: =C12-E12
B13: Debt service | C13: =Inputs!C9 | E13: =Inputs!E9 | G13: =C13-E13
B14: Cash flow | C14: =C12-C13 | E14: =E12-E13 | G14: =C14-E14
B15: Cash-on-Cash return | C15: =IFERROR(C14/Inputs!C8,0) | E15: =IFERROR(E14/Inputs!E8,0) | G15: =C15-E15
B16: Cap rate | C16: =IFERROR(C12/Settings!B9,0) | E16: =IFERROR(E12/Settings!B9,0) | G16: =C16-E16
B17: Hours / week | C17: =Inputs!C29 | E17: =Inputs!E29 | G17: =C17-E17
B18: Effective $ per hour (cash flow ÷ hrs/yr) | C18: =IFERROR(C14/(Inputs!C29*52),0) | E18: =IFERROR(E14/(Inputs!E29*52),0) | G18: =C18-E18
B19: Hours/week difference (STR − LTR) | G19: =C17-E17
B20: Regulatory risk (1-10) | C20: =Inputs!C30 | E20: =Inputs!E30 | G20: =C20-E20
B21: 5-year cumulative cash flow | C21: =C14*5 | E21: =E14*5 | G21: =C21-E21
A23: =IF(C18<E18,"⚠ Counterintuitive: STR's effective $/hr ("&TEXT(C18,"$#,##0")&") is lower than LTR's ("&TEXT(E18,"$#,##0")&"). The extra revenue is real — but so is the labor.","")
A27: Questions? hello@thestrledger.com
A28: ACQ-012 · v1.0 · Side-by-Side · DEMO

Sheet Decision Notes
A2: =HYPERLINK("#'Side-by-Side'!A1", "← BACK") | D2: DECISION NOTES | J2: =HYPERLINK("#'Settings'!A1", "NEXT →")
A4: Free-form notes. The numbers are only half the story.
A6: REGULATORY RISK
A7: What's your city saying about STR? Permit cap? Owner-occupancy requirement? Pending council vote? Document it here so future you remembers why this number is what it is.
A12: LIFE STAGE
A13: Are you OK with 8 hrs/wk of guest comms for the next 5 years? Will that change if you have a kid, take a new job, move?
A18: TIME AVAILABLE + OPPORTUNITY COST
A19: If your $/hr on the day job is higher than your STR effective $/hr, the LTR option may free up earning power elsewhere.
A24: CAPITAL EXIT
A25: STR-furnished property may sell to fewer buyers in a downturn. LTR property is a standard rental — broader buyer pool.
A30: TAX STRATEGY
A31: STR with material participation can offset W-2 income via cost seg + bonus depreciation (REPS-lite). LTR cannot, unless you're a real estate professional.
A38: Questions? hello@thestrledger.com
A39: ACQ-012 · v1.0 · Decision Notes · DEMO

Sheet Settings
A2: =HYPERLINK("#'Decision Notes'!A1", "← BACK") | D2: SETTINGS
A4: Workbook-wide settings. Set once, referenced everywhere.
B5: Property name: | C5: Smokies Ridge Cabin
B7: Active year: | C7: 2026
B9: Property value ($): | C9: 485000
A12: Property value drives the cap rate calculation on the Side-by-Side tab. If you don't have a recent appraisal, use your purchase price + a conservative appreciation estimate.
A17: Questions? hello@thestrledger.com
A18: ACQ-012 · v1.0 · Settings · DEMO
