Workbook

Sheet Start
A2: The STR Ledger
A4: Rental Arbitrage Analyzer
A5: Will the numbers actually work — through Year 2?
A7: ACQ-003 · v1.0 · DEMO
A11: =IF('Lease Terms'!C7="","(enter property on Lease Terms tab)",'Lease Terms'!C7)
A13: VERDICT
A14: ='Stress Test'!B22
A17: Y1 MONTHLY CASH FLOW | G17: STABILIZED MONTHLY CASH FLOW
A18: ='Operating Math'!C22 | G18: ='Operating Math'!D22
A21: ='Stress Test'!B23 | G21: ='MTR Fallback'!B16
A25: =HYPERLINK("#'Lease Terms'!A1", "Lease Terms") | D25: =HYPERLINK("#'Setup Costs'!A1", "Setup Costs") | G25: =HYPERLINK("#'Revenue Projection'!A1", "Revenue") | J25: =HYPERLINK("#'Operating Math'!A1", "Operating")
A29: =HYPERLINK("#'Stress Test'!A1", "→ Stress Test") | E29: =HYPERLINK("#'MTR Fallback'!A1", "→ MTR Fallback") | I29: =HYPERLINK("#'Landlord Pitch'!A1", "→ Landlord Pitch Page")
A34: Want to underwrite owned properties too? Get the STR Deal Analyzer (ACQ-001) at thestrledger.com — $47.
A37: Questions? hello@thestrledger.com
A38: ACQ-003 · v1.0 · DEMO · Free updates forever

Sheet Lease Terms
A2: =HYPERLINK("#'Start'!A1", "← BACK") | D2: LEASE TERMS | J2: =HYPERLINK("#'Setup Costs'!A1", "NEXT →")
A4: Section 1 of 4 — what the landlord is offering
A6: PROPERTY
B7: Property address: | C7: 428 Linden Ave, Unit 3B
B8: City, State, Zip: | C8: Denver, CO 80218
B9: Unit type: | C9: Apartment | E9: Dropdown
B10: Bedrooms: | C10: 2
B11: Bathrooms: | C11: 1.5
B12: Square feet: | C12: 980
A14: LEASE FINANCIALS
B15: Monthly rent ($): | C15: 2400 | E15: What the landlord wants you to pay
B16: Security deposit ($): | C16: 4800 | E16: Typically 1-2 months' rent
B17: Lease term (months): | C17: 12 | E17: 12 typical
B18: Lease start date: | C18: 2026-06-01
B19: Renewal escalator (%): | C19: 0.05 | E19: Year-2+ rent hike clause. Default 5%.
A21: RESTRICTIONS (the deal-killers)
B22: Sublet allowed? | C22: Conditional | E22: Yes / No / Conditional. NO = STR illegal under this lease.
B23: STR-zone allowed? | C23: Yes | E23: City zoning permits short-term rentals?
B24: Insurance addendum req.? | C24: Yes | E24: Most landlord-friendly. Plan to carry $1M liability.
B25: Pets allowed? | C25: No | E25: Yes / No
A27: =IF(OR(C22="No",C23="No"),"RED FLAG: Sublet or STR-zone is NO — this property cannot legally run as STR. The Verdict will lock to PASS.",IF(OR(C22="Conditional",C23="Unsure"),"YELLOW FLAG: Get the sublet allowance and STR-zoning in WRITING from the landlord and city before signing.","All restrictions clear — STR-eligible under this lease."))
A29: EARLY-TERM CLAUSE + LANDLORD CONTACT
B30: Early-termination clause: | C30: 60-day notice + 2 months' rent | E30: Free text. Most arbitrage operators want a 60-day exit.
B31: Landlord name / entity: | C31: Kestrel Property Group, LLC
B32: Landlord contact: | C32: Maria Chen · maria@kestrelpg.com · (303) 555-0142 | E32: Name · email · phone
A36: Questions? hello@thestrledger.com
A37: ACQ-003 · Lease Terms

Sheet Setup Costs
A2: =HYPERLINK("#'Lease Terms'!A1", "← BACK") | D2: SETUP COSTS | J2: =HYPERLINK("#'Revenue Projection'!A1", "NEXT →")
A4: Section 2 of 4 — one-time furnish + tech + supplies. Smaller than owned-property setup (no major appliances — landlord supplies those).
B6: Category | C6: Low ($) | D6: Mid ($) | E6: High ($) | G6: Note
B7: Kitchen — cookware/plates/utensils | C7: 1200 | D7: 2000 | E7: 3200 | G7: Coffee maker, knives, full kit for 6
B8: Bedding — mattresses/linens/towels | C8: 1500 | D8: 2400 | E8: 3600 | G8: Hotel-grade for premium ADR
B9: Bath — toilet brush/scale/shower | C9: 400 | D9: 650 | E9: 900 | G9: Soft launch consumables included
B10: Living — sofa/coffee table/TV | C10: 1800 | D10: 2800 | E10: 4200 | G10: Sleeper sofa raises occupancy
B11: Decor — art/rug/lamps | C11: 600 | D11: 1100 | E11: 1800 | G11: Photogenic = better listing photos
B12: Tech — smart locks/Wi-Fi/cameras | C12: 700 | D12: 1100 | E12: 1700 | G12: Schlage / eero / Ring Outdoor
B13: Security — exterior cameras/sensors | C13: 200 | D13: 450 | E13: 700 | G13: Required by some city STR ordinances
B14: Cleaning supplies (start kit) | C14: 300 | D14: 500 | E14: 800 | G14: Mop / vacuum / starter chemicals
B15: Initial deep clean | C15: 150 | D15: 300 | E15: 500 | G15: Pro deep-clean before listing
B16: Small tools / fasteners / hooks | C16: 200 | D16: 400 | E16: 700 | G16: Drill, level, picture hangers
B17: Outdoor — patio set / firepit | C17: 300 | D17: 600 | E17: 1000 | G17: If unit has outdoor space
B18: Consumables — soap/coffee/paper | C18: 250 | D18: 450 | E18: 700 | G18: First 3 months of restock
... B20: Buffer (5-8% of mid total) | C20: 500 | D20: 800 | E20: 1300 | G20: Always overruns. Always.
B22: TOTAL SETUP COST | C22: =SUM(C7:C20) | D22: =SUM(D7:D20) | E22: =SUM(E7:E20)
B24: Cash to launch (deposit + Mid setup): | D24: ='Lease Terms'!C16+D22
A28: Questions? hello@thestrledger.com
A29: ACQ-003 · Setup Costs

Sheet Revenue Projection
A2: =HYPERLINK("#'Setup Costs'!A1", "← BACK") | D2: REVENUE PROJECTION | J2: =HYPERLINK("#'Operating Math'!A1", "NEXT →")
A4: Section 3 of 4 — paste from AirDNA / Rabbu / KeyData. Haircut Y1 hard.
A6: MARKET ASSUMPTIONS
B7: ADR — avg nightly rate ($): | C7: 185 | E7: Paste from AirDNA
B8: Stabilized occupancy (%): | C8: 0.7 | E8: Year 2-3 expected
B9: Year 1 occupancy (%): | C9: 0.42 | E9: Default 60% of stabilized — arbitrage Y1 is harder
B10: Avg length of stay (nights): | C10: 2.8 | E10: 1.5-7 typical
B11: Cleaning fee charged ($): | C11: 145 | E11: What guests pay (separate from cleaning paid)
B12: Platform commission (%): | C12: 0.15 | E12: Airbnb 15%, VRBO 8%, direct 0-3%
B13: Seasonality factor (multiplier): | C13: 1 | E13: 1.00 = neutral; 1.10 = peak market; 0.90 = off-peak
A15: DERIVED (monthly)
B16: Y1 booked nights / mo: | C16: =C9*30.42*C13
B17: Stabilized booked nights / mo: | C17: =C8*30.42*C13
B18: Y1 turnovers / mo: | C18: =C16/C10
B19: Stabilized turnovers / mo: | C19: =C17/C10
B20: Y1 gross revenue / mo: | C20: =C16*C7+C18*C11
B21: Stabilized gross revenue / mo: | C21: =C17*C7+C19*C11
B22: Y1 net revenue / mo (after platform): | C22: =C20*(1-C12)
B23: Stabilized net revenue / mo: | C23: =C21*(1-C12)
A26: PASTE FROM AIRDNA / RABBU / KEYDATA
A27: Pull market RevPAR, ADR, and occupancy from AirDNA Markets. Look for the same beds/baths/unit type. Then haircut: arbitrage Y1 occupancy is roughly 60% of stabilized, not 80%. Ramp time is real — listings need ~50 reviews before they crack the algorithm.
A33: Questions? hello@thestrledger.com
A34: ACQ-003 · Revenue

Sheet Operating Math
A2: =HYPERLINK("#'Revenue Projection'!A1", "← BACK") | D2: OPERATING MATH | J2: =HYPERLINK("#'Stress Test'!A1", "NEXT →")
A4: Section 4 of 4 — monthly cash flow. Y1 vs Stabilized side-by-side.
B6: Line item | C6: Year 1 / mo | D6: Stabilized / mo | E6: Note
A7: MONTHLY OPERATING COSTS
B8: Rent (from Lease Terms): | C8: ='Lease Terms'!C15 | D8: =C8 | E8: Auto-pulled
B9: Utilities ($): | C9: 220 | D9: 220 | E9: Electric/gas/water/trash
B10: Internet ($): | C10: 80 | D10: 80
B11: Software / PMS ($): | C11: 40 | D11: 40 | E11: Hospitable, Hostfully, etc.
B12: Cleaning paid ($/turnover): | C12: 135 | D12: 135 | E12: What you pay your cleaner
B13: Supplies ($/turnover): | C13: 18 | D13: 18 | E13: Soap, paper, coffee restock
B14: Marketing ($): | C14: 45 | D14: 45 | E14: Photos refresh, Pinterest ads
B15: Insurance ($): | C15: 85 | D15: 85 | E15: Proper / Slice STR-specific
B16: Other ($): | C16: 40 | D16: 40
A18: ROLL-UP
B19: Total operating cost / mo: | C19: =C8+C9+C10+C11+C14+C15+C16+(C12+C13)*'Revenue Projection'!C18 | D19: =D8+D9+D10+D11+D14+D15+D16+(D12+D13)*'Revenue Projection'!C19
B20: Net revenue / mo: | C20: ='Revenue Projection'!C22 | D20: ='Revenue Projection'!C23
B22: MONTHLY CASH FLOW: | C22: =C20-C19 | D22: =D20-D19
B23: Annual cash flow: | C23: =C22*12 | D23: =D22*12
A27: Questions? hello@thestrledger.com
A28: ACQ-003 · Operating Math

Sheet Stress Test
A2: =HYPERLINK("#'Operating Math'!A1", "← BACK") | D2: STRESS TEST | J2: =HYPERLINK("#'MTR Fallback'!A1", "NEXT →")
A4: The arbitrage killer is the Year-2 rent escalator. Most gurus skip it. This tab bakes a 5% escalator into Year 2 and a 7%+ shock case.
B6: Metric | C6: Base (Y1) | D6: Y2 + 5% escalator | E6: Worst case | G6: Method
B7: Monthly cash flow: | C7: ='Operating Math'!C22 | D7: =('Operating Math'!D22 - 'Lease Terms'!C15*'Lease Terms'!C19) | E7: =(((('Revenue Projection'!C8-0.10)*30.42*'Revenue Projection'!C13)*'Revenue Projection'!C7 + (('Revenue Projection'!C8-0.10)*30.42*'Revenue Projection'!C13/'Revenue Projection'!C10)*'Revenue Projection'!C11)*(1-'Revenue Projection'!C12) - ('Lease Terms'!C15*1.07 + 'Operating Math'!D9 + 'Operating Math'!D10 + 'Operating Math'!D11 + 'Operating Math'!D14 + 'Operating Math'!D15 + 'Operating Math'!D16 + ('Operating Math'!D12 + 'Operating Math'!D13*1.15)*((('Revenue Projection'!C8-0.10)*30.42*'Revenue Projection'!C13)/'Revenue Projection'!C10))) | G7: Net rev − total opex
B8: Annual cash flow: | C8: ='Operating Math'!C22*12 | D8: =('Operating Math'!D22 - 'Lease Terms'!C15*'Lease Terms'!C19)*12 | E8: =(((('Revenue Projection'!C8-0.10)*30.42*'Revenue Projection'!C13)*'Revenue Projection'!C7 + (('Revenue Projection'!C8-0.10)*30.42*'Revenue Projection'!C13/'Revenue Projection'!C10)*'Revenue Projection'!C11)*(1-'Revenue Projection'!C12) - ('Lease Terms'!C15*1.07 + 'Operating Math'!D9 + 'Operating Math'!D10 + 'Operating Math'!D11 + 'Operating Math'!D14 + 'Operating Math'!D15 + 'Operating Math'!D16 + ('Operating Math'!D12 + 'Operating Math'!D13*1.15)*((('Revenue Projection'!C8-0.10)*30.42*'Revenue Projection'!C13)/'Revenue Projection'!C10)))*12 | G8: Monthly × 12
B9: Effective rent paid: | C9: ='Lease Terms'!C15 | D9: ='Lease Terms'!C15*(1+'Lease Terms'!C19) | E9: ='Lease Terms'!C15*1.07 | G9: Year-2 escalator applied
B10: Net revenue / mo: | C10: ='Revenue Projection'!C22 | D10: ='Revenue Projection'!C23 | E10: =((('Revenue Projection'!C8-0.10)*30.42*'Revenue Projection'!C13)*'Revenue Projection'!C7 + (('Revenue Projection'!C8-0.10)*30.42*'Revenue Projection'!C13/'Revenue Projection'!C10)*'Revenue Projection'!C11)*(1-'Revenue Projection'!C12) | G10: After platform commission
B11: Cash margin: | C11: =IFERROR('Operating Math'!C22/'Revenue Projection'!C22,0) | D11: =IFERROR(('Operating Math'!D22 - 'Lease Terms'!C15*'Lease Terms'!C19)/'Revenue Projection'!C23,0) | E11: =IFERROR((((('Revenue Projection'!C8-0.10)*30.42*'Revenue Projection'!C13)*'Revenue Projection'!C7 + (('Revenue Projection'!C8-0.10)*30.42*'Revenue Projection'!C13/'Revenue Projection'!C10)*'Revenue Projection'!C11)*(1-'Revenue Projection'!C12) - ('Lease Terms'!C15*1.07 + 'Operating Math'!D9 + 'Operating Math'!D10 + 'Operating Math'!D11 + 'Operating Math'!D14 + 'Operating Math'!D15 + 'Operating Math'!D16 + ('Operating Math'!D12 + 'Operating Math'!D13*1.15)*((('Revenue Projection'!C8-0.10)*30.42*'Revenue Projection'!C13)/'Revenue Projection'!C10)))/((('Revenue Projection'!C8-0.10)*30.42*'Revenue Projection'!C13)*'Revenue Projection'!C7 + (('Revenue Projection'!C8-0.10)*30.42*'Revenue Projection'!C13/'Revenue Projection'!C10)*'Revenue Projection'!C11)*(1-'Revenue Projection'!C12),0) | G11: Cash flow ÷ net revenue
B13: Verdict: | C13: =IF('Operating Math'!C22>300,"DEAL",IF('Operating Math'!C22>0,"MARGINAL","FAIL")) | D13: =IF(('Operating Math'!D22 - 'Lease Terms'!C15*'Lease Terms'!C19)>300,"DEAL",IF(('Operating Math'!D22 - 'Lease Terms'!C15*'Lease Terms'!C19)>0,"MARGINAL","FAIL")) | E13: =IF((((('Revenue Projection'!C8-0.10)*30.42*'Revenue Projection'!C13)*'Revenue Projection'!C7 + (('Revenue Projection'!C8-0.10)*30.42*'Revenue Projection'!C13/'Revenue Projection'!C10)*'Revenue Projection'!C11)*(1-'Revenue Projection'!C12) - ('Lease Terms'!C15*1.07 + 'Operating Math'!D9 + 'Operating Math'!D10 + 'Operating Math'!D11 + 'Operating Math'!D14 + 'Operating Math'!D15 + 'Operating Math'!D16 + ('Operating Math'!D12 + 'Operating Math'!D13*1.15)*((('Revenue Projection'!C8-0.10)*30.42*'Revenue Projection'!C13)/'Revenue Projection'!C10)))>300,"DEAL",IF((((('Revenue Projection'!C8-0.10)*30.42*'Revenue Projection'!C13)*'Revenue Projection'!C7 + (('Revenue Projection'!C8-0.10)*30.42*'Revenue Projection'!C13/'Revenue Projection'!C10)*'Revenue Projection'!C11)*(1-'Revenue Projection'!C12) - ('Lease Terms'!C15*1.07 + 'Operating Math'!D9 + 'Operating Math'!D10 + 'Operating Math'!D11 + 'Operating Math'!D14 + 'Operating Math'!D15 + 'Operating Math'!D16 + ('Operating Math'!D12 + 'Operating Math'!D13*1.15)*((('Revenue Projection'!C8-0.10)*30.42*'Revenue Projection'!C13)/'Revenue Projection'!C10)))>0,"MARGINAL","FAIL"))
A16: Stress test method: Year-2 column applies the renewal escalator from Lease Terms directly to rent, holds occupancy at stabilized. Worst-case applies a 7% rent shock, drops occupancy 10 percentage points, and adds 15% to supplies cost. If the worst-case column shows DEAL or MARGINAL — your underwriting has a real safety margin. If it shows FAIL — the deal works only if your assumptions hold perfectly. Most don't.
B21: OVERALL VERDICT
B22: =IF(OR('Lease Terms'!C22="No",'Lease Terms'!C23="No"),"PASS — illegal under current lease",IF(AND('Operating Math'!C22>0,(((('Revenue Projection'!C8-0.10)*30.42*'Revenue Projection'!C13)*'Revenue Projection'!C7 + (('Revenue Projection'!C8-0.10)*30.42*'Revenue Projection'!C13/'Revenue Projection'!C10)*'Revenue Projection'!C11)*(1-'Revenue Projection'!C12) - ('Lease Terms'!C15*1.07 + 'Operating Math'!D9 + 'Operating Math'!D10 + 'Operating Math'!D11 + 'Operating Math'!D14 + 'Operating Math'!D15 + 'Operating Math'!D16 + ('Operating Math'!D12 + 'Operating Math'!D13*1.15)*((('Revenue Projection'!C8-0.10)*30.42*'Revenue Projection'!C13)/'Revenue Projection'!C10)))>0),"DEAL",IF('Operating Math'!C22>0,"MARGINAL — survives Y1 but fails worst case","PASS — Y1 cash flow negative")))
B23: =IF((((('Revenue Projection'!C8-0.10)*30.42*'Revenue Projection'!C13)*'Revenue Projection'!C7 + (('Revenue Projection'!C8-0.10)*30.42*'Revenue Projection'!C13/'Revenue Projection'!C10)*'Revenue Projection'!C11)*(1-'Revenue Projection'!C12) - ('Lease Terms'!C15*1.07 + 'Operating Math'!D9 + 'Operating Math'!D10 + 'Operating Math'!D11 + 'Operating Math'!D14 + 'Operating Math'!D15 + 'Operating Math'!D16 + ('Operating Math'!D12 + 'Operating Math'!D13*1.15)*((('Revenue Projection'!C8-0.10)*30.42*'Revenue Projection'!C13)/'Revenue Projection'!C10)))>0,"Stress survives ($"&TEXT((((('Revenue Projection'!C8-0.10)*30.42*'Revenue Projection'!C13)*'Revenue Projection'!C7 + (('Revenue Projection'!C8-0.10)*30.42*'Revenue Projection'!C13/'Revenue Projection'!C10)*'Revenue Projection'!C11)*(1-'Revenue Projection'!C12) - ('Lease Terms'!C15*1.07 + 'Operating Math'!D9 + 'Operating Math'!D10 + 'Operating Math'!D11 + 'Operating Math'!D14 + 'Operating Math'!D15 + 'Operating Math'!D16 + ('Operating Math'!D12 + 'Operating Math'!D13*1.15)*((('Revenue Projection'!C8-0.10)*30.42*'Revenue Projection'!C13)/'Revenue Projection'!C10))),"#,##0")&"/mo worst)",IF((((('Revenue Projection'!C8-0.10)*30.42*'Revenue Projection'!C13)*'Revenue Projection'!C7 + (('Revenue Projection'!C8-0.10)*30.42*'Revenue Projection'!C13/'Revenue Projection'!C10)*'Revenue Projection'!C11)*(1-'Revenue Projection'!C12) - ('Lease Terms'!C15*1.07 + 'Operating Math'!D9 + 'Operating Math'!D10 + 'Operating Math'!D11 + 'Operating Math'!D14 + 'Operating Math'!D15 + 'Operating Math'!D16 + ('Operating Math'!D12 + 'Operating Math'!D13*1.15)*((('Revenue Projection'!C8-0.10)*30.42*'Revenue Projection'!C13)/'Revenue Projection'!C10)))>-200,"Stress marginal (−$"&TEXT(ABS((((('Revenue Projection'!C8-0.10)*30.42*'Revenue Projection'!C13)*'Revenue Projection'!C7 + (('Revenue Projection'!C8-0.10)*30.42*'Revenue Projection'!C13/'Revenue Projection'!C10)*'Revenue Projection'!C11)*(1-'Revenue Projection'!C12) - ('Lease Terms'!C15*1.07 + 'Operating Math'!D9 + 'Operating Math'!D10 + 'Operating Math'!D11 + 'Operating Math'!D14 + 'Operating Math'!D15 + 'Operating Math'!D16 + ('Operating Math'!D12 + 'Operating Math'!D13*1.15)*((('Revenue Projection'!C8-0.10)*30.42*'Revenue Projection'!C13)/'Revenue Projection'!C10)))),"#,##0")&"/mo)","Stress fails (−$"&TEXT(ABS((((('Revenue Projection'!C8-0.10)*30.42*'Revenue Projection'!C13)*'Revenue Projection'!C7 + (('Revenue Projection'!C8-0.10)*30.42*'Revenue Projection'!C13/'Revenue Projection'!C10)*'Revenue Projection'!C11)*(1-'Revenue Projection'!C12) - ('Lease Terms'!C15*1.07 + 'Operating Math'!D9 + 'Operating Math'!D10 + 'Operating Math'!D11 + 'Operating Math'!D14 + 'Operating Math'!D15 + 'Operating Math'!D16 + ('Operating Math'!D12 + 'Operating Math'!D13*1.15)*((('Revenue Projection'!C8-0.10)*30.42*'Revenue Projection'!C13)/'Revenue Projection'!C10)))),"#,##0")&"/mo)"))
A27: Questions? hello@thestrledger.com
A28: ACQ-003 · Stress Test

Sheet MTR Fallback
A2: =HYPERLINK("#'Stress Test'!A1", "← BACK") | D2: MTR FALLBACK | J2: =HYPERLINK("#'Landlord Pitch'!A1", "NEXT →")
A4: Plan B: if the STR play fails, can mid-term-rental (corporate housing, travel nurses, insurance displacement) cover the rent? Real arbitrage operators have an exit. Gurus don't.
A6: MTR INPUTS (paste from Furnished Finder)
B7: MTR rent / mo ($): | C7: 3400 | E7: 30+ day stays. Furnished Finder 'rent' field.
B8: MTR occupancy (%): | C8: 0.9 | E8: Once contracted, ~90% on signed term
B9: Utilities ($/mo): | C9: 240 | E9: Sometimes pass-through to MTR tenant
B10: Insurance ($/mo): | C10: 85
B11: Minor cleaning ($/mo): | C11: 90 | E11: Quarterly turnover ÷ 3
A13: MTR CASH FLOW
B14: Net MTR revenue / mo: | C14: =C7*C8
B15: MTR cash flow / mo: | C15: =C14-'Lease Terms'!C15-C9-C10-C11
B16: =IF(C15>0,"MTR covers rent: $"&TEXT(C15,"#,##0")&"/mo cushion",IF(C15>-300,"MTR shortfall: $"&TEXT(ABS(C15),"#,##0")&"/mo (manageable)","MTR cannot cover rent: $"&TEXT(ABS(C15),"#,##0")&"/mo gap"))
A19: Mid-term rentals (30+ days) skip Airbnb's platform fee, skip per-stay cleaning, and stabilize at ~90% occupancy once a tenant signs. Travel-nurse contracts run 13 weeks; corporate housing 60-180 days; insurance displacement (people whose homes burned/flooded) often 6+ months. Pull MTR rents from Furnished Finder for your zip code. If MTR covers rent + a small cushion — your downside is bounded. If MTR shortfall is large — DO NOT sign this lease. The escape hatch isn't there.
A26: Questions? hello@thestrledger.com
A27: ACQ-003 · MTR Fallback

Sheet Landlord Pitch
A1: =HYPERLINK("#'Start'!A1", "← BACK")
B3: [ YOUR LOGO HERE ]
B6: Master-Lease Proposal
B7: ="Date prepared: "&TEXT(TODAY(),"mmmm d, yyyy")
B9: PROPOSED TENANT
B10: Operator: | C10: Apex Stay Co.
B11: Entity / LLC: | C11: Apex Stay Holdings LLC
B12: Contact: | C12: Daniel Harrison · daniel@apexstay.co · (720) 555-0188
B13: Business: | C13: Professionally managed mid-term + short-term housing operator.
B15: PROPERTY
B16: Address: | C16: ='Lease Terms'!C7
B17: Unit type: | C17: ='Lease Terms'!C9&" · "&'Lease Terms'!C10&" bd / "&'Lease Terms'!C11&" ba"
B19: PROPOSED TERMS
B20: Monthly rent: | C20: ='Lease Terms'!C15
B21: Security deposit: | C21: ='Lease Terms'!C16
B22: Lease term: | C22: ='Lease Terms'!C17&" months"
B23: Start date: | C23: ='Lease Terms'!C18
B24: Renewal escalator: | C24: ='Lease Terms'!C19
B25: Tenant pays: | C25: Utilities · internet · insurance · cleaning · repairs <$200
B26: Landlord pays: | C26: Property tax · HOA · structural repairs · major systems
B28: WHY THIS WORKS FOR YOU
B29: + Guaranteed rent — paid on the 1st whether or not the unit is booked. You collect either way.
B30: + Zero tenant turnover — one professional operator, not a revolving door of renters.
B31: + Premium maintenance — we treat this unit like our reputation depends on it (because it does).
B32: + Tenant carries $1M liability + STR rider — your asset is over-insured, not under.
B33: + Indemnification clause — guests' actions are our liability, never yours.
B35: REFERENCES + PRIOR HISTORY
B36: Reference 1: | C36: James Whitman · Pearl St Properties · (303) 555-0119
B37: Reference 2: | C37: Anita Reyes · Highland Holdings · (720) 555-0177
B38: Prior history: | C38: 3 prior master-lease units in Denver metro since 2024 — zero late payments, all renewed.
B41: SIGNATURES
B43: Tenant signature: | F43: Date:
B45: Landlord signature: | F45: Date:
B48: This proposal is non-binding and subject to a formal master-lease agreement. Both parties should consult an attorney before signing.
