Workbook

Sheet Start
A2: The STR Ledger
A4: 1031 Exchange Tracker
A5: Two deadlines. Zero forgiveness. Don't miss them.
A6: =IF('Settings'!B11="","→ Enter sale date in Settings to start the countdown.","→ ID deadline in "&'Relinquished Property'!B16&" days · Closing deadline in "&'Relinquished Property'!B17&" days")
A7: ACQ-011 · v2.3 · BLANK
A10: 45-DAY IDENTIFICATION | G10: 180-DAY CLOSING
A11: ='Relinquished Property'!B16 | G11: ='Relinquished Property'!B17
A14: ='Relinquished Property'!B14 | G14: ='Relinquished Property'!B15
A15: Identify replacement properties by this date | G15: Close on replacement(s) by this date
A17: ⚠ 1031 EXCHANGE RULES ARE STRICT AND UNFORGIVING. This workbook is recordkeeping support only. Your Qualified Intermediary (QI) and CPA execute the exchange — not this spreadsheet. The exchange is VOID without a QI in place before sale closing. Miss the 45-day ID or 180-day closing window by ONE DAY and the entire deferral fails — you owe full tax on the gain.
A21: HOW TO USE
A22: ① Settings — enter sale date, QI info (REQUIRED), CPA contact.
A23: ② Relinquished Property — sale price, basis, depreciation -> realized gain.
A24: ③ Identification — pick a rule (3-property / 200% / 95%), list candidates by Day 45.
A25: ④ Replacement + Closing — log each closing, boot received, deferred gain.
A26: ⑤ Carryover Basis — read the new property's depreciation basis for next year.
A29: =HYPERLINK("#'Relinquished Property'!A5", "→ GO TO RELINQUISHED PROPERTY →")
A34: =HYPERLINK("#'Identification'!A1", "Identification") | D34: =HYPERLINK("#'Replacement + Closing'!A1", "Replacement + Closing") | G34: =HYPERLINK("#'Carryover Basis'!A1", "Carryover Basis") | J34: =HYPERLINK("#'Settings'!A1", "Settings")
A38: Questions? hello@thestrledger.com
A39: ACQ-011 · v2.3 · Free updates forever

Sheet Relinquished Property
A2: =HYPERLINK("#'Start'!A1", "← BACK") | D2: RELINQUISHED PROPERTY | J2: =HYPERLINK("#'Identification'!A1", "NEXT →")
A4: Sale of the property you're exchanging out of. Sale date drives both deadlines.
A5: PROPERTY + SALE
A6: Property name:
A7: Address:
A8: Sale date: | B8: ='Settings'!B11
A9: Sale price:
A10: Selling expenses (commissions, closing):
A11: Net sale proceeds: | B11: =B9-B10
A13: Original cost basis:
A14: 45-day ID deadline: | B14: =B8+45
A15: 180-day closing deadline: | B15: =B8+180
A16: Days remaining — ID deadline: | B16: =B14-TODAY()
A17: Days remaining — closing deadline: | B17: =B15-TODAY()
A19: BASIS + REALIZED GAIN
A20: Accumulated depreciation:
A21: Adjusted basis: | B21: =B13-B20
A22: Realized gain (sale proceeds − adjusted basis): | B22: =B11-B21
A23: Depreciation recapture portion (taxed up to 25%): | B23: =MIN(B20,B22)
A24: Capital gain portion (taxed up to 20%+NIIT): | B24: =MAX(B22-B23,0)
A26: ⓘ In a successful 1031 exchange, this realized gain is DEFERRED — you don't pay tax now. But the gain still exists; it carries into the new property's basis. The IRS gets paid eventually.

Sheet Identification
A2: =HYPERLINK("#'Relinquished Property'!A1", "← BACK") | D2: IDENTIFICATION | J2: =HYPERLINK("#'Replacement + Closing'!A1", "NEXT →")
A4: List candidate replacements by Day 45. Pick ONE rule: 3-property, 200%, or 95%.
A5: Rule: | C5: =IF(B5="3-property rule","Up to 3 properties; value doesn't matter.",IF(B5="200% rule","Any number; total FMV ≤ 200% of relinquished sale price.",IF(B5="95% rule","Any number; must close on ≥95% of identified value.","")))
A7: # | B7: Property name | C7: Address | D7: Asking price | E7: Status
A8: 1
A9: 2
A10: 3
A11: 4
A12: 5
A13: 6
A14: 7
A15: 8
A17: AGGREGATES + RULE CHECK
A18: Count of identified properties: | B18: =COUNTA(B8:B15)
A19: Aggregate asking value: | B19: =SUM(D8:D15)
A20: Closed value (status=Closed): | B20: =SUMIFS(D8:D15,E8:E15,"Closed")
A21: Relinquished sale price (reference): | B21: ='Relinquished Property'!B9
A22: 200% cap (2 × relinquished sale price): | B22: =B21*2
A23: 95% threshold (of aggregate identified): | B23: =B19*0.95
A25: Rule compliance: | B25: =IF(B5="3-property rule",IF(B18<=3,"✓ OK — within 3-property limit","✗ OVER — reduce to 3 or switch rule"),IF(B5="200% rule",IF(B19<=B22,"✓ OK — within 200% cap","✗ OVER — aggregate exceeds 200% cap"),IF(B5="95% rule",IF(B20>=B23,"✓ OK — closed value meets 95% threshold","✗ PENDING — must close on ≥95% of identified"),"Pick a rule above")))
A27: ⓘ Identification must be in writing, signed, and delivered to your QI by Day 45. Verbal identification doesn't count. After Day 45, you can ONLY close on identified properties — no swaps, no substitutions.

Sheet Replacement + Closing
A2: =HYPERLINK("#'Identification'!A1", "← BACK") | D2: REPLACEMENT + CLOSING | J2: =HYPERLINK("#'Carryover Basis'!A1", "NEXT →")
A4: Closings on selected replacement(s). Boot received = recognized gain; the rest is deferred.
A5: REPLACEMENT PROPERTY (combined if multiple)
A6: Selected replacement(s):
A7: Total purchase price:
A8: Closing date:
A9: Closing costs (paid by buyer):
A10: Additional cash paid in (boot paid):
A11: Mortgage debt assumed on replacement:
A12: Mortgage debt relieved on relinquished:
A14: BOOT + DEFERRED GAIN
A15: Net debt relief (relinquished mortgage − assumed mortgage): | B15: =MAX(B12-B11,0)
A16: Cash boot received (proceeds not reinvested): | B16: =MAX('Relinquished Property'!B11-B7,0)
A17: Total boot received (cash + debt relief): | B17: =B15+B16
A18: Realized gain (from Relinquished tab): | B18: ='Relinquished Property'!B22
A19: Recognized gain (= total boot, capped at realized): | B19: =MIN(B17,B18)
A20: Recapture portion of recognized gain (taxed first, up to 25%): | B20: =MIN(B19,'Relinquished Property'!B23)
A21: Capital-gain portion of recognized gain (up to 20%+NIIT): | B21: =MAX(B19-B20,0)
A22: DEFERRED GAIN (rolls into new basis): | B22: =B18-B19
A24: EST. TAX ON RECOGNIZED GAIN (informational)
A25: Recapture tax (25% × recapture portion): | B25: =ROUND(B20*0.25,0)
A26: Capital gain tax (20% × capital gain portion): | B26: =ROUND(B21*0.20,0)
A27: NIIT (3.8% × capital gain portion, if AGI threshold): | B27: =ROUND(B21*0.038,0)
A28: Total est. federal tax due on boot: | B28: =B25+B26+B27
A30: ⓘ Boot = anything you receive that isn't like-kind real estate. Cash, debt relief, personal property. Recapture is taxed FIRST (up to 25%), then capital gain (up to 20% + 3.8% NIIT). Your CPA confirms the tax — these are estimates only.

Sheet Carryover Basis
A2: =HYPERLINK("#'Replacement + Closing'!A1", "← BACK") | D2: CARRYOVER BASIS | J2: =HYPERLINK("#'Settings'!A1", "NEXT →")
A4: New property's tax basis carries from the relinquished property — not its purchase price.
A5: CARRYOVER BASIS BUILD-UP
A6: Relinquished adjusted basis: | B6: ='Relinquished Property'!B21
A7: + Boot paid (additional cash in): | B7: ='Replacement + Closing'!B10
A8: + Closing costs added to basis: | B8: ='Replacement + Closing'!B9
A9: + Net new debt (assumed − relieved): | B9: =MAX('Replacement + Closing'!B11-'Replacement + Closing'!B12,0)
A10: − Boot received (cash + debt relief): | B10: ='Replacement + Closing'!B17
A11: + Recognized gain (boot recognized now): | B11: ='Replacement + Closing'!B19
A12: =NEW PROPERTY TAX BASIS (for depreciation): | B12: =B6+B7+B8+B9-B10+B11
A14: HOLDING PERIOD
A15: Relinquished property acquired:
A16: Relinquished sale date: | B16: ='Relinquished Property'!B8
A17: Replacement closing date: | B17: ='Replacement + Closing'!B8
A18: Carryover holding period start (= acquired date above): | B18: =B15
A19: Years held (combined, as of replacement close): | B19: =ROUND((B17-B15)/365.25,1)
A21: DEPRECIATION HANDOFF (for next year's P&L)
A22: Depreciable building portion (typical 80%):
A23: Building basis subject to depreciation: | B23: =B12*B22
A24: MACRS recovery (residential rental — 27.5 yr): | B24: =ROUND(B23/27.5,0)
A26: ⓘ Your new property's depreciation basis is NOT what you paid — it's the relinquished basis plus adjustments. This is the IRS price for deferring the gain. Confirm with your CPA before filing Form 4562 next year.

Sheet Settings
A2: =HYPERLINK("#'Carryover Basis'!A1", "← BACK") | D2: SETTINGS
A4: Active year, sale date (drives countdowns), and your QI + CPA contacts.
A5: Active tax year: | B5: 2026
A6: Filing status: | B6: MFJ
A7: Qualified Intermediary (QI) name:
A8: QI contact (phone / email):
A9: CPA name + contact:
A10: CPA email:
A11: Sale date (drives all countdowns):
A13: ⚠ REQUIRED: A Qualified Intermediary (QI) must be in place BEFORE the relinquished sale closes. If you receive sale proceeds directly — even for one day — the exchange is VOID and the entire gain is taxable. The QI holds proceeds in escrow and transfers them to the replacement closing. This workbook tracks the timeline; the QI executes the exchange.
A17: Disclaimer: This workbook is recordkeeping and timeline support for a 1031 like-kind exchange under IRC §1031. It is not legal, tax, or financial advice. The IRS requires strict adherence to the 45-day identification window, the 180-day closing window, the QI safe harbor (Treas. Reg. §1.1031(k)-1), and the like-kind requirement (real estate held for investment or productive use only since the 2017 TCJA). Your QI and CPA execute the exchange. Confirm every figure with them before signing closing documents.
A23: Questions? hello@thestrledger.com
A24: ACQ-011 · v2.3 · Free updates forever
