Workbook

Sheet Start
A2: The STR Ledger
A4: Rehab Budget + ROI
A5: Track every line. Project the lift. Know your payback.
A7: ACQ-006 · v1.0 · BLANK
A10: PROJECT AT A GLANCE
A11: BUDGET (EST) | D11: SPENT (ACTUAL) | G11: VARIANCE % | J11: 5-YR ROI
A12: ='Cost Allocation'!C26 | D12: ='Cost Allocation'!D26 | G12: =IFERROR(('Cost Allocation'!D26-'Cost Allocation'!C26)/'Cost Allocation'!C26,0) | J12: ='ROI Projection'!C20
A15: Log every line item — estimate vs actual, contractor, payment status, capex/repair tag. The Cost Allocation tab rolls it up by category and shows where dollars went. ROI Projection turns rehab spend into a year-1 revenue lift and a payback-period number you can defend.
A19: =HYPERLINK("#'Budget Detail'!A1", "Budget Detail") | D19: =HYPERLINK("#'Cost Allocation'!A1", "Cost Allocation") | G19: =HYPERLINK("#'ROI Projection'!A1", "ROI Projection") | J19: =HYPERLINK("#'Settings'!A1", "Settings")
A23: =HYPERLINK("#'Budget Detail'!B7", "→ ADD A REHAB LINE")
A27: 1) Set property + dates on Settings. 2) Add lines on Budget Detail (estimate first; actual once paid). 3) Watch Variance % — red >+15% means you're over. 4) Cost Allocation auto-rolls by category, splits Capex/Repair for tax.
A32: Capex vs Repair classification matters for tax. Pair this with Cost Segregation DIY (TAX-010) to claim accelerated depreciation.
A35: Questions? hello@thestrledger.com
A36: ACQ-006 · v1.0 · BLANK · Free updates forever

Sheet Budget Detail
A2: =HYPERLINK("#'Start'!A1", "← BACK") | D2: BUDGET DETAIL | J2: =HYPERLINK("#'Cost Allocation'!A1", "NEXT →")
A4: Log every rehab line. Variance is auto-calculated. Capex/Repair drives tax treatment downstream.
A5: Line # | B5: Category | C5: Description | D5: Estimate | E5: Actual | F5: Variance | G5: Var % | H5: Contractor | I5: Status | J5: Capex/Repair | K5: Notes
A6: 1 | F6: =IF(AND(ISNUMBER(D6),ISNUMBER(E6)),E6-D6,"") | G6: =IF(AND(ISNUMBER(D6),ISNUMBER(E6),D6<>0),(E6-D6)/D6,"")
A7: 2 | F7: =IF(AND(ISNUMBER(D7),ISNUMBER(E7)),E7-D7,"") | G7: =IF(AND(ISNUMBER(D7),ISNUMBER(E7),D7<>0),(E7-D7)/D7,"")
A8: 3 | F8: =IF(AND(ISNUMBER(D8),ISNUMBER(E8)),E8-D8,"") | G8: =IF(AND(ISNUMBER(D8),ISNUMBER(E8),D8<>0),(E8-D8)/D8,"")
A9: 4 | F9: =IF(AND(ISNUMBER(D9),ISNUMBER(E9)),E9-D9,"") | G9: =IF(AND(ISNUMBER(D9),ISNUMBER(E9),D9<>0),(E9-D9)/D9,"")
A10: 5 | F10: =IF(AND(ISNUMBER(D10),ISNUMBER(E10)),E10-D10,"") | G10: =IF(AND(ISNUMBER(D10),ISNUMBER(E10),D10<>0),(E10-D10)/D10,"")
A11: 6 | F11: =IF(AND(ISNUMBER(D11),ISNUMBER(E11)),E11-D11,"") | G11: =IF(AND(ISNUMBER(D11),ISNUMBER(E11),D11<>0),(E11-D11)/D11,"")
A12: 7 | F12: =IF(AND(ISNUMBER(D12),ISNUMBER(E12)),E12-D12,"") | G12: =IF(AND(ISNUMBER(D12),ISNUMBER(E12),D12<>0),(E12-D12)/D12,"")
A13: 8 | F13: =IF(AND(ISNUMBER(D13),ISNUMBER(E13)),E13-D13,"") | G13: =IF(AND(ISNUMBER(D13),ISNUMBER(E13),D13<>0),(E13-D13)/D13,"")
A14: 9 | F14: =IF(AND(ISNUMBER(D14),ISNUMBER(E14)),E14-D14,"") | G14: =IF(AND(ISNUMBER(D14),ISNUMBER(E14),D14<>0),(E14-D14)/D14,"")
A15: 10 | F15: =IF(AND(ISNUMBER(D15),ISNUMBER(E15)),E15-D15,"") | G15: =IF(AND(ISNUMBER(D15),ISNUMBER(E15),D15<>0),(E15-D15)/D15,"")
A16: 11 | F16: =IF(AND(ISNUMBER(D16),ISNUMBER(E16)),E16-D16,"") | G16: =IF(AND(ISNUMBER(D16),ISNUMBER(E16),D16<>0),(E16-D16)/D16,"")
A17: 12 | F17: =IF(AND(ISNUMBER(D17),ISNUMBER(E17)),E17-D17,"") | G17: =IF(AND(ISNUMBER(D17),ISNUMBER(E17),D17<>0),(E17-D17)/D17,"")
... A105: 100 | F105: =IF(AND(ISNUMBER(D105),ISNUMBER(E105)),E105-D105,"") | G105: =IF(AND(ISNUMBER(D105),ISNUMBER(E105),D105<>0),(E105-D105)/D105,"")
C106: TOTALS | D106: =SUM(D6:D105) | E106: =SUM(E6:E105) | F106: =SUM(F6:F105) | G106: =IFERROR((E106-D106)/D106,0)

Sheet Cost Allocation
A2: =HYPERLINK("#'Budget Detail'!A1", "← BACK") | D2: COST ALLOCATION | J2: =HYPERLINK("#'ROI Projection'!A1", "NEXT →")
A4: By-category roll-up · Capex vs Repair split · Spend by category pie
B6: Category | C6: Estimate | D6: Actual | E6: Variance | F6: Var % | H6: Classification | I6: Estimate | J6: Actual
B7: Demolition | C7: =SUMIFS('Budget Detail'!D6:D105,'Budget Detail'!B6:B105,B7) | D7: =SUMIFS('Budget Detail'!E6:E105,'Budget Detail'!B6:B105,B7) | E7: =D7-C7 | F7: =IFERROR((D7-C7)/C7,0) | H7: Capex | I7: =SUMIFS('Budget Detail'!D6:D105,'Budget Detail'!J6:J105,H7) | J7: =SUMIFS('Budget Detail'!E6:E105,'Budget Detail'!J6:J105,H7)
B8: Plumbing | C8: =SUMIFS('Budget Detail'!D6:D105,'Budget Detail'!B6:B105,B8) | D8: =SUMIFS('Budget Detail'!E6:E105,'Budget Detail'!B6:B105,B8) | E8: =D8-C8 | F8: =IFERROR((D8-C8)/C8,0) | H8: Repair | I8: =SUMIFS('Budget Detail'!D6:D105,'Budget Detail'!J6:J105,H8) | J8: =SUMIFS('Budget Detail'!E6:E105,'Budget Detail'!J6:J105,H8)
B9: Electrical | C9: =SUMIFS('Budget Detail'!D6:D105,'Budget Detail'!B6:B105,B9) | D9: =SUMIFS('Budget Detail'!E6:E105,'Budget Detail'!B6:B105,B9) | E9: =D9-C9 | F9: =IFERROR((D9-C9)/C9,0) | H9: TOTAL | I9: =SUM(I7:I8) | J9: =SUM(J7:J8)
B10: HVAC | C10: =SUMIFS('Budget Detail'!D6:D105,'Budget Detail'!B6:B105,B10) | D10: =SUMIFS('Budget Detail'!E6:E105,'Budget Detail'!B6:B105,B10) | E10: =D10-C10 | F10: =IFERROR((D10-C10)/C10,0)
B11: Drywall | C11: =SUMIFS('Budget Detail'!D6:D105,'Budget Detail'!B6:B105,B11) | D11: =SUMIFS('Budget Detail'!E6:E105,'Budget Detail'!B6:B105,B11) | E11: =D11-C11 | F11: =IFERROR((D11-C11)/C11,0) | H11: Capex = depreciated over time (typically 27.5 yr res / 5-15 yr via cost seg). Repair = deductible in the year incurred. Hand this split to your CPA.
B12: Flooring | C12: =SUMIFS('Budget Detail'!D6:D105,'Budget Detail'!B6:B105,B12) | D12: =SUMIFS('Budget Detail'!E6:E105,'Budget Detail'!B6:B105,B12) | E12: =D12-C12 | F12: =IFERROR((D12-C12)/C12,0)
B13: Cabinets | C13: =SUMIFS('Budget Detail'!D6:D105,'Budget Detail'!B6:B105,B13) | D13: =SUMIFS('Budget Detail'!E6:E105,'Budget Detail'!B6:B105,B13) | E13: =D13-C13 | F13: =IFERROR((D13-C13)/C13,0)
B14: Countertops | C14: =SUMIFS('Budget Detail'!D6:D105,'Budget Detail'!B6:B105,B14) | D14: =SUMIFS('Budget Detail'!E6:E105,'Budget Detail'!B6:B105,B14) | E14: =D14-C14 | F14: =IFERROR((D14-C14)/C14,0)
B15: Appliances | C15: =SUMIFS('Budget Detail'!D6:D105,'Budget Detail'!B6:B105,B15) | D15: =SUMIFS('Budget Detail'!E6:E105,'Budget Detail'!B6:B105,B15) | E15: =D15-C15 | F15: =IFERROR((D15-C15)/C15,0)
B16: Painting | C16: =SUMIFS('Budget Detail'!D6:D105,'Budget Detail'!B6:B105,B16) | D16: =SUMIFS('Budget Detail'!E6:E105,'Budget Detail'!B6:B105,B16) | E16: =D16-C16 | F16: =IFERROR((D16-C16)/C16,0)
B17: Fixtures | C17: =SUMIFS('Budget Detail'!D6:D105,'Budget Detail'!B6:B105,B17) | D17: =SUMIFS('Budget Detail'!E6:E105,'Budget Detail'!B6:B105,B17) | E17: =D17-C17 | F17: =IFERROR((D17-C17)/C17,0)
B18: Furniture | C18: =SUMIFS('Budget Detail'!D6:D105,'Budget Detail'!B6:B105,B18) | D18: =SUMIFS('Budget Detail'!E6:E105,'Budget Detail'!B6:B105,B18) | E18: =D18-C18 | F18: =IFERROR((D18-C18)/C18,0)
B19: Decor | C19: =SUMIFS('Budget Detail'!D6:D105,'Budget Detail'!B6:B105,B19) | D19: =SUMIFS('Budget Detail'!E6:E105,'Budget Detail'!B6:B105,B19) | E19: =D19-C19 | F19: =IFERROR((D19-C19)/C19,0)
B20: Outdoor | C20: =SUMIFS('Budget Detail'!D6:D105,'Budget Detail'!B6:B105,B20) | D20: =SUMIFS('Budget Detail'!E6:E105,'Budget Detail'!B6:B105,B20) | E20: =D20-C20 | F20: =IFERROR((D20-C20)/C20,0)
B21: Permits | C21: =SUMIFS('Budget Detail'!D6:D105,'Budget Detail'!B6:B105,B21) | D21: =SUMIFS('Budget Detail'!E6:E105,'Budget Detail'!B6:B105,B21) | E21: =D21-C21 | F21: =IFERROR((D21-C21)/C21,0)
B22: Misc | C22: =SUMIFS('Budget Detail'!D6:D105,'Budget Detail'!B6:B105,B22) | D22: =SUMIFS('Budget Detail'!E6:E105,'Budget Detail'!B6:B105,B22) | E22: =D22-C22 | F22: =IFERROR((D22-C22)/C22,0)
B26: TOTAL | C26: =SUM(C7:C22) | D26: =SUM(D7:D22) | E26: =SUM(E7:E22) | F26: =IFERROR((D26-C26)/C26,0)

Sheet ROI Projection
A2: =HYPERLINK("#'Cost Allocation'!A1", "← BACK") | D2: ROI PROJECTION | J2: =HYPERLINK("#'Settings'!A1", "NEXT →")
A4: Pre vs post-rehab nightly rate · year-1 lift · payback period · 5-yr cumulative
A6: REVENUE INPUTS
B7: Pre-rehab nightly rate ($): | E7: ADR before this rehab — your baseline
B8: Post-rehab nightly rate ($): | E8: Defensible projection — pull from comp set
B9: Occupancy lift (% points): | E9: Extra occupancy nightly — e.g., +8% = 8 pts more
B10: Post-rehab occupancy (%): | E10: Used for 5-yr cumulative lift forecast
A12: OUTPUTS
B13: Total rehab spend (actual): | C13: ='Cost Allocation'!D26
B14: Year-1 revenue lift: | C14: =(C8-C7)*365*C9
B15: Payback (months): | C15: =IFERROR(('Cost Allocation'!D26)/(((C8-C7)*365*C9)/12),0)
B16: Year-1 lift (alt: rate × occ delta): | C16: =(C8*C10-C7*(C10-C9))*365
A18: 5-YEAR PROJECTION
B19: 5-year cumulative lift: | C19: =C14*5
B20: 5-year ROI on rehab: | C20: =IFERROR((C14*5)/'Cost Allocation'!D26,0)
B21: Net 5-yr profit (lift − spend): | C21: =C14*5-'Cost Allocation'!D26
A24: Why this matters: rehab dollars are an investment, not an expense. If your post-rehab ADR + occupancy lift can't pay back the spend in 60 months, the rehab is over-scoped. Right-size before you sign contractor estimates.
A30: Questions? hello@thestrledger.com
A31: ACQ-006 · ROI Projection

Sheet Settings
A2: =HYPERLINK("#'ROI Projection'!A1", "← BACK") | D2: SETTINGS
A4: Property identity · rehab dates · contingency · year-end archive
A5: Property name:
A6: Active rehab year: | B6: 2026 | C6: Bump in January for the next rehab. Drives any year-filtered logic.
A7: Rehab start date:
A9: Rehab end date (target):
A11: Contingency %: | B11: 0.15 | C11: Default 15%. Reserve held back for surprises.
A13: Contingency $ (auto): | B13: ='Cost Allocation'!C26*B11
A16: Year-end Archive
A17: Each January, copy the YTD totals from the Cost Allocation tab into the row for the closing year, then clear Budget Detail for the next rehab project.
A18: Year | B18: Property | C18: Total $ | D18: 5-yr ROI % | E18: Notes
A19: 2024
A20: 2025
A21: 2026
A22: 2027
A23: 2028
A24: 2029
A25: 2030
A29: Questions? hello@thestrledger.com
A30: ACQ-006 · Settings
