Workbook

Sheet Start
A2: The STR Ledger
A4: AirDNA Data Integrator
A5: Translate "AirDNA says $87K" into what your deal will actually do.
A7: ACQ-005 · v1.0 · BLANK
A10: WHAT THIS DOES
A11: Paste AirDNA Rentalizer output (annual + monthly revenue, occupancy, ADR, RevPAR, market score). The Quality Adjuster lets you mark each dimension above or below market — pro photos, hot tub, decor, review history, pricing strategy. Output: an adjusted revenue projection and a mini-underwriting verdict (NOI, CoC, DSCR) tuned to YOUR property, not the market median.
A17: HOW TO USE — 3 STEPS
A18: 1. Open AirDNA Rentalizer for your target address. Export CSV (or copy values).
A19: 2. Paste annual + monthly figures into the AirDNA Paste tab.
A20: 3. Mark your property quality on the Quality Adjuster tab — read the verdict.
A24: =HYPERLINK("#'AirDNA Paste'!A1", "1. Paste AirDNA") | D24: =HYPERLINK("#'Quality Adjuster'!A1", "2. Quality Adjuster") | G24: =HYPERLINK("#'Adjusted Underwriting'!A1", "3. Adjusted Underwriting") | J24: =HYPERLINK("#'Settings'!A1", "Settings")
A29: ⚠ IMPORTANT — AIRDNA TERMS OF SERVICE
A30: AirDNA is a paid product. This workbook does NOT scrape, automate, or download their data — that violates their Terms of Service. You must export or copy the data manually from your authorized AirDNA account. This template only translates what you've already paid for into your underwriting model.
A36: Questions? hello@thestrledger.com
A37: ACQ-005 · v1.0 · BLANK · Free updates forever

Sheet AirDNA Paste
A2: =HYPERLINK("#'Start'!A1", "← BACK") | D2: AIRDNA PASTE | J2: =HYPERLINK("#'Quality Adjuster'!A1", "NEXT →")
A4: ="Source data as of: "&TEXT(Settings!B7,"yyyy-mm-dd")&" · Market: "&Settings!B9
A6: ANNUAL SUMMARY (paste from AirDNA Rentalizer)
B7: Annual revenue ($): | E7: AirDNA Rentalizer 'Projected Revenue'
B8: Occupancy (%): | E8: AirDNA Rentalizer 'Projected Occupancy'
B9: ADR ($): | E9: AirDNA Rentalizer 'Projected ADR'
B10: RevPAR ($): | E10: Revenue per available night
B11: Market Score (0-100): | E11: AirDNA Market Score (higher = stronger)
B12: Comparables count: | E12: How many comps AirDNA used
B13: Source listing URL: | E13: Optional — paste AirDNA Rentalizer URL
A15: SANITY CHECK
B16: Implied annual rev (ADR × Occ × 365): | C16: =IFERROR(C9*C8*365,0)
B17: Variance vs AirDNA annual: | C17: =IFERROR((C7-C16)/C16,0)
A19: MONTHLY REVENUE BREAKDOWN
B20: Month | C20: AirDNA Revenue | E20: % of Year
B21: January | E21: =IFERROR(C21/SUM($C$21:$C$32),0)
B22: February | E22: =IFERROR(C22/SUM($C$21:$C$32),0)
B23: March | E23: =IFERROR(C23/SUM($C$21:$C$32),0)
B24: April | E24: =IFERROR(C24/SUM($C$21:$C$32),0)
B25: May | E25: =IFERROR(C25/SUM($C$21:$C$32),0)
B26: June | E26: =IFERROR(C26/SUM($C$21:$C$32),0)
B27: July | E27: =IFERROR(C27/SUM($C$21:$C$32),0)
B28: August | E28: =IFERROR(C28/SUM($C$21:$C$32),0)
B29: September | E29: =IFERROR(C29/SUM($C$21:$C$32),0)
B30: October | E30: =IFERROR(C30/SUM($C$21:$C$32),0)
B31: November | E31: =IFERROR(C31/SUM($C$21:$C$32),0)
B32: December | E32: =IFERROR(C32/SUM($C$21:$C$32),0)
B33: Total monthly: | C33: =SUM(C21:C32) | E33: =IFERROR((C33-C7)/C7,0)
A37: Questions? hello@thestrledger.com
A38: ACQ-005 · AirDNA Paste

Sheet Quality Adjuster
A2: =HYPERLINK("#'AirDNA Paste'!A1", "← BACK") | D2: QUALITY ADJUSTER | J2: =HYPERLINK("#'Adjusted Underwriting'!A1", "NEXT →")
A4: AirDNA reports the median listing in your market. Your property is NOT the median. Adjust each dimension below — 1.00 = market average, <1.00 = below market, >1.00 = above.
A6: QUALITY MULTIPLIERS (1.00 = market median)
B7: Dimension | C7: Min | D7: Your Mult | E7: Max | F7: Justification / notes
B8: Listing photos quality | C8: 0.85 | E8: 1.2
B9: Amenities (hot tub / pool / view) | C9: 0.9 | E9: 1.3
B10: Decor / staging | C10: 0.85 | E10: 1.15
B11: Reviews target (10+ at 4.8★) | C11: 0.7 | E11: 1
B12: Pricing strategy | C12: 0.95 | E12: 1.1
B14: TOTAL QUALITY MULTIPLIER: | D14: =PRODUCT(D8:D12)
B15: × Conservative-mode mult (Settings): | D15: =Settings!B11
B16: EFFECTIVE MULTIPLIER: | D16: =D14*D15
A18: INTERPRETATION
B19: =IF(D16>=1.10,"Above-market property — your photos, amenities, or pricing strategy should outperform the AirDNA median. Reasonable to expect "&TEXT(D16-1,"0.0%")&" lift.",IF(D16>=0.95,"Roughly market — you should land near AirDNAs median projection.","Below-market property — expect "&TEXT(1-D16,"0.0%")&" haircut. Consider whether reviews ramp + decor refresh can pull you back to neutral by Year 2."))
A26: Questions? hello@thestrledger.com
A27: ACQ-005 · Quality Adjuster

Sheet Adjusted Underwriting
A2: =HYPERLINK("#'Quality Adjuster'!A1", "← BACK") | D2: ADJUSTED UNDERWRITING | J2: =HYPERLINK("#'Settings'!A1", "NEXT →")
A4: AirDNA projection × your effective quality multiplier = adjusted underwriting. Compare AirDNA-as-paid against what you should ACTUALLY underwrite.
A6: REVENUE / OCCUPANCY / ADR — AirDNA vs Adjusted
B7: Metric | C7: AirDNA | D7: × Mult | E7: Adjusted
B8: Annual revenue: | C8: ='AirDNA Paste'!C7 | D8: ='Quality Adjuster'!D16 | E8: =C8*D8
B9: Occupancy: | C9: ='AirDNA Paste'!C8 | D9: ='Quality Adjuster'!D16 | E9: =C9*D9
B10: ADR: | C10: ='AirDNA Paste'!C9 | D10: ='Quality Adjuster'!D16 | E10: =C10*D10
B11: RevPAR: | C11: ='AirDNA Paste'!C10 | D11: ='Quality Adjuster'!D16 | E11: =C11*D11
B12: Booked nights: | C12: ='AirDNA Paste'!C8*365 | D12: ='Quality Adjuster'!D16 | E12: =C12*D12
A14: MINI UNDERWRITING — inputs (yellow) + verdict
B15: Annual operating expenses ($): | E15: Property tax + insurance + utilities + cleaning reserve + mgmt + capex
B16: Annual debt service ($): | E16: P&I × 12 — pull from your loan calc or ACQ-001
B17: Total cash invested ($): | E17: Down + closing + rehab + furnishing
B19: Adjusted NOI: | C19: =E8-C15
B20: Annual cash flow: | C20: =E8-C15-C16
B21: Cash-on-cash return: | C21: =IFERROR((E8-C15-C16)/C17,0)
B22: DSCR: | C22: =IFERROR((E8-C15)/C16,0)
A24: =IF(AND(C21>0.08,C22>1.25),"✅ STRONG DEAL — AirDNA-adjusted COC + DSCR pass",IF(OR(C21<0.04,C22<1.05),"❌ PASS — even AirDNA cant save it after adjusters","⚠ MARGINAL — needs a margin-of-safety sanity check"))
A26: ="If you underwrote at AirDNA face value, you would have projected $"&TEXT(C8-C15-C16,"#,##0")&" cash flow. Adjusted to YOUR property: $"&TEXT(E8-C15-C16,"#,##0")&". Δ "&TEXT(E8-C8,"+$#,##0;-$#,##0")
A30: Questions? hello@thestrledger.com
A31: ACQ-005 · Adjusted Underwriting

Sheet Settings
A2: =HYPERLINK("#'Adjusted Underwriting'!A1", "← BACK") | D2: SETTINGS
A4: Workbook-wide settings — active year, source date, market context, sensitivity.
A5: ACTIVE WORKBOOK | D5: Drives any date filtering throughout the workbook
A7: Source data date: | D7: When did you pull AirDNA? (it goes stale fast)
A9: AirDNA market name: | D9: Free text — appears on AirDNA Paste tab header
A11: Conservative-mode multiplier: | D11: Extra haircut applied on top of quality mult (default 0.90 = 10% margin of safety)
A14: YEAR-END ARCHIVE — paste adjusted projection vs actuals
A15: Year | B15: AirDNA Projected | C15: Adjusted Projected | D15: Actual Revenue | E15: Δ vs Adjusted | F15: Notes
A16: =Settings!B5+0 | E16: =IFERROR((D16-C16)/C16,"")
A17: =Settings!B5+1 | E17: =IFERROR((D17-C17)/C17,"")
A18: =Settings!B5+2 | E18: =IFERROR((D18-C18)/C18,"")
A19: =Settings!B5+3 | E19: =IFERROR((D19-C19)/C19,"")
A20: =Settings!B5+4 | E20: =IFERROR((D20-C20)/C20,"")
A21: =Settings!B5+5 | E21: =IFERROR((D21-C21)/C21,"")
A23: Each January, paste last year's actual revenue into column D. The Δ column shows how accurate your adjusted projection was — refine your quality multipliers based on what actually happened. Over 2-3 years your underwriting calibrates to your specific style of operating.
A29: Questions? hello@thestrledger.com
A30: ACQ-005 · Settings
