Workbook

Sheet Start
A2: The STR Ledger
A4: 5-Year Pro-Forma
A5: Five-year cash flow, IRR, and exit math — what real underwriters use.
A7: ACQ-008 · v1.0 · DEMO
A11: =IF(Settings!B7="","(enter property on Settings tab)",Settings!B7)
A13: YEAR-5 NOI | E13: 5-YEAR IRR | I13: EQUITY MULTIPLE
A14: ='5-Year Pro-Forma'!G16 | E14: ='Exit Analysis'!C20 | I14: ='Exit Analysis'!C19
A17: YEAR-5 SALE PRICE | G17: TOTAL CASH RETURNED
A18: ='Exit Analysis'!C8 | G18: ='Exit Analysis'!C17
A24: =HYPERLINK("#'Inputs'!A1", "Inputs") | D24: =HYPERLINK("#'5-Year Pro-Forma'!A1", "5-Year Pro-Forma") | G24: =HYPERLINK("#'Scenarios'!A1", "Scenarios") | J24: =HYPERLINK("#'Exit Analysis'!A1", "Exit Analysis")
A28: =HYPERLINK("#'Inputs'!A1", "→ Inputs (start here)") | G28: =HYPERLINK("#'Settings'!A1", "Settings")
A33: 💡 Underwriting a portfolio? Get the Acquisition Bundle at thestrledger.com — deal analyzer, cost-to-launch, arbitrage finder, and this pro-forma together.
A36: Questions? hello@thestrledger.com
A37: ACQ-008 · v1.0 · DEMO · Free updates forever

Sheet Inputs
A2: =HYPERLINK("#'Start'!A1", "← BACK") | D2: INPUTS | J2: =HYPERLINK("#'5-Year Pro-Forma'!A1", "NEXT →")
A4: All assumptions live here. Yellow = editable.
A6: PURCHASE & FINANCING
B7: Purchase price ($): | C7: 485000
B8: Down payment (%): | C8: 0.25 | E8: 20-25% typical for STR
B9: Interest rate (%): | C9: 0.0725
B10: Term (years): | C10: 30 | E10: 30 typical
B11: Closing costs ($): | C11: 9000 | E11: 2-3% of purchase typical
B12: Rehab budget ($): | C12: 35000
B13: Furnishing budget ($): | C13: 25000
A15: YEAR-1 REVENUE & EXPENSES
B16: Year-1 gross revenue ($): | C16: 96000 | E16: ADR × occ × 365
B17: Vacancy / credit loss (%): | C17: 0.05 | E17: 5% typical for STR cancellations
B18: Property tax (annual): | C18: 5800
B19: Insurance (annual): | C19: 3400 | E19: STR rider included
B20: HOA / Condo (annual): | C20: 0
B21: Utilities (annual): | C21: 2400
B22: Internet (annual): | C22: 960
B23: Software / PMS (annual): | C23: 480
B24: Marketing (annual): | C24: 1200
B25: Cleaning (annual): | C25: 14000 | E25: Total Y1 turnover labor
B26: Supplies (annual): | C26: 2400
B27: Management fee (annual): | C27: 0 | E27: 0 if self-managed
B28: Maintenance (annual): | C28: 3600
B29: Other operating ($): | C29: 1800
A31: GROWTH ASSUMPTIONS
B32: Annual revenue growth (%): | C32: 0.04 | E32: Typical 3-5%
B33: Annual expense inflation (%): | C33: 0.03 | E33: Typical 3%
B34: Capital reserve (% of revenue): | C34: 0.03 | E34: Typical 3%
A36: EXIT ASSUMPTIONS
B37: Exit cap rate (%): | C37: 0.075 | E37: Entry cap or +50bps
B38: Selling cost (%): | C38: 0.06 | E38: 5-7% typical
A40: DERIVED
B41: Loan amount: | C41: =C7*(1-C8)
B42: Annual debt service (P&I): | C42: =IFERROR(PMT(C9/12,C10*12,-C41)*12,0)
B43: Total cash to close: | C43: =C7*C8+C11+C12+C13
B44: Annual depreciation (27.5-yr SL): | C44: =(C7+C12+C13)*(1-0.2)/27.5
B45: Total Y1 operating expenses: | C45: =SUM(C18:C29)
A48: Questions? hello@thestrledger.com
A49: ACQ-008 · Inputs

Sheet 5-Year Pro-Forma
A2: =HYPERLINK("#'Inputs'!A1", "← BACK") | D2: 5-YEAR PRO-FORMA | J2: =HYPERLINK("#'Scenarios'!A1", "NEXT →")
A4: Five-year matrix. Revenue grows at Inputs!C32; expenses inflate at Inputs!C33.
B6: Line item | C6: Year 1 | D6: Year 2 | E6: Year 3 | F6: Year 4 | G6: Year 5
B7: REVENUE
B8: Gross potential revenue | C8: =Inputs!$C$16*(1+Inputs!$C$32)^0 | D8: =Inputs!$C$16*(1+Inputs!$C$32)^1 | E8: =Inputs!$C$16*(1+Inputs!$C$32)^2 | F8: =Inputs!$C$16*(1+Inputs!$C$32)^3 | G8: =Inputs!$C$16*(1+Inputs!$C$32)^4
B9: Less: vacancy / credit loss | C9: =-C8*Inputs!$C$17 | D9: =-D8*Inputs!$C$17 | E9: =-E8*Inputs!$C$17 | F9: =-F8*Inputs!$C$17 | G9: =-G8*Inputs!$C$17
B10: Effective gross income | C10: =C8+C9 | D10: =D8+D9 | E10: =E8+E9 | F10: =F8+F9 | G10: =G8+G9
B11: OPERATING EXPENSES
B12: Operating expenses (inflated) | C12: =-Inputs!$C$45*(1+Inputs!$C$33)^0 | D12: =-Inputs!$C$45*(1+Inputs!$C$33)^1 | E12: =-Inputs!$C$45*(1+Inputs!$C$33)^2 | F12: =-Inputs!$C$45*(1+Inputs!$C$33)^3 | G12: =-Inputs!$C$45*(1+Inputs!$C$33)^4
B13: Capital reserves (% of revenue) | C13: =-C10*Inputs!$C$34 | D13: =-D10*Inputs!$C$34 | E13: =-E10*Inputs!$C$34 | F13: =-F10*Inputs!$C$34 | G13: =-G10*Inputs!$C$34
B14: Total expenses | C14: =C12+C13 | D14: =D12+D13 | E14: =E12+E13 | F14: =F12+F13 | G14: =G12+G13
B16: NET OPERATING INCOME (NOI) | C16: =C10+C14 | D16: =D10+D14 | E16: =E10+E14 | F16: =F10+F14 | G16: =G10+G14
B17: Less: debt service (P&I) | C17: =-Inputs!$C$42 | D17: =-Inputs!$C$42 | E17: =-Inputs!$C$42 | F17: =-Inputs!$C$42 | G17: =-Inputs!$C$42
B18: CASH FLOW BEFORE TAX | C18: =C16+C17 | D18: =D16+D17 | E18: =E16+E17 | F18: =F16+F17 | G18: =G16+G17
B20: TAX TREATMENT
B21: Depreciation (27.5-yr SL) | C21: =-Inputs!$C$44 | D21: =-Inputs!$C$44 | E21: =-Inputs!$C$44 | F21: =-Inputs!$C$44 | G21: =-Inputs!$C$44
B22: Mortgage interest (IPMT) | C22: =IFERROR(CUMIPMT(Inputs!$C$9/12,Inputs!$C$10*12,Inputs!$C$41,(0*12)+1,1*12,0),0) | D22: =IFERROR(CUMIPMT(Inputs!$C$9/12,Inputs!$C$10*12,Inputs!$C$41,(1*12)+1,2*12,0),0) | E22: =IFERROR(CUMIPMT(Inputs!$C$9/12,Inputs!$C$10*12,Inputs!$C$41,(2*12)+1,3*12,0),0) | F22: =IFERROR(CUMIPMT(Inputs!$C$9/12,Inputs!$C$10*12,Inputs!$C$41,(3*12)+1,4*12,0),0) | G22: =IFERROR(CUMIPMT(Inputs!$C$9/12,Inputs!$C$10*12,Inputs!$C$41,(4*12)+1,5*12,0),0)
B23: Taxable income | C23: =C16+C21+C22 | D23: =D16+D21+D22 | E23: =E16+E21+E22 | F23: =F16+F21+F22 | G23: =G16+G21+G22
B24: Tax owed (Settings!B13 × max(0, taxable)) | C24: =-MAX(0,C23)*Settings!$B$13 | D24: =-MAX(0,D23)*Settings!$B$13 | E24: =-MAX(0,E23)*Settings!$B$13 | F24: =-MAX(0,F23)*Settings!$B$13 | G24: =-MAX(0,G23)*Settings!$B$13
B25: AFTER-TAX CASH FLOW | C25: =C18+C24 | D25: =D18+D24 | E25: =E18+E24 | F25: =F18+F24 | G25: =G18+G24
B27: Cumulative cash flow | C27: =C25 | D27: =C27+D25 | E27: =D27+E25 | F27: =E27+F25 | G27: =F27+G25
A31: Questions? hello@thestrledger.com
A32: ACQ-008 · 5-Year Pro-Forma

Sheet Scenarios
A2: =HYPERLINK("#'5-Year Pro-Forma'!A1", "← BACK") | D2: SCENARIOS | J2: =HYPERLINK("#'Exit Analysis'!A1", "NEXT →")
A4: Three side-by-side projections. Adjust the assumption rows; the math flows.
B6: Metric | C6: Conservative | D6: Base | E6: Aggressive
B7: Revenue growth (%): | C7: 0.01 | D7: 0.04 | E7: 0.06
B8: Expense inflation (%): | C8: 0.04 | D8: 0.03 | E8: 0.02
B9: Vacancy / occupancy hit (%): | C9: 0.1 | D9: 0.05 | E9: 0.02
A10: 5-YEAR FINANCIAL SUMMARY
B11: 5-yr gross revenue | C11: =SUMPRODUCT(Inputs!$C$16*(1-C$9)*(1+C$7)^{0;1;2;3;4}) | D11: =SUMPRODUCT(Inputs!$C$16*(1-D$9)*(1+D$7)^{0;1;2;3;4}) | E11: =SUMPRODUCT(Inputs!$C$16*(1-E$9)*(1+E$7)^{0;1;2;3;4})
B12: 5-yr operating expenses | C12: =SUMPRODUCT(Inputs!$C$45*(1+C$8)^{0;1;2;3;4}) | D12: =SUMPRODUCT(Inputs!$C$45*(1+D$8)^{0;1;2;3;4}) | E12: =SUMPRODUCT(Inputs!$C$45*(1+E$8)^{0;1;2;3;4})
B13: 5-yr capital reserves | C13: =SUMPRODUCT(Inputs!$C$16*(1-C$9)*(1+C$7)^{0;1;2;3;4}*Inputs!$C$34) | D13: =SUMPRODUCT(Inputs!$C$16*(1-D$9)*(1+D$7)^{0;1;2;3;4}*Inputs!$C$34) | E13: =SUMPRODUCT(Inputs!$C$16*(1-E$9)*(1+E$7)^{0;1;2;3;4}*Inputs!$C$34)
B14: 5-yr debt service | C14: =Inputs!$C$42*5 | D14: =Inputs!$C$42*5 | E14: =Inputs!$C$42*5
B15: 5-yr cumulative cash flow | C15: =(SUMPRODUCT(Inputs!$C$16*(1-C$9)*(1+C$7)^{0;1;2;3;4})-SUMPRODUCT(Inputs!$C$45*(1+C$8)^{0;1;2;3;4})-SUMPRODUCT(Inputs!$C$16*(1-C$9)*(1+C$7)^{0;1;2;3;4}*Inputs!$C$34)-Inputs!$C$42*5) | D15: =(SUMPRODUCT(Inputs!$C$16*(1-D$9)*(1+D$7)^{0;1;2;3;4})-SUMPRODUCT(Inputs!$C$45*(1+D$8)^{0;1;2;3;4})-SUMPRODUCT(Inputs!$C$16*(1-D$9)*(1+D$7)^{0;1;2;3;4}*Inputs!$C$34)-Inputs!$C$42*5) | E15: =(SUMPRODUCT(Inputs!$C$16*(1-E$9)*(1+E$7)^{0;1;2;3;4})-SUMPRODUCT(Inputs!$C$45*(1+E$8)^{0;1;2;3;4})-SUMPRODUCT(Inputs!$C$16*(1-E$9)*(1+E$7)^{0;1;2;3;4}*Inputs!$C$34)-Inputs!$C$42*5)
A16: EXIT METRICS (YEAR 5 SALE)
B17: Year-5 NOI | C17: =(Inputs!$C$16*(1-C$9)*(1+C$7)^4-Inputs!$C$45*(1+C$8)^4-Inputs!$C$16*(1-C$9)*(1+C$7)^4*Inputs!$C$34) | D17: =(Inputs!$C$16*(1-D$9)*(1+D$7)^4-Inputs!$C$45*(1+D$8)^4-Inputs!$C$16*(1-D$9)*(1+D$7)^4*Inputs!$C$34) | E17: =(Inputs!$C$16*(1-E$9)*(1+E$7)^4-Inputs!$C$45*(1+E$8)^4-Inputs!$C$16*(1-E$9)*(1+E$7)^4*Inputs!$C$34)
B18: Year-5 sale price | C18: =((Inputs!$C$16*(1-C$9)*(1+C$7)^4-Inputs!$C$45*(1+C$8)^4-Inputs!$C$16*(1-C$9)*(1+C$7)^4*Inputs!$C$34)/Inputs!$C$37)*(1-Inputs!$C$38) | D18: =((Inputs!$C$16*(1-D$9)*(1+D$7)^4-Inputs!$C$45*(1+D$8)^4-Inputs!$C$16*(1-D$9)*(1+D$7)^4*Inputs!$C$34)/Inputs!$C$37)*(1-Inputs!$C$38) | E18: =((Inputs!$C$16*(1-E$9)*(1+E$7)^4-Inputs!$C$45*(1+E$8)^4-Inputs!$C$16*(1-E$9)*(1+E$7)^4*Inputs!$C$34)/Inputs!$C$37)*(1-Inputs!$C$38)
B19: Less: loan balance at Y5 | C19: =(Inputs!$C$41+CUMPRINC(Inputs!$C$9/12,Inputs!$C$10*12,Inputs!$C$41,1,60,0)) | D19: =(Inputs!$C$41+CUMPRINC(Inputs!$C$9/12,Inputs!$C$10*12,Inputs!$C$41,1,60,0)) | E19: =(Inputs!$C$41+CUMPRINC(Inputs!$C$9/12,Inputs!$C$10*12,Inputs!$C$41,1,60,0))
B20: Net sale proceeds | C20: =(((Inputs!$C$16*(1-C$9)*(1+C$7)^4-Inputs!$C$45*(1+C$8)^4-Inputs!$C$16*(1-C$9)*(1+C$7)^4*Inputs!$C$34)/Inputs!$C$37)*(1-Inputs!$C$38)-(Inputs!$C$41+CUMPRINC(Inputs!$C$9/12,Inputs!$C$10*12,Inputs!$C$41,1,60,0))) | D20: =(((Inputs!$C$16*(1-D$9)*(1+D$7)^4-Inputs!$C$45*(1+D$8)^4-Inputs!$C$16*(1-D$9)*(1+D$7)^4*Inputs!$C$34)/Inputs!$C$37)*(1-Inputs!$C$38)-(Inputs!$C$41+CUMPRINC(Inputs!$C$9/12,Inputs!$C$10*12,Inputs!$C$41,1,60,0))) | E20: =(((Inputs!$C$16*(1-E$9)*(1+E$7)^4-Inputs!$C$45*(1+E$8)^4-Inputs!$C$16*(1-E$9)*(1+E$7)^4*Inputs!$C$34)/Inputs!$C$37)*(1-Inputs!$C$38)-(Inputs!$C$41+CUMPRINC(Inputs!$C$9/12,Inputs!$C$10*12,Inputs!$C$41,1,60,0)))
A21: TOTAL RETURN
B22: Total cash returned (CF + sale) | C22: =((SUMPRODUCT(Inputs!$C$16*(1-C$9)*(1+C$7)^{0;1;2;3;4})-SUMPRODUCT(Inputs!$C$45*(1+C$8)^{0;1;2;3;4})-SUMPRODUCT(Inputs!$C$16*(1-C$9)*(1+C$7)^{0;1;2;3;4}*Inputs!$C$34)-Inputs!$C$42*5)+(((Inputs!$C$16*(1-C$9)*(1+C$7)^4-Inputs!$C$45*(1+C$8)^4-Inputs!$C$16*(1-C$9)*(1+C$7)^4*Inputs!$C$34)/Inputs!$C$37)*(1-Inputs!$C$38)-(Inputs!$C$41+CUMPRINC(Inputs!$C$9/12,Inputs!$C$10*12,Inputs!$C$41,1,60,0)))) | D22: =((SUMPRODUCT(Inputs!$C$16*(1-D$9)*(1+D$7)^{0;1;2;3;4})-SUMPRODUCT(Inputs!$C$45*(1+D$8)^{0;1;2;3;4})-SUMPRODUCT(Inputs!$C$16*(1-D$9)*(1+D$7)^{0;1;2;3;4}*Inputs!$C$34)-Inputs!$C$42*5)+(((Inputs!$C$16*(1-D$9)*(1+D$7)^4-Inputs!$C$45*(1+D$8)^4-Inputs!$C$16*(1-D$9)*(1+D$7)^4*Inputs!$C$34)/Inputs!$C$37)*(1-Inputs!$C$38)-(Inputs!$C$41+CUMPRINC(Inputs!$C$9/12,Inputs!$C$10*12,Inputs!$C$41,1,60,0)))) | E22: =((SUMPRODUCT(Inputs!$C$16*(1-E$9)*(1+E$7)^{0;1;2;3;4})-SUMPRODUCT(Inputs!$C$45*(1+E$8)^{0;1;2;3;4})-SUMPRODUCT(Inputs!$C$16*(1-E$9)*(1+E$7)^{0;1;2;3;4}*Inputs!$C$34)-Inputs!$C$42*5)+(((Inputs!$C$16*(1-E$9)*(1+E$7)^4-Inputs!$C$45*(1+E$8)^4-Inputs!$C$16*(1-E$9)*(1+E$7)^4*Inputs!$C$34)/Inputs!$C$37)*(1-Inputs!$C$38)-(Inputs!$C$41+CUMPRINC(Inputs!$C$9/12,Inputs!$C$10*12,Inputs!$C$41,1,60,0))))
B23: Equity multiple | C23: =(((SUMPRODUCT(Inputs!$C$16*(1-C$9)*(1+C$7)^{0;1;2;3;4})-SUMPRODUCT(Inputs!$C$45*(1+C$8)^{0;1;2;3;4})-SUMPRODUCT(Inputs!$C$16*(1-C$9)*(1+C$7)^{0;1;2;3;4}*Inputs!$C$34)-Inputs!$C$42*5)+(((Inputs!$C$16*(1-C$9)*(1+C$7)^4-Inputs!$C$45*(1+C$8)^4-Inputs!$C$16*(1-C$9)*(1+C$7)^4*Inputs!$C$34)/Inputs!$C$37)*(1-Inputs!$C$38)-(Inputs!$C$41+CUMPRINC(Inputs!$C$9/12,Inputs!$C$10*12,Inputs!$C$41,1,60,0))))/Inputs!$C$43) | D23: =(((SUMPRODUCT(Inputs!$C$16*(1-D$9)*(1+D$7)^{0;1;2;3;4})-SUMPRODUCT(Inputs!$C$45*(1+D$8)^{0;1;2;3;4})-SUMPRODUCT(Inputs!$C$16*(1-D$9)*(1+D$7)^{0;1;2;3;4}*Inputs!$C$34)-Inputs!$C$42*5)+(((Inputs!$C$16*(1-D$9)*(1+D$7)^4-Inputs!$C$45*(1+D$8)^4-Inputs!$C$16*(1-D$9)*(1+D$7)^4*Inputs!$C$34)/Inputs!$C$37)*(1-Inputs!$C$38)-(Inputs!$C$41+CUMPRINC(Inputs!$C$9/12,Inputs!$C$10*12,Inputs!$C$41,1,60,0))))/Inputs!$C$43) | E23: =(((SUMPRODUCT(Inputs!$C$16*(1-E$9)*(1+E$7)^{0;1;2;3;4})-SUMPRODUCT(Inputs!$C$45*(1+E$8)^{0;1;2;3;4})-SUMPRODUCT(Inputs!$C$16*(1-E$9)*(1+E$7)^{0;1;2;3;4}*Inputs!$C$34)-Inputs!$C$42*5)+(((Inputs!$C$16*(1-E$9)*(1+E$7)^4-Inputs!$C$45*(1+E$8)^4-Inputs!$C$16*(1-E$9)*(1+E$7)^4*Inputs!$C$34)/Inputs!$C$37)*(1-Inputs!$C$38)-(Inputs!$C$41+CUMPRINC(Inputs!$C$9/12,Inputs!$C$10*12,Inputs!$C$41,1,60,0))))/Inputs!$C$43)
A27: Questions? hello@thestrledger.com
A28: ACQ-008 · Scenarios

Sheet Exit Analysis
A2: =HYPERLINK("#'Scenarios'!A1", "← BACK") | D2: EXIT ANALYSIS | J2: =HYPERLINK("#'Settings'!A1", "NEXT →")
A4: Year-5 sale math: NOI ÷ exit cap = sale price. Less loan balance, less selling costs.
A6: EXIT VALUATION
B7: Year-5 NOI: | C7: ='5-Year Pro-Forma'!G16
B8: Year-5 sale price (NOI ÷ exit cap): | C8: =C7/Inputs!C37
B9: Less: selling costs: | C9: =-C8*Inputs!C38
B10: Less: remaining loan balance: | C10: =-(Inputs!C41+CUMPRINC(Inputs!C9/12,Inputs!C10*12,Inputs!C41,1,60,0))
B11: Net sale proceeds: | C11: =C8+C9+C10
A13: TOTAL RETURN & IRR
B14: Total cash invested: | C14: =Inputs!C43
B15: Cumulative 5-yr cash flow: | C15: ='5-Year Pro-Forma'!G27
B16: Net sale proceeds: | C16: =C11
B17: Total cash returned: | C17: =C15+C16
B18: Total profit: | C18: =C17-C14
B19: Equity multiple (× cash invested): | C19: =C17/C14
B20: Internal Rate of Return (IRR): | C20: =IRR(CHOOSE({1;2;3;4;5;6},-C14,'5-Year Pro-Forma'!C25,'5-Year Pro-Forma'!D25,'5-Year Pro-Forma'!E25,'5-Year Pro-Forma'!F25,'5-Year Pro-Forma'!G25+C11))
A23: IRR uses Excel's IRR() across 6 periods: year-0 negative cash investment, years 1-4 after-tax cash flow, year 5 after-tax cash flow plus net sale proceeds. Loan balance computed via CUMPRINC over 60 monthly payments. Equity multiple = total cash returned ÷ total cash invested.
A28: Questions? hello@thestrledger.com
A29: ACQ-008 · Exit Analysis

Sheet Settings
A2: =HYPERLINK("#'Exit Analysis'!A1", "← BACK") | D2: SETTINGS
A4: Workbook-level settings. Property name shows on the Start tab banner.
A5: Active year: | B5: 2026 | D5: Year 1 calendar year
A7: Property name: | B7: Smokies Ridge Cabin | D7: Shown on Start banner
A9: Hold period (years): | B9: 5 | D9: Default 5
A11: Discount rate (NPV): | B11: 0.1 | D11: Default 10%
A13: Blended tax rate: | B13: 0.28 | D13: Used for taxable-income calc
A18: Questions? hello@thestrledger.com
A19: ACQ-008 · Settings
