Workbook

Sheet Start
A2: The STR Ledger
A4: 12-Month Cash Flow Forecast
A5: See your low month before it sees you.
A6: =IF(MIN('Cash Flow Forecast'!B11:M11)<0,"⚠ Projected cash dips to "&TEXT(MIN('Cash Flow Forecast'!B11:M11),"$#,##0")&" in "&INDEX({"Jan","Feb","Mar","Apr","May","Jun","Jul","Aug","Sep","Oct","Nov","Dec"},MATCH(MIN('Cash Flow Forecast'!B11:M11),'Cash Flow Forecast'!B11:M11,0))&" — raise reserve or move expenses.","✅ Cash stays positive every month — lowest = "&TEXT(MIN('Cash Flow Forecast'!B11:M11),"$#,##0")&".")
A7: FIN-003 · v2.2 · DEMO
A10: WHAT THIS DOES
A11: Combines confirmed bookings, projected revenue (occ × ADR × 30), recurring monthly expenses, and one-off planned costs (renovations, estimated taxes) into a single 12-month forecast. Cumulative cash starts from your Jan 1 balance and runs forward — the lowest month is the only one that matters.
A18: HOW TO USE
A19: ① Settings: enter your starting cash balance (Jan 1) and active year.
A20: ② Bookings + Revenue: paste confirmed $ from your PMS, set occ % + ADR per month per property.
A21: ③ Recurring Expenses: enter monthly amounts for mortgage, insurance, utilities, etc.
A22: ④ One-Off Expenses: log planned 1-time costs (renovations, estimated taxes) by date.
A23: ⑤ Cash Flow Forecast: read the chart. Red bars = months your cumulative cash goes negative.
A24: ⑥ Re-run monthly — drag confirmed bookings up as guests book; the low month moves with you.
A27: =HYPERLINK("#'Cash Flow Forecast'!A1", "→ OPEN CASH FLOW FORECAST")
A32: AVG MONTHLY NET | D32: LOWEST MONTH | G32: RUNWAY (MONTHS) | J32: DAYS-CASH-ON-HAND
A33: =AVERAGE('Cash Flow Forecast'!B10:M10) | D33: =MIN('Cash Flow Forecast'!B11:M11) | G33: =IFERROR(IF(AVERAGE('Cash Flow Forecast'!B10:M10)>=0,"∞",Settings!$B$7/(-1*AVERAGE('Cash Flow Forecast'!B10:M10))),"—") | J33: =IFERROR(Settings!$B$7/((SUM('Recurring Expenses'!B7:M21)+SUMPRODUCT(--ISNUMBER('One-Off Expenses'!D6:D105),'One-Off Expenses'!D6:D105))/365),0)
A35: revenue − all expenses | D35: cumulative cash floor | G35: if avg net is negative | J35: starting cash ÷ daily burn
A39: =HYPERLINK("#'Bookings + Revenue'!A1", "Bookings + Revenue") | D39: =HYPERLINK("#'Recurring Expenses'!A1", "Recurring Expenses") | G39: =HYPERLINK("#'One-Off Expenses'!A1", "One-Off Expenses") | J39: =HYPERLINK("#'Settings'!A1", "Settings")
A42: 📅 RE-FORECAST MONTHLY: replace projected booking $ with confirmed $ as guests book. The low month always shifts — don't trust a stale forecast.
A44: 💡 Upgrade to the Full version at thestrledger.com/upgrade — multi-property, depreciation, multi-LLC support.
A47: Questions? hello@thestrledger.com
A48: FIN-003 · v2.2 · Free updates forever

Sheet Bookings + Revenue
P1: 29
A2: =HYPERLINK("#'Start'!A1", "← BACK") | D2: BOOKINGS + REVENUE | J2: =HYPERLINK("#'Recurring Expenses'!A1", "NEXT →")
A4: Per property: confirmed $ + projected (occ % × ADR × 30 days). Update confirmed monthly as guests book.
A5: Line | B5: Jan | C5: Feb | D5: Mar | E5: Apr | F5: May | G5: Jun | H5: Jul | I5: Aug | J5: Sep | K5: Oct | L5: Nov | M5: Dec | N5: Total
A7: SMOKIES RIDGE CABIN
A8: Confirmed bookings ($) | B8: 3800 | C8: 3200 | D8: 2800 | E8: 2400 | F8: 1800 | G8: 2400 | H8: 1800 | I8: 1200 | J8: 900 | K8: 600 | L8: 300 | M8: 900 | N8: =SUM(B8:M8)
A9: Projected occupancy % | B9: 0.45 | C9: 0.4 | D9: 0.55 | E9: 0.65 | F9: 0.75 | G9: 0.88 | H9: 0.92 | I9: 0.9 | J9: 0.78 | K9: 0.7 | L9: 0.6 | M9: 0.65 | N9: =AVERAGE(B9:M9)
A10: Projected ADR ($) | B10: 280 | C10: 280 | D10: 290 | E10: 300 | F10: 320 | G10: 360 | H10: 380 | I10: 380 | J10: 340 | K10: 320 | L10: 300 | M10: 340 | N10: =AVERAGE(B10:M10)
A11: Projected revenue (occ × ADR × 30) | B11: =B9*B10*30 | C11: =C9*C10*30 | D11: =D9*D10*30 | E11: =E9*E10*30 | F11: =F9*F10*30 | G11: =G9*G10*30 | H11: =H9*H10*30 | I11: =I9*I10*30 | ... M11: =M9*M10*30 | N11: =SUM(B11:M11)
A12: TOTAL — property monthly revenue | B12: =B8+B11 | C12: =C8+C11 | D12: =D8+D11 | E12: =E8+E11 | F12: =F8+F11 | G12: =G8+G11 | H12: =H8+H11 | I12: =I8+I11 | ... M12: =M8+M11 | N12: =SUM(B12:M12)
A14: LAKESIDE LOFT
A15: Confirmed bookings ($) | B15: 2000 | C15: 1800 | D15: 1600 | E15: 1400 | F15: 1200 | G15: 1500 | H15: 1100 | I15: 800 | J15: 600 | K15: 400 | L15: 200 | M15: 600 | N15: =SUM(B15:M15)
A16: Projected occupancy % | B16: 0.38 | C16: 0.35 | D16: 0.48 | E16: 0.6 | F16: 0.72 | G16: 0.85 | H16: 0.9 | I16: 0.88 | J16: 0.72 | K16: 0.62 | L16: 0.5 | M16: 0.55 | N16: =AVERAGE(B16:M16)
A17: Projected ADR ($) | B17: 180 | C17: 180 | D17: 190 | E17: 200 | F17: 210 | G17: 240 | H17: 260 | I17: 260 | J17: 220 | K17: 210 | L17: 200 | M17: 220 | N17: =AVERAGE(B17:M17)
A18: Projected revenue (occ × ADR × 30) | B18: =B16*B17*30 | C18: =C16*C17*30 | D18: =D16*D17*30 | E18: =E16*E17*30 | F18: =F16*F17*30 | G18: =G16*G17*30 | H18: =H16*H17*30 | I18: =I16*I17*30 | ... M18: =M16*M17*30 | N18: =SUM(B18:M18)
A19: TOTAL — property monthly revenue | B19: =B15+B18 | C19: =C15+C18 | D19: =D15+D18 | E19: =E15+E18 | F19: =F15+F18 | G19: =G15+G18 | H19: =H15+H18 | I19: =I15+I18 | ... M19: =M15+M18 | N19: =SUM(B19:M19)
A21: DOWNTOWN STUDIO
A22: Confirmed bookings ($) | B22: 2200 | C22: 2300 | D22: 1800 | E22: 1600 | F22: 1300 | G22: 1100 | H22: 900 | I22: 700 | J22: 500 | K22: 400 | L22: 300 | M22: 500 | N22: =SUM(B22:M22)
A23: Projected occupancy % | B23: 0.55 | C23: 0.58 | D23: 0.62 | E23: 0.68 | F23: 0.7 | G23: 0.72 | H23: 0.74 | I23: 0.72 | J23: 0.7 | K23: 0.68 | L23: 0.62 | M23: 0.65 | N23: =AVERAGE(B23:M23)
A24: Projected ADR ($) | B24: 130 | C24: 130 | D24: 140 | E24: 145 | F24: 150 | G24: 160 | H24: 165 | I24: 165 | J24: 155 | K24: 150 | L24: 145 | M24: 150 | N24: =AVERAGE(B24:M24)
A25: Projected revenue (occ × ADR × 30) | B25: =B23*B24*30 | C25: =C23*C24*30 | D25: =D23*D24*30 | E25: =E23*E24*30 | F25: =F23*F24*30 | G25: =G23*G24*30 | H25: =H23*H24*30 | I25: =I23*I24*30 | ... M25: =M23*M24*30 | N25: =SUM(B25:M25)
A26: TOTAL — property monthly revenue | B26: =B22+B25 | C26: =C22+C25 | D26: =D22+D25 | E26: =E22+E25 | F26: =F22+F25 | G26: =G22+G25 | H26: =H22+H25 | I26: =I22+I25 | ... M26: =M22+M25 | N26: =SUM(B26:M26)
A29: PORTFOLIO TOTAL REVENUE | B29: =B12+B19+B26 | C29: =C12+C19+C26 | D29: =D12+D19+D26 | E29: =E12+E19+E26 | F29: =F12+F19+F26 | G29: =G12+G19+G26 | H29: =H12+H19+H26 | I29: =I12+I19+I26 | ... M29: =M12+M19+M26 | N29: =SUM(B29:M29)

Sheet Recurring Expenses
A2: =HYPERLINK("#'Bookings + Revenue'!A1", "← BACK") | D2: RECURRING EXPENSES | J2: =HYPERLINK("#'One-Off Expenses'!A1", "NEXT →")
A4: One row per category. Same amount every month? Type once, copy across. Override any month that's different.
A5: Category | B5: Jan | C5: Feb | D5: Mar | E5: Apr | F5: May | G5: Jun | H5: Jul | I5: Aug | J5: Sep | K5: Oct | L5: Nov | M5: Dec | N5: Total
A7: Mortgage (P&I) | B7: 4200 | C7: 4200 | D7: 4200 | E7: 4200 | F7: 4200 | G7: 4200 | H7: 4200 | I7: 4200 | J7: 4200 | K7: 4200 | L7: 4200 | M7: 4200 | N7: =SUM(B7:M7)
A8: Property tax (escrow) | B8: 850 | C8: 850 | D8: 850 | E8: 850 | F8: 850 | G8: 850 | H8: 850 | I8: 850 | J8: 850 | K8: 850 | L8: 850 | M8: 850 | N8: =SUM(B8:M8)
A9: Insurance | B9: 420 | C9: 420 | D9: 420 | E9: 420 | F9: 420 | G9: 420 | H9: 420 | I9: 420 | J9: 420 | K9: 420 | L9: 420 | M9: 420 | N9: =SUM(B9:M9)
A10: HOA / community fees | B10: 180 | C10: 180 | D10: 180 | E10: 180 | F10: 180 | G10: 180 | H10: 180 | I10: 180 | J10: 180 | K10: 180 | L10: 180 | M10: 180 | N10: =SUM(B10:M10)
A11: Internet | B11: 270 | C11: 270 | D11: 270 | E11: 270 | F11: 270 | G11: 270 | H11: 270 | I11: 270 | J11: 270 | K11: 270 | L11: 270 | M11: 270 | N11: =SUM(B11:M11)
A12: Electric | B12: 380 | C12: 380 | D12: 320 | E12: 280 | F12: 260 | G12: 320 | H12: 420 | I12: 440 | J12: 360 | K12: 290 | L12: 280 | M12: 360 | N12: =SUM(B12:M12)
A13: Gas | B13: 240 | C13: 240 | D13: 200 | E13: 140 | F13: 100 | G13: 80 | H13: 60 | I13: 60 | J13: 90 | K13: 140 | L13: 200 | M13: 240 | N13: =SUM(B13:M13)
A14: Water / sewer | B14: 180 | C14: 180 | D14: 180 | E14: 180 | F14: 180 | G14: 180 | H14: 180 | I14: 180 | J14: 180 | K14: 180 | L14: 180 | M14: 180 | N14: =SUM(B14:M14)
A15: Trash / recycling | B15: 90 | C15: 90 | D15: 90 | E15: 90 | F15: 90 | G15: 90 | H15: 90 | I15: 90 | J15: 90 | K15: 90 | L15: 90 | M15: 90 | N15: =SUM(B15:M15)
A16: Software (PMS, accounting) | B16: 240 | C16: 240 | D16: 240 | E16: 240 | F16: 240 | G16: 240 | H16: 240 | I16: 240 | J16: 240 | K16: 240 | L16: 240 | M16: 240 | N16: =SUM(B16:M16)
A17: Cleaning (recurring contract) | B17: 2400 | C17: 2200 | D17: 2400 | E17: 2600 | F17: 2800 | G17: 3000 | H17: 3200 | I17: 3200 | J17: 2800 | K17: 2600 | L17: 2400 | M17: 2600 | N17: =SUM(B17:M17)
A18: Supplies restock | B18: 180 | C18: 160 | D18: 200 | E18: 220 | F18: 240 | G18: 260 | H18: 280 | I18: 280 | J18: 240 | K18: 220 | L18: 200 | M18: 220 | N18: =SUM(B18:M18)
... A21: Misc / contingency | B21: 200 | C21: 200 | D21: 200 | E21: 200 | F21: 200 | G21: 200 | H21: 200 | I21: 200 | J21: 200 | K21: 200 | L21: 200 | M21: 200 | N21: =SUM(B21:M21)
A23: TOTAL RECURRING EXPENSES | B23: =SUM(B7:B21) | C23: =SUM(C7:C21) | D23: =SUM(D7:D21) | E23: =SUM(E7:E21) | F23: =SUM(F7:F21) | G23: =SUM(G7:G21) | H23: =SUM(H7:H21) | I23: =SUM(I7:I21) | ... N23: =SUM(N7:N21)

Sheet One-Off Expenses
A2: =HYPERLINK("#'Recurring Expenses'!A1", "← BACK") | D2: ONE-OFF EXPENSES | J2: =HYPERLINK("#'Cash Flow Forecast'!A1", "NEXT →")
A4: Planned 1-time expenses — renovations, appliance replacement, estimated tax payments, legal fees. Posted to Cash Flow Forecast by month.
A5: Date | B5: Property | C5: Category | D5: Amount | E5: Notes
A6: 46037 | B6: Smokies Ridge Cabin | C6: Estimated tax (Q1) | D6: 1500 | E6: Federal Q1
A7: 46037 | B7: Lakeside Loft | C7: Estimated tax (Q1) | D7: 1500 | E7: Federal Q1
A8: 46037 | B8: Downtown Studio | C8: Estimated tax (Q1) | D8: 1500 | E8: Federal Q1
A9: 46127 | B9: Smokies Ridge Cabin | C9: Estimated tax (Q2) | D9: 1200 | E9: Federal Q2
A10: 46127 | B10: Lakeside Loft | C10: Estimated tax (Q2) | D10: 1200 | E10: Federal Q2
A11: 46127 | B11: Downtown Studio | C11: Estimated tax (Q2) | D11: 1200 | E11: Federal Q2
A12: 46188 | B12: Smokies Ridge Cabin | C12: Estimated tax (Q3) | D12: 1200 | E12: Federal Q3
A13: 46188 | B13: Lakeside Loft | C13: Estimated tax (Q3) | D13: 1200 | E13: Federal Q3
A14: 46188 | B14: Downtown Studio | C14: Estimated tax (Q3) | D14: 1200 | E14: Federal Q3
A15: 46280 | B15: Smokies Ridge Cabin | C15: Estimated tax (Q4) | D15: 1500 | E15: Federal Q4
A16: 46280 | B16: Lakeside Loft | C16: Estimated tax (Q4) | D16: 1500 | E16: Federal Q4
A17: 46280 | B17: Downtown Studio | C17: Estimated tax (Q4) | D17: 1500 | E17: Federal Q4
... A21: 46254 | B21: Smokies Ridge Cabin | C21: Deck restain | D21: 1100 | E21: Annual maintenance

Sheet Cash Flow Forecast
A2: =HYPERLINK("#'One-Off Expenses'!A1", "← BACK") | D2: CASH FLOW FORECAST | J2: =HYPERLINK("#'Settings'!A1", "NEXT →")
A4: Combined 12-month forecast. Red bars = months where cumulative cash is negative. The chart on the right is your decision-support view.
A5: Line | B5: Jan | C5: Feb | D5: Mar | E5: Apr | F5: May | G5: Jun | H5: Jul | I5: Aug | J5: Sep | K5: Oct | L5: Nov | M5: Dec | N5: Total
A7: Revenue (portfolio total) | B7: ='Bookings + Revenue'!B29 | C7: ='Bookings + Revenue'!C29 | D7: ='Bookings + Revenue'!D29 | E7: ='Bookings + Revenue'!E29 | F7: ='Bookings + Revenue'!F29 | G7: ='Bookings + Revenue'!G29 | H7: ='Bookings + Revenue'!H29 | I7: ='Bookings + Revenue'!I29 | ... M7: ='Bookings + Revenue'!M29 | N7: =SUM(B7:M7)
A8: Recurring expenses | B8: ='Recurring Expenses'!B23 | C8: ='Recurring Expenses'!C23 | D8: ='Recurring Expenses'!D23 | E8: ='Recurring Expenses'!E23 | F8: ='Recurring Expenses'!F23 | G8: ='Recurring Expenses'!G23 | H8: ='Recurring Expenses'!H23 | I8: ='Recurring Expenses'!I23 | ... M8: ='Recurring Expenses'!M23 | N8: =SUM(B8:M8)
A9: One-off expenses | B9: =SUMPRODUCT((MONTH('One-Off Expenses'!$A$6:$A$105)=1)*(YEAR('One-Off Expenses'!$A$6:$A$105)=Settings!$B$5)*IFERROR('One-Off Expenses'!$D$6:$D$105,0)) | C9: =SUMPRODUCT((MONTH('One-Off Expenses'!$A$6:$A$105)=2)*(YEAR('One-Off Expenses'!$A$6:$A$105)=Settings!$B$5)*IFERROR('One-Off Expenses'!$D$6:$D$105,0)) | D9: =SUMPRODUCT((MONTH('One-Off Expenses'!$A$6:$A$105)=3)*(YEAR('One-Off Expenses'!$A$6:$A$105)=Settings!$B$5)*IFERROR('One-Off Expenses'!$D$6:$D$105,0)) | E9: =SUMPRODUCT((MONTH('One-Off Expenses'!$A$6:$A$105)=4)*(YEAR('One-Off Expenses'!$A$6:$A$105)=Settings!$B$5)*IFERROR('One-Off Expenses'!$D$6:$D$105,0)) | F9: =SUMPRODUCT((MONTH('One-Off Expenses'!$A$6:$A$105)=5)*(YEAR('One-Off Expenses'!$A$6:$A$105)=Settings!$B$5)*IFERROR('One-Off Expenses'!$D$6:$D$105,0)) | G9: =SUMPRODUCT((MONTH('One-Off Expenses'!$A$6:$A$105)=6)*(YEAR('One-Off Expenses'!$A$6:$A$105)=Settings!$B$5)*IFERROR('One-Off Expenses'!$D$6:$D$105,0)) | H9: =SUMPRODUCT((MONTH('One-Off Expenses'!$A$6:$A$105)=7)*(YEAR('One-Off Expenses'!$A$6:$A$105)=Settings!$B$5)*IFERROR('One-Off Expenses'!$D$6:$D$105,0)) | I9: =SUMPRODUCT((MONTH('One-Off Expenses'!$A$6:$A$105)=8)*(YEAR('One-Off Expenses'!$A$6:$A$105)=Settings!$B$5)*IFERROR('One-Off Expenses'!$D$6:$D$105,0)) | J9: =SUMPRODUCT((MONTH('One-Off Expenses'!$A$6:$A$105)=9)*(YEAR('One-Off Expenses'!$A$6:$A$105)=Settings!$B$5)*IFERROR('One-Off Expenses'!$D$6:$D$105,0)) | K9: =SUMPRODUCT((MONTH('One-Off Expenses'!$A$6:$A$105)=10)*(YEAR('One-Off Expenses'!$A$6:$A$105)=Settings!$B$5)*IFERROR('One-Off Expenses'!$D$6:$D$105,0)) | L9: =SUMPRODUCT((MONTH('One-Off Expenses'!$A$6:$A$105)=11)*(YEAR('One-Off Expenses'!$A$6:$A$105)=Settings!$B$5)*IFERROR('One-Off Expenses'!$D$6:$D$105,0)) | M9: =SUMPRODUCT((MONTH('One-Off Expenses'!$A$6:$A$105)=12)*(YEAR('One-Off Expenses'!$A$6:$A$105)=Settings!$B$5)*IFERROR('One-Off Expenses'!$D$6:$D$105,0)) | N9: =SUM(B9:M9)
A10: NET monthly cash flow | B10: =B7-B8-B9 | C10: =C7-C8-C9 | D10: =D7-D8-D9 | E10: =E7-E8-E9 | F10: =F7-F8-F9 | G10: =G7-G8-G9 | H10: =H7-H8-H9 | I10: =I7-I8-I9 | ... M10: =M7-M8-M9 | N10: =SUM(B10:M10)
A11: CUMULATIVE CASH ON HAND | B11: =Settings!$B$7+B10 | C11: =B11+C10 | D11: =C11+D10 | E11: =D11+E10 | F11: =E11+F10 | G11: =F11+G10 | H11: =G11+H10 | I11: =H11+I10 | J11: =I11+J10 | ... M11: =L11+M10 | N11: =M11

Sheet Settings
A2: =HYPERLINK("#'Cash Flow Forecast'!A1", "← BACK") | D2: SETTINGS
A4: Active year · starting cash balance · property list · category list
A5: Active year: | B5: 2026
A6: Drives the SUMPRODUCT date filter on the One-Off Expenses roll-up. Bump each January.
A7: Starting cash balance (Jan 1): | B7: 48000
A8: Operating cash on hand at the start of the year (checking + savings earmarked for the rentals). The cumulative-cash row builds from here.
A9: Property list (drives One-Off dropdown)
B10: Smokies Ridge Cabin
B11: Lakeside Loft
B12: Downtown Studio
A21: Recurring expense categories
A22: (Reference list — Recurring Expenses tab carries these)
A23: Mortgage (P&I)
A24: Property tax (escrow)
A25: Insurance
A26: HOA / community fees
A27: Internet
A28: Electric
A29: Gas
A30: Water / sewer
A31: Trash / recycling
A32: Software (PMS, accounting)
... A42: FIN-003 · v2.2 · Free updates forever
