Workbook

Sheet Start
A2: The STR Ledger
A4: Multi-Entity Consolidated P&L
A5: One workbook for the whole holding-company stack. CPA-ready.
A7: FIN-006 · v1.0 · BLANK
A10: ACTIVE ENTITIES | D10: CONSOLIDATED REVENUE | G10: CONSOLIDATED NOI | J10: DISTRIBUTIONS YTD
A11: =COUNTA('Entity Setup'!A6:A15) | D11: ='Consolidated P&L'!B7 | G11: ='Consolidated P&L'!B24 | J11: ='Member Distributions'!N17
A18: =HYPERLINK("#'Entity Setup'!A1", "Entity Setup") | D18: =HYPERLINK("#'Per-Entity P&L'!A1", "Per-Entity P&L") | G18: =HYPERLINK("#'Intercompany'!A1", "Intercompany") | J18: =HYPERLINK("#'Settings'!A1", "Settings")
A22: =HYPERLINK("#'Consolidated P&L'!A1", "Consolidated P&L") | D22: =HYPERLINK("#'Member Distributions'!A1", "Member Distributions") | G22: =HYPERLINK("#'K-1 Worksheet'!A1", "K-1 Worksheet") | J22: =HYPERLINK("#'Settings'!A1", "Settings")
A27: Hand-off ready. Print Consolidated P&L + K-1 Worksheet for your CPA — questions to hello@thestrledger.com.
A30: Questions? hello@thestrledger.com
A31: FIN-006 · v1.0 · BLANK · Free updates forever

Sheet Entity Setup
A2: =HYPERLINK("#'Start'!A1", "← BACK") | D2: ENTITY SETUP | J2: =HYPERLINK("#'Per-Entity P&L'!A1", "NEXT →")
A4: One row per LLC (capacity 10). Entity name drives the dropdowns on Per-Entity P&L, Intercompany, and K-1 Worksheet.
A5: Entity name | B5: EIN | C5: State of formation | D5: Property assigned | E5: Registered agent | F5: Tax classification | G5: Members | H5: Notes

Sheet Per-Entity P&L
A2: =HYPERLINK("#'Entity Setup'!A1", "← BACK") | D2: PER-ENTITY P&L | J2: =HYPERLINK("#'Intercompany'!A1", "NEXT →")
A4: One section per LLC (capacity 5). Each section: revenue + 12 expense lines + NOI, by month. Settings → B5 active tax year drives the period.
A6: =IF('Entity Setup'!A6="","(Entity slot 1 — empty)","ENTITY: "&'Entity Setup'!A6)
A7: Category | B7: Jan | C7: Feb | D7: Mar | E7: Apr | F7: May | G7: Jun | H7: Jul | I7: Aug | J7: Sep | K7: Oct | L7: Nov | M7: Dec | N7: YTD
A8: Revenue (rents + fees) | N8: =SUM(B8:M8)
A9: Advertising | N9: =SUM(B9:M9)
A10: Cleaning + maintenance | N10: =SUM(B10:M10)
A11: Insurance | N11: =SUM(B11:M11)
A12: Legal + professional | N12: =SUM(B12:M12)
A13: Management fees (intercompany) | N13: =SUM(B13:M13)
A14: Mortgage interest | N14: =SUM(B14:M14)
A15: Repairs | N15: =SUM(B15:M15)
A16: Supplies | N16: =SUM(B16:M16)
A17: Property taxes | N17: =SUM(B17:M17)
A18: Utilities | N18: =SUM(B18:M18)
A19: Platform fees | N19: =SUM(B19:M19)
A20: Other | N20: =SUM(B20:M20)
A21: TOTAL EXPENSES | B21: =SUM(B9:B20) | C21: =SUM(C9:C20) | D21: =SUM(D9:D20) | E21: =SUM(E9:E20) | F21: =SUM(F9:F20) | G21: =SUM(G9:G20) | H21: =SUM(H9:H20) | I21: =SUM(I9:I20) | ... N21: =SUM(N9:N20)
A22: NOI (Revenue − Expenses) | B22: =B8-B21 | C22: =C8-C21 | D22: =D8-D21 | E22: =E8-E21 | F22: =F8-F21 | G22: =G8-G21 | H22: =H8-H21 | I22: =I8-I21 | ... N22: =N8-N21
A28: =IF('Entity Setup'!A7="","(Entity slot 2 — empty)","ENTITY: "&'Entity Setup'!A7)
A29: Category | B29: Jan | C29: Feb | D29: Mar | E29: Apr | F29: May | G29: Jun | H29: Jul | I29: Aug | J29: Sep | K29: Oct | L29: Nov | M29: Dec | N29: YTD
A30: Revenue (rents + fees) | N30: =SUM(B30:M30)
A31: Advertising | N31: =SUM(B31:M31)
A32: Cleaning + maintenance | N32: =SUM(B32:M32)
A33: Insurance | N33: =SUM(B33:M33)
A34: Legal + professional | N34: =SUM(B34:M34)
A35: Management fees (intercompany) | N35: =SUM(B35:M35)
A36: Mortgage interest | N36: =SUM(B36:M36)
A37: Repairs | N37: =SUM(B37:M37)
A38: Supplies | N38: =SUM(B38:M38)
A39: Property taxes | N39: =SUM(B39:M39)
A40: Utilities | N40: =SUM(B40:M40)
A41: Platform fees | N41: =SUM(B41:M41)
A42: Other | N42: =SUM(B42:M42)
A43: TOTAL EXPENSES | B43: =SUM(B31:B42) | C43: =SUM(C31:C42) | D43: =SUM(D31:D42) | E43: =SUM(E31:E42) | F43: =SUM(F31:F42) | G43: =SUM(G31:G42) | H43: =SUM(H31:H42) | I43: =SUM(I31:I42) | ... N43: =SUM(N31:N42)
A44: NOI (Revenue − Expenses) | B44: =B30-B43 | C44: =C30-C43 | D44: =D30-D43 | E44: =E30-E43 | F44: =F30-F43 | G44: =G30-G43 | H44: =H30-H43 | I44: =I30-I43 | ... N44: =N30-N43
A50: =IF('Entity Setup'!A8="","(Entity slot 3 — empty)","ENTITY: "&'Entity Setup'!A8)
A51: Category | B51: Jan | C51: Feb | D51: Mar | E51: Apr | F51: May | G51: Jun | H51: Jul | I51: Aug | J51: Sep | K51: Oct | L51: Nov | M51: Dec | N51: YTD
A52: Revenue (rents + fees) | N52: =SUM(B52:M52)
A53: Advertising | N53: =SUM(B53:M53)
A54: Cleaning + maintenance | N54: =SUM(B54:M54)
A55: Insurance | N55: =SUM(B55:M55)
A56: Legal + professional | N56: =SUM(B56:M56)
A57: Management fees (intercompany) | N57: =SUM(B57:M57)
A58: Mortgage interest | N58: =SUM(B58:M58)
A59: Repairs | N59: =SUM(B59:M59)
A60: Supplies | N60: =SUM(B60:M60)
A61: Property taxes | N61: =SUM(B61:M61)
A62: Utilities | N62: =SUM(B62:M62)
A63: Platform fees | N63: =SUM(B63:M63)
A64: Other | N64: =SUM(B64:M64)
A65: TOTAL EXPENSES | B65: =SUM(B53:B64) | C65: =SUM(C53:C64) | D65: =SUM(D53:D64) | E65: =SUM(E53:E64) | F65: =SUM(F53:F64) | G65: =SUM(G53:G64) | H65: =SUM(H53:H64) | I65: =SUM(I53:I64) | ... N65: =SUM(N53:N64)
A66: NOI (Revenue − Expenses) | B66: =B52-B65 | C66: =C52-C65 | D66: =D52-D65 | E66: =E52-E65 | F66: =F52-F65 | G66: =G52-G65 | H66: =H52-H65 | I66: =I52-I65 | ... N66: =N52-N65
A72: =IF('Entity Setup'!A9="","(Entity slot 4 — empty)","ENTITY: "&'Entity Setup'!A9)
A73: Category | B73: Jan | C73: Feb | D73: Mar | E73: Apr | F73: May | G73: Jun | H73: Jul | I73: Aug | J73: Sep | K73: Oct | L73: Nov | M73: Dec | N73: YTD
A74: Revenue (rents + fees) | N74: =SUM(B74:M74)
A75: Advertising | N75: =SUM(B75:M75)
A76: Cleaning + maintenance | N76: =SUM(B76:M76)
A77: Insurance | N77: =SUM(B77:M77)
A78: Legal + professional | N78: =SUM(B78:M78)
A79: Management fees (intercompany) | N79: =SUM(B79:M79)
A80: Mortgage interest | N80: =SUM(B80:M80)
A81: Repairs | N81: =SUM(B81:M81)
A82: Supplies | N82: =SUM(B82:M82)
A83: Property taxes | N83: =SUM(B83:M83)
A84: Utilities | N84: =SUM(B84:M84)
A85: Platform fees | N85: =SUM(B85:M85)
A86: Other | N86: =SUM(B86:M86)
A87: TOTAL EXPENSES | B87: =SUM(B75:B86) | C87: =SUM(C75:C86) | D87: =SUM(D75:D86) | E87: =SUM(E75:E86) | F87: =SUM(F75:F86) | G87: =SUM(G75:G86) | H87: =SUM(H75:H86) | I87: =SUM(I75:I86) | ... N87: =SUM(N75:N86)
A88: NOI (Revenue − Expenses) | B88: =B74-B87 | C88: =C74-C87 | D88: =D74-D87 | E88: =E74-E87 | F88: =F74-F87 | G88: =G74-G87 | H88: =H74-H87 | I88: =I74-I87 | ... N88: =N74-N87
A94: =IF('Entity Setup'!A10="","(Entity slot 5 — empty)","ENTITY: "&'Entity Setup'!A10)
A95: Category | B95: Jan | C95: Feb | D95: Mar | E95: Apr | F95: May | G95: Jun | H95: Jul | I95: Aug | J95: Sep | K95: Oct | L95: Nov | M95: Dec | N95: YTD
A96: Revenue (rents + fees) | N96: =SUM(B96:M96)
A97: Advertising | N97: =SUM(B97:M97)
A98: Cleaning + maintenance | N98: =SUM(B98:M98)
A99: Insurance | N99: =SUM(B99:M99)
A100: Legal + professional | N100: =SUM(B100:M100)
A101: Management fees (intercompany) | N101: =SUM(B101:M101)
A102: Mortgage interest | N102: =SUM(B102:M102)
A103: Repairs | N103: =SUM(B103:M103)
A104: Supplies | N104: =SUM(B104:M104)
A105: Property taxes | N105: =SUM(B105:M105)
A106: Utilities | N106: =SUM(B106:M106)
A107: Platform fees | N107: =SUM(B107:M107)
A108: Other | N108: =SUM(B108:M108)
A109: TOTAL EXPENSES | B109: =SUM(B97:B108) | C109: =SUM(C97:C108) | D109: =SUM(D97:D108) | E109: =SUM(E97:E108) | F109: =SUM(F97:F108) | G109: =SUM(G97:G108) | H109: =SUM(H97:H108) | I109: =SUM(I97:I108) | ... N109: =SUM(N97:N108)
A110: NOI (Revenue − Expenses) | B110: =B96-B109 | C110: =C96-C109 | D110: =D96-D109 | E110: =E96-E109 | F110: =F96-F109 | G110: =G96-G109 | H110: =H96-H109 | I110: =I96-I109 | ... N110: =N96-N109

Sheet Intercompany
A2: =HYPERLINK("#'Per-Entity P&L'!A1", "← BACK") | D2: INTERCOMPANY | J2: =HYPERLINK("#'Consolidated P&L'!A1", "NEXT →")
A4: Eliminations register (capacity 30). Management fees, shared-service allocations, inter-LLC loans. 'Eliminated at consolidation?' = Yes removes the entry from the Consolidated P&L.
A5: Date | B5: From entity | C5: To entity | D5: Description | E5: Amount | F5: Type | G5: Eliminated?
A37: ELIMINATED TOTAL (Type=Mgmt fee, Eliminated=Yes): | E37: =SUMIFS(E6:E35,F6:F35,"Management fee",G6:G35,"Yes")

Sheet Consolidated P&L
A2: =HYPERLINK("#'Intercompany'!A1", "← BACK") | D2: CONSOLIDATED P&L | J2: =HYPERLINK("#'Member Distributions'!A1", "NEXT →")
A4: Holding-company-level roll-up. Sum of entity P&Ls minus intercompany eliminations. Print-ready for CPA hand-off. Tax year: Settings → B5.
A5: Category | B5: Consolidated YTD | D5: ="For tax year "&Settings!$B$5
A7: Revenue (rents + fees) | B7: ='Per-Entity P&L'!N8+'Per-Entity P&L'!N30+'Per-Entity P&L'!N52+'Per-Entity P&L'!N74+'Per-Entity P&L'!N96 | D7: READ-OUT NOTES • Pre-elim NOI sums every entity's net. • Symmetric intercompany activity (mgmt fee charged AND paid) nets to zero at consolidation. • If you only recorded one side of an intercompany, adjust the Eliminations row manually. • Print this tab + the K-1 Worksheet for your CPA hand-off.
A9: EXPENSES
A10: Advertising | B10: ='Per-Entity P&L'!N9+'Per-Entity P&L'!N31+'Per-Entity P&L'!N53+'Per-Entity P&L'!N75+'Per-Entity P&L'!N97
A11: Cleaning + maintenance | B11: ='Per-Entity P&L'!N10+'Per-Entity P&L'!N32+'Per-Entity P&L'!N54+'Per-Entity P&L'!N76+'Per-Entity P&L'!N98
A12: Insurance | B12: ='Per-Entity P&L'!N11+'Per-Entity P&L'!N33+'Per-Entity P&L'!N55+'Per-Entity P&L'!N77+'Per-Entity P&L'!N99
A13: Legal + professional | B13: ='Per-Entity P&L'!N12+'Per-Entity P&L'!N34+'Per-Entity P&L'!N56+'Per-Entity P&L'!N78+'Per-Entity P&L'!N100
A14: Management fees (intercompany) | B14: ='Per-Entity P&L'!N13+'Per-Entity P&L'!N35+'Per-Entity P&L'!N57+'Per-Entity P&L'!N79+'Per-Entity P&L'!N101
A15: Mortgage interest | B15: ='Per-Entity P&L'!N14+'Per-Entity P&L'!N36+'Per-Entity P&L'!N58+'Per-Entity P&L'!N80+'Per-Entity P&L'!N102
A16: Repairs | B16: ='Per-Entity P&L'!N15+'Per-Entity P&L'!N37+'Per-Entity P&L'!N59+'Per-Entity P&L'!N81+'Per-Entity P&L'!N103
A17: Supplies | B17: ='Per-Entity P&L'!N16+'Per-Entity P&L'!N38+'Per-Entity P&L'!N60+'Per-Entity P&L'!N82+'Per-Entity P&L'!N104
A18: Property taxes | B18: ='Per-Entity P&L'!N17+'Per-Entity P&L'!N39+'Per-Entity P&L'!N61+'Per-Entity P&L'!N83+'Per-Entity P&L'!N105
A19: Utilities | B19: ='Per-Entity P&L'!N18+'Per-Entity P&L'!N40+'Per-Entity P&L'!N62+'Per-Entity P&L'!N84+'Per-Entity P&L'!N106
A20: Platform fees | B20: ='Per-Entity P&L'!N19+'Per-Entity P&L'!N41+'Per-Entity P&L'!N63+'Per-Entity P&L'!N85+'Per-Entity P&L'!N107
A21: Other | B21: ='Per-Entity P&L'!N20+'Per-Entity P&L'!N42+'Per-Entity P&L'!N64+'Per-Entity P&L'!N86+'Per-Entity P&L'!N108
A22: TOTAL EXPENSES (pre-elimination) | B22: =SUM(B10:B21)
A23: Pre-elimination NOI | B23: =B7-B22
A24: Less: intercompany eliminations | B24: =SUMIFS(Intercompany!E6:E35,Intercompany!G6:G35,"Yes")
A25: CONSOLIDATED NOI | B25: =B23

Sheet Member Distributions
A2: =HYPERLINK("#'Consolidated P&L'!A1", "← BACK") | D2: MEMBER DISTRIBUTIONS | J2: =HYPERLINK("#'K-1 Worksheet'!A1", "NEXT →")
A4: Cash distributions to members across all entities. Rows pull from Settings → Member List. YTD totals roll up to Start tab.
A5: Member | B5: Jan | C5: Feb | D5: Mar | E5: Apr | F5: May | G5: Jun | H5: Jul | I5: Aug | J5: Sep | K5: Oct | L5: Nov | M5: Dec | N5: YTD
A6: =IFERROR(Settings!B18,"") | N6: =SUM(B6:M6)
A7: =IFERROR(Settings!B19,"") | N7: =SUM(B7:M7)
A8: =IFERROR(Settings!B20,"") | N8: =SUM(B8:M8)
A9: =IFERROR(Settings!B21,"") | N9: =SUM(B9:M9)
A10: =IFERROR(Settings!B22,"") | N10: =SUM(B10:M10)
A11: =IFERROR(Settings!B23,"") | N11: =SUM(B11:M11)
A12: =IFERROR(Settings!B24,"") | N12: =SUM(B12:M12)
A13: =IFERROR(Settings!B25,"") | N13: =SUM(B13:M13)
A14: =IFERROR(Settings!B26,"") | N14: =SUM(B14:M14)
A15: =IFERROR(Settings!B27,"") | N15: =SUM(B15:M15)
A17: TOTAL DISTRIBUTIONS | B17: =SUM(B6:B15) | C17: =SUM(C6:C15) | D17: =SUM(D6:D15) | E17: =SUM(E6:E15) | F17: =SUM(F6:F15) | G17: =SUM(G6:G15) | H17: =SUM(H6:H15) | I17: =SUM(I6:I15) | ... N17: =SUM(N6:N15)

Sheet K-1 Worksheet
A2: =HYPERLINK("#'Member Distributions'!A1", "← BACK") | D2: K-1 WORKSHEET | J2: =HYPERLINK("#'Settings'!A1", "NEXT →")
A4: CPA HAND-OFF NOTICE — These are working figures, NOT a filed K-1. Schedule K-1 (Form 1065) preparation is your CPA's job. The numbers below show your share of each LLC's ordinary income and distributions for the active tax year on Settings → B5. Hand this tab to your CPA.
A6: Tax year: (see Settings) · Ordinary income = Member % × Entity NOI · Distributions pulled from Member Distributions tab
A7: Member | B7: Entity | C7: Ownership % | D7: Entity NOI (YTD) | E7: Allocated ordinary income | F7: Distributions YTD | G7: Capital balance (manual) | H7: Notes
A30: K-1 prep is the CPA's job. Working figures only — does NOT account for guaranteed payments, basis adjustments, special allocations, or passive-activity loss limitations. Provide this sheet plus the Consolidated P&L to your CPA.

Sheet Settings
A2: =HYPERLINK("#'K-1 Worksheet'!A1", "← BACK") | D2: SETTINGS
A4: Active tax year drives all P&L formulas. Member list feeds the K-1 Worksheet and Member Distributions dropdowns.
A5: Active tax year: | B5: =YEAR(TODAY()) | D5: Type the tax year here. All consolidation tabs filter by this.
A7: ENTITY LIST (mirrors Entity Setup col A)
B8: =IFERROR('Entity Setup'!A6,"")
B9: =IFERROR('Entity Setup'!A7,"")
B10: =IFERROR('Entity Setup'!A8,"")
B11: =IFERROR('Entity Setup'!A9,"")
B12: =IFERROR('Entity Setup'!A10,"")
B13: =IFERROR('Entity Setup'!A11,"")
B14: =IFERROR('Entity Setup'!A12,"")
B15: =IFERROR('Entity Setup'!A13,"")
B16: =IFERROR('Entity Setup'!A14,"")
B17: =IFERROR('Entity Setup'!A15,"")
A19: MEMBER LIST (Name | last4 | role)
B20: Name | D20: EIN/SSN last4 | E20: Role
A34: Questions? hello@thestrledger.com
A35: FIN-006 · v1.0 · BLANK · Free updates forever
