Workbook

Sheet Start
A2: The STR Ledger
A4: Partnership Distribution Tracker
A5: K-1 Item L numbers, ready for your tax preparer in February.
A7: FIN-007 · v2.3 · DEMO
A10: WHAT THIS DOES
A11: For STR partnerships (LLC taxed as a partnership, not single-member). Tracks capital contributions, profit/loss allocation by ownership %, distributions paid, and ending capital account per partner. The five K-1 Item L numbers — beginning capital, contributions, profit allocated, distributions, ending capital — drop straight onto Schedule K-1 for each partner. Ownership % checksum flags the moment the roster drifts off 100%.
A18: HOW TO USE
A19: ① Settings: set the active tax year, partnership name, EIN, and allocation method.
A20: ② Partners: enter every partner — name, ownership %, beginning capital. % MUST sum to 100.
A21: ③ Capital Contributions: log each new contribution as it happens (date, partner, amount, type).
A22: ④ Distributions: log every distribution paid (date, partner, amount, type, source entity).
A23: ⑤ P&L Allocation: enter annual partnership net income — per-partner allocation auto-computes.
A24: ⑥ February: hand the Partners tab + P&L Allocation to your tax preparer for K-1s.
A27: =HYPERLINK("#'Distributions'!A6", "→ ADD A DISTRIBUTION (OPEN DISTRIBUTIONS)")
A32: PARTNERS | E32: DISTRIBUTIONS YTD | I32: TOTAL ENDING CAPITAL
A33: =COUNTA(Partners!B6:B13) | E33: =SUM(Distributions!C6:C205) | I33: =SUM(Partners!I6:I13)
A35: rows on the Partners tab | E35: all partners, current year | I35: sum of partner capital accounts
A39: =HYPERLINK("#'Partners'!A1", "Partners") | D39: =HYPERLINK("#'Capital Contributions'!A1", "Capital Contributions") | G39: =HYPERLINK("#'P&L Allocation'!A1", "P&L Allocation") | J39: =HYPERLINK("#'Settings'!A1", "Settings")
A42: 📅 K-1 PREP: in February, the Partners tab shows the five Item L numbers for each partner — beginning capital, contributions, profit allocated, distributions, ending capital. Hand it to your tax preparer.
A44: ⚠ Ownership % across all partners must equal 100%. The Partners tab shows a checksum — fix it before relying on the P&L allocation.
A46: 💡 Upgrade to the Full version at thestrledger.com/upgrade — multi-property, depreciation, multi-LLC support.
A49: Questions? hello@thestrledger.com
A50: FIN-007 · v2.3 · Free updates forever

Sheet Partners
A2: =HYPERLINK("#'Start'!A1", "← BACK") | D2: PARTNERS | J2: =HYPERLINK("#'Capital Contributions'!A1", "NEXT →")
A4: Partner roster (capacity 8) — % must sum to 100. Five K-1 Item L numbers per row.
A5: Partner # | B5: Partner name | C5: Tax ID last4 | D5: Ownership % | E5: Beginning capital (Jan 1) | F5: Contributions YTD | G5: Profit allocated YTD | H5: Distributions YTD | I5: Ending capital | J5: Notes
A6: 1 | B6: Daniel Harrison | C6: 1234 | D6: 0.6 | E6: 80000 | F6: =IF(B6="","",SUMIFS('Capital Contributions'!$C$6:$C$105,'Capital Contributions'!$B$6:$B$105,B6)) | G6: =IF(B6="","",IFERROR(VLOOKUP(B6,'P&L Allocation'!$A$8:$D$15,4,FALSE),0)) | H6: =IF(B6="","",SUMIFS(Distributions!$C$6:$C$205,Distributions!$B$6:$B$205,B6)) | I6: =IF(B6="","",E6+F6+G6-H6) | J6: Managing partner
A7: 2 | B7: Jordan Reeves | C7: 5678 | D7: 0.4 | E7: 40000 | F7: =IF(B7="","",SUMIFS('Capital Contributions'!$C$6:$C$105,'Capital Contributions'!$B$6:$B$105,B7)) | G7: =IF(B7="","",IFERROR(VLOOKUP(B7,'P&L Allocation'!$A$8:$D$15,4,FALSE),0)) | H7: =IF(B7="","",SUMIFS(Distributions!$C$6:$C$205,Distributions!$B$6:$B$205,B7)) | I7: =IF(B7="","",E7+F7+G7-H7) | J7: Capital partner
A8: 3 | F8: =IF(B8="","",SUMIFS('Capital Contributions'!$C$6:$C$105,'Capital Contributions'!$B$6:$B$105,B8)) | G8: =IF(B8="","",IFERROR(VLOOKUP(B8,'P&L Allocation'!$A$8:$D$15,4,FALSE),0)) | H8: =IF(B8="","",SUMIFS(Distributions!$C$6:$C$205,Distributions!$B$6:$B$205,B8)) | I8: =IF(B8="","",E8+F8+G8-H8)
A9: 4 | F9: =IF(B9="","",SUMIFS('Capital Contributions'!$C$6:$C$105,'Capital Contributions'!$B$6:$B$105,B9)) | G9: =IF(B9="","",IFERROR(VLOOKUP(B9,'P&L Allocation'!$A$8:$D$15,4,FALSE),0)) | H9: =IF(B9="","",SUMIFS(Distributions!$C$6:$C$205,Distributions!$B$6:$B$205,B9)) | I9: =IF(B9="","",E9+F9+G9-H9)
A10: 5 | F10: =IF(B10="","",SUMIFS('Capital Contributions'!$C$6:$C$105,'Capital Contributions'!$B$6:$B$105,B10)) | G10: =IF(B10="","",IFERROR(VLOOKUP(B10,'P&L Allocation'!$A$8:$D$15,4,FALSE),0)) | H10: =IF(B10="","",SUMIFS(Distributions!$C$6:$C$205,Distributions!$B$6:$B$205,B10)) | I10: =IF(B10="","",E10+F10+G10-H10)
A11: 6 | F11: =IF(B11="","",SUMIFS('Capital Contributions'!$C$6:$C$105,'Capital Contributions'!$B$6:$B$105,B11)) | G11: =IF(B11="","",IFERROR(VLOOKUP(B11,'P&L Allocation'!$A$8:$D$15,4,FALSE),0)) | H11: =IF(B11="","",SUMIFS(Distributions!$C$6:$C$205,Distributions!$B$6:$B$205,B11)) | I11: =IF(B11="","",E11+F11+G11-H11)
A12: 7 | F12: =IF(B12="","",SUMIFS('Capital Contributions'!$C$6:$C$105,'Capital Contributions'!$B$6:$B$105,B12)) | G12: =IF(B12="","",IFERROR(VLOOKUP(B12,'P&L Allocation'!$A$8:$D$15,4,FALSE),0)) | H12: =IF(B12="","",SUMIFS(Distributions!$C$6:$C$205,Distributions!$B$6:$B$205,B12)) | I12: =IF(B12="","",E12+F12+G12-H12)
A13: 8 | F13: =IF(B13="","",SUMIFS('Capital Contributions'!$C$6:$C$105,'Capital Contributions'!$B$6:$B$105,B13)) | G13: =IF(B13="","",IFERROR(VLOOKUP(B13,'P&L Allocation'!$A$8:$D$15,4,FALSE),0)) | H13: =IF(B13="","",SUMIFS(Distributions!$C$6:$C$205,Distributions!$B$6:$B$205,B13)) | I13: =IF(B13="","",E13+F13+G13-H13)
D15: =SUM(D6:D13) | E15: =IF(ROUND(D15,4)=1,"✓ OK","⚠ FIX — must equal 100%")
A17: K-1 Item L summary — these five numbers per partner
A18: Beginning capital · Contributions · Profit allocated · Distributions · Ending capital → drop straight onto Schedule K-1.

Sheet Capital Contributions
A2: =HYPERLINK("#'Partners'!A1", "← BACK") | D2: CAPITAL CONTRIBUTIONS | J2: =HYPERLINK("#'Distributions'!A1", "NEXT →")
A4: Log every contribution AS IT HAPPENS — date, partner, amount, type, notes.
A5: Date | B5: Partner | C5: Amount | D5: Type | E5: Notes
A6: 46037 | B6: Daniel Harrison | C6: 5000 | D6: Cash | E6: Working capital top-up
A7: 46103 | B7: Jordan Reeves | C7: 2500 | D7: Cash | E7: Furnishing budget
A8: 46183 | B8: Daniel Harrison | C8: 3000 | D8: Property contribution | E8: Tools + outdoor furniture

Sheet Distributions
A2: =HYPERLINK("#'Capital Contributions'!A1", "← BACK") | D2: DISTRIBUTIONS | J2: =HYPERLINK("#'P&L Allocation'!A1", "NEXT →")
A4: Log every distribution paid — date, partner, amount, type, source entity.
A5: Date | B5: Partner | C5: Amount | D5: Type | E5: Source entity | F5: Notes
A6: 46112 | B6: Daniel Harrison | C6: 4500 | D6: Cash | E6: Smokies Ridge LLC | F6: Q1 distribution
A7: 46112 | B7: Jordan Reeves | C7: 3000 | D7: Cash | E7: Smokies Ridge LLC | F7: Q1 distribution
A8: 46203 | B8: Daniel Harrison | C8: 4500 | D8: Cash | E8: Smokies Ridge LLC | F8: Q2 distribution
A9: 46203 | B9: Jordan Reeves | C9: 3000 | D9: Cash | E9: Smokies Ridge LLC | F9: Q2 distribution
A10: 46295 | B10: Daniel Harrison | C10: 4500 | D10: Cash | E10: Smokies Ridge LLC | F10: Q3 distribution
A11: 46295 | B11: Jordan Reeves | C11: 3000 | D11: Cash | E11: Smokies Ridge LLC | F11: Q3 distribution
A12: 46371 | B12: Daniel Harrison | C12: 4500 | D12: Tax distribution | E12: Smokies Ridge LLC | F12: Q4 + tax distribution
A13: 46371 | B13: Jordan Reeves | C13: 3000 | D13: Tax distribution | E13: Smokies Ridge LLC | F13: Q4 + tax distribution

Sheet P&L Allocation
A2: =HYPERLINK("#'Distributions'!A1", "← BACK") | D2: P&L ALLOCATION · FOR YOUR CPA | J2: =HYPERLINK("#'Settings'!A1", "NEXT →")
A4: 📄 FOR YOUR CPA — annual partnership net income allocated by ownership %.
A5: Annual partnership net income: | B5: 36000
A6: Special allocations (e.g., guaranteed payments): | B6: 0
A7: Partner | B7: Ownership % | C7: Pro-rata share | D7: Final allocated income | E7: Notes
A8: =IF(Partners!B6="","",Partners!B6) | B8: =IF(Partners!B6="","",Partners!D6) | C8: =IF(A8="","",($B$5-$B$6)*B8) | D8: =IF(A8="","",C8)
A9: =IF(Partners!B7="","",Partners!B7) | B9: =IF(Partners!B7="","",Partners!D7) | C9: =IF(A9="","",($B$5-$B$6)*B9) | D9: =IF(A9="","",C9)
A10: =IF(Partners!B8="","",Partners!B8) | B10: =IF(Partners!B8="","",Partners!D8) | C10: =IF(A10="","",($B$5-$B$6)*B10) | D10: =IF(A10="","",C10)
A11: =IF(Partners!B9="","",Partners!B9) | B11: =IF(Partners!B9="","",Partners!D9) | C11: =IF(A11="","",($B$5-$B$6)*B11) | D11: =IF(A11="","",C11)
A12: =IF(Partners!B10="","",Partners!B10) | B12: =IF(Partners!B10="","",Partners!D10) | C12: =IF(A12="","",($B$5-$B$6)*B12) | D12: =IF(A12="","",C12)
A13: =IF(Partners!B11="","",Partners!B11) | B13: =IF(Partners!B11="","",Partners!D11) | C13: =IF(A13="","",($B$5-$B$6)*B13) | D13: =IF(A13="","",C13)
A14: =IF(Partners!B12="","",Partners!B12) | B14: =IF(Partners!B12="","",Partners!D12) | C14: =IF(A14="","",($B$5-$B$6)*B14) | D14: =IF(A14="","",C14)
A15: =IF(Partners!B13="","",Partners!B13) | B15: =IF(Partners!B13="","",Partners!D13) | C15: =IF(A15="","",($B$5-$B$6)*B15) | D15: =IF(A15="","",C15)
A16: TOTAL | B16: =SUM(B8:B15) | C16: =SUM(C8:C15) | D16: =SUM(D8:D15)

Sheet Settings
A2: =HYPERLINK("#'P&L Allocation'!A1", "← BACK") | D2: SETTINGS
A4: Active tax year · partnership info · allocation method
A5: Active tax year: | B5: 2026
A6: Active year drives every YTD calculation and the K-1 Item L summary. Update each January when starting a new tax year.
A7: Partnership name: | B7: Smokies Ridge Holdings LLC
A9: EIN: | B9: XX-XXXXXXX
A11: Allocation method: | B11: Pro-rata by ownership
A13: Partner count (auto): | B13: =COUNTA(Partners!B6:B13)
A15: K-1 Item L summary (per partner)
A16: These five numbers per partner go directly to K-1 Item L. See the Partners tab for the live values.
A17: Beginning capital (total): | B17: =SUM(Partners!E6:Partners!E13)
A18: Contributions (total): | B18: =SUM(Partners!F6:Partners!F13)
A19: Profit allocated (total): | B19: =SUM(Partners!G6:Partners!G13)
A20: Distributions (total): | B20: =SUM(Partners!H6:Partners!H13)
A21: Ending capital (total): | B21: =SUM(Partners!I6:Partners!I13)
