Workbook

Sheet Start
A2: The STR Ledger
A4: Break-even Occupancy Calculator
A5: How empty can it get before you're losing money?
A7: FIN-002 · v1.0
A11: =IF(Calculator!C7="","(enter property name on Calculator tab)",Calculator!C7)
A13: BREAK-EVEN OCCUPANCY
A14: =Calculator!C47
A16: ="= "&ROUND(Calculator!C46,0)&" booked nights/year (~"&ROUND(Calculator!C46/12,1)&"/month)"
A18: Your current occupancy: | G18: 0.62 | I18: =IF(G18="","(enter your %)","")
A20: =IF(G18="","",IF(G18>=Calculator!C47,"✅ Margin = "&TEXT(G18-Calculator!C47,"0%")&" above break-even","⚠ Below break-even by "&TEXT(Calculator!C47-G18,"0%")))
A22: Note: this break-even covers operating costs + mortgage interest. It does NOT cover principal paydown or your time. True cash break-even is higher — re-run when costs change (insurance bumps, cleaner rate, refi).
A25: =HYPERLINK("#'Calculator'!A1", "→ Open Calculator") | G25: =HYPERLINK("#'Sensitivity'!A1", "Sensitivity Table")
A30: 💡 Want the full P&L picture? Get the Single-Property P&L Tracker (TAX-002) at thestrledger.com — Schedule E-ready, $47.
A33: Questions? hello@thestrledger.com
A34: FIN-002 · v1.0 · Free updates forever

Sheet Calculator
A2: =HYPERLINK("#'Start'!A1", "← BACK") | D2: CALCULATOR | J2: =HYPERLINK("#'Sensitivity'!A1", "NEXT →")
A4: All inputs on one page. Yellow = edit; gray = calculated.
A6: REVENUE ASSUMPTIONS
B7: Property name: | C7: Smokies Ridge Cabin | E7: (used in Start tab headline)
B8: (name shown above) | C8: =B7
B9: ADR — Avg nightly rate ($): | C9: 245 | E9: Gross nightly rate (commission applied below)
B10: Cleaning fee charged to guest ($): | C10: 150 | E10: What guest pays — host nets the spread vs. cleaning paid
B11: Avg length of stay (nights): | C11: 3.2 | E11: 1.5-7 typical; affects per-night variable cost
B12: Available nights/year: | C12: 350 | E12: 365 minus blocked (personal use, maintenance, owner stays)
B13: Platform commission (%): | C13: 0.15 | E13: Airbnb 15%, VRBO 8%, direct 0-3%
A15: ANNUAL FIXED COSTS
B16: Mortgage interest (annual, $): | C16: 4800 | E16: Interest only — principal is excluded from break-even
B17: Property tax (annual, $): | C17: 4800
B18: Insurance (annual, $): | C18: 2400 | E18: Including STR rider
B19: HOA / Condo fees (annual, $): | C19: 0
B20: Utilities (annual, $): | C20: 2160 | E20: Electric, gas, water, trash combined
B21: Internet (annual, $): | C21: 960
B22: PMS / Software (annual, $): | C22: 480 | E22: Hospitable, Hostfully, OwnerRez, etc.
B23: Marketing / photos (annual, $): | C23: 600 | E23: Photo refresh, listing fees
B24: Other fixed #1 (annual, $): | C24: 0 | E24: Label this if used
B25: Other fixed #2 (annual, $): | C25: 0
A28: PER-TURNOVER VARIABLE COSTS
B29: Cleaning paid to cleaner ($/turnover): | C29: 150
B30: Supplies ($/turnover): | C30: 25 | E30: Toiletries, paper, coffee top-ups
B31: Maintenance reserve ($/turnover): | C31: 12 | E31: Per-booking allocation; 5-8% of revenue typical
B32: Other variable ($/turnover): | C32: 0
A34: 📋 PULL FROM YOUR TAX-002 P&L
A35: If you own TAX-002 Single-Property P&L Tracker, your annual fixed costs map cleanly: Schedule E lines 13 (mortgage int), 17 (taxes), 10 (insurance), 18 (utilities), 19 (Other — software, marketing, etc.). Cleaning paid → Schedule E line 8. Supplies → line 16. Open TAX-002, copy YTD totals from the Schedule E Summary tab, annualize if mid-year, paste here.
A39: OUTPUTS — CALCULATED
B40: Total annual fixed costs: | C40: =SUM(C16:C25) | E40: All fixed annual costs combined
B41: Variable cost per turnover: | C41: =SUM(C29:C32) | E41: Cleaning + supplies + reserve + other
B42: Variable cost per night: | C42: =IFERROR(C41/C11,0) | E42: Per-turnover variable ÷ avg LOS
B43: Net revenue per night: | C43: =C9*(1-C13)+C10/C11 | E43: ADR × (1-commission) + cleaning_charged ÷ LOS
B44: Contribution margin per night: | C44: =C43-C42 | E44: Net rev/night − variable/night
B46: BREAK-EVEN NIGHTS / YEAR: | C46: =IFERROR(C40/C44,0) | E46: Nights you must book to cover fixed costs
B47: BREAK-EVEN OCCUPANCY: | C47: =IFERROR(C46/C12,0) | E47: Break-even nights ÷ available nights
A51: Questions? hello@thestrledger.com
A52: FIN-002 · v1.0 · Calculator

Sheet Sensitivity
A2: =HYPERLINK("#'Calculator'!A1", "← BACK") | D2: SENSITIVITY
A4: Annual cash flow at every combination of occupancy × ADR. Red = losing money. Gold = healthy.
B6: Occupancy | C6: ADR -10% | D6: Current ADR | E6: ADR +10%
B7: 0.3 | C7: =(0.3*Calculator!$C$12)*((Calculator!$C$9*0.9*(1-Calculator!$C$13))+Calculator!$C$10/Calculator!$C$11-(SUM(Calculator!$C$29:$C$32)/Calculator!$C$11))-SUM(Calculator!$C$16:$C$25) | D7: =(0.3*Calculator!$C$12)*((Calculator!$C$9*1.0*(1-Calculator!$C$13))+Calculator!$C$10/Calculator!$C$11-(SUM(Calculator!$C$29:$C$32)/Calculator!$C$11))-SUM(Calculator!$C$16:$C$25) | E7: =(0.3*Calculator!$C$12)*((Calculator!$C$9*1.1*(1-Calculator!$C$13))+Calculator!$C$10/Calculator!$C$11-(SUM(Calculator!$C$29:$C$32)/Calculator!$C$11))-SUM(Calculator!$C$16:$C$25)
B8: 0.4 | C8: =(0.4*Calculator!$C$12)*((Calculator!$C$9*0.9*(1-Calculator!$C$13))+Calculator!$C$10/Calculator!$C$11-(SUM(Calculator!$C$29:$C$32)/Calculator!$C$11))-SUM(Calculator!$C$16:$C$25) | D8: =(0.4*Calculator!$C$12)*((Calculator!$C$9*1.0*(1-Calculator!$C$13))+Calculator!$C$10/Calculator!$C$11-(SUM(Calculator!$C$29:$C$32)/Calculator!$C$11))-SUM(Calculator!$C$16:$C$25) | E8: =(0.4*Calculator!$C$12)*((Calculator!$C$9*1.1*(1-Calculator!$C$13))+Calculator!$C$10/Calculator!$C$11-(SUM(Calculator!$C$29:$C$32)/Calculator!$C$11))-SUM(Calculator!$C$16:$C$25)
B9: 0.5 | C9: =(0.5*Calculator!$C$12)*((Calculator!$C$9*0.9*(1-Calculator!$C$13))+Calculator!$C$10/Calculator!$C$11-(SUM(Calculator!$C$29:$C$32)/Calculator!$C$11))-SUM(Calculator!$C$16:$C$25) | D9: =(0.5*Calculator!$C$12)*((Calculator!$C$9*1.0*(1-Calculator!$C$13))+Calculator!$C$10/Calculator!$C$11-(SUM(Calculator!$C$29:$C$32)/Calculator!$C$11))-SUM(Calculator!$C$16:$C$25) | E9: =(0.5*Calculator!$C$12)*((Calculator!$C$9*1.1*(1-Calculator!$C$13))+Calculator!$C$10/Calculator!$C$11-(SUM(Calculator!$C$29:$C$32)/Calculator!$C$11))-SUM(Calculator!$C$16:$C$25)
B10: 0.6 | C10: =(0.6*Calculator!$C$12)*((Calculator!$C$9*0.9*(1-Calculator!$C$13))+Calculator!$C$10/Calculator!$C$11-(SUM(Calculator!$C$29:$C$32)/Calculator!$C$11))-SUM(Calculator!$C$16:$C$25) | D10: =(0.6*Calculator!$C$12)*((Calculator!$C$9*1.0*(1-Calculator!$C$13))+Calculator!$C$10/Calculator!$C$11-(SUM(Calculator!$C$29:$C$32)/Calculator!$C$11))-SUM(Calculator!$C$16:$C$25) | E10: =(0.6*Calculator!$C$12)*((Calculator!$C$9*1.1*(1-Calculator!$C$13))+Calculator!$C$10/Calculator!$C$11-(SUM(Calculator!$C$29:$C$32)/Calculator!$C$11))-SUM(Calculator!$C$16:$C$25)
B11: 0.7 | C11: =(0.7*Calculator!$C$12)*((Calculator!$C$9*0.9*(1-Calculator!$C$13))+Calculator!$C$10/Calculator!$C$11-(SUM(Calculator!$C$29:$C$32)/Calculator!$C$11))-SUM(Calculator!$C$16:$C$25) | D11: =(0.7*Calculator!$C$12)*((Calculator!$C$9*1.0*(1-Calculator!$C$13))+Calculator!$C$10/Calculator!$C$11-(SUM(Calculator!$C$29:$C$32)/Calculator!$C$11))-SUM(Calculator!$C$16:$C$25) | E11: =(0.7*Calculator!$C$12)*((Calculator!$C$9*1.1*(1-Calculator!$C$13))+Calculator!$C$10/Calculator!$C$11-(SUM(Calculator!$C$29:$C$32)/Calculator!$C$11))-SUM(Calculator!$C$16:$C$25)
B12: 0.8 | C12: =(0.8*Calculator!$C$12)*((Calculator!$C$9*0.9*(1-Calculator!$C$13))+Calculator!$C$10/Calculator!$C$11-(SUM(Calculator!$C$29:$C$32)/Calculator!$C$11))-SUM(Calculator!$C$16:$C$25) | D12: =(0.8*Calculator!$C$12)*((Calculator!$C$9*1.0*(1-Calculator!$C$13))+Calculator!$C$10/Calculator!$C$11-(SUM(Calculator!$C$29:$C$32)/Calculator!$C$11))-SUM(Calculator!$C$16:$C$25) | E12: =(0.8*Calculator!$C$12)*((Calculator!$C$9*1.1*(1-Calculator!$C$13))+Calculator!$C$10/Calculator!$C$11-(SUM(Calculator!$C$29:$C$32)/Calculator!$C$11))-SUM(Calculator!$C$16:$C$25)
A14: Read this grid by finding the ADR / occupancy combination that's realistic for your market. If most of your row is red, your fixed costs are too high relative to your revenue assumptions — re-check the Calculator tab for inflated cost lines, or reconsider the property.
A18: Questions? hello@thestrledger.com
A19: FIN-002 · v1.0 · Sensitivity
