Workbook

Sheet Start
A2: The STR Ledger
A4: DSCR Tracker
A5: Which properties qualify for a DSCR loan refinance?
A7: FIN-004 - v1.0
A11: PORTFOLIO DSCR
A12: =IFERROR(SUMIF('Per-Property'!A8:A17,"<>",'Per-Property'!D8:D17)/SUMIF('Per-Property'!A8:A17,"<>",'Per-Property'!H8:H17),0)
A14: =IF(A12>=Settings!B7,"Portfolio qualifies for DSCR loan refinance",IF(A12>=Settings!B9,"Portfolio is marginal - shop rates carefully","Portfolio is below break-even - debt restructuring needed"))
A16: PROPERTIES QUALIFYING (DSCR >= 1.20) | G16: WEAKEST PROPERTY
A17: =COUNTIFS('Per-Property'!A8:A17,"<>",'Per-Property'!I8:I17,">="&Settings!B7)&" of "&COUNTIF('Per-Property'!A8:A17,"<>") | G17: =IFERROR(INDEX('Per-Property'!A8:A17,MATCH(MINIFS('Per-Property'!I8:I17,'Per-Property'!A8:A17,"<>"),'Per-Property'!I8:I17,0)),"-")
G19: =IFERROR("DSCR = "&TEXT(MINIFS('Per-Property'!I8:I17,'Per-Property'!A8:A17,"<>"),"0.00"),"")
A21: DSCR = Net Operating Income / Annual Debt Service. Most DSCR lenders require >= 1.20 with LTV <= 75%. Below 1.0 means the property doesn't cover its own debt - refinance, restructure, or sell.
A25: =HYPERLINK("#'Per-Property'!A1", "-> Update Inputs") | G25: =HYPERLINK("#'Stress Test'!A1", "Stress Test")
A29: =HYPERLINK("#'Refi Eligibility'!A1", "Refi Eligibility") | G29: =HYPERLINK("#'Settings'!A1", "Settings")
A33: Want full P&L per property? Get TAX-002 Single-Property P&L Tracker at thestrledger.com - Schedule E-ready, $47.
A36: Questions? hello@thestrledger.com
A37: FIN-004 - v1.0 - Free updates forever

Sheet Per-Property
A2: =HYPERLINK("#'Start'!A1", "← BACK") | D2: PER-PROPERTY | J2: =HYPERLINK("#'Stress Test'!A1", "NEXT →")
A4: Yellow = edit; gray = calculated. NOI = Revenue - OpEx (no mortgage). Debt service = mortgage + HELOC + other annual debt.
A7: Property | B7: Annual Gross Revenue | C7: Operating Expenses | D7: NOI | E7: Mortgage P&I (monthly) | F7: Annual Debt Service | G7: Other Annual Debt | H7: Total Debt Service | I7: DSCR | J7: Status
A8: Smokies Ridge Cabin | B8: 90000 | C8: 28000 | D8: =IF(A8="","",B8-C8) | E8: 3640 | F8: =IF(A8="","",E8*12) | G8: 0 | H8: =IF(A8="","",F8+G8) | I8: =IFERROR(IF(A8="","",D8/H8),"") | J8: =IF(A8="","",IF(I8>=Settings!$B$7,"Qualifies",IF(I8>=Settings!$B$9,"Marginal","Negative")))
A9: Lakehouse A | B9: 78000 | C9: 25000 | D9: =IF(A9="","",B9-C9) | E9: 3742.94 | F9: =IF(A9="","",E9*12) | G9: 0 | H9: =IF(A9="","",F9+G9) | I9: =IFERROR(IF(A9="","",D9/H9),"") | J9: =IF(A9="","",IF(I9>=Settings!$B$7,"Qualifies",IF(I9>=Settings!$B$9,"Marginal","Negative")))
A10: Creek Side | B10: 52000 | C10: 21500 | D10: =IF(A10="","",B10-C10) | E10: 2704.43 | F10: =IF(A10="","",E10*12) | G10: 0 | H10: =IF(A10="","",F10+G10) | I10: =IFERROR(IF(A10="","",D10/H10),"") | J10: =IF(A10="","",IF(I10>=Settings!$B$7,"Qualifies",IF(I10>=Settings!$B$9,"Marginal","Negative")))
D11: =IF(A11="","",B11-C11) | F11: =IF(A11="","",E11*12) | H11: =IF(A11="","",F11+G11) | I11: =IFERROR(IF(A11="","",D11/H11),"") | J11: =IF(A11="","",IF(I11>=Settings!$B$7,"Qualifies",IF(I11>=Settings!$B$9,"Marginal","Negative")))
D12: =IF(A12="","",B12-C12) | F12: =IF(A12="","",E12*12) | H12: =IF(A12="","",F12+G12) | I12: =IFERROR(IF(A12="","",D12/H12),"") | J12: =IF(A12="","",IF(I12>=Settings!$B$7,"Qualifies",IF(I12>=Settings!$B$9,"Marginal","Negative")))
D13: =IF(A13="","",B13-C13) | F13: =IF(A13="","",E13*12) | H13: =IF(A13="","",F13+G13) | I13: =IFERROR(IF(A13="","",D13/H13),"") | J13: =IF(A13="","",IF(I13>=Settings!$B$7,"Qualifies",IF(I13>=Settings!$B$9,"Marginal","Negative")))
D14: =IF(A14="","",B14-C14) | F14: =IF(A14="","",E14*12) | H14: =IF(A14="","",F14+G14) | I14: =IFERROR(IF(A14="","",D14/H14),"") | J14: =IF(A14="","",IF(I14>=Settings!$B$7,"Qualifies",IF(I14>=Settings!$B$9,"Marginal","Negative")))
D15: =IF(A15="","",B15-C15) | F15: =IF(A15="","",E15*12) | H15: =IF(A15="","",F15+G15) | I15: =IFERROR(IF(A15="","",D15/H15),"") | J15: =IF(A15="","",IF(I15>=Settings!$B$7,"Qualifies",IF(I15>=Settings!$B$9,"Marginal","Negative")))
D16: =IF(A16="","",B16-C16) | F16: =IF(A16="","",E16*12) | H16: =IF(A16="","",F16+G16) | I16: =IFERROR(IF(A16="","",D16/H16),"") | J16: =IF(A16="","",IF(I16>=Settings!$B$7,"Qualifies",IF(I16>=Settings!$B$9,"Marginal","Negative")))
D17: =IF(A17="","",B17-C17) | F17: =IF(A17="","",E17*12) | H17: =IF(A17="","",F17+G17) | I17: =IFERROR(IF(A17="","",D17/H17),"") | J17: =IF(A17="","",IF(I17>=Settings!$B$7,"Qualifies",IF(I17>=Settings!$B$9,"Marginal","Negative")))
A18: PORTFOLIO TOTALS | B18: =SUM(B8:B17) | C18: =SUM(C8:C17) | D18: =SUM(D8:D17) | F18: =SUM(F8:F17) | G18: =SUM(G8:G17) | H18: =SUM(H8:H17) | I18: =IFERROR(D18/H18,0) | J18: =IF(I18>=Settings!$B$7,"Qualifies",IF(I18>=Settings!$B$9,"Marginal","Negative"))
A20: Status: Qualifies = DSCR >= 1.20 (DSCR-loan eligible). Marginal = 1.0 - 1.19 (covers debt but won't pass most DSCR-loan UW). Negative = < 1.0 (property is bleeding cash).
A24: Questions? hello@thestrledger.com
A25: FIN-004 - v1.0 - Per-Property

Sheet Stress Test
A2: =HYPERLINK("#'Per-Property'!A1", "← BACK") | D2: STRESS TEST | J2: =HYPERLINK("#'Refi Eligibility'!A1", "NEXT →")
A4: What happens to DSCR if revenue drops? Operating expenses and debt service stay constant. Watch which properties slip below 1.0.
B6: -10% Revenue | E6: -20% Revenue | H6: -30% Revenue
A7: Property | B7: Stressed Revenue | C7: Stressed NOI | D7: DSCR | E7: Stressed Revenue | F7: Stressed NOI | G7: DSCR | H7: Stressed Revenue | I7: Stressed NOI | J7: DSCR
A8: =IF('Per-Property'!A8="","",'Per-Property'!A8) | B8: =IF(A8="","",'Per-Property'!B8*0.9) | C8: =IF(A8="","",B8-'Per-Property'!C8) | D8: =IFERROR(IF(A8="","",C8/'Per-Property'!H8),"") | E8: =IF(A8="","",'Per-Property'!B8*0.8) | F8: =IF(A8="","",E8-'Per-Property'!C8) | G8: =IFERROR(IF(A8="","",F8/'Per-Property'!H8),"") | H8: =IF(A8="","",'Per-Property'!B8*0.7) | I8: =IF(A8="","",H8-'Per-Property'!C8) | J8: =IFERROR(IF(A8="","",I8/'Per-Property'!H8),"")
A9: =IF('Per-Property'!A9="","",'Per-Property'!A9) | B9: =IF(A9="","",'Per-Property'!B9*0.9) | C9: =IF(A9="","",B9-'Per-Property'!C9) | D9: =IFERROR(IF(A9="","",C9/'Per-Property'!H9),"") | E9: =IF(A9="","",'Per-Property'!B9*0.8) | F9: =IF(A9="","",E9-'Per-Property'!C9) | G9: =IFERROR(IF(A9="","",F9/'Per-Property'!H9),"") | H9: =IF(A9="","",'Per-Property'!B9*0.7) | I9: =IF(A9="","",H9-'Per-Property'!C9) | J9: =IFERROR(IF(A9="","",I9/'Per-Property'!H9),"")
A10: =IF('Per-Property'!A10="","",'Per-Property'!A10) | B10: =IF(A10="","",'Per-Property'!B10*0.9) | C10: =IF(A10="","",B10-'Per-Property'!C10) | D10: =IFERROR(IF(A10="","",C10/'Per-Property'!H10),"") | E10: =IF(A10="","",'Per-Property'!B10*0.8) | F10: =IF(A10="","",E10-'Per-Property'!C10) | G10: =IFERROR(IF(A10="","",F10/'Per-Property'!H10),"") | H10: =IF(A10="","",'Per-Property'!B10*0.7) | I10: =IF(A10="","",H10-'Per-Property'!C10) | J10: =IFERROR(IF(A10="","",I10/'Per-Property'!H10),"")
A11: =IF('Per-Property'!A11="","",'Per-Property'!A11) | B11: =IF(A11="","",'Per-Property'!B11*0.9) | C11: =IF(A11="","",B11-'Per-Property'!C11) | D11: =IFERROR(IF(A11="","",C11/'Per-Property'!H11),"") | E11: =IF(A11="","",'Per-Property'!B11*0.8) | F11: =IF(A11="","",E11-'Per-Property'!C11) | G11: =IFERROR(IF(A11="","",F11/'Per-Property'!H11),"") | H11: =IF(A11="","",'Per-Property'!B11*0.7) | I11: =IF(A11="","",H11-'Per-Property'!C11) | J11: =IFERROR(IF(A11="","",I11/'Per-Property'!H11),"")
A12: =IF('Per-Property'!A12="","",'Per-Property'!A12) | B12: =IF(A12="","",'Per-Property'!B12*0.9) | C12: =IF(A12="","",B12-'Per-Property'!C12) | D12: =IFERROR(IF(A12="","",C12/'Per-Property'!H12),"") | E12: =IF(A12="","",'Per-Property'!B12*0.8) | F12: =IF(A12="","",E12-'Per-Property'!C12) | G12: =IFERROR(IF(A12="","",F12/'Per-Property'!H12),"") | H12: =IF(A12="","",'Per-Property'!B12*0.7) | I12: =IF(A12="","",H12-'Per-Property'!C12) | J12: =IFERROR(IF(A12="","",I12/'Per-Property'!H12),"")
A13: =IF('Per-Property'!A13="","",'Per-Property'!A13) | B13: =IF(A13="","",'Per-Property'!B13*0.9) | C13: =IF(A13="","",B13-'Per-Property'!C13) | D13: =IFERROR(IF(A13="","",C13/'Per-Property'!H13),"") | E13: =IF(A13="","",'Per-Property'!B13*0.8) | F13: =IF(A13="","",E13-'Per-Property'!C13) | G13: =IFERROR(IF(A13="","",F13/'Per-Property'!H13),"") | H13: =IF(A13="","",'Per-Property'!B13*0.7) | I13: =IF(A13="","",H13-'Per-Property'!C13) | J13: =IFERROR(IF(A13="","",I13/'Per-Property'!H13),"")
A14: =IF('Per-Property'!A14="","",'Per-Property'!A14) | B14: =IF(A14="","",'Per-Property'!B14*0.9) | C14: =IF(A14="","",B14-'Per-Property'!C14) | D14: =IFERROR(IF(A14="","",C14/'Per-Property'!H14),"") | E14: =IF(A14="","",'Per-Property'!B14*0.8) | F14: =IF(A14="","",E14-'Per-Property'!C14) | G14: =IFERROR(IF(A14="","",F14/'Per-Property'!H14),"") | H14: =IF(A14="","",'Per-Property'!B14*0.7) | I14: =IF(A14="","",H14-'Per-Property'!C14) | J14: =IFERROR(IF(A14="","",I14/'Per-Property'!H14),"")
A15: =IF('Per-Property'!A15="","",'Per-Property'!A15) | B15: =IF(A15="","",'Per-Property'!B15*0.9) | C15: =IF(A15="","",B15-'Per-Property'!C15) | D15: =IFERROR(IF(A15="","",C15/'Per-Property'!H15),"") | E15: =IF(A15="","",'Per-Property'!B15*0.8) | F15: =IF(A15="","",E15-'Per-Property'!C15) | G15: =IFERROR(IF(A15="","",F15/'Per-Property'!H15),"") | H15: =IF(A15="","",'Per-Property'!B15*0.7) | I15: =IF(A15="","",H15-'Per-Property'!C15) | J15: =IFERROR(IF(A15="","",I15/'Per-Property'!H15),"")
A16: =IF('Per-Property'!A16="","",'Per-Property'!A16) | B16: =IF(A16="","",'Per-Property'!B16*0.9) | C16: =IF(A16="","",B16-'Per-Property'!C16) | D16: =IFERROR(IF(A16="","",C16/'Per-Property'!H16),"") | E16: =IF(A16="","",'Per-Property'!B16*0.8) | F16: =IF(A16="","",E16-'Per-Property'!C16) | G16: =IFERROR(IF(A16="","",F16/'Per-Property'!H16),"") | H16: =IF(A16="","",'Per-Property'!B16*0.7) | I16: =IF(A16="","",H16-'Per-Property'!C16) | J16: =IFERROR(IF(A16="","",I16/'Per-Property'!H16),"")
A17: =IF('Per-Property'!A17="","",'Per-Property'!A17) | B17: =IF(A17="","",'Per-Property'!B17*0.9) | C17: =IF(A17="","",B17-'Per-Property'!C17) | D17: =IFERROR(IF(A17="","",C17/'Per-Property'!H17),"") | E17: =IF(A17="","",'Per-Property'!B17*0.8) | F17: =IF(A17="","",E17-'Per-Property'!C17) | G17: =IFERROR(IF(A17="","",F17/'Per-Property'!H17),"") | H17: =IF(A17="","",'Per-Property'!B17*0.7) | I17: =IF(A17="","",H17-'Per-Property'!C17) | J17: =IFERROR(IF(A17="","",I17/'Per-Property'!H17),"")
A19: # AT RISK (DSCR < 1.0) | B19: =COUNTIFS(A8:A17,"<>",D8:D17,"<"&Settings!$B$9)&" of "&COUNTIF(A8:A17,"<>") | E19: =COUNTIFS(A8:A17,"<>",G8:G17,"<"&Settings!$B$9)&" of "&COUNTIF(A8:A17,"<>") | H19: =COUNTIFS(A8:A17,"<>",J8:J17,"<"&Settings!$B$9)&" of "&COUNTIF(A8:A17,"<>")
A21: Stress test holds operating expenses and debt service constant - real downturns may also reduce OpEx (cleanings, supplies). The pessimism is intentional: a property that survives -30% revenue with no OpEx relief will survive most real-world scenarios.
A25: Questions? hello@thestrledger.com
A26: FIN-004 - v1.0 - Stress Test

Sheet Refi Eligibility
A2: =HYPERLINK("#'Stress Test'!A1", "← BACK") | D2: REFI ELIGIBILITY | J2: =HYPERLINK("#'Settings'!A1", "NEXT →")
A4: DSCR loans typically require DSCR >= 1.20 AND LTV <= 75%. Enter property value + loan balance to see which qualify.
A7: Property | B7: Current DSCR | C7: Est. Property Value | D7: Current Loan Balance | E7: Implied LTV | F7: Max LTV | G7: DSCR Pass? | H7: LTV Pass? | I7: DSCR-Loan Eligible
A8: =IF('Per-Property'!A8="","",'Per-Property'!A8) | B8: =IFERROR(IF('Per-Property'!A8="","",'Per-Property'!I8),"") | C8: 525000 | D8: 360000 | E8: =IFERROR(IF(OR(A8="",C8=""),"",D8/C8),"") | F8: =IF(A8="","",Settings!$B$11) | G8: =IF(A8="","",IF(B8>=Settings!$B$7,"Pass","Fail")) | H8: =IF(OR(A8="",E8=""),"",IF(E8<=Settings!$B$11,"Pass","Fail")) | I8: =IF(OR(A8="",E8=""),"",IF(AND(B8>=Settings!$B$7,E8<=Settings!$B$11),"Eligible","Not Eligible"))
A9: =IF('Per-Property'!A9="","",'Per-Property'!A9) | B9: =IFERROR(IF('Per-Property'!A9="","",'Per-Property'!I9),"") | C9: 540000 | D9: 405000 | E9: =IFERROR(IF(OR(A9="",C9=""),"",D9/C9),"") | F9: =IF(A9="","",Settings!$B$11) | G9: =IF(A9="","",IF(B9>=Settings!$B$7,"Pass","Fail")) | H9: =IF(OR(A9="",E9=""),"",IF(E9<=Settings!$B$11,"Pass","Fail")) | I9: =IF(OR(A9="",E9=""),"",IF(AND(B9>=Settings!$B$7,E9<=Settings!$B$11),"Eligible","Not Eligible"))
A10: =IF('Per-Property'!A10="","",'Per-Property'!A10) | B10: =IFERROR(IF('Per-Property'!A10="","",'Per-Property'!I10),"") | C10: 340000 | D10: 272000 | E10: =IFERROR(IF(OR(A10="",C10=""),"",D10/C10),"") | F10: =IF(A10="","",Settings!$B$11) | G10: =IF(A10="","",IF(B10>=Settings!$B$7,"Pass","Fail")) | H10: =IF(OR(A10="",E10=""),"",IF(E10<=Settings!$B$11,"Pass","Fail")) | I10: =IF(OR(A10="",E10=""),"",IF(AND(B10>=Settings!$B$7,E10<=Settings!$B$11),"Eligible","Not Eligible"))
A11: =IF('Per-Property'!A11="","",'Per-Property'!A11) | B11: =IFERROR(IF('Per-Property'!A11="","",'Per-Property'!I11),"") | E11: =IFERROR(IF(OR(A11="",C11=""),"",D11/C11),"") | F11: =IF(A11="","",Settings!$B$11) | G11: =IF(A11="","",IF(B11>=Settings!$B$7,"Pass","Fail")) | H11: =IF(OR(A11="",E11=""),"",IF(E11<=Settings!$B$11,"Pass","Fail")) | I11: =IF(OR(A11="",E11=""),"",IF(AND(B11>=Settings!$B$7,E11<=Settings!$B$11),"Eligible","Not Eligible"))
A12: =IF('Per-Property'!A12="","",'Per-Property'!A12) | B12: =IFERROR(IF('Per-Property'!A12="","",'Per-Property'!I12),"") | E12: =IFERROR(IF(OR(A12="",C12=""),"",D12/C12),"") | F12: =IF(A12="","",Settings!$B$11) | G12: =IF(A12="","",IF(B12>=Settings!$B$7,"Pass","Fail")) | H12: =IF(OR(A12="",E12=""),"",IF(E12<=Settings!$B$11,"Pass","Fail")) | I12: =IF(OR(A12="",E12=""),"",IF(AND(B12>=Settings!$B$7,E12<=Settings!$B$11),"Eligible","Not Eligible"))
A13: =IF('Per-Property'!A13="","",'Per-Property'!A13) | B13: =IFERROR(IF('Per-Property'!A13="","",'Per-Property'!I13),"") | E13: =IFERROR(IF(OR(A13="",C13=""),"",D13/C13),"") | F13: =IF(A13="","",Settings!$B$11) | G13: =IF(A13="","",IF(B13>=Settings!$B$7,"Pass","Fail")) | H13: =IF(OR(A13="",E13=""),"",IF(E13<=Settings!$B$11,"Pass","Fail")) | I13: =IF(OR(A13="",E13=""),"",IF(AND(B13>=Settings!$B$7,E13<=Settings!$B$11),"Eligible","Not Eligible"))
A14: =IF('Per-Property'!A14="","",'Per-Property'!A14) | B14: =IFERROR(IF('Per-Property'!A14="","",'Per-Property'!I14),"") | E14: =IFERROR(IF(OR(A14="",C14=""),"",D14/C14),"") | F14: =IF(A14="","",Settings!$B$11) | G14: =IF(A14="","",IF(B14>=Settings!$B$7,"Pass","Fail")) | H14: =IF(OR(A14="",E14=""),"",IF(E14<=Settings!$B$11,"Pass","Fail")) | I14: =IF(OR(A14="",E14=""),"",IF(AND(B14>=Settings!$B$7,E14<=Settings!$B$11),"Eligible","Not Eligible"))
A15: =IF('Per-Property'!A15="","",'Per-Property'!A15) | B15: =IFERROR(IF('Per-Property'!A15="","",'Per-Property'!I15),"") | E15: =IFERROR(IF(OR(A15="",C15=""),"",D15/C15),"") | F15: =IF(A15="","",Settings!$B$11) | G15: =IF(A15="","",IF(B15>=Settings!$B$7,"Pass","Fail")) | H15: =IF(OR(A15="",E15=""),"",IF(E15<=Settings!$B$11,"Pass","Fail")) | I15: =IF(OR(A15="",E15=""),"",IF(AND(B15>=Settings!$B$7,E15<=Settings!$B$11),"Eligible","Not Eligible"))
A16: =IF('Per-Property'!A16="","",'Per-Property'!A16) | B16: =IFERROR(IF('Per-Property'!A16="","",'Per-Property'!I16),"") | E16: =IFERROR(IF(OR(A16="",C16=""),"",D16/C16),"") | F16: =IF(A16="","",Settings!$B$11) | G16: =IF(A16="","",IF(B16>=Settings!$B$7,"Pass","Fail")) | H16: =IF(OR(A16="",E16=""),"",IF(E16<=Settings!$B$11,"Pass","Fail")) | I16: =IF(OR(A16="",E16=""),"",IF(AND(B16>=Settings!$B$7,E16<=Settings!$B$11),"Eligible","Not Eligible"))
A17: =IF('Per-Property'!A17="","",'Per-Property'!A17) | B17: =IFERROR(IF('Per-Property'!A17="","",'Per-Property'!I17),"") | E17: =IFERROR(IF(OR(A17="",C17=""),"",D17/C17),"") | F17: =IF(A17="","",Settings!$B$11) | G17: =IF(A17="","",IF(B17>=Settings!$B$7,"Pass","Fail")) | H17: =IF(OR(A17="",E17=""),"",IF(E17<=Settings!$B$11,"Pass","Fail")) | I17: =IF(OR(A17="",E17=""),"",IF(AND(B17>=Settings!$B$7,E17<=Settings!$B$11),"Eligible","Not Eligible"))
A19: # DSCR-LOAN ELIGIBLE | I19: =COUNTIF(I8:I17,"Eligible")&" of "&COUNTIF(A8:A17,"<>")
A21: Lender thresholds vary - many DSCR lenders accept 1.10-1.15 with LTV <= 70% or charge a rate premium. Settings tab lets you adjust the qualify threshold + max LTV to match a specific lender's overlay.
A25: Questions? hello@thestrledger.com
A26: FIN-004 - v1.0 - Refi Eligibility

Sheet Settings
A2: =HYPERLINK("#'Refi Eligibility'!A1", "← BACK") | D2: SETTINGS
A4: Adjust thresholds and active year. Yellow = edit.
A5: Active year: | B5: 2026
A7: DSCR threshold - Qualifies (>=): | B7: 1.2
A8: Most DSCR lenders use 1.20. Some accept 1.10-1.15 with overlay.
A9: DSCR threshold - Negative (<): | B9: 1
A10: Below 1.0 means the property doesn't cover its own debt.
A11: Max LTV for DSCR-loan refi: | B11: 0.75
A12: Standard cap is 75%. Cash-out refis often capped 70%.
A13: PROPERTY LIST
A14: (Reference list - edit names directly on the Per-Property tab. These mirror via formula.)
A15: Property #1 | B15: =IF('Per-Property'!A8="","-",'Per-Property'!A8)
A16: Property #2 | B16: =IF('Per-Property'!A9="","-",'Per-Property'!A9)
A17: Property #3 | B17: =IF('Per-Property'!A10="","-",'Per-Property'!A10)
A18: Property #4 | B18: =IF('Per-Property'!A11="","-",'Per-Property'!A11)
A19: Property #5 | B19: =IF('Per-Property'!A12="","-",'Per-Property'!A12)
A20: Property #6 | B20: =IF('Per-Property'!A13="","-",'Per-Property'!A13)
A21: Property #7 | B21: =IF('Per-Property'!A14="","-",'Per-Property'!A14)
A22: Property #8 | B22: =IF('Per-Property'!A15="","-",'Per-Property'!A15)
A23: Property #9 | B23: =IF('Per-Property'!A16="","-",'Per-Property'!A16)
A24: Property #10 | B24: =IF('Per-Property'!A17="","-",'Per-Property'!A17)
A28: Questions? hello@thestrledger.com
A29: FIN-004 - v1.0 - Settings
