Workbook

Sheet Start
A2: The STR Ledger
A4: Utility Usage + Trend
A5: Catch a leak before it costs a month.
A6: =IF(COUNTA('Bills Log'!B6:B505)=0,"📊 Log your first bill to see your verdict.",IF('Trend & Anomalies'!$B$3=0,"✅ No anomalies detected — usage is steady year-over-year.","⚠ "&'Trend & Anomalies'!$B$3&" anomalies detected — see Trend & Anomalies tab."))
A7: OPS-007 · v2.2 · BLANK
A10: WHAT THIS DOES
A11: Track every utility bill (electric, gas, water, internet, trash, propane) per property in a 12-column matrix. The Trend & Anomalies tab compares each month to the prior year and flags any service whose bill jumped >25% — your early warning system for leaks, runaway HVAC, and price hikes you didn't see coming.
A18: HOW TO USE
A19: ① Settings: list your properties + confirm active year.
A20: ② Bills Log: log every utility bill — date, property, service, $, usage, notes.
A21: ③ Property Matrix: per-property 12-month roll-up by service (auto).
A22: ④ Trend & Anomalies: scan the ⚠ flags — anything >25% YoY needs a look.
A23: ⑤ Bump 'Active tax year' on Settings each January so YoY checks stay aligned.
A24: ⑥ Log bills the day they arrive — backfilling kills the trend signal.
A27: =HYPERLINK("#'Bills Log'!A6", "→ LOG A BILL")
A32: YTD UTILITY $ | E32: AVG $/MONTH | I32: ANOMALIES
A33: =SUMIFS('Bills Log'!F:F,'Bills Log'!A:A,">="&DATE(Settings!$B$5,1,1),'Bills Log'!A:A,"<"&DATE(Settings!$B$5+1,1,1)) | E33: =IFERROR(SUMIFS('Bills Log'!F:F,'Bills Log'!A:A,">="&DATE(Settings!$B$5,1,1),'Bills Log'!A:A,"<"&DATE(Settings!$B$5+1,1,1))/12,0) | I33: ='Trend & Anomalies'!$B$3
A35: all properties combined | E35: across all services | I35: YoY jumps >25%
A39: =HYPERLINK("#'Bills Log'!A1", "Bills Log") | D39: =HYPERLINK("#'Property Matrix'!A1", "Property Matrix") | G39: =HYPERLINK("#'Trend & Anomalies'!A1", "⚠ Trend & Anomalies") | J39: =HYPERLINK("#'Settings'!A1", "Settings")
A42: ⚠ ANOMALY = a month's bill jumped >25% vs the same month last year. Common causes: leak, AC/heat running while vacant, rate hike, or a misread meter. Check the Trend & Anomalies tab monthly.
A44: 💡 Upgrade to the Full version at thestrledger.com/upgrade — multi-property, depreciation, multi-LLC support.
A47: Questions? hello@thestrledger.com
A48: OPS-007 · v2.2 · Free updates forever

Sheet Bills Log
A2: =HYPERLINK("#'Start'!A1", "← BACK") | D2: BILLS LOG | J2: =HYPERLINK("#'Property Matrix'!A1", "NEXT →")
A4: One row per utility bill — date, property, service, $, usage
A5: Bill Date | B5: Property | C5: Service | D5: Period Start | E5: Period End | F5: $ Amount | G5: Usage | H5: Units | I5: $/Unit | J5: Notes
I6: =IFERROR(F6/G6,"")
I7: =IFERROR(F7/G7,"")
I8: =IFERROR(F8/G8,"")
I9: =IFERROR(F9/G9,"")
I10: =IFERROR(F10/G10,"")
I11: =IFERROR(F11/G11,"")
I12: =IFERROR(F12/G12,"")
I13: =IFERROR(F13/G13,"")
I14: =IFERROR(F14/G14,"")
I15: =IFERROR(F15/G15,"")
I16: =IFERROR(F16/G16,"")
I17: =IFERROR(F17/G17,"")
... I505: =IFERROR(F505/G505,"")

Sheet Property Matrix
A2: =HYPERLINK("#'Bills Log'!A1", "← BACK") | D2: PROPERTY MATRIX | J2: =HYPERLINK("#'Trend & Anomalies'!A1", "NEXT →")
A4: Per-property 12-month roll-up — auto-rolled from Bills Log
A6: ="Property: "&Settings!$B$7
A7: Service | B7: Jan | C7: Feb | D7: Mar | E7: Apr | F7: May | G7: Jun | H7: Jul | I7: Aug | J7: Sep | K7: Oct | L7: Nov | M7: Dec | N7: Total | O7: Avg
A8: Electric | B8: =SUMIFS('Bills Log'!$F$6:$F$505,'Bills Log'!$A$6:$A$505,">="&DATE(Settings!$B$5,1,1),'Bills Log'!$A$6:$A$505,"<"&DATE(Settings!$B$5,2,1),'Bills Log'!$B$6:$B$505,Settings!$B$7,'Bills Log'!$C$6:$C$505,$A8) | C8: =SUMIFS('Bills Log'!$F$6:$F$505,'Bills Log'!$A$6:$A$505,">="&DATE(Settings!$B$5,2,1),'Bills Log'!$A$6:$A$505,"<"&DATE(Settings!$B$5,3,1),'Bills Log'!$B$6:$B$505,Settings!$B$7,'Bills Log'!$C$6:$C$505,$A8) | D8: =SUMIFS('Bills Log'!$F$6:$F$505,'Bills Log'!$A$6:$A$505,">="&DATE(Settings!$B$5,3,1),'Bills Log'!$A$6:$A$505,"<"&DATE(Settings!$B$5,4,1),'Bills Log'!$B$6:$B$505,Settings!$B$7,'Bills Log'!$C$6:$C$505,$A8) | E8: =SUMIFS('Bills Log'!$F$6:$F$505,'Bills Log'!$A$6:$A$505,">="&DATE(Settings!$B$5,4,1),'Bills Log'!$A$6:$A$505,"<"&DATE(Settings!$B$5,5,1),'Bills Log'!$B$6:$B$505,Settings!$B$7,'Bills Log'!$C$6:$C$505,$A8) | F8: =SUMIFS('Bills Log'!$F$6:$F$505,'Bills Log'!$A$6:$A$505,">="&DATE(Settings!$B$5,5,1),'Bills Log'!$A$6:$A$505,"<"&DATE(Settings!$B$5,6,1),'Bills Log'!$B$6:$B$505,Settings!$B$7,'Bills Log'!$C$6:$C$505,$A8) | G8: =SUMIFS('Bills Log'!$F$6:$F$505,'Bills Log'!$A$6:$A$505,">="&DATE(Settings!$B$5,6,1),'Bills Log'!$A$6:$A$505,"<"&DATE(Settings!$B$5,7,1),'Bills Log'!$B$6:$B$505,Settings!$B$7,'Bills Log'!$C$6:$C$505,$A8) | H8: =SUMIFS('Bills Log'!$F$6:$F$505,'Bills Log'!$A$6:$A$505,">="&DATE(Settings!$B$5,7,1),'Bills Log'!$A$6:$A$505,"<"&DATE(Settings!$B$5,8,1),'Bills Log'!$B$6:$B$505,Settings!$B$7,'Bills Log'!$C$6:$C$505,$A8) | I8: =SUMIFS('Bills Log'!$F$6:$F$505,'Bills Log'!$A$6:$A$505,">="&DATE(Settings!$B$5,8,1),'Bills Log'!$A$6:$A$505,"<"&DATE(Settings!$B$5,9,1),'Bills Log'!$B$6:$B$505,Settings!$B$7,'Bills Log'!$C$6:$C$505,$A8) | J8: =SUMIFS('Bills Log'!$F$6:$F$505,'Bills Log'!$A$6:$A$505,">="&DATE(Settings!$B$5,9,1),'Bills Log'!$A$6:$A$505,"<"&DATE(Settings!$B$5,10,1),'Bills Log'!$B$6:$B$505,Settings!$B$7,'Bills Log'!$C$6:$C$505,$A8) | K8: =SUMIFS('Bills Log'!$F$6:$F$505,'Bills Log'!$A$6:$A$505,">="&DATE(Settings!$B$5,10,1),'Bills Log'!$A$6:$A$505,"<"&DATE(Settings!$B$5,11,1),'Bills Log'!$B$6:$B$505,Settings!$B$7,'Bills Log'!$C$6:$C$505,$A8) | L8: =SUMIFS('Bills Log'!$F$6:$F$505,'Bills Log'!$A$6:$A$505,">="&DATE(Settings!$B$5,11,1),'Bills Log'!$A$6:$A$505,"<"&DATE(Settings!$B$5,12,1),'Bills Log'!$B$6:$B$505,Settings!$B$7,'Bills Log'!$C$6:$C$505,$A8) | M8: =SUMIFS('Bills Log'!$F$6:$F$505,'Bills Log'!$A$6:$A$505,">="&DATE(Settings!$B$5,12,1),'Bills Log'!$A$6:$A$505,"<"&DATE(Settings!$B$5+1,1,1),'Bills Log'!$B$6:$B$505,Settings!$B$7,'Bills Log'!$C$6:$C$505,$A8) | N8: =SUM(B8:M8) | O8: =IFERROR(N8/12,0)
A9: Gas | B9: =SUMIFS('Bills Log'!$F$6:$F$505,'Bills Log'!$A$6:$A$505,">="&DATE(Settings!$B$5,1,1),'Bills Log'!$A$6:$A$505,"<"&DATE(Settings!$B$5,2,1),'Bills Log'!$B$6:$B$505,Settings!$B$7,'Bills Log'!$C$6:$C$505,$A9) | C9: =SUMIFS('Bills Log'!$F$6:$F$505,'Bills Log'!$A$6:$A$505,">="&DATE(Settings!$B$5,2,1),'Bills Log'!$A$6:$A$505,"<"&DATE(Settings!$B$5,3,1),'Bills Log'!$B$6:$B$505,Settings!$B$7,'Bills Log'!$C$6:$C$505,$A9) | D9: =SUMIFS('Bills Log'!$F$6:$F$505,'Bills Log'!$A$6:$A$505,">="&DATE(Settings!$B$5,3,1),'Bills Log'!$A$6:$A$505,"<"&DATE(Settings!$B$5,4,1),'Bills Log'!$B$6:$B$505,Settings!$B$7,'Bills Log'!$C$6:$C$505,$A9) | E9: =SUMIFS('Bills Log'!$F$6:$F$505,'Bills Log'!$A$6:$A$505,">="&DATE(Settings!$B$5,4,1),'Bills Log'!$A$6:$A$505,"<"&DATE(Settings!$B$5,5,1),'Bills Log'!$B$6:$B$505,Settings!$B$7,'Bills Log'!$C$6:$C$505,$A9) | F9: =SUMIFS('Bills Log'!$F$6:$F$505,'Bills Log'!$A$6:$A$505,">="&DATE(Settings!$B$5,5,1),'Bills Log'!$A$6:$A$505,"<"&DATE(Settings!$B$5,6,1),'Bills Log'!$B$6:$B$505,Settings!$B$7,'Bills Log'!$C$6:$C$505,$A9) | G9: =SUMIFS('Bills Log'!$F$6:$F$505,'Bills Log'!$A$6:$A$505,">="&DATE(Settings!$B$5,6,1),'Bills Log'!$A$6:$A$505,"<"&DATE(Settings!$B$5,7,1),'Bills Log'!$B$6:$B$505,Settings!$B$7,'Bills Log'!$C$6:$C$505,$A9) | H9: =SUMIFS('Bills Log'!$F$6:$F$505,'Bills Log'!$A$6:$A$505,">="&DATE(Settings!$B$5,7,1),'Bills Log'!$A$6:$A$505,"<"&DATE(Settings!$B$5,8,1),'Bills Log'!$B$6:$B$505,Settings!$B$7,'Bills Log'!$C$6:$C$505,$A9) | I9: =SUMIFS('Bills Log'!$F$6:$F$505,'Bills Log'!$A$6:$A$505,">="&DATE(Settings!$B$5,8,1),'Bills Log'!$A$6:$A$505,"<"&DATE(Settings!$B$5,9,1),'Bills Log'!$B$6:$B$505,Settings!$B$7,'Bills Log'!$C$6:$C$505,$A9) | J9: =SUMIFS('Bills Log'!$F$6:$F$505,'Bills Log'!$A$6:$A$505,">="&DATE(Settings!$B$5,9,1),'Bills Log'!$A$6:$A$505,"<"&DATE(Settings!$B$5,10,1),'Bills Log'!$B$6:$B$505,Settings!$B$7,'Bills Log'!$C$6:$C$505,$A9) | K9: =SUMIFS('Bills Log'!$F$6:$F$505,'Bills Log'!$A$6:$A$505,">="&DATE(Settings!$B$5,10,1),'Bills Log'!$A$6:$A$505,"<"&DATE(Settings!$B$5,11,1),'Bills Log'!$B$6:$B$505,Settings!$B$7,'Bills Log'!$C$6:$C$505,$A9) | L9: =SUMIFS('Bills Log'!$F$6:$F$505,'Bills Log'!$A$6:$A$505,">="&DATE(Settings!$B$5,11,1),'Bills Log'!$A$6:$A$505,"<"&DATE(Settings!$B$5,12,1),'Bills Log'!$B$6:$B$505,Settings!$B$7,'Bills Log'!$C$6:$C$505,$A9) | M9: =SUMIFS('Bills Log'!$F$6:$F$505,'Bills Log'!$A$6:$A$505,">="&DATE(Settings!$B$5,12,1),'Bills Log'!$A$6:$A$505,"<"&DATE(Settings!$B$5+1,1,1),'Bills Log'!$B$6:$B$505,Settings!$B$7,'Bills Log'!$C$6:$C$505,$A9) | N9: =SUM(B9:M9) | O9: =IFERROR(N9/12,0)
A10: Water | B10: =SUMIFS('Bills Log'!$F$6:$F$505,'Bills Log'!$A$6:$A$505,">="&DATE(Settings!$B$5,1,1),'Bills Log'!$A$6:$A$505,"<"&DATE(Settings!$B$5,2,1),'Bills Log'!$B$6:$B$505,Settings!$B$7,'Bills Log'!$C$6:$C$505,$A10) | C10: =SUMIFS('Bills Log'!$F$6:$F$505,'Bills Log'!$A$6:$A$505,">="&DATE(Settings!$B$5,2,1),'Bills Log'!$A$6:$A$505,"<"&DATE(Settings!$B$5,3,1),'Bills Log'!$B$6:$B$505,Settings!$B$7,'Bills Log'!$C$6:$C$505,$A10) | D10: =SUMIFS('Bills Log'!$F$6:$F$505,'Bills Log'!$A$6:$A$505,">="&DATE(Settings!$B$5,3,1),'Bills Log'!$A$6:$A$505,"<"&DATE(Settings!$B$5,4,1),'Bills Log'!$B$6:$B$505,Settings!$B$7,'Bills Log'!$C$6:$C$505,$A10) | E10: =SUMIFS('Bills Log'!$F$6:$F$505,'Bills Log'!$A$6:$A$505,">="&DATE(Settings!$B$5,4,1),'Bills Log'!$A$6:$A$505,"<"&DATE(Settings!$B$5,5,1),'Bills Log'!$B$6:$B$505,Settings!$B$7,'Bills Log'!$C$6:$C$505,$A10) | F10: =SUMIFS('Bills Log'!$F$6:$F$505,'Bills Log'!$A$6:$A$505,">="&DATE(Settings!$B$5,5,1),'Bills Log'!$A$6:$A$505,"<"&DATE(Settings!$B$5,6,1),'Bills Log'!$B$6:$B$505,Settings!$B$7,'Bills Log'!$C$6:$C$505,$A10) | G10: =SUMIFS('Bills Log'!$F$6:$F$505,'Bills Log'!$A$6:$A$505,">="&DATE(Settings!$B$5,6,1),'Bills Log'!$A$6:$A$505,"<"&DATE(Settings!$B$5,7,1),'Bills Log'!$B$6:$B$505,Settings!$B$7,'Bills Log'!$C$6:$C$505,$A10) | H10: =SUMIFS('Bills Log'!$F$6:$F$505,'Bills Log'!$A$6:$A$505,">="&DATE(Settings!$B$5,7,1),'Bills Log'!$A$6:$A$505,"<"&DATE(Settings!$B$5,8,1),'Bills Log'!$B$6:$B$505,Settings!$B$7,'Bills Log'!$C$6:$C$505,$A10) | I10: =SUMIFS('Bills Log'!$F$6:$F$505,'Bills Log'!$A$6:$A$505,">="&DATE(Settings!$B$5,8,1),'Bills Log'!$A$6:$A$505,"<"&DATE(Settings!$B$5,9,1),'Bills Log'!$B$6:$B$505,Settings!$B$7,'Bills Log'!$C$6:$C$505,$A10) | J10: =SUMIFS('Bills Log'!$F$6:$F$505,'Bills Log'!$A$6:$A$505,">="&DATE(Settings!$B$5,9,1),'Bills Log'!$A$6:$A$505,"<"&DATE(Settings!$B$5,10,1),'Bills Log'!$B$6:$B$505,Settings!$B$7,'Bills Log'!$C$6:$C$505,$A10) | K10: =SUMIFS('Bills Log'!$F$6:$F$505,'Bills Log'!$A$6:$A$505,">="&DATE(Settings!$B$5,10,1),'Bills Log'!$A$6:$A$505,"<"&DATE(Settings!$B$5,11,1),'Bills Log'!$B$6:$B$505,Settings!$B$7,'Bills Log'!$C$6:$C$505,$A10) | L10: =SUMIFS('Bills Log'!$F$6:$F$505,'Bills Log'!$A$6:$A$505,">="&DATE(Settings!$B$5,11,1),'Bills Log'!$A$6:$A$505,"<"&DATE(Settings!$B$5,12,1),'Bills Log'!$B$6:$B$505,Settings!$B$7,'Bills Log'!$C$6:$C$505,$A10) | M10: =SUMIFS('Bills Log'!$F$6:$F$505,'Bills Log'!$A$6:$A$505,">="&DATE(Settings!$B$5,12,1),'Bills Log'!$A$6:$A$505,"<"&DATE(Settings!$B$5+1,1,1),'Bills Log'!$B$6:$B$505,Settings!$B$7,'Bills Log'!$C$6:$C$505,$A10) | N10: =SUM(B10:M10) | O10: =IFERROR(N10/12,0)
A11: Internet | B11: =SUMIFS('Bills Log'!$F$6:$F$505,'Bills Log'!$A$6:$A$505,">="&DATE(Settings!$B$5,1,1),'Bills Log'!$A$6:$A$505,"<"&DATE(Settings!$B$5,2,1),'Bills Log'!$B$6:$B$505,Settings!$B$7,'Bills Log'!$C$6:$C$505,$A11) | C11: =SUMIFS('Bills Log'!$F$6:$F$505,'Bills Log'!$A$6:$A$505,">="&DATE(Settings!$B$5,2,1),'Bills Log'!$A$6:$A$505,"<"&DATE(Settings!$B$5,3,1),'Bills Log'!$B$6:$B$505,Settings!$B$7,'Bills Log'!$C$6:$C$505,$A11) | D11: =SUMIFS('Bills Log'!$F$6:$F$505,'Bills Log'!$A$6:$A$505,">="&DATE(Settings!$B$5,3,1),'Bills Log'!$A$6:$A$505,"<"&DATE(Settings!$B$5,4,1),'Bills Log'!$B$6:$B$505,Settings!$B$7,'Bills Log'!$C$6:$C$505,$A11) | E11: =SUMIFS('Bills Log'!$F$6:$F$505,'Bills Log'!$A$6:$A$505,">="&DATE(Settings!$B$5,4,1),'Bills Log'!$A$6:$A$505,"<"&DATE(Settings!$B$5,5,1),'Bills Log'!$B$6:$B$505,Settings!$B$7,'Bills Log'!$C$6:$C$505,$A11) | F11: =SUMIFS('Bills Log'!$F$6:$F$505,'Bills Log'!$A$6:$A$505,">="&DATE(Settings!$B$5,5,1),'Bills Log'!$A$6:$A$505,"<"&DATE(Settings!$B$5,6,1),'Bills Log'!$B$6:$B$505,Settings!$B$7,'Bills Log'!$C$6:$C$505,$A11) | G11: =SUMIFS('Bills Log'!$F$6:$F$505,'Bills Log'!$A$6:$A$505,">="&DATE(Settings!$B$5,6,1),'Bills Log'!$A$6:$A$505,"<"&DATE(Settings!$B$5,7,1),'Bills Log'!$B$6:$B$505,Settings!$B$7,'Bills Log'!$C$6:$C$505,$A11) | H11: =SUMIFS('Bills Log'!$F$6:$F$505,'Bills Log'!$A$6:$A$505,">="&DATE(Settings!$B$5,7,1),'Bills Log'!$A$6:$A$505,"<"&DATE(Settings!$B$5,8,1),'Bills Log'!$B$6:$B$505,Settings!$B$7,'Bills Log'!$C$6:$C$505,$A11) | I11: =SUMIFS('Bills Log'!$F$6:$F$505,'Bills Log'!$A$6:$A$505,">="&DATE(Settings!$B$5,8,1),'Bills Log'!$A$6:$A$505,"<"&DATE(Settings!$B$5,9,1),'Bills Log'!$B$6:$B$505,Settings!$B$7,'Bills Log'!$C$6:$C$505,$A11) | J11: =SUMIFS('Bills Log'!$F$6:$F$505,'Bills Log'!$A$6:$A$505,">="&DATE(Settings!$B$5,9,1),'Bills Log'!$A$6:$A$505,"<"&DATE(Settings!$B$5,10,1),'Bills Log'!$B$6:$B$505,Settings!$B$7,'Bills Log'!$C$6:$C$505,$A11) | K11: =SUMIFS('Bills Log'!$F$6:$F$505,'Bills Log'!$A$6:$A$505,">="&DATE(Settings!$B$5,10,1),'Bills Log'!$A$6:$A$505,"<"&DATE(Settings!$B$5,11,1),'Bills Log'!$B$6:$B$505,Settings!$B$7,'Bills Log'!$C$6:$C$505,$A11) | L11: =SUMIFS('Bills Log'!$F$6:$F$505,'Bills Log'!$A$6:$A$505,">="&DATE(Settings!$B$5,11,1),'Bills Log'!$A$6:$A$505,"<"&DATE(Settings!$B$5,12,1),'Bills Log'!$B$6:$B$505,Settings!$B$7,'Bills Log'!$C$6:$C$505,$A11) | M11: =SUMIFS('Bills Log'!$F$6:$F$505,'Bills Log'!$A$6:$A$505,">="&DATE(Settings!$B$5,12,1),'Bills Log'!$A$6:$A$505,"<"&DATE(Settings!$B$5+1,1,1),'Bills Log'!$B$6:$B$505,Settings!$B$7,'Bills Log'!$C$6:$C$505,$A11) | N11: =SUM(B11:M11) | O11: =IFERROR(N11/12,0)
A12: Trash | B12: =SUMIFS('Bills Log'!$F$6:$F$505,'Bills Log'!$A$6:$A$505,">="&DATE(Settings!$B$5,1,1),'Bills Log'!$A$6:$A$505,"<"&DATE(Settings!$B$5,2,1),'Bills Log'!$B$6:$B$505,Settings!$B$7,'Bills Log'!$C$6:$C$505,$A12) | C12: =SUMIFS('Bills Log'!$F$6:$F$505,'Bills Log'!$A$6:$A$505,">="&DATE(Settings!$B$5,2,1),'Bills Log'!$A$6:$A$505,"<"&DATE(Settings!$B$5,3,1),'Bills Log'!$B$6:$B$505,Settings!$B$7,'Bills Log'!$C$6:$C$505,$A12) | D12: =SUMIFS('Bills Log'!$F$6:$F$505,'Bills Log'!$A$6:$A$505,">="&DATE(Settings!$B$5,3,1),'Bills Log'!$A$6:$A$505,"<"&DATE(Settings!$B$5,4,1),'Bills Log'!$B$6:$B$505,Settings!$B$7,'Bills Log'!$C$6:$C$505,$A12) | E12: =SUMIFS('Bills Log'!$F$6:$F$505,'Bills Log'!$A$6:$A$505,">="&DATE(Settings!$B$5,4,1),'Bills Log'!$A$6:$A$505,"<"&DATE(Settings!$B$5,5,1),'Bills Log'!$B$6:$B$505,Settings!$B$7,'Bills Log'!$C$6:$C$505,$A12) | F12: =SUMIFS('Bills Log'!$F$6:$F$505,'Bills Log'!$A$6:$A$505,">="&DATE(Settings!$B$5,5,1),'Bills Log'!$A$6:$A$505,"<"&DATE(Settings!$B$5,6,1),'Bills Log'!$B$6:$B$505,Settings!$B$7,'Bills Log'!$C$6:$C$505,$A12) | G12: =SUMIFS('Bills Log'!$F$6:$F$505,'Bills Log'!$A$6:$A$505,">="&DATE(Settings!$B$5,6,1),'Bills Log'!$A$6:$A$505,"<"&DATE(Settings!$B$5,7,1),'Bills Log'!$B$6:$B$505,Settings!$B$7,'Bills Log'!$C$6:$C$505,$A12) | H12: =SUMIFS('Bills Log'!$F$6:$F$505,'Bills Log'!$A$6:$A$505,">="&DATE(Settings!$B$5,7,1),'Bills Log'!$A$6:$A$505,"<"&DATE(Settings!$B$5,8,1),'Bills Log'!$B$6:$B$505,Settings!$B$7,'Bills Log'!$C$6:$C$505,$A12) | I12: =SUMIFS('Bills Log'!$F$6:$F$505,'Bills Log'!$A$6:$A$505,">="&DATE(Settings!$B$5,8,1),'Bills Log'!$A$6:$A$505,"<"&DATE(Settings!$B$5,9,1),'Bills Log'!$B$6:$B$505,Settings!$B$7,'Bills Log'!$C$6:$C$505,$A12) | J12: =SUMIFS('Bills Log'!$F$6:$F$505,'Bills Log'!$A$6:$A$505,">="&DATE(Settings!$B$5,9,1),'Bills Log'!$A$6:$A$505,"<"&DATE(Settings!$B$5,10,1),'Bills Log'!$B$6:$B$505,Settings!$B$7,'Bills Log'!$C$6:$C$505,$A12) | K12: =SUMIFS('Bills Log'!$F$6:$F$505,'Bills Log'!$A$6:$A$505,">="&DATE(Settings!$B$5,10,1),'Bills Log'!$A$6:$A$505,"<"&DATE(Settings!$B$5,11,1),'Bills Log'!$B$6:$B$505,Settings!$B$7,'Bills Log'!$C$6:$C$505,$A12) | L12: =SUMIFS('Bills Log'!$F$6:$F$505,'Bills Log'!$A$6:$A$505,">="&DATE(Settings!$B$5,11,1),'Bills Log'!$A$6:$A$505,"<"&DATE(Settings!$B$5,12,1),'Bills Log'!$B$6:$B$505,Settings!$B$7,'Bills Log'!$C$6:$C$505,$A12) | M12: =SUMIFS('Bills Log'!$F$6:$F$505,'Bills Log'!$A$6:$A$505,">="&DATE(Settings!$B$5,12,1),'Bills Log'!$A$6:$A$505,"<"&DATE(Settings!$B$5+1,1,1),'Bills Log'!$B$6:$B$505,Settings!$B$7,'Bills Log'!$C$6:$C$505,$A12) | N12: =SUM(B12:M12) | O12: =IFERROR(N12/12,0)
A13: Propane | B13: =SUMIFS('Bills Log'!$F$6:$F$505,'Bills Log'!$A$6:$A$505,">="&DATE(Settings!$B$5,1,1),'Bills Log'!$A$6:$A$505,"<"&DATE(Settings!$B$5,2,1),'Bills Log'!$B$6:$B$505,Settings!$B$7,'Bills Log'!$C$6:$C$505,$A13) | C13: =SUMIFS('Bills Log'!$F$6:$F$505,'Bills Log'!$A$6:$A$505,">="&DATE(Settings!$B$5,2,1),'Bills Log'!$A$6:$A$505,"<"&DATE(Settings!$B$5,3,1),'Bills Log'!$B$6:$B$505,Settings!$B$7,'Bills Log'!$C$6:$C$505,$A13) | D13: =SUMIFS('Bills Log'!$F$6:$F$505,'Bills Log'!$A$6:$A$505,">="&DATE(Settings!$B$5,3,1),'Bills Log'!$A$6:$A$505,"<"&DATE(Settings!$B$5,4,1),'Bills Log'!$B$6:$B$505,Settings!$B$7,'Bills Log'!$C$6:$C$505,$A13) | E13: =SUMIFS('Bills Log'!$F$6:$F$505,'Bills Log'!$A$6:$A$505,">="&DATE(Settings!$B$5,4,1),'Bills Log'!$A$6:$A$505,"<"&DATE(Settings!$B$5,5,1),'Bills Log'!$B$6:$B$505,Settings!$B$7,'Bills Log'!$C$6:$C$505,$A13) | F13: =SUMIFS('Bills Log'!$F$6:$F$505,'Bills Log'!$A$6:$A$505,">="&DATE(Settings!$B$5,5,1),'Bills Log'!$A$6:$A$505,"<"&DATE(Settings!$B$5,6,1),'Bills Log'!$B$6:$B$505,Settings!$B$7,'Bills Log'!$C$6:$C$505,$A13) | G13: =SUMIFS('Bills Log'!$F$6:$F$505,'Bills Log'!$A$6:$A$505,">="&DATE(Settings!$B$5,6,1),'Bills Log'!$A$6:$A$505,"<"&DATE(Settings!$B$5,7,1),'Bills Log'!$B$6:$B$505,Settings!$B$7,'Bills Log'!$C$6:$C$505,$A13) | H13: =SUMIFS('Bills Log'!$F$6:$F$505,'Bills Log'!$A$6:$A$505,">="&DATE(Settings!$B$5,7,1),'Bills Log'!$A$6:$A$505,"<"&DATE(Settings!$B$5,8,1),'Bills Log'!$B$6:$B$505,Settings!$B$7,'Bills Log'!$C$6:$C$505,$A13) | I13: =SUMIFS('Bills Log'!$F$6:$F$505,'Bills Log'!$A$6:$A$505,">="&DATE(Settings!$B$5,8,1),'Bills Log'!$A$6:$A$505,"<"&DATE(Settings!$B$5,9,1),'Bills Log'!$B$6:$B$505,Settings!$B$7,'Bills Log'!$C$6:$C$505,$A13) | J13: =SUMIFS('Bills Log'!$F$6:$F$505,'Bills Log'!$A$6:$A$505,">="&DATE(Settings!$B$5,9,1),'Bills Log'!$A$6:$A$505,"<"&DATE(Settings!$B$5,10,1),'Bills Log'!$B$6:$B$505,Settings!$B$7,'Bills Log'!$C$6:$C$505,$A13) | K13: =SUMIFS('Bills Log'!$F$6:$F$505,'Bills Log'!$A$6:$A$505,">="&DATE(Settings!$B$5,10,1),'Bills Log'!$A$6:$A$505,"<"&DATE(Settings!$B$5,11,1),'Bills Log'!$B$6:$B$505,Settings!$B$7,'Bills Log'!$C$6:$C$505,$A13) | L13: =SUMIFS('Bills Log'!$F$6:$F$505,'Bills Log'!$A$6:$A$505,">="&DATE(Settings!$B$5,11,1),'Bills Log'!$A$6:$A$505,"<"&DATE(Settings!$B$5,12,1),'Bills Log'!$B$6:$B$505,Settings!$B$7,'Bills Log'!$C$6:$C$505,$A13) | M13: =SUMIFS('Bills Log'!$F$6:$F$505,'Bills Log'!$A$6:$A$505,">="&DATE(Settings!$B$5,12,1),'Bills Log'!$A$6:$A$505,"<"&DATE(Settings!$B$5+1,1,1),'Bills Log'!$B$6:$B$505,Settings!$B$7,'Bills Log'!$C$6:$C$505,$A13) | N13: =SUM(B13:M13) | O13: =IFERROR(N13/12,0)
A14: TOTAL | B14: =SUM(B8:B13) | C14: =SUM(C8:C13) | D14: =SUM(D8:D13) | E14: =SUM(E8:E13) | F14: =SUM(F8:F13) | G14: =SUM(G8:G13) | H14: =SUM(H8:H13) | I14: =SUM(I8:I13) | ... O14: =SUM(O8:O13)
A28: ="Property: "&Settings!$B$8
A29: Service | B29: Jan | C29: Feb | D29: Mar | E29: Apr | F29: May | G29: Jun | H29: Jul | I29: Aug | J29: Sep | K29: Oct | L29: Nov | M29: Dec | N29: Total | O29: Avg
A30: Electric | B30: =SUMIFS('Bills Log'!$F$6:$F$505,'Bills Log'!$A$6:$A$505,">="&DATE(Settings!$B$5,1,1),'Bills Log'!$A$6:$A$505,"<"&DATE(Settings!$B$5,2,1),'Bills Log'!$B$6:$B$505,Settings!$B$8,'Bills Log'!$C$6:$C$505,$A30) | C30: =SUMIFS('Bills Log'!$F$6:$F$505,'Bills Log'!$A$6:$A$505,">="&DATE(Settings!$B$5,2,1),'Bills Log'!$A$6:$A$505,"<"&DATE(Settings!$B$5,3,1),'Bills Log'!$B$6:$B$505,Settings!$B$8,'Bills Log'!$C$6:$C$505,$A30) | D30: =SUMIFS('Bills Log'!$F$6:$F$505,'Bills Log'!$A$6:$A$505,">="&DATE(Settings!$B$5,3,1),'Bills Log'!$A$6:$A$505,"<"&DATE(Settings!$B$5,4,1),'Bills Log'!$B$6:$B$505,Settings!$B$8,'Bills Log'!$C$6:$C$505,$A30) | E30: =SUMIFS('Bills Log'!$F$6:$F$505,'Bills Log'!$A$6:$A$505,">="&DATE(Settings!$B$5,4,1),'Bills Log'!$A$6:$A$505,"<"&DATE(Settings!$B$5,5,1),'Bills Log'!$B$6:$B$505,Settings!$B$8,'Bills Log'!$C$6:$C$505,$A30) | F30: =SUMIFS('Bills Log'!$F$6:$F$505,'Bills Log'!$A$6:$A$505,">="&DATE(Settings!$B$5,5,1),'Bills Log'!$A$6:$A$505,"<"&DATE(Settings!$B$5,6,1),'Bills Log'!$B$6:$B$505,Settings!$B$8,'Bills Log'!$C$6:$C$505,$A30) | G30: =SUMIFS('Bills Log'!$F$6:$F$505,'Bills Log'!$A$6:$A$505,">="&DATE(Settings!$B$5,6,1),'Bills Log'!$A$6:$A$505,"<"&DATE(Settings!$B$5,7,1),'Bills Log'!$B$6:$B$505,Settings!$B$8,'Bills Log'!$C$6:$C$505,$A30) | H30: =SUMIFS('Bills Log'!$F$6:$F$505,'Bills Log'!$A$6:$A$505,">="&DATE(Settings!$B$5,7,1),'Bills Log'!$A$6:$A$505,"<"&DATE(Settings!$B$5,8,1),'Bills Log'!$B$6:$B$505,Settings!$B$8,'Bills Log'!$C$6:$C$505,$A30) | I30: =SUMIFS('Bills Log'!$F$6:$F$505,'Bills Log'!$A$6:$A$505,">="&DATE(Settings!$B$5,8,1),'Bills Log'!$A$6:$A$505,"<"&DATE(Settings!$B$5,9,1),'Bills Log'!$B$6:$B$505,Settings!$B$8,'Bills Log'!$C$6:$C$505,$A30) | J30: =SUMIFS('Bills Log'!$F$6:$F$505,'Bills Log'!$A$6:$A$505,">="&DATE(Settings!$B$5,9,1),'Bills Log'!$A$6:$A$505,"<"&DATE(Settings!$B$5,10,1),'Bills Log'!$B$6:$B$505,Settings!$B$8,'Bills Log'!$C$6:$C$505,$A30) | K30: =SUMIFS('Bills Log'!$F$6:$F$505,'Bills Log'!$A$6:$A$505,">="&DATE(Settings!$B$5,10,1),'Bills Log'!$A$6:$A$505,"<"&DATE(Settings!$B$5,11,1),'Bills Log'!$B$6:$B$505,Settings!$B$8,'Bills Log'!$C$6:$C$505,$A30) | L30: =SUMIFS('Bills Log'!$F$6:$F$505,'Bills Log'!$A$6:$A$505,">="&DATE(Settings!$B$5,11,1),'Bills Log'!$A$6:$A$505,"<"&DATE(Settings!$B$5,12,1),'Bills Log'!$B$6:$B$505,Settings!$B$8,'Bills Log'!$C$6:$C$505,$A30) | M30: =SUMIFS('Bills Log'!$F$6:$F$505,'Bills Log'!$A$6:$A$505,">="&DATE(Settings!$B$5,12,1),'Bills Log'!$A$6:$A$505,"<"&DATE(Settings!$B$5+1,1,1),'Bills Log'!$B$6:$B$505,Settings!$B$8,'Bills Log'!$C$6:$C$505,$A30) | N30: =SUM(B30:M30) | O30: =IFERROR(N30/12,0)
A31: Gas | B31: =SUMIFS('Bills Log'!$F$6:$F$505,'Bills Log'!$A$6:$A$505,">="&DATE(Settings!$B$5,1,1),'Bills Log'!$A$6:$A$505,"<"&DATE(Settings!$B$5,2,1),'Bills Log'!$B$6:$B$505,Settings!$B$8,'Bills Log'!$C$6:$C$505,$A31) | C31: =SUMIFS('Bills Log'!$F$6:$F$505,'Bills Log'!$A$6:$A$505,">="&DATE(Settings!$B$5,2,1),'Bills Log'!$A$6:$A$505,"<"&DATE(Settings!$B$5,3,1),'Bills Log'!$B$6:$B$505,Settings!$B$8,'Bills Log'!$C$6:$C$505,$A31) | D31: =SUMIFS('Bills Log'!$F$6:$F$505,'Bills Log'!$A$6:$A$505,">="&DATE(Settings!$B$5,3,1),'Bills Log'!$A$6:$A$505,"<"&DATE(Settings!$B$5,4,1),'Bills Log'!$B$6:$B$505,Settings!$B$8,'Bills Log'!$C$6:$C$505,$A31) | E31: =SUMIFS('Bills Log'!$F$6:$F$505,'Bills Log'!$A$6:$A$505,">="&DATE(Settings!$B$5,4,1),'Bills Log'!$A$6:$A$505,"<"&DATE(Settings!$B$5,5,1),'Bills Log'!$B$6:$B$505,Settings!$B$8,'Bills Log'!$C$6:$C$505,$A31) | F31: =SUMIFS('Bills Log'!$F$6:$F$505,'Bills Log'!$A$6:$A$505,">="&DATE(Settings!$B$5,5,1),'Bills Log'!$A$6:$A$505,"<"&DATE(Settings!$B$5,6,1),'Bills Log'!$B$6:$B$505,Settings!$B$8,'Bills Log'!$C$6:$C$505,$A31) | G31: =SUMIFS('Bills Log'!$F$6:$F$505,'Bills Log'!$A$6:$A$505,">="&DATE(Settings!$B$5,6,1),'Bills Log'!$A$6:$A$505,"<"&DATE(Settings!$B$5,7,1),'Bills Log'!$B$6:$B$505,Settings!$B$8,'Bills Log'!$C$6:$C$505,$A31) | H31: =SUMIFS('Bills Log'!$F$6:$F$505,'Bills Log'!$A$6:$A$505,">="&DATE(Settings!$B$5,7,1),'Bills Log'!$A$6:$A$505,"<"&DATE(Settings!$B$5,8,1),'Bills Log'!$B$6:$B$505,Settings!$B$8,'Bills Log'!$C$6:$C$505,$A31) | I31: =SUMIFS('Bills Log'!$F$6:$F$505,'Bills Log'!$A$6:$A$505,">="&DATE(Settings!$B$5,8,1),'Bills Log'!$A$6:$A$505,"<"&DATE(Settings!$B$5,9,1),'Bills Log'!$B$6:$B$505,Settings!$B$8,'Bills Log'!$C$6:$C$505,$A31) | J31: =SUMIFS('Bills Log'!$F$6:$F$505,'Bills Log'!$A$6:$A$505,">="&DATE(Settings!$B$5,9,1),'Bills Log'!$A$6:$A$505,"<"&DATE(Settings!$B$5,10,1),'Bills Log'!$B$6:$B$505,Settings!$B$8,'Bills Log'!$C$6:$C$505,$A31) | K31: =SUMIFS('Bills Log'!$F$6:$F$505,'Bills Log'!$A$6:$A$505,">="&DATE(Settings!$B$5,10,1),'Bills Log'!$A$6:$A$505,"<"&DATE(Settings!$B$5,11,1),'Bills Log'!$B$6:$B$505,Settings!$B$8,'Bills Log'!$C$6:$C$505,$A31) | L31: =SUMIFS('Bills Log'!$F$6:$F$505,'Bills Log'!$A$6:$A$505,">="&DATE(Settings!$B$5,11,1),'Bills Log'!$A$6:$A$505,"<"&DATE(Settings!$B$5,12,1),'Bills Log'!$B$6:$B$505,Settings!$B$8,'Bills Log'!$C$6:$C$505,$A31) | M31: =SUMIFS('Bills Log'!$F$6:$F$505,'Bills Log'!$A$6:$A$505,">="&DATE(Settings!$B$5,12,1),'Bills Log'!$A$6:$A$505,"<"&DATE(Settings!$B$5+1,1,1),'Bills Log'!$B$6:$B$505,Settings!$B$8,'Bills Log'!$C$6:$C$505,$A31) | N31: =SUM(B31:M31) | O31: =IFERROR(N31/12,0)
A32: Water | B32: =SUMIFS('Bills Log'!$F$6:$F$505,'Bills Log'!$A$6:$A$505,">="&DATE(Settings!$B$5,1,1),'Bills Log'!$A$6:$A$505,"<"&DATE(Settings!$B$5,2,1),'Bills Log'!$B$6:$B$505,Settings!$B$8,'Bills Log'!$C$6:$C$505,$A32) | C32: =SUMIFS('Bills Log'!$F$6:$F$505,'Bills Log'!$A$6:$A$505,">="&DATE(Settings!$B$5,2,1),'Bills Log'!$A$6:$A$505,"<"&DATE(Settings!$B$5,3,1),'Bills Log'!$B$6:$B$505,Settings!$B$8,'Bills Log'!$C$6:$C$505,$A32) | D32: =SUMIFS('Bills Log'!$F$6:$F$505,'Bills Log'!$A$6:$A$505,">="&DATE(Settings!$B$5,3,1),'Bills Log'!$A$6:$A$505,"<"&DATE(Settings!$B$5,4,1),'Bills Log'!$B$6:$B$505,Settings!$B$8,'Bills Log'!$C$6:$C$505,$A32) | E32: =SUMIFS('Bills Log'!$F$6:$F$505,'Bills Log'!$A$6:$A$505,">="&DATE(Settings!$B$5,4,1),'Bills Log'!$A$6:$A$505,"<"&DATE(Settings!$B$5,5,1),'Bills Log'!$B$6:$B$505,Settings!$B$8,'Bills Log'!$C$6:$C$505,$A32) | F32: =SUMIFS('Bills Log'!$F$6:$F$505,'Bills Log'!$A$6:$A$505,">="&DATE(Settings!$B$5,5,1),'Bills Log'!$A$6:$A$505,"<"&DATE(Settings!$B$5,6,1),'Bills Log'!$B$6:$B$505,Settings!$B$8,'Bills Log'!$C$6:$C$505,$A32) | G32: =SUMIFS('Bills Log'!$F$6:$F$505,'Bills Log'!$A$6:$A$505,">="&DATE(Settings!$B$5,6,1),'Bills Log'!$A$6:$A$505,"<"&DATE(Settings!$B$5,7,1),'Bills Log'!$B$6:$B$505,Settings!$B$8,'Bills Log'!$C$6:$C$505,$A32) | H32: =SUMIFS('Bills Log'!$F$6:$F$505,'Bills Log'!$A$6:$A$505,">="&DATE(Settings!$B$5,7,1),'Bills Log'!$A$6:$A$505,"<"&DATE(Settings!$B$5,8,1),'Bills Log'!$B$6:$B$505,Settings!$B$8,'Bills Log'!$C$6:$C$505,$A32) | I32: =SUMIFS('Bills Log'!$F$6:$F$505,'Bills Log'!$A$6:$A$505,">="&DATE(Settings!$B$5,8,1),'Bills Log'!$A$6:$A$505,"<"&DATE(Settings!$B$5,9,1),'Bills Log'!$B$6:$B$505,Settings!$B$8,'Bills Log'!$C$6:$C$505,$A32) | J32: =SUMIFS('Bills Log'!$F$6:$F$505,'Bills Log'!$A$6:$A$505,">="&DATE(Settings!$B$5,9,1),'Bills Log'!$A$6:$A$505,"<"&DATE(Settings!$B$5,10,1),'Bills Log'!$B$6:$B$505,Settings!$B$8,'Bills Log'!$C$6:$C$505,$A32) | K32: =SUMIFS('Bills Log'!$F$6:$F$505,'Bills Log'!$A$6:$A$505,">="&DATE(Settings!$B$5,10,1),'Bills Log'!$A$6:$A$505,"<"&DATE(Settings!$B$5,11,1),'Bills Log'!$B$6:$B$505,Settings!$B$8,'Bills Log'!$C$6:$C$505,$A32) | L32: =SUMIFS('Bills Log'!$F$6:$F$505,'Bills Log'!$A$6:$A$505,">="&DATE(Settings!$B$5,11,1),'Bills Log'!$A$6:$A$505,"<"&DATE(Settings!$B$5,12,1),'Bills Log'!$B$6:$B$505,Settings!$B$8,'Bills Log'!$C$6:$C$505,$A32) | M32: =SUMIFS('Bills Log'!$F$6:$F$505,'Bills Log'!$A$6:$A$505,">="&DATE(Settings!$B$5,12,1),'Bills Log'!$A$6:$A$505,"<"&DATE(Settings!$B$5+1,1,1),'Bills Log'!$B$6:$B$505,Settings!$B$8,'Bills Log'!$C$6:$C$505,$A32) | N32: =SUM(B32:M32) | O32: =IFERROR(N32/12,0)
A33: Internet | B33: =SUMIFS('Bills Log'!$F$6:$F$505,'Bills Log'!$A$6:$A$505,">="&DATE(Settings!$B$5,1,1),'Bills Log'!$A$6:$A$505,"<"&DATE(Settings!$B$5,2,1),'Bills Log'!$B$6:$B$505,Settings!$B$8,'Bills Log'!$C$6:$C$505,$A33) | C33: =SUMIFS('Bills Log'!$F$6:$F$505,'Bills Log'!$A$6:$A$505,">="&DATE(Settings!$B$5,2,1),'Bills Log'!$A$6:$A$505,"<"&DATE(Settings!$B$5,3,1),'Bills Log'!$B$6:$B$505,Settings!$B$8,'Bills Log'!$C$6:$C$505,$A33) | D33: =SUMIFS('Bills Log'!$F$6:$F$505,'Bills Log'!$A$6:$A$505,">="&DATE(Settings!$B$5,3,1),'Bills Log'!$A$6:$A$505,"<"&DATE(Settings!$B$5,4,1),'Bills Log'!$B$6:$B$505,Settings!$B$8,'Bills Log'!$C$6:$C$505,$A33) | E33: =SUMIFS('Bills Log'!$F$6:$F$505,'Bills Log'!$A$6:$A$505,">="&DATE(Settings!$B$5,4,1),'Bills Log'!$A$6:$A$505,"<"&DATE(Settings!$B$5,5,1),'Bills Log'!$B$6:$B$505,Settings!$B$8,'Bills Log'!$C$6:$C$505,$A33) | F33: =SUMIFS('Bills Log'!$F$6:$F$505,'Bills Log'!$A$6:$A$505,">="&DATE(Settings!$B$5,5,1),'Bills Log'!$A$6:$A$505,"<"&DATE(Settings!$B$5,6,1),'Bills Log'!$B$6:$B$505,Settings!$B$8,'Bills Log'!$C$6:$C$505,$A33) | G33: =SUMIFS('Bills Log'!$F$6:$F$505,'Bills Log'!$A$6:$A$505,">="&DATE(Settings!$B$5,6,1),'Bills Log'!$A$6:$A$505,"<"&DATE(Settings!$B$5,7,1),'Bills Log'!$B$6:$B$505,Settings!$B$8,'Bills Log'!$C$6:$C$505,$A33) | H33: =SUMIFS('Bills Log'!$F$6:$F$505,'Bills Log'!$A$6:$A$505,">="&DATE(Settings!$B$5,7,1),'Bills Log'!$A$6:$A$505,"<"&DATE(Settings!$B$5,8,1),'Bills Log'!$B$6:$B$505,Settings!$B$8,'Bills Log'!$C$6:$C$505,$A33) | I33: =SUMIFS('Bills Log'!$F$6:$F$505,'Bills Log'!$A$6:$A$505,">="&DATE(Settings!$B$5,8,1),'Bills Log'!$A$6:$A$505,"<"&DATE(Settings!$B$5,9,1),'Bills Log'!$B$6:$B$505,Settings!$B$8,'Bills Log'!$C$6:$C$505,$A33) | J33: =SUMIFS('Bills Log'!$F$6:$F$505,'Bills Log'!$A$6:$A$505,">="&DATE(Settings!$B$5,9,1),'Bills Log'!$A$6:$A$505,"<"&DATE(Settings!$B$5,10,1),'Bills Log'!$B$6:$B$505,Settings!$B$8,'Bills Log'!$C$6:$C$505,$A33) | K33: =SUMIFS('Bills Log'!$F$6:$F$505,'Bills Log'!$A$6:$A$505,">="&DATE(Settings!$B$5,10,1),'Bills Log'!$A$6:$A$505,"<"&DATE(Settings!$B$5,11,1),'Bills Log'!$B$6:$B$505,Settings!$B$8,'Bills Log'!$C$6:$C$505,$A33) | L33: =SUMIFS('Bills Log'!$F$6:$F$505,'Bills Log'!$A$6:$A$505,">="&DATE(Settings!$B$5,11,1),'Bills Log'!$A$6:$A$505,"<"&DATE(Settings!$B$5,12,1),'Bills Log'!$B$6:$B$505,Settings!$B$8,'Bills Log'!$C$6:$C$505,$A33) | M33: =SUMIFS('Bills Log'!$F$6:$F$505,'Bills Log'!$A$6:$A$505,">="&DATE(Settings!$B$5,12,1),'Bills Log'!$A$6:$A$505,"<"&DATE(Settings!$B$5+1,1,1),'Bills Log'!$B$6:$B$505,Settings!$B$8,'Bills Log'!$C$6:$C$505,$A33) | N33: =SUM(B33:M33) | O33: =IFERROR(N33/12,0)
A34: Trash | B34: =SUMIFS('Bills Log'!$F$6:$F$505,'Bills Log'!$A$6:$A$505,">="&DATE(Settings!$B$5,1,1),'Bills Log'!$A$6:$A$505,"<"&DATE(Settings!$B$5,2,1),'Bills Log'!$B$6:$B$505,Settings!$B$8,'Bills Log'!$C$6:$C$505,$A34) | C34: =SUMIFS('Bills Log'!$F$6:$F$505,'Bills Log'!$A$6:$A$505,">="&DATE(Settings!$B$5,2,1),'Bills Log'!$A$6:$A$505,"<"&DATE(Settings!$B$5,3,1),'Bills Log'!$B$6:$B$505,Settings!$B$8,'Bills Log'!$C$6:$C$505,$A34) | D34: =SUMIFS('Bills Log'!$F$6:$F$505,'Bills Log'!$A$6:$A$505,">="&DATE(Settings!$B$5,3,1),'Bills Log'!$A$6:$A$505,"<"&DATE(Settings!$B$5,4,1),'Bills Log'!$B$6:$B$505,Settings!$B$8,'Bills Log'!$C$6:$C$505,$A34) | E34: =SUMIFS('Bills Log'!$F$6:$F$505,'Bills Log'!$A$6:$A$505,">="&DATE(Settings!$B$5,4,1),'Bills Log'!$A$6:$A$505,"<"&DATE(Settings!$B$5,5,1),'Bills Log'!$B$6:$B$505,Settings!$B$8,'Bills Log'!$C$6:$C$505,$A34) | F34: =SUMIFS('Bills Log'!$F$6:$F$505,'Bills Log'!$A$6:$A$505,">="&DATE(Settings!$B$5,5,1),'Bills Log'!$A$6:$A$505,"<"&DATE(Settings!$B$5,6,1),'Bills Log'!$B$6:$B$505,Settings!$B$8,'Bills Log'!$C$6:$C$505,$A34) | G34: =SUMIFS('Bills Log'!$F$6:$F$505,'Bills Log'!$A$6:$A$505,">="&DATE(Settings!$B$5,6,1),'Bills Log'!$A$6:$A$505,"<"&DATE(Settings!$B$5,7,1),'Bills Log'!$B$6:$B$505,Settings!$B$8,'Bills Log'!$C$6:$C$505,$A34) | H34: =SUMIFS('Bills Log'!$F$6:$F$505,'Bills Log'!$A$6:$A$505,">="&DATE(Settings!$B$5,7,1),'Bills Log'!$A$6:$A$505,"<"&DATE(Settings!$B$5,8,1),'Bills Log'!$B$6:$B$505,Settings!$B$8,'Bills Log'!$C$6:$C$505,$A34) | I34: =SUMIFS('Bills Log'!$F$6:$F$505,'Bills Log'!$A$6:$A$505,">="&DATE(Settings!$B$5,8,1),'Bills Log'!$A$6:$A$505,"<"&DATE(Settings!$B$5,9,1),'Bills Log'!$B$6:$B$505,Settings!$B$8,'Bills Log'!$C$6:$C$505,$A34) | J34: =SUMIFS('Bills Log'!$F$6:$F$505,'Bills Log'!$A$6:$A$505,">="&DATE(Settings!$B$5,9,1),'Bills Log'!$A$6:$A$505,"<"&DATE(Settings!$B$5,10,1),'Bills Log'!$B$6:$B$505,Settings!$B$8,'Bills Log'!$C$6:$C$505,$A34) | K34: =SUMIFS('Bills Log'!$F$6:$F$505,'Bills Log'!$A$6:$A$505,">="&DATE(Settings!$B$5,10,1),'Bills Log'!$A$6:$A$505,"<"&DATE(Settings!$B$5,11,1),'Bills Log'!$B$6:$B$505,Settings!$B$8,'Bills Log'!$C$6:$C$505,$A34) | L34: =SUMIFS('Bills Log'!$F$6:$F$505,'Bills Log'!$A$6:$A$505,">="&DATE(Settings!$B$5,11,1),'Bills Log'!$A$6:$A$505,"<"&DATE(Settings!$B$5,12,1),'Bills Log'!$B$6:$B$505,Settings!$B$8,'Bills Log'!$C$6:$C$505,$A34) | M34: =SUMIFS('Bills Log'!$F$6:$F$505,'Bills Log'!$A$6:$A$505,">="&DATE(Settings!$B$5,12,1),'Bills Log'!$A$6:$A$505,"<"&DATE(Settings!$B$5+1,1,1),'Bills Log'!$B$6:$B$505,Settings!$B$8,'Bills Log'!$C$6:$C$505,$A34) | N34: =SUM(B34:M34) | O34: =IFERROR(N34/12,0)
A35: Propane | B35: =SUMIFS('Bills Log'!$F$6:$F$505,'Bills Log'!$A$6:$A$505,">="&DATE(Settings!$B$5,1,1),'Bills Log'!$A$6:$A$505,"<"&DATE(Settings!$B$5,2,1),'Bills Log'!$B$6:$B$505,Settings!$B$8,'Bills Log'!$C$6:$C$505,$A35) | C35: =SUMIFS('Bills Log'!$F$6:$F$505,'Bills Log'!$A$6:$A$505,">="&DATE(Settings!$B$5,2,1),'Bills Log'!$A$6:$A$505,"<"&DATE(Settings!$B$5,3,1),'Bills Log'!$B$6:$B$505,Settings!$B$8,'Bills Log'!$C$6:$C$505,$A35) | D35: =SUMIFS('Bills Log'!$F$6:$F$505,'Bills Log'!$A$6:$A$505,">="&DATE(Settings!$B$5,3,1),'Bills Log'!$A$6:$A$505,"<"&DATE(Settings!$B$5,4,1),'Bills Log'!$B$6:$B$505,Settings!$B$8,'Bills Log'!$C$6:$C$505,$A35) | E35: =SUMIFS('Bills Log'!$F$6:$F$505,'Bills Log'!$A$6:$A$505,">="&DATE(Settings!$B$5,4,1),'Bills Log'!$A$6:$A$505,"<"&DATE(Settings!$B$5,5,1),'Bills Log'!$B$6:$B$505,Settings!$B$8,'Bills Log'!$C$6:$C$505,$A35) | F35: =SUMIFS('Bills Log'!$F$6:$F$505,'Bills Log'!$A$6:$A$505,">="&DATE(Settings!$B$5,5,1),'Bills Log'!$A$6:$A$505,"<"&DATE(Settings!$B$5,6,1),'Bills Log'!$B$6:$B$505,Settings!$B$8,'Bills Log'!$C$6:$C$505,$A35) | G35: =SUMIFS('Bills Log'!$F$6:$F$505,'Bills Log'!$A$6:$A$505,">="&DATE(Settings!$B$5,6,1),'Bills Log'!$A$6:$A$505,"<"&DATE(Settings!$B$5,7,1),'Bills Log'!$B$6:$B$505,Settings!$B$8,'Bills Log'!$C$6:$C$505,$A35) | H35: =SUMIFS('Bills Log'!$F$6:$F$505,'Bills Log'!$A$6:$A$505,">="&DATE(Settings!$B$5,7,1),'Bills Log'!$A$6:$A$505,"<"&DATE(Settings!$B$5,8,1),'Bills Log'!$B$6:$B$505,Settings!$B$8,'Bills Log'!$C$6:$C$505,$A35) | I35: =SUMIFS('Bills Log'!$F$6:$F$505,'Bills Log'!$A$6:$A$505,">="&DATE(Settings!$B$5,8,1),'Bills Log'!$A$6:$A$505,"<"&DATE(Settings!$B$5,9,1),'Bills Log'!$B$6:$B$505,Settings!$B$8,'Bills Log'!$C$6:$C$505,$A35) | J35: =SUMIFS('Bills Log'!$F$6:$F$505,'Bills Log'!$A$6:$A$505,">="&DATE(Settings!$B$5,9,1),'Bills Log'!$A$6:$A$505,"<"&DATE(Settings!$B$5,10,1),'Bills Log'!$B$6:$B$505,Settings!$B$8,'Bills Log'!$C$6:$C$505,$A35) | K35: =SUMIFS('Bills Log'!$F$6:$F$505,'Bills Log'!$A$6:$A$505,">="&DATE(Settings!$B$5,10,1),'Bills Log'!$A$6:$A$505,"<"&DATE(Settings!$B$5,11,1),'Bills Log'!$B$6:$B$505,Settings!$B$8,'Bills Log'!$C$6:$C$505,$A35) | L35: =SUMIFS('Bills Log'!$F$6:$F$505,'Bills Log'!$A$6:$A$505,">="&DATE(Settings!$B$5,11,1),'Bills Log'!$A$6:$A$505,"<"&DATE(Settings!$B$5,12,1),'Bills Log'!$B$6:$B$505,Settings!$B$8,'Bills Log'!$C$6:$C$505,$A35) | M35: =SUMIFS('Bills Log'!$F$6:$F$505,'Bills Log'!$A$6:$A$505,">="&DATE(Settings!$B$5,12,1),'Bills Log'!$A$6:$A$505,"<"&DATE(Settings!$B$5+1,1,1),'Bills Log'!$B$6:$B$505,Settings!$B$8,'Bills Log'!$C$6:$C$505,$A35) | N35: =SUM(B35:M35) | O35: =IFERROR(N35/12,0)
A36: TOTAL | B36: =SUM(B30:B35) | C36: =SUM(C30:C35) | D36: =SUM(D30:D35) | E36: =SUM(E30:E35) | F36: =SUM(F30:F35) | G36: =SUM(G30:G35) | H36: =SUM(H30:H35) | I36: =SUM(I30:I35) | ... O36: =SUM(O30:O35)
A50: ="Property: "&Settings!$B$9
A51: Service | B51: Jan | C51: Feb | D51: Mar | E51: Apr | F51: May | G51: Jun | H51: Jul | I51: Aug | J51: Sep | K51: Oct | L51: Nov | M51: Dec | N51: Total | O51: Avg
A52: Electric | B52: =SUMIFS('Bills Log'!$F$6:$F$505,'Bills Log'!$A$6:$A$505,">="&DATE(Settings!$B$5,1,1),'Bills Log'!$A$6:$A$505,"<"&DATE(Settings!$B$5,2,1),'Bills Log'!$B$6:$B$505,Settings!$B$9,'Bills Log'!$C$6:$C$505,$A52) | C52: =SUMIFS('Bills Log'!$F$6:$F$505,'Bills Log'!$A$6:$A$505,">="&DATE(Settings!$B$5,2,1),'Bills Log'!$A$6:$A$505,"<"&DATE(Settings!$B$5,3,1),'Bills Log'!$B$6:$B$505,Settings!$B$9,'Bills Log'!$C$6:$C$505,$A52) | D52: =SUMIFS('Bills Log'!$F$6:$F$505,'Bills Log'!$A$6:$A$505,">="&DATE(Settings!$B$5,3,1),'Bills Log'!$A$6:$A$505,"<"&DATE(Settings!$B$5,4,1),'Bills Log'!$B$6:$B$505,Settings!$B$9,'Bills Log'!$C$6:$C$505,$A52) | E52: =SUMIFS('Bills Log'!$F$6:$F$505,'Bills Log'!$A$6:$A$505,">="&DATE(Settings!$B$5,4,1),'Bills Log'!$A$6:$A$505,"<"&DATE(Settings!$B$5,5,1),'Bills Log'!$B$6:$B$505,Settings!$B$9,'Bills Log'!$C$6:$C$505,$A52) | F52: =SUMIFS('Bills Log'!$F$6:$F$505,'Bills Log'!$A$6:$A$505,">="&DATE(Settings!$B$5,5,1),'Bills Log'!$A$6:$A$505,"<"&DATE(Settings!$B$5,6,1),'Bills Log'!$B$6:$B$505,Settings!$B$9,'Bills Log'!$C$6:$C$505,$A52) | G52: =SUMIFS('Bills Log'!$F$6:$F$505,'Bills Log'!$A$6:$A$505,">="&DATE(Settings!$B$5,6,1),'Bills Log'!$A$6:$A$505,"<"&DATE(Settings!$B$5,7,1),'Bills Log'!$B$6:$B$505,Settings!$B$9,'Bills Log'!$C$6:$C$505,$A52) | H52: =SUMIFS('Bills Log'!$F$6:$F$505,'Bills Log'!$A$6:$A$505,">="&DATE(Settings!$B$5,7,1),'Bills Log'!$A$6:$A$505,"<"&DATE(Settings!$B$5,8,1),'Bills Log'!$B$6:$B$505,Settings!$B$9,'Bills Log'!$C$6:$C$505,$A52) | I52: =SUMIFS('Bills Log'!$F$6:$F$505,'Bills Log'!$A$6:$A$505,">="&DATE(Settings!$B$5,8,1),'Bills Log'!$A$6:$A$505,"<"&DATE(Settings!$B$5,9,1),'Bills Log'!$B$6:$B$505,Settings!$B$9,'Bills Log'!$C$6:$C$505,$A52) | J52: =SUMIFS('Bills Log'!$F$6:$F$505,'Bills Log'!$A$6:$A$505,">="&DATE(Settings!$B$5,9,1),'Bills Log'!$A$6:$A$505,"<"&DATE(Settings!$B$5,10,1),'Bills Log'!$B$6:$B$505,Settings!$B$9,'Bills Log'!$C$6:$C$505,$A52) | K52: =SUMIFS('Bills Log'!$F$6:$F$505,'Bills Log'!$A$6:$A$505,">="&DATE(Settings!$B$5,10,1),'Bills Log'!$A$6:$A$505,"<"&DATE(Settings!$B$5,11,1),'Bills Log'!$B$6:$B$505,Settings!$B$9,'Bills Log'!$C$6:$C$505,$A52) | L52: =SUMIFS('Bills Log'!$F$6:$F$505,'Bills Log'!$A$6:$A$505,">="&DATE(Settings!$B$5,11,1),'Bills Log'!$A$6:$A$505,"<"&DATE(Settings!$B$5,12,1),'Bills Log'!$B$6:$B$505,Settings!$B$9,'Bills Log'!$C$6:$C$505,$A52) | M52: =SUMIFS('Bills Log'!$F$6:$F$505,'Bills Log'!$A$6:$A$505,">="&DATE(Settings!$B$5,12,1),'Bills Log'!$A$6:$A$505,"<"&DATE(Settings!$B$5+1,1,1),'Bills Log'!$B$6:$B$505,Settings!$B$9,'Bills Log'!$C$6:$C$505,$A52) | N52: =SUM(B52:M52) | O52: =IFERROR(N52/12,0)
A53: Gas | B53: =SUMIFS('Bills Log'!$F$6:$F$505,'Bills Log'!$A$6:$A$505,">="&DATE(Settings!$B$5,1,1),'Bills Log'!$A$6:$A$505,"<"&DATE(Settings!$B$5,2,1),'Bills Log'!$B$6:$B$505,Settings!$B$9,'Bills Log'!$C$6:$C$505,$A53) | C53: =SUMIFS('Bills Log'!$F$6:$F$505,'Bills Log'!$A$6:$A$505,">="&DATE(Settings!$B$5,2,1),'Bills Log'!$A$6:$A$505,"<"&DATE(Settings!$B$5,3,1),'Bills Log'!$B$6:$B$505,Settings!$B$9,'Bills Log'!$C$6:$C$505,$A53) | D53: =SUMIFS('Bills Log'!$F$6:$F$505,'Bills Log'!$A$6:$A$505,">="&DATE(Settings!$B$5,3,1),'Bills Log'!$A$6:$A$505,"<"&DATE(Settings!$B$5,4,1),'Bills Log'!$B$6:$B$505,Settings!$B$9,'Bills Log'!$C$6:$C$505,$A53) | E53: =SUMIFS('Bills Log'!$F$6:$F$505,'Bills Log'!$A$6:$A$505,">="&DATE(Settings!$B$5,4,1),'Bills Log'!$A$6:$A$505,"<"&DATE(Settings!$B$5,5,1),'Bills Log'!$B$6:$B$505,Settings!$B$9,'Bills Log'!$C$6:$C$505,$A53) | F53: =SUMIFS('Bills Log'!$F$6:$F$505,'Bills Log'!$A$6:$A$505,">="&DATE(Settings!$B$5,5,1),'Bills Log'!$A$6:$A$505,"<"&DATE(Settings!$B$5,6,1),'Bills Log'!$B$6:$B$505,Settings!$B$9,'Bills Log'!$C$6:$C$505,$A53) | G53: =SUMIFS('Bills Log'!$F$6:$F$505,'Bills Log'!$A$6:$A$505,">="&DATE(Settings!$B$5,6,1),'Bills Log'!$A$6:$A$505,"<"&DATE(Settings!$B$5,7,1),'Bills Log'!$B$6:$B$505,Settings!$B$9,'Bills Log'!$C$6:$C$505,$A53) | H53: =SUMIFS('Bills Log'!$F$6:$F$505,'Bills Log'!$A$6:$A$505,">="&DATE(Settings!$B$5,7,1),'Bills Log'!$A$6:$A$505,"<"&DATE(Settings!$B$5,8,1),'Bills Log'!$B$6:$B$505,Settings!$B$9,'Bills Log'!$C$6:$C$505,$A53) | I53: =SUMIFS('Bills Log'!$F$6:$F$505,'Bills Log'!$A$6:$A$505,">="&DATE(Settings!$B$5,8,1),'Bills Log'!$A$6:$A$505,"<"&DATE(Settings!$B$5,9,1),'Bills Log'!$B$6:$B$505,Settings!$B$9,'Bills Log'!$C$6:$C$505,$A53) | J53: =SUMIFS('Bills Log'!$F$6:$F$505,'Bills Log'!$A$6:$A$505,">="&DATE(Settings!$B$5,9,1),'Bills Log'!$A$6:$A$505,"<"&DATE(Settings!$B$5,10,1),'Bills Log'!$B$6:$B$505,Settings!$B$9,'Bills Log'!$C$6:$C$505,$A53) | K53: =SUMIFS('Bills Log'!$F$6:$F$505,'Bills Log'!$A$6:$A$505,">="&DATE(Settings!$B$5,10,1),'Bills Log'!$A$6:$A$505,"<"&DATE(Settings!$B$5,11,1),'Bills Log'!$B$6:$B$505,Settings!$B$9,'Bills Log'!$C$6:$C$505,$A53) | L53: =SUMIFS('Bills Log'!$F$6:$F$505,'Bills Log'!$A$6:$A$505,">="&DATE(Settings!$B$5,11,1),'Bills Log'!$A$6:$A$505,"<"&DATE(Settings!$B$5,12,1),'Bills Log'!$B$6:$B$505,Settings!$B$9,'Bills Log'!$C$6:$C$505,$A53) | M53: =SUMIFS('Bills Log'!$F$6:$F$505,'Bills Log'!$A$6:$A$505,">="&DATE(Settings!$B$5,12,1),'Bills Log'!$A$6:$A$505,"<"&DATE(Settings!$B$5+1,1,1),'Bills Log'!$B$6:$B$505,Settings!$B$9,'Bills Log'!$C$6:$C$505,$A53) | N53: =SUM(B53:M53) | O53: =IFERROR(N53/12,0)
A54: Water | B54: =SUMIFS('Bills Log'!$F$6:$F$505,'Bills Log'!$A$6:$A$505,">="&DATE(Settings!$B$5,1,1),'Bills Log'!$A$6:$A$505,"<"&DATE(Settings!$B$5,2,1),'Bills Log'!$B$6:$B$505,Settings!$B$9,'Bills Log'!$C$6:$C$505,$A54) | C54: =SUMIFS('Bills Log'!$F$6:$F$505,'Bills Log'!$A$6:$A$505,">="&DATE(Settings!$B$5,2,1),'Bills Log'!$A$6:$A$505,"<"&DATE(Settings!$B$5,3,1),'Bills Log'!$B$6:$B$505,Settings!$B$9,'Bills Log'!$C$6:$C$505,$A54) | D54: =SUMIFS('Bills Log'!$F$6:$F$505,'Bills Log'!$A$6:$A$505,">="&DATE(Settings!$B$5,3,1),'Bills Log'!$A$6:$A$505,"<"&DATE(Settings!$B$5,4,1),'Bills Log'!$B$6:$B$505,Settings!$B$9,'Bills Log'!$C$6:$C$505,$A54) | E54: =SUMIFS('Bills Log'!$F$6:$F$505,'Bills Log'!$A$6:$A$505,">="&DATE(Settings!$B$5,4,1),'Bills Log'!$A$6:$A$505,"<"&DATE(Settings!$B$5,5,1),'Bills Log'!$B$6:$B$505,Settings!$B$9,'Bills Log'!$C$6:$C$505,$A54) | F54: =SUMIFS('Bills Log'!$F$6:$F$505,'Bills Log'!$A$6:$A$505,">="&DATE(Settings!$B$5,5,1),'Bills Log'!$A$6:$A$505,"<"&DATE(Settings!$B$5,6,1),'Bills Log'!$B$6:$B$505,Settings!$B$9,'Bills Log'!$C$6:$C$505,$A54) | G54: =SUMIFS('Bills Log'!$F$6:$F$505,'Bills Log'!$A$6:$A$505,">="&DATE(Settings!$B$5,6,1),'Bills Log'!$A$6:$A$505,"<"&DATE(Settings!$B$5,7,1),'Bills Log'!$B$6:$B$505,Settings!$B$9,'Bills Log'!$C$6:$C$505,$A54) | H54: =SUMIFS('Bills Log'!$F$6:$F$505,'Bills Log'!$A$6:$A$505,">="&DATE(Settings!$B$5,7,1),'Bills Log'!$A$6:$A$505,"<"&DATE(Settings!$B$5,8,1),'Bills Log'!$B$6:$B$505,Settings!$B$9,'Bills Log'!$C$6:$C$505,$A54) | I54: =SUMIFS('Bills Log'!$F$6:$F$505,'Bills Log'!$A$6:$A$505,">="&DATE(Settings!$B$5,8,1),'Bills Log'!$A$6:$A$505,"<"&DATE(Settings!$B$5,9,1),'Bills Log'!$B$6:$B$505,Settings!$B$9,'Bills Log'!$C$6:$C$505,$A54) | J54: =SUMIFS('Bills Log'!$F$6:$F$505,'Bills Log'!$A$6:$A$505,">="&DATE(Settings!$B$5,9,1),'Bills Log'!$A$6:$A$505,"<"&DATE(Settings!$B$5,10,1),'Bills Log'!$B$6:$B$505,Settings!$B$9,'Bills Log'!$C$6:$C$505,$A54) | K54: =SUMIFS('Bills Log'!$F$6:$F$505,'Bills Log'!$A$6:$A$505,">="&DATE(Settings!$B$5,10,1),'Bills Log'!$A$6:$A$505,"<"&DATE(Settings!$B$5,11,1),'Bills Log'!$B$6:$B$505,Settings!$B$9,'Bills Log'!$C$6:$C$505,$A54) | L54: =SUMIFS('Bills Log'!$F$6:$F$505,'Bills Log'!$A$6:$A$505,">="&DATE(Settings!$B$5,11,1),'Bills Log'!$A$6:$A$505,"<"&DATE(Settings!$B$5,12,1),'Bills Log'!$B$6:$B$505,Settings!$B$9,'Bills Log'!$C$6:$C$505,$A54) | M54: =SUMIFS('Bills Log'!$F$6:$F$505,'Bills Log'!$A$6:$A$505,">="&DATE(Settings!$B$5,12,1),'Bills Log'!$A$6:$A$505,"<"&DATE(Settings!$B$5+1,1,1),'Bills Log'!$B$6:$B$505,Settings!$B$9,'Bills Log'!$C$6:$C$505,$A54) | N54: =SUM(B54:M54) | O54: =IFERROR(N54/12,0)
A55: Internet | B55: =SUMIFS('Bills Log'!$F$6:$F$505,'Bills Log'!$A$6:$A$505,">="&DATE(Settings!$B$5,1,1),'Bills Log'!$A$6:$A$505,"<"&DATE(Settings!$B$5,2,1),'Bills Log'!$B$6:$B$505,Settings!$B$9,'Bills Log'!$C$6:$C$505,$A55) | C55: =SUMIFS('Bills Log'!$F$6:$F$505,'Bills Log'!$A$6:$A$505,">="&DATE(Settings!$B$5,2,1),'Bills Log'!$A$6:$A$505,"<"&DATE(Settings!$B$5,3,1),'Bills Log'!$B$6:$B$505,Settings!$B$9,'Bills Log'!$C$6:$C$505,$A55) | D55: =SUMIFS('Bills Log'!$F$6:$F$505,'Bills Log'!$A$6:$A$505,">="&DATE(Settings!$B$5,3,1),'Bills Log'!$A$6:$A$505,"<"&DATE(Settings!$B$5,4,1),'Bills Log'!$B$6:$B$505,Settings!$B$9,'Bills Log'!$C$6:$C$505,$A55) | E55: =SUMIFS('Bills Log'!$F$6:$F$505,'Bills Log'!$A$6:$A$505,">="&DATE(Settings!$B$5,4,1),'Bills Log'!$A$6:$A$505,"<"&DATE(Settings!$B$5,5,1),'Bills Log'!$B$6:$B$505,Settings!$B$9,'Bills Log'!$C$6:$C$505,$A55) | F55: =SUMIFS('Bills Log'!$F$6:$F$505,'Bills Log'!$A$6:$A$505,">="&DATE(Settings!$B$5,5,1),'Bills Log'!$A$6:$A$505,"<"&DATE(Settings!$B$5,6,1),'Bills Log'!$B$6:$B$505,Settings!$B$9,'Bills Log'!$C$6:$C$505,$A55) | G55: =SUMIFS('Bills Log'!$F$6:$F$505,'Bills Log'!$A$6:$A$505,">="&DATE(Settings!$B$5,6,1),'Bills Log'!$A$6:$A$505,"<"&DATE(Settings!$B$5,7,1),'Bills Log'!$B$6:$B$505,Settings!$B$9,'Bills Log'!$C$6:$C$505,$A55) | H55: =SUMIFS('Bills Log'!$F$6:$F$505,'Bills Log'!$A$6:$A$505,">="&DATE(Settings!$B$5,7,1),'Bills Log'!$A$6:$A$505,"<"&DATE(Settings!$B$5,8,1),'Bills Log'!$B$6:$B$505,Settings!$B$9,'Bills Log'!$C$6:$C$505,$A55) | I55: =SUMIFS('Bills Log'!$F$6:$F$505,'Bills Log'!$A$6:$A$505,">="&DATE(Settings!$B$5,8,1),'Bills Log'!$A$6:$A$505,"<"&DATE(Settings!$B$5,9,1),'Bills Log'!$B$6:$B$505,Settings!$B$9,'Bills Log'!$C$6:$C$505,$A55) | J55: =SUMIFS('Bills Log'!$F$6:$F$505,'Bills Log'!$A$6:$A$505,">="&DATE(Settings!$B$5,9,1),'Bills Log'!$A$6:$A$505,"<"&DATE(Settings!$B$5,10,1),'Bills Log'!$B$6:$B$505,Settings!$B$9,'Bills Log'!$C$6:$C$505,$A55) | K55: =SUMIFS('Bills Log'!$F$6:$F$505,'Bills Log'!$A$6:$A$505,">="&DATE(Settings!$B$5,10,1),'Bills Log'!$A$6:$A$505,"<"&DATE(Settings!$B$5,11,1),'Bills Log'!$B$6:$B$505,Settings!$B$9,'Bills Log'!$C$6:$C$505,$A55) | L55: =SUMIFS('Bills Log'!$F$6:$F$505,'Bills Log'!$A$6:$A$505,">="&DATE(Settings!$B$5,11,1),'Bills Log'!$A$6:$A$505,"<"&DATE(Settings!$B$5,12,1),'Bills Log'!$B$6:$B$505,Settings!$B$9,'Bills Log'!$C$6:$C$505,$A55) | M55: =SUMIFS('Bills Log'!$F$6:$F$505,'Bills Log'!$A$6:$A$505,">="&DATE(Settings!$B$5,12,1),'Bills Log'!$A$6:$A$505,"<"&DATE(Settings!$B$5+1,1,1),'Bills Log'!$B$6:$B$505,Settings!$B$9,'Bills Log'!$C$6:$C$505,$A55) | N55: =SUM(B55:M55) | O55: =IFERROR(N55/12,0)
A56: Trash | B56: =SUMIFS('Bills Log'!$F$6:$F$505,'Bills Log'!$A$6:$A$505,">="&DATE(Settings!$B$5,1,1),'Bills Log'!$A$6:$A$505,"<"&DATE(Settings!$B$5,2,1),'Bills Log'!$B$6:$B$505,Settings!$B$9,'Bills Log'!$C$6:$C$505,$A56) | C56: =SUMIFS('Bills Log'!$F$6:$F$505,'Bills Log'!$A$6:$A$505,">="&DATE(Settings!$B$5,2,1),'Bills Log'!$A$6:$A$505,"<"&DATE(Settings!$B$5,3,1),'Bills Log'!$B$6:$B$505,Settings!$B$9,'Bills Log'!$C$6:$C$505,$A56) | D56: =SUMIFS('Bills Log'!$F$6:$F$505,'Bills Log'!$A$6:$A$505,">="&DATE(Settings!$B$5,3,1),'Bills Log'!$A$6:$A$505,"<"&DATE(Settings!$B$5,4,1),'Bills Log'!$B$6:$B$505,Settings!$B$9,'Bills Log'!$C$6:$C$505,$A56) | E56: =SUMIFS('Bills Log'!$F$6:$F$505,'Bills Log'!$A$6:$A$505,">="&DATE(Settings!$B$5,4,1),'Bills Log'!$A$6:$A$505,"<"&DATE(Settings!$B$5,5,1),'Bills Log'!$B$6:$B$505,Settings!$B$9,'Bills Log'!$C$6:$C$505,$A56) | F56: =SUMIFS('Bills Log'!$F$6:$F$505,'Bills Log'!$A$6:$A$505,">="&DATE(Settings!$B$5,5,1),'Bills Log'!$A$6:$A$505,"<"&DATE(Settings!$B$5,6,1),'Bills Log'!$B$6:$B$505,Settings!$B$9,'Bills Log'!$C$6:$C$505,$A56) | G56: =SUMIFS('Bills Log'!$F$6:$F$505,'Bills Log'!$A$6:$A$505,">="&DATE(Settings!$B$5,6,1),'Bills Log'!$A$6:$A$505,"<"&DATE(Settings!$B$5,7,1),'Bills Log'!$B$6:$B$505,Settings!$B$9,'Bills Log'!$C$6:$C$505,$A56) | H56: =SUMIFS('Bills Log'!$F$6:$F$505,'Bills Log'!$A$6:$A$505,">="&DATE(Settings!$B$5,7,1),'Bills Log'!$A$6:$A$505,"<"&DATE(Settings!$B$5,8,1),'Bills Log'!$B$6:$B$505,Settings!$B$9,'Bills Log'!$C$6:$C$505,$A56) | I56: =SUMIFS('Bills Log'!$F$6:$F$505,'Bills Log'!$A$6:$A$505,">="&DATE(Settings!$B$5,8,1),'Bills Log'!$A$6:$A$505,"<"&DATE(Settings!$B$5,9,1),'Bills Log'!$B$6:$B$505,Settings!$B$9,'Bills Log'!$C$6:$C$505,$A56) | J56: =SUMIFS('Bills Log'!$F$6:$F$505,'Bills Log'!$A$6:$A$505,">="&DATE(Settings!$B$5,9,1),'Bills Log'!$A$6:$A$505,"<"&DATE(Settings!$B$5,10,1),'Bills Log'!$B$6:$B$505,Settings!$B$9,'Bills Log'!$C$6:$C$505,$A56) | K56: =SUMIFS('Bills Log'!$F$6:$F$505,'Bills Log'!$A$6:$A$505,">="&DATE(Settings!$B$5,10,1),'Bills Log'!$A$6:$A$505,"<"&DATE(Settings!$B$5,11,1),'Bills Log'!$B$6:$B$505,Settings!$B$9,'Bills Log'!$C$6:$C$505,$A56) | L56: =SUMIFS('Bills Log'!$F$6:$F$505,'Bills Log'!$A$6:$A$505,">="&DATE(Settings!$B$5,11,1),'Bills Log'!$A$6:$A$505,"<"&DATE(Settings!$B$5,12,1),'Bills Log'!$B$6:$B$505,Settings!$B$9,'Bills Log'!$C$6:$C$505,$A56) | M56: =SUMIFS('Bills Log'!$F$6:$F$505,'Bills Log'!$A$6:$A$505,">="&DATE(Settings!$B$5,12,1),'Bills Log'!$A$6:$A$505,"<"&DATE(Settings!$B$5+1,1,1),'Bills Log'!$B$6:$B$505,Settings!$B$9,'Bills Log'!$C$6:$C$505,$A56) | N56: =SUM(B56:M56) | O56: =IFERROR(N56/12,0)
A57: Propane | B57: =SUMIFS('Bills Log'!$F$6:$F$505,'Bills Log'!$A$6:$A$505,">="&DATE(Settings!$B$5,1,1),'Bills Log'!$A$6:$A$505,"<"&DATE(Settings!$B$5,2,1),'Bills Log'!$B$6:$B$505,Settings!$B$9,'Bills Log'!$C$6:$C$505,$A57) | C57: =SUMIFS('Bills Log'!$F$6:$F$505,'Bills Log'!$A$6:$A$505,">="&DATE(Settings!$B$5,2,1),'Bills Log'!$A$6:$A$505,"<"&DATE(Settings!$B$5,3,1),'Bills Log'!$B$6:$B$505,Settings!$B$9,'Bills Log'!$C$6:$C$505,$A57) | D57: =SUMIFS('Bills Log'!$F$6:$F$505,'Bills Log'!$A$6:$A$505,">="&DATE(Settings!$B$5,3,1),'Bills Log'!$A$6:$A$505,"<"&DATE(Settings!$B$5,4,1),'Bills Log'!$B$6:$B$505,Settings!$B$9,'Bills Log'!$C$6:$C$505,$A57) | E57: =SUMIFS('Bills Log'!$F$6:$F$505,'Bills Log'!$A$6:$A$505,">="&DATE(Settings!$B$5,4,1),'Bills Log'!$A$6:$A$505,"<"&DATE(Settings!$B$5,5,1),'Bills Log'!$B$6:$B$505,Settings!$B$9,'Bills Log'!$C$6:$C$505,$A57) | F57: =SUMIFS('Bills Log'!$F$6:$F$505,'Bills Log'!$A$6:$A$505,">="&DATE(Settings!$B$5,5,1),'Bills Log'!$A$6:$A$505,"<"&DATE(Settings!$B$5,6,1),'Bills Log'!$B$6:$B$505,Settings!$B$9,'Bills Log'!$C$6:$C$505,$A57) | G57: =SUMIFS('Bills Log'!$F$6:$F$505,'Bills Log'!$A$6:$A$505,">="&DATE(Settings!$B$5,6,1),'Bills Log'!$A$6:$A$505,"<"&DATE(Settings!$B$5,7,1),'Bills Log'!$B$6:$B$505,Settings!$B$9,'Bills Log'!$C$6:$C$505,$A57) | H57: =SUMIFS('Bills Log'!$F$6:$F$505,'Bills Log'!$A$6:$A$505,">="&DATE(Settings!$B$5,7,1),'Bills Log'!$A$6:$A$505,"<"&DATE(Settings!$B$5,8,1),'Bills Log'!$B$6:$B$505,Settings!$B$9,'Bills Log'!$C$6:$C$505,$A57) | I57: =SUMIFS('Bills Log'!$F$6:$F$505,'Bills Log'!$A$6:$A$505,">="&DATE(Settings!$B$5,8,1),'Bills Log'!$A$6:$A$505,"<"&DATE(Settings!$B$5,9,1),'Bills Log'!$B$6:$B$505,Settings!$B$9,'Bills Log'!$C$6:$C$505,$A57) | J57: =SUMIFS('Bills Log'!$F$6:$F$505,'Bills Log'!$A$6:$A$505,">="&DATE(Settings!$B$5,9,1),'Bills Log'!$A$6:$A$505,"<"&DATE(Settings!$B$5,10,1),'Bills Log'!$B$6:$B$505,Settings!$B$9,'Bills Log'!$C$6:$C$505,$A57) | K57: =SUMIFS('Bills Log'!$F$6:$F$505,'Bills Log'!$A$6:$A$505,">="&DATE(Settings!$B$5,10,1),'Bills Log'!$A$6:$A$505,"<"&DATE(Settings!$B$5,11,1),'Bills Log'!$B$6:$B$505,Settings!$B$9,'Bills Log'!$C$6:$C$505,$A57) | L57: =SUMIFS('Bills Log'!$F$6:$F$505,'Bills Log'!$A$6:$A$505,">="&DATE(Settings!$B$5,11,1),'Bills Log'!$A$6:$A$505,"<"&DATE(Settings!$B$5,12,1),'Bills Log'!$B$6:$B$505,Settings!$B$9,'Bills Log'!$C$6:$C$505,$A57) | M57: =SUMIFS('Bills Log'!$F$6:$F$505,'Bills Log'!$A$6:$A$505,">="&DATE(Settings!$B$5,12,1),'Bills Log'!$A$6:$A$505,"<"&DATE(Settings!$B$5+1,1,1),'Bills Log'!$B$6:$B$505,Settings!$B$9,'Bills Log'!$C$6:$C$505,$A57) | N57: =SUM(B57:M57) | O57: =IFERROR(N57/12,0)
A58: TOTAL | B58: =SUM(B52:B57) | C58: =SUM(C52:C57) | D58: =SUM(D52:D57) | E58: =SUM(E52:E57) | F58: =SUM(F52:F57) | G58: =SUM(G52:G57) | H58: =SUM(H52:H57) | I58: =SUM(I52:I57) | ... O58: =SUM(O52:O57)

Sheet Trend & Anomalies
A2: =HYPERLINK("#'Property Matrix'!A1", "← BACK") | D2: TREND & ANOMALIES | J2: =HYPERLINK("#'Settings'!A1", "NEXT →")
A3: Anomalies: | B3: =COUNTIF(H6:H221,"⚠*")
A4: Year-over-year check — anomaly if a month's bill jumped >25% vs prior year
A5: Property | B5: Service | C5: Month | D5: Current Yr $ | E5: Prior Yr $ | F5: YoY % | G5: Δ $ | H5: Anomaly
A6: =Settings!$B$7 | B6: Electric | C6: Jan | D6: =SUMIFS('Bills Log'!$F$6:$F$505,'Bills Log'!$A$6:$A$505,">="&DATE(Settings!$B$5,1,1),'Bills Log'!$A$6:$A$505,"<"&DATE(Settings!$B$5,2,1),'Bills Log'!$B$6:$B$505,A6,'Bills Log'!$C$6:$C$505,B6) | E6: =SUMIFS('Bills Log'!$F$6:$F$505,'Bills Log'!$A$6:$A$505,">="&DATE(Settings!$B$5-1,1,1),'Bills Log'!$A$6:$A$505,"<"&DATE((Settings!$B$5-1),2,1),'Bills Log'!$B$6:$B$505,A6,'Bills Log'!$C$6:$C$505,B6) | F6: =IFERROR(IF(E6=0,"",D6/E6-1),"") | G6: =D6-E6 | H6: =IFERROR(IF(ABS(D6/E6-1)>0.25,"⚠ "&ROUND((D6/E6-1)*100,0)&"%",""),"")
A7: =Settings!$B$7 | B7: Electric | C7: Feb | D7: =SUMIFS('Bills Log'!$F$6:$F$505,'Bills Log'!$A$6:$A$505,">="&DATE(Settings!$B$5,2,1),'Bills Log'!$A$6:$A$505,"<"&DATE(Settings!$B$5,3,1),'Bills Log'!$B$6:$B$505,A7,'Bills Log'!$C$6:$C$505,B7) | E7: =SUMIFS('Bills Log'!$F$6:$F$505,'Bills Log'!$A$6:$A$505,">="&DATE(Settings!$B$5-1,2,1),'Bills Log'!$A$6:$A$505,"<"&DATE((Settings!$B$5-1),3,1),'Bills Log'!$B$6:$B$505,A7,'Bills Log'!$C$6:$C$505,B7) | F7: =IFERROR(IF(E7=0,"",D7/E7-1),"") | G7: =D7-E7 | H7: =IFERROR(IF(ABS(D7/E7-1)>0.25,"⚠ "&ROUND((D7/E7-1)*100,0)&"%",""),"")
A8: =Settings!$B$7 | B8: Electric | C8: Mar | D8: =SUMIFS('Bills Log'!$F$6:$F$505,'Bills Log'!$A$6:$A$505,">="&DATE(Settings!$B$5,3,1),'Bills Log'!$A$6:$A$505,"<"&DATE(Settings!$B$5,4,1),'Bills Log'!$B$6:$B$505,A8,'Bills Log'!$C$6:$C$505,B8) | E8: =SUMIFS('Bills Log'!$F$6:$F$505,'Bills Log'!$A$6:$A$505,">="&DATE(Settings!$B$5-1,3,1),'Bills Log'!$A$6:$A$505,"<"&DATE((Settings!$B$5-1),4,1),'Bills Log'!$B$6:$B$505,A8,'Bills Log'!$C$6:$C$505,B8) | F8: =IFERROR(IF(E8=0,"",D8/E8-1),"") | G8: =D8-E8 | H8: =IFERROR(IF(ABS(D8/E8-1)>0.25,"⚠ "&ROUND((D8/E8-1)*100,0)&"%",""),"")
A9: =Settings!$B$7 | B9: Electric | C9: Apr | D9: =SUMIFS('Bills Log'!$F$6:$F$505,'Bills Log'!$A$6:$A$505,">="&DATE(Settings!$B$5,4,1),'Bills Log'!$A$6:$A$505,"<"&DATE(Settings!$B$5,5,1),'Bills Log'!$B$6:$B$505,A9,'Bills Log'!$C$6:$C$505,B9) | E9: =SUMIFS('Bills Log'!$F$6:$F$505,'Bills Log'!$A$6:$A$505,">="&DATE(Settings!$B$5-1,4,1),'Bills Log'!$A$6:$A$505,"<"&DATE((Settings!$B$5-1),5,1),'Bills Log'!$B$6:$B$505,A9,'Bills Log'!$C$6:$C$505,B9) | F9: =IFERROR(IF(E9=0,"",D9/E9-1),"") | G9: =D9-E9 | H9: =IFERROR(IF(ABS(D9/E9-1)>0.25,"⚠ "&ROUND((D9/E9-1)*100,0)&"%",""),"")
A10: =Settings!$B$7 | B10: Electric | C10: May | D10: =SUMIFS('Bills Log'!$F$6:$F$505,'Bills Log'!$A$6:$A$505,">="&DATE(Settings!$B$5,5,1),'Bills Log'!$A$6:$A$505,"<"&DATE(Settings!$B$5,6,1),'Bills Log'!$B$6:$B$505,A10,'Bills Log'!$C$6:$C$505,B10) | E10: =SUMIFS('Bills Log'!$F$6:$F$505,'Bills Log'!$A$6:$A$505,">="&DATE(Settings!$B$5-1,5,1),'Bills Log'!$A$6:$A$505,"<"&DATE((Settings!$B$5-1),6,1),'Bills Log'!$B$6:$B$505,A10,'Bills Log'!$C$6:$C$505,B10) | F10: =IFERROR(IF(E10=0,"",D10/E10-1),"") | G10: =D10-E10 | H10: =IFERROR(IF(ABS(D10/E10-1)>0.25,"⚠ "&ROUND((D10/E10-1)*100,0)&"%",""),"")
A11: =Settings!$B$7 | B11: Electric | C11: Jun | D11: =SUMIFS('Bills Log'!$F$6:$F$505,'Bills Log'!$A$6:$A$505,">="&DATE(Settings!$B$5,6,1),'Bills Log'!$A$6:$A$505,"<"&DATE(Settings!$B$5,7,1),'Bills Log'!$B$6:$B$505,A11,'Bills Log'!$C$6:$C$505,B11) | E11: =SUMIFS('Bills Log'!$F$6:$F$505,'Bills Log'!$A$6:$A$505,">="&DATE(Settings!$B$5-1,6,1),'Bills Log'!$A$6:$A$505,"<"&DATE((Settings!$B$5-1),7,1),'Bills Log'!$B$6:$B$505,A11,'Bills Log'!$C$6:$C$505,B11) | F11: =IFERROR(IF(E11=0,"",D11/E11-1),"") | G11: =D11-E11 | H11: =IFERROR(IF(ABS(D11/E11-1)>0.25,"⚠ "&ROUND((D11/E11-1)*100,0)&"%",""),"")
A12: =Settings!$B$7 | B12: Electric | C12: Jul | D12: =SUMIFS('Bills Log'!$F$6:$F$505,'Bills Log'!$A$6:$A$505,">="&DATE(Settings!$B$5,7,1),'Bills Log'!$A$6:$A$505,"<"&DATE(Settings!$B$5,8,1),'Bills Log'!$B$6:$B$505,A12,'Bills Log'!$C$6:$C$505,B12) | E12: =SUMIFS('Bills Log'!$F$6:$F$505,'Bills Log'!$A$6:$A$505,">="&DATE(Settings!$B$5-1,7,1),'Bills Log'!$A$6:$A$505,"<"&DATE((Settings!$B$5-1),8,1),'Bills Log'!$B$6:$B$505,A12,'Bills Log'!$C$6:$C$505,B12) | F12: =IFERROR(IF(E12=0,"",D12/E12-1),"") | G12: =D12-E12 | H12: =IFERROR(IF(ABS(D12/E12-1)>0.25,"⚠ "&ROUND((D12/E12-1)*100,0)&"%",""),"")
A13: =Settings!$B$7 | B13: Electric | C13: Aug | D13: =SUMIFS('Bills Log'!$F$6:$F$505,'Bills Log'!$A$6:$A$505,">="&DATE(Settings!$B$5,8,1),'Bills Log'!$A$6:$A$505,"<"&DATE(Settings!$B$5,9,1),'Bills Log'!$B$6:$B$505,A13,'Bills Log'!$C$6:$C$505,B13) | E13: =SUMIFS('Bills Log'!$F$6:$F$505,'Bills Log'!$A$6:$A$505,">="&DATE(Settings!$B$5-1,8,1),'Bills Log'!$A$6:$A$505,"<"&DATE((Settings!$B$5-1),9,1),'Bills Log'!$B$6:$B$505,A13,'Bills Log'!$C$6:$C$505,B13) | F13: =IFERROR(IF(E13=0,"",D13/E13-1),"") | G13: =D13-E13 | H13: =IFERROR(IF(ABS(D13/E13-1)>0.25,"⚠ "&ROUND((D13/E13-1)*100,0)&"%",""),"")
A14: =Settings!$B$7 | B14: Electric | C14: Sep | D14: =SUMIFS('Bills Log'!$F$6:$F$505,'Bills Log'!$A$6:$A$505,">="&DATE(Settings!$B$5,9,1),'Bills Log'!$A$6:$A$505,"<"&DATE(Settings!$B$5,10,1),'Bills Log'!$B$6:$B$505,A14,'Bills Log'!$C$6:$C$505,B14) | E14: =SUMIFS('Bills Log'!$F$6:$F$505,'Bills Log'!$A$6:$A$505,">="&DATE(Settings!$B$5-1,9,1),'Bills Log'!$A$6:$A$505,"<"&DATE((Settings!$B$5-1),10,1),'Bills Log'!$B$6:$B$505,A14,'Bills Log'!$C$6:$C$505,B14) | F14: =IFERROR(IF(E14=0,"",D14/E14-1),"") | G14: =D14-E14 | H14: =IFERROR(IF(ABS(D14/E14-1)>0.25,"⚠ "&ROUND((D14/E14-1)*100,0)&"%",""),"")
A15: =Settings!$B$7 | B15: Electric | C15: Oct | D15: =SUMIFS('Bills Log'!$F$6:$F$505,'Bills Log'!$A$6:$A$505,">="&DATE(Settings!$B$5,10,1),'Bills Log'!$A$6:$A$505,"<"&DATE(Settings!$B$5,11,1),'Bills Log'!$B$6:$B$505,A15,'Bills Log'!$C$6:$C$505,B15) | E15: =SUMIFS('Bills Log'!$F$6:$F$505,'Bills Log'!$A$6:$A$505,">="&DATE(Settings!$B$5-1,10,1),'Bills Log'!$A$6:$A$505,"<"&DATE((Settings!$B$5-1),11,1),'Bills Log'!$B$6:$B$505,A15,'Bills Log'!$C$6:$C$505,B15) | F15: =IFERROR(IF(E15=0,"",D15/E15-1),"") | G15: =D15-E15 | H15: =IFERROR(IF(ABS(D15/E15-1)>0.25,"⚠ "&ROUND((D15/E15-1)*100,0)&"%",""),"")
A16: =Settings!$B$7 | B16: Electric | C16: Nov | D16: =SUMIFS('Bills Log'!$F$6:$F$505,'Bills Log'!$A$6:$A$505,">="&DATE(Settings!$B$5,11,1),'Bills Log'!$A$6:$A$505,"<"&DATE(Settings!$B$5,12,1),'Bills Log'!$B$6:$B$505,A16,'Bills Log'!$C$6:$C$505,B16) | E16: =SUMIFS('Bills Log'!$F$6:$F$505,'Bills Log'!$A$6:$A$505,">="&DATE(Settings!$B$5-1,11,1),'Bills Log'!$A$6:$A$505,"<"&DATE((Settings!$B$5-1),12,1),'Bills Log'!$B$6:$B$505,A16,'Bills Log'!$C$6:$C$505,B16) | F16: =IFERROR(IF(E16=0,"",D16/E16-1),"") | G16: =D16-E16 | H16: =IFERROR(IF(ABS(D16/E16-1)>0.25,"⚠ "&ROUND((D16/E16-1)*100,0)&"%",""),"")
A17: =Settings!$B$7 | B17: Electric | C17: Dec | D17: =SUMIFS('Bills Log'!$F$6:$F$505,'Bills Log'!$A$6:$A$505,">="&DATE(Settings!$B$5,12,1),'Bills Log'!$A$6:$A$505,"<"&DATE(Settings!$B$5+1,1,1),'Bills Log'!$B$6:$B$505,A17,'Bills Log'!$C$6:$C$505,B17) | E17: =SUMIFS('Bills Log'!$F$6:$F$505,'Bills Log'!$A$6:$A$505,">="&DATE(Settings!$B$5-1,12,1),'Bills Log'!$A$6:$A$505,"<"&DATE(Settings!$B$5,1,1),'Bills Log'!$B$6:$B$505,A17,'Bills Log'!$C$6:$C$505,B17) | F17: =IFERROR(IF(E17=0,"",D17/E17-1),"") | G17: =D17-E17 | H17: =IFERROR(IF(ABS(D17/E17-1)>0.25,"⚠ "&ROUND((D17/E17-1)*100,0)&"%",""),"")
A18: =Settings!$B$7 | B18: Gas | C18: Jan | D18: =SUMIFS('Bills Log'!$F$6:$F$505,'Bills Log'!$A$6:$A$505,">="&DATE(Settings!$B$5,1,1),'Bills Log'!$A$6:$A$505,"<"&DATE(Settings!$B$5,2,1),'Bills Log'!$B$6:$B$505,A18,'Bills Log'!$C$6:$C$505,B18) | E18: =SUMIFS('Bills Log'!$F$6:$F$505,'Bills Log'!$A$6:$A$505,">="&DATE(Settings!$B$5-1,1,1),'Bills Log'!$A$6:$A$505,"<"&DATE((Settings!$B$5-1),2,1),'Bills Log'!$B$6:$B$505,A18,'Bills Log'!$C$6:$C$505,B18) | F18: =IFERROR(IF(E18=0,"",D18/E18-1),"") | G18: =D18-E18 | H18: =IFERROR(IF(ABS(D18/E18-1)>0.25,"⚠ "&ROUND((D18/E18-1)*100,0)&"%",""),"")
A19: =Settings!$B$7 | B19: Gas | C19: Feb | D19: =SUMIFS('Bills Log'!$F$6:$F$505,'Bills Log'!$A$6:$A$505,">="&DATE(Settings!$B$5,2,1),'Bills Log'!$A$6:$A$505,"<"&DATE(Settings!$B$5,3,1),'Bills Log'!$B$6:$B$505,A19,'Bills Log'!$C$6:$C$505,B19) | E19: =SUMIFS('Bills Log'!$F$6:$F$505,'Bills Log'!$A$6:$A$505,">="&DATE(Settings!$B$5-1,2,1),'Bills Log'!$A$6:$A$505,"<"&DATE((Settings!$B$5-1),3,1),'Bills Log'!$B$6:$B$505,A19,'Bills Log'!$C$6:$C$505,B19) | F19: =IFERROR(IF(E19=0,"",D19/E19-1),"") | G19: =D19-E19 | H19: =IFERROR(IF(ABS(D19/E19-1)>0.25,"⚠ "&ROUND((D19/E19-1)*100,0)&"%",""),"")
A20: =Settings!$B$7 | B20: Gas | C20: Mar | D20: =SUMIFS('Bills Log'!$F$6:$F$505,'Bills Log'!$A$6:$A$505,">="&DATE(Settings!$B$5,3,1),'Bills Log'!$A$6:$A$505,"<"&DATE(Settings!$B$5,4,1),'Bills Log'!$B$6:$B$505,A20,'Bills Log'!$C$6:$C$505,B20) | E20: =SUMIFS('Bills Log'!$F$6:$F$505,'Bills Log'!$A$6:$A$505,">="&DATE(Settings!$B$5-1,3,1),'Bills Log'!$A$6:$A$505,"<"&DATE((Settings!$B$5-1),4,1),'Bills Log'!$B$6:$B$505,A20,'Bills Log'!$C$6:$C$505,B20) | F20: =IFERROR(IF(E20=0,"",D20/E20-1),"") | G20: =D20-E20 | H20: =IFERROR(IF(ABS(D20/E20-1)>0.25,"⚠ "&ROUND((D20/E20-1)*100,0)&"%",""),"")
A21: =Settings!$B$7 | B21: Gas | C21: Apr | D21: =SUMIFS('Bills Log'!$F$6:$F$505,'Bills Log'!$A$6:$A$505,">="&DATE(Settings!$B$5,4,1),'Bills Log'!$A$6:$A$505,"<"&DATE(Settings!$B$5,5,1),'Bills Log'!$B$6:$B$505,A21,'Bills Log'!$C$6:$C$505,B21) | E21: =SUMIFS('Bills Log'!$F$6:$F$505,'Bills Log'!$A$6:$A$505,">="&DATE(Settings!$B$5-1,4,1),'Bills Log'!$A$6:$A$505,"<"&DATE((Settings!$B$5-1),5,1),'Bills Log'!$B$6:$B$505,A21,'Bills Log'!$C$6:$C$505,B21) | F21: =IFERROR(IF(E21=0,"",D21/E21-1),"") | G21: =D21-E21 | H21: =IFERROR(IF(ABS(D21/E21-1)>0.25,"⚠ "&ROUND((D21/E21-1)*100,0)&"%",""),"")
A22: =Settings!$B$7 | B22: Gas | C22: May | D22: =SUMIFS('Bills Log'!$F$6:$F$505,'Bills Log'!$A$6:$A$505,">="&DATE(Settings!$B$5,5,1),'Bills Log'!$A$6:$A$505,"<"&DATE(Settings!$B$5,6,1),'Bills Log'!$B$6:$B$505,A22,'Bills Log'!$C$6:$C$505,B22) | E22: =SUMIFS('Bills Log'!$F$6:$F$505,'Bills Log'!$A$6:$A$505,">="&DATE(Settings!$B$5-1,5,1),'Bills Log'!$A$6:$A$505,"<"&DATE((Settings!$B$5-1),6,1),'Bills Log'!$B$6:$B$505,A22,'Bills Log'!$C$6:$C$505,B22) | F22: =IFERROR(IF(E22=0,"",D22/E22-1),"") | G22: =D22-E22 | H22: =IFERROR(IF(ABS(D22/E22-1)>0.25,"⚠ "&ROUND((D22/E22-1)*100,0)&"%",""),"")
A23: =Settings!$B$7 | B23: Gas | C23: Jun | D23: =SUMIFS('Bills Log'!$F$6:$F$505,'Bills Log'!$A$6:$A$505,">="&DATE(Settings!$B$5,6,1),'Bills Log'!$A$6:$A$505,"<"&DATE(Settings!$B$5,7,1),'Bills Log'!$B$6:$B$505,A23,'Bills Log'!$C$6:$C$505,B23) | E23: =SUMIFS('Bills Log'!$F$6:$F$505,'Bills Log'!$A$6:$A$505,">="&DATE(Settings!$B$5-1,6,1),'Bills Log'!$A$6:$A$505,"<"&DATE((Settings!$B$5-1),7,1),'Bills Log'!$B$6:$B$505,A23,'Bills Log'!$C$6:$C$505,B23) | F23: =IFERROR(IF(E23=0,"",D23/E23-1),"") | G23: =D23-E23 | H23: =IFERROR(IF(ABS(D23/E23-1)>0.25,"⚠ "&ROUND((D23/E23-1)*100,0)&"%",""),"")
A24: =Settings!$B$7 | B24: Gas | C24: Jul | D24: =SUMIFS('Bills Log'!$F$6:$F$505,'Bills Log'!$A$6:$A$505,">="&DATE(Settings!$B$5,7,1),'Bills Log'!$A$6:$A$505,"<"&DATE(Settings!$B$5,8,1),'Bills Log'!$B$6:$B$505,A24,'Bills Log'!$C$6:$C$505,B24) | E24: =SUMIFS('Bills Log'!$F$6:$F$505,'Bills Log'!$A$6:$A$505,">="&DATE(Settings!$B$5-1,7,1),'Bills Log'!$A$6:$A$505,"<"&DATE((Settings!$B$5-1),8,1),'Bills Log'!$B$6:$B$505,A24,'Bills Log'!$C$6:$C$505,B24) | F24: =IFERROR(IF(E24=0,"",D24/E24-1),"") | G24: =D24-E24 | H24: =IFERROR(IF(ABS(D24/E24-1)>0.25,"⚠ "&ROUND((D24/E24-1)*100,0)&"%",""),"")
A25: =Settings!$B$7 | B25: Gas | C25: Aug | D25: =SUMIFS('Bills Log'!$F$6:$F$505,'Bills Log'!$A$6:$A$505,">="&DATE(Settings!$B$5,8,1),'Bills Log'!$A$6:$A$505,"<"&DATE(Settings!$B$5,9,1),'Bills Log'!$B$6:$B$505,A25,'Bills Log'!$C$6:$C$505,B25) | E25: =SUMIFS('Bills Log'!$F$6:$F$505,'Bills Log'!$A$6:$A$505,">="&DATE(Settings!$B$5-1,8,1),'Bills Log'!$A$6:$A$505,"<"&DATE((Settings!$B$5-1),9,1),'Bills Log'!$B$6:$B$505,A25,'Bills Log'!$C$6:$C$505,B25) | F25: =IFERROR(IF(E25=0,"",D25/E25-1),"") | G25: =D25-E25 | H25: =IFERROR(IF(ABS(D25/E25-1)>0.25,"⚠ "&ROUND((D25/E25-1)*100,0)&"%",""),"")
A26: =Settings!$B$7 | B26: Gas | C26: Sep | D26: =SUMIFS('Bills Log'!$F$6:$F$505,'Bills Log'!$A$6:$A$505,">="&DATE(Settings!$B$5,9,1),'Bills Log'!$A$6:$A$505,"<"&DATE(Settings!$B$5,10,1),'Bills Log'!$B$6:$B$505,A26,'Bills Log'!$C$6:$C$505,B26) | E26: =SUMIFS('Bills Log'!$F$6:$F$505,'Bills Log'!$A$6:$A$505,">="&DATE(Settings!$B$5-1,9,1),'Bills Log'!$A$6:$A$505,"<"&DATE((Settings!$B$5-1),10,1),'Bills Log'!$B$6:$B$505,A26,'Bills Log'!$C$6:$C$505,B26) | F26: =IFERROR(IF(E26=0,"",D26/E26-1),"") | G26: =D26-E26 | H26: =IFERROR(IF(ABS(D26/E26-1)>0.25,"⚠ "&ROUND((D26/E26-1)*100,0)&"%",""),"")
A27: =Settings!$B$7 | B27: Gas | C27: Oct | D27: =SUMIFS('Bills Log'!$F$6:$F$505,'Bills Log'!$A$6:$A$505,">="&DATE(Settings!$B$5,10,1),'Bills Log'!$A$6:$A$505,"<"&DATE(Settings!$B$5,11,1),'Bills Log'!$B$6:$B$505,A27,'Bills Log'!$C$6:$C$505,B27) | E27: =SUMIFS('Bills Log'!$F$6:$F$505,'Bills Log'!$A$6:$A$505,">="&DATE(Settings!$B$5-1,10,1),'Bills Log'!$A$6:$A$505,"<"&DATE((Settings!$B$5-1),11,1),'Bills Log'!$B$6:$B$505,A27,'Bills Log'!$C$6:$C$505,B27) | F27: =IFERROR(IF(E27=0,"",D27/E27-1),"") | G27: =D27-E27 | H27: =IFERROR(IF(ABS(D27/E27-1)>0.25,"⚠ "&ROUND((D27/E27-1)*100,0)&"%",""),"")
A28: =Settings!$B$7 | B28: Gas | C28: Nov | D28: =SUMIFS('Bills Log'!$F$6:$F$505,'Bills Log'!$A$6:$A$505,">="&DATE(Settings!$B$5,11,1),'Bills Log'!$A$6:$A$505,"<"&DATE(Settings!$B$5,12,1),'Bills Log'!$B$6:$B$505,A28,'Bills Log'!$C$6:$C$505,B28) | E28: =SUMIFS('Bills Log'!$F$6:$F$505,'Bills Log'!$A$6:$A$505,">="&DATE(Settings!$B$5-1,11,1),'Bills Log'!$A$6:$A$505,"<"&DATE((Settings!$B$5-1),12,1),'Bills Log'!$B$6:$B$505,A28,'Bills Log'!$C$6:$C$505,B28) | F28: =IFERROR(IF(E28=0,"",D28/E28-1),"") | G28: =D28-E28 | H28: =IFERROR(IF(ABS(D28/E28-1)>0.25,"⚠ "&ROUND((D28/E28-1)*100,0)&"%",""),"")
A29: =Settings!$B$7 | B29: Gas | C29: Dec | D29: =SUMIFS('Bills Log'!$F$6:$F$505,'Bills Log'!$A$6:$A$505,">="&DATE(Settings!$B$5,12,1),'Bills Log'!$A$6:$A$505,"<"&DATE(Settings!$B$5+1,1,1),'Bills Log'!$B$6:$B$505,A29,'Bills Log'!$C$6:$C$505,B29) | E29: =SUMIFS('Bills Log'!$F$6:$F$505,'Bills Log'!$A$6:$A$505,">="&DATE(Settings!$B$5-1,12,1),'Bills Log'!$A$6:$A$505,"<"&DATE(Settings!$B$5,1,1),'Bills Log'!$B$6:$B$505,A29,'Bills Log'!$C$6:$C$505,B29) | F29: =IFERROR(IF(E29=0,"",D29/E29-1),"") | G29: =D29-E29 | H29: =IFERROR(IF(ABS(D29/E29-1)>0.25,"⚠ "&ROUND((D29/E29-1)*100,0)&"%",""),"")
A30: =Settings!$B$7 | B30: Water | C30: Jan | D30: =SUMIFS('Bills Log'!$F$6:$F$505,'Bills Log'!$A$6:$A$505,">="&DATE(Settings!$B$5,1,1),'Bills Log'!$A$6:$A$505,"<"&DATE(Settings!$B$5,2,1),'Bills Log'!$B$6:$B$505,A30,'Bills Log'!$C$6:$C$505,B30) | E30: =SUMIFS('Bills Log'!$F$6:$F$505,'Bills Log'!$A$6:$A$505,">="&DATE(Settings!$B$5-1,1,1),'Bills Log'!$A$6:$A$505,"<"&DATE((Settings!$B$5-1),2,1),'Bills Log'!$B$6:$B$505,A30,'Bills Log'!$C$6:$C$505,B30) | F30: =IFERROR(IF(E30=0,"",D30/E30-1),"") | G30: =D30-E30 | H30: =IFERROR(IF(ABS(D30/E30-1)>0.25,"⚠ "&ROUND((D30/E30-1)*100,0)&"%",""),"")
A31: =Settings!$B$7 | B31: Water | C31: Feb | D31: =SUMIFS('Bills Log'!$F$6:$F$505,'Bills Log'!$A$6:$A$505,">="&DATE(Settings!$B$5,2,1),'Bills Log'!$A$6:$A$505,"<"&DATE(Settings!$B$5,3,1),'Bills Log'!$B$6:$B$505,A31,'Bills Log'!$C$6:$C$505,B31) | E31: =SUMIFS('Bills Log'!$F$6:$F$505,'Bills Log'!$A$6:$A$505,">="&DATE(Settings!$B$5-1,2,1),'Bills Log'!$A$6:$A$505,"<"&DATE((Settings!$B$5-1),3,1),'Bills Log'!$B$6:$B$505,A31,'Bills Log'!$C$6:$C$505,B31) | F31: =IFERROR(IF(E31=0,"",D31/E31-1),"") | G31: =D31-E31 | H31: =IFERROR(IF(ABS(D31/E31-1)>0.25,"⚠ "&ROUND((D31/E31-1)*100,0)&"%",""),"")
A32: =Settings!$B$7 | B32: Water | C32: Mar | D32: =SUMIFS('Bills Log'!$F$6:$F$505,'Bills Log'!$A$6:$A$505,">="&DATE(Settings!$B$5,3,1),'Bills Log'!$A$6:$A$505,"<"&DATE(Settings!$B$5,4,1),'Bills Log'!$B$6:$B$505,A32,'Bills Log'!$C$6:$C$505,B32) | E32: =SUMIFS('Bills Log'!$F$6:$F$505,'Bills Log'!$A$6:$A$505,">="&DATE(Settings!$B$5-1,3,1),'Bills Log'!$A$6:$A$505,"<"&DATE((Settings!$B$5-1),4,1),'Bills Log'!$B$6:$B$505,A32,'Bills Log'!$C$6:$C$505,B32) | F32: =IFERROR(IF(E32=0,"",D32/E32-1),"") | G32: =D32-E32 | H32: =IFERROR(IF(ABS(D32/E32-1)>0.25,"⚠ "&ROUND((D32/E32-1)*100,0)&"%",""),"")
A33: =Settings!$B$7 | B33: Water | C33: Apr | D33: =SUMIFS('Bills Log'!$F$6:$F$505,'Bills Log'!$A$6:$A$505,">="&DATE(Settings!$B$5,4,1),'Bills Log'!$A$6:$A$505,"<"&DATE(Settings!$B$5,5,1),'Bills Log'!$B$6:$B$505,A33,'Bills Log'!$C$6:$C$505,B33) | E33: =SUMIFS('Bills Log'!$F$6:$F$505,'Bills Log'!$A$6:$A$505,">="&DATE(Settings!$B$5-1,4,1),'Bills Log'!$A$6:$A$505,"<"&DATE((Settings!$B$5-1),5,1),'Bills Log'!$B$6:$B$505,A33,'Bills Log'!$C$6:$C$505,B33) | F33: =IFERROR(IF(E33=0,"",D33/E33-1),"") | G33: =D33-E33 | H33: =IFERROR(IF(ABS(D33/E33-1)>0.25,"⚠ "&ROUND((D33/E33-1)*100,0)&"%",""),"")
A34: =Settings!$B$7 | B34: Water | C34: May | D34: =SUMIFS('Bills Log'!$F$6:$F$505,'Bills Log'!$A$6:$A$505,">="&DATE(Settings!$B$5,5,1),'Bills Log'!$A$6:$A$505,"<"&DATE(Settings!$B$5,6,1),'Bills Log'!$B$6:$B$505,A34,'Bills Log'!$C$6:$C$505,B34) | E34: =SUMIFS('Bills Log'!$F$6:$F$505,'Bills Log'!$A$6:$A$505,">="&DATE(Settings!$B$5-1,5,1),'Bills Log'!$A$6:$A$505,"<"&DATE((Settings!$B$5-1),6,1),'Bills Log'!$B$6:$B$505,A34,'Bills Log'!$C$6:$C$505,B34) | F34: =IFERROR(IF(E34=0,"",D34/E34-1),"") | G34: =D34-E34 | H34: =IFERROR(IF(ABS(D34/E34-1)>0.25,"⚠ "&ROUND((D34/E34-1)*100,0)&"%",""),"")
A35: =Settings!$B$7 | B35: Water | C35: Jun | D35: =SUMIFS('Bills Log'!$F$6:$F$505,'Bills Log'!$A$6:$A$505,">="&DATE(Settings!$B$5,6,1),'Bills Log'!$A$6:$A$505,"<"&DATE(Settings!$B$5,7,1),'Bills Log'!$B$6:$B$505,A35,'Bills Log'!$C$6:$C$505,B35) | E35: =SUMIFS('Bills Log'!$F$6:$F$505,'Bills Log'!$A$6:$A$505,">="&DATE(Settings!$B$5-1,6,1),'Bills Log'!$A$6:$A$505,"<"&DATE((Settings!$B$5-1),7,1),'Bills Log'!$B$6:$B$505,A35,'Bills Log'!$C$6:$C$505,B35) | F35: =IFERROR(IF(E35=0,"",D35/E35-1),"") | G35: =D35-E35 | H35: =IFERROR(IF(ABS(D35/E35-1)>0.25,"⚠ "&ROUND((D35/E35-1)*100,0)&"%",""),"")
A36: =Settings!$B$7 | B36: Water | C36: Jul | D36: =SUMIFS('Bills Log'!$F$6:$F$505,'Bills Log'!$A$6:$A$505,">="&DATE(Settings!$B$5,7,1),'Bills Log'!$A$6:$A$505,"<"&DATE(Settings!$B$5,8,1),'Bills Log'!$B$6:$B$505,A36,'Bills Log'!$C$6:$C$505,B36) | E36: =SUMIFS('Bills Log'!$F$6:$F$505,'Bills Log'!$A$6:$A$505,">="&DATE(Settings!$B$5-1,7,1),'Bills Log'!$A$6:$A$505,"<"&DATE((Settings!$B$5-1),8,1),'Bills Log'!$B$6:$B$505,A36,'Bills Log'!$C$6:$C$505,B36) | F36: =IFERROR(IF(E36=0,"",D36/E36-1),"") | G36: =D36-E36 | H36: =IFERROR(IF(ABS(D36/E36-1)>0.25,"⚠ "&ROUND((D36/E36-1)*100,0)&"%",""),"")
A37: =Settings!$B$7 | B37: Water | C37: Aug | D37: =SUMIFS('Bills Log'!$F$6:$F$505,'Bills Log'!$A$6:$A$505,">="&DATE(Settings!$B$5,8,1),'Bills Log'!$A$6:$A$505,"<"&DATE(Settings!$B$5,9,1),'Bills Log'!$B$6:$B$505,A37,'Bills Log'!$C$6:$C$505,B37) | E37: =SUMIFS('Bills Log'!$F$6:$F$505,'Bills Log'!$A$6:$A$505,">="&DATE(Settings!$B$5-1,8,1),'Bills Log'!$A$6:$A$505,"<"&DATE((Settings!$B$5-1),9,1),'Bills Log'!$B$6:$B$505,A37,'Bills Log'!$C$6:$C$505,B37) | F37: =IFERROR(IF(E37=0,"",D37/E37-1),"") | G37: =D37-E37 | H37: =IFERROR(IF(ABS(D37/E37-1)>0.25,"⚠ "&ROUND((D37/E37-1)*100,0)&"%",""),"")
A38: =Settings!$B$7 | B38: Water | C38: Sep | D38: =SUMIFS('Bills Log'!$F$6:$F$505,'Bills Log'!$A$6:$A$505,">="&DATE(Settings!$B$5,9,1),'Bills Log'!$A$6:$A$505,"<"&DATE(Settings!$B$5,10,1),'Bills Log'!$B$6:$B$505,A38,'Bills Log'!$C$6:$C$505,B38) | E38: =SUMIFS('Bills Log'!$F$6:$F$505,'Bills Log'!$A$6:$A$505,">="&DATE(Settings!$B$5-1,9,1),'Bills Log'!$A$6:$A$505,"<"&DATE((Settings!$B$5-1),10,1),'Bills Log'!$B$6:$B$505,A38,'Bills Log'!$C$6:$C$505,B38) | F38: =IFERROR(IF(E38=0,"",D38/E38-1),"") | G38: =D38-E38 | H38: =IFERROR(IF(ABS(D38/E38-1)>0.25,"⚠ "&ROUND((D38/E38-1)*100,0)&"%",""),"")
A39: =Settings!$B$7 | B39: Water | C39: Oct | D39: =SUMIFS('Bills Log'!$F$6:$F$505,'Bills Log'!$A$6:$A$505,">="&DATE(Settings!$B$5,10,1),'Bills Log'!$A$6:$A$505,"<"&DATE(Settings!$B$5,11,1),'Bills Log'!$B$6:$B$505,A39,'Bills Log'!$C$6:$C$505,B39) | E39: =SUMIFS('Bills Log'!$F$6:$F$505,'Bills Log'!$A$6:$A$505,">="&DATE(Settings!$B$5-1,10,1),'Bills Log'!$A$6:$A$505,"<"&DATE((Settings!$B$5-1),11,1),'Bills Log'!$B$6:$B$505,A39,'Bills Log'!$C$6:$C$505,B39) | F39: =IFERROR(IF(E39=0,"",D39/E39-1),"") | G39: =D39-E39 | H39: =IFERROR(IF(ABS(D39/E39-1)>0.25,"⚠ "&ROUND((D39/E39-1)*100,0)&"%",""),"")
A40: =Settings!$B$7 | B40: Water | C40: Nov | D40: =SUMIFS('Bills Log'!$F$6:$F$505,'Bills Log'!$A$6:$A$505,">="&DATE(Settings!$B$5,11,1),'Bills Log'!$A$6:$A$505,"<"&DATE(Settings!$B$5,12,1),'Bills Log'!$B$6:$B$505,A40,'Bills Log'!$C$6:$C$505,B40) | E40: =SUMIFS('Bills Log'!$F$6:$F$505,'Bills Log'!$A$6:$A$505,">="&DATE(Settings!$B$5-1,11,1),'Bills Log'!$A$6:$A$505,"<"&DATE((Settings!$B$5-1),12,1),'Bills Log'!$B$6:$B$505,A40,'Bills Log'!$C$6:$C$505,B40) | F40: =IFERROR(IF(E40=0,"",D40/E40-1),"") | G40: =D40-E40 | H40: =IFERROR(IF(ABS(D40/E40-1)>0.25,"⚠ "&ROUND((D40/E40-1)*100,0)&"%",""),"")
A41: =Settings!$B$7 | B41: Water | C41: Dec | D41: =SUMIFS('Bills Log'!$F$6:$F$505,'Bills Log'!$A$6:$A$505,">="&DATE(Settings!$B$5,12,1),'Bills Log'!$A$6:$A$505,"<"&DATE(Settings!$B$5+1,1,1),'Bills Log'!$B$6:$B$505,A41,'Bills Log'!$C$6:$C$505,B41) | E41: =SUMIFS('Bills Log'!$F$6:$F$505,'Bills Log'!$A$6:$A$505,">="&DATE(Settings!$B$5-1,12,1),'Bills Log'!$A$6:$A$505,"<"&DATE(Settings!$B$5,1,1),'Bills Log'!$B$6:$B$505,A41,'Bills Log'!$C$6:$C$505,B41) | F41: =IFERROR(IF(E41=0,"",D41/E41-1),"") | G41: =D41-E41 | H41: =IFERROR(IF(ABS(D41/E41-1)>0.25,"⚠ "&ROUND((D41/E41-1)*100,0)&"%",""),"")
A42: =Settings!$B$7 | B42: Internet | C42: Jan | D42: =SUMIFS('Bills Log'!$F$6:$F$505,'Bills Log'!$A$6:$A$505,">="&DATE(Settings!$B$5,1,1),'Bills Log'!$A$6:$A$505,"<"&DATE(Settings!$B$5,2,1),'Bills Log'!$B$6:$B$505,A42,'Bills Log'!$C$6:$C$505,B42) | E42: =SUMIFS('Bills Log'!$F$6:$F$505,'Bills Log'!$A$6:$A$505,">="&DATE(Settings!$B$5-1,1,1),'Bills Log'!$A$6:$A$505,"<"&DATE((Settings!$B$5-1),2,1),'Bills Log'!$B$6:$B$505,A42,'Bills Log'!$C$6:$C$505,B42) | F42: =IFERROR(IF(E42=0,"",D42/E42-1),"") | G42: =D42-E42 | H42: =IFERROR(IF(ABS(D42/E42-1)>0.25,"⚠ "&ROUND((D42/E42-1)*100,0)&"%",""),"")
A43: =Settings!$B$7 | B43: Internet | C43: Feb | D43: =SUMIFS('Bills Log'!$F$6:$F$505,'Bills Log'!$A$6:$A$505,">="&DATE(Settings!$B$5,2,1),'Bills Log'!$A$6:$A$505,"<"&DATE(Settings!$B$5,3,1),'Bills Log'!$B$6:$B$505,A43,'Bills Log'!$C$6:$C$505,B43) | E43: =SUMIFS('Bills Log'!$F$6:$F$505,'Bills Log'!$A$6:$A$505,">="&DATE(Settings!$B$5-1,2,1),'Bills Log'!$A$6:$A$505,"<"&DATE((Settings!$B$5-1),3,1),'Bills Log'!$B$6:$B$505,A43,'Bills Log'!$C$6:$C$505,B43) | F43: =IFERROR(IF(E43=0,"",D43/E43-1),"") | G43: =D43-E43 | H43: =IFERROR(IF(ABS(D43/E43-1)>0.25,"⚠ "&ROUND((D43/E43-1)*100,0)&"%",""),"")
A44: =Settings!$B$7 | B44: Internet | C44: Mar | D44: =SUMIFS('Bills Log'!$F$6:$F$505,'Bills Log'!$A$6:$A$505,">="&DATE(Settings!$B$5,3,1),'Bills Log'!$A$6:$A$505,"<"&DATE(Settings!$B$5,4,1),'Bills Log'!$B$6:$B$505,A44,'Bills Log'!$C$6:$C$505,B44) | E44: =SUMIFS('Bills Log'!$F$6:$F$505,'Bills Log'!$A$6:$A$505,">="&DATE(Settings!$B$5-1,3,1),'Bills Log'!$A$6:$A$505,"<"&DATE((Settings!$B$5-1),4,1),'Bills Log'!$B$6:$B$505,A44,'Bills Log'!$C$6:$C$505,B44) | F44: =IFERROR(IF(E44=0,"",D44/E44-1),"") | G44: =D44-E44 | H44: =IFERROR(IF(ABS(D44/E44-1)>0.25,"⚠ "&ROUND((D44/E44-1)*100,0)&"%",""),"")
A45: =Settings!$B$7 | B45: Internet | C45: Apr | D45: =SUMIFS('Bills Log'!$F$6:$F$505,'Bills Log'!$A$6:$A$505,">="&DATE(Settings!$B$5,4,1),'Bills Log'!$A$6:$A$505,"<"&DATE(Settings!$B$5,5,1),'Bills Log'!$B$6:$B$505,A45,'Bills Log'!$C$6:$C$505,B45) | E45: =SUMIFS('Bills Log'!$F$6:$F$505,'Bills Log'!$A$6:$A$505,">="&DATE(Settings!$B$5-1,4,1),'Bills Log'!$A$6:$A$505,"<"&DATE((Settings!$B$5-1),5,1),'Bills Log'!$B$6:$B$505,A45,'Bills Log'!$C$6:$C$505,B45) | F45: =IFERROR(IF(E45=0,"",D45/E45-1),"") | G45: =D45-E45 | H45: =IFERROR(IF(ABS(D45/E45-1)>0.25,"⚠ "&ROUND((D45/E45-1)*100,0)&"%",""),"")
A46: =Settings!$B$7 | B46: Internet | C46: May | D46: =SUMIFS('Bills Log'!$F$6:$F$505,'Bills Log'!$A$6:$A$505,">="&DATE(Settings!$B$5,5,1),'Bills Log'!$A$6:$A$505,"<"&DATE(Settings!$B$5,6,1),'Bills Log'!$B$6:$B$505,A46,'Bills Log'!$C$6:$C$505,B46) | E46: =SUMIFS('Bills Log'!$F$6:$F$505,'Bills Log'!$A$6:$A$505,">="&DATE(Settings!$B$5-1,5,1),'Bills Log'!$A$6:$A$505,"<"&DATE((Settings!$B$5-1),6,1),'Bills Log'!$B$6:$B$505,A46,'Bills Log'!$C$6:$C$505,B46) | F46: =IFERROR(IF(E46=0,"",D46/E46-1),"") | G46: =D46-E46 | H46: =IFERROR(IF(ABS(D46/E46-1)>0.25,"⚠ "&ROUND((D46/E46-1)*100,0)&"%",""),"")
A47: =Settings!$B$7 | B47: Internet | C47: Jun | D47: =SUMIFS('Bills Log'!$F$6:$F$505,'Bills Log'!$A$6:$A$505,">="&DATE(Settings!$B$5,6,1),'Bills Log'!$A$6:$A$505,"<"&DATE(Settings!$B$5,7,1),'Bills Log'!$B$6:$B$505,A47,'Bills Log'!$C$6:$C$505,B47) | E47: =SUMIFS('Bills Log'!$F$6:$F$505,'Bills Log'!$A$6:$A$505,">="&DATE(Settings!$B$5-1,6,1),'Bills Log'!$A$6:$A$505,"<"&DATE((Settings!$B$5-1),7,1),'Bills Log'!$B$6:$B$505,A47,'Bills Log'!$C$6:$C$505,B47) | F47: =IFERROR(IF(E47=0,"",D47/E47-1),"") | G47: =D47-E47 | H47: =IFERROR(IF(ABS(D47/E47-1)>0.25,"⚠ "&ROUND((D47/E47-1)*100,0)&"%",""),"")
A48: =Settings!$B$7 | B48: Internet | C48: Jul | D48: =SUMIFS('Bills Log'!$F$6:$F$505,'Bills Log'!$A$6:$A$505,">="&DATE(Settings!$B$5,7,1),'Bills Log'!$A$6:$A$505,"<"&DATE(Settings!$B$5,8,1),'Bills Log'!$B$6:$B$505,A48,'Bills Log'!$C$6:$C$505,B48) | E48: =SUMIFS('Bills Log'!$F$6:$F$505,'Bills Log'!$A$6:$A$505,">="&DATE(Settings!$B$5-1,7,1),'Bills Log'!$A$6:$A$505,"<"&DATE((Settings!$B$5-1),8,1),'Bills Log'!$B$6:$B$505,A48,'Bills Log'!$C$6:$C$505,B48) | F48: =IFERROR(IF(E48=0,"",D48/E48-1),"") | G48: =D48-E48 | H48: =IFERROR(IF(ABS(D48/E48-1)>0.25,"⚠ "&ROUND((D48/E48-1)*100,0)&"%",""),"")
A49: =Settings!$B$7 | B49: Internet | C49: Aug | D49: =SUMIFS('Bills Log'!$F$6:$F$505,'Bills Log'!$A$6:$A$505,">="&DATE(Settings!$B$5,8,1),'Bills Log'!$A$6:$A$505,"<"&DATE(Settings!$B$5,9,1),'Bills Log'!$B$6:$B$505,A49,'Bills Log'!$C$6:$C$505,B49) | E49: =SUMIFS('Bills Log'!$F$6:$F$505,'Bills Log'!$A$6:$A$505,">="&DATE(Settings!$B$5-1,8,1),'Bills Log'!$A$6:$A$505,"<"&DATE((Settings!$B$5-1),9,1),'Bills Log'!$B$6:$B$505,A49,'Bills Log'!$C$6:$C$505,B49) | F49: =IFERROR(IF(E49=0,"",D49/E49-1),"") | G49: =D49-E49 | H49: =IFERROR(IF(ABS(D49/E49-1)>0.25,"⚠ "&ROUND((D49/E49-1)*100,0)&"%",""),"")
A50: =Settings!$B$7 | B50: Internet | C50: Sep | D50: =SUMIFS('Bills Log'!$F$6:$F$505,'Bills Log'!$A$6:$A$505,">="&DATE(Settings!$B$5,9,1),'Bills Log'!$A$6:$A$505,"<"&DATE(Settings!$B$5,10,1),'Bills Log'!$B$6:$B$505,A50,'Bills Log'!$C$6:$C$505,B50) | E50: =SUMIFS('Bills Log'!$F$6:$F$505,'Bills Log'!$A$6:$A$505,">="&DATE(Settings!$B$5-1,9,1),'Bills Log'!$A$6:$A$505,"<"&DATE((Settings!$B$5-1),10,1),'Bills Log'!$B$6:$B$505,A50,'Bills Log'!$C$6:$C$505,B50) | F50: =IFERROR(IF(E50=0,"",D50/E50-1),"") | G50: =D50-E50 | H50: =IFERROR(IF(ABS(D50/E50-1)>0.25,"⚠ "&ROUND((D50/E50-1)*100,0)&"%",""),"")
A51: =Settings!$B$7 | B51: Internet | C51: Oct | D51: =SUMIFS('Bills Log'!$F$6:$F$505,'Bills Log'!$A$6:$A$505,">="&DATE(Settings!$B$5,10,1),'Bills Log'!$A$6:$A$505,"<"&DATE(Settings!$B$5,11,1),'Bills Log'!$B$6:$B$505,A51,'Bills Log'!$C$6:$C$505,B51) | E51: =SUMIFS('Bills Log'!$F$6:$F$505,'Bills Log'!$A$6:$A$505,">="&DATE(Settings!$B$5-1,10,1),'Bills Log'!$A$6:$A$505,"<"&DATE((Settings!$B$5-1),11,1),'Bills Log'!$B$6:$B$505,A51,'Bills Log'!$C$6:$C$505,B51) | F51: =IFERROR(IF(E51=0,"",D51/E51-1),"") | G51: =D51-E51 | H51: =IFERROR(IF(ABS(D51/E51-1)>0.25,"⚠ "&ROUND((D51/E51-1)*100,0)&"%",""),"")
A52: =Settings!$B$7 | B52: Internet | C52: Nov | D52: =SUMIFS('Bills Log'!$F$6:$F$505,'Bills Log'!$A$6:$A$505,">="&DATE(Settings!$B$5,11,1),'Bills Log'!$A$6:$A$505,"<"&DATE(Settings!$B$5,12,1),'Bills Log'!$B$6:$B$505,A52,'Bills Log'!$C$6:$C$505,B52) | E52: =SUMIFS('Bills Log'!$F$6:$F$505,'Bills Log'!$A$6:$A$505,">="&DATE(Settings!$B$5-1,11,1),'Bills Log'!$A$6:$A$505,"<"&DATE((Settings!$B$5-1),12,1),'Bills Log'!$B$6:$B$505,A52,'Bills Log'!$C$6:$C$505,B52) | F52: =IFERROR(IF(E52=0,"",D52/E52-1),"") | G52: =D52-E52 | H52: =IFERROR(IF(ABS(D52/E52-1)>0.25,"⚠ "&ROUND((D52/E52-1)*100,0)&"%",""),"")
A53: =Settings!$B$7 | B53: Internet | C53: Dec | D53: =SUMIFS('Bills Log'!$F$6:$F$505,'Bills Log'!$A$6:$A$505,">="&DATE(Settings!$B$5,12,1),'Bills Log'!$A$6:$A$505,"<"&DATE(Settings!$B$5+1,1,1),'Bills Log'!$B$6:$B$505,A53,'Bills Log'!$C$6:$C$505,B53) | E53: =SUMIFS('Bills Log'!$F$6:$F$505,'Bills Log'!$A$6:$A$505,">="&DATE(Settings!$B$5-1,12,1),'Bills Log'!$A$6:$A$505,"<"&DATE(Settings!$B$5,1,1),'Bills Log'!$B$6:$B$505,A53,'Bills Log'!$C$6:$C$505,B53) | F53: =IFERROR(IF(E53=0,"",D53/E53-1),"") | G53: =D53-E53 | H53: =IFERROR(IF(ABS(D53/E53-1)>0.25,"⚠ "&ROUND((D53/E53-1)*100,0)&"%",""),"")
A54: =Settings!$B$7 | B54: Trash | C54: Jan | D54: =SUMIFS('Bills Log'!$F$6:$F$505,'Bills Log'!$A$6:$A$505,">="&DATE(Settings!$B$5,1,1),'Bills Log'!$A$6:$A$505,"<"&DATE(Settings!$B$5,2,1),'Bills Log'!$B$6:$B$505,A54,'Bills Log'!$C$6:$C$505,B54) | E54: =SUMIFS('Bills Log'!$F$6:$F$505,'Bills Log'!$A$6:$A$505,">="&DATE(Settings!$B$5-1,1,1),'Bills Log'!$A$6:$A$505,"<"&DATE((Settings!$B$5-1),2,1),'Bills Log'!$B$6:$B$505,A54,'Bills Log'!$C$6:$C$505,B54) | F54: =IFERROR(IF(E54=0,"",D54/E54-1),"") | G54: =D54-E54 | H54: =IFERROR(IF(ABS(D54/E54-1)>0.25,"⚠ "&ROUND((D54/E54-1)*100,0)&"%",""),"")
A55: =Settings!$B$7 | B55: Trash | C55: Feb | D55: =SUMIFS('Bills Log'!$F$6:$F$505,'Bills Log'!$A$6:$A$505,">="&DATE(Settings!$B$5,2,1),'Bills Log'!$A$6:$A$505,"<"&DATE(Settings!$B$5,3,1),'Bills Log'!$B$6:$B$505,A55,'Bills Log'!$C$6:$C$505,B55) | E55: =SUMIFS('Bills Log'!$F$6:$F$505,'Bills Log'!$A$6:$A$505,">="&DATE(Settings!$B$5-1,2,1),'Bills Log'!$A$6:$A$505,"<"&DATE((Settings!$B$5-1),3,1),'Bills Log'!$B$6:$B$505,A55,'Bills Log'!$C$6:$C$505,B55) | F55: =IFERROR(IF(E55=0,"",D55/E55-1),"") | G55: =D55-E55 | H55: =IFERROR(IF(ABS(D55/E55-1)>0.25,"⚠ "&ROUND((D55/E55-1)*100,0)&"%",""),"")
A56: =Settings!$B$7 | B56: Trash | C56: Mar | D56: =SUMIFS('Bills Log'!$F$6:$F$505,'Bills Log'!$A$6:$A$505,">="&DATE(Settings!$B$5,3,1),'Bills Log'!$A$6:$A$505,"<"&DATE(Settings!$B$5,4,1),'Bills Log'!$B$6:$B$505,A56,'Bills Log'!$C$6:$C$505,B56) | E56: =SUMIFS('Bills Log'!$F$6:$F$505,'Bills Log'!$A$6:$A$505,">="&DATE(Settings!$B$5-1,3,1),'Bills Log'!$A$6:$A$505,"<"&DATE((Settings!$B$5-1),4,1),'Bills Log'!$B$6:$B$505,A56,'Bills Log'!$C$6:$C$505,B56) | F56: =IFERROR(IF(E56=0,"",D56/E56-1),"") | G56: =D56-E56 | H56: =IFERROR(IF(ABS(D56/E56-1)>0.25,"⚠ "&ROUND((D56/E56-1)*100,0)&"%",""),"")
A57: =Settings!$B$7 | B57: Trash | C57: Apr | D57: =SUMIFS('Bills Log'!$F$6:$F$505,'Bills Log'!$A$6:$A$505,">="&DATE(Settings!$B$5,4,1),'Bills Log'!$A$6:$A$505,"<"&DATE(Settings!$B$5,5,1),'Bills Log'!$B$6:$B$505,A57,'Bills Log'!$C$6:$C$505,B57) | E57: =SUMIFS('Bills Log'!$F$6:$F$505,'Bills Log'!$A$6:$A$505,">="&DATE(Settings!$B$5-1,4,1),'Bills Log'!$A$6:$A$505,"<"&DATE((Settings!$B$5-1),5,1),'Bills Log'!$B$6:$B$505,A57,'Bills Log'!$C$6:$C$505,B57) | F57: =IFERROR(IF(E57=0,"",D57/E57-1),"") | G57: =D57-E57 | H57: =IFERROR(IF(ABS(D57/E57-1)>0.25,"⚠ "&ROUND((D57/E57-1)*100,0)&"%",""),"")
A58: =Settings!$B$7 | B58: Trash | C58: May | D58: =SUMIFS('Bills Log'!$F$6:$F$505,'Bills Log'!$A$6:$A$505,">="&DATE(Settings!$B$5,5,1),'Bills Log'!$A$6:$A$505,"<"&DATE(Settings!$B$5,6,1),'Bills Log'!$B$6:$B$505,A58,'Bills Log'!$C$6:$C$505,B58) | E58: =SUMIFS('Bills Log'!$F$6:$F$505,'Bills Log'!$A$6:$A$505,">="&DATE(Settings!$B$5-1,5,1),'Bills Log'!$A$6:$A$505,"<"&DATE((Settings!$B$5-1),6,1),'Bills Log'!$B$6:$B$505,A58,'Bills Log'!$C$6:$C$505,B58) | F58: =IFERROR(IF(E58=0,"",D58/E58-1),"") | G58: =D58-E58 | H58: =IFERROR(IF(ABS(D58/E58-1)>0.25,"⚠ "&ROUND((D58/E58-1)*100,0)&"%",""),"")
A59: =Settings!$B$7 | B59: Trash | C59: Jun | D59: =SUMIFS('Bills Log'!$F$6:$F$505,'Bills Log'!$A$6:$A$505,">="&DATE(Settings!$B$5,6,1),'Bills Log'!$A$6:$A$505,"<"&DATE(Settings!$B$5,7,1),'Bills Log'!$B$6:$B$505,A59,'Bills Log'!$C$6:$C$505,B59) | E59: =SUMIFS('Bills Log'!$F$6:$F$505,'Bills Log'!$A$6:$A$505,">="&DATE(Settings!$B$5-1,6,1),'Bills Log'!$A$6:$A$505,"<"&DATE((Settings!$B$5-1),7,1),'Bills Log'!$B$6:$B$505,A59,'Bills Log'!$C$6:$C$505,B59) | F59: =IFERROR(IF(E59=0,"",D59/E59-1),"") | G59: =D59-E59 | H59: =IFERROR(IF(ABS(D59/E59-1)>0.25,"⚠ "&ROUND((D59/E59-1)*100,0)&"%",""),"")
A60: =Settings!$B$7 | B60: Trash | C60: Jul | D60: =SUMIFS('Bills Log'!$F$6:$F$505,'Bills Log'!$A$6:$A$505,">="&DATE(Settings!$B$5,7,1),'Bills Log'!$A$6:$A$505,"<"&DATE(Settings!$B$5,8,1),'Bills Log'!$B$6:$B$505,A60,'Bills Log'!$C$6:$C$505,B60) | E60: =SUMIFS('Bills Log'!$F$6:$F$505,'Bills Log'!$A$6:$A$505,">="&DATE(Settings!$B$5-1,7,1),'Bills Log'!$A$6:$A$505,"<"&DATE((Settings!$B$5-1),8,1),'Bills Log'!$B$6:$B$505,A60,'Bills Log'!$C$6:$C$505,B60) | F60: =IFERROR(IF(E60=0,"",D60/E60-1),"") | G60: =D60-E60 | H60: =IFERROR(IF(ABS(D60/E60-1)>0.25,"⚠ "&ROUND((D60/E60-1)*100,0)&"%",""),"")
A61: =Settings!$B$7 | B61: Trash | C61: Aug | D61: =SUMIFS('Bills Log'!$F$6:$F$505,'Bills Log'!$A$6:$A$505,">="&DATE(Settings!$B$5,8,1),'Bills Log'!$A$6:$A$505,"<"&DATE(Settings!$B$5,9,1),'Bills Log'!$B$6:$B$505,A61,'Bills Log'!$C$6:$C$505,B61) | E61: =SUMIFS('Bills Log'!$F$6:$F$505,'Bills Log'!$A$6:$A$505,">="&DATE(Settings!$B$5-1,8,1),'Bills Log'!$A$6:$A$505,"<"&DATE((Settings!$B$5-1),9,1),'Bills Log'!$B$6:$B$505,A61,'Bills Log'!$C$6:$C$505,B61) | F61: =IFERROR(IF(E61=0,"",D61/E61-1),"") | G61: =D61-E61 | H61: =IFERROR(IF(ABS(D61/E61-1)>0.25,"⚠ "&ROUND((D61/E61-1)*100,0)&"%",""),"")
A62: =Settings!$B$7 | B62: Trash | C62: Sep | D62: =SUMIFS('Bills Log'!$F$6:$F$505,'Bills Log'!$A$6:$A$505,">="&DATE(Settings!$B$5,9,1),'Bills Log'!$A$6:$A$505,"<"&DATE(Settings!$B$5,10,1),'Bills Log'!$B$6:$B$505,A62,'Bills Log'!$C$6:$C$505,B62) | E62: =SUMIFS('Bills Log'!$F$6:$F$505,'Bills Log'!$A$6:$A$505,">="&DATE(Settings!$B$5-1,9,1),'Bills Log'!$A$6:$A$505,"<"&DATE((Settings!$B$5-1),10,1),'Bills Log'!$B$6:$B$505,A62,'Bills Log'!$C$6:$C$505,B62) | F62: =IFERROR(IF(E62=0,"",D62/E62-1),"") | G62: =D62-E62 | H62: =IFERROR(IF(ABS(D62/E62-1)>0.25,"⚠ "&ROUND((D62/E62-1)*100,0)&"%",""),"")
A63: =Settings!$B$7 | B63: Trash | C63: Oct | D63: =SUMIFS('Bills Log'!$F$6:$F$505,'Bills Log'!$A$6:$A$505,">="&DATE(Settings!$B$5,10,1),'Bills Log'!$A$6:$A$505,"<"&DATE(Settings!$B$5,11,1),'Bills Log'!$B$6:$B$505,A63,'Bills Log'!$C$6:$C$505,B63) | E63: =SUMIFS('Bills Log'!$F$6:$F$505,'Bills Log'!$A$6:$A$505,">="&DATE(Settings!$B$5-1,10,1),'Bills Log'!$A$6:$A$505,"<"&DATE((Settings!$B$5-1),11,1),'Bills Log'!$B$6:$B$505,A63,'Bills Log'!$C$6:$C$505,B63) | F63: =IFERROR(IF(E63=0,"",D63/E63-1),"") | G63: =D63-E63 | H63: =IFERROR(IF(ABS(D63/E63-1)>0.25,"⚠ "&ROUND((D63/E63-1)*100,0)&"%",""),"")
A64: =Settings!$B$7 | B64: Trash | C64: Nov | D64: =SUMIFS('Bills Log'!$F$6:$F$505,'Bills Log'!$A$6:$A$505,">="&DATE(Settings!$B$5,11,1),'Bills Log'!$A$6:$A$505,"<"&DATE(Settings!$B$5,12,1),'Bills Log'!$B$6:$B$505,A64,'Bills Log'!$C$6:$C$505,B64) | E64: =SUMIFS('Bills Log'!$F$6:$F$505,'Bills Log'!$A$6:$A$505,">="&DATE(Settings!$B$5-1,11,1),'Bills Log'!$A$6:$A$505,"<"&DATE((Settings!$B$5-1),12,1),'Bills Log'!$B$6:$B$505,A64,'Bills Log'!$C$6:$C$505,B64) | F64: =IFERROR(IF(E64=0,"",D64/E64-1),"") | G64: =D64-E64 | H64: =IFERROR(IF(ABS(D64/E64-1)>0.25,"⚠ "&ROUND((D64/E64-1)*100,0)&"%",""),"")
A65: =Settings!$B$7 | B65: Trash | C65: Dec | D65: =SUMIFS('Bills Log'!$F$6:$F$505,'Bills Log'!$A$6:$A$505,">="&DATE(Settings!$B$5,12,1),'Bills Log'!$A$6:$A$505,"<"&DATE(Settings!$B$5+1,1,1),'Bills Log'!$B$6:$B$505,A65,'Bills Log'!$C$6:$C$505,B65) | E65: =SUMIFS('Bills Log'!$F$6:$F$505,'Bills Log'!$A$6:$A$505,">="&DATE(Settings!$B$5-1,12,1),'Bills Log'!$A$6:$A$505,"<"&DATE(Settings!$B$5,1,1),'Bills Log'!$B$6:$B$505,A65,'Bills Log'!$C$6:$C$505,B65) | F65: =IFERROR(IF(E65=0,"",D65/E65-1),"") | G65: =D65-E65 | H65: =IFERROR(IF(ABS(D65/E65-1)>0.25,"⚠ "&ROUND((D65/E65-1)*100,0)&"%",""),"")
A66: =Settings!$B$7 | B66: Propane | C66: Jan | D66: =SUMIFS('Bills Log'!$F$6:$F$505,'Bills Log'!$A$6:$A$505,">="&DATE(Settings!$B$5,1,1),'Bills Log'!$A$6:$A$505,"<"&DATE(Settings!$B$5,2,1),'Bills Log'!$B$6:$B$505,A66,'Bills Log'!$C$6:$C$505,B66) | E66: =SUMIFS('Bills Log'!$F$6:$F$505,'Bills Log'!$A$6:$A$505,">="&DATE(Settings!$B$5-1,1,1),'Bills Log'!$A$6:$A$505,"<"&DATE((Settings!$B$5-1),2,1),'Bills Log'!$B$6:$B$505,A66,'Bills Log'!$C$6:$C$505,B66) | F66: =IFERROR(IF(E66=0,"",D66/E66-1),"") | G66: =D66-E66 | H66: =IFERROR(IF(ABS(D66/E66-1)>0.25,"⚠ "&ROUND((D66/E66-1)*100,0)&"%",""),"")
A67: =Settings!$B$7 | B67: Propane | C67: Feb | D67: =SUMIFS('Bills Log'!$F$6:$F$505,'Bills Log'!$A$6:$A$505,">="&DATE(Settings!$B$5,2,1),'Bills Log'!$A$6:$A$505,"<"&DATE(Settings!$B$5,3,1),'Bills Log'!$B$6:$B$505,A67,'Bills Log'!$C$6:$C$505,B67) | E67: =SUMIFS('Bills Log'!$F$6:$F$505,'Bills Log'!$A$6:$A$505,">="&DATE(Settings!$B$5-1,2,1),'Bills Log'!$A$6:$A$505,"<"&DATE((Settings!$B$5-1),3,1),'Bills Log'!$B$6:$B$505,A67,'Bills Log'!$C$6:$C$505,B67) | F67: =IFERROR(IF(E67=0,"",D67/E67-1),"") | G67: =D67-E67 | H67: =IFERROR(IF(ABS(D67/E67-1)>0.25,"⚠ "&ROUND((D67/E67-1)*100,0)&"%",""),"")
A68: =Settings!$B$7 | B68: Propane | C68: Mar | D68: =SUMIFS('Bills Log'!$F$6:$F$505,'Bills Log'!$A$6:$A$505,">="&DATE(Settings!$B$5,3,1),'Bills Log'!$A$6:$A$505,"<"&DATE(Settings!$B$5,4,1),'Bills Log'!$B$6:$B$505,A68,'Bills Log'!$C$6:$C$505,B68) | E68: =SUMIFS('Bills Log'!$F$6:$F$505,'Bills Log'!$A$6:$A$505,">="&DATE(Settings!$B$5-1,3,1),'Bills Log'!$A$6:$A$505,"<"&DATE((Settings!$B$5-1),4,1),'Bills Log'!$B$6:$B$505,A68,'Bills Log'!$C$6:$C$505,B68) | F68: =IFERROR(IF(E68=0,"",D68/E68-1),"") | G68: =D68-E68 | H68: =IFERROR(IF(ABS(D68/E68-1)>0.25,"⚠ "&ROUND((D68/E68-1)*100,0)&"%",""),"")
A69: =Settings!$B$7 | B69: Propane | C69: Apr | D69: =SUMIFS('Bills Log'!$F$6:$F$505,'Bills Log'!$A$6:$A$505,">="&DATE(Settings!$B$5,4,1),'Bills Log'!$A$6:$A$505,"<"&DATE(Settings!$B$5,5,1),'Bills Log'!$B$6:$B$505,A69,'Bills Log'!$C$6:$C$505,B69) | E69: =SUMIFS('Bills Log'!$F$6:$F$505,'Bills Log'!$A$6:$A$505,">="&DATE(Settings!$B$5-1,4,1),'Bills Log'!$A$6:$A$505,"<"&DATE((Settings!$B$5-1),5,1),'Bills Log'!$B$6:$B$505,A69,'Bills Log'!$C$6:$C$505,B69) | F69: =IFERROR(IF(E69=0,"",D69/E69-1),"") | G69: =D69-E69 | H69: =IFERROR(IF(ABS(D69/E69-1)>0.25,"⚠ "&ROUND((D69/E69-1)*100,0)&"%",""),"")
A70: =Settings!$B$7 | B70: Propane | C70: May | D70: =SUMIFS('Bills Log'!$F$6:$F$505,'Bills Log'!$A$6:$A$505,">="&DATE(Settings!$B$5,5,1),'Bills Log'!$A$6:$A$505,"<"&DATE(Settings!$B$5,6,1),'Bills Log'!$B$6:$B$505,A70,'Bills Log'!$C$6:$C$505,B70) | E70: =SUMIFS('Bills Log'!$F$6:$F$505,'Bills Log'!$A$6:$A$505,">="&DATE(Settings!$B$5-1,5,1),'Bills Log'!$A$6:$A$505,"<"&DATE((Settings!$B$5-1),6,1),'Bills Log'!$B$6:$B$505,A70,'Bills Log'!$C$6:$C$505,B70) | F70: =IFERROR(IF(E70=0,"",D70/E70-1),"") | G70: =D70-E70 | H70: =IFERROR(IF(ABS(D70/E70-1)>0.25,"⚠ "&ROUND((D70/E70-1)*100,0)&"%",""),"")
A71: =Settings!$B$7 | B71: Propane | C71: Jun | D71: =SUMIFS('Bills Log'!$F$6:$F$505,'Bills Log'!$A$6:$A$505,">="&DATE(Settings!$B$5,6,1),'Bills Log'!$A$6:$A$505,"<"&DATE(Settings!$B$5,7,1),'Bills Log'!$B$6:$B$505,A71,'Bills Log'!$C$6:$C$505,B71) | E71: =SUMIFS('Bills Log'!$F$6:$F$505,'Bills Log'!$A$6:$A$505,">="&DATE(Settings!$B$5-1,6,1),'Bills Log'!$A$6:$A$505,"<"&DATE((Settings!$B$5-1),7,1),'Bills Log'!$B$6:$B$505,A71,'Bills Log'!$C$6:$C$505,B71) | F71: =IFERROR(IF(E71=0,"",D71/E71-1),"") | G71: =D71-E71 | H71: =IFERROR(IF(ABS(D71/E71-1)>0.25,"⚠ "&ROUND((D71/E71-1)*100,0)&"%",""),"")
A72: =Settings!$B$7 | B72: Propane | C72: Jul | D72: =SUMIFS('Bills Log'!$F$6:$F$505,'Bills Log'!$A$6:$A$505,">="&DATE(Settings!$B$5,7,1),'Bills Log'!$A$6:$A$505,"<"&DATE(Settings!$B$5,8,1),'Bills Log'!$B$6:$B$505,A72,'Bills Log'!$C$6:$C$505,B72) | E72: =SUMIFS('Bills Log'!$F$6:$F$505,'Bills Log'!$A$6:$A$505,">="&DATE(Settings!$B$5-1,7,1),'Bills Log'!$A$6:$A$505,"<"&DATE((Settings!$B$5-1),8,1),'Bills Log'!$B$6:$B$505,A72,'Bills Log'!$C$6:$C$505,B72) | F72: =IFERROR(IF(E72=0,"",D72/E72-1),"") | G72: =D72-E72 | H72: =IFERROR(IF(ABS(D72/E72-1)>0.25,"⚠ "&ROUND((D72/E72-1)*100,0)&"%",""),"")
A73: =Settings!$B$7 | B73: Propane | C73: Aug | D73: =SUMIFS('Bills Log'!$F$6:$F$505,'Bills Log'!$A$6:$A$505,">="&DATE(Settings!$B$5,8,1),'Bills Log'!$A$6:$A$505,"<"&DATE(Settings!$B$5,9,1),'Bills Log'!$B$6:$B$505,A73,'Bills Log'!$C$6:$C$505,B73) | E73: =SUMIFS('Bills Log'!$F$6:$F$505,'Bills Log'!$A$6:$A$505,">="&DATE(Settings!$B$5-1,8,1),'Bills Log'!$A$6:$A$505,"<"&DATE((Settings!$B$5-1),9,1),'Bills Log'!$B$6:$B$505,A73,'Bills Log'!$C$6:$C$505,B73) | F73: =IFERROR(IF(E73=0,"",D73/E73-1),"") | G73: =D73-E73 | H73: =IFERROR(IF(ABS(D73/E73-1)>0.25,"⚠ "&ROUND((D73/E73-1)*100,0)&"%",""),"")
A74: =Settings!$B$7 | B74: Propane | C74: Sep | D74: =SUMIFS('Bills Log'!$F$6:$F$505,'Bills Log'!$A$6:$A$505,">="&DATE(Settings!$B$5,9,1),'Bills Log'!$A$6:$A$505,"<"&DATE(Settings!$B$5,10,1),'Bills Log'!$B$6:$B$505,A74,'Bills Log'!$C$6:$C$505,B74) | E74: =SUMIFS('Bills Log'!$F$6:$F$505,'Bills Log'!$A$6:$A$505,">="&DATE(Settings!$B$5-1,9,1),'Bills Log'!$A$6:$A$505,"<"&DATE((Settings!$B$5-1),10,1),'Bills Log'!$B$6:$B$505,A74,'Bills Log'!$C$6:$C$505,B74) | F74: =IFERROR(IF(E74=0,"",D74/E74-1),"") | G74: =D74-E74 | H74: =IFERROR(IF(ABS(D74/E74-1)>0.25,"⚠ "&ROUND((D74/E74-1)*100,0)&"%",""),"")
A75: =Settings!$B$7 | B75: Propane | C75: Oct | D75: =SUMIFS('Bills Log'!$F$6:$F$505,'Bills Log'!$A$6:$A$505,">="&DATE(Settings!$B$5,10,1),'Bills Log'!$A$6:$A$505,"<"&DATE(Settings!$B$5,11,1),'Bills Log'!$B$6:$B$505,A75,'Bills Log'!$C$6:$C$505,B75) | E75: =SUMIFS('Bills Log'!$F$6:$F$505,'Bills Log'!$A$6:$A$505,">="&DATE(Settings!$B$5-1,10,1),'Bills Log'!$A$6:$A$505,"<"&DATE((Settings!$B$5-1),11,1),'Bills Log'!$B$6:$B$505,A75,'Bills Log'!$C$6:$C$505,B75) | F75: =IFERROR(IF(E75=0,"",D75/E75-1),"") | G75: =D75-E75 | H75: =IFERROR(IF(ABS(D75/E75-1)>0.25,"⚠ "&ROUND((D75/E75-1)*100,0)&"%",""),"")
A76: =Settings!$B$7 | B76: Propane | C76: Nov | D76: =SUMIFS('Bills Log'!$F$6:$F$505,'Bills Log'!$A$6:$A$505,">="&DATE(Settings!$B$5,11,1),'Bills Log'!$A$6:$A$505,"<"&DATE(Settings!$B$5,12,1),'Bills Log'!$B$6:$B$505,A76,'Bills Log'!$C$6:$C$505,B76) | E76: =SUMIFS('Bills Log'!$F$6:$F$505,'Bills Log'!$A$6:$A$505,">="&DATE(Settings!$B$5-1,11,1),'Bills Log'!$A$6:$A$505,"<"&DATE((Settings!$B$5-1),12,1),'Bills Log'!$B$6:$B$505,A76,'Bills Log'!$C$6:$C$505,B76) | F76: =IFERROR(IF(E76=0,"",D76/E76-1),"") | G76: =D76-E76 | H76: =IFERROR(IF(ABS(D76/E76-1)>0.25,"⚠ "&ROUND((D76/E76-1)*100,0)&"%",""),"")
A77: =Settings!$B$7 | B77: Propane | C77: Dec | D77: =SUMIFS('Bills Log'!$F$6:$F$505,'Bills Log'!$A$6:$A$505,">="&DATE(Settings!$B$5,12,1),'Bills Log'!$A$6:$A$505,"<"&DATE(Settings!$B$5+1,1,1),'Bills Log'!$B$6:$B$505,A77,'Bills Log'!$C$6:$C$505,B77) | E77: =SUMIFS('Bills Log'!$F$6:$F$505,'Bills Log'!$A$6:$A$505,">="&DATE(Settings!$B$5-1,12,1),'Bills Log'!$A$6:$A$505,"<"&DATE(Settings!$B$5,1,1),'Bills Log'!$B$6:$B$505,A77,'Bills Log'!$C$6:$C$505,B77) | F77: =IFERROR(IF(E77=0,"",D77/E77-1),"") | G77: =D77-E77 | H77: =IFERROR(IF(ABS(D77/E77-1)>0.25,"⚠ "&ROUND((D77/E77-1)*100,0)&"%",""),"")
A78: =Settings!$B$8 | B78: Electric | C78: Jan | D78: =SUMIFS('Bills Log'!$F$6:$F$505,'Bills Log'!$A$6:$A$505,">="&DATE(Settings!$B$5,1,1),'Bills Log'!$A$6:$A$505,"<"&DATE(Settings!$B$5,2,1),'Bills Log'!$B$6:$B$505,A78,'Bills Log'!$C$6:$C$505,B78) | E78: =SUMIFS('Bills Log'!$F$6:$F$505,'Bills Log'!$A$6:$A$505,">="&DATE(Settings!$B$5-1,1,1),'Bills Log'!$A$6:$A$505,"<"&DATE((Settings!$B$5-1),2,1),'Bills Log'!$B$6:$B$505,A78,'Bills Log'!$C$6:$C$505,B78) | F78: =IFERROR(IF(E78=0,"",D78/E78-1),"") | G78: =D78-E78 | H78: =IFERROR(IF(ABS(D78/E78-1)>0.25,"⚠ "&ROUND((D78/E78-1)*100,0)&"%",""),"")
A79: =Settings!$B$8 | B79: Electric | C79: Feb | D79: =SUMIFS('Bills Log'!$F$6:$F$505,'Bills Log'!$A$6:$A$505,">="&DATE(Settings!$B$5,2,1),'Bills Log'!$A$6:$A$505,"<"&DATE(Settings!$B$5,3,1),'Bills Log'!$B$6:$B$505,A79,'Bills Log'!$C$6:$C$505,B79) | E79: =SUMIFS('Bills Log'!$F$6:$F$505,'Bills Log'!$A$6:$A$505,">="&DATE(Settings!$B$5-1,2,1),'Bills Log'!$A$6:$A$505,"<"&DATE((Settings!$B$5-1),3,1),'Bills Log'!$B$6:$B$505,A79,'Bills Log'!$C$6:$C$505,B79) | F79: =IFERROR(IF(E79=0,"",D79/E79-1),"") | G79: =D79-E79 | H79: =IFERROR(IF(ABS(D79/E79-1)>0.25,"⚠ "&ROUND((D79/E79-1)*100,0)&"%",""),"")
A80: =Settings!$B$8 | B80: Electric | C80: Mar | D80: =SUMIFS('Bills Log'!$F$6:$F$505,'Bills Log'!$A$6:$A$505,">="&DATE(Settings!$B$5,3,1),'Bills Log'!$A$6:$A$505,"<"&DATE(Settings!$B$5,4,1),'Bills Log'!$B$6:$B$505,A80,'Bills Log'!$C$6:$C$505,B80) | E80: =SUMIFS('Bills Log'!$F$6:$F$505,'Bills Log'!$A$6:$A$505,">="&DATE(Settings!$B$5-1,3,1),'Bills Log'!$A$6:$A$505,"<"&DATE((Settings!$B$5-1),4,1),'Bills Log'!$B$6:$B$505,A80,'Bills Log'!$C$6:$C$505,B80) | F80: =IFERROR(IF(E80=0,"",D80/E80-1),"") | G80: =D80-E80 | H80: =IFERROR(IF(ABS(D80/E80-1)>0.25,"⚠ "&ROUND((D80/E80-1)*100,0)&"%",""),"")
A81: =Settings!$B$8 | B81: Electric | C81: Apr | D81: =SUMIFS('Bills Log'!$F$6:$F$505,'Bills Log'!$A$6:$A$505,">="&DATE(Settings!$B$5,4,1),'Bills Log'!$A$6:$A$505,"<"&DATE(Settings!$B$5,5,1),'Bills Log'!$B$6:$B$505,A81,'Bills Log'!$C$6:$C$505,B81) | E81: =SUMIFS('Bills Log'!$F$6:$F$505,'Bills Log'!$A$6:$A$505,">="&DATE(Settings!$B$5-1,4,1),'Bills Log'!$A$6:$A$505,"<"&DATE((Settings!$B$5-1),5,1),'Bills Log'!$B$6:$B$505,A81,'Bills Log'!$C$6:$C$505,B81) | F81: =IFERROR(IF(E81=0,"",D81/E81-1),"") | G81: =D81-E81 | H81: =IFERROR(IF(ABS(D81/E81-1)>0.25,"⚠ "&ROUND((D81/E81-1)*100,0)&"%",""),"")
A82: =Settings!$B$8 | B82: Electric | C82: May | D82: =SUMIFS('Bills Log'!$F$6:$F$505,'Bills Log'!$A$6:$A$505,">="&DATE(Settings!$B$5,5,1),'Bills Log'!$A$6:$A$505,"<"&DATE(Settings!$B$5,6,1),'Bills Log'!$B$6:$B$505,A82,'Bills Log'!$C$6:$C$505,B82) | E82: =SUMIFS('Bills Log'!$F$6:$F$505,'Bills Log'!$A$6:$A$505,">="&DATE(Settings!$B$5-1,5,1),'Bills Log'!$A$6:$A$505,"<"&DATE((Settings!$B$5-1),6,1),'Bills Log'!$B$6:$B$505,A82,'Bills Log'!$C$6:$C$505,B82) | F82: =IFERROR(IF(E82=0,"",D82/E82-1),"") | G82: =D82-E82 | H82: =IFERROR(IF(ABS(D82/E82-1)>0.25,"⚠ "&ROUND((D82/E82-1)*100,0)&"%",""),"")
A83: =Settings!$B$8 | B83: Electric | C83: Jun | D83: =SUMIFS('Bills Log'!$F$6:$F$505,'Bills Log'!$A$6:$A$505,">="&DATE(Settings!$B$5,6,1),'Bills Log'!$A$6:$A$505,"<"&DATE(Settings!$B$5,7,1),'Bills Log'!$B$6:$B$505,A83,'Bills Log'!$C$6:$C$505,B83) | E83: =SUMIFS('Bills Log'!$F$6:$F$505,'Bills Log'!$A$6:$A$505,">="&DATE(Settings!$B$5-1,6,1),'Bills Log'!$A$6:$A$505,"<"&DATE((Settings!$B$5-1),7,1),'Bills Log'!$B$6:$B$505,A83,'Bills Log'!$C$6:$C$505,B83) | F83: =IFERROR(IF(E83=0,"",D83/E83-1),"") | G83: =D83-E83 | H83: =IFERROR(IF(ABS(D83/E83-1)>0.25,"⚠ "&ROUND((D83/E83-1)*100,0)&"%",""),"")
A84: =Settings!$B$8 | B84: Electric | C84: Jul | D84: =SUMIFS('Bills Log'!$F$6:$F$505,'Bills Log'!$A$6:$A$505,">="&DATE(Settings!$B$5,7,1),'Bills Log'!$A$6:$A$505,"<"&DATE(Settings!$B$5,8,1),'Bills Log'!$B$6:$B$505,A84,'Bills Log'!$C$6:$C$505,B84) | E84: =SUMIFS('Bills Log'!$F$6:$F$505,'Bills Log'!$A$6:$A$505,">="&DATE(Settings!$B$5-1,7,1),'Bills Log'!$A$6:$A$505,"<"&DATE((Settings!$B$5-1),8,1),'Bills Log'!$B$6:$B$505,A84,'Bills Log'!$C$6:$C$505,B84) | F84: =IFERROR(IF(E84=0,"",D84/E84-1),"") | G84: =D84-E84 | H84: =IFERROR(IF(ABS(D84/E84-1)>0.25,"⚠ "&ROUND((D84/E84-1)*100,0)&"%",""),"")
A85: =Settings!$B$8 | B85: Electric | C85: Aug | D85: =SUMIFS('Bills Log'!$F$6:$F$505,'Bills Log'!$A$6:$A$505,">="&DATE(Settings!$B$5,8,1),'Bills Log'!$A$6:$A$505,"<"&DATE(Settings!$B$5,9,1),'Bills Log'!$B$6:$B$505,A85,'Bills Log'!$C$6:$C$505,B85) | E85: =SUMIFS('Bills Log'!$F$6:$F$505,'Bills Log'!$A$6:$A$505,">="&DATE(Settings!$B$5-1,8,1),'Bills Log'!$A$6:$A$505,"<"&DATE((Settings!$B$5-1),9,1),'Bills Log'!$B$6:$B$505,A85,'Bills Log'!$C$6:$C$505,B85) | F85: =IFERROR(IF(E85=0,"",D85/E85-1),"") | G85: =D85-E85 | H85: =IFERROR(IF(ABS(D85/E85-1)>0.25,"⚠ "&ROUND((D85/E85-1)*100,0)&"%",""),"")
A86: =Settings!$B$8 | B86: Electric | C86: Sep | D86: =SUMIFS('Bills Log'!$F$6:$F$505,'Bills Log'!$A$6:$A$505,">="&DATE(Settings!$B$5,9,1),'Bills Log'!$A$6:$A$505,"<"&DATE(Settings!$B$5,10,1),'Bills Log'!$B$6:$B$505,A86,'Bills Log'!$C$6:$C$505,B86) | E86: =SUMIFS('Bills Log'!$F$6:$F$505,'Bills Log'!$A$6:$A$505,">="&DATE(Settings!$B$5-1,9,1),'Bills Log'!$A$6:$A$505,"<"&DATE((Settings!$B$5-1),10,1),'Bills Log'!$B$6:$B$505,A86,'Bills Log'!$C$6:$C$505,B86) | F86: =IFERROR(IF(E86=0,"",D86/E86-1),"") | G86: =D86-E86 | H86: =IFERROR(IF(ABS(D86/E86-1)>0.25,"⚠ "&ROUND((D86/E86-1)*100,0)&"%",""),"")
A87: =Settings!$B$8 | B87: Electric | C87: Oct | D87: =SUMIFS('Bills Log'!$F$6:$F$505,'Bills Log'!$A$6:$A$505,">="&DATE(Settings!$B$5,10,1),'Bills Log'!$A$6:$A$505,"<"&DATE(Settings!$B$5,11,1),'Bills Log'!$B$6:$B$505,A87,'Bills Log'!$C$6:$C$505,B87) | E87: =SUMIFS('Bills Log'!$F$6:$F$505,'Bills Log'!$A$6:$A$505,">="&DATE(Settings!$B$5-1,10,1),'Bills Log'!$A$6:$A$505,"<"&DATE((Settings!$B$5-1),11,1),'Bills Log'!$B$6:$B$505,A87,'Bills Log'!$C$6:$C$505,B87) | F87: =IFERROR(IF(E87=0,"",D87/E87-1),"") | G87: =D87-E87 | H87: =IFERROR(IF(ABS(D87/E87-1)>0.25,"⚠ "&ROUND((D87/E87-1)*100,0)&"%",""),"")
A88: =Settings!$B$8 | B88: Electric | C88: Nov | D88: =SUMIFS('Bills Log'!$F$6:$F$505,'Bills Log'!$A$6:$A$505,">="&DATE(Settings!$B$5,11,1),'Bills Log'!$A$6:$A$505,"<"&DATE(Settings!$B$5,12,1),'Bills Log'!$B$6:$B$505,A88,'Bills Log'!$C$6:$C$505,B88) | E88: =SUMIFS('Bills Log'!$F$6:$F$505,'Bills Log'!$A$6:$A$505,">="&DATE(Settings!$B$5-1,11,1),'Bills Log'!$A$6:$A$505,"<"&DATE((Settings!$B$5-1),12,1),'Bills Log'!$B$6:$B$505,A88,'Bills Log'!$C$6:$C$505,B88) | F88: =IFERROR(IF(E88=0,"",D88/E88-1),"") | G88: =D88-E88 | H88: =IFERROR(IF(ABS(D88/E88-1)>0.25,"⚠ "&ROUND((D88/E88-1)*100,0)&"%",""),"")
A89: =Settings!$B$8 | B89: Electric | C89: Dec | D89: =SUMIFS('Bills Log'!$F$6:$F$505,'Bills Log'!$A$6:$A$505,">="&DATE(Settings!$B$5,12,1),'Bills Log'!$A$6:$A$505,"<"&DATE(Settings!$B$5+1,1,1),'Bills Log'!$B$6:$B$505,A89,'Bills Log'!$C$6:$C$505,B89) | E89: =SUMIFS('Bills Log'!$F$6:$F$505,'Bills Log'!$A$6:$A$505,">="&DATE(Settings!$B$5-1,12,1),'Bills Log'!$A$6:$A$505,"<"&DATE(Settings!$B$5,1,1),'Bills Log'!$B$6:$B$505,A89,'Bills Log'!$C$6:$C$505,B89) | F89: =IFERROR(IF(E89=0,"",D89/E89-1),"") | G89: =D89-E89 | H89: =IFERROR(IF(ABS(D89/E89-1)>0.25,"⚠ "&ROUND((D89/E89-1)*100,0)&"%",""),"")
A90: =Settings!$B$8 | B90: Gas | C90: Jan | D90: =SUMIFS('Bills Log'!$F$6:$F$505,'Bills Log'!$A$6:$A$505,">="&DATE(Settings!$B$5,1,1),'Bills Log'!$A$6:$A$505,"<"&DATE(Settings!$B$5,2,1),'Bills Log'!$B$6:$B$505,A90,'Bills Log'!$C$6:$C$505,B90) | E90: =SUMIFS('Bills Log'!$F$6:$F$505,'Bills Log'!$A$6:$A$505,">="&DATE(Settings!$B$5-1,1,1),'Bills Log'!$A$6:$A$505,"<"&DATE((Settings!$B$5-1),2,1),'Bills Log'!$B$6:$B$505,A90,'Bills Log'!$C$6:$C$505,B90) | F90: =IFERROR(IF(E90=0,"",D90/E90-1),"") | G90: =D90-E90 | H90: =IFERROR(IF(ABS(D90/E90-1)>0.25,"⚠ "&ROUND((D90/E90-1)*100,0)&"%",""),"")
A91: =Settings!$B$8 | B91: Gas | C91: Feb | D91: =SUMIFS('Bills Log'!$F$6:$F$505,'Bills Log'!$A$6:$A$505,">="&DATE(Settings!$B$5,2,1),'Bills Log'!$A$6:$A$505,"<"&DATE(Settings!$B$5,3,1),'Bills Log'!$B$6:$B$505,A91,'Bills Log'!$C$6:$C$505,B91) | E91: =SUMIFS('Bills Log'!$F$6:$F$505,'Bills Log'!$A$6:$A$505,">="&DATE(Settings!$B$5-1,2,1),'Bills Log'!$A$6:$A$505,"<"&DATE((Settings!$B$5-1),3,1),'Bills Log'!$B$6:$B$505,A91,'Bills Log'!$C$6:$C$505,B91) | F91: =IFERROR(IF(E91=0,"",D91/E91-1),"") | G91: =D91-E91 | H91: =IFERROR(IF(ABS(D91/E91-1)>0.25,"⚠ "&ROUND((D91/E91-1)*100,0)&"%",""),"")
A92: =Settings!$B$8 | B92: Gas | C92: Mar | D92: =SUMIFS('Bills Log'!$F$6:$F$505,'Bills Log'!$A$6:$A$505,">="&DATE(Settings!$B$5,3,1),'Bills Log'!$A$6:$A$505,"<"&DATE(Settings!$B$5,4,1),'Bills Log'!$B$6:$B$505,A92,'Bills Log'!$C$6:$C$505,B92) | E92: =SUMIFS('Bills Log'!$F$6:$F$505,'Bills Log'!$A$6:$A$505,">="&DATE(Settings!$B$5-1,3,1),'Bills Log'!$A$6:$A$505,"<"&DATE((Settings!$B$5-1),4,1),'Bills Log'!$B$6:$B$505,A92,'Bills Log'!$C$6:$C$505,B92) | F92: =IFERROR(IF(E92=0,"",D92/E92-1),"") | G92: =D92-E92 | H92: =IFERROR(IF(ABS(D92/E92-1)>0.25,"⚠ "&ROUND((D92/E92-1)*100,0)&"%",""),"")
A93: =Settings!$B$8 | B93: Gas | C93: Apr | D93: =SUMIFS('Bills Log'!$F$6:$F$505,'Bills Log'!$A$6:$A$505,">="&DATE(Settings!$B$5,4,1),'Bills Log'!$A$6:$A$505,"<"&DATE(Settings!$B$5,5,1),'Bills Log'!$B$6:$B$505,A93,'Bills Log'!$C$6:$C$505,B93) | E93: =SUMIFS('Bills Log'!$F$6:$F$505,'Bills Log'!$A$6:$A$505,">="&DATE(Settings!$B$5-1,4,1),'Bills Log'!$A$6:$A$505,"<"&DATE((Settings!$B$5-1),5,1),'Bills Log'!$B$6:$B$505,A93,'Bills Log'!$C$6:$C$505,B93) | F93: =IFERROR(IF(E93=0,"",D93/E93-1),"") | G93: =D93-E93 | H93: =IFERROR(IF(ABS(D93/E93-1)>0.25,"⚠ "&ROUND((D93/E93-1)*100,0)&"%",""),"")
A94: =Settings!$B$8 | B94: Gas | C94: May | D94: =SUMIFS('Bills Log'!$F$6:$F$505,'Bills Log'!$A$6:$A$505,">="&DATE(Settings!$B$5,5,1),'Bills Log'!$A$6:$A$505,"<"&DATE(Settings!$B$5,6,1),'Bills Log'!$B$6:$B$505,A94,'Bills Log'!$C$6:$C$505,B94) | E94: =SUMIFS('Bills Log'!$F$6:$F$505,'Bills Log'!$A$6:$A$505,">="&DATE(Settings!$B$5-1,5,1),'Bills Log'!$A$6:$A$505,"<"&DATE((Settings!$B$5-1),6,1),'Bills Log'!$B$6:$B$505,A94,'Bills Log'!$C$6:$C$505,B94) | F94: =IFERROR(IF(E94=0,"",D94/E94-1),"") | G94: =D94-E94 | H94: =IFERROR(IF(ABS(D94/E94-1)>0.25,"⚠ "&ROUND((D94/E94-1)*100,0)&"%",""),"")
A95: =Settings!$B$8 | B95: Gas | C95: Jun | D95: =SUMIFS('Bills Log'!$F$6:$F$505,'Bills Log'!$A$6:$A$505,">="&DATE(Settings!$B$5,6,1),'Bills Log'!$A$6:$A$505,"<"&DATE(Settings!$B$5,7,1),'Bills Log'!$B$6:$B$505,A95,'Bills Log'!$C$6:$C$505,B95) | E95: =SUMIFS('Bills Log'!$F$6:$F$505,'Bills Log'!$A$6:$A$505,">="&DATE(Settings!$B$5-1,6,1),'Bills Log'!$A$6:$A$505,"<"&DATE((Settings!$B$5-1),7,1),'Bills Log'!$B$6:$B$505,A95,'Bills Log'!$C$6:$C$505,B95) | F95: =IFERROR(IF(E95=0,"",D95/E95-1),"") | G95: =D95-E95 | H95: =IFERROR(IF(ABS(D95/E95-1)>0.25,"⚠ "&ROUND((D95/E95-1)*100,0)&"%",""),"")
A96: =Settings!$B$8 | B96: Gas | C96: Jul | D96: =SUMIFS('Bills Log'!$F$6:$F$505,'Bills Log'!$A$6:$A$505,">="&DATE(Settings!$B$5,7,1),'Bills Log'!$A$6:$A$505,"<"&DATE(Settings!$B$5,8,1),'Bills Log'!$B$6:$B$505,A96,'Bills Log'!$C$6:$C$505,B96) | E96: =SUMIFS('Bills Log'!$F$6:$F$505,'Bills Log'!$A$6:$A$505,">="&DATE(Settings!$B$5-1,7,1),'Bills Log'!$A$6:$A$505,"<"&DATE((Settings!$B$5-1),8,1),'Bills Log'!$B$6:$B$505,A96,'Bills Log'!$C$6:$C$505,B96) | F96: =IFERROR(IF(E96=0,"",D96/E96-1),"") | G96: =D96-E96 | H96: =IFERROR(IF(ABS(D96/E96-1)>0.25,"⚠ "&ROUND((D96/E96-1)*100,0)&"%",""),"")
A97: =Settings!$B$8 | B97: Gas | C97: Aug | D97: =SUMIFS('Bills Log'!$F$6:$F$505,'Bills Log'!$A$6:$A$505,">="&DATE(Settings!$B$5,8,1),'Bills Log'!$A$6:$A$505,"<"&DATE(Settings!$B$5,9,1),'Bills Log'!$B$6:$B$505,A97,'Bills Log'!$C$6:$C$505,B97) | E97: =SUMIFS('Bills Log'!$F$6:$F$505,'Bills Log'!$A$6:$A$505,">="&DATE(Settings!$B$5-1,8,1),'Bills Log'!$A$6:$A$505,"<"&DATE((Settings!$B$5-1),9,1),'Bills Log'!$B$6:$B$505,A97,'Bills Log'!$C$6:$C$505,B97) | F97: =IFERROR(IF(E97=0,"",D97/E97-1),"") | G97: =D97-E97 | H97: =IFERROR(IF(ABS(D97/E97-1)>0.25,"⚠ "&ROUND((D97/E97-1)*100,0)&"%",""),"")
A98: =Settings!$B$8 | B98: Gas | C98: Sep | D98: =SUMIFS('Bills Log'!$F$6:$F$505,'Bills Log'!$A$6:$A$505,">="&DATE(Settings!$B$5,9,1),'Bills Log'!$A$6:$A$505,"<"&DATE(Settings!$B$5,10,1),'Bills Log'!$B$6:$B$505,A98,'Bills Log'!$C$6:$C$505,B98) | E98: =SUMIFS('Bills Log'!$F$6:$F$505,'Bills Log'!$A$6:$A$505,">="&DATE(Settings!$B$5-1,9,1),'Bills Log'!$A$6:$A$505,"<"&DATE((Settings!$B$5-1),10,1),'Bills Log'!$B$6:$B$505,A98,'Bills Log'!$C$6:$C$505,B98) | F98: =IFERROR(IF(E98=0,"",D98/E98-1),"") | G98: =D98-E98 | H98: =IFERROR(IF(ABS(D98/E98-1)>0.25,"⚠ "&ROUND((D98/E98-1)*100,0)&"%",""),"")
A99: =Settings!$B$8 | B99: Gas | C99: Oct | D99: =SUMIFS('Bills Log'!$F$6:$F$505,'Bills Log'!$A$6:$A$505,">="&DATE(Settings!$B$5,10,1),'Bills Log'!$A$6:$A$505,"<"&DATE(Settings!$B$5,11,1),'Bills Log'!$B$6:$B$505,A99,'Bills Log'!$C$6:$C$505,B99) | E99: =SUMIFS('Bills Log'!$F$6:$F$505,'Bills Log'!$A$6:$A$505,">="&DATE(Settings!$B$5-1,10,1),'Bills Log'!$A$6:$A$505,"<"&DATE((Settings!$B$5-1),11,1),'Bills Log'!$B$6:$B$505,A99,'Bills Log'!$C$6:$C$505,B99) | F99: =IFERROR(IF(E99=0,"",D99/E99-1),"") | G99: =D99-E99 | H99: =IFERROR(IF(ABS(D99/E99-1)>0.25,"⚠ "&ROUND((D99/E99-1)*100,0)&"%",""),"")
A100: =Settings!$B$8 | B100: Gas | C100: Nov | D100: =SUMIFS('Bills Log'!$F$6:$F$505,'Bills Log'!$A$6:$A$505,">="&DATE(Settings!$B$5,11,1),'Bills Log'!$A$6:$A$505,"<"&DATE(Settings!$B$5,12,1),'Bills Log'!$B$6:$B$505,A100,'Bills Log'!$C$6:$C$505,B100) | E100: =SUMIFS('Bills Log'!$F$6:$F$505,'Bills Log'!$A$6:$A$505,">="&DATE(Settings!$B$5-1,11,1),'Bills Log'!$A$6:$A$505,"<"&DATE((Settings!$B$5-1),12,1),'Bills Log'!$B$6:$B$505,A100,'Bills Log'!$C$6:$C$505,B100) | F100: =IFERROR(IF(E100=0,"",D100/E100-1),"") | G100: =D100-E100 | H100: =IFERROR(IF(ABS(D100/E100-1)>0.25,"⚠ "&ROUND((D100/E100-1)*100,0)&"%",""),"")
A101: =Settings!$B$8 | B101: Gas | C101: Dec | D101: =SUMIFS('Bills Log'!$F$6:$F$505,'Bills Log'!$A$6:$A$505,">="&DATE(Settings!$B$5,12,1),'Bills Log'!$A$6:$A$505,"<"&DATE(Settings!$B$5+1,1,1),'Bills Log'!$B$6:$B$505,A101,'Bills Log'!$C$6:$C$505,B101) | E101: =SUMIFS('Bills Log'!$F$6:$F$505,'Bills Log'!$A$6:$A$505,">="&DATE(Settings!$B$5-1,12,1),'Bills Log'!$A$6:$A$505,"<"&DATE(Settings!$B$5,1,1),'Bills Log'!$B$6:$B$505,A101,'Bills Log'!$C$6:$C$505,B101) | F101: =IFERROR(IF(E101=0,"",D101/E101-1),"") | G101: =D101-E101 | H101: =IFERROR(IF(ABS(D101/E101-1)>0.25,"⚠ "&ROUND((D101/E101-1)*100,0)&"%",""),"")
...

Sheet Settings
A2: =HYPERLINK("#'Trend & Anomalies'!A1", "← BACK") | D2: SETTINGS
A4: Active tax year · Property list · Service list
A5: Active tax year: | B5: 2026
A6: Bump this each January. The Trend & Anomalies tab compares this year to (this year - 1). Without it, dashboards return $0 when the system clock doesn't match logged dates.
A7: Properties:
A17: Services:
B18: Electric
B19: Gas
B20: Water
B21: Internet
B22: Trash
B23: Propane
B24: Other
A27: The Bills Log Property and Service dropdowns read directly from these two ranges (B7:B16 and B18:B25). Renaming a property here cascades to the matrix automatically.
