Workbook

Sheet Start
A2: The STR Ledger
A4: License / Permit / STR-Reg Tracker
A5: An alarm clock for the renewals you'd otherwise forget.
A7: OPS-003 · v1.0 · BLANK
A10: EXPIRED | E10: RENEW NOW (<30 DAYS) | I10: FILING $ YTD
A11: =COUNTIF('Permits Register'!M7:M206,"EXPIRED") | E11: =COUNTIFS('Permits Register'!L7:L206,">=0",'Permits Register'!L7:L206,"<30") | I11: =SUMPRODUCT((YEAR('Filing Log'!A7:A506)=YEAR(TODAY()))*'Filing Log'!E7:E506)
A14: permits past renewal date | E14: permits due in next 30 days | I14: fees paid year to date
A17: =IF(COUNTIF('Permits Register'!M7:M206,"EXPIRED")>0,"OPERATING WHILE EXPIRED — STOP. One or more permits below are past their renewal date. Operating without a current permit creates legal + financial liability. Renew before the next booking starts.","ALL CLEAR — No expired permits in your portfolio.")
A20: TOP RENEWAL ACTIONS
A21: Open the Renewal Calendar tab — permits are sorted by urgency (EXPIRED on top, then <30 days red, then 30-90 gold). The five most urgent permits in your portfolio are listed there.
A23: Why this matters: most STR fines come from missed renewals, not from regulatory violations. Knox County, TN issues a $750 fine + 30-day suspension for an expired Type 2 permit. Nashville has issued $1,500 fines for operating without a current STRP. Use the Renewal Calendar to nail the dates before the platforms (Airbnb, VRBO) auto-suspend the listing.
A28: =HYPERLINK("#'Permits Register'!A1", "Permits Register") | D28: =HYPERLINK("#'Renewal Calendar'!A1", "Renewal Calendar") | G28: =HYPERLINK("#'Permit Discovery'!A1", "Permit Discovery") | J28: =HYPERLINK("#'Filing Log'!A1", "Filing Log")
A32: =HYPERLINK("#'Settings'!A1", "Settings")
A36: Need full operations coverage? Add the Operator Bundle at thestrledger.com/operator — turnover + maintenance + supply + damage claims + insurance + permits, $197.
A39: Questions? hello@thestrledger.com
A40: OPS-003 · v1.0 · BLANK · Free updates forever

Sheet Permits Register
A2: =HYPERLINK("#'Start'!A1", "← BACK") | D2: PERMITS REGISTER | J2: =HYPERLINK("#'Renewal Calendar'!A1", "NEXT →")
A4: One row per property × permit type. Days-to-renewal auto-calculates from the Renewal date — keep that column accurate.
A6: Property | B6: Permit type | C6: Jurisdiction | D6: Permit # | E6: Issue date | F6: Renewal date | G6: Cadence | H6: $ Cost | I6: Status (entered) | J6: File location | K6: Notes | L6: Days to renewal | M6: Auto status
L7: =IF(F7<>"",F7-TODAY(),"") | M7: =IF(F7="","",IF(AND(L7<0,I7<>"Renewed",I7<>"N/A"),"EXPIRED",I7))
L8: =IF(F8<>"",F8-TODAY(),"") | M8: =IF(F8="","",IF(AND(L8<0,I8<>"Renewed",I8<>"N/A"),"EXPIRED",I8))
L9: =IF(F9<>"",F9-TODAY(),"") | M9: =IF(F9="","",IF(AND(L9<0,I9<>"Renewed",I9<>"N/A"),"EXPIRED",I9))
L10: =IF(F10<>"",F10-TODAY(),"") | M10: =IF(F10="","",IF(AND(L10<0,I10<>"Renewed",I10<>"N/A"),"EXPIRED",I10))
L11: =IF(F11<>"",F11-TODAY(),"") | M11: =IF(F11="","",IF(AND(L11<0,I11<>"Renewed",I11<>"N/A"),"EXPIRED",I11))
L12: =IF(F12<>"",F12-TODAY(),"") | M12: =IF(F12="","",IF(AND(L12<0,I12<>"Renewed",I12<>"N/A"),"EXPIRED",I12))
L13: =IF(F13<>"",F13-TODAY(),"") | M13: =IF(F13="","",IF(AND(L13<0,I13<>"Renewed",I13<>"N/A"),"EXPIRED",I13))
L14: =IF(F14<>"",F14-TODAY(),"") | M14: =IF(F14="","",IF(AND(L14<0,I14<>"Renewed",I14<>"N/A"),"EXPIRED",I14))
L15: =IF(F15<>"",F15-TODAY(),"") | M15: =IF(F15="","",IF(AND(L15<0,I15<>"Renewed",I15<>"N/A"),"EXPIRED",I15))
L16: =IF(F16<>"",F16-TODAY(),"") | M16: =IF(F16="","",IF(AND(L16<0,I16<>"Renewed",I16<>"N/A"),"EXPIRED",I16))
L17: =IF(F17<>"",F17-TODAY(),"") | M17: =IF(F17="","",IF(AND(L17<0,I17<>"Renewed",I17<>"N/A"),"EXPIRED",I17))
L18: =IF(F18<>"",F18-TODAY(),"") | M18: =IF(F18="","",IF(AND(L18<0,I18<>"Renewed",I18<>"N/A"),"EXPIRED",I18))
... L206: =IF(F206<>"",F206-TODAY(),"") | M206: =IF(F206="","",IF(AND(L206<0,I206<>"Renewed",I206<>"N/A"),"EXPIRED",I206))

Sheet Renewal Calendar
A2: =HYPERLINK("#'Permits Register'!A1", "← BACK") | D2: RENEWAL CALENDAR | J2: =HYPERLINK("#'Permit Discovery'!A1", "NEXT →")
A4: Three urgency bands sorted by days-to-renewal. The list refreshes automatically — updates flow from the Permits Register every time you open the workbook.
A6: EXPIRED — RENEW IMMEDIATELY
A7: Property | B7: Permit type | C7: Jurisdiction | D7: Permit # | E7: Renewal date | F7: Days | G7: $ Cost | H7: Notes
A13: RENEW NOW — LESS THAN 30 DAYS
A14: Property | B14: Permit type | C14: Jurisdiction | D14: Permit # | E14: Renewal date | F14: Days | G14: $ Cost | H14: Notes
A21: UPCOMING — 30 TO 90 DAYS
A22: Property | B22: Permit type | C22: Jurisdiction | D22: Permit # | E22: Renewal date | F22: Days | G22: $ Cost | H22: Notes
A32: =IF(COUNTIFS('Permits Register'!L7:L206,">90")>0,"Permits more than 90 days out: "&COUNTIFS('Permits Register'!L7:L206,">90")&" — open the Permits Register for the full list.","All long-horizon permits will surface here as their dates approach.")
A34: Note: this view is a manual snapshot — the rows above show the permits as of build time. After you edit the Permits Register, the days-to-renewal columns recalc automatically; rerun-sort by hand if you need this view re-ranked.

Sheet Permit Discovery
A2: =HYPERLINK("#'Renewal Calendar'!A1", "← BACK") | D2: PERMIT DISCOVERY | J2: =HYPERLINK("#'Filing Log'!A1", "NEXT →")
A4: Top STR markets — typical permit stack as of 2026-05-02. Rules change frequently. Verify with the issuing jurisdiction before relying on this snapshot.
A5: REFERENCE ONLY — NOT LEGAL ADVICE. STR ordinances change frequently, sometimes mid-year. The permit names, fees, and restrictions below are starting points for your research, not authoritative guidance. Always verify the current rules with the issuing jurisdiction (or your local STR attorney) before applying for, renewing, or relying on a permit. Snapshot date: 2026-05-02.
A8: New York City, NY
B9: Authority | C9: NYC Mayor's Office of Special Enforcement (OSE)
B10: Permit name | C10: Short-Term Rental Registration (Local Law 18)
B11: Typical fees | C11: $145 application fee
B12: Renewal cadence | C12: One-time registration; updates required on changes
B13: Key restriction | C13: Owner-occupancy required (Y) — host must be present during stay; max 2 guests; stays under 30 days only allowed if registered.
B14: Reference URL | C14: https://www.nyc.gov/site/specialenforcement/registration/short-term-rental.page
B15: As-of | C15: 2026-05-02
A16: Verify locally — STR rules in this jurisdiction change and may have updated since the as-of date above.
A18: Los Angeles, CA
B19: Authority | C19: LA Department of City Planning
B20: Permit name | C20: Home-Sharing Registration
B21: Typical fees | C21: $89 annual
B22: Renewal cadence | C22: Annual
B23: Key restriction | C23: Owner-occupancy required (Y) — primary residence only; 120-night cap unless Extended Home-Sharing approved.
B24: Reference URL | C24: https://planning.lacity.gov/development-services/home-sharing
B25: As-of | C25: 2026-05-02
A26: Verify locally — STR rules in this jurisdiction change and may have updated since the as-of date above.
A28: Austin, TX
B29: Authority | C29: City of Austin Development Services Department
B30: Permit name | C30: Short-Term Rental License (Type 1, 2, 3)
B31: Typical fees | C31: $767 initial / $462 renewal
B32: Renewal cadence | C32: Annual
B33: Key restriction | C33: Owner-occupancy required for Type 1 (Y); Type 2 prohibited in residential zones since 2016; Type 3 multifamily.
B34: Reference URL | C34: https://www.austintexas.gov/department/short-term-rentals
B35: As-of | C35: 2026-05-02
A36: Verify locally — STR rules in this jurisdiction change and may have updated since the as-of date above.
A38: Denver, CO
B39: Authority | C39: Denver Department of Excise and Licenses
B40: Permit name | C40: Short-Term Rental Business License
B41: Typical fees | C41: $50 application + $50 license / annual
B42: Renewal cadence | C42: Annual
B43: Key restriction | C43: Owner-occupancy required (Y) — must be primary residence; lodger's tax registration also required.
B44: Reference URL | C44: https://www.denvergov.org/Government/Agencies-Departments-Offices/Business-Licensing/Business-Licenses/Short-Term-Rentals
B45: As-of | C45: 2026-05-02
A46: Verify locally — STR rules in this jurisdiction change and may have updated since the as-of date above.
A48: Nashville (Metro Davidson), TN
B49: Authority | C49: Metro Codes Department
B50: Permit name | C50: Short-Term Rental Property Permit (Type 1 / Type 2)
B51: Typical fees | C51: $313 annual
B52: Renewal cadence | C52: Annual
B53: Key restriction | C53: Type 1 owner-occupied (Y); Type 2 non-owner-occupied capped by zoning + grandfathered in many districts.
B54: Reference URL | C54: https://www.nashville.gov/departments/codes/short-term-rentals
B55: As-of | C55: 2026-05-02
A56: Verify locally — STR rules in this jurisdiction change and may have updated since the as-of date above.
A58: New Orleans, LA
B59: Authority | C59: City of New Orleans Department of Safety and Permits
B60: Permit name | C60: Short-Term Rental Permit (Residential / Commercial)
B61: Typical fees | C61: $500 residential / $500+ commercial annual
B62: Renewal cadence | C62: Annual
B63: Key restriction | C63: Residential STR requires owner-occupancy (Y); homestead exemption required; one permit per lot in most districts.
B64: Reference URL | C64: https://nola.gov/short-term-rentals/
B65: As-of | C65: 2026-05-02
A66: Verify locally — STR rules in this jurisdiction change and may have updated since the as-of date above.
A68: Honolulu, HI
B69: Authority | C69: Honolulu Department of Planning and Permitting
B70: Permit name | C70: Short-Term Rental Registration (Bill 41 / Ord 22-7)
B71: Typical fees | C71: $1,000 registration + annual renewal
B72: Renewal cadence | C72: Annual
B73: Key restriction | C73: Strict — 90-day minimum stay outside resort districts; operating permit limited; non-conforming use grandfathering only.
B74: Reference URL | C74: https://www.honolulu.gov/dpp/short-term-rentals.html
B75: As-of | C75: 2026-05-02
A76: Verify locally — STR rules in this jurisdiction change and may have updated since the as-of date above.
A78: San Francisco, CA
B79: Authority | C79: SF Office of Short-Term Rentals
B80: Permit name | C80: Short-Term Residential Rental Certificate
B81: Typical fees | C81: $1,025 biennial
B82: Renewal cadence | C82: Biennial
B83: Key restriction | C83: Owner-occupancy required (Y) — primary residence 275+ nights/year; 90-night cap on un-hosted stays.
B84: Reference URL | C84: https://sf.gov/topics/short-term-rentals
B85: As-of | C85: 2026-05-02
A86: Verify locally — STR rules in this jurisdiction change and may have updated since the as-of date above.
A88: Miami Beach, FL
B89: Authority | C89: Miami Beach Code Compliance
B90: Permit name | C90: Short-Term Rental Business Tax Receipt
B91: Typical fees | C91: $390 BTR + $1,500 resort tax registration
B92: Renewal cadence | C92: Annual
B93: Key restriction | C93: Owner-occupancy NOT required (N) — but STRs banned in many single-family zones; fines up to $100,000 for unpermitted use.
B94: Reference URL | C94: https://www.miamibeachfl.gov/code-compliance/short-term-rentals/
B95: As-of | C95: 2026-05-02
A96: Verify locally — STR rules in this jurisdiction change and may have updated since the as-of date above.
A98: Portland, OR
B99: Authority | C99: Portland Bureau of Development Services
B100: Permit name | C100: Accessory Short-Term Rental Permit
B101: Typical fees | C101: $67 (Type A) / $4,432 (Type B) initial
B102: Renewal cadence | C102: Biennial (Type A) / Conditional Use (Type B)
B103: Key restriction | C103: Owner-occupancy required for Type A (Y) — owner present 270+ nights/year; Type B requires conditional-use review.
B104: Reference URL | C104: https://www.portland.gov/bds/zoning-land-use/accessory-short-term-rentals
B105: As-of | C105: 2026-05-02
A106: Verify locally — STR rules in this jurisdiction change and may have updated since the as-of date above.
A108: Seattle, WA
B109: Authority | C109: Seattle Department of Finance and Administrative Services
B110: Permit name | C110: Short-Term Rental Operator's License
B111: Typical fees | C111: $75 operator + $14 per unit annual
B112: Renewal cadence | C112: Annual
B113: Key restriction | C113: Two-unit cap per operator (one must be primary residence); city business license also required.
B114: Reference URL | C114: https://www.seattle.gov/business-regulations/short-term-rentals
...

Sheet Filing Log
A2: =HYPERLINK("#'Permit Discovery'!A1", "← BACK") | D2: FILING LOG | J2: =HYPERLINK("#'Settings'!A1", "NEXT →")
A4: Every renewal, amendment, and initial filing — keep the proof. Filing $ YTD on the Start tab pulls from this log.
A6: Date | B6: Property | C6: Permit type | D6: Action | E6: $ Paid | F6: Confirmation # | G6: Certificate? | H6: Certificate path | I6: Notes

Sheet Settings
A2: =HYPERLINK("#'Filing Log'!A1", "← BACK") | D2: SETTINGS
A4: Lists drive the dropdowns on Permits Register, Renewal Calendar, and Filing Log. Edit to match your portfolio.
B5: Properties | C5: Permit types | D5: Cadence | E5: Status | F5: Action (Filing Log)
B6: Smokies Ridge Cabin | C6: STR permit | D6: Annual | E6: Active | F6: Initial filing
B7: Creek Side | C7: Business license | D7: Biennial | E7: Pending | F7: Renewal
B8: Lakehouse A | C8: Sales tax license | D8: Triennial | E8: Renewed | F8: Amendment
B9: Mountain Loft | C9: Lodging tax registration | D9: One-time | E9: EXPIRED | F9: Cancellation
B10: Forest Cabin | C10: Fire inspection | E10: N/A
B11: Lakehouse B | C11: Life safety
B12: Downtown Loft | C12: Building permit
B13: Beach House | C13: Other
B33: Permit Discovery verified: | C33: 46144
B34: Manually update this date when you re-verify the Permit Discovery snapshot. STR ordinances change — re-check once a quarter at minimum.
