Workbook

Sheet Start
A2: The STR Ledger
A4: Cleaning Cost per Turnover
A5: Price the cleaning fee like you mean it.
A7: OPS-004 · v2.2 · DEMO
A10: WHAT THIS DOES
A11: Logs every turnover with hours, supplies, and flat fees so you see the real cost per turnover and per night of stay. The Summary tab rolls cost up by property and by month — feed those numbers into your cleaning-fee pricing each season so you stop subsidizing guests with thin margins.
A18: HOW TO USE
A19: ① Click the navy button below to open the Log — one row per turnover event.
A20: ② Use Hours + Hourly Rate for hourly cleaners, OR Flat Fee for contracted services.
A21: ③ Total $ auto-calculates as (Hours × Rate) + Flat Fee + Supplies.
A22: ④ Enter Nights of stay just ended — gets you $ per night, the number Airbnb pricing cares about.
A23: ⑤ Visit the Summary tab monthly to see per-property and per-month rollups.
A26: =HYPERLINK("#'Log'!A6", "→ ADD A NEW TURNOVER (OPEN LOG)")
A32: TURNOVERS YTD | E32: AVG $/TURNOVER | I32: LAST ENTRY
A33: ='Summary'!B6 | E33: ='Summary'!B8 | I33: =IFERROR(TEXT(MAX('Log'!A6:A305),"yyyy-mm-dd"),"—")
A35: events logged this year | E35: true cost per event | I35: most recent turnover date
A39: =HYPERLINK("#'Summary'!A1", "Summary") | E39: =HYPERLINK("#'Summary'!A1", "📄 Print Packet") | I39: =HYPERLINK("#'Settings'!A1", "Settings")
A42: 📄 TAX TIME: print the Summary tab (File → Print → 'Print Active Sheets'). 📅 YEAR END: copy YTD totals into Settings → Year-end Archive before Jan 1.
A44: 💡 Upgrade to the Full version at thestrledger.com/upgrade — multi-property, depreciation, multi-LLC support.
A47: Questions? hello@thestrledger.com
A48: OPS-004 · v2.2 · Free updates forever

Sheet Log
A2: =HYPERLINK("#'Start'!A1", "← BACK") | D2: CLEANING LOG | J2: =HYPERLINK("#'Summary'!A1", "NEXT →")
A4: One row per turnover — Hours×Rate or Flat Fee, plus supplies
A5: Date | B5: Property | C5: Cleaner | D5: Booking ID | E5: Hours | F5: Hourly Rate | G5: Flat Fee | H5: Supplies $ | I5: Total $ | J5: Nights of stay | K5: $ per night | L5: Notes
A6: 46026 | B6: Smokies Ridge | C6: Jamie M. | D6: ABNB-1041 | E6: 2.5 | F6: 35 | H6: 18.5 | I6: =IF(AND(E6="",F6="",G6="",H6=""),"",IFERROR(E6*F6,0)+IFERROR(G6,0)+IFERROR(H6,0)) | J6: 3 | K6: =IF(OR(J6="",J6=0,I6=""),"",I6/J6) | L6: Standard turn
A7: 46030 | B7: Creek Side | C7: Carla R. | D7: ABNB-1042 | E7: 3 | F7: 35 | H7: 24 | I7: =IF(AND(E7="",F7="",G7="",H7=""),"",IFERROR(E7*F7,0)+IFERROR(G7,0)+IFERROR(H7,0)) | J7: 4 | K7: =IF(OR(J7="",J7=0,I7=""),"",I7/J7) | L7: Hot tub deep clean
A8: 46034 | B8: Smokies Ridge | C8: Jamie M. | D8: VRBO-2210 | E8: 2 | F8: 35 | H8: 12.75 | I8: =IF(AND(E8="",F8="",G8="",H8=""),"",IFERROR(E8*F8,0)+IFERROR(G8,0)+IFERROR(H8,0)) | J8: 2 | K8: =IF(OR(J8="",J8=0,I8=""),"",I8/J8)
A9: 46037 | B9: Lakehouse A | C9: BrightHome Co. | D9: ABNB-1051 | G9: 120 | I9: =IF(AND(E9="",F9="",G9="",H9=""),"",IFERROR(E9*F9,0)+IFERROR(G9,0)+IFERROR(H9,0)) | J9: 5 | K9: =IF(OR(J9="",J9=0,I9=""),"",I9/J9) | L9: Flat-fee contract
A10: 46041 | B10: Creek Side | C10: Carla R. | D10: ABNB-1059 | E10: 3.5 | F10: 35 | H10: 32 | I10: =IF(AND(E10="",F10="",G10="",H10=""),"",IFERROR(E10*F10,0)+IFERROR(G10,0)+IFERROR(H10,0)) | J10: 5 | K10: =IF(OR(J10="",J10=0,I10=""),"",I10/J10) | L10: Pet hair extra
A11: 46044 | B11: Smokies Ridge | C11: Jamie M. | D11: VRBO-2231 | E11: 2.5 | F11: 35 | H11: 15.5 | I11: =IF(AND(E11="",F11="",G11="",H11=""),"",IFERROR(E11*F11,0)+IFERROR(G11,0)+IFERROR(H11,0)) | J11: 3 | K11: =IF(OR(J11="",J11=0,I11=""),"",I11/J11)
A12: 46049 | B12: Lakehouse A | C12: BrightHome Co. | D12: ABNB-1064 | G12: 120 | H12: 9.25 | I12: =IF(AND(E12="",F12="",G12="",H12=""),"",IFERROR(E12*F12,0)+IFERROR(G12,0)+IFERROR(H12,0)) | J12: 4 | K12: =IF(OR(J12="",J12=0,I12=""),"",I12/J12)
A13: 46055 | B13: Creek Side | C13: Pete H. | D13: ABNB-1071 | E13: 2.5 | F13: 40 | H13: 18 | I13: =IF(AND(E13="",F13="",G13="",H13=""),"",IFERROR(E13*F13,0)+IFERROR(G13,0)+IFERROR(H13,0)) | J13: 3 | K13: =IF(OR(J13="",J13=0,I13=""),"",I13/J13) | L13: Carla unavailable
A14: 46058 | B14: Smokies Ridge | C14: Jamie M. | D14: VRBO-2255 | E14: 2 | F14: 35 | H14: 14.25 | I14: =IF(AND(E14="",F14="",G14="",H14=""),"",IFERROR(E14*F14,0)+IFERROR(G14,0)+IFERROR(H14,0)) | J14: 2 | K14: =IF(OR(J14="",J14=0,I14=""),"",I14/J14)
A15: 46062 | B15: Lakehouse A | C15: BrightHome Co. | D15: ABNB-1080 | G15: 130 | I15: =IF(AND(E15="",F15="",G15="",H15=""),"",IFERROR(E15*F15,0)+IFERROR(G15,0)+IFERROR(H15,0)) | J15: 6 | K15: =IF(OR(J15="",J15=0,I15=""),"",I15/J15) | L15: Rate bump
A16: 46066 | B16: Creek Side | C16: Carla R. | D16: ABNB-1085 | E16: 3 | F16: 35 | H16: 22.5 | I16: =IF(AND(E16="",F16="",G16="",H16=""),"",IFERROR(E16*F16,0)+IFERROR(G16,0)+IFERROR(H16,0)) | J16: 4 | K16: =IF(OR(J16="",J16=0,I16=""),"",I16/J16)
A17: 46069 | B17: Smokies Ridge | C17: Jamie M. | D17: ABNB-1089 | E17: 2.5 | F17: 35 | H17: 19.75 | I17: =IF(AND(E17="",F17="",G17="",H17=""),"",IFERROR(E17*F17,0)+IFERROR(G17,0)+IFERROR(H17,0)) | J17: 3 | K17: =IF(OR(J17="",J17=0,I17=""),"",I17/J17) | L17: Valentine's quick turn
A18: 46073 | B18: Lakehouse A | C18: BrightHome Co. | D18: VRBO-2280 | G18: 120 | I18: =IF(AND(E18="",F18="",G18="",H18=""),"",IFERROR(E18*F18,0)+IFERROR(G18,0)+IFERROR(H18,0)) | J18: 4 | K18: =IF(OR(J18="",J18=0,I18=""),"",I18/J18)
A19: 46077 | B19: Creek Side | C19: Carla R. | D19: ABNB-1099 | E19: 3.5 | F19: 35 | H19: 28 | I19: =IF(AND(E19="",F19="",G19="",H19=""),"",IFERROR(E19*F19,0)+IFERROR(G19,0)+IFERROR(H19,0)) | J19: 5 | K19: =IF(OR(J19="",J19=0,I19=""),"",I19/J19) | L19: Stained linens replaced
A20: 46081 | B20: Smokies Ridge | C20: Jamie M. | D20: ABNB-1104 | E20: 2 | F20: 35 | H20: 11.5 | I20: =IF(AND(E20="",F20="",G20="",H20=""),"",IFERROR(E20*F20,0)+IFERROR(G20,0)+IFERROR(H20,0)) | J20: 2 | K20: =IF(OR(J20="",J20=0,I20=""),"",I20/J20)
A21: 46085 | B21: Lakehouse A | C21: BrightHome Co. | D21: ABNB-1110 | G21: 120 | H21: 16 | I21: =IF(AND(E21="",F21="",G21="",H21=""),"",IFERROR(E21*F21,0)+IFERROR(G21,0)+IFERROR(H21,0)) | J21: 5 | K21: =IF(OR(J21="",J21=0,I21=""),"",I21/J21) | L21: Extra supplies bill
A22: 46089 | B22: Creek Side | C22: Pete H. | D22: VRBO-2305 | E22: 2.5 | F22: 40 | H22: 18 | I22: =IF(AND(E22="",F22="",G22="",H22=""),"",IFERROR(E22*F22,0)+IFERROR(G22,0)+IFERROR(H22,0)) | J22: 3 | K22: =IF(OR(J22="",J22=0,I22=""),"",I22/J22)
A23: 46093 | B23: Smokies Ridge | C23: Jamie M. | D23: ABNB-1119 | E23: 2.5 | F23: 35 | H23: 16.5 | I23: =IF(AND(E23="",F23="",G23="",H23=""),"",IFERROR(E23*F23,0)+IFERROR(G23,0)+IFERROR(H23,0)) | J23: 3 | K23: =IF(OR(J23="",J23=0,I23=""),"",I23/J23)
A24: 46098 | B24: Lakehouse A | C24: BrightHome Co. | D24: ABNB-1128 | G24: 130 | I24: =IF(AND(E24="",F24="",G24="",H24=""),"",IFERROR(E24*F24,0)+IFERROR(G24,0)+IFERROR(H24,0)) | J24: 7 | K24: =IF(OR(J24="",J24=0,I24=""),"",I24/J24) | L24: Long stay turn
A25: 46103 | B25: Creek Side | C25: Carla R. | D25: ABNB-1135 | E25: 3 | F25: 35 | H25: 21 | I25: =IF(AND(E25="",F25="",G25="",H25=""),"",IFERROR(E25*F25,0)+IFERROR(G25,0)+IFERROR(H25,0)) | J25: 4 | K25: =IF(OR(J25="",J25=0,I25=""),"",I25/J25)
I26: =IF(AND(E26="",F26="",G26="",H26=""),"",IFERROR(E26*F26,0)+IFERROR(G26,0)+IFERROR(H26,0)) | K26: =IF(OR(J26="",J26=0,I26=""),"",I26/J26)
I27: =IF(AND(E27="",F27="",G27="",H27=""),"",IFERROR(E27*F27,0)+IFERROR(G27,0)+IFERROR(H27,0)) | K27: =IF(OR(J27="",J27=0,I27=""),"",I27/J27)
I28: =IF(AND(E28="",F28="",G28="",H28=""),"",IFERROR(E28*F28,0)+IFERROR(G28,0)+IFERROR(H28,0)) | K28: =IF(OR(J28="",J28=0,I28=""),"",I28/J28)
I29: =IF(AND(E29="",F29="",G29="",H29=""),"",IFERROR(E29*F29,0)+IFERROR(G29,0)+IFERROR(H29,0)) | K29: =IF(OR(J29="",J29=0,I29=""),"",I29/J29)
I30: =IF(AND(E30="",F30="",G30="",H30=""),"",IFERROR(E30*F30,0)+IFERROR(G30,0)+IFERROR(H30,0)) | K30: =IF(OR(J30="",J30=0,I30=""),"",I30/J30)
I31: =IF(AND(E31="",F31="",G31="",H31=""),"",IFERROR(E31*F31,0)+IFERROR(G31,0)+IFERROR(H31,0)) | K31: =IF(OR(J31="",J31=0,I31=""),"",I31/J31)
I32: =IF(AND(E32="",F32="",G32="",H32=""),"",IFERROR(E32*F32,0)+IFERROR(G32,0)+IFERROR(H32,0)) | K32: =IF(OR(J32="",J32=0,I32=""),"",I32/J32)
I33: =IF(AND(E33="",F33="",G33="",H33=""),"",IFERROR(E33*F33,0)+IFERROR(G33,0)+IFERROR(H33,0)) | K33: =IF(OR(J33="",J33=0,I33=""),"",I33/J33)
I34: =IF(AND(E34="",F34="",G34="",H34=""),"",IFERROR(E34*F34,0)+IFERROR(G34,0)+IFERROR(H34,0)) | K34: =IF(OR(J34="",J34=0,I34=""),"",I34/J34)
I35: =IF(AND(E35="",F35="",G35="",H35=""),"",IFERROR(E35*F35,0)+IFERROR(G35,0)+IFERROR(H35,0)) | K35: =IF(OR(J35="",J35=0,I35=""),"",I35/J35)
I36: =IF(AND(E36="",F36="",G36="",H36=""),"",IFERROR(E36*F36,0)+IFERROR(G36,0)+IFERROR(H36,0)) | K36: =IF(OR(J36="",J36=0,I36=""),"",I36/J36)
I37: =IF(AND(E37="",F37="",G37="",H37=""),"",IFERROR(E37*F37,0)+IFERROR(G37,0)+IFERROR(H37,0)) | K37: =IF(OR(J37="",J37=0,I37=""),"",I37/J37)
... I305: =IF(AND(E305="",F305="",G305="",H305=""),"",IFERROR(E305*F305,0)+IFERROR(G305,0)+IFERROR(H305,0)) | K305: =IF(OR(J305="",J305=0,I305=""),"",I305/J305)

Sheet Summary
A2: =HYPERLINK("#'Log'!A1", "← BACK") | D2: SUMMARY · FOR YOUR CPA | J2: =HYPERLINK("#'Settings'!A1", "NEXT →")
A4: 📄 FOR YOUR CPA — print this tab. Per-property and per-month rollups.
A6: YTD Turnovers: | B6: =COUNTIFS('Log'!$A$6:$A$305,">="&DATE(Settings!$B$5,1,1),'Log'!$A$6:$A$305,"<"&DATE(Settings!$B$5+1,1,1))
A7: YTD Total Spent: | B7: =SUMIFS('Log'!$I$6:$I$305,'Log'!$A$6:$A$305,">="&DATE(Settings!$B$5,1,1),'Log'!$A$6:$A$305,"<"&DATE(Settings!$B$5+1,1,1))
A8: Avg $/Turnover: | B8: =IFERROR(B7/B6,0)
A9: Avg $/Night: | B9: =IFERROR(SUMIFS('Log'!$I$6:$I$305,'Log'!$A$6:$A$305,">="&DATE(Settings!$B$5,1,1),'Log'!$A$6:$A$305,"<"&DATE(Settings!$B$5+1,1,1)) / SUMIFS('Log'!$J$6:$J$305,'Log'!$A$6:$A$305,">="&DATE(Settings!$B$5,1,1),'Log'!$A$6:$A$305,"<"&DATE(Settings!$B$5+1,1,1)),0)
A10: Most Expensive Month: | B10: =IFERROR(INDEX(A23:A34,MATCH(MAX(C23:C34),C23:C34,0)),"—")
A12: By Property
A13: Property | B13: Turnovers | C13: Total $ | D13: Avg $/Turn
A14: Smokies Ridge | B14: =COUNTIFS('Log'!$B$6:$B$305,A14,'Log'!$A$6:$A$305,">="&DATE(Settings!$B$5,1,1),'Log'!$A$6:$A$305,"<"&DATE(Settings!$B$5+1,1,1)) | C14: =SUMIFS('Log'!$I$6:$I$305,'Log'!$B$6:$B$305,A14,'Log'!$A$6:$A$305,">="&DATE(Settings!$B$5,1,1),'Log'!$A$6:$A$305,"<"&DATE(Settings!$B$5+1,1,1)) | D14: =IFERROR(C14/B14,0)
A15: Creek Side | B15: =COUNTIFS('Log'!$B$6:$B$305,A15,'Log'!$A$6:$A$305,">="&DATE(Settings!$B$5,1,1),'Log'!$A$6:$A$305,"<"&DATE(Settings!$B$5+1,1,1)) | C15: =SUMIFS('Log'!$I$6:$I$305,'Log'!$B$6:$B$305,A15,'Log'!$A$6:$A$305,">="&DATE(Settings!$B$5,1,1),'Log'!$A$6:$A$305,"<"&DATE(Settings!$B$5+1,1,1)) | D15: =IFERROR(C15/B15,0)
A16: Lakehouse A | B16: =COUNTIFS('Log'!$B$6:$B$305,A16,'Log'!$A$6:$A$305,">="&DATE(Settings!$B$5,1,1),'Log'!$A$6:$A$305,"<"&DATE(Settings!$B$5+1,1,1)) | C16: =SUMIFS('Log'!$I$6:$I$305,'Log'!$B$6:$B$305,A16,'Log'!$A$6:$A$305,">="&DATE(Settings!$B$5,1,1),'Log'!$A$6:$A$305,"<"&DATE(Settings!$B$5+1,1,1)) | D16: =IFERROR(C16/B16,0)
A21: By Month
A22: Month | B22: Turnovers | C22: Total $ | D22: Avg $/Turn
A23: Jan | B23: =COUNTIFS('Log'!$A$6:$A$305,">="&DATE(Settings!$B$5,1,1),'Log'!$A$6:$A$305,"<"&DATE(Settings!$B$5,2,1)) | C23: =SUMIFS('Log'!$I$6:$I$305,'Log'!$A$6:$A$305,">="&DATE(Settings!$B$5,1,1),'Log'!$A$6:$A$305,"<"&DATE(Settings!$B$5,2,1)) | D23: =IFERROR(C23/B23,0)
A24: Feb | B24: =COUNTIFS('Log'!$A$6:$A$305,">="&DATE(Settings!$B$5,2,1),'Log'!$A$6:$A$305,"<"&DATE(Settings!$B$5,3,1)) | C24: =SUMIFS('Log'!$I$6:$I$305,'Log'!$A$6:$A$305,">="&DATE(Settings!$B$5,2,1),'Log'!$A$6:$A$305,"<"&DATE(Settings!$B$5,3,1)) | D24: =IFERROR(C24/B24,0)
A25: Mar | B25: =COUNTIFS('Log'!$A$6:$A$305,">="&DATE(Settings!$B$5,3,1),'Log'!$A$6:$A$305,"<"&DATE(Settings!$B$5,4,1)) | C25: =SUMIFS('Log'!$I$6:$I$305,'Log'!$A$6:$A$305,">="&DATE(Settings!$B$5,3,1),'Log'!$A$6:$A$305,"<"&DATE(Settings!$B$5,4,1)) | D25: =IFERROR(C25/B25,0)
A26: Apr | B26: =COUNTIFS('Log'!$A$6:$A$305,">="&DATE(Settings!$B$5,4,1),'Log'!$A$6:$A$305,"<"&DATE(Settings!$B$5,5,1)) | C26: =SUMIFS('Log'!$I$6:$I$305,'Log'!$A$6:$A$305,">="&DATE(Settings!$B$5,4,1),'Log'!$A$6:$A$305,"<"&DATE(Settings!$B$5,5,1)) | D26: =IFERROR(C26/B26,0)
A27: May | B27: =COUNTIFS('Log'!$A$6:$A$305,">="&DATE(Settings!$B$5,5,1),'Log'!$A$6:$A$305,"<"&DATE(Settings!$B$5,6,1)) | C27: =SUMIFS('Log'!$I$6:$I$305,'Log'!$A$6:$A$305,">="&DATE(Settings!$B$5,5,1),'Log'!$A$6:$A$305,"<"&DATE(Settings!$B$5,6,1)) | D27: =IFERROR(C27/B27,0)
A28: Jun | B28: =COUNTIFS('Log'!$A$6:$A$305,">="&DATE(Settings!$B$5,6,1),'Log'!$A$6:$A$305,"<"&DATE(Settings!$B$5,7,1)) | C28: =SUMIFS('Log'!$I$6:$I$305,'Log'!$A$6:$A$305,">="&DATE(Settings!$B$5,6,1),'Log'!$A$6:$A$305,"<"&DATE(Settings!$B$5,7,1)) | D28: =IFERROR(C28/B28,0)
A29: Jul | B29: =COUNTIFS('Log'!$A$6:$A$305,">="&DATE(Settings!$B$5,7,1),'Log'!$A$6:$A$305,"<"&DATE(Settings!$B$5,8,1)) | C29: =SUMIFS('Log'!$I$6:$I$305,'Log'!$A$6:$A$305,">="&DATE(Settings!$B$5,7,1),'Log'!$A$6:$A$305,"<"&DATE(Settings!$B$5,8,1)) | D29: =IFERROR(C29/B29,0)
A30: Aug | B30: =COUNTIFS('Log'!$A$6:$A$305,">="&DATE(Settings!$B$5,8,1),'Log'!$A$6:$A$305,"<"&DATE(Settings!$B$5,9,1)) | C30: =SUMIFS('Log'!$I$6:$I$305,'Log'!$A$6:$A$305,">="&DATE(Settings!$B$5,8,1),'Log'!$A$6:$A$305,"<"&DATE(Settings!$B$5,9,1)) | D30: =IFERROR(C30/B30,0)
A31: Sep | B31: =COUNTIFS('Log'!$A$6:$A$305,">="&DATE(Settings!$B$5,9,1),'Log'!$A$6:$A$305,"<"&DATE(Settings!$B$5,10,1)) | C31: =SUMIFS('Log'!$I$6:$I$305,'Log'!$A$6:$A$305,">="&DATE(Settings!$B$5,9,1),'Log'!$A$6:$A$305,"<"&DATE(Settings!$B$5,10,1)) | D31: =IFERROR(C31/B31,0)
A32: Oct | B32: =COUNTIFS('Log'!$A$6:$A$305,">="&DATE(Settings!$B$5,10,1),'Log'!$A$6:$A$305,"<"&DATE(Settings!$B$5,11,1)) | C32: =SUMIFS('Log'!$I$6:$I$305,'Log'!$A$6:$A$305,">="&DATE(Settings!$B$5,10,1),'Log'!$A$6:$A$305,"<"&DATE(Settings!$B$5,11,1)) | D32: =IFERROR(C32/B32,0)
A33: Nov | B33: =COUNTIFS('Log'!$A$6:$A$305,">="&DATE(Settings!$B$5,11,1),'Log'!$A$6:$A$305,"<"&DATE(Settings!$B$5,12,1)) | C33: =SUMIFS('Log'!$I$6:$I$305,'Log'!$A$6:$A$305,">="&DATE(Settings!$B$5,11,1),'Log'!$A$6:$A$305,"<"&DATE(Settings!$B$5,12,1)) | D33: =IFERROR(C33/B33,0)
A34: Dec | B34: =COUNTIFS('Log'!$A$6:$A$305,">="&DATE(Settings!$B$5,12,1),'Log'!$A$6:$A$305,"<"&DATE(Settings!$B$5+1,1,1)) | C34: =SUMIFS('Log'!$I$6:$I$305,'Log'!$A$6:$A$305,">="&DATE(Settings!$B$5,12,1),'Log'!$A$6:$A$305,"<"&DATE(Settings!$B$5+1,1,1)) | D34: =IFERROR(C34/B34,0)

Sheet Settings
A2: =HYPERLINK("#'Summary'!A1", "← BACK") | D2: SETTINGS
A4: Active tax year · default rate · property/cleaner rosters · year-end archive
A5: Active tax year: | B5: 2026
A6: Drives all date-filtered SUMIFS on the Summary tab. Bump this each January so historical years stay archived but separate.
A7: Default hourly rate: | B7: 35
A8: Property roster (up to 10):
B9: Smokies Ridge
B10: Creek Side
B11: Lakehouse A
A19: Cleaner roster (up to 10):
B20: Jamie M.
B21: Carla R.
B22: Pete H.
B23: BrightHome Co.
A38: Year-end Archive
A39: Each January, copy YTD totals into the row for the closing year, then clear the Log for the new year.
A40: Year | B40: Turnovers | C40: Total $ | D40: Avg $/Turn | E40: Avg $/Night
A41: 2024
A42: 2025
A43: 2026
A44: 2027
A45: 2028
A46: 2029
A47: 2030
