Workbook

Sheet Start
A2: The STR Ledger
A4: Cleaner CRM + Payroll
A5: Your cleaning team — paid right, rated honestly, 1099-ready.
A7: PAM-002 · v2.3 · DEMO
A10: WHAT THIS DOES
A11: Once you cross 5+ properties, your cleaning team becomes a small business of its own. This workbook tracks every cleaner (CRM), logs every turnover (hours, flat fee, bonus, inspection rating), runs payroll in one click, and rolls totals into a 1099-NEC year-end summary that drops straight into TAX-003. Stop paying late, stop rehiring drama, and walk into January with clean books.
A18: ACTIVE CLEANERS | D18: TURNOVERS YTD | G18: $ PAID YTD | J18: TOP PERFORMER
A19: =COUNTIF(Cleaners!M6:M55,"Y") | D19: =SUMPRODUCT((YEAR('Turnover Assignment'!A6:A1005)=Settings!$B$5)*('Turnover Assignment'!A6:A1005<>"")) | G19: =SUMPRODUCT((YEAR('Turnover Assignment'!A6:A1005)=Settings!$B$5)*'Turnover Assignment'!K6:K1005) | J19: =IFERROR(INDEX(Performance!A6:A55,MATCH(MAX(Performance!C6:C55),Performance!C6:C55,0)),"—")
A21: on roster | D21: in active year | G21: all cleaner pay | J21: by avg rating
A25: =HYPERLINK("#'Cleaners'!A6", "→ ADD A CLEANER (OPEN CLEANERS CRM)")
A30: =HYPERLINK("#'Turnover Assignment'!A1", "Turnover Assignment") | D30: =HYPERLINK("#'Payroll Run'!A1", "Payroll Run") | G30: =HYPERLINK("#'Performance'!A1", "Performance") | J30: =HYPERLINK("#'1099-NEC Year-End'!A1", "1099-NEC Year-End")
A33: HOW TO USE
A34: ① Cleaners tab: enter every team member — pay rate, W-9 status, certifications, service area.
A35: ② Turnover Assignment: log every cleaning AS IT HAPPENS — hours, flat fee, bonus, rating.
A36: ③ Payroll Run: set the period start/end → totals roll up per cleaner. Print and pay.
A37: ④ Performance: review monthly — flag top performers, decide who to coach or cut.
A38: ⑤ 1099-NEC Year-End: in January, copy totals into TAX-003 1099-NEC tracker.
A41: ⚠ Pay any cleaner $600+ in a calendar year and you owe them a 1099-NEC by January 31 (IRS Pub 1220, $60–$660 penalty per missed form). Year-End tab tracks who crosses the line.
A43: 💡 Upgrade to the Full version at thestrledger.com/upgrade — multi-property, depreciation, multi-LLC support.
A46: Questions? hello@thestrledger.com
A47: PAM-002 · v2.3 · Free updates forever

Sheet Cleaners
A2: =HYPERLINK("#'Start'!A1", "← BACK") | D2: CLEANERS CRM | J2: =HYPERLINK("#'Turnover Assignment'!A1", "NEXT →")
A4: Add every cleaner — pay rate, W-9 status, certifications, service area
A5: Cleaner ID | B5: Name | C5: Phone | D5: Email | E5: Address | F5: EIN/SSN last4 | G5: W-9? | H5: Pay rate type | I5: Hourly $ | J5: Per-turnover $ | K5: Service area | L5: Certifications | M5: Active? | N5: Avg rating | O5: Notes
A6: C-001 | B6: Sarah Mitchell | C6: (865) 555-0145 | D6: sarah@smokiesclean.com | E6: 147 Pine St, Gatlinburg, TN 37738 | F6: 4421 | G6: Yes | H6: Per-turnover | I6: 0 | J6: 120 | K6: Gatlinburg, Pigeon Forge | L6: Insured, bonded, COVID-19 | M6: Y | N6: =IFERROR(VLOOKUP(B6,Performance!$A$6:$D$55,4,FALSE),"") | O6: Top performer — keep on rotation
A7: C-002 | B7: Maria Gonzalez | C7: (865) 555-0192 | D7: maria@cleanmtn.com | E7: 82 Ridge Ln, Pigeon Forge, TN 37863 | F7: 8810 | G7: Yes | H7: Hourly | I7: 28 | J7: 0 | K7: Pigeon Forge, Sevierville | L7: Insured | M7: Y | N7: =IFERROR(VLOOKUP(B7,Performance!$A$6:$D$55,4,FALSE),"") | O7: Reliable, slow on linens
A8: C-003 | B8: Jenny Park | C8: (865) 555-0211 | D8: jenny@parkclean.com | E8: 9 Oak Dr, Sevierville, TN 37862 | F8: 5573 | G8: Yes | H8: Hybrid | I8: 22 | J8: 90 | K8: Sevierville, Knoxville | L8: Insured, bonded | M8: Y | N8: =IFERROR(VLOOKUP(B8,Performance!$A$6:$D$55,4,FALSE),"") | O8: Backup for Sarah
A9: C-004 | B9: Tom Bradley | C9: (865) 555-0166 | D9: tom@bradleyturn.com | E9: 55 Lake Rd, Gatlinburg, TN 37738 | F9: 2298 | G9: No | H9: Per-turnover | I9: 0 | J9: 110 | K9: Gatlinburg | L9: Bonded | M9: Y | N9: =IFERROR(VLOOKUP(B9,Performance!$A$6:$D$55,4,FALSE),"") | O9: Need W-9 — request before next pay
A10: C-005 | B10: Lisa Chen | C10: (865) 555-0177 | D10: lisa@chenclean.net | E10: 21 Cherry St, Knoxville, TN 37902 | F10: 6634 | G10: Yes | H10: Per-turnover | I10: 0 | J10: 115 | K10: Knoxville | L10: Insured, bonded, eco | M10: Y | N10: =IFERROR(VLOOKUP(B10,Performance!$A$6:$D$55,4,FALSE),"")
A11: C-006 | B11: Backup Helper | C11: (865) 555-0188 | D11: — | E11: Various | F11: — | G11: No | H11: Hourly | I11: 20 | J11: 0 | K11: Local only | L11: — | M11: N | N11: =IFERROR(VLOOKUP(B11,Performance!$A$6:$D$55,4,FALSE),"") | O11: Inactive — used Q1 only
N12: =IFERROR(VLOOKUP(B12,Performance!$A$6:$D$55,4,FALSE),"")
N13: =IFERROR(VLOOKUP(B13,Performance!$A$6:$D$55,4,FALSE),"")
N14: =IFERROR(VLOOKUP(B14,Performance!$A$6:$D$55,4,FALSE),"")
N15: =IFERROR(VLOOKUP(B15,Performance!$A$6:$D$55,4,FALSE),"")
N16: =IFERROR(VLOOKUP(B16,Performance!$A$6:$D$55,4,FALSE),"")
N17: =IFERROR(VLOOKUP(B17,Performance!$A$6:$D$55,4,FALSE),"")
N18: =IFERROR(VLOOKUP(B18,Performance!$A$6:$D$55,4,FALSE),"")
N19: =IFERROR(VLOOKUP(B19,Performance!$A$6:$D$55,4,FALSE),"")
N20: =IFERROR(VLOOKUP(B20,Performance!$A$6:$D$55,4,FALSE),"")
N21: =IFERROR(VLOOKUP(B21,Performance!$A$6:$D$55,4,FALSE),"")
N22: =IFERROR(VLOOKUP(B22,Performance!$A$6:$D$55,4,FALSE),"")
N23: =IFERROR(VLOOKUP(B23,Performance!$A$6:$D$55,4,FALSE),"")
... N35: =IFERROR(VLOOKUP(B35,Performance!$A$6:$D$55,4,FALSE),"")

Sheet Turnover Assignment
A2: =HYPERLINK("#'Cleaners'!A1", "← BACK") | D2: TURNOVER ASSIGNMENT | J2: =HYPERLINK("#'Payroll Run'!A1", "NEXT →")
A4: Log every turnover AS IT HAPPENS — hours, flat fee, bonus, inspection rating
A5: Date | B5: Property | C5: Cleaner | D5: Hours | E5: Per-turn $ | F5: Bonus $ | G5: Hourly $ (lkup) | H5: Status | I5: Inspection rating | J5: Notes | K5: Total payment
A6: 46023 | B6: Creek Side | C6: Sarah Mitchell | D6: 3 | E6: 120 | F6: 25 | G6: =IFERROR(VLOOKUP(C6,Cleaners!$B$6:$I$35,8,FALSE),0) | H6: Inspected | I6: 4.6 | K6: =IF(C6="","",IFERROR(D6,0)*G6+IFERROR(E6,0)+IFERROR(F6,0))
A7: 46024 | B7: Smokies Ridge | C7: Sarah Mitchell | D7: 3.25 | E7: 120 | G7: =IFERROR(VLOOKUP(C7,Cleaners!$B$6:$I$35,8,FALSE),0) | H7: Inspected | I7: 4.7 | K7: =IF(C7="","",IFERROR(D7,0)*G7+IFERROR(E7,0)+IFERROR(F7,0))
A8: 46025 | B8: Lakehouse A | C8: Sarah Mitchell | D8: 3.5 | E8: 120 | G8: =IFERROR(VLOOKUP(C8,Cleaners!$B$6:$I$35,8,FALSE),0) | H8: Inspected | I8: 4.8 | K8: =IF(C8="","",IFERROR(D8,0)*G8+IFERROR(E8,0)+IFERROR(F8,0))
A9: 46026 | B9: Creek Side | C9: Sarah Mitchell | D9: 3.75 | E9: 120 | G9: =IFERROR(VLOOKUP(C9,Cleaners!$B$6:$I$35,8,FALSE),0) | H9: Inspected | I9: 4.9 | K9: =IF(C9="","",IFERROR(D9,0)*G9+IFERROR(E9,0)+IFERROR(F9,0))
A10: 46027 | B10: Smokies Ridge | C10: Sarah Mitchell | D10: 4 | E10: 120 | G10: =IFERROR(VLOOKUP(C10,Cleaners!$B$6:$I$35,8,FALSE),0) | H10: Inspected | I10: 5 | K10: =IF(C10="","",IFERROR(D10,0)*G10+IFERROR(E10,0)+IFERROR(F10,0))
A11: 46028 | B11: Lakehouse A | C11: Sarah Mitchell | D11: 3 | E11: 120 | G11: =IFERROR(VLOOKUP(C11,Cleaners!$B$6:$I$35,8,FALSE),0) | H11: Inspected | I11: 5 | K11: =IF(C11="","",IFERROR(D11,0)*G11+IFERROR(E11,0)+IFERROR(F11,0))
A12: 46029 | B12: Creek Side | C12: Sarah Mitchell | D12: 3.25 | E12: 120 | G12: =IFERROR(VLOOKUP(C12,Cleaners!$B$6:$I$35,8,FALSE),0) | H12: Inspected | I12: 5 | K12: =IF(C12="","",IFERROR(D12,0)*G12+IFERROR(E12,0)+IFERROR(F12,0))
A13: 46030 | B13: Smokies Ridge | C13: Sarah Mitchell | D13: 3.5 | E13: 120 | G13: =IFERROR(VLOOKUP(C13,Cleaners!$B$6:$I$35,8,FALSE),0) | H13: Inspected | I13: 4.6 | K13: =IF(C13="","",IFERROR(D13,0)*G13+IFERROR(E13,0)+IFERROR(F13,0))
A14: 46031 | B14: Lakehouse A | C14: Sarah Mitchell | D14: 3.75 | E14: 120 | G14: =IFERROR(VLOOKUP(C14,Cleaners!$B$6:$I$35,8,FALSE),0) | H14: Inspected | I14: 4.7 | K14: =IF(C14="","",IFERROR(D14,0)*G14+IFERROR(E14,0)+IFERROR(F14,0))
A15: 46032 | B15: Creek Side | C15: Sarah Mitchell | D15: 4 | E15: 120 | G15: =IFERROR(VLOOKUP(C15,Cleaners!$B$6:$I$35,8,FALSE),0) | H15: Inspected | I15: 4.8 | K15: =IF(C15="","",IFERROR(D15,0)*G15+IFERROR(E15,0)+IFERROR(F15,0))
A16: 46033 | B16: Smokies Ridge | C16: Sarah Mitchell | D16: 3 | E16: 120 | G16: =IFERROR(VLOOKUP(C16,Cleaners!$B$6:$I$35,8,FALSE),0) | H16: Inspected | I16: 4.9 | K16: =IF(C16="","",IFERROR(D16,0)*G16+IFERROR(E16,0)+IFERROR(F16,0))
A17: 46034 | B17: Lakehouse A | C17: Sarah Mitchell | D17: 3.25 | E17: 120 | G17: =IFERROR(VLOOKUP(C17,Cleaners!$B$6:$I$35,8,FALSE),0) | H17: Inspected | I17: 5 | K17: =IF(C17="","",IFERROR(D17,0)*G17+IFERROR(E17,0)+IFERROR(F17,0))
A18: 46035 | B18: Creek Side | C18: Sarah Mitchell | D18: 3.5 | E18: 120 | F18: 25 | G18: =IFERROR(VLOOKUP(C18,Cleaners!$B$6:$I$35,8,FALSE),0) | H18: Inspected | I18: 5 | K18: =IF(C18="","",IFERROR(D18,0)*G18+IFERROR(E18,0)+IFERROR(F18,0))
A19: 46036 | B19: Smokies Ridge | C19: Sarah Mitchell | D19: 3.75 | E19: 120 | G19: =IFERROR(VLOOKUP(C19,Cleaners!$B$6:$I$35,8,FALSE),0) | H19: Inspected | I19: 5 | K19: =IF(C19="","",IFERROR(D19,0)*G19+IFERROR(E19,0)+IFERROR(F19,0))
A20: 46037 | B20: Lakehouse A | C20: Sarah Mitchell | D20: 4 | E20: 120 | G20: =IFERROR(VLOOKUP(C20,Cleaners!$B$6:$I$35,8,FALSE),0) | H20: Inspected | I20: 4.6 | K20: =IF(C20="","",IFERROR(D20,0)*G20+IFERROR(E20,0)+IFERROR(F20,0))
A21: 46038 | B21: Creek Side | C21: Sarah Mitchell | D21: 3 | E21: 120 | G21: =IFERROR(VLOOKUP(C21,Cleaners!$B$6:$I$35,8,FALSE),0) | H21: Inspected | I21: 4.7 | K21: =IF(C21="","",IFERROR(D21,0)*G21+IFERROR(E21,0)+IFERROR(F21,0))
A22: 46039 | B22: Smokies Ridge | C22: Sarah Mitchell | D22: 3.25 | E22: 120 | G22: =IFERROR(VLOOKUP(C22,Cleaners!$B$6:$I$35,8,FALSE),0) | H22: Inspected | I22: 4.8 | K22: =IF(C22="","",IFERROR(D22,0)*G22+IFERROR(E22,0)+IFERROR(F22,0))
A23: 46040 | B23: Lakehouse A | C23: Sarah Mitchell | D23: 3.5 | E23: 120 | G23: =IFERROR(VLOOKUP(C23,Cleaners!$B$6:$I$35,8,FALSE),0) | H23: Inspected | I23: 4.9 | K23: =IF(C23="","",IFERROR(D23,0)*G23+IFERROR(E23,0)+IFERROR(F23,0))
A24: 46041 | B24: Creek Side | C24: Sarah Mitchell | D24: 3.75 | E24: 120 | G24: =IFERROR(VLOOKUP(C24,Cleaners!$B$6:$I$35,8,FALSE),0) | H24: Inspected | I24: 5 | K24: =IF(C24="","",IFERROR(D24,0)*G24+IFERROR(E24,0)+IFERROR(F24,0))
A25: 46042 | B25: Smokies Ridge | C25: Sarah Mitchell | D25: 4 | E25: 120 | G25: =IFERROR(VLOOKUP(C25,Cleaners!$B$6:$I$35,8,FALSE),0) | H25: Inspected | I25: 5 | K25: =IF(C25="","",IFERROR(D25,0)*G25+IFERROR(E25,0)+IFERROR(F25,0))
A26: 46043 | B26: Lakehouse A | C26: Sarah Mitchell | D26: 3 | E26: 120 | G26: =IFERROR(VLOOKUP(C26,Cleaners!$B$6:$I$35,8,FALSE),0) | H26: Inspected | I26: 5 | K26: =IF(C26="","",IFERROR(D26,0)*G26+IFERROR(E26,0)+IFERROR(F26,0))
A27: 46044 | B27: Creek Side | C27: Sarah Mitchell | D27: 3.25 | E27: 120 | G27: =IFERROR(VLOOKUP(C27,Cleaners!$B$6:$I$35,8,FALSE),0) | H27: Inspected | I27: 4.6 | K27: =IF(C27="","",IFERROR(D27,0)*G27+IFERROR(E27,0)+IFERROR(F27,0))
A28: 46045 | B28: Smokies Ridge | C28: Sarah Mitchell | D28: 3.5 | E28: 120 | G28: =IFERROR(VLOOKUP(C28,Cleaners!$B$6:$I$35,8,FALSE),0) | H28: Inspected | I28: 4.7 | K28: =IF(C28="","",IFERROR(D28,0)*G28+IFERROR(E28,0)+IFERROR(F28,0))
A29: 46046 | B29: Lakehouse A | C29: Sarah Mitchell | D29: 3.75 | E29: 120 | G29: =IFERROR(VLOOKUP(C29,Cleaners!$B$6:$I$35,8,FALSE),0) | H29: Inspected | I29: 4.8 | K29: =IF(C29="","",IFERROR(D29,0)*G29+IFERROR(E29,0)+IFERROR(F29,0))
A30: 46047 | B30: Creek Side | C30: Sarah Mitchell | D30: 4 | E30: 120 | F30: 25 | G30: =IFERROR(VLOOKUP(C30,Cleaners!$B$6:$I$35,8,FALSE),0) | H30: Inspected | I30: 4.9 | K30: =IF(C30="","",IFERROR(D30,0)*G30+IFERROR(E30,0)+IFERROR(F30,0))
A31: 46048 | B31: Smokies Ridge | C31: Sarah Mitchell | D31: 3 | E31: 120 | G31: =IFERROR(VLOOKUP(C31,Cleaners!$B$6:$I$35,8,FALSE),0) | H31: Inspected | I31: 5 | K31: =IF(C31="","",IFERROR(D31,0)*G31+IFERROR(E31,0)+IFERROR(F31,0))
A32: 46049 | B32: Lakehouse A | C32: Sarah Mitchell | D32: 3.25 | E32: 120 | G32: =IFERROR(VLOOKUP(C32,Cleaners!$B$6:$I$35,8,FALSE),0) | H32: Inspected | I32: 5 | K32: =IF(C32="","",IFERROR(D32,0)*G32+IFERROR(E32,0)+IFERROR(F32,0))
A33: 46050 | B33: Creek Side | C33: Sarah Mitchell | D33: 3.5 | E33: 120 | G33: =IFERROR(VLOOKUP(C33,Cleaners!$B$6:$I$35,8,FALSE),0) | H33: Inspected | I33: 5 | K33: =IF(C33="","",IFERROR(D33,0)*G33+IFERROR(E33,0)+IFERROR(F33,0))
A34: 46051 | B34: Smokies Ridge | C34: Sarah Mitchell | D34: 3.75 | E34: 120 | G34: =IFERROR(VLOOKUP(C34,Cleaners!$B$6:$I$35,8,FALSE),0) | H34: Inspected | I34: 4.6 | K34: =IF(C34="","",IFERROR(D34,0)*G34+IFERROR(E34,0)+IFERROR(F34,0))
A35: 46052 | B35: Lakehouse A | C35: Sarah Mitchell | D35: 4 | E35: 120 | G35: =IFERROR(VLOOKUP(C35,Cleaners!$B$6:$I$35,8,FALSE),0) | H35: Inspected | I35: 4.7 | K35: =IF(C35="","",IFERROR(D35,0)*G35+IFERROR(E35,0)+IFERROR(F35,0))
A36: 46053 | B36: Creek Side | C36: Sarah Mitchell | D36: 3 | E36: 120 | G36: =IFERROR(VLOOKUP(C36,Cleaners!$B$6:$I$35,8,FALSE),0) | H36: Inspected | I36: 4.8 | K36: =IF(C36="","",IFERROR(D36,0)*G36+IFERROR(E36,0)+IFERROR(F36,0))
A37: 46054 | B37: Smokies Ridge | C37: Sarah Mitchell | D37: 3.25 | E37: 120 | G37: =IFERROR(VLOOKUP(C37,Cleaners!$B$6:$I$35,8,FALSE),0) | H37: Inspected | I37: 4.9 | K37: =IF(C37="","",IFERROR(D37,0)*G37+IFERROR(E37,0)+IFERROR(F37,0))
A38: 46055 | B38: Lakehouse A | C38: Sarah Mitchell | D38: 3.5 | E38: 120 | G38: =IFERROR(VLOOKUP(C38,Cleaners!$B$6:$I$35,8,FALSE),0) | H38: Inspected | I38: 5 | K38: =IF(C38="","",IFERROR(D38,0)*G38+IFERROR(E38,0)+IFERROR(F38,0))
A39: 46056 | B39: Creek Side | C39: Sarah Mitchell | D39: 3.75 | E39: 120 | G39: =IFERROR(VLOOKUP(C39,Cleaners!$B$6:$I$35,8,FALSE),0) | H39: Inspected | I39: 5 | K39: =IF(C39="","",IFERROR(D39,0)*G39+IFERROR(E39,0)+IFERROR(F39,0))
A40: 46057 | B40: Smokies Ridge | C40: Sarah Mitchell | D40: 4 | E40: 120 | G40: =IFERROR(VLOOKUP(C40,Cleaners!$B$6:$I$35,8,FALSE),0) | H40: Inspected | I40: 5 | K40: =IF(C40="","",IFERROR(D40,0)*G40+IFERROR(E40,0)+IFERROR(F40,0))
A41: 46058 | B41: Lakehouse A | C41: Sarah Mitchell | D41: 3 | E41: 120 | G41: =IFERROR(VLOOKUP(C41,Cleaners!$B$6:$I$35,8,FALSE),0) | H41: Inspected | I41: 4.6 | K41: =IF(C41="","",IFERROR(D41,0)*G41+IFERROR(E41,0)+IFERROR(F41,0))
A42: 46059 | B42: Creek Side | C42: Sarah Mitchell | D42: 3.25 | E42: 120 | F42: 25 | G42: =IFERROR(VLOOKUP(C42,Cleaners!$B$6:$I$35,8,FALSE),0) | H42: Inspected | I42: 4.7 | K42: =IF(C42="","",IFERROR(D42,0)*G42+IFERROR(E42,0)+IFERROR(F42,0))
A43: 46060 | B43: Smokies Ridge | C43: Sarah Mitchell | D43: 3.5 | E43: 120 | G43: =IFERROR(VLOOKUP(C43,Cleaners!$B$6:$I$35,8,FALSE),0) | H43: Inspected | I43: 4.8 | K43: =IF(C43="","",IFERROR(D43,0)*G43+IFERROR(E43,0)+IFERROR(F43,0))
A44: 46061 | B44: Lakehouse A | C44: Sarah Mitchell | D44: 3.75 | E44: 120 | G44: =IFERROR(VLOOKUP(C44,Cleaners!$B$6:$I$35,8,FALSE),0) | H44: Inspected | I44: 4.9 | K44: =IF(C44="","",IFERROR(D44,0)*G44+IFERROR(E44,0)+IFERROR(F44,0))
A45: 46062 | B45: Creek Side | C45: Sarah Mitchell | D45: 4 | E45: 120 | G45: =IFERROR(VLOOKUP(C45,Cleaners!$B$6:$I$35,8,FALSE),0) | H45: Inspected | I45: 5 | K45: =IF(C45="","",IFERROR(D45,0)*G45+IFERROR(E45,0)+IFERROR(F45,0))
A46: 46063 | B46: Smokies Ridge | C46: Sarah Mitchell | D46: 3 | E46: 120 | G46: =IFERROR(VLOOKUP(C46,Cleaners!$B$6:$I$35,8,FALSE),0) | H46: Inspected | I46: 5 | K46: =IF(C46="","",IFERROR(D46,0)*G46+IFERROR(E46,0)+IFERROR(F46,0))
A47: 46064 | B47: Lakehouse A | C47: Sarah Mitchell | D47: 3.25 | E47: 120 | G47: =IFERROR(VLOOKUP(C47,Cleaners!$B$6:$I$35,8,FALSE),0) | H47: Inspected | I47: 5 | K47: =IF(C47="","",IFERROR(D47,0)*G47+IFERROR(E47,0)+IFERROR(F47,0))
A48: 46065 | B48: Creek Side | C48: Sarah Mitchell | D48: 3.5 | E48: 120 | G48: =IFERROR(VLOOKUP(C48,Cleaners!$B$6:$I$35,8,FALSE),0) | H48: Inspected | I48: 4.6 | K48: =IF(C48="","",IFERROR(D48,0)*G48+IFERROR(E48,0)+IFERROR(F48,0))
A49: 46066 | B49: Smokies Ridge | C49: Sarah Mitchell | D49: 3.75 | E49: 120 | G49: =IFERROR(VLOOKUP(C49,Cleaners!$B$6:$I$35,8,FALSE),0) | H49: Inspected | I49: 4.7 | K49: =IF(C49="","",IFERROR(D49,0)*G49+IFERROR(E49,0)+IFERROR(F49,0))
A50: 46067 | B50: Lakehouse A | C50: Sarah Mitchell | D50: 4 | E50: 120 | G50: =IFERROR(VLOOKUP(C50,Cleaners!$B$6:$I$35,8,FALSE),0) | H50: Inspected | I50: 4.8 | K50: =IF(C50="","",IFERROR(D50,0)*G50+IFERROR(E50,0)+IFERROR(F50,0))
A51: 46068 | B51: Creek Side | C51: Sarah Mitchell | D51: 3 | E51: 120 | G51: =IFERROR(VLOOKUP(C51,Cleaners!$B$6:$I$35,8,FALSE),0) | H51: Inspected | I51: 4.9 | K51: =IF(C51="","",IFERROR(D51,0)*G51+IFERROR(E51,0)+IFERROR(F51,0))
A52: 46069 | B52: Smokies Ridge | C52: Sarah Mitchell | D52: 3.25 | E52: 120 | G52: =IFERROR(VLOOKUP(C52,Cleaners!$B$6:$I$35,8,FALSE),0) | H52: Inspected | I52: 5 | K52: =IF(C52="","",IFERROR(D52,0)*G52+IFERROR(E52,0)+IFERROR(F52,0))
A53: 46070 | B53: Lakehouse A | C53: Sarah Mitchell | D53: 3.5 | E53: 120 | G53: =IFERROR(VLOOKUP(C53,Cleaners!$B$6:$I$35,8,FALSE),0) | H53: Inspected | I53: 5 | K53: =IF(C53="","",IFERROR(D53,0)*G53+IFERROR(E53,0)+IFERROR(F53,0))
A54: 46071 | B54: Creek Side | C54: Sarah Mitchell | D54: 3.75 | E54: 120 | F54: 25 | G54: =IFERROR(VLOOKUP(C54,Cleaners!$B$6:$I$35,8,FALSE),0) | H54: Inspected | I54: 5 | K54: =IF(C54="","",IFERROR(D54,0)*G54+IFERROR(E54,0)+IFERROR(F54,0))
A55: 46072 | B55: Smokies Ridge | C55: Sarah Mitchell | D55: 4 | E55: 120 | G55: =IFERROR(VLOOKUP(C55,Cleaners!$B$6:$I$35,8,FALSE),0) | H55: Inspected | I55: 4.6 | K55: =IF(C55="","",IFERROR(D55,0)*G55+IFERROR(E55,0)+IFERROR(F55,0))
A56: 46073 | B56: Lakehouse A | C56: Sarah Mitchell | D56: 3 | E56: 120 | G56: =IFERROR(VLOOKUP(C56,Cleaners!$B$6:$I$35,8,FALSE),0) | H56: Inspected | I56: 4.7 | K56: =IF(C56="","",IFERROR(D56,0)*G56+IFERROR(E56,0)+IFERROR(F56,0))
A57: 46074 | B57: Creek Side | C57: Sarah Mitchell | D57: 3.25 | E57: 120 | G57: =IFERROR(VLOOKUP(C57,Cleaners!$B$6:$I$35,8,FALSE),0) | H57: Inspected | I57: 4.8 | K57: =IF(C57="","",IFERROR(D57,0)*G57+IFERROR(E57,0)+IFERROR(F57,0))
A58: 46075 | B58: Smokies Ridge | C58: Sarah Mitchell | D58: 3.5 | E58: 120 | G58: =IFERROR(VLOOKUP(C58,Cleaners!$B$6:$I$35,8,FALSE),0) | H58: Inspected | I58: 4.9 | K58: =IF(C58="","",IFERROR(D58,0)*G58+IFERROR(E58,0)+IFERROR(F58,0))
A59: 46076 | B59: Lakehouse A | C59: Sarah Mitchell | D59: 3.75 | E59: 120 | G59: =IFERROR(VLOOKUP(C59,Cleaners!$B$6:$I$35,8,FALSE),0) | H59: Inspected | I59: 5 | K59: =IF(C59="","",IFERROR(D59,0)*G59+IFERROR(E59,0)+IFERROR(F59,0))
A60: 46077 | B60: Creek Side | C60: Sarah Mitchell | D60: 4 | E60: 120 | G60: =IFERROR(VLOOKUP(C60,Cleaners!$B$6:$I$35,8,FALSE),0) | H60: Inspected | I60: 5 | K60: =IF(C60="","",IFERROR(D60,0)*G60+IFERROR(E60,0)+IFERROR(F60,0))
A61: 46078 | B61: Smokies Ridge | C61: Sarah Mitchell | D61: 3 | E61: 120 | G61: =IFERROR(VLOOKUP(C61,Cleaners!$B$6:$I$35,8,FALSE),0) | H61: Inspected | I61: 5 | K61: =IF(C61="","",IFERROR(D61,0)*G61+IFERROR(E61,0)+IFERROR(F61,0))
A62: 46079 | B62: Lakehouse A | C62: Sarah Mitchell | D62: 3.25 | E62: 120 | G62: =IFERROR(VLOOKUP(C62,Cleaners!$B$6:$I$35,8,FALSE),0) | H62: Inspected | I62: 4.6 | K62: =IF(C62="","",IFERROR(D62,0)*G62+IFERROR(E62,0)+IFERROR(F62,0))
A63: 46080 | B63: Creek Side | C63: Sarah Mitchell | D63: 3.5 | E63: 120 | G63: =IFERROR(VLOOKUP(C63,Cleaners!$B$6:$I$35,8,FALSE),0) | H63: Inspected | I63: 4.7 | K63: =IF(C63="","",IFERROR(D63,0)*G63+IFERROR(E63,0)+IFERROR(F63,0))
A64: 46081 | B64: Smokies Ridge | C64: Sarah Mitchell | D64: 3.75 | E64: 120 | G64: =IFERROR(VLOOKUP(C64,Cleaners!$B$6:$I$35,8,FALSE),0) | H64: Inspected | I64: 4.8 | K64: =IF(C64="","",IFERROR(D64,0)*G64+IFERROR(E64,0)+IFERROR(F64,0))
A65: 46082 | B65: Lakehouse A | C65: Sarah Mitchell | D65: 4 | E65: 120 | G65: =IFERROR(VLOOKUP(C65,Cleaners!$B$6:$I$35,8,FALSE),0) | H65: Inspected | I65: 4.9 | K65: =IF(C65="","",IFERROR(D65,0)*G65+IFERROR(E65,0)+IFERROR(F65,0))
A66: 46083 | B66: Creek Side | C66: Sarah Mitchell | D66: 3 | E66: 120 | F66: 25 | G66: =IFERROR(VLOOKUP(C66,Cleaners!$B$6:$I$35,8,FALSE),0) | H66: Inspected | I66: 5 | K66: =IF(C66="","",IFERROR(D66,0)*G66+IFERROR(E66,0)+IFERROR(F66,0))
A67: 46084 | B67: Smokies Ridge | C67: Sarah Mitchell | D67: 3.25 | E67: 120 | G67: =IFERROR(VLOOKUP(C67,Cleaners!$B$6:$I$35,8,FALSE),0) | H67: Inspected | I67: 5 | K67: =IF(C67="","",IFERROR(D67,0)*G67+IFERROR(E67,0)+IFERROR(F67,0))
A68: 46085 | B68: Lakehouse A | C68: Sarah Mitchell | D68: 3.5 | E68: 120 | G68: =IFERROR(VLOOKUP(C68,Cleaners!$B$6:$I$35,8,FALSE),0) | H68: Inspected | I68: 5 | K68: =IF(C68="","",IFERROR(D68,0)*G68+IFERROR(E68,0)+IFERROR(F68,0))
A69: 46086 | B69: Creek Side | C69: Sarah Mitchell | D69: 3.75 | E69: 120 | G69: =IFERROR(VLOOKUP(C69,Cleaners!$B$6:$I$35,8,FALSE),0) | H69: Done | I69: 4.6 | K69: =IF(C69="","",IFERROR(D69,0)*G69+IFERROR(E69,0)+IFERROR(F69,0))
A70: 46087 | B70: Smokies Ridge | C70: Sarah Mitchell | D70: 4 | E70: 120 | G70: =IFERROR(VLOOKUP(C70,Cleaners!$B$6:$I$35,8,FALSE),0) | H70: Done | I70: 4.7 | K70: =IF(C70="","",IFERROR(D70,0)*G70+IFERROR(E70,0)+IFERROR(F70,0))
A71: 46088 | B71: Smokies Ridge | C71: Maria Gonzalez | D71: 4 | G71: =IFERROR(VLOOKUP(C71,Cleaners!$B$6:$I$35,8,FALSE),0) | H71: Inspected | I71: 4.3 | K71: =IF(C71="","",IFERROR(D71,0)*G71+IFERROR(E71,0)+IFERROR(F71,0))
A72: 46089 | B72: Lakehouse A | C72: Maria Gonzalez | D72: 4.25 | G72: =IFERROR(VLOOKUP(C72,Cleaners!$B$6:$I$35,8,FALSE),0) | H72: Inspected | I72: 4.4 | K72: =IF(C72="","",IFERROR(D72,0)*G72+IFERROR(E72,0)+IFERROR(F72,0))
A73: 46090 | B73: Creek Side | C73: Maria Gonzalez | D73: 4.5 | G73: =IFERROR(VLOOKUP(C73,Cleaners!$B$6:$I$35,8,FALSE),0) | H73: Inspected | I73: 4.5 | K73: =IF(C73="","",IFERROR(D73,0)*G73+IFERROR(E73,0)+IFERROR(F73,0))
A74: 46091 | B74: Smokies Ridge | C74: Maria Gonzalez | D74: 4.75 | G74: =IFERROR(VLOOKUP(C74,Cleaners!$B$6:$I$35,8,FALSE),0) | H74: Inspected | I74: 4.6 | K74: =IF(C74="","",IFERROR(D74,0)*G74+IFERROR(E74,0)+IFERROR(F74,0))
A75: 46092 | B75: Lakehouse A | C75: Maria Gonzalez | D75: 5 | G75: =IFERROR(VLOOKUP(C75,Cleaners!$B$6:$I$35,8,FALSE),0) | H75: Inspected | I75: 4.7 | K75: =IF(C75="","",IFERROR(D75,0)*G75+IFERROR(E75,0)+IFERROR(F75,0))
A76: 46093 | B76: Creek Side | C76: Maria Gonzalez | D76: 4 | G76: =IFERROR(VLOOKUP(C76,Cleaners!$B$6:$I$35,8,FALSE),0) | H76: Inspected | I76: 4.8 | K76: =IF(C76="","",IFERROR(D76,0)*G76+IFERROR(E76,0)+IFERROR(F76,0))
A77: 46094 | B77: Smokies Ridge | C77: Maria Gonzalez | D77: 4.25 | G77: =IFERROR(VLOOKUP(C77,Cleaners!$B$6:$I$35,8,FALSE),0) | H77: Inspected | I77: 4.9 | K77: =IF(C77="","",IFERROR(D77,0)*G77+IFERROR(E77,0)+IFERROR(F77,0))
A78: 46095 | B78: Lakehouse A | C78: Maria Gonzalez | D78: 4.5 | G78: =IFERROR(VLOOKUP(C78,Cleaners!$B$6:$I$35,8,FALSE),0) | H78: Inspected | I78: 4.3 | K78: =IF(C78="","",IFERROR(D78,0)*G78+IFERROR(E78,0)+IFERROR(F78,0))
A79: 46096 | B79: Creek Side | C79: Maria Gonzalez | D79: 4.75 | G79: =IFERROR(VLOOKUP(C79,Cleaners!$B$6:$I$35,8,FALSE),0) | H79: Inspected | I79: 4.4 | K79: =IF(C79="","",IFERROR(D79,0)*G79+IFERROR(E79,0)+IFERROR(F79,0))
A80: 46097 | B80: Smokies Ridge | C80: Maria Gonzalez | D80: 5 | G80: =IFERROR(VLOOKUP(C80,Cleaners!$B$6:$I$35,8,FALSE),0) | H80: Inspected | I80: 4.5 | K80: =IF(C80="","",IFERROR(D80,0)*G80+IFERROR(E80,0)+IFERROR(F80,0))
A81: 46098 | B81: Lakehouse A | C81: Maria Gonzalez | D81: 4 | G81: =IFERROR(VLOOKUP(C81,Cleaners!$B$6:$I$35,8,FALSE),0) | H81: Inspected | I81: 4.6 | K81: =IF(C81="","",IFERROR(D81,0)*G81+IFERROR(E81,0)+IFERROR(F81,0))
A82: 46099 | B82: Creek Side | C82: Maria Gonzalez | D82: 4.25 | G82: =IFERROR(VLOOKUP(C82,Cleaners!$B$6:$I$35,8,FALSE),0) | H82: Inspected | I82: 4.7 | K82: =IF(C82="","",IFERROR(D82,0)*G82+IFERROR(E82,0)+IFERROR(F82,0))
... A120: 46048 | B120: Lakehouse A | C120: Maria Gonzalez | D120: 5 | G120: =IFERROR(VLOOKUP(C120,Cleaners!$B$6:$I$35,8,FALSE),0) | H120: Done | I120: 4.3 | K120: =IF(C120="","",IFERROR(D120,0)*G120+IFERROR(E120,0)+IFERROR(F120,0))
A121: 46049 | B121: Lakehouse A | C121: Jenny Park | D121: 3.5 | E121: 90 | G121: =IFERROR(VLOOKUP(C121,Cleaners!$B$6:$I$35,8,FALSE),0) | H121: Inspected | I121: 4.4 | K121: =IF(C121="","",IFERROR(D121,0)*G121+IFERROR(E121,0)+IFERROR(F121,0))
A122: 46050 | B122: Creek Side | C122: Jenny Park | D122: 3.75 | E122: 90 | G122: =IFERROR(VLOOKUP(C122,Cleaners!$B$6:$I$35,8,FALSE),0) | H122: Inspected | I122: 4.5 | K122: =IF(C122="","",IFERROR(D122,0)*G122+IFERROR(E122,0)+IFERROR(F122,0))
A123: 46051 | B123: Smokies Ridge | C123: Jenny Park | D123: 4 | E123: 90 | G123: =IFERROR(VLOOKUP(C123,Cleaners!$B$6:$I$35,8,FALSE),0) | H123: Inspected | I123: 4.6 | K123: =IF(C123="","",IFERROR(D123,0)*G123+IFERROR(E123,0)+IFERROR(F123,0))
A124: 46052 | B124: Lakehouse A | C124: Jenny Park | D124: 4.25 | E124: 90 | G124: =IFERROR(VLOOKUP(C124,Cleaners!$B$6:$I$35,8,FALSE),0) | H124: Inspected | I124: 4.7 | K124: =IF(C124="","",IFERROR(D124,0)*G124+IFERROR(E124,0)+IFERROR(F124,0))
A125: 46053 | B125: Creek Side | C125: Jenny Park | D125: 4.5 | E125: 90 | G125: =IFERROR(VLOOKUP(C125,Cleaners!$B$6:$I$35,8,FALSE),0) | H125: Inspected | I125: 4.8 | K125: =IF(C125="","",IFERROR(D125,0)*G125+IFERROR(E125,0)+IFERROR(F125,0))
A126: 46054 | B126: Smokies Ridge | C126: Jenny Park | D126: 3.5 | E126: 90 | G126: =IFERROR(VLOOKUP(C126,Cleaners!$B$6:$I$35,8,FALSE),0) | H126: Inspected | I126: 4.9 | K126: =IF(C126="","",IFERROR(D126,0)*G126+IFERROR(E126,0)+IFERROR(F126,0))
A127: 46055 | B127: Lakehouse A | C127: Jenny Park | D127: 3.75 | E127: 90 | G127: =IFERROR(VLOOKUP(C127,Cleaners!$B$6:$I$35,8,FALSE),0) | H127: Inspected | I127: 5 | K127: =IF(C127="","",IFERROR(D127,0)*G127+IFERROR(E127,0)+IFERROR(F127,0))
A128: 46056 | B128: Creek Side | C128: Jenny Park | D128: 4 | E128: 90 | G128: =IFERROR(VLOOKUP(C128,Cleaners!$B$6:$I$35,8,FALSE),0) | H128: Inspected | I128: 4.4 | K128: =IF(C128="","",IFERROR(D128,0)*G128+IFERROR(E128,0)+IFERROR(F128,0))
A129: 46057 | B129: Smokies Ridge | C129: Jenny Park | D129: 4.25 | E129: 90 | G129: =IFERROR(VLOOKUP(C129,Cleaners!$B$6:$I$35,8,FALSE),0) | H129: Inspected | I129: 4.5 | K129: =IF(C129="","",IFERROR(D129,0)*G129+IFERROR(E129,0)+IFERROR(F129,0))
A130: 46058 | B130: Lakehouse A | C130: Jenny Park | D130: 4.5 | E130: 90 | G130: =IFERROR(VLOOKUP(C130,Cleaners!$B$6:$I$35,8,FALSE),0) | H130: Inspected | I130: 4.6 | K130: =IF(C130="","",IFERROR(D130,0)*G130+IFERROR(E130,0)+IFERROR(F130,0))
A131: 46059 | B131: Creek Side | C131: Jenny Park | D131: 3.5 | E131: 90 | G131: =IFERROR(VLOOKUP(C131,Cleaners!$B$6:$I$35,8,FALSE),0) | H131: Inspected | I131: 4.7 | K131: =IF(C131="","",IFERROR(D131,0)*G131+IFERROR(E131,0)+IFERROR(F131,0))
A132: 46060 | B132: Smokies Ridge | C132: Jenny Park | D132: 3.75 | E132: 90 | G132: =IFERROR(VLOOKUP(C132,Cleaners!$B$6:$I$35,8,FALSE),0) | H132: Inspected | I132: 4.8 | K132: =IF(C132="","",IFERROR(D132,0)*G132+IFERROR(E132,0)+IFERROR(F132,0))
... A240: 46079 | B240: Lakehouse A | C240: Lisa Chen | D240: 4.5 | E240: 115 | G240: =IFERROR(VLOOKUP(C240,Cleaners!$B$6:$I$35,8,FALSE),0) | H240: Done | I240: 4.8 | K240: =IF(C240="","",IFERROR(D240,0)*G240+IFERROR(E240,0)+IFERROR(F240,0))
A241: 46080 | B241: Lakehouse A | C241: Backup Helper | D241: 4.5 | G241: =IFERROR(VLOOKUP(C241,Cleaners!$B$6:$I$35,8,FALSE),0) | H241: Inspected | I241: 3.7 | K241: =IF(C241="","",IFERROR(D241,0)*G241+IFERROR(E241,0)+IFERROR(F241,0))
A242: 46081 | B242: Creek Side | C242: Backup Helper | D242: 4.75 | G242: =IFERROR(VLOOKUP(C242,Cleaners!$B$6:$I$35,8,FALSE),0) | H242: Inspected | I242: 3.8 | K242: =IF(C242="","",IFERROR(D242,0)*G242+IFERROR(E242,0)+IFERROR(F242,0))
A243: 46082 | B243: Smokies Ridge | C243: Backup Helper | D243: 5 | G243: =IFERROR(VLOOKUP(C243,Cleaners!$B$6:$I$35,8,FALSE),0) | H243: Inspected | I243: 3.9 | K243: =IF(C243="","",IFERROR(D243,0)*G243+IFERROR(E243,0)+IFERROR(F243,0))
A244: 46083 | B244: Lakehouse A | C244: Backup Helper | D244: 5.25 | G244: =IFERROR(VLOOKUP(C244,Cleaners!$B$6:$I$35,8,FALSE),0) | H244: Done | I244: 4 | K244: =IF(C244="","",IFERROR(D244,0)*G244+IFERROR(E244,0)+IFERROR(F244,0))
A245: 46084 | B245: Creek Side | C245: Backup Helper | D245: 5.5 | G245: =IFERROR(VLOOKUP(C245,Cleaners!$B$6:$I$35,8,FALSE),0) | H245: Done | I245: 4.1 | K245: =IF(C245="","",IFERROR(D245,0)*G245+IFERROR(E245,0)+IFERROR(F245,0))
G246: =IFERROR(VLOOKUP(C246,Cleaners!$B$6:$I$35,8,FALSE),0) | K246: =IF(C246="","",IFERROR(D246,0)*G246+IFERROR(E246,0)+IFERROR(F246,0))
...

Sheet Payroll Run
A2: =HYPERLINK("#'Turnover Assignment'!A1", "← BACK") | D2: PAYROLL RUN | J2: =HYPERLINK("#'Performance'!A1", "NEXT →")
A4: Set period dates → totals roll up per cleaner. Print this tab to pay.
A5: Period start: | B5: 46023
A6: Period end: | B6: 46036
A8: Cleaner | B8: Turnovers | C8: Hours | D8: Hourly $ | E8: Per-turn $ | F8: Bonuses | G8: Gross pay
A9: =IF(Cleaners!B6="","",Cleaners!B6) | B9: =IF(A9="","",COUNTIFS('Turnover Assignment'!$C$6:$C$1005,A9,'Turnover Assignment'!$A$6:$A$1005,">="&$B$5,'Turnover Assignment'!$A$6:$A$1005,"<="&$B$6)) | C9: =IF(A9="","",SUMIFS('Turnover Assignment'!$D$6:$D$1005,'Turnover Assignment'!$C$6:$C$1005,A9,'Turnover Assignment'!$A$6:$A$1005,">="&$B$5,'Turnover Assignment'!$A$6:$A$1005,"<="&$B$6)) | D9: =IF(A9="","",C9*IFERROR(VLOOKUP(A9,Cleaners!$B$6:$I$35,8,FALSE),0)) | E9: =IF(A9="","",SUMIFS('Turnover Assignment'!$E$6:$E$1005,'Turnover Assignment'!$C$6:$C$1005,A9,'Turnover Assignment'!$A$6:$A$1005,">="&$B$5,'Turnover Assignment'!$A$6:$A$1005,"<="&$B$6)) | F9: =IF(A9="","",SUMIFS('Turnover Assignment'!$F$6:$F$1005,'Turnover Assignment'!$C$6:$C$1005,A9,'Turnover Assignment'!$A$6:$A$1005,">="&$B$5,'Turnover Assignment'!$A$6:$A$1005,"<="&$B$6)) | G9: =IF(A9="","",D9+E9+F9)
A10: =IF(Cleaners!B7="","",Cleaners!B7) | B10: =IF(A10="","",COUNTIFS('Turnover Assignment'!$C$6:$C$1005,A10,'Turnover Assignment'!$A$6:$A$1005,">="&$B$5,'Turnover Assignment'!$A$6:$A$1005,"<="&$B$6)) | C10: =IF(A10="","",SUMIFS('Turnover Assignment'!$D$6:$D$1005,'Turnover Assignment'!$C$6:$C$1005,A10,'Turnover Assignment'!$A$6:$A$1005,">="&$B$5,'Turnover Assignment'!$A$6:$A$1005,"<="&$B$6)) | D10: =IF(A10="","",C10*IFERROR(VLOOKUP(A10,Cleaners!$B$6:$I$35,8,FALSE),0)) | E10: =IF(A10="","",SUMIFS('Turnover Assignment'!$E$6:$E$1005,'Turnover Assignment'!$C$6:$C$1005,A10,'Turnover Assignment'!$A$6:$A$1005,">="&$B$5,'Turnover Assignment'!$A$6:$A$1005,"<="&$B$6)) | F10: =IF(A10="","",SUMIFS('Turnover Assignment'!$F$6:$F$1005,'Turnover Assignment'!$C$6:$C$1005,A10,'Turnover Assignment'!$A$6:$A$1005,">="&$B$5,'Turnover Assignment'!$A$6:$A$1005,"<="&$B$6)) | G10: =IF(A10="","",D10+E10+F10)
A11: =IF(Cleaners!B8="","",Cleaners!B8) | B11: =IF(A11="","",COUNTIFS('Turnover Assignment'!$C$6:$C$1005,A11,'Turnover Assignment'!$A$6:$A$1005,">="&$B$5,'Turnover Assignment'!$A$6:$A$1005,"<="&$B$6)) | C11: =IF(A11="","",SUMIFS('Turnover Assignment'!$D$6:$D$1005,'Turnover Assignment'!$C$6:$C$1005,A11,'Turnover Assignment'!$A$6:$A$1005,">="&$B$5,'Turnover Assignment'!$A$6:$A$1005,"<="&$B$6)) | D11: =IF(A11="","",C11*IFERROR(VLOOKUP(A11,Cleaners!$B$6:$I$35,8,FALSE),0)) | E11: =IF(A11="","",SUMIFS('Turnover Assignment'!$E$6:$E$1005,'Turnover Assignment'!$C$6:$C$1005,A11,'Turnover Assignment'!$A$6:$A$1005,">="&$B$5,'Turnover Assignment'!$A$6:$A$1005,"<="&$B$6)) | F11: =IF(A11="","",SUMIFS('Turnover Assignment'!$F$6:$F$1005,'Turnover Assignment'!$C$6:$C$1005,A11,'Turnover Assignment'!$A$6:$A$1005,">="&$B$5,'Turnover Assignment'!$A$6:$A$1005,"<="&$B$6)) | G11: =IF(A11="","",D11+E11+F11)
A12: =IF(Cleaners!B9="","",Cleaners!B9) | B12: =IF(A12="","",COUNTIFS('Turnover Assignment'!$C$6:$C$1005,A12,'Turnover Assignment'!$A$6:$A$1005,">="&$B$5,'Turnover Assignment'!$A$6:$A$1005,"<="&$B$6)) | C12: =IF(A12="","",SUMIFS('Turnover Assignment'!$D$6:$D$1005,'Turnover Assignment'!$C$6:$C$1005,A12,'Turnover Assignment'!$A$6:$A$1005,">="&$B$5,'Turnover Assignment'!$A$6:$A$1005,"<="&$B$6)) | D12: =IF(A12="","",C12*IFERROR(VLOOKUP(A12,Cleaners!$B$6:$I$35,8,FALSE),0)) | E12: =IF(A12="","",SUMIFS('Turnover Assignment'!$E$6:$E$1005,'Turnover Assignment'!$C$6:$C$1005,A12,'Turnover Assignment'!$A$6:$A$1005,">="&$B$5,'Turnover Assignment'!$A$6:$A$1005,"<="&$B$6)) | F12: =IF(A12="","",SUMIFS('Turnover Assignment'!$F$6:$F$1005,'Turnover Assignment'!$C$6:$C$1005,A12,'Turnover Assignment'!$A$6:$A$1005,">="&$B$5,'Turnover Assignment'!$A$6:$A$1005,"<="&$B$6)) | G12: =IF(A12="","",D12+E12+F12)
A13: =IF(Cleaners!B10="","",Cleaners!B10) | B13: =IF(A13="","",COUNTIFS('Turnover Assignment'!$C$6:$C$1005,A13,'Turnover Assignment'!$A$6:$A$1005,">="&$B$5,'Turnover Assignment'!$A$6:$A$1005,"<="&$B$6)) | C13: =IF(A13="","",SUMIFS('Turnover Assignment'!$D$6:$D$1005,'Turnover Assignment'!$C$6:$C$1005,A13,'Turnover Assignment'!$A$6:$A$1005,">="&$B$5,'Turnover Assignment'!$A$6:$A$1005,"<="&$B$6)) | D13: =IF(A13="","",C13*IFERROR(VLOOKUP(A13,Cleaners!$B$6:$I$35,8,FALSE),0)) | E13: =IF(A13="","",SUMIFS('Turnover Assignment'!$E$6:$E$1005,'Turnover Assignment'!$C$6:$C$1005,A13,'Turnover Assignment'!$A$6:$A$1005,">="&$B$5,'Turnover Assignment'!$A$6:$A$1005,"<="&$B$6)) | F13: =IF(A13="","",SUMIFS('Turnover Assignment'!$F$6:$F$1005,'Turnover Assignment'!$C$6:$C$1005,A13,'Turnover Assignment'!$A$6:$A$1005,">="&$B$5,'Turnover Assignment'!$A$6:$A$1005,"<="&$B$6)) | G13: =IF(A13="","",D13+E13+F13)
A14: =IF(Cleaners!B11="","",Cleaners!B11) | B14: =IF(A14="","",COUNTIFS('Turnover Assignment'!$C$6:$C$1005,A14,'Turnover Assignment'!$A$6:$A$1005,">="&$B$5,'Turnover Assignment'!$A$6:$A$1005,"<="&$B$6)) | C14: =IF(A14="","",SUMIFS('Turnover Assignment'!$D$6:$D$1005,'Turnover Assignment'!$C$6:$C$1005,A14,'Turnover Assignment'!$A$6:$A$1005,">="&$B$5,'Turnover Assignment'!$A$6:$A$1005,"<="&$B$6)) | D14: =IF(A14="","",C14*IFERROR(VLOOKUP(A14,Cleaners!$B$6:$I$35,8,FALSE),0)) | E14: =IF(A14="","",SUMIFS('Turnover Assignment'!$E$6:$E$1005,'Turnover Assignment'!$C$6:$C$1005,A14,'Turnover Assignment'!$A$6:$A$1005,">="&$B$5,'Turnover Assignment'!$A$6:$A$1005,"<="&$B$6)) | F14: =IF(A14="","",SUMIFS('Turnover Assignment'!$F$6:$F$1005,'Turnover Assignment'!$C$6:$C$1005,A14,'Turnover Assignment'!$A$6:$A$1005,">="&$B$5,'Turnover Assignment'!$A$6:$A$1005,"<="&$B$6)) | G14: =IF(A14="","",D14+E14+F14)
A15: =IF(Cleaners!B12="","",Cleaners!B12) | B15: =IF(A15="","",COUNTIFS('Turnover Assignment'!$C$6:$C$1005,A15,'Turnover Assignment'!$A$6:$A$1005,">="&$B$5,'Turnover Assignment'!$A$6:$A$1005,"<="&$B$6)) | C15: =IF(A15="","",SUMIFS('Turnover Assignment'!$D$6:$D$1005,'Turnover Assignment'!$C$6:$C$1005,A15,'Turnover Assignment'!$A$6:$A$1005,">="&$B$5,'Turnover Assignment'!$A$6:$A$1005,"<="&$B$6)) | D15: =IF(A15="","",C15*IFERROR(VLOOKUP(A15,Cleaners!$B$6:$I$35,8,FALSE),0)) | E15: =IF(A15="","",SUMIFS('Turnover Assignment'!$E$6:$E$1005,'Turnover Assignment'!$C$6:$C$1005,A15,'Turnover Assignment'!$A$6:$A$1005,">="&$B$5,'Turnover Assignment'!$A$6:$A$1005,"<="&$B$6)) | F15: =IF(A15="","",SUMIFS('Turnover Assignment'!$F$6:$F$1005,'Turnover Assignment'!$C$6:$C$1005,A15,'Turnover Assignment'!$A$6:$A$1005,">="&$B$5,'Turnover Assignment'!$A$6:$A$1005,"<="&$B$6)) | G15: =IF(A15="","",D15+E15+F15)
A16: =IF(Cleaners!B13="","",Cleaners!B13) | B16: =IF(A16="","",COUNTIFS('Turnover Assignment'!$C$6:$C$1005,A16,'Turnover Assignment'!$A$6:$A$1005,">="&$B$5,'Turnover Assignment'!$A$6:$A$1005,"<="&$B$6)) | C16: =IF(A16="","",SUMIFS('Turnover Assignment'!$D$6:$D$1005,'Turnover Assignment'!$C$6:$C$1005,A16,'Turnover Assignment'!$A$6:$A$1005,">="&$B$5,'Turnover Assignment'!$A$6:$A$1005,"<="&$B$6)) | D16: =IF(A16="","",C16*IFERROR(VLOOKUP(A16,Cleaners!$B$6:$I$35,8,FALSE),0)) | E16: =IF(A16="","",SUMIFS('Turnover Assignment'!$E$6:$E$1005,'Turnover Assignment'!$C$6:$C$1005,A16,'Turnover Assignment'!$A$6:$A$1005,">="&$B$5,'Turnover Assignment'!$A$6:$A$1005,"<="&$B$6)) | F16: =IF(A16="","",SUMIFS('Turnover Assignment'!$F$6:$F$1005,'Turnover Assignment'!$C$6:$C$1005,A16,'Turnover Assignment'!$A$6:$A$1005,">="&$B$5,'Turnover Assignment'!$A$6:$A$1005,"<="&$B$6)) | G16: =IF(A16="","",D16+E16+F16)
A17: =IF(Cleaners!B14="","",Cleaners!B14) | B17: =IF(A17="","",COUNTIFS('Turnover Assignment'!$C$6:$C$1005,A17,'Turnover Assignment'!$A$6:$A$1005,">="&$B$5,'Turnover Assignment'!$A$6:$A$1005,"<="&$B$6)) | C17: =IF(A17="","",SUMIFS('Turnover Assignment'!$D$6:$D$1005,'Turnover Assignment'!$C$6:$C$1005,A17,'Turnover Assignment'!$A$6:$A$1005,">="&$B$5,'Turnover Assignment'!$A$6:$A$1005,"<="&$B$6)) | D17: =IF(A17="","",C17*IFERROR(VLOOKUP(A17,Cleaners!$B$6:$I$35,8,FALSE),0)) | E17: =IF(A17="","",SUMIFS('Turnover Assignment'!$E$6:$E$1005,'Turnover Assignment'!$C$6:$C$1005,A17,'Turnover Assignment'!$A$6:$A$1005,">="&$B$5,'Turnover Assignment'!$A$6:$A$1005,"<="&$B$6)) | F17: =IF(A17="","",SUMIFS('Turnover Assignment'!$F$6:$F$1005,'Turnover Assignment'!$C$6:$C$1005,A17,'Turnover Assignment'!$A$6:$A$1005,">="&$B$5,'Turnover Assignment'!$A$6:$A$1005,"<="&$B$6)) | G17: =IF(A17="","",D17+E17+F17)
A18: =IF(Cleaners!B15="","",Cleaners!B15) | B18: =IF(A18="","",COUNTIFS('Turnover Assignment'!$C$6:$C$1005,A18,'Turnover Assignment'!$A$6:$A$1005,">="&$B$5,'Turnover Assignment'!$A$6:$A$1005,"<="&$B$6)) | C18: =IF(A18="","",SUMIFS('Turnover Assignment'!$D$6:$D$1005,'Turnover Assignment'!$C$6:$C$1005,A18,'Turnover Assignment'!$A$6:$A$1005,">="&$B$5,'Turnover Assignment'!$A$6:$A$1005,"<="&$B$6)) | D18: =IF(A18="","",C18*IFERROR(VLOOKUP(A18,Cleaners!$B$6:$I$35,8,FALSE),0)) | E18: =IF(A18="","",SUMIFS('Turnover Assignment'!$E$6:$E$1005,'Turnover Assignment'!$C$6:$C$1005,A18,'Turnover Assignment'!$A$6:$A$1005,">="&$B$5,'Turnover Assignment'!$A$6:$A$1005,"<="&$B$6)) | F18: =IF(A18="","",SUMIFS('Turnover Assignment'!$F$6:$F$1005,'Turnover Assignment'!$C$6:$C$1005,A18,'Turnover Assignment'!$A$6:$A$1005,">="&$B$5,'Turnover Assignment'!$A$6:$A$1005,"<="&$B$6)) | G18: =IF(A18="","",D18+E18+F18)
A19: =IF(Cleaners!B16="","",Cleaners!B16) | B19: =IF(A19="","",COUNTIFS('Turnover Assignment'!$C$6:$C$1005,A19,'Turnover Assignment'!$A$6:$A$1005,">="&$B$5,'Turnover Assignment'!$A$6:$A$1005,"<="&$B$6)) | C19: =IF(A19="","",SUMIFS('Turnover Assignment'!$D$6:$D$1005,'Turnover Assignment'!$C$6:$C$1005,A19,'Turnover Assignment'!$A$6:$A$1005,">="&$B$5,'Turnover Assignment'!$A$6:$A$1005,"<="&$B$6)) | D19: =IF(A19="","",C19*IFERROR(VLOOKUP(A19,Cleaners!$B$6:$I$35,8,FALSE),0)) | E19: =IF(A19="","",SUMIFS('Turnover Assignment'!$E$6:$E$1005,'Turnover Assignment'!$C$6:$C$1005,A19,'Turnover Assignment'!$A$6:$A$1005,">="&$B$5,'Turnover Assignment'!$A$6:$A$1005,"<="&$B$6)) | F19: =IF(A19="","",SUMIFS('Turnover Assignment'!$F$6:$F$1005,'Turnover Assignment'!$C$6:$C$1005,A19,'Turnover Assignment'!$A$6:$A$1005,">="&$B$5,'Turnover Assignment'!$A$6:$A$1005,"<="&$B$6)) | G19: =IF(A19="","",D19+E19+F19)
A20: =IF(Cleaners!B17="","",Cleaners!B17) | B20: =IF(A20="","",COUNTIFS('Turnover Assignment'!$C$6:$C$1005,A20,'Turnover Assignment'!$A$6:$A$1005,">="&$B$5,'Turnover Assignment'!$A$6:$A$1005,"<="&$B$6)) | C20: =IF(A20="","",SUMIFS('Turnover Assignment'!$D$6:$D$1005,'Turnover Assignment'!$C$6:$C$1005,A20,'Turnover Assignment'!$A$6:$A$1005,">="&$B$5,'Turnover Assignment'!$A$6:$A$1005,"<="&$B$6)) | D20: =IF(A20="","",C20*IFERROR(VLOOKUP(A20,Cleaners!$B$6:$I$35,8,FALSE),0)) | E20: =IF(A20="","",SUMIFS('Turnover Assignment'!$E$6:$E$1005,'Turnover Assignment'!$C$6:$C$1005,A20,'Turnover Assignment'!$A$6:$A$1005,">="&$B$5,'Turnover Assignment'!$A$6:$A$1005,"<="&$B$6)) | F20: =IF(A20="","",SUMIFS('Turnover Assignment'!$F$6:$F$1005,'Turnover Assignment'!$C$6:$C$1005,A20,'Turnover Assignment'!$A$6:$A$1005,">="&$B$5,'Turnover Assignment'!$A$6:$A$1005,"<="&$B$6)) | G20: =IF(A20="","",D20+E20+F20)
... A38: =IF(Cleaners!B35="","",Cleaners!B35) | B38: =IF(A38="","",COUNTIFS('Turnover Assignment'!$C$6:$C$1005,A38,'Turnover Assignment'!$A$6:$A$1005,">="&$B$5,'Turnover Assignment'!$A$6:$A$1005,"<="&$B$6)) | C38: =IF(A38="","",SUMIFS('Turnover Assignment'!$D$6:$D$1005,'Turnover Assignment'!$C$6:$C$1005,A38,'Turnover Assignment'!$A$6:$A$1005,">="&$B$5,'Turnover Assignment'!$A$6:$A$1005,"<="&$B$6)) | D38: =IF(A38="","",C38*IFERROR(VLOOKUP(A38,Cleaners!$B$6:$I$35,8,FALSE),0)) | E38: =IF(A38="","",SUMIFS('Turnover Assignment'!$E$6:$E$1005,'Turnover Assignment'!$C$6:$C$1005,A38,'Turnover Assignment'!$A$6:$A$1005,">="&$B$5,'Turnover Assignment'!$A$6:$A$1005,"<="&$B$6)) | F38: =IF(A38="","",SUMIFS('Turnover Assignment'!$F$6:$F$1005,'Turnover Assignment'!$C$6:$C$1005,A38,'Turnover Assignment'!$A$6:$A$1005,">="&$B$5,'Turnover Assignment'!$A$6:$A$1005,"<="&$B$6)) | G38: =IF(A38="","",D38+E38+F38)
A40: TOTALS | B40: =SUM(B9:B38) | C40: =SUM(C9:C38) | D40: =SUM(D9:D38) | E40: =SUM(E9:E38) | F40: =SUM(F9:F38) | G40: =SUM(G9:G38)

Sheet Performance
A2: =HYPERLINK("#'Payroll Run'!A1", "← BACK") | D2: PERFORMANCE | J2: =HYPERLINK("#'1099-NEC Year-End'!A1", "NEXT →")
A4: Per-cleaner scorecard — review monthly to coach, flag, or cut
A5: Cleaner | B5: Turnovers YTD | C5: Avg rating | D5: Avg hrs/turn | E5: Complaints | F5: Performance flag
A6: =IF(Cleaners!B6="","",Cleaners!B6) | B6: =IF(A6="","",SUMPRODUCT(('Turnover Assignment'!$C$6:$C$1005=A6)*(YEAR('Turnover Assignment'!$A$6:$A$1005)=Settings!$B$5))) | C6: =IF(A6="","",IFERROR(AVERAGEIFS('Turnover Assignment'!$I$6:$I$1005,'Turnover Assignment'!$C$6:$C$1005,A6,'Turnover Assignment'!$I$6:$I$1005,">0"),"")) | D6: =IF(A6="","",IFERROR(AVERAGEIFS('Turnover Assignment'!$D$6:$D$1005,'Turnover Assignment'!$C$6:$C$1005,A6,'Turnover Assignment'!$D$6:$D$1005,">0"),"")) | F6: =IF(A6="","",IF(C6="","Insufficient data",IF(AND(C6>=4.7,IFERROR(E6,0)<=1),"Top performer",IF(OR(C6<4.0,IFERROR(E6,0)>=3),"Needs review","Standard"))))
A7: =IF(Cleaners!B7="","",Cleaners!B7) | B7: =IF(A7="","",SUMPRODUCT(('Turnover Assignment'!$C$6:$C$1005=A7)*(YEAR('Turnover Assignment'!$A$6:$A$1005)=Settings!$B$5))) | C7: =IF(A7="","",IFERROR(AVERAGEIFS('Turnover Assignment'!$I$6:$I$1005,'Turnover Assignment'!$C$6:$C$1005,A7,'Turnover Assignment'!$I$6:$I$1005,">0"),"")) | D7: =IF(A7="","",IFERROR(AVERAGEIFS('Turnover Assignment'!$D$6:$D$1005,'Turnover Assignment'!$C$6:$C$1005,A7,'Turnover Assignment'!$D$6:$D$1005,">0"),"")) | F7: =IF(A7="","",IF(C7="","Insufficient data",IF(AND(C7>=4.7,IFERROR(E7,0)<=1),"Top performer",IF(OR(C7<4.0,IFERROR(E7,0)>=3),"Needs review","Standard"))))
A8: =IF(Cleaners!B8="","",Cleaners!B8) | B8: =IF(A8="","",SUMPRODUCT(('Turnover Assignment'!$C$6:$C$1005=A8)*(YEAR('Turnover Assignment'!$A$6:$A$1005)=Settings!$B$5))) | C8: =IF(A8="","",IFERROR(AVERAGEIFS('Turnover Assignment'!$I$6:$I$1005,'Turnover Assignment'!$C$6:$C$1005,A8,'Turnover Assignment'!$I$6:$I$1005,">0"),"")) | D8: =IF(A8="","",IFERROR(AVERAGEIFS('Turnover Assignment'!$D$6:$D$1005,'Turnover Assignment'!$C$6:$C$1005,A8,'Turnover Assignment'!$D$6:$D$1005,">0"),"")) | F8: =IF(A8="","",IF(C8="","Insufficient data",IF(AND(C8>=4.7,IFERROR(E8,0)<=1),"Top performer",IF(OR(C8<4.0,IFERROR(E8,0)>=3),"Needs review","Standard"))))
A9: =IF(Cleaners!B9="","",Cleaners!B9) | B9: =IF(A9="","",SUMPRODUCT(('Turnover Assignment'!$C$6:$C$1005=A9)*(YEAR('Turnover Assignment'!$A$6:$A$1005)=Settings!$B$5))) | C9: =IF(A9="","",IFERROR(AVERAGEIFS('Turnover Assignment'!$I$6:$I$1005,'Turnover Assignment'!$C$6:$C$1005,A9,'Turnover Assignment'!$I$6:$I$1005,">0"),"")) | D9: =IF(A9="","",IFERROR(AVERAGEIFS('Turnover Assignment'!$D$6:$D$1005,'Turnover Assignment'!$C$6:$C$1005,A9,'Turnover Assignment'!$D$6:$D$1005,">0"),"")) | F9: =IF(A9="","",IF(C9="","Insufficient data",IF(AND(C9>=4.7,IFERROR(E9,0)<=1),"Top performer",IF(OR(C9<4.0,IFERROR(E9,0)>=3),"Needs review","Standard"))))
A10: =IF(Cleaners!B10="","",Cleaners!B10) | B10: =IF(A10="","",SUMPRODUCT(('Turnover Assignment'!$C$6:$C$1005=A10)*(YEAR('Turnover Assignment'!$A$6:$A$1005)=Settings!$B$5))) | C10: =IF(A10="","",IFERROR(AVERAGEIFS('Turnover Assignment'!$I$6:$I$1005,'Turnover Assignment'!$C$6:$C$1005,A10,'Turnover Assignment'!$I$6:$I$1005,">0"),"")) | D10: =IF(A10="","",IFERROR(AVERAGEIFS('Turnover Assignment'!$D$6:$D$1005,'Turnover Assignment'!$C$6:$C$1005,A10,'Turnover Assignment'!$D$6:$D$1005,">0"),"")) | F10: =IF(A10="","",IF(C10="","Insufficient data",IF(AND(C10>=4.7,IFERROR(E10,0)<=1),"Top performer",IF(OR(C10<4.0,IFERROR(E10,0)>=3),"Needs review","Standard"))))
A11: =IF(Cleaners!B11="","",Cleaners!B11) | B11: =IF(A11="","",SUMPRODUCT(('Turnover Assignment'!$C$6:$C$1005=A11)*(YEAR('Turnover Assignment'!$A$6:$A$1005)=Settings!$B$5))) | C11: =IF(A11="","",IFERROR(AVERAGEIFS('Turnover Assignment'!$I$6:$I$1005,'Turnover Assignment'!$C$6:$C$1005,A11,'Turnover Assignment'!$I$6:$I$1005,">0"),"")) | D11: =IF(A11="","",IFERROR(AVERAGEIFS('Turnover Assignment'!$D$6:$D$1005,'Turnover Assignment'!$C$6:$C$1005,A11,'Turnover Assignment'!$D$6:$D$1005,">0"),"")) | F11: =IF(A11="","",IF(C11="","Insufficient data",IF(AND(C11>=4.7,IFERROR(E11,0)<=1),"Top performer",IF(OR(C11<4.0,IFERROR(E11,0)>=3),"Needs review","Standard"))))
A12: =IF(Cleaners!B12="","",Cleaners!B12) | B12: =IF(A12="","",SUMPRODUCT(('Turnover Assignment'!$C$6:$C$1005=A12)*(YEAR('Turnover Assignment'!$A$6:$A$1005)=Settings!$B$5))) | C12: =IF(A12="","",IFERROR(AVERAGEIFS('Turnover Assignment'!$I$6:$I$1005,'Turnover Assignment'!$C$6:$C$1005,A12,'Turnover Assignment'!$I$6:$I$1005,">0"),"")) | D12: =IF(A12="","",IFERROR(AVERAGEIFS('Turnover Assignment'!$D$6:$D$1005,'Turnover Assignment'!$C$6:$C$1005,A12,'Turnover Assignment'!$D$6:$D$1005,">0"),"")) | F12: =IF(A12="","",IF(C12="","Insufficient data",IF(AND(C12>=4.7,IFERROR(E12,0)<=1),"Top performer",IF(OR(C12<4.0,IFERROR(E12,0)>=3),"Needs review","Standard"))))
A13: =IF(Cleaners!B13="","",Cleaners!B13) | B13: =IF(A13="","",SUMPRODUCT(('Turnover Assignment'!$C$6:$C$1005=A13)*(YEAR('Turnover Assignment'!$A$6:$A$1005)=Settings!$B$5))) | C13: =IF(A13="","",IFERROR(AVERAGEIFS('Turnover Assignment'!$I$6:$I$1005,'Turnover Assignment'!$C$6:$C$1005,A13,'Turnover Assignment'!$I$6:$I$1005,">0"),"")) | D13: =IF(A13="","",IFERROR(AVERAGEIFS('Turnover Assignment'!$D$6:$D$1005,'Turnover Assignment'!$C$6:$C$1005,A13,'Turnover Assignment'!$D$6:$D$1005,">0"),"")) | F13: =IF(A13="","",IF(C13="","Insufficient data",IF(AND(C13>=4.7,IFERROR(E13,0)<=1),"Top performer",IF(OR(C13<4.0,IFERROR(E13,0)>=3),"Needs review","Standard"))))
A14: =IF(Cleaners!B14="","",Cleaners!B14) | B14: =IF(A14="","",SUMPRODUCT(('Turnover Assignment'!$C$6:$C$1005=A14)*(YEAR('Turnover Assignment'!$A$6:$A$1005)=Settings!$B$5))) | C14: =IF(A14="","",IFERROR(AVERAGEIFS('Turnover Assignment'!$I$6:$I$1005,'Turnover Assignment'!$C$6:$C$1005,A14,'Turnover Assignment'!$I$6:$I$1005,">0"),"")) | D14: =IF(A14="","",IFERROR(AVERAGEIFS('Turnover Assignment'!$D$6:$D$1005,'Turnover Assignment'!$C$6:$C$1005,A14,'Turnover Assignment'!$D$6:$D$1005,">0"),"")) | F14: =IF(A14="","",IF(C14="","Insufficient data",IF(AND(C14>=4.7,IFERROR(E14,0)<=1),"Top performer",IF(OR(C14<4.0,IFERROR(E14,0)>=3),"Needs review","Standard"))))
A15: =IF(Cleaners!B15="","",Cleaners!B15) | B15: =IF(A15="","",SUMPRODUCT(('Turnover Assignment'!$C$6:$C$1005=A15)*(YEAR('Turnover Assignment'!$A$6:$A$1005)=Settings!$B$5))) | C15: =IF(A15="","",IFERROR(AVERAGEIFS('Turnover Assignment'!$I$6:$I$1005,'Turnover Assignment'!$C$6:$C$1005,A15,'Turnover Assignment'!$I$6:$I$1005,">0"),"")) | D15: =IF(A15="","",IFERROR(AVERAGEIFS('Turnover Assignment'!$D$6:$D$1005,'Turnover Assignment'!$C$6:$C$1005,A15,'Turnover Assignment'!$D$6:$D$1005,">0"),"")) | F15: =IF(A15="","",IF(C15="","Insufficient data",IF(AND(C15>=4.7,IFERROR(E15,0)<=1),"Top performer",IF(OR(C15<4.0,IFERROR(E15,0)>=3),"Needs review","Standard"))))
A16: =IF(Cleaners!B16="","",Cleaners!B16) | B16: =IF(A16="","",SUMPRODUCT(('Turnover Assignment'!$C$6:$C$1005=A16)*(YEAR('Turnover Assignment'!$A$6:$A$1005)=Settings!$B$5))) | C16: =IF(A16="","",IFERROR(AVERAGEIFS('Turnover Assignment'!$I$6:$I$1005,'Turnover Assignment'!$C$6:$C$1005,A16,'Turnover Assignment'!$I$6:$I$1005,">0"),"")) | D16: =IF(A16="","",IFERROR(AVERAGEIFS('Turnover Assignment'!$D$6:$D$1005,'Turnover Assignment'!$C$6:$C$1005,A16,'Turnover Assignment'!$D$6:$D$1005,">0"),"")) | F16: =IF(A16="","",IF(C16="","Insufficient data",IF(AND(C16>=4.7,IFERROR(E16,0)<=1),"Top performer",IF(OR(C16<4.0,IFERROR(E16,0)>=3),"Needs review","Standard"))))
A17: =IF(Cleaners!B17="","",Cleaners!B17) | B17: =IF(A17="","",SUMPRODUCT(('Turnover Assignment'!$C$6:$C$1005=A17)*(YEAR('Turnover Assignment'!$A$6:$A$1005)=Settings!$B$5))) | C17: =IF(A17="","",IFERROR(AVERAGEIFS('Turnover Assignment'!$I$6:$I$1005,'Turnover Assignment'!$C$6:$C$1005,A17,'Turnover Assignment'!$I$6:$I$1005,">0"),"")) | D17: =IF(A17="","",IFERROR(AVERAGEIFS('Turnover Assignment'!$D$6:$D$1005,'Turnover Assignment'!$C$6:$C$1005,A17,'Turnover Assignment'!$D$6:$D$1005,">0"),"")) | F17: =IF(A17="","",IF(C17="","Insufficient data",IF(AND(C17>=4.7,IFERROR(E17,0)<=1),"Top performer",IF(OR(C17<4.0,IFERROR(E17,0)>=3),"Needs review","Standard"))))
... A55: =IF(Cleaners!B55="","",Cleaners!B55) | B55: =IF(A55="","",SUMPRODUCT(('Turnover Assignment'!$C$6:$C$1005=A55)*(YEAR('Turnover Assignment'!$A$6:$A$1005)=Settings!$B$5))) | C55: =IF(A55="","",IFERROR(AVERAGEIFS('Turnover Assignment'!$I$6:$I$1005,'Turnover Assignment'!$C$6:$C$1005,A55,'Turnover Assignment'!$I$6:$I$1005,">0"),"")) | D55: =IF(A55="","",IFERROR(AVERAGEIFS('Turnover Assignment'!$D$6:$D$1005,'Turnover Assignment'!$C$6:$C$1005,A55,'Turnover Assignment'!$D$6:$D$1005,">0"),"")) | F55: =IF(A55="","",IF(C55="","Insufficient data",IF(AND(C55>=4.7,IFERROR(E55,0)<=1),"Top performer",IF(OR(C55<4.0,IFERROR(E55,0)>=3),"Needs review","Standard"))))

Sheet 1099-NEC Year-End
A2: =HYPERLINK("#'Performance'!A1", "← BACK") | D2: 1099-NEC YEAR-END · FOR YOUR CPA | J2: =HYPERLINK("#'Settings'!A1", "NEXT →")
A4: 📄 Year-end totals per cleaner — drops directly into TAX-003 1099-NEC tracker
A5: Cleaner | B5: Total paid YTD | C5: 1099 required? | D5: W-9 on file? | E5: Mailing address ready? | F5: Status
A6: =IF(Cleaners!B6="","",Cleaners!B6) | B6: =IF(A6="","",SUMPRODUCT(('Turnover Assignment'!$C$6:$C$1005=A6)*(YEAR('Turnover Assignment'!$A$6:$A$1005)=Settings!$B$5)*'Turnover Assignment'!$K$6:$K$1005)) | C6: =IF(A6="","",IF(B6>=Settings!$B$20,"✓ Required","Below threshold")) | D6: =IF(A6="","",IFERROR(VLOOKUP(A6,Cleaners!$B$6:$G$35,6,FALSE),"?")) | E6: =IF(A6="","",IF(IFERROR(VLOOKUP(A6,Cleaners!$B$6:$E$35,4,FALSE),"")="","⚠ Missing","✓ On file")) | F6: =IF(A6="","",IF(C6="✓ Required",IF(AND(D6="Yes",LEFT(E6,1)="✓"),"✓ Ready to file","⚠ Missing W-9 or address"),"n/a"))
A7: =IF(Cleaners!B7="","",Cleaners!B7) | B7: =IF(A7="","",SUMPRODUCT(('Turnover Assignment'!$C$6:$C$1005=A7)*(YEAR('Turnover Assignment'!$A$6:$A$1005)=Settings!$B$5)*'Turnover Assignment'!$K$6:$K$1005)) | C7: =IF(A7="","",IF(B7>=Settings!$B$20,"✓ Required","Below threshold")) | D7: =IF(A7="","",IFERROR(VLOOKUP(A7,Cleaners!$B$6:$G$35,6,FALSE),"?")) | E7: =IF(A7="","",IF(IFERROR(VLOOKUP(A7,Cleaners!$B$6:$E$35,4,FALSE),"")="","⚠ Missing","✓ On file")) | F7: =IF(A7="","",IF(C7="✓ Required",IF(AND(D7="Yes",LEFT(E7,1)="✓"),"✓ Ready to file","⚠ Missing W-9 or address"),"n/a"))
A8: =IF(Cleaners!B8="","",Cleaners!B8) | B8: =IF(A8="","",SUMPRODUCT(('Turnover Assignment'!$C$6:$C$1005=A8)*(YEAR('Turnover Assignment'!$A$6:$A$1005)=Settings!$B$5)*'Turnover Assignment'!$K$6:$K$1005)) | C8: =IF(A8="","",IF(B8>=Settings!$B$20,"✓ Required","Below threshold")) | D8: =IF(A8="","",IFERROR(VLOOKUP(A8,Cleaners!$B$6:$G$35,6,FALSE),"?")) | E8: =IF(A8="","",IF(IFERROR(VLOOKUP(A8,Cleaners!$B$6:$E$35,4,FALSE),"")="","⚠ Missing","✓ On file")) | F8: =IF(A8="","",IF(C8="✓ Required",IF(AND(D8="Yes",LEFT(E8,1)="✓"),"✓ Ready to file","⚠ Missing W-9 or address"),"n/a"))
A9: =IF(Cleaners!B9="","",Cleaners!B9) | B9: =IF(A9="","",SUMPRODUCT(('Turnover Assignment'!$C$6:$C$1005=A9)*(YEAR('Turnover Assignment'!$A$6:$A$1005)=Settings!$B$5)*'Turnover Assignment'!$K$6:$K$1005)) | C9: =IF(A9="","",IF(B9>=Settings!$B$20,"✓ Required","Below threshold")) | D9: =IF(A9="","",IFERROR(VLOOKUP(A9,Cleaners!$B$6:$G$35,6,FALSE),"?")) | E9: =IF(A9="","",IF(IFERROR(VLOOKUP(A9,Cleaners!$B$6:$E$35,4,FALSE),"")="","⚠ Missing","✓ On file")) | F9: =IF(A9="","",IF(C9="✓ Required",IF(AND(D9="Yes",LEFT(E9,1)="✓"),"✓ Ready to file","⚠ Missing W-9 or address"),"n/a"))
A10: =IF(Cleaners!B10="","",Cleaners!B10) | B10: =IF(A10="","",SUMPRODUCT(('Turnover Assignment'!$C$6:$C$1005=A10)*(YEAR('Turnover Assignment'!$A$6:$A$1005)=Settings!$B$5)*'Turnover Assignment'!$K$6:$K$1005)) | C10: =IF(A10="","",IF(B10>=Settings!$B$20,"✓ Required","Below threshold")) | D10: =IF(A10="","",IFERROR(VLOOKUP(A10,Cleaners!$B$6:$G$35,6,FALSE),"?")) | E10: =IF(A10="","",IF(IFERROR(VLOOKUP(A10,Cleaners!$B$6:$E$35,4,FALSE),"")="","⚠ Missing","✓ On file")) | F10: =IF(A10="","",IF(C10="✓ Required",IF(AND(D10="Yes",LEFT(E10,1)="✓"),"✓ Ready to file","⚠ Missing W-9 or address"),"n/a"))
A11: =IF(Cleaners!B11="","",Cleaners!B11) | B11: =IF(A11="","",SUMPRODUCT(('Turnover Assignment'!$C$6:$C$1005=A11)*(YEAR('Turnover Assignment'!$A$6:$A$1005)=Settings!$B$5)*'Turnover Assignment'!$K$6:$K$1005)) | C11: =IF(A11="","",IF(B11>=Settings!$B$20,"✓ Required","Below threshold")) | D11: =IF(A11="","",IFERROR(VLOOKUP(A11,Cleaners!$B$6:$G$35,6,FALSE),"?")) | E11: =IF(A11="","",IF(IFERROR(VLOOKUP(A11,Cleaners!$B$6:$E$35,4,FALSE),"")="","⚠ Missing","✓ On file")) | F11: =IF(A11="","",IF(C11="✓ Required",IF(AND(D11="Yes",LEFT(E11,1)="✓"),"✓ Ready to file","⚠ Missing W-9 or address"),"n/a"))
A12: =IF(Cleaners!B12="","",Cleaners!B12) | B12: =IF(A12="","",SUMPRODUCT(('Turnover Assignment'!$C$6:$C$1005=A12)*(YEAR('Turnover Assignment'!$A$6:$A$1005)=Settings!$B$5)*'Turnover Assignment'!$K$6:$K$1005)) | C12: =IF(A12="","",IF(B12>=Settings!$B$20,"✓ Required","Below threshold")) | D12: =IF(A12="","",IFERROR(VLOOKUP(A12,Cleaners!$B$6:$G$35,6,FALSE),"?")) | E12: =IF(A12="","",IF(IFERROR(VLOOKUP(A12,Cleaners!$B$6:$E$35,4,FALSE),"")="","⚠ Missing","✓ On file")) | F12: =IF(A12="","",IF(C12="✓ Required",IF(AND(D12="Yes",LEFT(E12,1)="✓"),"✓ Ready to file","⚠ Missing W-9 or address"),"n/a"))
A13: =IF(Cleaners!B13="","",Cleaners!B13) | B13: =IF(A13="","",SUMPRODUCT(('Turnover Assignment'!$C$6:$C$1005=A13)*(YEAR('Turnover Assignment'!$A$6:$A$1005)=Settings!$B$5)*'Turnover Assignment'!$K$6:$K$1005)) | C13: =IF(A13="","",IF(B13>=Settings!$B$20,"✓ Required","Below threshold")) | D13: =IF(A13="","",IFERROR(VLOOKUP(A13,Cleaners!$B$6:$G$35,6,FALSE),"?")) | E13: =IF(A13="","",IF(IFERROR(VLOOKUP(A13,Cleaners!$B$6:$E$35,4,FALSE),"")="","⚠ Missing","✓ On file")) | F13: =IF(A13="","",IF(C13="✓ Required",IF(AND(D13="Yes",LEFT(E13,1)="✓"),"✓ Ready to file","⚠ Missing W-9 or address"),"n/a"))
A14: =IF(Cleaners!B14="","",Cleaners!B14) | B14: =IF(A14="","",SUMPRODUCT(('Turnover Assignment'!$C$6:$C$1005=A14)*(YEAR('Turnover Assignment'!$A$6:$A$1005)=Settings!$B$5)*'Turnover Assignment'!$K$6:$K$1005)) | C14: =IF(A14="","",IF(B14>=Settings!$B$20,"✓ Required","Below threshold")) | D14: =IF(A14="","",IFERROR(VLOOKUP(A14,Cleaners!$B$6:$G$35,6,FALSE),"?")) | E14: =IF(A14="","",IF(IFERROR(VLOOKUP(A14,Cleaners!$B$6:$E$35,4,FALSE),"")="","⚠ Missing","✓ On file")) | F14: =IF(A14="","",IF(C14="✓ Required",IF(AND(D14="Yes",LEFT(E14,1)="✓"),"✓ Ready to file","⚠ Missing W-9 or address"),"n/a"))
A15: =IF(Cleaners!B15="","",Cleaners!B15) | B15: =IF(A15="","",SUMPRODUCT(('Turnover Assignment'!$C$6:$C$1005=A15)*(YEAR('Turnover Assignment'!$A$6:$A$1005)=Settings!$B$5)*'Turnover Assignment'!$K$6:$K$1005)) | C15: =IF(A15="","",IF(B15>=Settings!$B$20,"✓ Required","Below threshold")) | D15: =IF(A15="","",IFERROR(VLOOKUP(A15,Cleaners!$B$6:$G$35,6,FALSE),"?")) | E15: =IF(A15="","",IF(IFERROR(VLOOKUP(A15,Cleaners!$B$6:$E$35,4,FALSE),"")="","⚠ Missing","✓ On file")) | F15: =IF(A15="","",IF(C15="✓ Required",IF(AND(D15="Yes",LEFT(E15,1)="✓"),"✓ Ready to file","⚠ Missing W-9 or address"),"n/a"))
A16: =IF(Cleaners!B16="","",Cleaners!B16) | B16: =IF(A16="","",SUMPRODUCT(('Turnover Assignment'!$C$6:$C$1005=A16)*(YEAR('Turnover Assignment'!$A$6:$A$1005)=Settings!$B$5)*'Turnover Assignment'!$K$6:$K$1005)) | C16: =IF(A16="","",IF(B16>=Settings!$B$20,"✓ Required","Below threshold")) | D16: =IF(A16="","",IFERROR(VLOOKUP(A16,Cleaners!$B$6:$G$35,6,FALSE),"?")) | E16: =IF(A16="","",IF(IFERROR(VLOOKUP(A16,Cleaners!$B$6:$E$35,4,FALSE),"")="","⚠ Missing","✓ On file")) | F16: =IF(A16="","",IF(C16="✓ Required",IF(AND(D16="Yes",LEFT(E16,1)="✓"),"✓ Ready to file","⚠ Missing W-9 or address"),"n/a"))
A17: =IF(Cleaners!B17="","",Cleaners!B17) | B17: =IF(A17="","",SUMPRODUCT(('Turnover Assignment'!$C$6:$C$1005=A17)*(YEAR('Turnover Assignment'!$A$6:$A$1005)=Settings!$B$5)*'Turnover Assignment'!$K$6:$K$1005)) | C17: =IF(A17="","",IF(B17>=Settings!$B$20,"✓ Required","Below threshold")) | D17: =IF(A17="","",IFERROR(VLOOKUP(A17,Cleaners!$B$6:$G$35,6,FALSE),"?")) | E17: =IF(A17="","",IF(IFERROR(VLOOKUP(A17,Cleaners!$B$6:$E$35,4,FALSE),"")="","⚠ Missing","✓ On file")) | F17: =IF(A17="","",IF(C17="✓ Required",IF(AND(D17="Yes",LEFT(E17,1)="✓"),"✓ Ready to file","⚠ Missing W-9 or address"),"n/a"))
... A35: =IF(Cleaners!B35="","",Cleaners!B35) | B35: =IF(A35="","",SUMPRODUCT(('Turnover Assignment'!$C$6:$C$1005=A35)*(YEAR('Turnover Assignment'!$A$6:$A$1005)=Settings!$B$5)*'Turnover Assignment'!$K$6:$K$1005)) | C35: =IF(A35="","",IF(B35>=Settings!$B$20,"✓ Required","Below threshold")) | D35: =IF(A35="","",IFERROR(VLOOKUP(A35,Cleaners!$B$6:$G$35,6,FALSE),"?")) | E35: =IF(A35="","",IF(IFERROR(VLOOKUP(A35,Cleaners!$B$6:$E$35,4,FALSE),"")="","⚠ Missing","✓ On file")) | F35: =IF(A35="","",IF(C35="✓ Required",IF(AND(D35="Yes",LEFT(E35,1)="✓"),"✓ Ready to file","⚠ Missing W-9 or address"),"n/a"))
A38: Summary
A39: Cleaners requiring 1099: | B39: =COUNTIF(C6:C35,"✓ Required")
A40: Of those, ready to file: | B40: =COUNTIF(F6:F35,"✓ Ready to file")
A41: Of those, missing W-9 or address: | B41: =COUNTIF(C6:C35,"✓ Required")-COUNTIF(F6:F35,"✓ Ready to file")
A42: Total 1099-NEC $ volume: | B42: =SUMIFS(B6:B35,C6:C35,"✓ Required")

Sheet Settings
A2: =HYPERLINK("#'1099-NEC Year-End'!A1", "← BACK") | D2: SETTINGS
A4: Active year · property list · pay cadence · 1099 threshold
A5: Active tax year: | B5: 2026
A6: All YTD formulas filter on this year. Update once each January after you archive the prior year's data.
A7: Properties (used in Turnover dropdown):
B8: Smokies Ridge
B9: Creek Side
B10: Lakehouse A
B11: Mountain View
B12: Downtown Loft
A18: Payment cadence: | B18: Bi-weekly
A20: 1099-NEC threshold ($): | B20: 600
A21: $600 is locked by IRS rule. Don't change unless the IRS publishes a new threshold (rare) — Year-End formulas filter on this cell.
A23: Year-end Archive
A24: Each January, copy YTD totals into the row for the closing year, then clear the Turnover Assignment log for the new year (keep Cleaners).
A25: Year | B25: Active cleaners | C25: Turnovers | D25: Total $ paid
A26: 2024
A27: 2025
A28: 2026
A29: 2027
A30: 2028
A31: 2029
A32: 2030
