Workbook

Sheet Start
A2: The STR Ledger
A4: Minimum-Night-Stay Optimizer
A5: Does 1-night really beat 3-night? Run the math.
A7: REV-004 · v1.0 · DEMO
A11: =IF(Settings!C5="","(set property on Settings tab)",Settings!C5)
A13: Most hosts assume a 1-night minimum maximizes revenue. Turnover cost often makes 3-night MNS net better. Let's see.
A16: RECOMMENDED MINIMUM-NIGHT-STAY
A17: =INDEX(Comparison!C7:G7,MATCH(MAX(Comparison!C24:G24),Comparison!C24:G24,0))&"-night minimum"
A20: ="Annual NET: "&TEXT(MAX(Comparison!C24:G24),"$#,##0")&" · vs 1-night NET: "&TEXT(Comparison!C24,"$#,##0")
A22: ="Lift over 1-night minimum: "&TEXT(MAX(Comparison!C24:G24)-Comparison!C24,"+$#,##0;-$#,##0;$0")&" / year"
A25: =HYPERLINK("#'Inputs'!A1", "→ Inputs") | E25: =HYPERLINK("#'Comparison'!A1", "→ Run Comparison") | I25: =HYPERLINK("#'Settings'!A1", "Settings")
A30: Optimizing pricing across scenarios? Get the Pricing Bundle at thestrledger.com/pricing — cleaning fee + MNS + base-rate together.
A33: Questions? hello@thestrledger.com
A34: REV-004 · v1.0 · Free updates forever

Sheet Inputs
A2: =HYPERLINK("#'Start'!A1", "← BACK") | D2: INPUTS | J2: =HYPERLINK("#'Comparison'!A1", "NEXT →")
A4: Yellow = edit. Set base costs once, then tune per-scenario occupancy + ADR by MNS.
A6: BASE PROPERTY & COSTS
B7: Base nightly rate ($): | C7: 185 | E7: Reference rate — per-scenario ADR overrides below
B8: Cleaning cost per turnover ($): | C8: 90 | E8: What you pay your cleaner each turnover
B9: Supply restock per turnover ($): | C9: 25 | E9: Toiletries, paper, coffee, consumables
B10: Host hours per turnover: | C10: 1.5 | E10: Coordination, inspection, supply runs
B11: Host hourly opportunity cost ($): | C11: 40 | E11: What your time is worth — be honest
A15: PER-SCENARIO — OCCUPANCY & ADR BY MNS
B16: MNS scenario | C16: Expected occ. | D16: Expected ADR | E16: Note
B17: 1-night MNS | C17: 0.78 | D17: 185 | E17: 1-night = max nightly availability, max turnovers
B18: 2-night MNS | C18: 0.76 | D18: 185 | E18: Filters out single-night party bookers
B19: 3-night MNS | C19: 0.7 | D19: 192 | E19: Sweet spot for most STR markets
B20: 5-night MNS | C20: 0.58 | D20: 200 | E20: Long-weekend bookings only
B21: 7-night MNS | C21: 0.45 | D21: 210 | E21: Week-long stays — lowest ops cost, lowest occupancy
A24: Why ADR rises with longer MNS: longer minimums filter to vacationers (less price-sensitive) and avoid Airbnb's length-of-stay discount territory. Conservative estimate: +$5-15/night per additional MNS step. Pull real numbers from PriceLabs/Wheelhouse.
A29: Questions? hello@thestrledger.com
A30: REV-004 · Inputs

Sheet Comparison
A2: =HYPERLINK("#'Inputs'!A1", "← BACK") | D2: COMPARISON | J2: =HYPERLINK("#'Settings'!A1", "NEXT →")
A4: Five MNS policies side-by-side. Gold-soft column = highest NET. Numbers update from Inputs.
B6: Metric | C6: 1-night MNS | D6: 2-night MNS | E6: 3-night MNS | F6: 5-night MNS | G6: 7-night MNS
B7: Min nights per booking | C7: 1 | D7: 2 | E7: 3 | F7: 5 | G7: 7
B8: Avg nights per booking | C8: =C7 | D8: =D7 | E8: =E7 | F8: =F7 | G8: =G7
B9: Bookings / year | C9: =IFERROR((365*Inputs!C17)/C7,0) | D9: =IFERROR((365*Inputs!C18)/D7,0) | E9: =IFERROR((365*Inputs!C19)/E7,0) | F9: =IFERROR((365*Inputs!C20)/F7,0) | G9: =IFERROR((365*Inputs!C21)/G7,0)
B10: Turnovers / year | C10: =C9 | D10: =D9 | E10: =E9 | F10: =F9 | G10: =G9
B11: Occupied nights / year | C11: =365*Inputs!C17 | D11: =365*Inputs!C18 | E11: =365*Inputs!C19 | F11: =365*Inputs!C20 | G11: =365*Inputs!C21
A12: REVENUE & COSTS
B13: Gross revenue | C13: =365*Inputs!C17*Inputs!D17 | D13: =365*Inputs!C18*Inputs!D18 | E13: =365*Inputs!C19*Inputs!D19 | F13: =365*Inputs!C20*Inputs!D20 | G13: =365*Inputs!C21*Inputs!D21
B14: Cleaning cost (total) | C14: =C10*Inputs!$C$8 | D14: =D10*Inputs!$C$8 | E14: =E10*Inputs!$C$8 | F14: =F10*Inputs!$C$8 | G14: =G10*Inputs!$C$8
B15: Supply restock cost | C15: =C10*Inputs!$C$9 | D15: =D10*Inputs!$C$9 | E15: =E10*Inputs!$C$9 | F15: =F10*Inputs!$C$9 | G15: =G10*Inputs!$C$9
B16: Host labor cost | C16: =C10*Inputs!$C$10*Inputs!$C$11 | D16: =D10*Inputs!$C$10*Inputs!$C$11 | E16: =E10*Inputs!$C$10*Inputs!$C$11 | F16: =F10*Inputs!$C$10*Inputs!$C$11 | G16: =G10*Inputs!$C$10*Inputs!$C$11
B17: Total operating costs | C17: =SUM(C14:C16) | D17: =SUM(D14:D16) | E17: =SUM(E14:E16) | F17: =SUM(F14:F16) | G17: =SUM(G14:G16)
A23: NET RESULT
B24: ANNUAL NET REVENUE | C24: =C13-C17 | D24: =D13-D17 | E24: =E13-E17 | F24: =F13-F17 | G24: =G13-G17
B25: NET / occupied night | C25: =IFERROR(C24/C11,0) | D25: =IFERROR(D24/D11,0) | E25: =IFERROR(E24/E11,0) | F25: =IFERROR(F24/F11,0) | G25: =IFERROR(G24/G11,0)
B26: Δ vs 1-night MNS | C26: ="—" | D26: =D24-C24 | E26: =E24-C24 | F26: =F24-C24 | G26: =G24-C24
A50: Why this matters: every turnover costs cleaning + supplies + your hours. A 1-night minimum maximizes booking velocity but multiplies turnover cost. Most properties net more at a 2- or 3-night minimum even with lower occupancy. Re-run when your cleaner rate or occupancy data shifts.
A55: Questions? hello@thestrledger.com
A56: REV-004 · Comparison

Sheet Settings
A2: =HYPERLINK("#'Comparison'!A1", "← BACK") | D2: SETTINGS
A4: Property selector + active year. Used in the Start tab headline.
B5: Property: | C5: Smokies Ridge Cabin | E5: Shown on Start tab headline
B7: Active year: | C7: 2026 | E7: Tax/reporting year for this analysis
A13: Questions? hello@thestrledger.com
A14: REV-004 · Settings
