Workbook

Sheet Start
A2: The STR Ledger
A4: Corporate Housing & Travel-Nurse Tracker
A5: Mid-term hosting is a different game — gap days are the killer metric.
A7: SPC-002 · v2.3 · BLANK
A10: ACTIVE TENANTS | D10: MRR (PORTFOLIO) | G10: TENANTS YTD | J10: FUTURE-SIGNED
A11: =COUNTIF(Tenants!N6:N105,"Active") | D11: =SUMIFS(Tenants!K6:K105,Tenants!N6:N105,"Active") | G11: =COUNTA(Tenants!A6:A105) | J11: =COUNTIF(Tenants!N6:N105,"Approved")
A14: currently in residence | D14: monthly recurring revenue | G14: all leases logged | J14: approved but not yet active
A17: WHAT THIS DOES
A18: Mid-term hosts (30-day+ stays on Furnished Finder, Blueground, or direct with corporate clients/travel nurses) need to track tenant pipeline, monthly recurring revenue, and the gap days that quietly eat margin between leases. This workbook is a CRM + revenue matrix + pipeline funnel — purpose-built for the mid-term model.
A24: =HYPERLINK("#'Tenants'!A6", "→ ADD A TENANT (OPEN TENANTS)")
A29: =HYPERLINK("#'Lease Calendar'!A1", "Lease Calendar") | D29: =HYPERLINK("#'Monthly Revenue'!A1", "Monthly Revenue") | G29: =HYPERLINK("#'Pipeline'!A1", "Pipeline") | J29: =HYPERLINK("#'Settings'!A1", "Settings")
A32: 💡 MID-TERM RULE OF THUMB: a 1-week gap on a $3,000/mo unit costs $700 in lost rent. Future-signed leases beat backfilling. Watch the Pipeline tab — your inquiry-to-signed conversion is your true occupancy lever.
A35: 💡 Upgrade to the Full version at thestrledger.com/upgrade — multi-property, depreciation, multi-LLC support.
A38: Questions? hello@thestrledger.com
A39: SPC-002 · v2.3 · Free updates forever

Sheet Tenants
A2: =HYPERLINK("#'Start'!A1", "← BACK") | D2: TENANTS | J2: =HYPERLINK("#'Lease Calendar'!A1", "NEXT →")
A4: One row per tenant — past, current, future. Pipeline (Lead → Past) tracked in Status.
A5: Tenant ID | B5: Name | C5: Email | D5: Phone | E5: Employer / Agency | F5: Profession | G5: Property Assigned | H5: Channel | I5: Lease Start | J5: Lease End | K5: Monthly Rent | L5: Deposit | M5: Util Incl? | N5: Status | O5: Notes

Sheet Lease Calendar
A2: =HYPERLINK("#'Tenants'!A1", "← BACK") | D2: LEASE CALENDAR | J2: =HYPERLINK("#'Monthly Revenue'!A1", "NEXT →")
A4: 12-month Gantt grid — rows = properties, columns = months. Cells colored by tenant status.
A5: Property | B5: Jan | C5: Feb | D5: Mar | E5: Apr | F5: May | G5: Jun | H5: Jul | I5: Aug | J5: Sep | K5: Oct | L5: Nov | M5: Dec | N5: Active Months
A6: =IF(Settings!$B$7="","",Settings!$B$7) | B6: =IF($A6="","",IFERROR(INDEX(Tenants!$B$6:$B$105,MATCH(1,(Tenants!$G$6:$G$105=$A6)*(Tenants!$I$6:$I$105<=DATE(Settings!$B$5,2,1)-1)*(Tenants!$J$6:$J$105>=DATE(Settings!$B$5,1,1)),0)),"")) | C6: =IF($A6="","",IFERROR(INDEX(Tenants!$B$6:$B$105,MATCH(1,(Tenants!$G$6:$G$105=$A6)*(Tenants!$I$6:$I$105<=DATE(Settings!$B$5,3,1)-1)*(Tenants!$J$6:$J$105>=DATE(Settings!$B$5,2,1)),0)),"")) | D6: =IF($A6="","",IFERROR(INDEX(Tenants!$B$6:$B$105,MATCH(1,(Tenants!$G$6:$G$105=$A6)*(Tenants!$I$6:$I$105<=DATE(Settings!$B$5,4,1)-1)*(Tenants!$J$6:$J$105>=DATE(Settings!$B$5,3,1)),0)),"")) | E6: =IF($A6="","",IFERROR(INDEX(Tenants!$B$6:$B$105,MATCH(1,(Tenants!$G$6:$G$105=$A6)*(Tenants!$I$6:$I$105<=DATE(Settings!$B$5,5,1)-1)*(Tenants!$J$6:$J$105>=DATE(Settings!$B$5,4,1)),0)),"")) | F6: =IF($A6="","",IFERROR(INDEX(Tenants!$B$6:$B$105,MATCH(1,(Tenants!$G$6:$G$105=$A6)*(Tenants!$I$6:$I$105<=DATE(Settings!$B$5,6,1)-1)*(Tenants!$J$6:$J$105>=DATE(Settings!$B$5,5,1)),0)),"")) | G6: =IF($A6="","",IFERROR(INDEX(Tenants!$B$6:$B$105,MATCH(1,(Tenants!$G$6:$G$105=$A6)*(Tenants!$I$6:$I$105<=DATE(Settings!$B$5,7,1)-1)*(Tenants!$J$6:$J$105>=DATE(Settings!$B$5,6,1)),0)),"")) | H6: =IF($A6="","",IFERROR(INDEX(Tenants!$B$6:$B$105,MATCH(1,(Tenants!$G$6:$G$105=$A6)*(Tenants!$I$6:$I$105<=DATE(Settings!$B$5,8,1)-1)*(Tenants!$J$6:$J$105>=DATE(Settings!$B$5,7,1)),0)),"")) | I6: =IF($A6="","",IFERROR(INDEX(Tenants!$B$6:$B$105,MATCH(1,(Tenants!$G$6:$G$105=$A6)*(Tenants!$I$6:$I$105<=DATE(Settings!$B$5,9,1)-1)*(Tenants!$J$6:$J$105>=DATE(Settings!$B$5,8,1)),0)),"")) | J6: =IF($A6="","",IFERROR(INDEX(Tenants!$B$6:$B$105,MATCH(1,(Tenants!$G$6:$G$105=$A6)*(Tenants!$I$6:$I$105<=DATE(Settings!$B$5,10,1)-1)*(Tenants!$J$6:$J$105>=DATE(Settings!$B$5,9,1)),0)),"")) | K6: =IF($A6="","",IFERROR(INDEX(Tenants!$B$6:$B$105,MATCH(1,(Tenants!$G$6:$G$105=$A6)*(Tenants!$I$6:$I$105<=DATE(Settings!$B$5,11,1)-1)*(Tenants!$J$6:$J$105>=DATE(Settings!$B$5,10,1)),0)),"")) | L6: =IF($A6="","",IFERROR(INDEX(Tenants!$B$6:$B$105,MATCH(1,(Tenants!$G$6:$G$105=$A6)*(Tenants!$I$6:$I$105<=DATE(Settings!$B$5,12,1)-1)*(Tenants!$J$6:$J$105>=DATE(Settings!$B$5,11,1)),0)),"")) | M6: =IF($A6="","",IFERROR(INDEX(Tenants!$B$6:$B$105,MATCH(1,(Tenants!$G$6:$G$105=$A6)*(Tenants!$I$6:$I$105<=DATE(Settings!$B$5+1,1,1)-1)*(Tenants!$J$6:$J$105>=DATE(Settings!$B$5,12,1)),0)),"")) | N6: =COUNTIF(B6:M6,"?*")
A7: =IF(Settings!$B$8="","",Settings!$B$8) | B7: =IF($A7="","",IFERROR(INDEX(Tenants!$B$6:$B$105,MATCH(1,(Tenants!$G$6:$G$105=$A7)*(Tenants!$I$6:$I$105<=DATE(Settings!$B$5,2,1)-1)*(Tenants!$J$6:$J$105>=DATE(Settings!$B$5,1,1)),0)),"")) | C7: =IF($A7="","",IFERROR(INDEX(Tenants!$B$6:$B$105,MATCH(1,(Tenants!$G$6:$G$105=$A7)*(Tenants!$I$6:$I$105<=DATE(Settings!$B$5,3,1)-1)*(Tenants!$J$6:$J$105>=DATE(Settings!$B$5,2,1)),0)),"")) | D7: =IF($A7="","",IFERROR(INDEX(Tenants!$B$6:$B$105,MATCH(1,(Tenants!$G$6:$G$105=$A7)*(Tenants!$I$6:$I$105<=DATE(Settings!$B$5,4,1)-1)*(Tenants!$J$6:$J$105>=DATE(Settings!$B$5,3,1)),0)),"")) | E7: =IF($A7="","",IFERROR(INDEX(Tenants!$B$6:$B$105,MATCH(1,(Tenants!$G$6:$G$105=$A7)*(Tenants!$I$6:$I$105<=DATE(Settings!$B$5,5,1)-1)*(Tenants!$J$6:$J$105>=DATE(Settings!$B$5,4,1)),0)),"")) | F7: =IF($A7="","",IFERROR(INDEX(Tenants!$B$6:$B$105,MATCH(1,(Tenants!$G$6:$G$105=$A7)*(Tenants!$I$6:$I$105<=DATE(Settings!$B$5,6,1)-1)*(Tenants!$J$6:$J$105>=DATE(Settings!$B$5,5,1)),0)),"")) | G7: =IF($A7="","",IFERROR(INDEX(Tenants!$B$6:$B$105,MATCH(1,(Tenants!$G$6:$G$105=$A7)*(Tenants!$I$6:$I$105<=DATE(Settings!$B$5,7,1)-1)*(Tenants!$J$6:$J$105>=DATE(Settings!$B$5,6,1)),0)),"")) | H7: =IF($A7="","",IFERROR(INDEX(Tenants!$B$6:$B$105,MATCH(1,(Tenants!$G$6:$G$105=$A7)*(Tenants!$I$6:$I$105<=DATE(Settings!$B$5,8,1)-1)*(Tenants!$J$6:$J$105>=DATE(Settings!$B$5,7,1)),0)),"")) | I7: =IF($A7="","",IFERROR(INDEX(Tenants!$B$6:$B$105,MATCH(1,(Tenants!$G$6:$G$105=$A7)*(Tenants!$I$6:$I$105<=DATE(Settings!$B$5,9,1)-1)*(Tenants!$J$6:$J$105>=DATE(Settings!$B$5,8,1)),0)),"")) | J7: =IF($A7="","",IFERROR(INDEX(Tenants!$B$6:$B$105,MATCH(1,(Tenants!$G$6:$G$105=$A7)*(Tenants!$I$6:$I$105<=DATE(Settings!$B$5,10,1)-1)*(Tenants!$J$6:$J$105>=DATE(Settings!$B$5,9,1)),0)),"")) | K7: =IF($A7="","",IFERROR(INDEX(Tenants!$B$6:$B$105,MATCH(1,(Tenants!$G$6:$G$105=$A7)*(Tenants!$I$6:$I$105<=DATE(Settings!$B$5,11,1)-1)*(Tenants!$J$6:$J$105>=DATE(Settings!$B$5,10,1)),0)),"")) | L7: =IF($A7="","",IFERROR(INDEX(Tenants!$B$6:$B$105,MATCH(1,(Tenants!$G$6:$G$105=$A7)*(Tenants!$I$6:$I$105<=DATE(Settings!$B$5,12,1)-1)*(Tenants!$J$6:$J$105>=DATE(Settings!$B$5,11,1)),0)),"")) | M7: =IF($A7="","",IFERROR(INDEX(Tenants!$B$6:$B$105,MATCH(1,(Tenants!$G$6:$G$105=$A7)*(Tenants!$I$6:$I$105<=DATE(Settings!$B$5+1,1,1)-1)*(Tenants!$J$6:$J$105>=DATE(Settings!$B$5,12,1)),0)),"")) | N7: =COUNTIF(B7:M7,"?*")
A8: =IF(Settings!$B$9="","",Settings!$B$9) | B8: =IF($A8="","",IFERROR(INDEX(Tenants!$B$6:$B$105,MATCH(1,(Tenants!$G$6:$G$105=$A8)*(Tenants!$I$6:$I$105<=DATE(Settings!$B$5,2,1)-1)*(Tenants!$J$6:$J$105>=DATE(Settings!$B$5,1,1)),0)),"")) | C8: =IF($A8="","",IFERROR(INDEX(Tenants!$B$6:$B$105,MATCH(1,(Tenants!$G$6:$G$105=$A8)*(Tenants!$I$6:$I$105<=DATE(Settings!$B$5,3,1)-1)*(Tenants!$J$6:$J$105>=DATE(Settings!$B$5,2,1)),0)),"")) | D8: =IF($A8="","",IFERROR(INDEX(Tenants!$B$6:$B$105,MATCH(1,(Tenants!$G$6:$G$105=$A8)*(Tenants!$I$6:$I$105<=DATE(Settings!$B$5,4,1)-1)*(Tenants!$J$6:$J$105>=DATE(Settings!$B$5,3,1)),0)),"")) | E8: =IF($A8="","",IFERROR(INDEX(Tenants!$B$6:$B$105,MATCH(1,(Tenants!$G$6:$G$105=$A8)*(Tenants!$I$6:$I$105<=DATE(Settings!$B$5,5,1)-1)*(Tenants!$J$6:$J$105>=DATE(Settings!$B$5,4,1)),0)),"")) | F8: =IF($A8="","",IFERROR(INDEX(Tenants!$B$6:$B$105,MATCH(1,(Tenants!$G$6:$G$105=$A8)*(Tenants!$I$6:$I$105<=DATE(Settings!$B$5,6,1)-1)*(Tenants!$J$6:$J$105>=DATE(Settings!$B$5,5,1)),0)),"")) | G8: =IF($A8="","",IFERROR(INDEX(Tenants!$B$6:$B$105,MATCH(1,(Tenants!$G$6:$G$105=$A8)*(Tenants!$I$6:$I$105<=DATE(Settings!$B$5,7,1)-1)*(Tenants!$J$6:$J$105>=DATE(Settings!$B$5,6,1)),0)),"")) | H8: =IF($A8="","",IFERROR(INDEX(Tenants!$B$6:$B$105,MATCH(1,(Tenants!$G$6:$G$105=$A8)*(Tenants!$I$6:$I$105<=DATE(Settings!$B$5,8,1)-1)*(Tenants!$J$6:$J$105>=DATE(Settings!$B$5,7,1)),0)),"")) | I8: =IF($A8="","",IFERROR(INDEX(Tenants!$B$6:$B$105,MATCH(1,(Tenants!$G$6:$G$105=$A8)*(Tenants!$I$6:$I$105<=DATE(Settings!$B$5,9,1)-1)*(Tenants!$J$6:$J$105>=DATE(Settings!$B$5,8,1)),0)),"")) | J8: =IF($A8="","",IFERROR(INDEX(Tenants!$B$6:$B$105,MATCH(1,(Tenants!$G$6:$G$105=$A8)*(Tenants!$I$6:$I$105<=DATE(Settings!$B$5,10,1)-1)*(Tenants!$J$6:$J$105>=DATE(Settings!$B$5,9,1)),0)),"")) | K8: =IF($A8="","",IFERROR(INDEX(Tenants!$B$6:$B$105,MATCH(1,(Tenants!$G$6:$G$105=$A8)*(Tenants!$I$6:$I$105<=DATE(Settings!$B$5,11,1)-1)*(Tenants!$J$6:$J$105>=DATE(Settings!$B$5,10,1)),0)),"")) | L8: =IF($A8="","",IFERROR(INDEX(Tenants!$B$6:$B$105,MATCH(1,(Tenants!$G$6:$G$105=$A8)*(Tenants!$I$6:$I$105<=DATE(Settings!$B$5,12,1)-1)*(Tenants!$J$6:$J$105>=DATE(Settings!$B$5,11,1)),0)),"")) | M8: =IF($A8="","",IFERROR(INDEX(Tenants!$B$6:$B$105,MATCH(1,(Tenants!$G$6:$G$105=$A8)*(Tenants!$I$6:$I$105<=DATE(Settings!$B$5+1,1,1)-1)*(Tenants!$J$6:$J$105>=DATE(Settings!$B$5,12,1)),0)),"")) | N8: =COUNTIF(B8:M8,"?*")
A9: =IF(Settings!$B$10="","",Settings!$B$10) | B9: =IF($A9="","",IFERROR(INDEX(Tenants!$B$6:$B$105,MATCH(1,(Tenants!$G$6:$G$105=$A9)*(Tenants!$I$6:$I$105<=DATE(Settings!$B$5,2,1)-1)*(Tenants!$J$6:$J$105>=DATE(Settings!$B$5,1,1)),0)),"")) | C9: =IF($A9="","",IFERROR(INDEX(Tenants!$B$6:$B$105,MATCH(1,(Tenants!$G$6:$G$105=$A9)*(Tenants!$I$6:$I$105<=DATE(Settings!$B$5,3,1)-1)*(Tenants!$J$6:$J$105>=DATE(Settings!$B$5,2,1)),0)),"")) | D9: =IF($A9="","",IFERROR(INDEX(Tenants!$B$6:$B$105,MATCH(1,(Tenants!$G$6:$G$105=$A9)*(Tenants!$I$6:$I$105<=DATE(Settings!$B$5,4,1)-1)*(Tenants!$J$6:$J$105>=DATE(Settings!$B$5,3,1)),0)),"")) | E9: =IF($A9="","",IFERROR(INDEX(Tenants!$B$6:$B$105,MATCH(1,(Tenants!$G$6:$G$105=$A9)*(Tenants!$I$6:$I$105<=DATE(Settings!$B$5,5,1)-1)*(Tenants!$J$6:$J$105>=DATE(Settings!$B$5,4,1)),0)),"")) | F9: =IF($A9="","",IFERROR(INDEX(Tenants!$B$6:$B$105,MATCH(1,(Tenants!$G$6:$G$105=$A9)*(Tenants!$I$6:$I$105<=DATE(Settings!$B$5,6,1)-1)*(Tenants!$J$6:$J$105>=DATE(Settings!$B$5,5,1)),0)),"")) | G9: =IF($A9="","",IFERROR(INDEX(Tenants!$B$6:$B$105,MATCH(1,(Tenants!$G$6:$G$105=$A9)*(Tenants!$I$6:$I$105<=DATE(Settings!$B$5,7,1)-1)*(Tenants!$J$6:$J$105>=DATE(Settings!$B$5,6,1)),0)),"")) | H9: =IF($A9="","",IFERROR(INDEX(Tenants!$B$6:$B$105,MATCH(1,(Tenants!$G$6:$G$105=$A9)*(Tenants!$I$6:$I$105<=DATE(Settings!$B$5,8,1)-1)*(Tenants!$J$6:$J$105>=DATE(Settings!$B$5,7,1)),0)),"")) | I9: =IF($A9="","",IFERROR(INDEX(Tenants!$B$6:$B$105,MATCH(1,(Tenants!$G$6:$G$105=$A9)*(Tenants!$I$6:$I$105<=DATE(Settings!$B$5,9,1)-1)*(Tenants!$J$6:$J$105>=DATE(Settings!$B$5,8,1)),0)),"")) | J9: =IF($A9="","",IFERROR(INDEX(Tenants!$B$6:$B$105,MATCH(1,(Tenants!$G$6:$G$105=$A9)*(Tenants!$I$6:$I$105<=DATE(Settings!$B$5,10,1)-1)*(Tenants!$J$6:$J$105>=DATE(Settings!$B$5,9,1)),0)),"")) | K9: =IF($A9="","",IFERROR(INDEX(Tenants!$B$6:$B$105,MATCH(1,(Tenants!$G$6:$G$105=$A9)*(Tenants!$I$6:$I$105<=DATE(Settings!$B$5,11,1)-1)*(Tenants!$J$6:$J$105>=DATE(Settings!$B$5,10,1)),0)),"")) | L9: =IF($A9="","",IFERROR(INDEX(Tenants!$B$6:$B$105,MATCH(1,(Tenants!$G$6:$G$105=$A9)*(Tenants!$I$6:$I$105<=DATE(Settings!$B$5,12,1)-1)*(Tenants!$J$6:$J$105>=DATE(Settings!$B$5,11,1)),0)),"")) | M9: =IF($A9="","",IFERROR(INDEX(Tenants!$B$6:$B$105,MATCH(1,(Tenants!$G$6:$G$105=$A9)*(Tenants!$I$6:$I$105<=DATE(Settings!$B$5+1,1,1)-1)*(Tenants!$J$6:$J$105>=DATE(Settings!$B$5,12,1)),0)),"")) | N9: =COUNTIF(B9:M9,"?*")
A10: =IF(Settings!$B$11="","",Settings!$B$11) | B10: =IF($A10="","",IFERROR(INDEX(Tenants!$B$6:$B$105,MATCH(1,(Tenants!$G$6:$G$105=$A10)*(Tenants!$I$6:$I$105<=DATE(Settings!$B$5,2,1)-1)*(Tenants!$J$6:$J$105>=DATE(Settings!$B$5,1,1)),0)),"")) | C10: =IF($A10="","",IFERROR(INDEX(Tenants!$B$6:$B$105,MATCH(1,(Tenants!$G$6:$G$105=$A10)*(Tenants!$I$6:$I$105<=DATE(Settings!$B$5,3,1)-1)*(Tenants!$J$6:$J$105>=DATE(Settings!$B$5,2,1)),0)),"")) | D10: =IF($A10="","",IFERROR(INDEX(Tenants!$B$6:$B$105,MATCH(1,(Tenants!$G$6:$G$105=$A10)*(Tenants!$I$6:$I$105<=DATE(Settings!$B$5,4,1)-1)*(Tenants!$J$6:$J$105>=DATE(Settings!$B$5,3,1)),0)),"")) | E10: =IF($A10="","",IFERROR(INDEX(Tenants!$B$6:$B$105,MATCH(1,(Tenants!$G$6:$G$105=$A10)*(Tenants!$I$6:$I$105<=DATE(Settings!$B$5,5,1)-1)*(Tenants!$J$6:$J$105>=DATE(Settings!$B$5,4,1)),0)),"")) | F10: =IF($A10="","",IFERROR(INDEX(Tenants!$B$6:$B$105,MATCH(1,(Tenants!$G$6:$G$105=$A10)*(Tenants!$I$6:$I$105<=DATE(Settings!$B$5,6,1)-1)*(Tenants!$J$6:$J$105>=DATE(Settings!$B$5,5,1)),0)),"")) | G10: =IF($A10="","",IFERROR(INDEX(Tenants!$B$6:$B$105,MATCH(1,(Tenants!$G$6:$G$105=$A10)*(Tenants!$I$6:$I$105<=DATE(Settings!$B$5,7,1)-1)*(Tenants!$J$6:$J$105>=DATE(Settings!$B$5,6,1)),0)),"")) | H10: =IF($A10="","",IFERROR(INDEX(Tenants!$B$6:$B$105,MATCH(1,(Tenants!$G$6:$G$105=$A10)*(Tenants!$I$6:$I$105<=DATE(Settings!$B$5,8,1)-1)*(Tenants!$J$6:$J$105>=DATE(Settings!$B$5,7,1)),0)),"")) | I10: =IF($A10="","",IFERROR(INDEX(Tenants!$B$6:$B$105,MATCH(1,(Tenants!$G$6:$G$105=$A10)*(Tenants!$I$6:$I$105<=DATE(Settings!$B$5,9,1)-1)*(Tenants!$J$6:$J$105>=DATE(Settings!$B$5,8,1)),0)),"")) | J10: =IF($A10="","",IFERROR(INDEX(Tenants!$B$6:$B$105,MATCH(1,(Tenants!$G$6:$G$105=$A10)*(Tenants!$I$6:$I$105<=DATE(Settings!$B$5,10,1)-1)*(Tenants!$J$6:$J$105>=DATE(Settings!$B$5,9,1)),0)),"")) | K10: =IF($A10="","",IFERROR(INDEX(Tenants!$B$6:$B$105,MATCH(1,(Tenants!$G$6:$G$105=$A10)*(Tenants!$I$6:$I$105<=DATE(Settings!$B$5,11,1)-1)*(Tenants!$J$6:$J$105>=DATE(Settings!$B$5,10,1)),0)),"")) | L10: =IF($A10="","",IFERROR(INDEX(Tenants!$B$6:$B$105,MATCH(1,(Tenants!$G$6:$G$105=$A10)*(Tenants!$I$6:$I$105<=DATE(Settings!$B$5,12,1)-1)*(Tenants!$J$6:$J$105>=DATE(Settings!$B$5,11,1)),0)),"")) | M10: =IF($A10="","",IFERROR(INDEX(Tenants!$B$6:$B$105,MATCH(1,(Tenants!$G$6:$G$105=$A10)*(Tenants!$I$6:$I$105<=DATE(Settings!$B$5+1,1,1)-1)*(Tenants!$J$6:$J$105>=DATE(Settings!$B$5,12,1)),0)),"")) | N10: =COUNTIF(B10:M10,"?*")
A11: =IF(Settings!$B$12="","",Settings!$B$12) | B11: =IF($A11="","",IFERROR(INDEX(Tenants!$B$6:$B$105,MATCH(1,(Tenants!$G$6:$G$105=$A11)*(Tenants!$I$6:$I$105<=DATE(Settings!$B$5,2,1)-1)*(Tenants!$J$6:$J$105>=DATE(Settings!$B$5,1,1)),0)),"")) | C11: =IF($A11="","",IFERROR(INDEX(Tenants!$B$6:$B$105,MATCH(1,(Tenants!$G$6:$G$105=$A11)*(Tenants!$I$6:$I$105<=DATE(Settings!$B$5,3,1)-1)*(Tenants!$J$6:$J$105>=DATE(Settings!$B$5,2,1)),0)),"")) | D11: =IF($A11="","",IFERROR(INDEX(Tenants!$B$6:$B$105,MATCH(1,(Tenants!$G$6:$G$105=$A11)*(Tenants!$I$6:$I$105<=DATE(Settings!$B$5,4,1)-1)*(Tenants!$J$6:$J$105>=DATE(Settings!$B$5,3,1)),0)),"")) | E11: =IF($A11="","",IFERROR(INDEX(Tenants!$B$6:$B$105,MATCH(1,(Tenants!$G$6:$G$105=$A11)*(Tenants!$I$6:$I$105<=DATE(Settings!$B$5,5,1)-1)*(Tenants!$J$6:$J$105>=DATE(Settings!$B$5,4,1)),0)),"")) | F11: =IF($A11="","",IFERROR(INDEX(Tenants!$B$6:$B$105,MATCH(1,(Tenants!$G$6:$G$105=$A11)*(Tenants!$I$6:$I$105<=DATE(Settings!$B$5,6,1)-1)*(Tenants!$J$6:$J$105>=DATE(Settings!$B$5,5,1)),0)),"")) | G11: =IF($A11="","",IFERROR(INDEX(Tenants!$B$6:$B$105,MATCH(1,(Tenants!$G$6:$G$105=$A11)*(Tenants!$I$6:$I$105<=DATE(Settings!$B$5,7,1)-1)*(Tenants!$J$6:$J$105>=DATE(Settings!$B$5,6,1)),0)),"")) | H11: =IF($A11="","",IFERROR(INDEX(Tenants!$B$6:$B$105,MATCH(1,(Tenants!$G$6:$G$105=$A11)*(Tenants!$I$6:$I$105<=DATE(Settings!$B$5,8,1)-1)*(Tenants!$J$6:$J$105>=DATE(Settings!$B$5,7,1)),0)),"")) | I11: =IF($A11="","",IFERROR(INDEX(Tenants!$B$6:$B$105,MATCH(1,(Tenants!$G$6:$G$105=$A11)*(Tenants!$I$6:$I$105<=DATE(Settings!$B$5,9,1)-1)*(Tenants!$J$6:$J$105>=DATE(Settings!$B$5,8,1)),0)),"")) | J11: =IF($A11="","",IFERROR(INDEX(Tenants!$B$6:$B$105,MATCH(1,(Tenants!$G$6:$G$105=$A11)*(Tenants!$I$6:$I$105<=DATE(Settings!$B$5,10,1)-1)*(Tenants!$J$6:$J$105>=DATE(Settings!$B$5,9,1)),0)),"")) | K11: =IF($A11="","",IFERROR(INDEX(Tenants!$B$6:$B$105,MATCH(1,(Tenants!$G$6:$G$105=$A11)*(Tenants!$I$6:$I$105<=DATE(Settings!$B$5,11,1)-1)*(Tenants!$J$6:$J$105>=DATE(Settings!$B$5,10,1)),0)),"")) | L11: =IF($A11="","",IFERROR(INDEX(Tenants!$B$6:$B$105,MATCH(1,(Tenants!$G$6:$G$105=$A11)*(Tenants!$I$6:$I$105<=DATE(Settings!$B$5,12,1)-1)*(Tenants!$J$6:$J$105>=DATE(Settings!$B$5,11,1)),0)),"")) | M11: =IF($A11="","",IFERROR(INDEX(Tenants!$B$6:$B$105,MATCH(1,(Tenants!$G$6:$G$105=$A11)*(Tenants!$I$6:$I$105<=DATE(Settings!$B$5+1,1,1)-1)*(Tenants!$J$6:$J$105>=DATE(Settings!$B$5,12,1)),0)),"")) | N11: =COUNTIF(B11:M11,"?*")
A12: =IF(Settings!$B$13="","",Settings!$B$13) | B12: =IF($A12="","",IFERROR(INDEX(Tenants!$B$6:$B$105,MATCH(1,(Tenants!$G$6:$G$105=$A12)*(Tenants!$I$6:$I$105<=DATE(Settings!$B$5,2,1)-1)*(Tenants!$J$6:$J$105>=DATE(Settings!$B$5,1,1)),0)),"")) | C12: =IF($A12="","",IFERROR(INDEX(Tenants!$B$6:$B$105,MATCH(1,(Tenants!$G$6:$G$105=$A12)*(Tenants!$I$6:$I$105<=DATE(Settings!$B$5,3,1)-1)*(Tenants!$J$6:$J$105>=DATE(Settings!$B$5,2,1)),0)),"")) | D12: =IF($A12="","",IFERROR(INDEX(Tenants!$B$6:$B$105,MATCH(1,(Tenants!$G$6:$G$105=$A12)*(Tenants!$I$6:$I$105<=DATE(Settings!$B$5,4,1)-1)*(Tenants!$J$6:$J$105>=DATE(Settings!$B$5,3,1)),0)),"")) | E12: =IF($A12="","",IFERROR(INDEX(Tenants!$B$6:$B$105,MATCH(1,(Tenants!$G$6:$G$105=$A12)*(Tenants!$I$6:$I$105<=DATE(Settings!$B$5,5,1)-1)*(Tenants!$J$6:$J$105>=DATE(Settings!$B$5,4,1)),0)),"")) | F12: =IF($A12="","",IFERROR(INDEX(Tenants!$B$6:$B$105,MATCH(1,(Tenants!$G$6:$G$105=$A12)*(Tenants!$I$6:$I$105<=DATE(Settings!$B$5,6,1)-1)*(Tenants!$J$6:$J$105>=DATE(Settings!$B$5,5,1)),0)),"")) | G12: =IF($A12="","",IFERROR(INDEX(Tenants!$B$6:$B$105,MATCH(1,(Tenants!$G$6:$G$105=$A12)*(Tenants!$I$6:$I$105<=DATE(Settings!$B$5,7,1)-1)*(Tenants!$J$6:$J$105>=DATE(Settings!$B$5,6,1)),0)),"")) | H12: =IF($A12="","",IFERROR(INDEX(Tenants!$B$6:$B$105,MATCH(1,(Tenants!$G$6:$G$105=$A12)*(Tenants!$I$6:$I$105<=DATE(Settings!$B$5,8,1)-1)*(Tenants!$J$6:$J$105>=DATE(Settings!$B$5,7,1)),0)),"")) | I12: =IF($A12="","",IFERROR(INDEX(Tenants!$B$6:$B$105,MATCH(1,(Tenants!$G$6:$G$105=$A12)*(Tenants!$I$6:$I$105<=DATE(Settings!$B$5,9,1)-1)*(Tenants!$J$6:$J$105>=DATE(Settings!$B$5,8,1)),0)),"")) | J12: =IF($A12="","",IFERROR(INDEX(Tenants!$B$6:$B$105,MATCH(1,(Tenants!$G$6:$G$105=$A12)*(Tenants!$I$6:$I$105<=DATE(Settings!$B$5,10,1)-1)*(Tenants!$J$6:$J$105>=DATE(Settings!$B$5,9,1)),0)),"")) | K12: =IF($A12="","",IFERROR(INDEX(Tenants!$B$6:$B$105,MATCH(1,(Tenants!$G$6:$G$105=$A12)*(Tenants!$I$6:$I$105<=DATE(Settings!$B$5,11,1)-1)*(Tenants!$J$6:$J$105>=DATE(Settings!$B$5,10,1)),0)),"")) | L12: =IF($A12="","",IFERROR(INDEX(Tenants!$B$6:$B$105,MATCH(1,(Tenants!$G$6:$G$105=$A12)*(Tenants!$I$6:$I$105<=DATE(Settings!$B$5,12,1)-1)*(Tenants!$J$6:$J$105>=DATE(Settings!$B$5,11,1)),0)),"")) | M12: =IF($A12="","",IFERROR(INDEX(Tenants!$B$6:$B$105,MATCH(1,(Tenants!$G$6:$G$105=$A12)*(Tenants!$I$6:$I$105<=DATE(Settings!$B$5+1,1,1)-1)*(Tenants!$J$6:$J$105>=DATE(Settings!$B$5,12,1)),0)),"")) | N12: =COUNTIF(B12:M12,"?*")
A13: =IF(Settings!$B$14="","",Settings!$B$14) | B13: =IF($A13="","",IFERROR(INDEX(Tenants!$B$6:$B$105,MATCH(1,(Tenants!$G$6:$G$105=$A13)*(Tenants!$I$6:$I$105<=DATE(Settings!$B$5,2,1)-1)*(Tenants!$J$6:$J$105>=DATE(Settings!$B$5,1,1)),0)),"")) | C13: =IF($A13="","",IFERROR(INDEX(Tenants!$B$6:$B$105,MATCH(1,(Tenants!$G$6:$G$105=$A13)*(Tenants!$I$6:$I$105<=DATE(Settings!$B$5,3,1)-1)*(Tenants!$J$6:$J$105>=DATE(Settings!$B$5,2,1)),0)),"")) | D13: =IF($A13="","",IFERROR(INDEX(Tenants!$B$6:$B$105,MATCH(1,(Tenants!$G$6:$G$105=$A13)*(Tenants!$I$6:$I$105<=DATE(Settings!$B$5,4,1)-1)*(Tenants!$J$6:$J$105>=DATE(Settings!$B$5,3,1)),0)),"")) | E13: =IF($A13="","",IFERROR(INDEX(Tenants!$B$6:$B$105,MATCH(1,(Tenants!$G$6:$G$105=$A13)*(Tenants!$I$6:$I$105<=DATE(Settings!$B$5,5,1)-1)*(Tenants!$J$6:$J$105>=DATE(Settings!$B$5,4,1)),0)),"")) | F13: =IF($A13="","",IFERROR(INDEX(Tenants!$B$6:$B$105,MATCH(1,(Tenants!$G$6:$G$105=$A13)*(Tenants!$I$6:$I$105<=DATE(Settings!$B$5,6,1)-1)*(Tenants!$J$6:$J$105>=DATE(Settings!$B$5,5,1)),0)),"")) | G13: =IF($A13="","",IFERROR(INDEX(Tenants!$B$6:$B$105,MATCH(1,(Tenants!$G$6:$G$105=$A13)*(Tenants!$I$6:$I$105<=DATE(Settings!$B$5,7,1)-1)*(Tenants!$J$6:$J$105>=DATE(Settings!$B$5,6,1)),0)),"")) | H13: =IF($A13="","",IFERROR(INDEX(Tenants!$B$6:$B$105,MATCH(1,(Tenants!$G$6:$G$105=$A13)*(Tenants!$I$6:$I$105<=DATE(Settings!$B$5,8,1)-1)*(Tenants!$J$6:$J$105>=DATE(Settings!$B$5,7,1)),0)),"")) | I13: =IF($A13="","",IFERROR(INDEX(Tenants!$B$6:$B$105,MATCH(1,(Tenants!$G$6:$G$105=$A13)*(Tenants!$I$6:$I$105<=DATE(Settings!$B$5,9,1)-1)*(Tenants!$J$6:$J$105>=DATE(Settings!$B$5,8,1)),0)),"")) | J13: =IF($A13="","",IFERROR(INDEX(Tenants!$B$6:$B$105,MATCH(1,(Tenants!$G$6:$G$105=$A13)*(Tenants!$I$6:$I$105<=DATE(Settings!$B$5,10,1)-1)*(Tenants!$J$6:$J$105>=DATE(Settings!$B$5,9,1)),0)),"")) | K13: =IF($A13="","",IFERROR(INDEX(Tenants!$B$6:$B$105,MATCH(1,(Tenants!$G$6:$G$105=$A13)*(Tenants!$I$6:$I$105<=DATE(Settings!$B$5,11,1)-1)*(Tenants!$J$6:$J$105>=DATE(Settings!$B$5,10,1)),0)),"")) | L13: =IF($A13="","",IFERROR(INDEX(Tenants!$B$6:$B$105,MATCH(1,(Tenants!$G$6:$G$105=$A13)*(Tenants!$I$6:$I$105<=DATE(Settings!$B$5,12,1)-1)*(Tenants!$J$6:$J$105>=DATE(Settings!$B$5,11,1)),0)),"")) | M13: =IF($A13="","",IFERROR(INDEX(Tenants!$B$6:$B$105,MATCH(1,(Tenants!$G$6:$G$105=$A13)*(Tenants!$I$6:$I$105<=DATE(Settings!$B$5+1,1,1)-1)*(Tenants!$J$6:$J$105>=DATE(Settings!$B$5,12,1)),0)),"")) | N13: =COUNTIF(B13:M13,"?*")
A14: =IF(Settings!$B$15="","",Settings!$B$15) | B14: =IF($A14="","",IFERROR(INDEX(Tenants!$B$6:$B$105,MATCH(1,(Tenants!$G$6:$G$105=$A14)*(Tenants!$I$6:$I$105<=DATE(Settings!$B$5,2,1)-1)*(Tenants!$J$6:$J$105>=DATE(Settings!$B$5,1,1)),0)),"")) | C14: =IF($A14="","",IFERROR(INDEX(Tenants!$B$6:$B$105,MATCH(1,(Tenants!$G$6:$G$105=$A14)*(Tenants!$I$6:$I$105<=DATE(Settings!$B$5,3,1)-1)*(Tenants!$J$6:$J$105>=DATE(Settings!$B$5,2,1)),0)),"")) | D14: =IF($A14="","",IFERROR(INDEX(Tenants!$B$6:$B$105,MATCH(1,(Tenants!$G$6:$G$105=$A14)*(Tenants!$I$6:$I$105<=DATE(Settings!$B$5,4,1)-1)*(Tenants!$J$6:$J$105>=DATE(Settings!$B$5,3,1)),0)),"")) | E14: =IF($A14="","",IFERROR(INDEX(Tenants!$B$6:$B$105,MATCH(1,(Tenants!$G$6:$G$105=$A14)*(Tenants!$I$6:$I$105<=DATE(Settings!$B$5,5,1)-1)*(Tenants!$J$6:$J$105>=DATE(Settings!$B$5,4,1)),0)),"")) | F14: =IF($A14="","",IFERROR(INDEX(Tenants!$B$6:$B$105,MATCH(1,(Tenants!$G$6:$G$105=$A14)*(Tenants!$I$6:$I$105<=DATE(Settings!$B$5,6,1)-1)*(Tenants!$J$6:$J$105>=DATE(Settings!$B$5,5,1)),0)),"")) | G14: =IF($A14="","",IFERROR(INDEX(Tenants!$B$6:$B$105,MATCH(1,(Tenants!$G$6:$G$105=$A14)*(Tenants!$I$6:$I$105<=DATE(Settings!$B$5,7,1)-1)*(Tenants!$J$6:$J$105>=DATE(Settings!$B$5,6,1)),0)),"")) | H14: =IF($A14="","",IFERROR(INDEX(Tenants!$B$6:$B$105,MATCH(1,(Tenants!$G$6:$G$105=$A14)*(Tenants!$I$6:$I$105<=DATE(Settings!$B$5,8,1)-1)*(Tenants!$J$6:$J$105>=DATE(Settings!$B$5,7,1)),0)),"")) | I14: =IF($A14="","",IFERROR(INDEX(Tenants!$B$6:$B$105,MATCH(1,(Tenants!$G$6:$G$105=$A14)*(Tenants!$I$6:$I$105<=DATE(Settings!$B$5,9,1)-1)*(Tenants!$J$6:$J$105>=DATE(Settings!$B$5,8,1)),0)),"")) | J14: =IF($A14="","",IFERROR(INDEX(Tenants!$B$6:$B$105,MATCH(1,(Tenants!$G$6:$G$105=$A14)*(Tenants!$I$6:$I$105<=DATE(Settings!$B$5,10,1)-1)*(Tenants!$J$6:$J$105>=DATE(Settings!$B$5,9,1)),0)),"")) | K14: =IF($A14="","",IFERROR(INDEX(Tenants!$B$6:$B$105,MATCH(1,(Tenants!$G$6:$G$105=$A14)*(Tenants!$I$6:$I$105<=DATE(Settings!$B$5,11,1)-1)*(Tenants!$J$6:$J$105>=DATE(Settings!$B$5,10,1)),0)),"")) | L14: =IF($A14="","",IFERROR(INDEX(Tenants!$B$6:$B$105,MATCH(1,(Tenants!$G$6:$G$105=$A14)*(Tenants!$I$6:$I$105<=DATE(Settings!$B$5,12,1)-1)*(Tenants!$J$6:$J$105>=DATE(Settings!$B$5,11,1)),0)),"")) | M14: =IF($A14="","",IFERROR(INDEX(Tenants!$B$6:$B$105,MATCH(1,(Tenants!$G$6:$G$105=$A14)*(Tenants!$I$6:$I$105<=DATE(Settings!$B$5+1,1,1)-1)*(Tenants!$J$6:$J$105>=DATE(Settings!$B$5,12,1)),0)),"")) | N14: =COUNTIF(B14:M14,"?*")
A15: =IF(Settings!$B$16="","",Settings!$B$16) | B15: =IF($A15="","",IFERROR(INDEX(Tenants!$B$6:$B$105,MATCH(1,(Tenants!$G$6:$G$105=$A15)*(Tenants!$I$6:$I$105<=DATE(Settings!$B$5,2,1)-1)*(Tenants!$J$6:$J$105>=DATE(Settings!$B$5,1,1)),0)),"")) | C15: =IF($A15="","",IFERROR(INDEX(Tenants!$B$6:$B$105,MATCH(1,(Tenants!$G$6:$G$105=$A15)*(Tenants!$I$6:$I$105<=DATE(Settings!$B$5,3,1)-1)*(Tenants!$J$6:$J$105>=DATE(Settings!$B$5,2,1)),0)),"")) | D15: =IF($A15="","",IFERROR(INDEX(Tenants!$B$6:$B$105,MATCH(1,(Tenants!$G$6:$G$105=$A15)*(Tenants!$I$6:$I$105<=DATE(Settings!$B$5,4,1)-1)*(Tenants!$J$6:$J$105>=DATE(Settings!$B$5,3,1)),0)),"")) | E15: =IF($A15="","",IFERROR(INDEX(Tenants!$B$6:$B$105,MATCH(1,(Tenants!$G$6:$G$105=$A15)*(Tenants!$I$6:$I$105<=DATE(Settings!$B$5,5,1)-1)*(Tenants!$J$6:$J$105>=DATE(Settings!$B$5,4,1)),0)),"")) | F15: =IF($A15="","",IFERROR(INDEX(Tenants!$B$6:$B$105,MATCH(1,(Tenants!$G$6:$G$105=$A15)*(Tenants!$I$6:$I$105<=DATE(Settings!$B$5,6,1)-1)*(Tenants!$J$6:$J$105>=DATE(Settings!$B$5,5,1)),0)),"")) | G15: =IF($A15="","",IFERROR(INDEX(Tenants!$B$6:$B$105,MATCH(1,(Tenants!$G$6:$G$105=$A15)*(Tenants!$I$6:$I$105<=DATE(Settings!$B$5,7,1)-1)*(Tenants!$J$6:$J$105>=DATE(Settings!$B$5,6,1)),0)),"")) | H15: =IF($A15="","",IFERROR(INDEX(Tenants!$B$6:$B$105,MATCH(1,(Tenants!$G$6:$G$105=$A15)*(Tenants!$I$6:$I$105<=DATE(Settings!$B$5,8,1)-1)*(Tenants!$J$6:$J$105>=DATE(Settings!$B$5,7,1)),0)),"")) | I15: =IF($A15="","",IFERROR(INDEX(Tenants!$B$6:$B$105,MATCH(1,(Tenants!$G$6:$G$105=$A15)*(Tenants!$I$6:$I$105<=DATE(Settings!$B$5,9,1)-1)*(Tenants!$J$6:$J$105>=DATE(Settings!$B$5,8,1)),0)),"")) | J15: =IF($A15="","",IFERROR(INDEX(Tenants!$B$6:$B$105,MATCH(1,(Tenants!$G$6:$G$105=$A15)*(Tenants!$I$6:$I$105<=DATE(Settings!$B$5,10,1)-1)*(Tenants!$J$6:$J$105>=DATE(Settings!$B$5,9,1)),0)),"")) | K15: =IF($A15="","",IFERROR(INDEX(Tenants!$B$6:$B$105,MATCH(1,(Tenants!$G$6:$G$105=$A15)*(Tenants!$I$6:$I$105<=DATE(Settings!$B$5,11,1)-1)*(Tenants!$J$6:$J$105>=DATE(Settings!$B$5,10,1)),0)),"")) | L15: =IF($A15="","",IFERROR(INDEX(Tenants!$B$6:$B$105,MATCH(1,(Tenants!$G$6:$G$105=$A15)*(Tenants!$I$6:$I$105<=DATE(Settings!$B$5,12,1)-1)*(Tenants!$J$6:$J$105>=DATE(Settings!$B$5,11,1)),0)),"")) | M15: =IF($A15="","",IFERROR(INDEX(Tenants!$B$6:$B$105,MATCH(1,(Tenants!$G$6:$G$105=$A15)*(Tenants!$I$6:$I$105<=DATE(Settings!$B$5+1,1,1)-1)*(Tenants!$J$6:$J$105>=DATE(Settings!$B$5,12,1)),0)),"")) | N15: =COUNTIF(B15:M15,"?*")
A18: Legend: GREEN cell = occupied month (tenant name shown) · RED cell = gap month (no tenant covers this month — backfill or raise on Pipeline tab)
A20: ="Showing year "&Settings!$B$5&". Change Active Year on Settings to switch the calendar to a different year."

Sheet Monthly Revenue
A2: =HYPERLINK("#'Lease Calendar'!A1", "← BACK") | D2: MONTHLY REVENUE | J2: =HYPERLINK("#'Pipeline'!A1", "NEXT →")
A4: Per-property monthly rent collected — bump Active Year on Settings to switch.
A5: Property | B5: Jan | C5: Feb | D5: Mar | E5: Apr | F5: May | G5: Jun | H5: Jul | I5: Aug | J5: Sep | K5: Oct | L5: Nov | M5: Dec | N5: YTD
A6: =IF(Settings!$B$7="","",Settings!$B$7) | B6: =IF($A6="","",SUMPRODUCT((Tenants!$G$6:$G$105=$A6)*(Tenants!$I$6:$I$105<=DATE(Settings!$B$5,2,1)-1)*(Tenants!$J$6:$J$105>=DATE(Settings!$B$5,1,1))*Tenants!$K$6:$K$105)) | C6: =IF($A6="","",SUMPRODUCT((Tenants!$G$6:$G$105=$A6)*(Tenants!$I$6:$I$105<=DATE(Settings!$B$5,3,1)-1)*(Tenants!$J$6:$J$105>=DATE(Settings!$B$5,2,1))*Tenants!$K$6:$K$105)) | D6: =IF($A6="","",SUMPRODUCT((Tenants!$G$6:$G$105=$A6)*(Tenants!$I$6:$I$105<=DATE(Settings!$B$5,4,1)-1)*(Tenants!$J$6:$J$105>=DATE(Settings!$B$5,3,1))*Tenants!$K$6:$K$105)) | E6: =IF($A6="","",SUMPRODUCT((Tenants!$G$6:$G$105=$A6)*(Tenants!$I$6:$I$105<=DATE(Settings!$B$5,5,1)-1)*(Tenants!$J$6:$J$105>=DATE(Settings!$B$5,4,1))*Tenants!$K$6:$K$105)) | F6: =IF($A6="","",SUMPRODUCT((Tenants!$G$6:$G$105=$A6)*(Tenants!$I$6:$I$105<=DATE(Settings!$B$5,6,1)-1)*(Tenants!$J$6:$J$105>=DATE(Settings!$B$5,5,1))*Tenants!$K$6:$K$105)) | G6: =IF($A6="","",SUMPRODUCT((Tenants!$G$6:$G$105=$A6)*(Tenants!$I$6:$I$105<=DATE(Settings!$B$5,7,1)-1)*(Tenants!$J$6:$J$105>=DATE(Settings!$B$5,6,1))*Tenants!$K$6:$K$105)) | H6: =IF($A6="","",SUMPRODUCT((Tenants!$G$6:$G$105=$A6)*(Tenants!$I$6:$I$105<=DATE(Settings!$B$5,8,1)-1)*(Tenants!$J$6:$J$105>=DATE(Settings!$B$5,7,1))*Tenants!$K$6:$K$105)) | I6: =IF($A6="","",SUMPRODUCT((Tenants!$G$6:$G$105=$A6)*(Tenants!$I$6:$I$105<=DATE(Settings!$B$5,9,1)-1)*(Tenants!$J$6:$J$105>=DATE(Settings!$B$5,8,1))*Tenants!$K$6:$K$105)) | J6: =IF($A6="","",SUMPRODUCT((Tenants!$G$6:$G$105=$A6)*(Tenants!$I$6:$I$105<=DATE(Settings!$B$5,10,1)-1)*(Tenants!$J$6:$J$105>=DATE(Settings!$B$5,9,1))*Tenants!$K$6:$K$105)) | K6: =IF($A6="","",SUMPRODUCT((Tenants!$G$6:$G$105=$A6)*(Tenants!$I$6:$I$105<=DATE(Settings!$B$5,11,1)-1)*(Tenants!$J$6:$J$105>=DATE(Settings!$B$5,10,1))*Tenants!$K$6:$K$105)) | L6: =IF($A6="","",SUMPRODUCT((Tenants!$G$6:$G$105=$A6)*(Tenants!$I$6:$I$105<=DATE(Settings!$B$5,12,1)-1)*(Tenants!$J$6:$J$105>=DATE(Settings!$B$5,11,1))*Tenants!$K$6:$K$105)) | M6: =IF($A6="","",SUMPRODUCT((Tenants!$G$6:$G$105=$A6)*(Tenants!$I$6:$I$105<=DATE(Settings!$B$5+1,1,1)-1)*(Tenants!$J$6:$J$105>=DATE(Settings!$B$5,12,1))*Tenants!$K$6:$K$105)) | N6: =IF($A6="","",SUM(B6:M6))
A7: =IF(Settings!$B$8="","",Settings!$B$8) | B7: =IF($A7="","",SUMPRODUCT((Tenants!$G$6:$G$105=$A7)*(Tenants!$I$6:$I$105<=DATE(Settings!$B$5,2,1)-1)*(Tenants!$J$6:$J$105>=DATE(Settings!$B$5,1,1))*Tenants!$K$6:$K$105)) | C7: =IF($A7="","",SUMPRODUCT((Tenants!$G$6:$G$105=$A7)*(Tenants!$I$6:$I$105<=DATE(Settings!$B$5,3,1)-1)*(Tenants!$J$6:$J$105>=DATE(Settings!$B$5,2,1))*Tenants!$K$6:$K$105)) | D7: =IF($A7="","",SUMPRODUCT((Tenants!$G$6:$G$105=$A7)*(Tenants!$I$6:$I$105<=DATE(Settings!$B$5,4,1)-1)*(Tenants!$J$6:$J$105>=DATE(Settings!$B$5,3,1))*Tenants!$K$6:$K$105)) | E7: =IF($A7="","",SUMPRODUCT((Tenants!$G$6:$G$105=$A7)*(Tenants!$I$6:$I$105<=DATE(Settings!$B$5,5,1)-1)*(Tenants!$J$6:$J$105>=DATE(Settings!$B$5,4,1))*Tenants!$K$6:$K$105)) | F7: =IF($A7="","",SUMPRODUCT((Tenants!$G$6:$G$105=$A7)*(Tenants!$I$6:$I$105<=DATE(Settings!$B$5,6,1)-1)*(Tenants!$J$6:$J$105>=DATE(Settings!$B$5,5,1))*Tenants!$K$6:$K$105)) | G7: =IF($A7="","",SUMPRODUCT((Tenants!$G$6:$G$105=$A7)*(Tenants!$I$6:$I$105<=DATE(Settings!$B$5,7,1)-1)*(Tenants!$J$6:$J$105>=DATE(Settings!$B$5,6,1))*Tenants!$K$6:$K$105)) | H7: =IF($A7="","",SUMPRODUCT((Tenants!$G$6:$G$105=$A7)*(Tenants!$I$6:$I$105<=DATE(Settings!$B$5,8,1)-1)*(Tenants!$J$6:$J$105>=DATE(Settings!$B$5,7,1))*Tenants!$K$6:$K$105)) | I7: =IF($A7="","",SUMPRODUCT((Tenants!$G$6:$G$105=$A7)*(Tenants!$I$6:$I$105<=DATE(Settings!$B$5,9,1)-1)*(Tenants!$J$6:$J$105>=DATE(Settings!$B$5,8,1))*Tenants!$K$6:$K$105)) | J7: =IF($A7="","",SUMPRODUCT((Tenants!$G$6:$G$105=$A7)*(Tenants!$I$6:$I$105<=DATE(Settings!$B$5,10,1)-1)*(Tenants!$J$6:$J$105>=DATE(Settings!$B$5,9,1))*Tenants!$K$6:$K$105)) | K7: =IF($A7="","",SUMPRODUCT((Tenants!$G$6:$G$105=$A7)*(Tenants!$I$6:$I$105<=DATE(Settings!$B$5,11,1)-1)*(Tenants!$J$6:$J$105>=DATE(Settings!$B$5,10,1))*Tenants!$K$6:$K$105)) | L7: =IF($A7="","",SUMPRODUCT((Tenants!$G$6:$G$105=$A7)*(Tenants!$I$6:$I$105<=DATE(Settings!$B$5,12,1)-1)*(Tenants!$J$6:$J$105>=DATE(Settings!$B$5,11,1))*Tenants!$K$6:$K$105)) | M7: =IF($A7="","",SUMPRODUCT((Tenants!$G$6:$G$105=$A7)*(Tenants!$I$6:$I$105<=DATE(Settings!$B$5+1,1,1)-1)*(Tenants!$J$6:$J$105>=DATE(Settings!$B$5,12,1))*Tenants!$K$6:$K$105)) | N7: =IF($A7="","",SUM(B7:M7))
A8: =IF(Settings!$B$9="","",Settings!$B$9) | B8: =IF($A8="","",SUMPRODUCT((Tenants!$G$6:$G$105=$A8)*(Tenants!$I$6:$I$105<=DATE(Settings!$B$5,2,1)-1)*(Tenants!$J$6:$J$105>=DATE(Settings!$B$5,1,1))*Tenants!$K$6:$K$105)) | C8: =IF($A8="","",SUMPRODUCT((Tenants!$G$6:$G$105=$A8)*(Tenants!$I$6:$I$105<=DATE(Settings!$B$5,3,1)-1)*(Tenants!$J$6:$J$105>=DATE(Settings!$B$5,2,1))*Tenants!$K$6:$K$105)) | D8: =IF($A8="","",SUMPRODUCT((Tenants!$G$6:$G$105=$A8)*(Tenants!$I$6:$I$105<=DATE(Settings!$B$5,4,1)-1)*(Tenants!$J$6:$J$105>=DATE(Settings!$B$5,3,1))*Tenants!$K$6:$K$105)) | E8: =IF($A8="","",SUMPRODUCT((Tenants!$G$6:$G$105=$A8)*(Tenants!$I$6:$I$105<=DATE(Settings!$B$5,5,1)-1)*(Tenants!$J$6:$J$105>=DATE(Settings!$B$5,4,1))*Tenants!$K$6:$K$105)) | F8: =IF($A8="","",SUMPRODUCT((Tenants!$G$6:$G$105=$A8)*(Tenants!$I$6:$I$105<=DATE(Settings!$B$5,6,1)-1)*(Tenants!$J$6:$J$105>=DATE(Settings!$B$5,5,1))*Tenants!$K$6:$K$105)) | G8: =IF($A8="","",SUMPRODUCT((Tenants!$G$6:$G$105=$A8)*(Tenants!$I$6:$I$105<=DATE(Settings!$B$5,7,1)-1)*(Tenants!$J$6:$J$105>=DATE(Settings!$B$5,6,1))*Tenants!$K$6:$K$105)) | H8: =IF($A8="","",SUMPRODUCT((Tenants!$G$6:$G$105=$A8)*(Tenants!$I$6:$I$105<=DATE(Settings!$B$5,8,1)-1)*(Tenants!$J$6:$J$105>=DATE(Settings!$B$5,7,1))*Tenants!$K$6:$K$105)) | I8: =IF($A8="","",SUMPRODUCT((Tenants!$G$6:$G$105=$A8)*(Tenants!$I$6:$I$105<=DATE(Settings!$B$5,9,1)-1)*(Tenants!$J$6:$J$105>=DATE(Settings!$B$5,8,1))*Tenants!$K$6:$K$105)) | J8: =IF($A8="","",SUMPRODUCT((Tenants!$G$6:$G$105=$A8)*(Tenants!$I$6:$I$105<=DATE(Settings!$B$5,10,1)-1)*(Tenants!$J$6:$J$105>=DATE(Settings!$B$5,9,1))*Tenants!$K$6:$K$105)) | K8: =IF($A8="","",SUMPRODUCT((Tenants!$G$6:$G$105=$A8)*(Tenants!$I$6:$I$105<=DATE(Settings!$B$5,11,1)-1)*(Tenants!$J$6:$J$105>=DATE(Settings!$B$5,10,1))*Tenants!$K$6:$K$105)) | L8: =IF($A8="","",SUMPRODUCT((Tenants!$G$6:$G$105=$A8)*(Tenants!$I$6:$I$105<=DATE(Settings!$B$5,12,1)-1)*(Tenants!$J$6:$J$105>=DATE(Settings!$B$5,11,1))*Tenants!$K$6:$K$105)) | M8: =IF($A8="","",SUMPRODUCT((Tenants!$G$6:$G$105=$A8)*(Tenants!$I$6:$I$105<=DATE(Settings!$B$5+1,1,1)-1)*(Tenants!$J$6:$J$105>=DATE(Settings!$B$5,12,1))*Tenants!$K$6:$K$105)) | N8: =IF($A8="","",SUM(B8:M8))
A9: =IF(Settings!$B$10="","",Settings!$B$10) | B9: =IF($A9="","",SUMPRODUCT((Tenants!$G$6:$G$105=$A9)*(Tenants!$I$6:$I$105<=DATE(Settings!$B$5,2,1)-1)*(Tenants!$J$6:$J$105>=DATE(Settings!$B$5,1,1))*Tenants!$K$6:$K$105)) | C9: =IF($A9="","",SUMPRODUCT((Tenants!$G$6:$G$105=$A9)*(Tenants!$I$6:$I$105<=DATE(Settings!$B$5,3,1)-1)*(Tenants!$J$6:$J$105>=DATE(Settings!$B$5,2,1))*Tenants!$K$6:$K$105)) | D9: =IF($A9="","",SUMPRODUCT((Tenants!$G$6:$G$105=$A9)*(Tenants!$I$6:$I$105<=DATE(Settings!$B$5,4,1)-1)*(Tenants!$J$6:$J$105>=DATE(Settings!$B$5,3,1))*Tenants!$K$6:$K$105)) | E9: =IF($A9="","",SUMPRODUCT((Tenants!$G$6:$G$105=$A9)*(Tenants!$I$6:$I$105<=DATE(Settings!$B$5,5,1)-1)*(Tenants!$J$6:$J$105>=DATE(Settings!$B$5,4,1))*Tenants!$K$6:$K$105)) | F9: =IF($A9="","",SUMPRODUCT((Tenants!$G$6:$G$105=$A9)*(Tenants!$I$6:$I$105<=DATE(Settings!$B$5,6,1)-1)*(Tenants!$J$6:$J$105>=DATE(Settings!$B$5,5,1))*Tenants!$K$6:$K$105)) | G9: =IF($A9="","",SUMPRODUCT((Tenants!$G$6:$G$105=$A9)*(Tenants!$I$6:$I$105<=DATE(Settings!$B$5,7,1)-1)*(Tenants!$J$6:$J$105>=DATE(Settings!$B$5,6,1))*Tenants!$K$6:$K$105)) | H9: =IF($A9="","",SUMPRODUCT((Tenants!$G$6:$G$105=$A9)*(Tenants!$I$6:$I$105<=DATE(Settings!$B$5,8,1)-1)*(Tenants!$J$6:$J$105>=DATE(Settings!$B$5,7,1))*Tenants!$K$6:$K$105)) | I9: =IF($A9="","",SUMPRODUCT((Tenants!$G$6:$G$105=$A9)*(Tenants!$I$6:$I$105<=DATE(Settings!$B$5,9,1)-1)*(Tenants!$J$6:$J$105>=DATE(Settings!$B$5,8,1))*Tenants!$K$6:$K$105)) | J9: =IF($A9="","",SUMPRODUCT((Tenants!$G$6:$G$105=$A9)*(Tenants!$I$6:$I$105<=DATE(Settings!$B$5,10,1)-1)*(Tenants!$J$6:$J$105>=DATE(Settings!$B$5,9,1))*Tenants!$K$6:$K$105)) | K9: =IF($A9="","",SUMPRODUCT((Tenants!$G$6:$G$105=$A9)*(Tenants!$I$6:$I$105<=DATE(Settings!$B$5,11,1)-1)*(Tenants!$J$6:$J$105>=DATE(Settings!$B$5,10,1))*Tenants!$K$6:$K$105)) | L9: =IF($A9="","",SUMPRODUCT((Tenants!$G$6:$G$105=$A9)*(Tenants!$I$6:$I$105<=DATE(Settings!$B$5,12,1)-1)*(Tenants!$J$6:$J$105>=DATE(Settings!$B$5,11,1))*Tenants!$K$6:$K$105)) | M9: =IF($A9="","",SUMPRODUCT((Tenants!$G$6:$G$105=$A9)*(Tenants!$I$6:$I$105<=DATE(Settings!$B$5+1,1,1)-1)*(Tenants!$J$6:$J$105>=DATE(Settings!$B$5,12,1))*Tenants!$K$6:$K$105)) | N9: =IF($A9="","",SUM(B9:M9))
A10: =IF(Settings!$B$11="","",Settings!$B$11) | B10: =IF($A10="","",SUMPRODUCT((Tenants!$G$6:$G$105=$A10)*(Tenants!$I$6:$I$105<=DATE(Settings!$B$5,2,1)-1)*(Tenants!$J$6:$J$105>=DATE(Settings!$B$5,1,1))*Tenants!$K$6:$K$105)) | C10: =IF($A10="","",SUMPRODUCT((Tenants!$G$6:$G$105=$A10)*(Tenants!$I$6:$I$105<=DATE(Settings!$B$5,3,1)-1)*(Tenants!$J$6:$J$105>=DATE(Settings!$B$5,2,1))*Tenants!$K$6:$K$105)) | D10: =IF($A10="","",SUMPRODUCT((Tenants!$G$6:$G$105=$A10)*(Tenants!$I$6:$I$105<=DATE(Settings!$B$5,4,1)-1)*(Tenants!$J$6:$J$105>=DATE(Settings!$B$5,3,1))*Tenants!$K$6:$K$105)) | E10: =IF($A10="","",SUMPRODUCT((Tenants!$G$6:$G$105=$A10)*(Tenants!$I$6:$I$105<=DATE(Settings!$B$5,5,1)-1)*(Tenants!$J$6:$J$105>=DATE(Settings!$B$5,4,1))*Tenants!$K$6:$K$105)) | F10: =IF($A10="","",SUMPRODUCT((Tenants!$G$6:$G$105=$A10)*(Tenants!$I$6:$I$105<=DATE(Settings!$B$5,6,1)-1)*(Tenants!$J$6:$J$105>=DATE(Settings!$B$5,5,1))*Tenants!$K$6:$K$105)) | G10: =IF($A10="","",SUMPRODUCT((Tenants!$G$6:$G$105=$A10)*(Tenants!$I$6:$I$105<=DATE(Settings!$B$5,7,1)-1)*(Tenants!$J$6:$J$105>=DATE(Settings!$B$5,6,1))*Tenants!$K$6:$K$105)) | H10: =IF($A10="","",SUMPRODUCT((Tenants!$G$6:$G$105=$A10)*(Tenants!$I$6:$I$105<=DATE(Settings!$B$5,8,1)-1)*(Tenants!$J$6:$J$105>=DATE(Settings!$B$5,7,1))*Tenants!$K$6:$K$105)) | I10: =IF($A10="","",SUMPRODUCT((Tenants!$G$6:$G$105=$A10)*(Tenants!$I$6:$I$105<=DATE(Settings!$B$5,9,1)-1)*(Tenants!$J$6:$J$105>=DATE(Settings!$B$5,8,1))*Tenants!$K$6:$K$105)) | J10: =IF($A10="","",SUMPRODUCT((Tenants!$G$6:$G$105=$A10)*(Tenants!$I$6:$I$105<=DATE(Settings!$B$5,10,1)-1)*(Tenants!$J$6:$J$105>=DATE(Settings!$B$5,9,1))*Tenants!$K$6:$K$105)) | K10: =IF($A10="","",SUMPRODUCT((Tenants!$G$6:$G$105=$A10)*(Tenants!$I$6:$I$105<=DATE(Settings!$B$5,11,1)-1)*(Tenants!$J$6:$J$105>=DATE(Settings!$B$5,10,1))*Tenants!$K$6:$K$105)) | L10: =IF($A10="","",SUMPRODUCT((Tenants!$G$6:$G$105=$A10)*(Tenants!$I$6:$I$105<=DATE(Settings!$B$5,12,1)-1)*(Tenants!$J$6:$J$105>=DATE(Settings!$B$5,11,1))*Tenants!$K$6:$K$105)) | M10: =IF($A10="","",SUMPRODUCT((Tenants!$G$6:$G$105=$A10)*(Tenants!$I$6:$I$105<=DATE(Settings!$B$5+1,1,1)-1)*(Tenants!$J$6:$J$105>=DATE(Settings!$B$5,12,1))*Tenants!$K$6:$K$105)) | N10: =IF($A10="","",SUM(B10:M10))
A11: =IF(Settings!$B$12="","",Settings!$B$12) | B11: =IF($A11="","",SUMPRODUCT((Tenants!$G$6:$G$105=$A11)*(Tenants!$I$6:$I$105<=DATE(Settings!$B$5,2,1)-1)*(Tenants!$J$6:$J$105>=DATE(Settings!$B$5,1,1))*Tenants!$K$6:$K$105)) | C11: =IF($A11="","",SUMPRODUCT((Tenants!$G$6:$G$105=$A11)*(Tenants!$I$6:$I$105<=DATE(Settings!$B$5,3,1)-1)*(Tenants!$J$6:$J$105>=DATE(Settings!$B$5,2,1))*Tenants!$K$6:$K$105)) | D11: =IF($A11="","",SUMPRODUCT((Tenants!$G$6:$G$105=$A11)*(Tenants!$I$6:$I$105<=DATE(Settings!$B$5,4,1)-1)*(Tenants!$J$6:$J$105>=DATE(Settings!$B$5,3,1))*Tenants!$K$6:$K$105)) | E11: =IF($A11="","",SUMPRODUCT((Tenants!$G$6:$G$105=$A11)*(Tenants!$I$6:$I$105<=DATE(Settings!$B$5,5,1)-1)*(Tenants!$J$6:$J$105>=DATE(Settings!$B$5,4,1))*Tenants!$K$6:$K$105)) | F11: =IF($A11="","",SUMPRODUCT((Tenants!$G$6:$G$105=$A11)*(Tenants!$I$6:$I$105<=DATE(Settings!$B$5,6,1)-1)*(Tenants!$J$6:$J$105>=DATE(Settings!$B$5,5,1))*Tenants!$K$6:$K$105)) | G11: =IF($A11="","",SUMPRODUCT((Tenants!$G$6:$G$105=$A11)*(Tenants!$I$6:$I$105<=DATE(Settings!$B$5,7,1)-1)*(Tenants!$J$6:$J$105>=DATE(Settings!$B$5,6,1))*Tenants!$K$6:$K$105)) | H11: =IF($A11="","",SUMPRODUCT((Tenants!$G$6:$G$105=$A11)*(Tenants!$I$6:$I$105<=DATE(Settings!$B$5,8,1)-1)*(Tenants!$J$6:$J$105>=DATE(Settings!$B$5,7,1))*Tenants!$K$6:$K$105)) | I11: =IF($A11="","",SUMPRODUCT((Tenants!$G$6:$G$105=$A11)*(Tenants!$I$6:$I$105<=DATE(Settings!$B$5,9,1)-1)*(Tenants!$J$6:$J$105>=DATE(Settings!$B$5,8,1))*Tenants!$K$6:$K$105)) | J11: =IF($A11="","",SUMPRODUCT((Tenants!$G$6:$G$105=$A11)*(Tenants!$I$6:$I$105<=DATE(Settings!$B$5,10,1)-1)*(Tenants!$J$6:$J$105>=DATE(Settings!$B$5,9,1))*Tenants!$K$6:$K$105)) | K11: =IF($A11="","",SUMPRODUCT((Tenants!$G$6:$G$105=$A11)*(Tenants!$I$6:$I$105<=DATE(Settings!$B$5,11,1)-1)*(Tenants!$J$6:$J$105>=DATE(Settings!$B$5,10,1))*Tenants!$K$6:$K$105)) | L11: =IF($A11="","",SUMPRODUCT((Tenants!$G$6:$G$105=$A11)*(Tenants!$I$6:$I$105<=DATE(Settings!$B$5,12,1)-1)*(Tenants!$J$6:$J$105>=DATE(Settings!$B$5,11,1))*Tenants!$K$6:$K$105)) | M11: =IF($A11="","",SUMPRODUCT((Tenants!$G$6:$G$105=$A11)*(Tenants!$I$6:$I$105<=DATE(Settings!$B$5+1,1,1)-1)*(Tenants!$J$6:$J$105>=DATE(Settings!$B$5,12,1))*Tenants!$K$6:$K$105)) | N11: =IF($A11="","",SUM(B11:M11))
A12: =IF(Settings!$B$13="","",Settings!$B$13) | B12: =IF($A12="","",SUMPRODUCT((Tenants!$G$6:$G$105=$A12)*(Tenants!$I$6:$I$105<=DATE(Settings!$B$5,2,1)-1)*(Tenants!$J$6:$J$105>=DATE(Settings!$B$5,1,1))*Tenants!$K$6:$K$105)) | C12: =IF($A12="","",SUMPRODUCT((Tenants!$G$6:$G$105=$A12)*(Tenants!$I$6:$I$105<=DATE(Settings!$B$5,3,1)-1)*(Tenants!$J$6:$J$105>=DATE(Settings!$B$5,2,1))*Tenants!$K$6:$K$105)) | D12: =IF($A12="","",SUMPRODUCT((Tenants!$G$6:$G$105=$A12)*(Tenants!$I$6:$I$105<=DATE(Settings!$B$5,4,1)-1)*(Tenants!$J$6:$J$105>=DATE(Settings!$B$5,3,1))*Tenants!$K$6:$K$105)) | E12: =IF($A12="","",SUMPRODUCT((Tenants!$G$6:$G$105=$A12)*(Tenants!$I$6:$I$105<=DATE(Settings!$B$5,5,1)-1)*(Tenants!$J$6:$J$105>=DATE(Settings!$B$5,4,1))*Tenants!$K$6:$K$105)) | F12: =IF($A12="","",SUMPRODUCT((Tenants!$G$6:$G$105=$A12)*(Tenants!$I$6:$I$105<=DATE(Settings!$B$5,6,1)-1)*(Tenants!$J$6:$J$105>=DATE(Settings!$B$5,5,1))*Tenants!$K$6:$K$105)) | G12: =IF($A12="","",SUMPRODUCT((Tenants!$G$6:$G$105=$A12)*(Tenants!$I$6:$I$105<=DATE(Settings!$B$5,7,1)-1)*(Tenants!$J$6:$J$105>=DATE(Settings!$B$5,6,1))*Tenants!$K$6:$K$105)) | H12: =IF($A12="","",SUMPRODUCT((Tenants!$G$6:$G$105=$A12)*(Tenants!$I$6:$I$105<=DATE(Settings!$B$5,8,1)-1)*(Tenants!$J$6:$J$105>=DATE(Settings!$B$5,7,1))*Tenants!$K$6:$K$105)) | I12: =IF($A12="","",SUMPRODUCT((Tenants!$G$6:$G$105=$A12)*(Tenants!$I$6:$I$105<=DATE(Settings!$B$5,9,1)-1)*(Tenants!$J$6:$J$105>=DATE(Settings!$B$5,8,1))*Tenants!$K$6:$K$105)) | J12: =IF($A12="","",SUMPRODUCT((Tenants!$G$6:$G$105=$A12)*(Tenants!$I$6:$I$105<=DATE(Settings!$B$5,10,1)-1)*(Tenants!$J$6:$J$105>=DATE(Settings!$B$5,9,1))*Tenants!$K$6:$K$105)) | K12: =IF($A12="","",SUMPRODUCT((Tenants!$G$6:$G$105=$A12)*(Tenants!$I$6:$I$105<=DATE(Settings!$B$5,11,1)-1)*(Tenants!$J$6:$J$105>=DATE(Settings!$B$5,10,1))*Tenants!$K$6:$K$105)) | L12: =IF($A12="","",SUMPRODUCT((Tenants!$G$6:$G$105=$A12)*(Tenants!$I$6:$I$105<=DATE(Settings!$B$5,12,1)-1)*(Tenants!$J$6:$J$105>=DATE(Settings!$B$5,11,1))*Tenants!$K$6:$K$105)) | M12: =IF($A12="","",SUMPRODUCT((Tenants!$G$6:$G$105=$A12)*(Tenants!$I$6:$I$105<=DATE(Settings!$B$5+1,1,1)-1)*(Tenants!$J$6:$J$105>=DATE(Settings!$B$5,12,1))*Tenants!$K$6:$K$105)) | N12: =IF($A12="","",SUM(B12:M12))
A13: =IF(Settings!$B$14="","",Settings!$B$14) | B13: =IF($A13="","",SUMPRODUCT((Tenants!$G$6:$G$105=$A13)*(Tenants!$I$6:$I$105<=DATE(Settings!$B$5,2,1)-1)*(Tenants!$J$6:$J$105>=DATE(Settings!$B$5,1,1))*Tenants!$K$6:$K$105)) | C13: =IF($A13="","",SUMPRODUCT((Tenants!$G$6:$G$105=$A13)*(Tenants!$I$6:$I$105<=DATE(Settings!$B$5,3,1)-1)*(Tenants!$J$6:$J$105>=DATE(Settings!$B$5,2,1))*Tenants!$K$6:$K$105)) | D13: =IF($A13="","",SUMPRODUCT((Tenants!$G$6:$G$105=$A13)*(Tenants!$I$6:$I$105<=DATE(Settings!$B$5,4,1)-1)*(Tenants!$J$6:$J$105>=DATE(Settings!$B$5,3,1))*Tenants!$K$6:$K$105)) | E13: =IF($A13="","",SUMPRODUCT((Tenants!$G$6:$G$105=$A13)*(Tenants!$I$6:$I$105<=DATE(Settings!$B$5,5,1)-1)*(Tenants!$J$6:$J$105>=DATE(Settings!$B$5,4,1))*Tenants!$K$6:$K$105)) | F13: =IF($A13="","",SUMPRODUCT((Tenants!$G$6:$G$105=$A13)*(Tenants!$I$6:$I$105<=DATE(Settings!$B$5,6,1)-1)*(Tenants!$J$6:$J$105>=DATE(Settings!$B$5,5,1))*Tenants!$K$6:$K$105)) | G13: =IF($A13="","",SUMPRODUCT((Tenants!$G$6:$G$105=$A13)*(Tenants!$I$6:$I$105<=DATE(Settings!$B$5,7,1)-1)*(Tenants!$J$6:$J$105>=DATE(Settings!$B$5,6,1))*Tenants!$K$6:$K$105)) | H13: =IF($A13="","",SUMPRODUCT((Tenants!$G$6:$G$105=$A13)*(Tenants!$I$6:$I$105<=DATE(Settings!$B$5,8,1)-1)*(Tenants!$J$6:$J$105>=DATE(Settings!$B$5,7,1))*Tenants!$K$6:$K$105)) | I13: =IF($A13="","",SUMPRODUCT((Tenants!$G$6:$G$105=$A13)*(Tenants!$I$6:$I$105<=DATE(Settings!$B$5,9,1)-1)*(Tenants!$J$6:$J$105>=DATE(Settings!$B$5,8,1))*Tenants!$K$6:$K$105)) | J13: =IF($A13="","",SUMPRODUCT((Tenants!$G$6:$G$105=$A13)*(Tenants!$I$6:$I$105<=DATE(Settings!$B$5,10,1)-1)*(Tenants!$J$6:$J$105>=DATE(Settings!$B$5,9,1))*Tenants!$K$6:$K$105)) | K13: =IF($A13="","",SUMPRODUCT((Tenants!$G$6:$G$105=$A13)*(Tenants!$I$6:$I$105<=DATE(Settings!$B$5,11,1)-1)*(Tenants!$J$6:$J$105>=DATE(Settings!$B$5,10,1))*Tenants!$K$6:$K$105)) | L13: =IF($A13="","",SUMPRODUCT((Tenants!$G$6:$G$105=$A13)*(Tenants!$I$6:$I$105<=DATE(Settings!$B$5,12,1)-1)*(Tenants!$J$6:$J$105>=DATE(Settings!$B$5,11,1))*Tenants!$K$6:$K$105)) | M13: =IF($A13="","",SUMPRODUCT((Tenants!$G$6:$G$105=$A13)*(Tenants!$I$6:$I$105<=DATE(Settings!$B$5+1,1,1)-1)*(Tenants!$J$6:$J$105>=DATE(Settings!$B$5,12,1))*Tenants!$K$6:$K$105)) | N13: =IF($A13="","",SUM(B13:M13))
A14: =IF(Settings!$B$15="","",Settings!$B$15) | B14: =IF($A14="","",SUMPRODUCT((Tenants!$G$6:$G$105=$A14)*(Tenants!$I$6:$I$105<=DATE(Settings!$B$5,2,1)-1)*(Tenants!$J$6:$J$105>=DATE(Settings!$B$5,1,1))*Tenants!$K$6:$K$105)) | C14: =IF($A14="","",SUMPRODUCT((Tenants!$G$6:$G$105=$A14)*(Tenants!$I$6:$I$105<=DATE(Settings!$B$5,3,1)-1)*(Tenants!$J$6:$J$105>=DATE(Settings!$B$5,2,1))*Tenants!$K$6:$K$105)) | D14: =IF($A14="","",SUMPRODUCT((Tenants!$G$6:$G$105=$A14)*(Tenants!$I$6:$I$105<=DATE(Settings!$B$5,4,1)-1)*(Tenants!$J$6:$J$105>=DATE(Settings!$B$5,3,1))*Tenants!$K$6:$K$105)) | E14: =IF($A14="","",SUMPRODUCT((Tenants!$G$6:$G$105=$A14)*(Tenants!$I$6:$I$105<=DATE(Settings!$B$5,5,1)-1)*(Tenants!$J$6:$J$105>=DATE(Settings!$B$5,4,1))*Tenants!$K$6:$K$105)) | F14: =IF($A14="","",SUMPRODUCT((Tenants!$G$6:$G$105=$A14)*(Tenants!$I$6:$I$105<=DATE(Settings!$B$5,6,1)-1)*(Tenants!$J$6:$J$105>=DATE(Settings!$B$5,5,1))*Tenants!$K$6:$K$105)) | G14: =IF($A14="","",SUMPRODUCT((Tenants!$G$6:$G$105=$A14)*(Tenants!$I$6:$I$105<=DATE(Settings!$B$5,7,1)-1)*(Tenants!$J$6:$J$105>=DATE(Settings!$B$5,6,1))*Tenants!$K$6:$K$105)) | H14: =IF($A14="","",SUMPRODUCT((Tenants!$G$6:$G$105=$A14)*(Tenants!$I$6:$I$105<=DATE(Settings!$B$5,8,1)-1)*(Tenants!$J$6:$J$105>=DATE(Settings!$B$5,7,1))*Tenants!$K$6:$K$105)) | I14: =IF($A14="","",SUMPRODUCT((Tenants!$G$6:$G$105=$A14)*(Tenants!$I$6:$I$105<=DATE(Settings!$B$5,9,1)-1)*(Tenants!$J$6:$J$105>=DATE(Settings!$B$5,8,1))*Tenants!$K$6:$K$105)) | J14: =IF($A14="","",SUMPRODUCT((Tenants!$G$6:$G$105=$A14)*(Tenants!$I$6:$I$105<=DATE(Settings!$B$5,10,1)-1)*(Tenants!$J$6:$J$105>=DATE(Settings!$B$5,9,1))*Tenants!$K$6:$K$105)) | K14: =IF($A14="","",SUMPRODUCT((Tenants!$G$6:$G$105=$A14)*(Tenants!$I$6:$I$105<=DATE(Settings!$B$5,11,1)-1)*(Tenants!$J$6:$J$105>=DATE(Settings!$B$5,10,1))*Tenants!$K$6:$K$105)) | L14: =IF($A14="","",SUMPRODUCT((Tenants!$G$6:$G$105=$A14)*(Tenants!$I$6:$I$105<=DATE(Settings!$B$5,12,1)-1)*(Tenants!$J$6:$J$105>=DATE(Settings!$B$5,11,1))*Tenants!$K$6:$K$105)) | M14: =IF($A14="","",SUMPRODUCT((Tenants!$G$6:$G$105=$A14)*(Tenants!$I$6:$I$105<=DATE(Settings!$B$5+1,1,1)-1)*(Tenants!$J$6:$J$105>=DATE(Settings!$B$5,12,1))*Tenants!$K$6:$K$105)) | N14: =IF($A14="","",SUM(B14:M14))
A15: =IF(Settings!$B$16="","",Settings!$B$16) | B15: =IF($A15="","",SUMPRODUCT((Tenants!$G$6:$G$105=$A15)*(Tenants!$I$6:$I$105<=DATE(Settings!$B$5,2,1)-1)*(Tenants!$J$6:$J$105>=DATE(Settings!$B$5,1,1))*Tenants!$K$6:$K$105)) | C15: =IF($A15="","",SUMPRODUCT((Tenants!$G$6:$G$105=$A15)*(Tenants!$I$6:$I$105<=DATE(Settings!$B$5,3,1)-1)*(Tenants!$J$6:$J$105>=DATE(Settings!$B$5,2,1))*Tenants!$K$6:$K$105)) | D15: =IF($A15="","",SUMPRODUCT((Tenants!$G$6:$G$105=$A15)*(Tenants!$I$6:$I$105<=DATE(Settings!$B$5,4,1)-1)*(Tenants!$J$6:$J$105>=DATE(Settings!$B$5,3,1))*Tenants!$K$6:$K$105)) | E15: =IF($A15="","",SUMPRODUCT((Tenants!$G$6:$G$105=$A15)*(Tenants!$I$6:$I$105<=DATE(Settings!$B$5,5,1)-1)*(Tenants!$J$6:$J$105>=DATE(Settings!$B$5,4,1))*Tenants!$K$6:$K$105)) | F15: =IF($A15="","",SUMPRODUCT((Tenants!$G$6:$G$105=$A15)*(Tenants!$I$6:$I$105<=DATE(Settings!$B$5,6,1)-1)*(Tenants!$J$6:$J$105>=DATE(Settings!$B$5,5,1))*Tenants!$K$6:$K$105)) | G15: =IF($A15="","",SUMPRODUCT((Tenants!$G$6:$G$105=$A15)*(Tenants!$I$6:$I$105<=DATE(Settings!$B$5,7,1)-1)*(Tenants!$J$6:$J$105>=DATE(Settings!$B$5,6,1))*Tenants!$K$6:$K$105)) | H15: =IF($A15="","",SUMPRODUCT((Tenants!$G$6:$G$105=$A15)*(Tenants!$I$6:$I$105<=DATE(Settings!$B$5,8,1)-1)*(Tenants!$J$6:$J$105>=DATE(Settings!$B$5,7,1))*Tenants!$K$6:$K$105)) | I15: =IF($A15="","",SUMPRODUCT((Tenants!$G$6:$G$105=$A15)*(Tenants!$I$6:$I$105<=DATE(Settings!$B$5,9,1)-1)*(Tenants!$J$6:$J$105>=DATE(Settings!$B$5,8,1))*Tenants!$K$6:$K$105)) | J15: =IF($A15="","",SUMPRODUCT((Tenants!$G$6:$G$105=$A15)*(Tenants!$I$6:$I$105<=DATE(Settings!$B$5,10,1)-1)*(Tenants!$J$6:$J$105>=DATE(Settings!$B$5,9,1))*Tenants!$K$6:$K$105)) | K15: =IF($A15="","",SUMPRODUCT((Tenants!$G$6:$G$105=$A15)*(Tenants!$I$6:$I$105<=DATE(Settings!$B$5,11,1)-1)*(Tenants!$J$6:$J$105>=DATE(Settings!$B$5,10,1))*Tenants!$K$6:$K$105)) | L15: =IF($A15="","",SUMPRODUCT((Tenants!$G$6:$G$105=$A15)*(Tenants!$I$6:$I$105<=DATE(Settings!$B$5,12,1)-1)*(Tenants!$J$6:$J$105>=DATE(Settings!$B$5,11,1))*Tenants!$K$6:$K$105)) | M15: =IF($A15="","",SUMPRODUCT((Tenants!$G$6:$G$105=$A15)*(Tenants!$I$6:$I$105<=DATE(Settings!$B$5+1,1,1)-1)*(Tenants!$J$6:$J$105>=DATE(Settings!$B$5,12,1))*Tenants!$K$6:$K$105)) | N15: =IF($A15="","",SUM(B15:M15))
A17: PORTFOLIO TOTAL | B17: =SUM(B6:B15) | C17: =SUM(C6:C15) | D17: =SUM(D6:D15) | E17: =SUM(E6:E15) | F17: =SUM(F6:F15) | G17: =SUM(G6:G15) | H17: =SUM(H6:H15) | I17: =SUM(I6:I15) | ... N17: =SUM(N6:N15)

Sheet Pipeline
A2: =HYPERLINK("#'Monthly Revenue'!A1", "← BACK") | D2: PIPELINE | J2: =HYPERLINK("#'Settings'!A1", "NEXT →")
A4: Inquiry-to-signed conversion funnel by channel — find your strongest acquisition lever.
A5: Channel | B5: Inquiries | C5: Applications | D5: Approved | E5: Signed | F5: Inq → App % | G5: App → Apv % | H5: Apv → Sign % | I5: Inq → Sign %
A6: Furnished Finder | F6: =IFERROR(C6/B6,0) | G6: =IFERROR(D6/C6,0) | H6: =IFERROR(E6/D6,0) | I6: =IFERROR(E6/B6,0)
A7: Blueground | F7: =IFERROR(C7/B7,0) | G7: =IFERROR(D7/C7,0) | H7: =IFERROR(E7/D7,0) | I7: =IFERROR(E7/B7,0)
A8: AnyPlace | F8: =IFERROR(C8/B8,0) | G8: =IFERROR(D8/C8,0) | H8: =IFERROR(E8/D8,0) | I8: =IFERROR(E8/B8,0)
A9: Direct | F9: =IFERROR(C9/B9,0) | G9: =IFERROR(D9/C9,0) | H9: =IFERROR(E9/D9,0) | I9: =IFERROR(E9/B9,0)
A10: Referral | F10: =IFERROR(C10/B10,0) | G10: =IFERROR(D10/C10,0) | H10: =IFERROR(E10/D10,0) | I10: =IFERROR(E10/B10,0)
A11: Other | F11: =IFERROR(C11/B11,0) | G11: =IFERROR(D11/C11,0) | H11: =IFERROR(E11/D11,0) | I11: =IFERROR(E11/B11,0)
A12: TOTAL | B12: =SUM(B6:B10) | C12: =SUM(C6:C10) | D12: =SUM(D6:D10) | E12: =SUM(E6:E10) | F12: =IFERROR(C12/B12,0) | G12: =IFERROR(D12/C12,0) | H12: =IFERROR(E12/D12,0) | I12: =IFERROR(E12/B12,0)
A14: Funnel Stage (totals)
A15: Inquiries | B15: =B12
A16: Applications | B16: =C12
A17: Approved | B17: =D12
A18: Signed | B18: =E12

Sheet Settings
A2: =HYPERLINK("#'Pipeline'!A1", "← BACK") | D2: SETTINGS
A4: Active year · property list · channel list · lease type list
A5: Active year: | B5: 2026
A7: Property list (10 max)
A18: Channel list | B18: Furnished Finder
B19: Blueground
B20: AnyPlace
B21: Direct
B22: Referral
B23: Other
A27: Lease type list | B27: 3-month
B28: 6-month
B29: Month-to-month
B30: Corporate negotiated
B31: Travel nurse contract
B32: Other
A36: Year-end archive
A37: Each January, log YTD totals for the closing year, then bump Active year above and clear past tenants from the Tenants tab (or archive separately).
A38: Year | B38: Tenants Hosted | C38: Total MRR Collected | D38: Gap Days
A39: 2024
A40: 2025
A41: 2026
A42: 2027
A43: 2028
A44: 2029
A45: 2030
