Workbook

Sheet Start
A2: The STR Ledger
A4: Portfolio Valuation Model
A5: Three valuation methods. One number a buyer would pay.
A7: STR-002 · v1.0 · DEMO
A11: PORTFOLIO MARKET VALUE | E11: TOTAL EQUITY | I11: PORTFOLIO LTV
A12: ='Equity Summary'!C7 | E12: ='Equity Summary'!C9 | I12: ='Equity Summary'!C10
A16: ="As of "&TEXT(Settings!B5,"yyyy")&" · "&COUNTIF(Settings!B7:B16,"<>")&" properties tracked"
A18: WHAT A BUYER WOULD PAY
A19: ='Equity Summary'!C7
A24: =HYPERLINK("#'Per Property'!A1", "Per Property") | D24: =HYPERLINK("#'Cap Rate Reference'!A1", "Cap Rate Reference") | G24: =HYPERLINK("#'Equity Summary'!A1", "Equity Summary") | J24: =HYPERLINK("#'Settings'!A1", "Settings")
A29: 💡 Run this annually — and any time you're talking refi or sale. Free updates forever at thestrledger.com.
A32: Questions? hello@thestrledger.com
A33: STR-002 · v1.0 · DEMO · Free updates forever

Sheet Per Property
A2: =HYPERLINK("#'Start'!A1", "← BACK") | D2: PER PROPERTY | J2: =HYPERLINK("#'Cap Rate Reference'!A1", "NEXT →")
A4: Three methods averaged into final value column · capacity 10 properties
A6: Property | B6: NOI YTD | C6: Cap rate | D6: M1: Cap×NOI | E6: Comp $/BR | F6: Beds | G6: Baths | H6: M2: Comp value | I6: Annual gross rent | J6: GRM | K6: M3: GRM×Rent | L6: Average value | M6: Loan balance | N6: Equity | O6: LTV
A7: =Settings!B7 | B7: 42000 | C7: =IFERROR(VLOOKUP(Settings!C7,'Cap Rate Reference'!A7:B16,2,FALSE),0) | D7: =IF(OR(B7="",C7=0,C7=""),"",B7/C7) | E7: 195000 | F7: 3 | G7: 2 | H7: =IF(OR(E7="",F7=""),"",E7*F7*(1+MAX(0,G7-F7)*0.05)) | I7: 96000 | J7: 6.04 | K7: =IF(OR(I7="",J7=""),"",I7*J7) | L7: =IFERROR(AVERAGE(IF(ISNUMBER(D7),D7),IF(ISNUMBER(H7),H7),IF(ISNUMBER(K7),K7)),"") | M7: 364000 | N7: =IF(OR(L7="",M7=""),"",L7-M7) | O7: =IF(OR(L7="",L7=0,M7=""),"",M7/L7)
A8: =Settings!B8 | B8: 48000 | C8: =IFERROR(VLOOKUP(Settings!C8,'Cap Rate Reference'!A7:B16,2,FALSE),0) | D8: =IF(OR(B8="",C8=0,C8=""),"",B8/C8) | E8: 240000 | F8: 3 | G8: 2.5 | H8: =IF(OR(E8="",F8=""),"",E8*F8*(1+MAX(0,G8-F8)*0.05)) | I8: 110000 | J8: 6.55 | K8: =IF(OR(I8="",J8=""),"",I8*J8) | L8: =IFERROR(AVERAGE(IF(ISNUMBER(D8),D8),IF(ISNUMBER(H8),H8),IF(ISNUMBER(K8),K8)),"") | M8: 469000 | N8: =IF(OR(L8="",M8=""),"",L8-M8) | O8: =IF(OR(L8="",L8=0,M8=""),"",M8/L8)
A9: =Settings!B9 | B9: 34000 | C9: =IFERROR(VLOOKUP(Settings!C9,'Cap Rate Reference'!A7:B16,2,FALSE),0) | D9: =IF(OR(B9="",C9=0,C9=""),"",B9/C9) | E9: 150000 | F9: 3 | G9: 2 | H9: =IF(OR(E9="",F9=""),"",E9*F9*(1+MAX(0,G9-F9)*0.05)) | I9: 78000 | J9: 5.64 | K9: =IF(OR(I9="",J9=""),"",I9*J9) | L9: =IFERROR(AVERAGE(IF(ISNUMBER(D9),D9),IF(ISNUMBER(H9),H9),IF(ISNUMBER(K9),K9)),"") | M9: 270000 | N9: =IF(OR(L9="",M9=""),"",L9-M9) | O9: =IF(OR(L9="",L9=0,M9=""),"",M9/L9)
A10: =Settings!B10 | C10: =IFERROR(VLOOKUP(Settings!C10,'Cap Rate Reference'!A7:B16,2,FALSE),0) | D10: =IF(OR(B10="",C10=0,C10=""),"",B10/C10) | H10: =IF(OR(E10="",F10=""),"",E10*F10*(1+MAX(0,G10-F10)*0.05)) | K10: =IF(OR(I10="",J10=""),"",I10*J10) | L10: =IFERROR(AVERAGE(IF(ISNUMBER(D10),D10),IF(ISNUMBER(H10),H10),IF(ISNUMBER(K10),K10)),"") | N10: =IF(OR(L10="",M10=""),"",L10-M10) | O10: =IF(OR(L10="",L10=0,M10=""),"",M10/L10)
A11: =Settings!B11 | C11: =IFERROR(VLOOKUP(Settings!C11,'Cap Rate Reference'!A7:B16,2,FALSE),0) | D11: =IF(OR(B11="",C11=0,C11=""),"",B11/C11) | H11: =IF(OR(E11="",F11=""),"",E11*F11*(1+MAX(0,G11-F11)*0.05)) | K11: =IF(OR(I11="",J11=""),"",I11*J11) | L11: =IFERROR(AVERAGE(IF(ISNUMBER(D11),D11),IF(ISNUMBER(H11),H11),IF(ISNUMBER(K11),K11)),"") | N11: =IF(OR(L11="",M11=""),"",L11-M11) | O11: =IF(OR(L11="",L11=0,M11=""),"",M11/L11)
A12: =Settings!B12 | C12: =IFERROR(VLOOKUP(Settings!C12,'Cap Rate Reference'!A7:B16,2,FALSE),0) | D12: =IF(OR(B12="",C12=0,C12=""),"",B12/C12) | H12: =IF(OR(E12="",F12=""),"",E12*F12*(1+MAX(0,G12-F12)*0.05)) | K12: =IF(OR(I12="",J12=""),"",I12*J12) | L12: =IFERROR(AVERAGE(IF(ISNUMBER(D12),D12),IF(ISNUMBER(H12),H12),IF(ISNUMBER(K12),K12)),"") | N12: =IF(OR(L12="",M12=""),"",L12-M12) | O12: =IF(OR(L12="",L12=0,M12=""),"",M12/L12)
A13: =Settings!B13 | C13: =IFERROR(VLOOKUP(Settings!C13,'Cap Rate Reference'!A7:B16,2,FALSE),0) | D13: =IF(OR(B13="",C13=0,C13=""),"",B13/C13) | H13: =IF(OR(E13="",F13=""),"",E13*F13*(1+MAX(0,G13-F13)*0.05)) | K13: =IF(OR(I13="",J13=""),"",I13*J13) | L13: =IFERROR(AVERAGE(IF(ISNUMBER(D13),D13),IF(ISNUMBER(H13),H13),IF(ISNUMBER(K13),K13)),"") | N13: =IF(OR(L13="",M13=""),"",L13-M13) | O13: =IF(OR(L13="",L13=0,M13=""),"",M13/L13)
A14: =Settings!B14 | C14: =IFERROR(VLOOKUP(Settings!C14,'Cap Rate Reference'!A7:B16,2,FALSE),0) | D14: =IF(OR(B14="",C14=0,C14=""),"",B14/C14) | H14: =IF(OR(E14="",F14=""),"",E14*F14*(1+MAX(0,G14-F14)*0.05)) | K14: =IF(OR(I14="",J14=""),"",I14*J14) | L14: =IFERROR(AVERAGE(IF(ISNUMBER(D14),D14),IF(ISNUMBER(H14),H14),IF(ISNUMBER(K14),K14)),"") | N14: =IF(OR(L14="",M14=""),"",L14-M14) | O14: =IF(OR(L14="",L14=0,M14=""),"",M14/L14)
A15: =Settings!B15 | C15: =IFERROR(VLOOKUP(Settings!C15,'Cap Rate Reference'!A7:B16,2,FALSE),0) | D15: =IF(OR(B15="",C15=0,C15=""),"",B15/C15) | H15: =IF(OR(E15="",F15=""),"",E15*F15*(1+MAX(0,G15-F15)*0.05)) | K15: =IF(OR(I15="",J15=""),"",I15*J15) | L15: =IFERROR(AVERAGE(IF(ISNUMBER(D15),D15),IF(ISNUMBER(H15),H15),IF(ISNUMBER(K15),K15)),"") | N15: =IF(OR(L15="",M15=""),"",L15-M15) | O15: =IF(OR(L15="",L15=0,M15=""),"",M15/L15)
A16: =Settings!B16 | C16: =IFERROR(VLOOKUP(Settings!C16,'Cap Rate Reference'!A7:B16,2,FALSE),0) | D16: =IF(OR(B16="",C16=0,C16=""),"",B16/C16) | H16: =IF(OR(E16="",F16=""),"",E16*F16*(1+MAX(0,G16-F16)*0.05)) | K16: =IF(OR(I16="",J16=""),"",I16*J16) | L16: =IFERROR(AVERAGE(IF(ISNUMBER(D16),D16),IF(ISNUMBER(H16),H16),IF(ISNUMBER(K16),K16)),"") | N16: =IF(OR(L16="",M16=""),"",L16-M16) | O16: =IF(OR(L16="",L16=0,M16=""),"",M16/L16)
A17: PORTFOLIO TOTAL | L17: =SUMIF(L7:L16,"<>") | M17: =SUM(M7:M16) | N17: =SUMIF(N7:N16,"<>") | O17: =IFERROR(M17/L17,0)
A21: Questions? hello@thestrledger.com
A22: STR-002 · Per Property

Sheet Cap Rate Reference
A2: =HYPERLINK("#'Per Property'!A1", "← BACK") | D2: CAP RATE REFERENCE | J2: =HYPERLINK("#'Equity Summary'!A1", "NEXT →")
A4: Edit ranges per your actual market — Per Property tab VLOOKUPs against this table.
A6: Market type | B6: Cap rate | D6: Range low | E6: Range high
A7: Mountain resort STR | B7: 0.075 | D7: 0.06 | E7: 0.08
A8: Beach STR | B8: 0.07 | D8: 0.07 | E8: 0.09
A9: Urban STR | B9: 0.09 | D9: 0.08 | E9: 0.1
A10: Rural / cabin | B10: 0.08 | D10: 0.08 | E10: 0.12
A19: WHY THESE RANGES?
A20: STR cap rates run higher than long-term rentals because operating risk is higher and revenue is more volatile. Mountain/beach resort markets compress to 6-8% (institutional appetite); urban and rural stay in the 8-12% zone (thinner buyer pool). When in doubt, ask a local STR-savvy commercial broker for a recent comp sale and back-solve the cap from their NOI.
A27: Questions? hello@thestrledger.com
A28: STR-002 · Cap Rate Reference

Sheet Equity Summary
A2: =HYPERLINK("#'Cap Rate Reference'!A1", "← BACK") | D2: EQUITY SUMMARY | J2: =HYPERLINK("#'Settings'!A1", "NEXT →")
A4: Roll-up of value, debt, equity, and LTV — plus per-property equity pie chart.
A6: PORTFOLIO ROLL-UP
B7: Total portfolio market value: | C7: ='Per Property'!L17
B8: Total loan balances: | C8: ='Per Property'!M17
B9: Total equity: | C9: ='Per Property'!N17
B10: Portfolio LTV: | C10: ='Per Property'!O17
E12: Property | F12: Equity
E13: =Settings!B7 | F13: =IFERROR(IF('Per Property'!N13="",0,'Per Property'!N13),0)
E14: =Settings!B8 | F14: =IFERROR(IF('Per Property'!N14="",0,'Per Property'!N14),0)
E15: =Settings!B9 | F15: =IFERROR(IF('Per Property'!N15="",0,'Per Property'!N15),0)
E16: =Settings!B10 | F16: =IFERROR(IF('Per Property'!N16="",0,'Per Property'!N16),0)
E17: =Settings!B11 | F17: =IFERROR(IF('Per Property'!N17="",0,'Per Property'!N17),0)
E18: =Settings!B12 | F18: =IFERROR(IF('Per Property'!N18="",0,'Per Property'!N18),0)
E19: =Settings!B13 | F19: =IFERROR(IF('Per Property'!N19="",0,'Per Property'!N19),0)
A20: VALUATION METHODS
A21: Method 1 — Income (Cap × NOI): NOI ÷ market cap rate. The number a buyer with a calculator runs. Method 2 — Sales comparison ($/BR × beds, half-bath premium): the number a residential agent runs. Method 3 — Gross Rent Multiplier (rent × GRM): the back-of-the-envelope an experienced STR investor runs. The three averaged is your defensible valuation — when one method is wildly off, dig in before quoting it.
A28: Questions? hello@thestrledger.com
A29: STR-002 · Equity Summary

Sheet Settings
A2: =HYPERLINK("#'Equity Summary'!A1", "← BACK") | D2: SETTINGS
A4: Property roster, valuation date, and market types — single source of truth.
B5: Valuation date: | C5: 2026
B6: Property name | C6: Market type
B7: Smokies Ridge | C7: Mountain resort STR
B8: Lakehouse | C8: Beach STR
B9: Creek Side | C9: Rural / cabin
A19: HOW TO USE
A20: 1) Set valuation year above. 2) List each property and pick its market type from the dropdown (drives cap rate via Cap Rate Reference). 3) Customize the Cap Rate Reference table for your actual sub-market — Gatlinburg's cap is not Aspen's. 4) Fill NOI, comps, rent, GRM, and loan balance on the Per Property tab. 5) Read the answer on Start and Equity Summary.
A28: Questions? hello@thestrledger.com
A29: STR-002 · Settings
