Workbook

Sheet Start
A2: The STR Ledger
A4: Refi-or-Sell Decision Matrix
A5: Three paths. One year-5 number each. The biggest wins.
A7: STR-003 · v1.0 · BLANK
A11: =IF(Settings!C5="","(enter property on Settings tab)",Settings!C5)
A14: PATH 1 · HOLD + REFI | E14: PATH 2 · SELL | I14: PATH 3 · SELL + 1031
A15: 5-YEAR WEALTH | E15: 5-YEAR WEALTH | I15: 5-YEAR WEALTH
A16: ='Path 1 Refi'!C30 | E16: ='Path 2 Sell'!C25 | I16: ='Path 3 1031'!C30
A20: ="Cash out: "&TEXT('Path 1 Refi'!C12,"$#,##0") | E20: ="Net cash: "&TEXT('Path 2 Sell'!C13,"$#,##0") | I20: ="Replacement: "&TEXT('Path 3 1031'!C13,"$#,##0")
A23: Scenario projections only. Actual outcome depends on market timing, guest reality, and financing availability when you act.
A25: =HYPERLINK("#'Property Inputs'!A1", "Property Inputs") | D25: =HYPERLINK("#'Path 1 Refi'!A1", "Path 1: Refi") | G25: =HYPERLINK("#'Path 2 Sell'!A1", "Path 2: Sell") | J25: =HYPERLINK("#'Path 3 1031'!A1", "Path 3: 1031")
A29: =HYPERLINK("#'Settings'!A1", "→ Settings & Assumptions") | G29: =HYPERLINK("https://thestrledger.com", "More tools at thestrledger.com")
A34: Questions? hello@thestrledger.com
A35: STR-003 · v1.0 · BLANK · Free updates forever

Sheet Property Inputs
A2: =HYPERLINK("#'Start'!A1", "← BACK") | D2: PROPERTY INPUTS | J2: =HYPERLINK("#'Path 1 Refi'!A1", "NEXT →")
A4: What you own today — value, loan, NOI, basis, depreciation
A6: CURRENT POSITION
B7: Current market value ($): | E7: From STR-002 valuation, broker BPO, or recent comp
B8: Current loan balance ($): | E8: Today's principal owed
B9: Current monthly P&I ($): | E9: Existing payment (P&I only, exclude tax/ins escrow)
B10: Annual NOI ($): | E10: Net operating income — revenue minus opex (no debt)
A12: TAX BASIS
B13: Original cost basis ($): | E13: Purchase price + capitalized improvements
B14: Years held:
B15: Accumulated depreciation ($): | E15: From your tax returns (Form 4562 / Sched E)
A17: DERIVED — IF SOLD TODAY
B18: Adjusted basis: | C18: =C13-C15
B19: Realized gain (sale @ current value): | C19: =C7*(1-Settings!C19)-C18
B20: Depreciation recapture portion: | C20: =MIN(C15,MAX(0,C19))
B21: Capital gain portion: | C21: =MAX(0,C19-C20)
B22: Recapture tax (25%): | C22: =C20*Settings!C17
B23: Capital gain tax (LTCG): | C23: =C21*Settings!C15
B24: Total tax if sold today: | C24: =C22+C23
A28: Questions? hello@thestrledger.com
A29: STR-003 · Property Inputs

Sheet Path 1 Refi
A2: =HYPERLINK("#'Property Inputs'!A1", "← BACK") | D2: PATH 1: HOLD + REFI | J2: =HYPERLINK("#'Path 2 Sell'!A1", "NEXT →")
A4: Cash-out refi at current rates. Wealth = cash out + 5-yr cash flow + final equity.
A6: REFI INPUTS
B7: New LTV (% of value): | E7: Cash-out STR loans typically max 70-75% LTV
B8: Refi term (years): | E8: 30 typical
B9: Refi closing costs ($): | E9: 2-3% of loan amount typical
A11: REFI MECHANICS
B12: New loan amount: | C12: ='Property Inputs'!C7*C7
B13: Cash out at close: | C13: =C12-'Property Inputs'!C8-C9
B14: New monthly P&I (Excel PMT): | C14: =IFERROR(PMT(Settings!C13/12,C8*12,-C12),0)
B15: New annual debt service: | C15: =C14*12
B16: Cash flow change (NOI - new DS): | C16: ='Property Inputs'!C10-C15
B17: Old annual debt service (for ref): | C17: ='Property Inputs'!C9*12
A19: 5-YEAR PROJECTION
B20: Annual cash flow (Y1, post-refi): | C20: =C16
B21: 5-year cumulative cash flow: | C21: =C20*Settings!C7
B22: Property value at year-5: | C22: ='Property Inputs'!C7*(1+Settings!C9)^Settings!C7
B23: New loan balance at year-5: | C23: =-FV(Settings!C13/12,Settings!C7*12,C14,-C12)
B24: Final equity at year-5: | C24: =C22-C23
A27: TOTAL 5-YEAR WEALTH
B30: Total wealth at year-5: | C30: =C13+C21+C24
A33: Method: Hold the property, refinance to extract tax-free cash. 5-yr wealth = cash extracted + cumulative levered cash flow + final equity (value × growth − amortized new loan).
A37: Questions? hello@thestrledger.com
A38: STR-003 · Path 1 Refi

Sheet Path 2 Sell
A2: =HYPERLINK("#'Path 1 Refi'!A1", "← BACK") | D2: PATH 2: SELL | J2: =HYPERLINK("#'Path 3 1031'!A1", "NEXT →")
A4: Sell outright. Reinvest net cash at the assumed rate. Wealth = future value at year-5.
A6: SALE MECHANICS
B7: Gross sale price (current value): | C7: ='Property Inputs'!C7
B8: Selling costs (commission + closing): | C8: =C7*Settings!C19
B9: Net sale proceeds: | C9: =C7-C8
B10: Mortgage payoff: | C10: ='Property Inputs'!C8
B11: Cash before tax: | C11: =C9-C10
B12: Total tax (recapture + LTCG): | C12: ='Property Inputs'!C24
B13: Net cash freed up: | C13: =C11-C12
A15: REINVESTMENT
B16: Reinvestment rate (override Settings): | E16: Default pulls from Settings; override for sensitivity
B17: Effective reinvest rate: | C17: =IF(C16="",Settings!C11,C16)
B18: Years compounding: | C18: =Settings!C7
B19: Future value at year-5: | C19: =C13*(1+C17)^C18
A22: TOTAL 5-YEAR WEALTH
B25: Total wealth at year-5: | C25: =C19
A28: Method: Sell at current value, pay selling costs and taxes (recapture at 25% + capital gain at LTCG rate), reinvest net cash at the assumed rate for the hold period.
A32: Questions? hello@thestrledger.com
A33: STR-003 · Path 2 Sell

Sheet Path 3 1031
A2: =HYPERLINK("#'Path 2 Sell'!A1", "← BACK") | D2: PATH 3: SELL + 1031 | J2: =HYPERLINK("#'Settings'!A1", "NEXT →")
A4: Sell + 1031 into a larger asset. Defer all gain. Wealth = replacement equity + 5-yr cash flow.
A6: REPLACEMENT PROPERTY INPUTS
B7: Replacement property value ($): | E7: Equal or greater for full gain deferral
B8: Replacement annual NOI ($): | E8: Larger asset = larger NOI typically
B9: Replacement loan amount ($): | E9: 70% LTV typical for STR
B10: Replacement loan rate: | E10: Current acquisition rate
A12: 1031 MECHANICS
B13: Equity into replacement: | C13: =C7-C9
B14: Cash from sale (deferred): | C14: ='Path 2 Sell'!C9-'Path 2 Sell'!C10
B15: Carryover basis (replacement): | C15: ='Property Inputs'!C18+(C7-'Property Inputs'!C7)
A17: REPLACEMENT OPERATIONS
B18: Replacement monthly P&I (Excel PMT): | C18: =IFERROR(PMT(C10/12,30*12,-C9),0)
B19: Replacement annual debt service: | C19: =C18*12
B20: Annual cash flow (NOI − DS): | C20: =C8-C19
B21: 5-year cumulative cash flow: | C21: =C20*Settings!C7
A23: EXIT EQUITY AT YEAR-5
B24: Replacement value at year-5: | C24: =C7*(1+Settings!C9)^Settings!C7
B25: Replacement loan balance at year-5: | C25: =-FV(C10/12,Settings!C7*12,C18,-C9)
B26: Final equity at year-5: | C26: =C24-C25
A28: TOTAL 5-YEAR WEALTH
B30: Total wealth at year-5: | C30: =C26+C21
A33: Method: 1031 exchange defers all gain. Equity rolls into a larger asset; depreciation basis carries over. 5-yr wealth = year-5 equity + cumulative cash flow on the replacement.
A37: Questions? hello@thestrledger.com
A38: STR-003 · Path 3 1031

Sheet Settings
A2: =HYPERLINK("#'Path 3 1031'!A1", "← BACK") | D2: SETTINGS | J2: =HYPERLINK("#'Start'!A1", "HOME →")
A4: Property name + assumptions used by all three path tabs.
B5: Property name: | E5: Shows on Start tab hero band
B7: Hold / projection period (years): | E7: Default 5 yrs — matches brief
B9: Property value growth (%/yr): | E9: Annual appreciation assumption (3% conservative default)
B11: Reinvestment rate (Path 2): | E11: Where do sale proceeds go? S&P ≈ 7-9%, another deal ≈ 8-12%
B13: Refi rate (Path 1): | E13: Today's cash-out STR rate
B15: Long-term capital gains rate: | E15: 15% or 20% federal — check your bracket + state add-on
B17: Depreciation recapture rate: | E17: Federal flat 25% on accumulated depreciation
B19: Selling costs (% of sale): | E19: 6% commission + 1.5% closing typical (= 7.5%)
A23: Questions? hello@thestrledger.com
A24: STR-003 · Settings
