Workbook

Sheet Start
A2: The STR Ledger
A4: Escape the W2 Planner
A5: When the math says you can.
A7: STR-001 · v1.0 · DEMO
A8: OPTIMISTIC QUIT DATE
A9: ='Quit Date Calculator'!C7
A11: CONSERVATIVE QUIT DATE
A12: ='Quit Date Calculator'!C8
A14: ="Spread: "&TEXT('Quit Date Calculator'!C9,"0.0")&" years between best- and worst-case."
A16: PROPS NEEDED | D16: CASH NEEDED AT QUIT | G16: HEALTHCARE BRIDGE | J16: Y1 PROJECTED NET
A17: ='Target State'!C20 | D17: ='Target State'!C22 | G17: ='Risk Plan'!C22 | J17: ='Quit Date Calculator'!C19
A20: ="You're "&TEXT('Target State'!C20-'Current State'!C16,"0")&" properties and "&TEXT(MAX(0,'Target State'!C22-'Current State'!C18),"$#,##0")&" away from the target. Two paths get you there: "&TEXT('Quit Date Calculator'!C7,"mmm yyyy")&" optimistic, "&TEXT('Quit Date Calculator'!C8,"mmm yyyy")&" conservative. The biggest swing factor is acquisition pace. Re-run when you close on a property."
A24: =HYPERLINK("#'Current State'!A1", "Current State") | D24: =HYPERLINK("#'Target State'!A1", "Target State") | G24: =HYPERLINK("#'Acquisition Schedule'!A1", "Acquisitions") | J24: =HYPERLINK("#'Risk Plan'!A1", "Risk Plan")
A28: =HYPERLINK("#'Quit Date Calculator'!A1", "→ Quit Date Calculator") | G28: =HYPERLINK("#'Conversation Doc'!A1", "Conversation Doc (printable)")
A33: Underwriting your next acquisition? Get the STR Deal Analyzer at thestrledger.com — $47.
A36: Questions? hello@thestrledger.com
A37: STR-001 · v1.0 · DEMO · Free updates forever

Sheet Current State
A2: =HYPERLINK("#'Start'!A1", "← BACK") | D2: CURRENT STATE | J2: =HYPERLINK("#'Target State'!A1", "NEXT →")
A4: Section 1 — what you have today: W2, partner income, STR portfolio, runway.
A6: PLAN ANCHOR
B7: Plan start date: | C7: 46143 | E7: Today's date — when you started this planning round
A9: HOUSEHOLD INCOME
B10: Your W2 gross ($/yr): | C10: 145000
B11: Your W2 net ($/yr): | C11: 98000 | E11: After taxes, 401k, benefits
B12: W2 benefits value ($/yr): | C12: 18000 | E12: Employer 401k match + health + life + disability
B13: Partner W2 net ($/yr): | C13: 72000 | E13: Zero if single-income household
A15: CURRENT STR PORTFOLIO
B16: # properties owned: | C16: 2
B17: Portfolio gross ($/yr): | C17: 58000 | E17: Total revenue across all properties YTD-annualized
B18: Portfolio net ($/yr): | C18: 19000 | E18: Schedule E line 26 — what hits your tax return
B19: Avg stab. net per prop ($/yr): | C19: 14000 | E19: Use a Y3 property — Y1/Y2 are depressed
A21: EXPENSES & RUNWAY
B22: Annual household expenses ($): | C22: 96000 | E22: All in — mortgage, food, kids, etc.
B23: Annual savings rate ($): | C23: 42000 | E23: What you actually deploy into properties each year
B24: Current liquid runway ($): | C24: 48000 | E24: Cash after closing on existing properties
A26: ROLLUP
B27: Total household income (net): | C27: =C11+C13+C18
B28: Income replaced by STR today: | C28: =IFERROR(C18/(C11+C12),0)
B29: Implied savings rate: | C29: =IFERROR(C23/(C11+C13+C18),0)
B30: Years runway covers expenses: | C30: =IFERROR(C24/C22,0)
A34: Questions? hello@thestrledger.com
A35: STR-001 · Current State

Sheet Target State
A2: =HYPERLINK("#'Current State'!A1", "← BACK") | D2: TARGET STATE | J2: =HYPERLINK("#'Acquisition Schedule'!A1", "NEXT →")
A4: Section 2 — what 'enough' looks like: replacement income, buffer, properties needed.
A6: REPLACEMENT INCOME
B7: Target replacement income ($/yr): | C7: 112000 | E7: Default = current W2 net + benefits cost + healthcare bridge
B8: Buffer multiple (×): | C8: 1.5 | E8: 1.5× = handle a bad year without panic
B9: Target liquid reserve at quit ($): | C9: 48000 | E9: Default 6 months of expenses
B10: Target stabilized net per prop ($/yr): | C10: 14000 | E10: Use the per-property economics you actually achieve
A12: WHAT THE MATH SAYS
B13: Buffered income required ($/yr): | C13: =C7*C8
B14: Less current STR portfolio net: | C14: ='Current State'!C18
B15: Net new STR income required: | C15: =MAX(0,C13-C14)
B16: Properties to add (rounded up): | C16: =IFERROR(CEILING(C15/C10,1),0)
B17: Total properties at quit: | C17: ='Current State'!C16+C16
A19: HEADLINE NUMBERS (referenced by Start tab)
B20: TOTAL PROPERTIES NEEDED: | C20: =C17
B21: Cash deployment per property ($): | C21: =95000
B22: TOTAL CASH NEEDED AT QUIT ($): | C22: =C16*C21+C9
A26: Questions? hello@thestrledger.com
A27: STR-001 · Target State

Sheet Acquisition Schedule
A2: =HYPERLINK("#'Target State'!A1", "← BACK") | D2: ACQUISITION SCHEDULE | J2: =HYPERLINK("#'Risk Plan'!A1", "NEXT →")
A4: Section 3 — year-by-year property adds and cash deployment.
A6: PACE ASSUMPTIONS
B7: Optimistic props/year: | C7: 3 | E7: Faster acquisition pace, current per-prop economics
B8: Conservative props/year: | C8: 1.5 | E8: Slower pace, conservative occupancy
B9: Cash per property ($): | C9: 95000 | E9: Down + closing + rehab + furnish + reserve
B10: Y1 net haircut (%): | C10: 0.65 | E10: Y1 ≈ 65% of stabilized
A12: 7-YEAR SCHEDULE (Optimistic pace)
B13: Year | C13: Plan year | D13: Props added | E13: Cash deployed | F13: Y1 net added | G13: Stabilized net total | H13: Cumulative net | I13: Reaches target?
B14: 1 | C14: =YEAR('Current State'!C7)+0 | D14: =$C$7 | E14: =D14*$C$9 | F14: =D14*'Target State'!C10*$C$10 | G14: ='Current State'!C18+D14*'Target State'!C10*$C$10 | H14: =G14 | I14: =IF(H14>='Target State'!C13,"YES","")
B15: 2 | C15: =YEAR('Current State'!C7)+1 | D15: =IF(H14>='Target State'!C13,0,$C$7) | E15: =D15*$C$9 | F15: =D15*'Target State'!C10*$C$10 | G15: =G14+D15*'Target State'!C10*$C$10+SUM($D$14:$D14)*'Target State'!C10*(1-$C$10)/2 | H15: =G15 | I15: =IF(H15>='Target State'!C13,"YES","")
B16: 3 | C16: =YEAR('Current State'!C7)+2 | D16: =IF(H15>='Target State'!C13,0,$C$7) | E16: =D16*$C$9 | F16: =D16*'Target State'!C10*$C$10 | G16: =G15+D16*'Target State'!C10*$C$10+SUM($D$14:$D15)*'Target State'!C10*(1-$C$10)/2 | H16: =G16 | I16: =IF(H16>='Target State'!C13,"YES","")
B17: 4 | C17: =YEAR('Current State'!C7)+3 | D17: =IF(H16>='Target State'!C13,0,$C$7) | E17: =D17*$C$9 | F17: =D17*'Target State'!C10*$C$10 | G17: =G16+D17*'Target State'!C10*$C$10+SUM($D$14:$D16)*'Target State'!C10*(1-$C$10)/2 | H17: =G17 | I17: =IF(H17>='Target State'!C13,"YES","")
B18: 5 | C18: =YEAR('Current State'!C7)+4 | D18: =IF(H17>='Target State'!C13,0,$C$7) | E18: =D18*$C$9 | F18: =D18*'Target State'!C10*$C$10 | G18: =G17+D18*'Target State'!C10*$C$10+SUM($D$14:$D17)*'Target State'!C10*(1-$C$10)/2 | H18: =G18 | I18: =IF(H18>='Target State'!C13,"YES","")
B19: 6 | C19: =YEAR('Current State'!C7)+5 | D19: =IF(H18>='Target State'!C13,0,$C$7) | E19: =D19*$C$9 | F19: =D19*'Target State'!C10*$C$10 | G19: =G18+D19*'Target State'!C10*$C$10+SUM($D$14:$D18)*'Target State'!C10*(1-$C$10)/2 | H19: =G19 | I19: =IF(H19>='Target State'!C13,"YES","")
B20: 7 | C20: =YEAR('Current State'!C7)+6 | D20: =IF(H19>='Target State'!C13,0,$C$7) | E20: =D20*$C$9 | F20: =D20*'Target State'!C10*$C$10 | G20: =G19+D20*'Target State'!C10*$C$10+SUM($D$14:$D19)*'Target State'!C10*(1-$C$10)/2 | H20: =G20 | I20: =IF(H20>='Target State'!C13,"YES","")
A22: Note: schedule shows the optimistic pace. Conservative pace is modeled on the Quit Date Calculator tab. This table assumes you don't sell — additions are layered on top of the current portfolio. The Conversation Doc tab folds this into the partner-facing summary.
A27: Questions? hello@thestrledger.com
A28: STR-001 · Acquisition Schedule

Sheet Risk Plan
A2: =HYPERLINK("#'Acquisition Schedule'!A1", "← BACK") | D2: RISK PLAN | J2: =HYPERLINK("#'Quit Date Calculator'!A1", "NEXT →")
A4: Section 4 — what no one talks about: healthcare bridge, insurance gap, partner buy-in.
A6: HEALTHCARE BRIDGE
B7: Current employer cost ($/yr): | C7: 3600 | E7: Your share of premium today
B8: COBRA cost ($/yr, family): | C8: 14400 | E8: Typically 102% of full premium — DOL
B9: ACA cost ($/yr, family): | C9: 9600 | E9: Post-subsidy mid-range — KFF benchmark
B10: COBRA bridge (months): | C10: 18 | E10: Max 18 per federal law
B11: ACA bridge (months): | C11: 24 | E11: Until STR income covers ACA
A13: INSURANCE & BENEFITS LOST
B14: Disability insurance lost ($/yr): | C14: 1800 | E14: Replacement long-term disability premium
B15: Life insurance lost ($/yr): | C15: 600 | E15: Term life premium to replace employer policy
A17: PARTNER RISK-SHARE
B18: Partner expense coverage (%): | C18: 0.4 | E18: Share of household expenses partner W2 covers in transition
B19: Partner buy-in (1-5): | C19: 4 | E19: 1=skeptical, 5=enthusiastic — drives Conservative scenario
A21: HEADLINE NUMBERS (referenced by Start tab as C22)
B22: HEALTHCARE BRIDGE TOTAL ($): | C22: =(C8*C10/12)+(C9*C11/12)
B23: Insurance gap total ($/yr): | C23: =C14+C15
B24: Annual partner coverage ($): | C24: =C18*'Current State'!C22
A28: Questions? hello@thestrledger.com
A29: STR-001 · Risk Plan

Sheet Quit Date Calculator
A2: =HYPERLINK("#'Risk Plan'!A1", "← BACK") | D2: QUIT DATE CALCULATOR | J2: =HYPERLINK("#'Conversation Doc'!A1", "NEXT →")
A4: Section 5 — the math behind the headline date. Adjust assumptions below.
A6: QUIT DATES
B7: Optimistic quit date: | C7: =EDATE('Current State'!C7,(MAX(0,'Target State'!C16/C12))*12)
B8: Conservative quit date: | C8: =EDATE('Current State'!C7,(MAX(0,'Target State'!C16/C13)*(1+(5-'Risk Plan'!C19)/10))*12)
B9: Spread (years): | C9: =(C8-C7)/365.25
A11: ASSUMPTIONS (edit to test scenarios)
B12: Optimistic props/year: | C12: 3 | E12: Faster pace + current per-prop economics
B13: Conservative props/year: | C13: 1.5 | E13: Slower pace; further adjusted by partner buy-in
B14: Optimistic stabilized occ: | C14: 0.68 | E14: Used by acquisition modeling
B15: Conservative stabilized occ: | C15: 0.55
A17: HEADLINE NUMBERS (referenced by Start tab)
B18: Stabilized portfolio at quit ($/yr): | C18: ='Target State'!C17*'Target State'!C10
B19: Y1 PROJECTED NET ($/yr): | C19: =C18*0.65
A23: Questions? hello@thestrledger.com
A24: STR-001 · Quit Date Calculator

Sheet Conversation Doc
A2: =HYPERLINK("#'Quit Date Calculator'!A1", "← BACK") | D2: CONVERSATION DOC
A4: ="Our Path Off W2 — "&TEXT(TODAY(),"mmmm d, yyyy")
A7: A calm reading of where we are, what we need, and when the math says we can.
A9: QUIT DATE
B10: Optimistic | D10: Conservative
B11: ='Quit Date Calculator'!C7 | D11: ='Quit Date Calculator'!C8
A14: THE FOUR NUMBERS
B15: Properties needed: | C15: ='Target State'!C20
B16: Cash needed at quit: | C16: ='Target State'!C22
B17: Healthcare bridge: | C17: ='Risk Plan'!C22
B18: Y1-after-quit projected net: | C18: ='Quit Date Calculator'!C19
A20: THREE BIGGEST SWING FACTORS
B21: 1. Acquisition pace | C21: ="Optimistic adds "&TEXT('Quit Date Calculator'!C12,"0.0")&" props/yr; conservative "&TEXT('Quit Date Calculator'!C13,"0.0")&"/yr."
B22: 2. Healthcare bridge | C22: ="Total bridge cost "&TEXT('Risk Plan'!C20,"$#,##0")&" across "&'Risk Plan'!C10&"mo COBRA + "&'Risk Plan'!C11&"mo ACA."
B23: 3. Partner buy-in | C23: ="Buy-in level "&'Risk Plan'!C19&"/5. Partner covers "&TEXT('Risk Plan'!C18,"0%")&" of expenses during transition."
A25: ACTION PLAN — NEXT THREE PROPERTIES
B26: # | C26: Plan year | D26: Cash needed | E26: Notes
B27: 1 | C27: =YEAR('Current State'!C7)+0 | D27: ='Acquisition Schedule'!C9
B28: 2 | C28: =YEAR('Current State'!C7)+1 | D28: ='Acquisition Schedule'!C9
B29: 3 | C29: =YEAR('Current State'!C7)+2 | D29: ='Acquisition Schedule'!C9
A31: RISK ACKNOWLEDGMENTS
B32: · We have priced the healthcare bridge into our target replacement income.
B33: · We have a partner risk-share plan if STR income disappoints in Y1.
B34: · We will re-run this workbook after every property close.
B35: · We will not quit until the conservative cash flow figure is positive.
A38: PARTNER SIGN-OFF
B39: Signed:
B40: Date:
B41: Signed:
B42: Date:
