Workbook

Sheet Start
A2: The STR Ledger
A4: STR Mileage Log
A5: Close your year before April does.
A7: TAX-001 · v2.3 · DEMO
A10: WHAT THIS DOES
A11: The IRS requires 4 things on every business-mileage entry: date, destination, business purpose, and miles driven (Pub 463). This log captures all 4 plus odometer readings, property allocation, and calculated $ deduction at the current rate. Print the Monthly Summary and YTD Dashboard tabs for your CPA at year-end.
A18: HOW TO USE
A19: ① Click the navy button below to open the Mileage Log — log one row per trip.
A20: ② Use odometer columns (Start + End) OR type miles directly. Formula prefers odometer.
A21: ③ Fill 'Duration (hr)' too — it counts toward 100/500-hour material-participation tests.
A22: ④ Column K shows ✓ when an entry meets the IRS 4-element rule; ⚠ flags missing fields.
A23: ⑤ Log within 7 days of each trip — auditors disallow records reconstructed at year-end.
A26: =HYPERLINK("#'Mileage Log'!A6", "→ ADD A NEW TRIP (OPEN MILEAGE LOG)")
A32: TRIPS LOGGED | E32: YTD DEDUCTION | I32: LAST ENTRY
A33: =COUNTA('Mileage Log'!A6:A2005) | E33: ='Monthly Summary'!C19 | I33: =IFERROR(TEXT(MAX('Mileage Log'!A6:A2005),"yyyy-mm-dd"),"—")
A35: trips this year | E35: at current IRS rate | I35: most recent trip date
A39: =HYPERLINK("#'Monthly Summary'!A1", "Monthly Summary") | D39: =HYPERLINK("#'YTD Dashboard'!A1", "YTD Dashboard") | G39: =HYPERLINK("#'Monthly Summary'!A1", "📄 Print Packet") | J39: =HYPERLINK("#'Settings'!A1", "Settings")
A42: 📄 TAX TIME: print Monthly Summary + YTD Dashboard (File → Print → 'Print Active Sheets'). 📅 YEAR END: copy YTD totals into Settings → Year-end Archive before Jan 1.
A44: ⚠ IRS rate updates January 1 each year. Current 2026: $0.725/mi (Notice 2026-10). Update Settings → B5 each January (irs.gov Publication 463).
A46: 💡 Upgrade to the Full version at thestrledger.com/upgrade — multi-property, depreciation, multi-LLC support.
A49: Questions? hello@thestrledger.com
A50: TAX-001 · v2.2 · Free updates forever

Sheet Mileage Log
A2: =HYPERLINK("#'Start'!A1", "← BACK") | D2: MILEAGE LOG | J2: =HYPERLINK("#'Monthly Summary'!A1", "NEXT →")
A4: One row per trip — odometer or typed miles
A5: Trip Date | B5: Property | C5: Destination | D5: Business Purpose | E5: Start Odo | F5: End Odo | G5: Miles (typed alt) | H5: Calculated Miles | I5: $ Deduction | J5: Notes | K5: ✔ IRS | L5: Duration (hr) | M5: 📎 Receipt | N5: Logged On | O5: Parking + Tolls $
A6: 46027 | B6: Smokies Ridge | C6: Home Depot run | D6: Supplies run | E6: 45120 | F6: 45144 | H6: =IF(AND(E6<>"",F6<>""), F6-E6, IF(G6<>"", G6, 0)) | I6: =H6*Settings!$B$5 | J6: Hot tub chemicals | K6: =IF(AND(A6<>"",C6<>"",D6<>"",H6>0),"✓","⚠ missing") | L6: 1.5 | M6: Y | N6: 46027
A7: 46030 | B7: Smokies Ridge | C7: Property inspection visit | D7: Property inspection | E7: 45150 | F7: 45195 | H7: =IF(AND(E7<>"",F7<>""), F7-E7, IF(G7<>"", G7, 0)) | I7: =H7*Settings!$B$5 | J7: Quarterly inspection | K7: =IF(AND(A7<>"",C7<>"",D7<>"",H7>0),"✓","⚠ missing") | L7: 2.5 | N7: 46031
A8: 46037 | B8: Creek Side | C8: Knoxville airport guest pickup | D8: Guest transport | E8: 45200 | F8: 45292 | H8: =IF(AND(E8<>"",F8<>""), F8-E8, IF(G8<>"", G8, 0)) | I8: =H8*Settings!$B$5 | J8: Airbnb Plus comped ride | K8: =IF(AND(A8<>"",C8<>"",D8<>"",H8>0),"✓","⚠ missing") | L8: 3 | N8: 46037 | O8: 14
A9: 46042 | B9: Smokies Ridge | C9: Meet new cleaner onsite | D9: Meeting cleaner / staff | E9: 45300 | F9: 45345 | H9: =IF(AND(E9<>"",F9<>""), F9-E9, IF(G9<>"", G9, 0)) | I9: =H9*Settings!$B$5 | J9: Onboard Jamie | K9: =IF(AND(A9<>"",C9<>"",D9<>"",H9>0),"✓","⚠ missing") | L9: 2 | N9: 46043
A10: 46055 | B10: Creek Side | C10: Turnover walkthrough | D10: Turnover (laundry/clean) | E10: 45400 | F10: 45490 | H10: =IF(AND(E10<>"",F10<>""), F10-E10, IF(G10<>"", G10, 0)) | I10: =H10*Settings!$B$5 | K10: =IF(AND(A10<>"",C10<>"",D10<>"",H10>0),"✓","⚠ missing") | L10: 4 | M10: Y | N10: 46055
A11: 46060 | B11: Lakehouse A | C11: Supplies + inspection | D11: Supplies run | E11: 45500 | F11: 45565 | H11: =IF(AND(E11<>"",F11<>""), F11-E11, IF(G11<>"", G11, 0)) | I11: =H11*Settings!$B$5 | K11: =IF(AND(A11<>"",C11<>"",D11<>"",H11>0),"✓","⚠ missing") | L11: 2.5 | M11: Y | N11: 46061
A12: 46063 | B12: Smokies Ridge | C12: Burst pipe emergency | D12: Emergency response | E12: 45600 | F12: 45648 | H12: =IF(AND(E12<>"",F12<>""), F12-E12, IF(G12<>"", G12, 0)) | I12: =H12*Settings!$B$5 | J12: Plumber met me | K12: =IF(AND(A12<>"",C12<>"",D12<>"",H12>0),"✓","⚠ missing") | L12: 3.5 | M12: Y | N12: 46063
A13: 46067 | B13: Creek Side | C13: Hot tub service | D13: Contractor walkthrough | E13: 45700 | F13: 45790 | H13: =IF(AND(E13<>"",F13<>""), F13-E13, IF(G13<>"", G13, 0)) | I13: =H13*Settings!$B$5 | K13: =IF(AND(A13<>"",C13<>"",D13<>"",H13>0),"✓","⚠ missing") | L13: 2 | N13: 46068
A14: 46071 | B14: Lakehouse A | C14: Quarterly inspection | D14: Property inspection | E14: 45800 | F14: 45867 | H14: =IF(AND(E14<>"",F14<>""), F14-E14, IF(G14<>"", G14, 0)) | I14: =H14*Settings!$B$5 | K14: =IF(AND(A14<>"",C14<>"",D14<>"",H14>0),"✓","⚠ missing") | L14: 2.5 | N14: 46072
A15: 46075 | B15: Smokies Ridge | C15: Guest pickup airport | D15: Guest transport | E15: 45900 | F15: 45992 | H15: =IF(AND(E15<>"",F15<>""), F15-E15, IF(G15<>"", G15, 0)) | I15: =H15*Settings!$B$5 | K15: =IF(AND(A15<>"",C15<>"",D15<>"",H15>0),"✓","⚠ missing") | L15: 3 | N15: 46075 | O15: 18
A16: 46081 | B16: Creek Side | C16: Cleaner check-in | D16: Meeting cleaner / staff | E16: 46050 | F16: 46095 | H16: =IF(AND(E16<>"",F16<>""), F16-E16, IF(G16<>"", G16, 0)) | I16: =H16*Settings!$B$5 | K16: =IF(AND(A16<>"",C16<>"",D16<>"",H16>0),"✓","⚠ missing") | L16: 1.5 | N16: 46082
A17: 46086 | B17: Lakehouse A | C17: Lowe's run | D17: Supplies run | E17: 46150 | F17: 46178 | H17: =IF(AND(E17<>"",F17<>""), F17-E17, IF(G17<>"", G17, 0)) | I17: =H17*Settings!$B$5 | J17: Bought new kettle | K17: =IF(AND(A17<>"",C17<>"",D17<>"",H17>0),"✓","⚠ missing") | L17: 1 | M17: Y | N17: 46086
A18: 46091 | B18: Smokies Ridge | C18: Turnover issue callback | D18: Turnover (laundry/clean) | E18: 46200 | F18: 46245 | H18: =IF(AND(E18<>"",F18<>""), F18-E18, IF(G18<>"", G18, 0)) | I18: =H18*Settings!$B$5 | J18: Guest complaint follow-up | K18: =IF(AND(A18<>"",C18<>"",D18<>"",H18>0),"✓","⚠ missing") | L18: 2 | N18: 46092
A19: 46095 | B19: Creek Side | C19: Handyman meeting | D19: Contractor walkthrough | E19: 46300 | F19: 46349 | H19: =IF(AND(E19<>"",F19<>""), F19-E19, IF(G19<>"", G19, 0)) | I19: =H19*Settings!$B$5 | K19: =IF(AND(A19<>"",C19<>"",D19<>"",H19>0),"✓","⚠ missing") | L19: 1.5 | N19: 46096
A20: 46099 | B20: Smokies Ridge | C20: Bank deposit run | D20: Bank / deposit | E20: 46400 | F20: 46420 | H20: =IF(AND(E20<>"",F20<>""), F20-E20, IF(G20<>"", G20, 0)) | I20: =H20*Settings!$B$5 | J20: Q1 guest deposits | K20: =IF(AND(A20<>"",C20<>"",D20<>"",H20>0),"✓","⚠ missing") | L20: 0.75 | M20: Y | N20: 46099
A21: 46103 | B21: Lakehouse A | C21: Guest transport — late flight | D21: Guest transport | E21: 46500 | F21: 46587 | H21: =IF(AND(E21<>"",F21<>""), F21-E21, IF(G21<>"", G21, 0)) | I21: =H21*Settings!$B$5 | K21: =IF(AND(A21<>"",C21<>"",D21<>"",H21>0),"✓","⚠ missing") | L21: 3.5 | N21: 46103 | O21: 22
A22: 46106 | B22: Creek Side | C22: Supplies — Costco | D22: Supplies run | E22: 46650 | F22: 46695 | H22: =IF(AND(E22<>"",F22<>""), F22-E22, IF(G22<>"", G22, 0)) | I22: =H22*Settings!$B$5 | K22: =IF(AND(A22<>"",C22<>"",D22<>"",H22>0),"✓","⚠ missing") | L22: 1.5 | M22: Y | N22: 46107
A23: 46109 | B23: Smokies Ridge | C23: Mailing key set to next guest | D23: Mailing / post office | E23: 46800 | F23: 46815 | H23: =IF(AND(E23<>"",F23<>""), F23-E23, IF(G23<>"", G23, 0)) | I23: =H23*Settings!$B$5 | J23: Lockbox malfunction backup | K23: =IF(AND(A23<>"",C23<>"",D23<>"",H23>0),"✓","⚠ missing") | L23: 0.5 | M23: Y | N23: 46109
A24: 46111 | B24: Lakehouse A | C24: CPA tax-prep meeting | D24: CPA / attorney meeting | E24: 46900 | F24: 46928 | H24: =IF(AND(E24<>"",F24<>""), F24-E24, IF(G24<>"", G24, 0)) | I24: =H24*Settings!$B$5 | J24: Q1 review (Re: Smith CPA) | K24: =IF(AND(A24<>"",C24<>"",D24<>"",H24>0),"✓","⚠ missing") | L24: 1.5 | M24: Y | N24: 46112
A25: 46112 | B25: Smokies Ridge | C25: Month-end inspection | D25: Property inspection | E25: 46950 | F25: 46995 | H25: =IF(AND(E25<>"",F25<>""), F25-E25, IF(G25<>"", G25, 0)) | I25: =H25*Settings!$B$5 | K25: =IF(AND(A25<>"",C25<>"",D25<>"",H25>0),"✓","⚠ missing") | L25: 2 | N25: 46113
H26: =IF(AND(E26<>"",F26<>""), F26-E26, IF(G26<>"", G26, 0)) | I26: =H26*Settings!$B$5 | K26: =IF(AND(A26<>"",C26<>"",D26<>"",H26>0),"✓","⚠ missing")
H27: =IF(AND(E27<>"",F27<>""), F27-E27, IF(G27<>"", G27, 0)) | I27: =H27*Settings!$B$5 | K27: =IF(AND(A27<>"",C27<>"",D27<>"",H27>0),"✓","⚠ missing")
H28: =IF(AND(E28<>"",F28<>""), F28-E28, IF(G28<>"", G28, 0)) | I28: =H28*Settings!$B$5 | K28: =IF(AND(A28<>"",C28<>"",D28<>"",H28>0),"✓","⚠ missing")
H29: =IF(AND(E29<>"",F29<>""), F29-E29, IF(G29<>"", G29, 0)) | I29: =H29*Settings!$B$5 | K29: =IF(AND(A29<>"",C29<>"",D29<>"",H29>0),"✓","⚠ missing")
H30: =IF(AND(E30<>"",F30<>""), F30-E30, IF(G30<>"", G30, 0)) | I30: =H30*Settings!$B$5 | K30: =IF(AND(A30<>"",C30<>"",D30<>"",H30>0),"✓","⚠ missing")
H31: =IF(AND(E31<>"",F31<>""), F31-E31, IF(G31<>"", G31, 0)) | I31: =H31*Settings!$B$5 | K31: =IF(AND(A31<>"",C31<>"",D31<>"",H31>0),"✓","⚠ missing")
H32: =IF(AND(E32<>"",F32<>""), F32-E32, IF(G32<>"", G32, 0)) | I32: =H32*Settings!$B$5 | K32: =IF(AND(A32<>"",C32<>"",D32<>"",H32>0),"✓","⚠ missing")
H33: =IF(AND(E33<>"",F33<>""), F33-E33, IF(G33<>"", G33, 0)) | I33: =H33*Settings!$B$5 | K33: =IF(AND(A33<>"",C33<>"",D33<>"",H33>0),"✓","⚠ missing")
H34: =IF(AND(E34<>"",F34<>""), F34-E34, IF(G34<>"", G34, 0)) | I34: =H34*Settings!$B$5 | K34: =IF(AND(A34<>"",C34<>"",D34<>"",H34>0),"✓","⚠ missing")
H35: =IF(AND(E35<>"",F35<>""), F35-E35, IF(G35<>"", G35, 0)) | I35: =H35*Settings!$B$5 | K35: =IF(AND(A35<>"",C35<>"",D35<>"",H35>0),"✓","⚠ missing")
H36: =IF(AND(E36<>"",F36<>""), F36-E36, IF(G36<>"", G36, 0)) | I36: =H36*Settings!$B$5 | K36: =IF(AND(A36<>"",C36<>"",D36<>"",H36>0),"✓","⚠ missing")
H37: =IF(AND(E37<>"",F37<>""), F37-E37, IF(G37<>"", G37, 0)) | I37: =H37*Settings!$B$5 | K37: =IF(AND(A37<>"",C37<>"",D37<>"",H37>0),"✓","⚠ missing")
... H2005: =IF(AND(E2005<>"",F2005<>""), F2005-E2005, IF(G2005<>"", G2005, 0)) | I2005: =H2005*Settings!$B$5 | K2005: =IF(AND(A2005<>"",C2005<>"",D2005<>"",H2005>0),"✓","⚠ missing")

Sheet Monthly Summary
A2: =HYPERLINK("#'Mileage Log'!A1", "← BACK") | D2: MONTHLY SUMMARY | J2: =HYPERLINK("#'YTD Dashboard'!A1", "NEXT →")
A4: Auto-calculated from the Mileage Log
A5: Month | B5: Miles | C5: $ Deduction | D5: Trip Count
A6: Jan | B6: =SUMIFS('Mileage Log'!$H:$H,'Mileage Log'!$A:$A,">="&DATE(Settings!$B$6,1,1),'Mileage Log'!$A:$A,"<"&DATE(Settings!$B$6,2,1)) | C6: =B6*Settings!$B$5 | D6: =COUNTIFS('Mileage Log'!$A:$A,">="&DATE(Settings!$B$6,1,1),'Mileage Log'!$A:$A,"<"&DATE(Settings!$B$6,2,1))
A7: Feb | B7: =SUMIFS('Mileage Log'!$H:$H,'Mileage Log'!$A:$A,">="&DATE(Settings!$B$6,2,1),'Mileage Log'!$A:$A,"<"&DATE(Settings!$B$6,3,1)) | C7: =B7*Settings!$B$5 | D7: =COUNTIFS('Mileage Log'!$A:$A,">="&DATE(Settings!$B$6,2,1),'Mileage Log'!$A:$A,"<"&DATE(Settings!$B$6,3,1))
A8: Mar | B8: =SUMIFS('Mileage Log'!$H:$H,'Mileage Log'!$A:$A,">="&DATE(Settings!$B$6,3,1),'Mileage Log'!$A:$A,"<"&DATE(Settings!$B$6,4,1)) | C8: =B8*Settings!$B$5 | D8: =COUNTIFS('Mileage Log'!$A:$A,">="&DATE(Settings!$B$6,3,1),'Mileage Log'!$A:$A,"<"&DATE(Settings!$B$6,4,1))
A9: Apr | B9: =SUMIFS('Mileage Log'!$H:$H,'Mileage Log'!$A:$A,">="&DATE(Settings!$B$6,4,1),'Mileage Log'!$A:$A,"<"&DATE(Settings!$B$6,5,1)) | C9: =B9*Settings!$B$5 | D9: =COUNTIFS('Mileage Log'!$A:$A,">="&DATE(Settings!$B$6,4,1),'Mileage Log'!$A:$A,"<"&DATE(Settings!$B$6,5,1))
A10: May | B10: =SUMIFS('Mileage Log'!$H:$H,'Mileage Log'!$A:$A,">="&DATE(Settings!$B$6,5,1),'Mileage Log'!$A:$A,"<"&DATE(Settings!$B$6,6,1)) | C10: =B10*Settings!$B$5 | D10: =COUNTIFS('Mileage Log'!$A:$A,">="&DATE(Settings!$B$6,5,1),'Mileage Log'!$A:$A,"<"&DATE(Settings!$B$6,6,1))
A11: Jun | B11: =SUMIFS('Mileage Log'!$H:$H,'Mileage Log'!$A:$A,">="&DATE(Settings!$B$6,6,1),'Mileage Log'!$A:$A,"<"&DATE(Settings!$B$6,7,1)) | C11: =B11*Settings!$B$5 | D11: =COUNTIFS('Mileage Log'!$A:$A,">="&DATE(Settings!$B$6,6,1),'Mileage Log'!$A:$A,"<"&DATE(Settings!$B$6,7,1))
A12: Jul | B12: =SUMIFS('Mileage Log'!$H:$H,'Mileage Log'!$A:$A,">="&DATE(Settings!$B$6,7,1),'Mileage Log'!$A:$A,"<"&DATE(Settings!$B$6,8,1)) | C12: =B12*Settings!$B$5 | D12: =COUNTIFS('Mileage Log'!$A:$A,">="&DATE(Settings!$B$6,7,1),'Mileage Log'!$A:$A,"<"&DATE(Settings!$B$6,8,1))
A13: Aug | B13: =SUMIFS('Mileage Log'!$H:$H,'Mileage Log'!$A:$A,">="&DATE(Settings!$B$6,8,1),'Mileage Log'!$A:$A,"<"&DATE(Settings!$B$6,9,1)) | C13: =B13*Settings!$B$5 | D13: =COUNTIFS('Mileage Log'!$A:$A,">="&DATE(Settings!$B$6,8,1),'Mileage Log'!$A:$A,"<"&DATE(Settings!$B$6,9,1))
A14: Sep | B14: =SUMIFS('Mileage Log'!$H:$H,'Mileage Log'!$A:$A,">="&DATE(Settings!$B$6,9,1),'Mileage Log'!$A:$A,"<"&DATE(Settings!$B$6,10,1)) | C14: =B14*Settings!$B$5 | D14: =COUNTIFS('Mileage Log'!$A:$A,">="&DATE(Settings!$B$6,9,1),'Mileage Log'!$A:$A,"<"&DATE(Settings!$B$6,10,1))
A15: Oct | B15: =SUMIFS('Mileage Log'!$H:$H,'Mileage Log'!$A:$A,">="&DATE(Settings!$B$6,10,1),'Mileage Log'!$A:$A,"<"&DATE(Settings!$B$6,11,1)) | C15: =B15*Settings!$B$5 | D15: =COUNTIFS('Mileage Log'!$A:$A,">="&DATE(Settings!$B$6,10,1),'Mileage Log'!$A:$A,"<"&DATE(Settings!$B$6,11,1))
A16: Nov | B16: =SUMIFS('Mileage Log'!$H:$H,'Mileage Log'!$A:$A,">="&DATE(Settings!$B$6,11,1),'Mileage Log'!$A:$A,"<"&DATE(Settings!$B$6,12,1)) | C16: =B16*Settings!$B$5 | D16: =COUNTIFS('Mileage Log'!$A:$A,">="&DATE(Settings!$B$6,11,1),'Mileage Log'!$A:$A,"<"&DATE(Settings!$B$6,12,1))
A17: Dec | B17: =SUMIFS('Mileage Log'!$H:$H,'Mileage Log'!$A:$A,">="&DATE(Settings!$B$6,12,1),'Mileage Log'!$A:$A,"<"&DATE(Settings!$B$6+1,1,1)) | C17: =B17*Settings!$B$5 | D17: =COUNTIFS('Mileage Log'!$A:$A,">="&DATE(Settings!$B$6,12,1),'Mileage Log'!$A:$A,"<"&DATE(Settings!$B$6+1,1,1))
A19: YTD Total | B19: =SUM(B6:B17) | C19: =SUM(C6:C17) | D19: =SUM(D6:D17)

Sheet YTD Dashboard
A2: =HYPERLINK("#'Monthly Summary'!A1", "← BACK") | D2: YTD DASHBOARD · FOR YOUR CPA | J2: =HYPERLINK("#'Settings'!A1", "NEXT →")
A4: 📄 FOR YOUR CPA — print this tab. Totals + breakdown by purpose and property.
A5: YTD Total Miles: | B5: ='Monthly Summary'!B19
A6: YTD Total Deduction ($): | B6: ='Monthly Summary'!C19
A7: YTD Trips: | B7: ='Monthly Summary'!D19
A8: YTD Hours (material participation): | B8: =SUM('Mileage Log'!L6:L2005)
A9: YTD Parking + Tolls ($): | B9: =SUM('Mileage Log'!O6:O2005)
A11: Miles by Business Purpose
A12: Purpose | B12: Miles | C12: $
A13: Property inspection | B13: =SUMIFS('Mileage Log'!$H:$H,'Mileage Log'!$D:$D,A13) | C13: =B13*Settings!$B$5
A14: Turnover (laundry/clean) | B14: =SUMIFS('Mileage Log'!$H:$H,'Mileage Log'!$D:$D,A14) | C14: =B14*Settings!$B$5
A15: Supplies run | B15: =SUMIFS('Mileage Log'!$H:$H,'Mileage Log'!$D:$D,A15) | C15: =B15*Settings!$B$5
A16: Guest transport | B16: =SUMIFS('Mileage Log'!$H:$H,'Mileage Log'!$D:$D,A16) | C16: =B16*Settings!$B$5
A17: Repairs | B17: =SUMIFS('Mileage Log'!$H:$H,'Mileage Log'!$D:$D,A17) | C17: =B17*Settings!$B$5
A18: Contractor walkthrough | B18: =SUMIFS('Mileage Log'!$H:$H,'Mileage Log'!$D:$D,A18) | C18: =B18*Settings!$B$5
A19: Emergency response | B19: =SUMIFS('Mileage Log'!$H:$H,'Mileage Log'!$D:$D,A19) | C19: =B19*Settings!$B$5
A20: Meeting cleaner / staff | B20: =SUMIFS('Mileage Log'!$H:$H,'Mileage Log'!$D:$D,A20) | C20: =B20*Settings!$B$5
A21: Bank / deposit | B21: =SUMIFS('Mileage Log'!$H:$H,'Mileage Log'!$D:$D,A21) | C21: =B21*Settings!$B$5
A22: Mailing / post office | B22: =SUMIFS('Mileage Log'!$H:$H,'Mileage Log'!$D:$D,A22) | C22: =B22*Settings!$B$5
A23: CPA / attorney meeting | B23: =SUMIFS('Mileage Log'!$H:$H,'Mileage Log'!$D:$D,A23) | C23: =B23*Settings!$B$5
A24: Other (describe in Notes) | B24: =SUMIFS('Mileage Log'!$H:$H,'Mileage Log'!$D:$D,A24) | C24: =B24*Settings!$B$5
A26: Miles by Property
A27: Property | B27: Miles | C27: $
A28: Smokies Ridge | B28: =SUMIFS('Mileage Log'!$H:$H,'Mileage Log'!$B:$B,A28) | C28: =B28*Settings!$B$5
A29: Creek Side | B29: =SUMIFS('Mileage Log'!$H:$H,'Mileage Log'!$B:$B,A29) | C29: =B29*Settings!$B$5
A30: Lakehouse A | B30: =SUMIFS('Mileage Log'!$H:$H,'Mileage Log'!$B:$B,A30) | C30: =B30*Settings!$B$5
A32: =IF(Settings!$B$15="Schedule E (passive)","→ Schedule E (Form 1040), Line 6.",IF(Settings!$B$15="Schedule C (active)","→ Schedule C, Line 9 + Form 4562 Part V.","→ Schedule routing not set — see Settings."))

Sheet Settings
A2: =HYPERLINK("#'YTD Dashboard'!A1", "← BACK") | D2: SETTINGS
A4: IRS rate · tax classification · Form 4562 · vehicles · sources
A5: IRS Rate (per mile, business): | B5: 0.725 | C5: 📅 Rate as of 2026-01-01 — IRS publishes the next year's rate each Dec; edit B5 then.
A6: Active tax year: | B6: 2026
A7: Historical rates for reference: | I7: Frequent destinations:
A8: 2023: | B8: 0.655
A9: 2024: | B9: 0.67
A10: 2025: | B10: 0.7 | E10: Property list | G10: Purpose list | I10: From | J10: To | K10: Typical mi
E11: Smokies Ridge | G11: Property inspection | I11: Smokies Ridge | J11: Home Depot | K11: 24
A12: Tax Classification & Recordkeeping | E12: Creek Side | G12: Turnover (laundry/clean) | I12: Smokies Ridge | J12: Knoxville airport | K12: 46
A13: Home office is principal place of business: | B13: Not yet established | E13: Lakehouse A | G13: Supplies run | I13: Smokies Ridge | J13: Lowe's | K13: 22
A14: If 'Yes', trips from home → STR are deductible business travel. If 'No', they're non-deductible commuting (track separately for Form 4562 Part V below). | I14: Smokies Ridge | J14: Costco | K14: 52
A15: Schedule classification: | B15: Ask my CPA | G15: Repairs | I15: Creek Side | J15: Home Depot | K15: 18
A16: ⚠ Substantial-services trigger: if you provide cleaning DURING stays, meals, or concierge, IRS requires Schedule C (15.3% self-employment tax applies). | I16: Creek Side | J16: Knoxville airport | K16: 45
G17: Emergency response | I17: Lakehouse A | J17: Home Depot | K17: 14
A18: Form 4562 Part V — Vehicle Information | G18: Meeting cleaner / staff | I18: Lakehouse A | J18: Costco | K18: 33
A19: Required if you depreciate the vehicle (actual-expense method or Section 179). Hand these numbers to your CPA at year-end.
A20: Year-start odometer: | G20: Mailing / post office
A21: Year-end odometer: | G21: CPA / attorney meeting
A22: Total miles (all use): | B22: =IF(AND(B20<>"",B21<>""),B21-B20,0) | G22: Other (describe in Notes)
A23: Total business miles (logged): | B23: =SUM('Mileage Log'!H6:H2005)
A24: Total commuting miles:
A25: Total personal miles: | B25: =IF(B22>0,B22-B23-B24,0)
A26: Business use %: | B26: =IF(B22>0,B23/B22,0)
A27: ⚠ If Business Use % drops to 50% or below, IRS disallows Section 179 / accelerated depreciation and may recapture prior-year deductions as ordinary income (IRC §280F).
A28: Vehicles & Method Election
A29: List each vehicle once. The Method (Standard mileage / Actual expenses) locks in Year 1 for owned cars; leased cars must keep Standard for the full lease (Pub 463).
A30: Nickname | B30: Year placed in service | C30: Owned/Leased | D30: Method | E30: Notes
A31: Truck (F-150) | B31: 2026 | C31: Owned | D31: Standard mileage | E31: Primary STR vehicle
A35: Year-end Archive
A36: Each January, copy YTD totals into the row for the closing year, then clear the Mileage Log for the new year.
A37: Year | B37: Total Miles | C37: Total $ | D37: # Trips
A38: 2024
A39: 2025
A40: 2026
A41: 2027
A42: 2028
A43: 2029
A44: 2030
