Workbook

Sheet Start
A2: The STR Ledger
A4: Home Office Allocator
A5: Make your laundry room pay you back.
A6: =IF(IFERROR('Launch'!A10,0)>0,"✅ Home-office deduction = "&TEXT('Launch'!A10,"$#,##0")&" · "&'Launch'!E10&" method.","📊 Fill Eligibility + Space Allocation to see your deduction.")
A7: TAX-006 · v2.3 · DEMO
A11: What you'll get
A13: 📐 BUSINESS-USE % | E13: ⚖ METHOD COMPARE | I13: 📄 FORM 8829
A14: Your office sqft as a % of total home — drives every indirect expense. | E14: Simplified ($5/sqft, max $1,500) vs Actual side-by-side, recommend the better one. | I14: Print-ready Form 8829 mirror — Schedule E line 18a or Schedule C line 30.
A23: Quick Start — be done in 10 minutes
B24: ① Eligibility: regular + exclusive + principal place tests | H24: ④ Actual expenses: utilities, insurance, mortgage int., depreciation
B25: ② Measure: total home sqft, office sqft | H25: ⑤ Routing: Schedule E or Schedule C
B26: ③ Method: Simplified or Actual
A30: =HYPERLINK("#'Eligibility'!A5", "GET STARTED — CHECK ELIGIBILITY →")
A36: Progress: | G36: =TEXT((COUNTA('Eligibility'!B8:B12) + COUNTA('Space Allocation'!B8:B11) + COUNTA('Method Election'!B8) + COUNTA('Actual Expenses'!B8:B17) + COUNTA('STR Routing'!B8))/21,"0%") & " complete"
A38: ① Eligibility | G38: =IF(COUNTA('Eligibility'!B8:B12)=5,"✅ Done",IF(COUNTA('Eligibility'!B8:B12)=0,"⏳ Empty","⏳ "&COUNTA('Eligibility'!B8:B12)&" of 5")) | K38: =HYPERLINK("#'Eligibility'!A5","→ go")
A39: ② Space Allocation | G39: =IF(COUNTA('Space Allocation'!B8:B11)=4,"✅ Done",IF(COUNTA('Space Allocation'!B8:B11)=0,"⏳ Empty","⏳ "&COUNTA('Space Allocation'!B8:B11)&" of 4")) | K39: =HYPERLINK("#'Space Allocation'!A5","→ go")
A40: ③ Method Election | G40: =IF(COUNTA('Method Election'!B8)=1,"✅ Done",IF(COUNTA('Method Election'!B8)=0,"⏳ Empty","⏳ "&COUNTA('Method Election'!B8)&" of 1")) | K40: =HYPERLINK("#'Method Election'!A5","→ go")
A41: ④ Actual Expenses | G41: =IF(COUNTA('Actual Expenses'!B8:B17)=10,"✅ Done",IF(COUNTA('Actual Expenses'!B8:B17)=0,"⏳ Empty","⏳ "&COUNTA('Actual Expenses'!B8:B17)&" of 10")) | K41: =HYPERLINK("#'Actual Expenses'!A5","→ go")
A42: ⑤ STR Routing | G42: =IF(COUNTA('STR Routing'!B8)=1,"✅ Done",IF(COUNTA('STR Routing'!B8)=0,"⏳ Empty","⏳ "&COUNTA('STR Routing'!B8)&" of 1")) | K42: =HYPERLINK("#'STR Routing'!A5","→ go")
A48: Questions? hello@thestrledger.com
A49: TAX-006 · v2.2 · Free updates forever

Sheet Eligibility
A2: =HYPERLINK("#'Start'!A1", "← START") | D2: SECTION 1 OF 5 | J2: =HYPERLINK("#'Space Allocation'!A5", "NEXT →")
A4: Eligibility
A5: IRC §280A — pass all three core tests, or the deduction is zero.
A6: Fill the highlighted fields below.
A7: ELIGIBILITY
A8: Office space used REGULARLY for STR business? | B8: Y
A9: Office space used EXCLUSIVELY for business? | B9: Y
A10: Is this your PRINCIPAL PLACE of STR business? | B10: Y
A11: Used for storage of inventory/samples (alt qualifier)? | B11: N
A12: Used for day-care services (alt qualifier)? | B12: N
A14: ⓘ Three-test rule (IRC §280A): the office must be used (1) regularly, (2) exclusively, and (3) as your principal place of business OR a place where you meet clients/customers OR a separate structure. STR managers typically qualify under 'principal place of business' if substantial admin work happens there and there's no other fixed location.
A16: =HYPERLINK("#'Start'!A1", "← Back: Start") | G16: =HYPERLINK("#'Space Allocation'!A5", "Next: Space Allocation →")

Sheet Space Allocation
A2: =HYPERLINK("#'Eligibility'!A5", "← BACK") | D2: SECTION 2 OF 5 | J2: =HYPERLINK("#'Method Election'!A5", "NEXT →")
A4: Space Allocation
A5: Square footage drives the indirect-expense allocation.
A6: Fill the highlighted fields below.
A7: SPACE ALLOCATION
A8: Total home square footage: | B8: 2400
A9: Office square footage (regular + exclusive): | B9: 110
A10: Total rooms in home (alt method): | B10: 9
A11: Rooms used for business (alt method): | B11: 1
A13: Business-use % (computed): | B13: =IF(B8>0,B9/B8,0)
A15: Business-use % above = office sqft ÷ total home sqft. The IRS also accepts rooms-based allocation if all rooms are roughly equal in size — less common for STR. When in doubt, use sqft.
A17: =HYPERLINK("#'Eligibility'!A5", "← Back: Eligibility") | G17: =HYPERLINK("#'Method Election'!A5", "Next: Method Election →")

Sheet Method Election
A2: =HYPERLINK("#'Space Allocation'!A5", "← BACK") | D2: SECTION 3 OF 5 | J2: =HYPERLINK("#'Actual Expenses'!A5", "NEXT →")
A4: Method Election
A5: Simplified ($5/sqft cap $1,500) vs Actual.
A6: Fill the highlighted fields below.
A7: METHOD ELECTION
A8: Method: | B8: Actual
B11: Simplified | C11: Actual | D11: Difference
A12: Deduction this year | B12: =MIN('Space Allocation'!B9,300)*5 | C12: =IF(B8="Actual",'Actual Expenses'!B22,0) | D12: =C12-B12
A13: Depreciation recapture risk? | B13: "None" | C13: "Yes (Sec 1250)" | D13: ""
A14: Loss carryover allowed? | B14: "No" | C14: "Yes" | D14: ""
A15: Recommended? | B15: =IF(B12>=C12,"✅ Pick this","") | C15: =IF(C12>B12,"✅ Pick this","") | D15: ""
A17: ⚠ Actual-method depreciation locks the home's office-portion into Section 1250 unrecaptured-gain treatment if you sell — taxed at up to 25% on the depreciation recapture. Simplified avoids this. If you plan to sell the home within 5 years, the math often favors Simplified.
A19: =HYPERLINK("#'Space Allocation'!A5", "← Back: Space Allocation") | G19: =HYPERLINK("#'Actual Expenses'!A5", "Next: Actual Expenses →")

Sheet Actual Expenses
A2: =HYPERLINK("#'Method Election'!A5", "← BACK") | D2: SECTION 4 OF 5 | J2: =HYPERLINK("#'STR Routing'!A5", "NEXT →")
A4: Actual Expenses
A5: Direct + indirect + depreciation. Indirect is allocated by business-use %.
A6: Fill the highlighted fields below.
A7: ACTUAL EXPENSES
A8: Direct repairs (only-office, 100% deductible): | B8: 0
A9: Indirect — Electric ($/yr): | B9: 2400
A10: Indirect — Gas ($/yr): | B10: 980
A11: Indirect — Water ($/yr): | B11: 420
A12: Indirect — Internet ($/yr): | B12: 720
A13: Indirect — Insurance ($/yr): | B13: 1840
A14: Indirect — Repairs (whole house): | B14: 620
A15: Indirect — Real estate tax: | B15: 4800
A16: Indirect — Mortgage interest: | B16: 9800
A17: Home depreciable basis (building only): | B17: 312000
A19: Total indirect (sum): | B19: =SUM(B9:B16)
A20: Indirect × business-use % (Form 8829 Line 22): | B20: =B19*'Space Allocation'!B13
A21: Annual depreciation (basis × biz % ÷ 39): | B21: =B17*'Space Allocation'!B13/39
A22: Direct + Indirect × biz% + Depreciation: | B22: =B8+B20+B21
A24: ⓘ Direct expenses (only the office) are 100% deductible. Indirect expenses (whole house) are deductible at the business-use % from the Space Allocation tab. Home depreciation = (basis × business-use %) ÷ 39 yrs.
A26: =HYPERLINK("#'Method Election'!A5", "← Back: Method Election") | G26: =HYPERLINK("#'STR Routing'!A5", "Next: STR Routing →")

Sheet STR Routing
A2: =HYPERLINK("#'Actual Expenses'!A5", "← BACK") | D2: SECTION 5 OF 5 | J2: =HYPERLINK("#'Form 8829 Map'!A5", "NEXT →")
A4: STR Routing
A5: Where the deduction lands on your tax return.
A6: Fill the highlighted fields below.
A7: STR ROUTING
A8: Schedule classification: | B8: Schedule E (passive)
A10: Form line for your deduction: | B10: =IF(B8="Schedule E (passive)","Schedule E Line 18a (Other) — describe as ""Home office""",IF(B8="Schedule C (active)","Schedule C Line 30 (via Form 8829)","Set classification above"))
A12: Schedule E filers: deduction lands on Line 18a (Other) of Schedule E. Schedule C filers: deduction lands on Form 8829 → Line 30 of Schedule C. Both methods (Simplified and Actual) work for both Schedule E and C.
A14: =HYPERLINK("#'Actual Expenses'!A5", "← Back: Actual Expenses") | G14: =HYPERLINK("#'Form 8829 Map'!A5", "Next: Form 8829 Map →")

Sheet Form 8829 Map
A2: =HYPERLINK("#'STR Routing'!A1", "← BACK") | D2: FORM 8829 MAP | J2: =HYPERLINK("#'Launch'!A1", "NEXT →")
A4: Print this tab — mirror of Form 8829 (Expenses for Business Use of Your Home).
A5: Line | B5: Description | C5: Amount
A6: Part I — BUSINESS-USE %
A7: 1 | B7: Office area (sqft) | C7: ='Space Allocation'!B9
A8: 2 | B8: Total home area (sqft) | C8: ='Space Allocation'!B8
A9: 3 | B9: Business-use percentage | C9: ='Space Allocation'!B13
A10: Part II — EXPENSES
A11: 8 | B11: Direct expenses | C11: ='Actual Expenses'!B8
A12: 9-13 | B12: Indirect (utilities + ins. + repairs + RE tax + mortgage int.) | C12: ='Actual Expenses'!B19
A13: 14 | B13: Indirect × business-use % | C13: ='Actual Expenses'!B20
A14: 15 | B14: Add lines 8 + 14 (operating exp.) | C14: =C12+C14
A15: Part III — DEPRECIATION
A16: 36 | B16: Annual depreciation (39-yr SL × biz %) | C16: ='Actual Expenses'!B21
A17: Part IV — TOTAL
B18: TOTAL ACTUAL DEDUCTION | C18: ='Actual Expenses'!B22
B19: TOTAL SIMPLIFIED DEDUCTION | C19: =MIN('Space Allocation'!B9,300)*5
B20: ELECTED METHOD | C20: ='Method Election'!B8
B21: FINAL DEDUCTION | C21: =IF('Method Election'!B8="Simplified",MIN('Space Allocation'!B9,300)*5,IF('Method Election'!B8="Actual",'Actual Expenses'!B22,0))

Sheet Launch
A2: =HYPERLINK("#'Form 8829 Map'!A1", "← BACK") | D2: LAUNCH
A4: Your home-office deduction
A5: Print the Form 8829 Map and route per your filing schedule.
A9: FINAL DEDUCTION | E9: METHOD | I9: SCHEDULE
A10: =IF('Method Election'!B8="Simplified",MIN('Space Allocation'!B9,300)*5,IF('Method Election'!B8="Actual",'Actual Expenses'!B22,0)) | E10: ='Method Election'!B8 | I10: ='STR Routing'!B8
A12: this tax year | E12: elected for this year | I12: where it lands
A16: =HYPERLINK("#'Form 8829 Map'!A1", "📄 PRINT FORM 8829 MAP →")
A23: 💡 Upgrade to the Tax Season Bundle ($147) at thestrledger.com/tax-bundle.
A26: Questions? hello@thestrledger.com
A27: TAX-006 · v2.2 · Free updates forever

Sheet Settings
A2: =HYPERLINK("#'Launch'!A1", "← BACK") | D2: SETTINGS
A4: Active tax year · references
A5: Active tax year: | B5: 2026
A6: Simplified-method rate ($/sqft): | B6: 5
A7: Simplified-method sqft cap: | B7: 300
A8: Home depreciation life (yr): | B8: 39
A11: Year-end Archive
A12: Year | B12: Method | C12: Deduction ($)
A13: 2024
A14: 2025
A15: 2026
A16: 2027
A17: 2028
A18: 2029
A19: 2030
A23: Questions? hello@thestrledger.com
A24: TAX-006 · v2.2 · Free updates forever
