Workbook

Sheet Start
A2: The STR Ledger
A4: Schedule C Tax-Prep Workbook
A5: Active host. Substantial services. SE tax in plain sight.
A7: TAX-012 · v1.0 · BLANK
A9: ⚠ ARE YOU SURE Schedule C is right? Most STR hosts file Schedule E. If you don't provide substantial services AND don't materially participate, switch to TAX-004 — Schedule E.
A12: What you'll hand to your CPA
A14: 📄 SCHEDULE C | E14: ⚖ SE TAX PREVIEW | I14: 📋 DOC CHECKLIST
A15: Print-ready Lines 1-31, Schedule C Form 1040. | E15: Net × 92.35% × 15.3% — half deductible above-the-line. | I15: 30 items your CPA will ask for. Tick as you collect.
A23: Quick Start — be done in 45 minutes
B25: ① Confirm Schedule C eligibility (5 questions) | H25: ② Income — gross rent, cleaning, platform fees
B26: ③ All 22 Schedule C expense lines | H26: ④ Vehicle + Home Office allocations
B27: ⑤ Depreciation + Section 179 elections | H27: ⑥ Review SE tax preview (15.3% × 92.35%)
B28: ⑦ Tick the 30-item document checklist | H28: ⑧ Print Launch tab and email to your CPA
A32: =HYPERLINK("#'§1 Eligibility'!A5", "GET STARTED — CONFIRM ELIGIBILITY →")
A38: Progress: | G38: =TEXT((COUNTA('§1 Eligibility'!B8:B12) + COUNTA('§2 Income'!B8:B12) + COUNTA('§3 Expenses'!B8:B30) + COUNTA('§4 Vehicle'!B8:B18) + COUNTA('§5 Home Office'!B8:B14) + COUNTA('§6 Depreciation'!B8:B14) + COUNTA('§7 SE Tax'!B8:B8) + COUNTA('§8 Doc Checklist'!B8:B37))/89,"0%") & " complete"
A40: ① Eligibility | G40: =IF(COUNTA('§1 Eligibility'!B8:B12)=5,"✅ Done",IF(COUNTA('§1 Eligibility'!B8:B12)=0,"⏳ Empty","⏳ "&COUNTA('§1 Eligibility'!B8:B12)&" of 5")) | K40: =HYPERLINK("#'§1 Eligibility'!A5","→ go")
A41: ② Income | G41: =IF(COUNTA('§2 Income'!B8:B12)=5,"✅ Done",IF(COUNTA('§2 Income'!B8:B12)=0,"⏳ Empty","⏳ "&COUNTA('§2 Income'!B8:B12)&" of 5")) | K41: =HYPERLINK("#'§2 Income'!A5","→ go")
A42: ③ Expenses | G42: =IF(COUNTA('§3 Expenses'!B8:B30)=23,"✅ Done",IF(COUNTA('§3 Expenses'!B8:B30)=0,"⏳ Empty","⏳ "&COUNTA('§3 Expenses'!B8:B30)&" of 23")) | K42: =HYPERLINK("#'§3 Expenses'!A5","→ go")
A43: ④ Vehicle | G43: =IF(COUNTA('§4 Vehicle'!B8:B18)=11,"✅ Done",IF(COUNTA('§4 Vehicle'!B8:B18)=0,"⏳ Empty","⏳ "&COUNTA('§4 Vehicle'!B8:B18)&" of 11")) | K43: =HYPERLINK("#'§4 Vehicle'!A5","→ go")
A44: ⑤ Home Office | G44: =IF(COUNTA('§5 Home Office'!B8:B14)=7,"✅ Done",IF(COUNTA('§5 Home Office'!B8:B14)=0,"⏳ Empty","⏳ "&COUNTA('§5 Home Office'!B8:B14)&" of 7")) | K44: =HYPERLINK("#'§5 Home Office'!A5","→ go")
A45: ⑥ Depreciation | G45: =IF(COUNTA('§6 Depreciation'!B8:B14)=7,"✅ Done",IF(COUNTA('§6 Depreciation'!B8:B14)=0,"⏳ Empty","⏳ "&COUNTA('§6 Depreciation'!B8:B14)&" of 7")) | K45: =HYPERLINK("#'§6 Depreciation'!A5","→ go")
A46: ⑦ SE Tax | G46: =IF(COUNTA('§7 SE Tax'!B8:B8)=1,"✅ Done",IF(COUNTA('§7 SE Tax'!B8:B8)=0,"⏳ Empty","⏳ "&COUNTA('§7 SE Tax'!B8:B8)&" of 1")) | K46: =HYPERLINK("#'§7 SE Tax'!A5","→ go")
A47: ⑧ Doc Checklist | G47: =IF(COUNTA('§8 Doc Checklist'!B8:B37)=30,"✅ Done",IF(COUNTA('§8 Doc Checklist'!B8:B37)=0,"⏳ Empty","⏳ "&COUNTA('§8 Doc Checklist'!B8:B37)&" of 30")) | K47: =HYPERLINK("#'§8 Doc Checklist'!A5","→ go")
A51: Questions? hello@thestrledger.com
A52: TAX-012 · v1.0 · Free updates forever

Sheet §1 Eligibility
A2: =HYPERLINK("#'Start'!A1", "← START") | D2: SECTION 1 OF 8 | J2: =HYPERLINK("#'§2 Income'!A5", "NEXT →")
A4: §1 Eligibility Confirmation
A5: Five Y/N questions verifying Schedule C is the right form.
A6: Answer Y or N for each. If you answer N to 3 or more, your STR is likely a passive rental — switch to Schedule E (TAX-004).
A7: §1 ELIGIBILITY CONFIRMATION
A8: Q1. Substantial services during stays? (cleaning DURING stay, meals, concierge, transport)
A9: Q2. Do you meet a material-participation test (500 hrs / 100 hrs + most active / substantially all)?
A10: Q3. Have you been filing Schedule C in prior years?
A11: Q4. Has your CPA confirmed Schedule C is correct?
A12: Q5. Is this a hospitality business, not a passive rental?
A14: ⓘ Schedule C is required when you provide SUBSTANTIAL SERVICES (cleaning DURING stays, meals, concierge, transport) — IRS treats this as a hospitality business, triggering 15.3% SE tax. Material participation (500 hrs / 100 hrs + most-active / substantially-all-work) additionally non-passivates losses but does NOT alone trigger Schedule C. Most STR hosts who self-clean between guests stay on Schedule E.
A16: No-count (potential red flag if ≥3): | B16: =COUNTIF(B8:B12,"N")
A17: Verdict: | B17: =IF(COUNTIF(B8:B12,"N")>=3,"🚩 RED FLAG — confirm with your CPA. Schedule E may be more appropriate.",IF(COUNTIF(B8:B12,"Y")=5,"✅ Schedule C confirmed.","⏳ Finish answering all 5 questions."))
A19: =HYPERLINK("#'Start'!A1", "← Back: Start") | G19: =HYPERLINK("#'§2 Income'!A5", "Next: §2 Income →")

Sheet §2 Income
A2: =HYPERLINK("#'§1 Eligibility'!A5", "← BACK") | D2: SECTION 2 OF 8 | J2: =HYPERLINK("#'§3 Expenses'!A5", "NEXT →")
A4: §2 Income
A5: Schedule C Lines 1-7. Gross receipts, returns, other income.
A6: Enter all gross income received from rental + hospitality services. Refundable security deposits are NOT income — track separately.
A7: §2 INCOME
A8: Gross rents received ($)
A9: Cleaning fees collected from guests ($)
A10: Platform service fees withheld ($, memo)
A11: Other income — refunds, forfeited deposits ($)
A12: Returns and allowances ($)
A14: GROSS INCOME (Schedule C Line 7) | B14: =B8+B9+B11-B12
A16: =HYPERLINK("#'§1 Eligibility'!A5", "← Back: §1 Eligibility") | G16: =HYPERLINK("#'§3 Expenses'!A5", "Next: §3 Expenses →")

Sheet §3 Expenses
A2: =HYPERLINK("#'§2 Income'!A5", "← BACK") | D2: SECTION 3 OF 8 | J2: =HYPERLINK("#'§4 Vehicle'!A5", "NEXT →")
A4: §3 Operating Expenses
A5: All 22 Schedule C expense lines (8-27).
A6: Each row maps to a Schedule C line. Repairs are deductible — improvements must be capitalized via §6 Depreciation.
A7: §3 OPERATING EXPENSES
A8: 8 Advertising
A9: 9 Car and truck expenses (from §4 Vehicle)
A10: 10 Commissions and fees (Airbnb host fees)
A11: 11 Contract labor (1099-NEC paid)
A12: 12 Depletion
A13: 13 Depreciation + Sec 179 (from §6)
A14: 14 Employee benefit programs
A15: 15 Insurance (other than health)
... A30: 27a Other expenses (list on Part V)
A32: TOTAL EXPENSES (Schedule C Line 28) | B32: =SUM(B8:B30)
A34: =HYPERLINK("#'§2 Income'!A5", "← Back: §2 Income") | G34: =HYPERLINK("#'§4 Vehicle'!A5", "Next: §4 Vehicle →")

Sheet §4 Vehicle
A2: =HYPERLINK("#'§3 Expenses'!A5", "← BACK") | D2: SECTION 4 OF 8 | J2: =HYPERLINK("#'§5 Home Office'!A5", "NEXT →")
A4: §4 Vehicle
A5: Mileage method + Form 4562 Part V (listed property).
A6: Vehicles are LISTED PROPERTY (IRC §280F). If you depreciate or claimed Section 179, Form 4562 Part V is required.
A7: §4 VEHICLE
A8: Method elected (Standard / Actual)
A9: Vehicle make/model
A10: Date placed in service
A11: Year-start odometer
A12: Year-end odometer
A13: Total business miles (from Mileage Log)
A14: Commuting miles
A15: Other personal miles
... A18: Used >50% qualified business use? (Y/N)
A20: Total miles (year-end - year-start): | B20: =B12-B11
A21: Personal miles (total - business - commuting): | B21: =(B12-B11)-B13-B14
A22: Business-use % (excludes commuting + personal): | B22: =IFERROR(B13/(B12-B11),0)
A23: Standard mileage deduction (business mi × IRS rate): | B23: =B13*B16+B17
A24: 4562 Part V — qualified-business-use ≥50%? | B24: =IF(IFERROR(B13/(B12-B11),0)>=0.5,"Yes","No — Sec 179 disallowed")
A27: =HYPERLINK("#'§3 Expenses'!A5", "← Back: §3 Expenses") | G27: =HYPERLINK("#'§5 Home Office'!A5", "Next: §5 Home Office →")

Sheet §5 Home Office
A2: =HYPERLINK("#'§4 Vehicle'!A5", "← BACK") | D2: SECTION 5 OF 8 | J2: =HYPERLINK("#'§6 Depreciation'!A5", "NEXT →")
A4: §5 Home Office
A5: Form 8829 inputs — regular + exclusive use required.
A6: Office must be used REGULARLY and EXCLUSIVELY for the STR business. Simplified method = $5/sq ft up to 300 sq ft ($1,500 max).
A7: §5 HOME OFFICE
A8: Allocation method (Simplified / Actual)
A9: Total home sq ft
A10: Office sq ft (regular + exclusive use)
A11: % business use
A12: Total annual home expenses ($, actual)
A13: Direct office expenses ($)
A14: Form 8829 will be filed? (Y/N)
A16: % business use (auto from sq ft): | B16: =IFERROR(B10/B9,0)
A17: Indirect home expenses × % business: | B17: =B11*B12
A18: Total Home Office Deduction (Form 8829 Line 36): | B18: =IF(B8="Simplified",MIN(B10,300)*5,B11*B12+B13)
A21: =HYPERLINK("#'§4 Vehicle'!A5", "← Back: §4 Vehicle") | G21: =HYPERLINK("#'§6 Depreciation'!A5", "Next: §6 Depreciation →")

Sheet §6 Depreciation
A2: =HYPERLINK("#'§5 Home Office'!A5", "← BACK") | D2: SECTION 6 OF 8 | J2: =HYPERLINK("#'§7 SE Tax'!A5", "NEXT →")
A4: §6 Depreciation + Section 179
A5: Asset list + annual depreciation summary — Schedule C Line 13.
A6: Customers electing accelerated methods should use the Section 179 Planner (TAX-009) and feed the totals here. Land is NOT depreciable.
A7: §6 DEPRECIATION + SECTION 179
A8: Asset 1 — description
A9: Asset 1 — basis ($, building only)
A10: Asset 1 — date placed in service
A11: Asset 1 — recovery period (yr)
A12: Asset 1 — accumulated prior depr ($)
A13: Section 179 election this year ($)
A14: Bonus depreciation this year ($)
A16: Annual straight-line depreciation (basis ÷ recovery): | B16: =IFERROR(B9/B11,0)
A17: Total Schedule C Line 13 (depr + 179 + bonus): | B17: =IFERROR(B9/B11,0)+B13+B14
A20: =HYPERLINK("#'§5 Home Office'!A5", "← Back: §5 Home Office") | G20: =HYPERLINK("#'§7 SE Tax'!A5", "Next: §7 SE Tax →")

Sheet §7 SE Tax
A2: =HYPERLINK("#'§6 Depreciation'!A5", "← BACK") | D2: SECTION 7 OF 8 | J2: =HYPERLINK("#'§8 Doc Checklist'!A5", "NEXT →")
A4: §7 Self-Employment Tax
A5: Net Schedule C × 92.35% × 15.3% — half deductible above-the-line.
A6: SE tax = Social Security (12.4% up to wage base) + Medicare (2.9% unlimited). Half is deductible on Form 1040 Line 15.
A7: §7 SELF-EMPLOYMENT TAX
A8: Net Schedule C profit ($) — auto-pulled, override if needed | B8: ='§2 Income'!B14-'§3 Expenses'!B32
A10: × 92.35% (SE earnings subject to tax): | B10: =B8*0.9235
A11: × 15.3% (12.4% SS + 2.9% Medicare): | B11: =B10*0.153
A13: Half deductible on Form 1040 Line 15: | B13: =B11/2
A14: Effective SE tax rate on net Schedule C: | B14: =IFERROR(B11/B8,0)
A17: ESTIMATED SE TAX
A18: =B11
A19: ="Half ($"&TEXT(B13,"#,##0")&") is deductible above-the-line on Form 1040 Line 15."
A21: ⓘ Combined federal liability includes regular income tax + SE tax. Use TAX-005 Quarterly Estimated Tax planner to space your 1040-ES vouchers (April / June / September / January).
A23: =HYPERLINK("#'§6 Depreciation'!A5", "← Back: §6 Depreciation") | G23: =HYPERLINK("#'§8 Doc Checklist'!A5", "Next: §8 Doc Checklist →")

Sheet §8 Doc Checklist
A2: =HYPERLINK("#'§7 SE Tax'!A5", "← BACK") | D2: SECTION 8 OF 8 | J2: =HYPERLINK("#'Launch'!A1", "LAUNCH →")
A4: §8 Document Checklist
A5: 30 items your CPA will request. Tick as you collect.
A6: Tick column B (mark ✓ or Y) as each document is collected. Email the whole packet to your CPA at year-end.
A7: §8 DOCUMENT CHECKLIST
A8: 1 | C8: 1099-K from Airbnb (annual gross payouts)
A9: 2 | C9: 1099-K from VRBO / Booking / other platforms
A10: 3 | C10: 1099-NEC issued to each contractor paid $600+
A11: 4 | C11: 1099-NEC RECEIVED from any platform that classifies you as a worker
A12: 5 | C12: Form 1098 — mortgage interest statement(s)
A13: 6 | C13: Form 1098-T / 1098-E — education / student loan (if applicable)
A14: 7 | C14: Property tax bills (county, paid in tax year)
A15: 8 | C15: Insurance declaration pages (property + liability + AirCover supplemental)
A16: 9 | C16: Utility year-end summaries (electric, gas, water, internet)
A17: 10 | C17: HOA / association dues year-end statement
A18: 11 | C18: Mortgage payoff / refinance closing statements (HUD-1 / Closing Disclosure)
A19: 12 | C19: Mileage log totals (business / commuting / personal — from TAX-001)
... A37: 30 | C37: STR permit / registration certificate (for the active tax year)
B39: =COUNTA(B8:B37) | C39: =B39&" of 30 documents collected"
A41: =HYPERLINK("#'§7 SE Tax'!A5", "← Back: §7 SE Tax") | G41: =HYPERLINK("#'Launch'!A1", "Launch →")

Sheet Launch
A2: =HYPERLINK("#'§8 Doc Checklist'!A5", "← BACK") | D2: LAUNCH
A4: Your Schedule C is ready
A5: Print this tab and send the packet to your CPA.
A9: COMPLETION | E9: SE TAX (PREVIEW) | I9: STATUS
A10: =TEXT((COUNTA('§1 Eligibility'!B8:B12) + COUNTA('§2 Income'!B8:B12) + COUNTA('§3 Expenses'!B8:B30) + COUNTA('§4 Vehicle'!B8:B18) + COUNTA('§5 Home Office'!B8:B14) + COUNTA('§6 Depreciation'!B8:B14) + COUNTA('§7 SE Tax'!B8:B8) + COUNTA('§8 Doc Checklist'!B8:B37))/89,"0%") | E10: ='§7 SE Tax'!B11 | I10: =IF((IF('§1 Eligibility'!B8="",1,0) + IF('§1 Eligibility'!B12="",1,0) + IF('§2 Income'!B8="",1,0) + IF('§3 Expenses'!B8="",1,0) + IF('§7 SE Tax'!B8="",1,0))=0,"READY",IF((IF('§1 Eligibility'!B8="",1,0) + IF('§1 Eligibility'!B12="",1,0) + IF('§2 Income'!B8="",1,0) + IF('§3 Expenses'!B8="",1,0) + IF('§7 SE Tax'!B8="",1,0))<=2,"MINOR","NEEDS WORK"))
A12: of 89 fields filled | E12: 15.3% × 92.35% × net Schedule C | I12: 0 missing = green
A15: Schedule C — Line-by-Line Summary (print this for your CPA)
A16: Line | B16: Description | L16: Amount
A17: 1 | B17: Gross receipts (rents + cleaning + other) | L17: ='§2 Income'!B8+'§2 Income'!B9+'§2 Income'!B11
A18: 2 | B18: Returns and allowances | L18: ='§2 Income'!B12
A19: 7 | B19: Gross income | L19: ='§2 Income'!B14
A20: 28 | B20: Total expenses (Lines 8-27) | L20: ='§3 Expenses'!B32
A21: 29 | B21: Tentative profit (Line 7 − 28) | L21: ='§2 Income'!B14-'§3 Expenses'!B32
A22: 30 | B22: Home office (from §5) | L22: ='§5 Home Office'!B18
A23: 31 | B23: Net profit or (loss) — to Schedule SE + Form 1040 Schedule 1 Line 3 | L23: ='§2 Income'!B14-'§3 Expenses'!B32-'§5 Home Office'!B18
A24: SE | B24: Self-employment tax preview (×92.35% ×15.3%) | L24: ='§7 SE Tax'!B11
A25: SE½ | B25: Half SE tax — deductible Form 1040 Line 15 | L25: ='§7 SE Tax'!B13
A28: =HYPERLINK("#'Launch'!A15", "📄 PRINT SCHEDULE C SUMMARY →")
A33: Tip: print the Schedule C summary above + the §8 Document Checklist tab and send both to your CPA — saves billable hours.
A35: 💡 Upgrade to the Tax Season Bundle ($147) at thestrledger.com/tax-bundle — Schedule C + Schedule E + Mileage + 1099 + Home Office + Section 179 + Quarterly Estimateds + Per-Diem.
A38: Questions? hello@thestrledger.com
A39: TAX-012 · v1.0 · Free updates forever
