Workbook

Sheet Start
A2: The STR Ledger
A4: Cost Segregation DIY
A5: Pull 5 years of depreciation into one. The IRS-acceptable DIY method.
A7: TAX-010 · v2.3 · DEMO
A11: What you'll get
A13: ⚡ MUCH BIGGER YEAR 1 | E13: 🛡 AUDIT-DEFENSIBLE | I13: 📄 CPA HAND-OFF
A14: Reclassify 5/7/15-year components out of the default 27.5-year schedule. Overlay bonus depreciation. Typical STR pulls $30K–$60K extra into Year 1. | E14: Methodology disclosure block, supporting-document checklist, and per-class sanity guardrails — built per the IRS Cost Segregation Audit Techniques Guide. | I14: Print-ready Form 4562 mirror (Parts I / II / III) plus the per-asset breakdown your CPA needs — including for a Form 3115 retroactive catch-up.
A23: Quick Start — be done in 90 minutes
B24: ① Property Basics: purchase + closing + placed-in-service | H24: ④ Itemize 7-year (furniture, electronics, kitchen)
B25: ② Land Allocation: county-assessor ratio method | H25: ⑤ Itemize 15-year exterior (drive, landscape, fence, deck)
B26: ③ Itemize 5-year property (carpet, appliances, hot tub…) | H26: ⑥ Print Form 4562 mirror — hand to CPA
A31: =HYPERLINK("#'Property Basics'!A5", "GET STARTED — PROPERTY BASICS →")
A37: Progress: | G37: =TEXT(MIN((COUNTA('Property Basics'!B8:B9,'Property Basics'!B11:B13) + COUNTA('Land Allocation'!B8:B9) + COUNTA('5-Year Property'!C8:C19) + COUNTA('7-Year Property'!C8:C17) + COUNTA('15-Year Property'!C8:C17))/39,1),"0%") & " complete"
A39: ① Property Basics | G39: =IF(COUNTA('Property Basics'!B8:B9,'Property Basics'!B11:B13)=0,"⏳ Empty","⏳ "&COUNTA('Property Basics'!B8:B9,'Property Basics'!B11:B13)&" of up to 5") | K39: =HYPERLINK("#'Property Basics'!A5","→ go")
A40: ② Land Allocation | G40: =IF(COUNTA('Land Allocation'!B8:B9)=0,"⏳ Empty","⏳ "&COUNTA('Land Allocation'!B8:B9)&" of up to 2") | K40: =HYPERLINK("#'Land Allocation'!A5","→ go")
A41: ③ 5-Year Property | G41: =IF(COUNTA('5-Year Property'!C8:C19)=0,"⏳ Empty","⏳ "&COUNTA('5-Year Property'!C8:C19)&" of up to 12") | K41: =HYPERLINK("#'5-Year Property'!A5","→ go")
A42: ④ 7-Year Property | G42: =IF(COUNTA('7-Year Property'!C8:C17)=0,"○ Skipped (optional)","⏳ "&COUNTA('7-Year Property'!C8:C17)&" item(s) entered") | K42: =HYPERLINK("#'7-Year Property'!A5","→ go")
A43: ⑤ 15-Year Property | G43: =IF(COUNTA('15-Year Property'!C8:C17)=0,"⏳ Empty","⏳ "&COUNTA('15-Year Property'!C8:C17)&" of up to 10") | K43: =HYPERLINK("#'15-Year Property'!A5","→ go")
A47: Questions? hello@thestrledger.com
A48: TAX-010 · v2.3 · Free updates forever

Sheet Property Basics
A2: =HYPERLINK("#'Start'!A1", "← START") | D2: SECTION 1 OF 5 | J2: =HYPERLINK("#'Land Allocation'!A5", "NEXT →")
A4: Property Basics
A5: Purchase price, closing costs, placed-in-service date.
A6: Fill the highlighted fields below.
A7: PURCHASE + PLACED-IN-SERVICE
A8: Purchase price ($): | B8: 480000
A9: Capitalizable closing/title costs ($): | B9: 8000
A10: TOTAL BASIS: | B10: =B8+B9
A11: Property address: | B11: 1247 Wears Valley Rd, Sevierville TN 37862
A12: Placed-in-service date: | B12: 46127
A13: Schedule classification: | B13: Schedule E (passive)
A15: ⓘ Capitalizable closing costs include title insurance, recording fees, transfer taxes, attorney fees, and survey costs — NOT prepaid insurance, prepaid property tax, or financing points (those are deducted differently). Your settlement statement (HUD-1 / Closing Disclosure) lists each line item — when in doubt, ask your CPA which lines are capitalizable.
A17: ⓘ Placed-in-service date drives the 27.5-year mid-month convention for the building residual. Most STRs are placed in service the day they're first marketed for rental (listing live + photos), not the closing date. Document this with your first listing screenshot.
A19: =HYPERLINK("#'Start'!A1", "← Back: Start") | G19: =HYPERLINK("#'Land Allocation'!A5", "Next: Land Allocation →")

Sheet Land Allocation
A2: =HYPERLINK("#'Property Basics'!A5", "← BACK") | D2: SECTION 2 OF 5 | J2: =HYPERLINK("#'5-Year Property'!A5", "NEXT →")
A4: Land Allocation
A5: County tax assessor ratio method — separates land from depreciable basis.
A6: Look up your county tax assessor's land + improvements values for the property — usually free online.
A7: COUNTY TAX ASSESSOR RATIO
A8: County tax assessor — LAND value ($): | B8: 80000
A9: County tax assessor — IMPROVEMENTS value ($): | B9: 408000
A10: County total (land + improvements): | B10: =B8+B9
A11: Land ratio (land ÷ county total): | B11: =IFERROR(B8/B10,0)
A12: ALLOCATED LAND ($) — non-depreciable: | B12: ='Property Basics'!B10*B11
A13: DEPRECIABLE IMPROVEMENTS BASIS: | B13: ='Property Basics'!B10-B12
A15: =IF(B11=0,"",IF(B11<0.1,"⚠ Land ratio under 10% — confirm county assessor values are correct. STR land is rarely below 10%.",IF(B11>0.35,"⚠ Land ratio over 35% — confirm county assessor values. High land ratio reduces depreciable basis significantly.","")))
A17: ⓘ The county tax assessor ratio method is the default IRS-accepted approach for DIY land allocation. Alternatives: (a) use the appraisal report's land value if your purchase appraisal broke it out, or (b) hire a land appraiser for ~$300 if you believe the county ratio is unreasonable. Document whichever method you use in the Launch tab's methodology block.
A19: ⓘ Land is NEVER depreciable — this is the single most-audited line in cost segregation. Auditors compare your land allocation to county records. If you allocate less to land than the county does, be prepared to defend why (e.g., appraisal report, comparable sales).
A21: =HYPERLINK("#'Property Basics'!A5", "← Back: Property Basics") | G21: =HYPERLINK("#'5-Year Property'!A5", "Next: 5-Year Property →")

Sheet 5-Year Property
A2: =HYPERLINK("#'Land Allocation'!A5", "← BACK") | D2: SECTION 3 OF 5 | J2: =HYPERLINK("#'7-Year Property'!A5", "NEXT →")
A4: 5-Year Property
A5: Carpet, appliances, decorative lighting, hot tub, smart-home gear, etc.
A6: 5-year MACRS = personal property used in the rental — the highest-value reclassification class for STRs.
A7: # | B7: Item description | C7: Amount ($)
A8: 1 | B8: Whole-home furniture package (3BR) | C8: 32000
A9: 2 | B9: Stainless appliance package (fridge/range/DW/W+D) | C9: 12500
A10: 3 | B10: Hot tub (8-person, installed) | C10: 14500
A11: 4 | B11: Game room equipment (pool table + arcade) | C11: 9800
A12: 5 | B12: Smart TVs + wall mounts × 4 | C12: 4500
A13: 6 | B13: Window treatments (custom blackouts × 9) | C13: 4200
A14: 7 | B14: Decorative lighting + ceiling fans | C14: 3800
A15: 8 | B15: Smart locks + Ring camera package | C15: 2200
A16: 9 | B16: Initial linens + kitchenware package | C16: 1500
A17: 10
A18: 11
A19: 12
B20: TOTAL: | C20: =SUM(C8:C19)
A22: ⓘ Common 5-year items: appliances (fridge, range, dishwasher, W/D), carpet + area rugs, decorative lighting + ceiling fans, window treatments + blinds, hot tubs + saunas, smart locks + cameras, smart TVs, game-room equipment, initial linens + kitchenware. Some 5-year items also qualify for §179 — see TAX-009 Section 179 Planner.
A24: ⓘ For each item, keep supporting documents: vendor invoices, purchase agreement furniture inventory, photos with date metadata, or an inspector report itemization. Vague descriptions ('misc furnishings', 'fixtures') are the #1 audit weak point — be specific and itemized.
A26: =HYPERLINK("#'Land Allocation'!A5", "← Back: Land Allocation") | G26: =HYPERLINK("#'7-Year Property'!A5", "Next: 7-Year Property →")

Sheet 7-Year Property
A2: =HYPERLINK("#'5-Year Property'!A5", "← BACK") | D2: SECTION 4 OF 5 | J2: =HYPERLINK("#'15-Year Property'!A5", "NEXT →")
A4: 7-Year Property
A5: Furniture, electronics, kitchen equipment with 7-year recovery.
A6: 7-year MACRS = office/business furniture and certain equipment. Optional — can be combined into 5-year if simpler.
A7: # | B7: Item description | C7: Amount ($)
A8: 1
A9: 2
A10: 3
A11: 4
A12: 5
A13: 6
A14: 7
A15: 8
A16: 9
A17: 10
B18: TOTAL: | C18: =SUM(C8:C17)
A20: ⓘ Common 7-year items: office furniture (if you have a workspace in the rental), some commercial-grade kitchen equipment, agricultural or specialty equipment. Most STR personal property fits better in 5-year — leave this tab empty if your items are clearly 5-year.
A22: ⓘ For each item, keep supporting documents: vendor invoices, purchase agreement furniture inventory, photos with date metadata, or an inspector report itemization. Vague descriptions ('misc furnishings', 'fixtures') are the #1 audit weak point — be specific and itemized.
A24: =HYPERLINK("#'5-Year Property'!A5", "← Back: 5-Year Property") | G24: =HYPERLINK("#'15-Year Property'!A5", "Next: 15-Year Property →")

Sheet 15-Year Property
A2: =HYPERLINK("#'7-Year Property'!A5", "← BACK") | D2: SECTION 5 OF 5 | J2: =HYPERLINK("#'Y1 Summary'!A5", "NEXT →")
A4: 15-Year Property
A5: Land improvements — driveway, landscaping, fencing, exterior lighting.
A6: 15-year MACRS = land improvements. NOT the land itself — things attached to or done to the land outside the building.
A7: # | B7: Item description | C7: Amount ($)
A8: 1 | B8: Hot tub deck + stairs | C8: 7000
A9: 2 | B9: Privacy fence (back yard, 220 ft) | C9: 6500
A10: 3 | B10: Gravel driveway extension + parking | C10: 9500
A11: 4 | B11: Landscaping (perennials, mulch, wall) | C11: 7200
A12: 5 | B12: Exterior lighting (path/flood/accent) | C12: 4800
A13: 6
A14: 7
A15: 8
A16: 9
A17: 10
B18: TOTAL: | C18: =SUM(C8:C17)
A20: ⓘ Common 15-year items: driveway + parking pad, landscaping (plantings, retaining walls, mulch), exterior lighting (path, flood, accent), fencing, exterior decks + stairs (if separate from the building), in-ground sprinklers, walkways, exterior signage. Land improvements are eligible for bonus depreciation (40% in 2026).
A22: ⓘ For each item, keep supporting documents: vendor invoices, purchase agreement furniture inventory, photos with date metadata, or an inspector report itemization. Vague descriptions ('misc furnishings', 'fixtures') are the #1 audit weak point — be specific and itemized.
A24: =HYPERLINK("#'7-Year Property'!A5", "← Back: 7-Year Property") | G24: =HYPERLINK("#'Y1 Summary'!A5", "Next: Y1 Summary →")

Sheet Y1 Summary
A2: =HYPERLINK("#'15-Year Property'!A1", "← BACK") | D2: Y1 SUMMARY | J2: =HYPERLINK("#'Form 4562 Mirror'!A1", "NEXT →")
A4: Per-class Year 1 deduction with bonus overlay, vs. naive 27.5-year baseline. Settings drives the bonus % and marginal rate.
A6: Class | B6: Basis ($) | C6: Bonus % | D6: Bonus $ | E6: Non-bonus × MACRS Y1 % | F6: Total Y1 ($)
A7: 5-year | B7: ='5-Year Property'!C20 | C7: =Settings!$B$6 | D7: =B7*C7 | E7: =(B7-D7)*Settings!$B$8 | F7: =D7+E7
A8: 7-year | B8: ='7-Year Property'!C18 | C8: =Settings!$B$6 | D8: =B8*C8 | E8: =(B8-D8)*Settings!$B$9 | F8: =D8+E8
A9: 15-year | B9: ='15-Year Property'!C18 | C9: =Settings!$B$6 | D9: =B9*C9 | E9: =(B9-D9)*Settings!$B$10 | F9: =D9+E9
A10: 27.5-yr (residual) | B10: ='Land Allocation'!B13-B7-B8-B9 | C10: — | D10: 0 | E10: =IFERROR((12.5-MONTH('Property Basics'!B12))/12/27.5,0) | F10: =B10*E10
A11: Land (non-depreciable) | B11: ='Land Allocation'!B12 | C11: — | D11: — | E11: — | F11: —
A12: TOTAL | B12: ='Property Basics'!B10 | F12: =SUM(F7:F10)
A14: =IFERROR(IF((B7+B8+B9)/'Land Allocation'!B13>0.4,"⚠ Reclassification at "&TEXT((B7+B8+B9)/'Land Allocation'!B13,"0.0%")&" of improvements basis — above the typical 25–35% defensible range. Consider an engineer-led study (>$750K acquisition) or reduce reclassifications.",""),"")
A16: NAIVE 27.5-YR BASELINE — WHAT YOU SAVED
A17: Naive Y1 deduction (everything at 27.5-yr): | F17: ='Land Allocation'!B13*E10
A18: Accelerated Y1 deduction (this workbook): | F18: =F12
A19: EXTRA Y1 DEDUCTION: | F19: =F18-F17
A20: Y1 TAX SAVINGS @ marginal rate: | F20: =F19*Settings!$B$7
A23: 5-YEAR MACRS SCHEDULE (NON-BONUS PORTIONS)
A24: Year | B24: 5-yr | C24: 7-yr | D24: 15-yr | E24: 27.5-yr (bldg) | F24: Total
A25: Year 1 | B25: =(B7-D7)*0.2 | C25: =(B8-D8)*0.1429 | D25: =(B9-D9)*0.05 | E25: =B10*E10 | F25: =SUM(B25:E25)
A26: Year 2 | B26: =(B7-D7)*0.32 | C26: =(B8-D8)*0.2449 | D26: =(B9-D9)*0.095 | E26: =B10/27.5 | F26: =SUM(B26:E26)
A27: Year 3 | B27: =(B7-D7)*0.192 | C27: =(B8-D8)*0.1749 | D27: =(B9-D9)*0.0855 | E27: =B10/27.5 | F27: =SUM(B27:E27)
A28: Year 4 | B28: =(B7-D7)*0.1152 | C28: =(B8-D8)*0.1249 | D28: =(B9-D9)*0.077 | E28: =B10/27.5 | F28: =SUM(B28:E28)
A29: Year 5 | B29: =(B7-D7)*0.1152 | C29: =(B8-D8)*0.0893 | D29: =(B9-D9)*0.0693 | E29: =B10/27.5 | F29: =SUM(B29:E29)
A31: ⓘ Year 1 totals above show the NON-BONUS portions only — add the bonus depreciation row (F12 minus E10×B10 etc.) to get the full Y1 number from the table at the top. The Form 4562 Mirror tab consolidates everything into the IRS line items your CPA needs.
A33: ⓘ The 27.5-yr (bldg) Year 1 reflects the mid-month convention based on your placed-in-service month. Years 2+ use the full 1/27.5 = 3.636% annual rate. Bonus depreciation does NOT apply to the 27.5-yr residual (only to property with recovery period ≤ 20 years).

Sheet Form 4562 Mirror
A2: =HYPERLINK("#'Y1 Summary'!A1", "← BACK") | D2: FORM 4562 MIRROR | J2: =HYPERLINK("#'Launch'!A1", "NEXT →")
A4: IRS Form 4562 — Parts II (Bonus) and III (MACRS) for your CPA. Print this and attach to the asset detail.
A5: Line | B5: Description | C5: Amount
A6: Part II — PART II — SPECIAL DEPRECIATION (BONUS)
A7: 14a | B7: Bonus depr — 5-yr property: | C7: ='Y1 Summary'!D7
A8: 14b | B8: Bonus depr — 7-yr property: | C8: ='Y1 Summary'!D8
A9: 14c | B9: Bonus depr — 15-yr property: | C9: ='Y1 Summary'!D9
A10: 14 | B10: Total bonus depreciation (sum 14a–14c): | C10: ='Y1 Summary'!D7+'Y1 Summary'!D8+'Y1 Summary'!D9
A11: Part III — PART III — MACRS DEPRECIATION (CURRENT YEAR)
A12: 19a | B12: 5-year property — non-bonus basis × Y1 %: | C12: ='Y1 Summary'!E7
A13: 19b | B13: 7-year property — non-bonus basis × Y1 %: | C13: ='Y1 Summary'!E8
A14: 19c | B14: 15-year property — non-bonus basis × Y1 %: | C14: ='Y1 Summary'!E9
A15: 19h | B15: 27.5-yr residential (mid-month conv.): | C15: ='Y1 Summary'!F10
A16: 21 | B16: Total MACRS this year (sum 19a–19h): | C16: ='Y1 Summary'!E7+'Y1 Summary'!E8+'Y1 Summary'!E9+'Y1 Summary'!F10
A17: Part IV — PART IV — SUMMARY
A18: 22 | B18: GRAND TOTAL Y1 DEDUCTION: | C18: ='Y1 Summary'!F12
A19: Routing — ROUTING — where this lands on your return
A20: If Schedule E filer: Form 4562 → Sched E Line 18
A21: If Schedule C filer: Form 4562 → Sched C Line 13

Sheet Launch
A2: =HYPERLINK("#'Form 4562 Mirror'!A1", "← BACK") | D2: LAUNCH
A4: Your cost segregation is ready
A5: Print Form 4562 Mirror, complete the methodology block below, and hand both to your CPA.
A9: TOTAL Y1 DEDUCTION | E9: EXTRA vs. NAIVE 27.5-YR | I9: Y1 TAX SAVINGS
A10: ='Y1 Summary'!F12 | E10: ='Y1 Summary'!F19 | I10: ='Y1 Summary'!F20
A12: Bonus + MACRS, all classes | E12: extra Y1 deduction this gives you | I12: at your marginal rate (Settings)
A16: =HYPERLINK("#'Form 4562 Mirror'!A1", "📄 PRINT FORM 4562 MIRROR →")
A22: AUDIT-DEFENSE — METHODOLOGY DISCLOSURE (SIGN + DATE)
A23: I used the DIY rule-of-thumb cost segregation method described in the IRS Cost Segregation Audit Techniques Guide. Allocations were derived from the sources checked below:
A24: [ ] Purchase agreement / settlement statement (HUD-1 / Closing Disclosure)
A25: [ ] Appraisal report (provides land + improvements split)
A26: [ ] County tax assessor records (for land allocation ratio)
A27: [ ] Pre-purchase inspector report (itemized fixtures + components)
A28: [ ] Vendor invoices for post-purchase furniture/appliances
A29: [ ] Photographs with date metadata (before-rental documentation)
A30: [ ] Industry benchmark percentages (RSMeans, AICPA, etc.)
A32: Taxpayer signature:
A33: Date:
A35: WHEN TO HIRE AN ENGINEER INSTEAD
... A50: TAX-010 · v2.3 · Free updates forever

Sheet Settings
A2: =HYPERLINK("#'Launch'!A1", "← BACK") | D2: SETTINGS
A4: Active tax year · bonus depreciation % · marginal rate · MACRS Y1 % per class.
A5: Active tax year: | B5: 2026
A6: Bonus depreciation % (placed in service Y1): | B6: 0.4
A7: Marginal tax rate (for Y1 savings calc): | B7: 0.24
A8: MACRS Y1 % — 5-year property: | B8: 0.2
A9: MACRS Y1 % — 7-year property: | B9: 0.1429
A10: MACRS Y1 % — 15-year property: | B10: 0.05
A13: Historical bonus depreciation %:
A14: 2022: | B14: 1
A15: 2023: | B15: 0.8
A16: 2024: | B16: 0.6
A17: 2025: | B17: 0.4
A18: 2026: | B18: 0.4
A19: 2027: | B19: 0.2
A20: 2028: | B20: 0
A23: MACRS reference (200% DB half-year):
A24: 5-yr Y1: | B24: 0.2
A25: 5-yr Y2: | B25: 0.32
A26: 5-yr Y3: | B26: 0.192
A27: 7-yr Y1: | B27: 0.1429
A28: 7-yr Y2: | B28: 0.2449
A29: 15-yr Y1: | B29: 0.05
A30: 15-yr Y2: | B30: 0.095
