Workbook

Sheet Start
A2: The STR Ledger
A4: Schedule E Tax-Prep Workbook
A5: Hand your CPA a finished Schedule E.
A7: TAX-004 · v2.2 · BLANK
A11: What you'll hand to your CPA
A13: 📄 SCHEDULE E | E13: 📊 PER-PROPERTY P&L | I13: ⚖ LOSS LIMITS
A14: Print-ready Lines 1-26, three properties per page. | E14: Rents − expenses − depreciation per property. | I14: Active + material participation flagged, $25K rule applied.
A22: Quick Start — be done in 30 minutes
B24: ① Property identity (address, type, days) | H24: ④ Depreciation basis + prior accumulated
B25: ② Rents received per property | H25: ⑤ Material-participation answer + AGI
B26: ③ All 14 Schedule E expense lines
A30: =HYPERLINK("#'Property Info'!A5", "GET STARTED — FILL PROPERTY INFO →")
A36: Progress: | G36: =TEXT((COUNTA('Property Info'!B8:D15) + COUNTA('Income'!B8:D10) + COUNTA('Expenses'!B8:D21) + COUNTA('Depreciation'!B8:D12) + COUNTA('Loss Limitations'!B8:B11,'Loss Limitations'!B14:D14))/97,"0%") & " complete"
A38: ① Property Info | G38: =IF(COUNTA('Property Info'!B8:D15)=24,"✅ Done",IF(COUNTA('Property Info'!B8:D15)=0,"⏳ Empty","⏳ "&COUNTA('Property Info'!B8:D15)&" of 24")) | K38: =HYPERLINK("#'Property Info'!A5","→ go")
A39: ② Income | G39: =IF(COUNTA('Income'!B8:D10)=9,"✅ Done",IF(COUNTA('Income'!B8:D10)=0,"⏳ Empty","⏳ "&COUNTA('Income'!B8:D10)&" of 9")) | K39: =HYPERLINK("#'Income'!A5","→ go")
A40: ③ Expenses | G40: =IF(COUNTA('Expenses'!B8:D21)=42,"✅ Done",IF(COUNTA('Expenses'!B8:D21)=0,"⏳ Empty","⏳ "&COUNTA('Expenses'!B8:D21)&" of 42")) | K40: =HYPERLINK("#'Expenses'!A5","→ go")
A41: ④ Depreciation | G41: =IF(COUNTA('Depreciation'!B8:D12)=15,"✅ Done",IF(COUNTA('Depreciation'!B8:D12)=0,"⏳ Empty","⏳ "&COUNTA('Depreciation'!B8:D12)&" of 15")) | K41: =HYPERLINK("#'Depreciation'!A5","→ go")
A42: ⑤ Loss Limitations | G42: =IF(COUNTA('Loss Limitations'!B8:B11,'Loss Limitations'!B14:D14)=7,"✅ Done",IF(COUNTA('Loss Limitations'!B8:B11,'Loss Limitations'!B14:D14)=0,"⏳ Empty","⏳ "&COUNTA('Loss Limitations'!B8:B11,'Loss Limitations'!B14:D14)&" of 7")) | K42: =HYPERLINK("#'Loss Limitations'!A5","→ go")
A48: Questions? hello@thestrledger.com
A49: TAX-004 · v2.2 · Free updates forever

Sheet Property Info
A2: =HYPERLINK("#'Start'!A1", "← START") | D2: SECTION 1 OF 5 | J2: =HYPERLINK("#'Income'!A5", "NEXT →")
A4: Property Info
A5: Identity, days rented, ownership — Schedule E Lines 1-2.
A6: Fill the highlighted fields for each of your properties (3 max).
B7: Smokies Ridge | C7: Creek Side | D7: Lakehouse A
A8: Property address
A9: Type (Schedule E code 1-8)
A10: Fair-rental days
A11: Personal-use days
A12: % ownership
A13: Date placed in service
A14: EIN (if any)
A15: QJV election (Y/N)
A17: ⚠ Personal-use days > 14 OR > 10% of rental days triggers vacation-home rules (IRC §280A) — limits deductions to rental income. Flag for your CPA if exceeded.

Sheet Income
A2: =HYPERLINK("#'Property Info'!A5", "← BACK") | D2: SECTION 2 OF 5 | J2: =HYPERLINK("#'Expenses'!A5", "NEXT →")
A4: Income
A5: Rents and royalties received — Schedule E Lines 3-4.
A6: Fill the highlighted fields for each of your properties (3 max).
B7: Smokies Ridge | C7: Creek Side | D7: Lakehouse A
A8: Rents received ($)
A9: Royalties ($)
A10: Refundable deposits held (memo)
A11: TOTAL INCOME (Lines 3 + 4) | B11: =SUM(B8:B9) | C11: =SUM(C8:C9) | D11: =SUM(D8:D9)
A12: ⚠ Refundable security deposits are NOT income (IRC §61) — list them as memo only. Forfeited deposits become income in the year of forfeiture; track separately on the Expenses tab.

Sheet Expenses
A2: =HYPERLINK("#'Income'!A5", "← BACK") | D2: SECTION 3 OF 5 | J2: =HYPERLINK("#'Depreciation'!A5", "NEXT →")
A4: Expenses
A5: All 14 Schedule E Part I expense lines (5-19).
A6: Fill the highlighted fields for each of your properties (3 max).
B7: Smokies Ridge | C7: Creek Side | D7: Lakehouse A
A8: 5 Advertising
A9: 6 Auto and travel
A10: 7 Cleaning and maintenance
A11: 8 Commissions
A12: 9 Insurance
A13: 10 Legal and professional
A14: 11 Management fees
A15: 12 Mortgage interest (banks)
A16: 13 Other interest
A17: 14 Repairs
A18: 15 Supplies
A19: 16 Taxes
... A21: 19 Other (list)
A23: TOTAL EXPENSES (Line 20) | B23: =SUM(B8:B21) | C23: =SUM(C8:C21) | D23: =SUM(D8:D21)

Sheet Depreciation
A2: =HYPERLINK("#'Expenses'!A5", "← BACK") | D2: SECTION 4 OF 5 | J2: =HYPERLINK("#'Loss Limitations'!A5", "NEXT →")
A4: Depreciation
A5: Per-property basis + recovery — Schedule E Line 18.
A6: Fill the highlighted fields for each of your properties (3 max).
B7: Smokies Ridge | C7: Creek Side | D7: Lakehouse A
A8: Depreciable basis ($, building only)
A9: Date placed in service
A10: Recovery period (27.5 / 39 yr)
A11: Convention (mid-month)
A12: Accumulated prior depreciation ($)
A14: ⓘ Default for residential STR is 27.5-year MACRS straight-line (non-residential = 39 yr). Building only — land is NOT depreciable. First-year and disposal-year prorate via mid-month convention. Customers electing accelerated depreciation (Section 179, bonus) should use the Section 179 Planner (TAX-009) and feed the result into Line 18 below.
A16: ANNUAL DEPRECIATION (Schedule E Line 18) | B16: =IF(AND(B8<>"",B10<>""),B8/B10,0) | C16: =IF(AND(C8<>"",C10<>""),C8/C10,0) | D16: =IF(AND(D8<>"",D10<>""),D8/D10,0)

Sheet Loss Limitations
A2: =HYPERLINK("#'Depreciation'!A5", "← BACK") | D2: SECTION 5 OF 5 | J2: =HYPERLINK("#'Schedule E Map'!A5", "NEXT →")
A4: Loss Limitations
A5: Active vs. material participation — IRC §469.
A6: Portfolio-level participation drives loss treatment under IRC §469. Hours must be contemporaneously documented.
A7: LOSS LIMITATIONS
A8: Filing AGI ($, for $25K phase-out)
A9: Active Participation? (Y/N)
A10: Material Participation? (Y/N STR loophole)
A11: Prior-year suspended losses ($)
A13: Per-property participation: | B13: Smokies Ridge | C13: Creek Side | D13: Lakehouse A
A14: Hours of personal services this year (per prop)
A16: $25K offset eligible? (Active + AGI ≤ $100K, phases out to $150K) | B16: =IF(AND(B9="Y",B8<=100000),"Yes — full $25K",IF(AND(B9="Y",B8<150000),"Partial — phase-out range","No — AGI > $150K or not active"))
A17: STR loophole (material participation, non-passive)? | B17: =IF(B10="Y","Yes — losses offset W-2 income (IRC §469(c)(7))","No — losses limited to passive income or carryforward")
A18: Total per-property hours: | B18: =SUM(B14:D14)
A19: 500-hour test met (single-property)? | B19: =IF(MAX(B14:D14)>=500,"Yes (one property meets it)","No — combined-activity election may apply (consult CPA)")
A21: ⚖ Passive losses you can't use this year carry forward to next year (no expiration). When you sell the property, suspended losses release in full against the gain (IRC §469(g)).
A23: =HYPERLINK("#'Depreciation'!A5", "← Back: Depreciation") | G23: =HYPERLINK("#'Schedule E Map'!A5", "Next: Schedule E Map →")

Sheet Schedule E Map
A2: =HYPERLINK("#'Loss Limitations'!A1", "← BACK") | D2: SCHEDULE E MAP | J2: =HYPERLINK("#'Launch'!A1", "NEXT →")
A4: Print this tab and hand it to your CPA. Lines 1-26 mirror IRS Schedule E (Form 1040), Part I.
A5: Line | B5: Description | C5: A | D5: B | E5: C
B6: Property name | C6: Smokies Ridge | D6: Creek Side | E6: Lakehouse A
A8: 1a | B8: Property address | C8: ='Property Info'!B8 | D8: ='Property Info'!C8 | E8: ='Property Info'!D8
A9: 1b | B9: Type | C9: ='Property Info'!B9 | D9: ='Property Info'!C9 | E9: ='Property Info'!D9
A10: 2 | B10: Fair rental days | C10: ='Property Info'!B10 | D10: ='Property Info'!C10 | E10: ='Property Info'!D10
A11: 2 | B11: Personal use days | C11: ='Property Info'!B11 | D11: ='Property Info'!C11 | E11: ='Property Info'!D11
A12: 3 | B12: Rents received | C12: ='Income'!B8 | D12: ='Income'!C8 | E12: ='Income'!D8
A13: 4 | B13: Royalties received | C13: ='Income'!B9 | D13: ='Income'!C9 | E13: ='Income'!D9
A14: 5 | B14: Advertising | C14: ='Expenses'!B8 | D14: ='Expenses'!C8 | E14: ='Expenses'!D8
A15: 6 | B15: Auto and travel | C15: ='Expenses'!B9 | D15: ='Expenses'!C9 | E15: ='Expenses'!D9
A16: 7 | B16: Cleaning and maintenance | C16: ='Expenses'!B10 | D16: ='Expenses'!C10 | E16: ='Expenses'!D10
A17: 8 | B17: Commissions | C17: ='Expenses'!B11 | D17: ='Expenses'!C11 | E17: ='Expenses'!D11
A18: 9 | B18: Insurance | C18: ='Expenses'!B12 | D18: ='Expenses'!C12 | E18: ='Expenses'!D12
A19: 10 | B19: Legal and professional | C19: ='Expenses'!B13 | D19: ='Expenses'!C13 | E19: ='Expenses'!D13
A20: 11 | B20: Management fees | C20: ='Expenses'!B14 | D20: ='Expenses'!C14 | E20: ='Expenses'!D14
A21: 12 | B21: Mortgage interest paid (banks) | C21: ='Expenses'!B15 | D21: ='Expenses'!C15 | E21: ='Expenses'!D15
A22: 13 | B22: Other interest | C22: ='Expenses'!B16 | D22: ='Expenses'!C16 | E22: ='Expenses'!D16
A23: 14 | B23: Repairs | C23: ='Expenses'!B17 | D23: ='Expenses'!C17 | E23: ='Expenses'!D17
A24: 15 | B24: Supplies | C24: ='Expenses'!B18 | D24: ='Expenses'!C18 | E24: ='Expenses'!D18
A25: 16 | B25: Taxes | C25: ='Expenses'!B19 | D25: ='Expenses'!C19 | E25: ='Expenses'!D19
A26: 17 | B26: Utilities | C26: ='Expenses'!B20 | D26: ='Expenses'!C20 | E26: ='Expenses'!D20
A27: 20 | B27: Total expenses (Lines 5-19) | C27: =SUM(C12:C26) | D27: =SUM(D12:D26) | E27: =SUM(E12:E26)
A28: 21 | B28: Income or (loss) [Lines 3+4 − 20] | C28: =C12+C13-C27 | D28: =D12+D13-D27 | E28: =E12+E13-E27
A30: 26 | B30: Total rental real estate income or (loss) — to Form 1040 Schedule 1 Line 5 | C30: =SUM(C28:E28)
A32: =IF('Loss Limitations'!B10="Y","→ Material participation: losses non-passive, offset W-2 income.","→ Passive: losses limited to passive income; carry forward suspended losses (Form 8582).")

Sheet Launch
A2: =HYPERLINK("#'Schedule E Map'!A1", "← BACK") | D2: LAUNCH
A4: Your Schedule E is ready
A5: Print the Schedule E Map and send it to your CPA.
A9: COMPLETION | E9: SCHEDULE E LINE 26 | I9: STATUS
A10: =TEXT((COUNTA('Property Info'!B8:D15) + COUNTA('Income'!B8:D10) + COUNTA('Expenses'!B8:D21) + COUNTA('Depreciation'!B8:D12) + COUNTA('Loss Limitations'!B8:B11,'Loss Limitations'!B14:D14))/97,"0%") | E10: ='Schedule E Map'!C30 | I10: =IF((IF('Property Info'!B8="",1,0) + IF('Property Info'!B9="",1,0) + IF('Income'!B8="",1,0) + IF('Expenses'!B15="",1,0) + IF('Depreciation'!B8="",1,0))=0,"READY",IF((IF('Property Info'!B8="",1,0) + IF('Property Info'!B9="",1,0) + IF('Income'!B8="",1,0) + IF('Expenses'!B15="",1,0) + IF('Depreciation'!B8="",1,0))<=2,"MINOR","NEEDS WORK"))
A12: of 97 fields filled | E12: to Form 1040 Schedule 1 Line 5 | I12: 0 missing = green
A16: =HYPERLINK("#'Schedule E Map'!A1", "📄 PRINT SCHEDULE E MAP →")
A21: Tip: print 1 page (the Schedule E Map tab) and email it with your supporting workbook to your CPA — saves billable hours.
A23: 💡 Upgrade to the Tax Season Bundle ($147) at thestrledger.com/tax-bundle — Schedule E + Schedule C + Mileage + 1099 + Home Office + Section 179 + Quarterly Estimateds + Per-Diem.
A26: Questions? hello@thestrledger.com
A27: TAX-004 · v2.2 · Free updates forever

Sheet Settings
A2: =HYPERLINK("#'Launch'!A1", "← BACK") | D2: SETTINGS
A4: Active tax year · Schedule classification · references
A5: Active tax year: | B5: 2026
A6: Schedule classification: | B6: Schedule E (passive)
A7: ⚠ Substantial-services trigger: if you provide cleaning DURING stays, meals, or concierge, IRS requires Schedule C (15.3% SE tax).
A9: Year-end Archive
A10: Each January, copy total Net (Line 26) into the row for the closing year, then update the Active tax year above.
A11: Year | B11: Schedule E Line 26 | C11: Active/Material?
A12: 2024
A13: 2025
A14: 2026
A15: 2027
A16: 2028
A17: 2029
A18: 2030
A22: Questions? hello@thestrledger.com
A23: TAX-004 · v2.2 · Free updates forever
