Workbook

Sheet Start
A2: The STR Ledger
A4: Quarterly Estimated Tax
A5: Stop guessing what you owe.
A6: =IF(SUM('Quarterly P&L'!B11:E11)=0,"📊 Fill Settings + Quarterly P&L to see your verdict.","→ Next voucher = "&TEXT(IFERROR(INDEX('Payment Schedule'!E6:E9,MATCH("",'Payment Schedule'!F6:F9,0)),0),"$#,##0")&" · "&'Estimated Tax'!B27)
A7: TAX-005 · v2.3 · DEMO
A10: WHAT THIS DOES
A11: Track your rental income and expenses by IRS quarter (NOT calendar quarter — Q1 = Jan-Mar 31, Q2 = Apr-May 31, Q3 = Jun-Aug 31, Q4 = Sep-Dec 31). The Estimated Tax tab applies the safe-harbor rule (100% / 110% of prior-year tax) and the annualized installment method (Form 1040-ES). The Payment Schedule tab shows what to send each due date.
A18: HOW TO USE
A19: ① Open Settings — fill prior-year AGI, prior-year tax, filing status.
A20: ② Quarterly P&L — enter each quarter's actual income and expenses as they happen.
A21: ③ Estimated Tax — automatic. Shows annualized vs safe-harbor; uses the lower.
A22: ④ Payment Schedule — print or screenshot the quarter's voucher amount.
A23: ⑤ Pay via IRS Direct Pay (irs.gov/payments) and mark the row Paid.
A26: =HYPERLINK("#'Quarterly P&L'!A6", "→ UPDATE QUARTERLY P&L →")
A32: YTD NET PROFIT | E32: NEXT VOUCHER | I32: STATUS
A33: ='Quarterly P&L'!F31 | E33: =IFERROR(INDEX('Payment Schedule'!E6:E9,MATCH("",'Payment Schedule'!F6:F9,0)),"all paid") | I33: ='Estimated Tax'!B27
A35: from rentals YTD | E35: next unpaid quarter | I35: vs safe-harbor floor
A38: =HYPERLINK("#'Quarterly P&L'!A1", "Quarterly P&L") | D38: =HYPERLINK("#'Estimated Tax'!A1", "Estimated Tax") | G38: =HYPERLINK("#'Payment Schedule'!A1", "Payment Schedule") | J38: =HYPERLINK("#'Settings'!A1", "Settings")
A41: 📅 IRS due dates — Apr 15 (Q1), Jun 15 (Q2), Sep 15 (Q3), Jan 15 NEXT YEAR (Q4). Underpayment penalty is 8% APR (IRC §6621) on each shortfall.
A44: Questions? hello@thestrledger.com
A45: TAX-005 · v2.3 · Free updates forever

Sheet Quarterly P&L
A2: =HYPERLINK("#'Start'!A1", "← BACK") | D2: QUARTERLY P&L | J2: =HYPERLINK("#'Estimated Tax'!A1", "NEXT →")
A4: Income and expenses by IRS quarter — Q1 (Jan-Mar), Q2 (Apr-May), Q3 (Jun-Aug), Q4 (Sep-Dec).
A5: Line | B5: Q1 (Jan-Mar) | C5: Q2 (Apr-May) | D5: Q3 (Jun-Aug) | E5: Q4 (Sep-Dec) | F5: YTD
A6: INCOME
A7: Gross rents (Airbnb/VRBO net of host fee) | B7: 12400 | C7: 18900 | D7: 22600 | E7: 14200 | F7: =SUM(B7:E7)
A8: Cleaning fees collected | B8: 1800 | C8: 2400 | D8: 2900 | E8: 1900 | F8: =SUM(B8:E8)
A9: Other income (cancellations kept, late fees) | B9: 120 | C9: 240 | D9: 360 | E9: 80 | F9: =SUM(B9:E9)
A10: Less refunds / chargebacks | B10: -200 | C10: 0 | D10: -150 | E10: -100 | F10: =SUM(B10:E10)
A11: Total Income | B11: =SUM(B7:B10) | C11: =SUM(C7:C10) | D11: =SUM(D7:D10) | E11: =SUM(E7:E10) | F11: =SUM(F7:F10)
A13: EXPENSES
A14: Advertising / listing photos | B14: 180 | C14: 0 | D14: 0 | E14: 220 | F14: =SUM(B14:E14)
A15: Auto and travel (mileage × IRS rate) | B15: 820 | C15: 1240 | D15: 1680 | E15: 940 | F15: =SUM(B15:E15)
A16: Cleaning and maintenance | B16: 1800 | C16: 2200 | D16: 2600 | E16: 1900 | F16: =SUM(B16:E16)
A17: Commissions (Airbnb host fee 3%) | B17: 372 | C17: 567 | D17: 678 | E17: 426 | F17: =SUM(B17:E17)
A18: Insurance | B18: 620 | C18: 0 | D18: 620 | E18: 0 | F18: =SUM(B18:E18)
A19: Legal / professional fees | B19: 0 | C19: 280 | D19: 0 | E19: 200 | F19: =SUM(B19:E19)
A20: Management fees | B20: 0 | C20: 0 | D20: 0 | E20: 0 | F20: =SUM(B20:E20)
A21: Mortgage interest | B21: 3200 | C21: 3180 | D21: 3160 | E21: 3140 | F21: =SUM(B21:E21)
A22: Repairs | B22: 380 | C22: 720 | D22: 940 | E22: 280 | F22: =SUM(B22:E22)
A23: Supplies | B23: 410 | C23: 380 | D23: 480 | E23: 320 | F23: =SUM(B23:E23)
A24: Property taxes | B24: 0 | C24: 0 | D24: 1840 | E24: 0 | F24: =SUM(B24:E24)
A25: Utilities | B25: 820 | C25: 940 | D25: 1140 | E25: 880 | F25: =SUM(B25:E25)
... A28: Other (platform tech, software) | B28: 180 | C28: 220 | D28: 240 | E28: 200 | F28: =SUM(B28:E28)
A29: Total Expenses | B29: =SUM(B14:B28) | C29: =SUM(C14:C28) | D29: =SUM(D14:D28) | E29: =SUM(E14:E28) | F29: =SUM(F14:F28)
A31: NET PROFIT (Income − Expenses) | B31: =B11-B29 | C31: =C11-C29 | D31: =D11-D29 | E31: =E11-E29 | F31: =F11-F29

Sheet Estimated Tax
A2: =HYPERLINK("#'Quarterly P&L'!A1", "← BACK") | D2: ESTIMATED TAX | J2: =HYPERLINK("#'Payment Schedule'!A1", "NEXT →")
A4: 1040-ES annualized installment method + safe-harbor rule.
A5: METHOD A — Annualized installment
A6: YTD net profit (from Quarterly P&L): | B6: ='Quarterly P&L'!F31
A7: Other YTD income (memo, e.g., spouse W-2): | B7: ='Settings'!B11
A8: Combined YTD income: | B8: =B6+B7
A9: Standard deduction (filing status): | B9: =VLOOKUP('Settings'!B8,'Settings'!E15:F18,2,FALSE)
A10: Taxable income (YTD, est.): | B10: =MAX(B8-B9,0)
A11: Income tax (bracket lookup, est.): | B11: =ROUND(B10*0.22,0)
A12: SE tax (Sched C only — 15.3% × 92.35% × net SE): | B12: =IF('Settings'!B6="Schedule C (active)",ROUND(B6*0.9235*0.153,0),0)
A13: Half SE-tax adjustment (deductible above the line): | B13: =ROUND(B12/2,0)
A14: Total federal tax (annualized YTD): | B14: =B11+B12-B13
A16: METHOD B — Safe harbor (prior-year)
A17: Prior-year AGI: | B17: =Settings!B9
A18: Prior-year total tax: | B18: =Settings!B10
A19: Safe-harbor multiplier (110% if prior AGI > $150K): | B19: =IF(B17>150000,1.10,1.00)
A20: Safe-harbor minimum required: | B20: =ROUND(B18*B19,0)
A22: REQUIRED PAYMENT — annual + per-quarter
A23: Required annual (lesser of A or B): | B23: =MIN(B14,B20)
A24: Less: YTD W-2 withholding (spouse, etc.): | B24: =Settings!B12
A25: Net required from estimateds: | B25: =MAX(B23-B24,0)
A26: Per-quarter voucher (÷ 4): | B26: =ROUND(B25/4,0)
A27: Underpayment risk flag: | B27: =IF(SUM('Payment Schedule'!E6:E9)>=B25,"ON TRACK",IF(SUM('Payment Schedule'!G6:G9)>=B25*COUNTIF('Payment Schedule'!F6:F9,"Paid")/4,"PACED","BEHIND"))
A29: ⓘ Method A is forward-looking (where YTD income suggests the year will land); Method B locks in protection from underpayment penalty by guaranteeing you pay at least last year's tax. The IRS waives §6654 penalty if you pay the lower.

Sheet Payment Schedule
A2: =HYPERLINK("#'Estimated Tax'!A1", "← BACK") | D2: PAYMENT SCHEDULE · FOR YOUR CPA | J2: =HYPERLINK("#'Settings'!A1", "NEXT →")
A4: 📄 FOR YOUR CPA — print this tab. Quarterly voucher amounts and IRS due dates (Form 1040-ES).
A5: Quarter | B5: Period | C5: Due Date | D5: Suggested $ | E5: Voucher $ | F5: Status | G5: Paid $ | H5: Confirmation # / Method
A6: Q1 | B6: (Jan-Mar) | C6: 46127 | D6: ='Estimated Tax'!$B$26
A7: Q2 | B7: (Apr-May) | C7: 46188 | D7: ='Estimated Tax'!$B$26
A8: Q3 | B8: (Jun-Aug) | C8: 46280 | D8: ='Estimated Tax'!$B$26
A9: Q4 | B9: (Sep-Dec) | C9: 46402 | D9: ='Estimated Tax'!$B$26
A11: YTD | D11: =SUM(D6:D9) | E11: =SUM(E6:E9) | G11: =SUM(G6:G9)
A13: 💡 Pay via IRS Direct Pay (irs.gov/payments) — free, no enrollment, or EFTPS (eftps.gov, requires enrollment). Mail-in vouchers also accepted with check, but allow 7-10 days for posting. Save the confirmation number.

Sheet Settings
A2: =HYPERLINK("#'Payment Schedule'!A1", "← BACK") | D2: SETTINGS
A4: Tax year · classification · prior year · withholding · brackets.
A5: Active tax year: | B5: 2026
A6: Schedule classification: | B6: Schedule E (passive)
A7: Substantial services? (Y/N — drives Schedule C): | B7: N
A8: Filing status: | B8: MFJ
A9: Prior-year AGI: | B9: 148000
A10: Prior-year total tax (Form 1040 Line 24): | B10: 14200
A11: Other YTD income (memo, e.g., spouse W-2): | B11: 88000
A12: YTD W-2 withholding (spouse, this year): | B12: 8000
E14: 2026 Standard Deduction
E15: Single | F15: 15750
E16: MFJ | F16: 31500
E17: HoH | F17: 23625
E18: MFS | F18: 15750
A19: 📅 Brackets + standard deduction as of 2026-01-01 — edit me each Nov when IRS publishes new figures.
A20: 2026 Federal Income Tax Brackets (reference)
A21: From (Single) | B21: To (Single) | C21: Rate | D21: From (MFJ) | E21: To (MFJ) | F21: Rate
A22: 0 | B22: 11925 | C22: 0.1 | D22: 0 | E22: 23850 | F22: 0.1
A23: 11925 | B23: 48475 | C23: 0.12 | D23: 23850 | E23: 96950 | F23: 0.12
A24: 48475 | B24: 103350 | C24: 0.22 | D24: 96950 | E24: 206700 | F24: 0.22
A25: 103350 | B25: 197300 | C25: 0.24 | D25: 206700 | E25: 394600 | F25: 0.24
A26: 197300 | B26: 250525 | C26: 0.32 | D26: 394600 | E26: 501050 | F26: 0.32
A27: 250525 | B27: 626350 | C27: 0.35 | D27: 501050 | E27: 751600 | F27: 0.35
A28: 626350 | B28: — | C28: 0.37 | D28: 751600 | E28: — | F28: 0.37
A31: Year-end Archive
A32: Each January, copy YTD net + total paid + filed-tax into the row.
A33: Year | B33: YTD Net Profit | C33: Total Paid (Estimateds) | D33: Filed Tax
A34: 2024
A35: 2025
A36: 2026
A37: 2027
A38: 2028
A39: 2029
A40: 2030
