Workbook

Sheet Start
A2: The STR Ledger
A4: Depreciation Tracker
A5: Every depreciable asset, every year, one ledger.
A6: =IF(IFERROR('Current Year Summary'!F109,0)>0,"✅ Current-year depreciation = "&TEXT('Current Year Summary'!F109,"$#,##0")&" · Assets tracked = "&COUNTA('Asset Register'!A8:A107),"📊 Add an asset on the Asset Register to see your deduction.")
A7: TAX-013 · v2.3 · DEMO
A11: Portfolio at a glance
A13: ASSETS TRACKED | E13: CURRENT-YEAR DEPRECIATION | I13: ACCUMULATED THROUGH PRIOR YEAR
A14: =COUNTA('Asset Register'!A8:A107) | E14: ='Current Year Summary'!F109 | I14: ='Current Year Summary'!G109
A20: Quick Start
B22: ① Settings: confirm your active tax year and property list
B23: ② Asset Register: enter every depreciable asset (cost, class, date)
B24: ③ Schedule by Year: see the full life-of-asset depreciation arc
B25: ④ Current Year Summary: drop the totals onto Schedule C line 13 / Schedule E line 18
B26: ⑤ Form 4562 Worksheet: print + hand to your CPA
A29: =HYPERLINK("#'Asset Register'!A5", "ADD AN ASSET — OPEN REGISTER →")
A34: =HYPERLINK("#'Schedule by Year'!A1", "📅 Schedule by Year") | G34: =HYPERLINK("#'Form 4562 Worksheet'!A1", "📄 Form 4562 Worksheet")
A37: ⓘ Connects with TAX-009 (Section 179 Planner) and TAX-010 (Cost Segregation DIY). §179 + Bonus amounts entered on the Asset Register reduce adjusted basis before the year-by-year MACRS schedule runs.
A41: Questions? hello@thestrledger.com
A42: TAX-013 · v2.3 · Free updates forever

Sheet Asset Register
A2: =HYPERLINK("#'Start'!A1", "← BACK") | D2: ASSET REGISTER | J2: =HYPERLINK("#'Schedule by Year'!A1", "NEXT →")
A4: Master register — capacity 100 assets. Buildings = 27.5 (residential) / 39 (commercial), furniture = 7, appliances/tech/vehicles = 5, land improvements = 15. Land is non-depreciable.
A6: Yellow cells = your input. Gray cells = formulas (do not edit).
A7: Asset name | B7: Property | C7: Placed in service | D7: Cost basis | E7: MACRS yr | F7: Conv. | G7: Method | H7: §179 taken | I7: Bonus | J7: Adj. basis | K7: Recovery | L7: Salvage | M7: Disposition | N7: Notes
A8: Smokies Ridge — building | B8: Smokies Ridge Cabin | C8: 45458 | D8: 250000 | E8: 27.5 | F8: MM | G8: SL | H8: 0 | I8: 0 | J8: =IF(D8="","",MAX(D8-IFERROR(H8,0)-IFERROR(I8,0),0)) | K8: =IF(E8="","",IFERROR(VLOOKUP(E8,Settings!$A$22:$B$27,2,FALSE),"")) | L8: 0 | N8: Cost basis = purchase − land allocation
A9: Creek Side Lodge — building | B9: Creek Side Lodge | C9: 45458 | D9: 250000 | E9: 27.5 | F9: MM | G9: SL | H9: 0 | I9: 0 | J9: =IF(D9="","",MAX(D9-IFERROR(H9,0)-IFERROR(I9,0),0)) | K9: =IF(E9="","",IFERROR(VLOOKUP(E9,Settings!$A$22:$B$27,2,FALSE),"")) | L9: 0 | N9: Cost basis = purchase − land allocation
A10: Lakehouse A — building | B10: Lakehouse A | C10: 45458 | D10: 250000 | E10: 27.5 | F10: MM | G10: SL | H10: 0 | I10: 0 | J10: =IF(D10="","",MAX(D10-IFERROR(H10,0)-IFERROR(I10,0),0)) | K10: =IF(E10="","",IFERROR(VLOOKUP(E10,Settings!$A$22:$B$27,2,FALSE),"")) | L10: 0 | N10: Cost basis = purchase − land allocation
A11: Whole-home furniture set | B11: Smokies Ridge Cabin | C11: 45463 | D11: 18000 | E11: 7 | F11: HY | G11: 200% DB | H11: 0 | I11: 7200 | J11: =IF(D11="","",MAX(D11-IFERROR(H11,0)-IFERROR(I11,0),0)) | K11: =IF(E11="","",IFERROR(VLOOKUP(E11,Settings!$A$22:$B$27,2,FALSE),"")) | L11: 0 | N11: Bonus 40% taken Y1
A12: Stainless appliance package | B12: Creek Side Lodge | C12: 45478 | D12: 2400 | E12: 5 | F12: HY | G12: 200% DB | H12: 0 | I12: 960 | J12: =IF(D12="","",MAX(D12-IFERROR(H12,0)-IFERROR(I12,0),0)) | K12: =IF(E12="","",IFERROR(VLOOKUP(E12,Settings!$A$22:$B$27,2,FALSE),"")) | L12: 0 | N12: Bonus 40% taken Y1
A13: Smart TV + mounts package | B13: Lakehouse A | C13: 45516 | D13: 1600 | E13: 5 | F13: HY | G13: 200% DB | H13: 0 | I13: 640 | J13: =IF(D13="","",MAX(D13-IFERROR(H13,0)-IFERROR(I13,0),0)) | K13: =IF(E13="","",IFERROR(VLOOKUP(E13,Settings!$A$22:$B$27,2,FALSE),"")) | L13: 0 | N13: Bonus 40% taken Y1
A14: Ford F-150 (heavy truck >6,000lb) | B14: Smokies Ridge Cabin | C14: 45306 | D14: 42000 | E14: 5 | F14: HY | G14: 200% DB | H14: 30500 | I14: 4600 | J14: =IF(D14="","",MAX(D14-IFERROR(H14,0)-IFERROR(I14,0),0)) | K14: =IF(E14="","",IFERROR(VLOOKUP(E14,Settings!$A$22:$B$27,2,FALSE),"")) | L14: 0 | N14: Listed property — Form 4562 Part V
A15: Driveway extension + parking | B15: Smokies Ridge Cabin | C15: 45536 | D15: 12000 | E15: 15 | F15: HY | G15: 150% DB | H15: 0 | I15: 4800 | J15: =IF(D15="","",MAX(D15-IFERROR(H15,0)-IFERROR(I15,0),0)) | K15: =IF(E15="","",IFERROR(VLOOKUP(E15,Settings!$A$22:$B$27,2,FALSE),"")) | L15: 0 | N15: Land improvement
J16: =IF(D16="","",MAX(D16-IFERROR(H16,0)-IFERROR(I16,0),0)) | K16: =IF(E16="","",IFERROR(VLOOKUP(E16,Settings!$A$22:$B$27,2,FALSE),""))
J17: =IF(D17="","",MAX(D17-IFERROR(H17,0)-IFERROR(I17,0),0)) | K17: =IF(E17="","",IFERROR(VLOOKUP(E17,Settings!$A$22:$B$27,2,FALSE),""))
J18: =IF(D18="","",MAX(D18-IFERROR(H18,0)-IFERROR(I18,0),0)) | K18: =IF(E18="","",IFERROR(VLOOKUP(E18,Settings!$A$22:$B$27,2,FALSE),""))
J19: =IF(D19="","",MAX(D19-IFERROR(H19,0)-IFERROR(I19,0),0)) | K19: =IF(E19="","",IFERROR(VLOOKUP(E19,Settings!$A$22:$B$27,2,FALSE),""))
J20: =IF(D20="","",MAX(D20-IFERROR(H20,0)-IFERROR(I20,0),0)) | K20: =IF(E20="","",IFERROR(VLOOKUP(E20,Settings!$A$22:$B$27,2,FALSE),""))
J21: =IF(D21="","",MAX(D21-IFERROR(H21,0)-IFERROR(I21,0),0)) | K21: =IF(E21="","",IFERROR(VLOOKUP(E21,Settings!$A$22:$B$27,2,FALSE),""))
J22: =IF(D22="","",MAX(D22-IFERROR(H22,0)-IFERROR(I22,0),0)) | K22: =IF(E22="","",IFERROR(VLOOKUP(E22,Settings!$A$22:$B$27,2,FALSE),""))
J23: =IF(D23="","",MAX(D23-IFERROR(H23,0)-IFERROR(I23,0),0)) | K23: =IF(E23="","",IFERROR(VLOOKUP(E23,Settings!$A$22:$B$27,2,FALSE),""))
J24: =IF(D24="","",MAX(D24-IFERROR(H24,0)-IFERROR(I24,0),0)) | K24: =IF(E24="","",IFERROR(VLOOKUP(E24,Settings!$A$22:$B$27,2,FALSE),""))
J25: =IF(D25="","",MAX(D25-IFERROR(H25,0)-IFERROR(I25,0),0)) | K25: =IF(E25="","",IFERROR(VLOOKUP(E25,Settings!$A$22:$B$27,2,FALSE),""))
J26: =IF(D26="","",MAX(D26-IFERROR(H26,0)-IFERROR(I26,0),0)) | K26: =IF(E26="","",IFERROR(VLOOKUP(E26,Settings!$A$22:$B$27,2,FALSE),""))
J27: =IF(D27="","",MAX(D27-IFERROR(H27,0)-IFERROR(I27,0),0)) | K27: =IF(E27="","",IFERROR(VLOOKUP(E27,Settings!$A$22:$B$27,2,FALSE),""))
... J107: =IF(D107="","",MAX(D107-IFERROR(H107,0)-IFERROR(I107,0),0)) | K107: =IF(E107="","",IFERROR(VLOOKUP(E107,Settings!$A$22:$B$27,2,FALSE),""))
A108: Portfolio totals: | D108: =SUM(D8:D107) | H108: =SUM(H8:H107) | I108: =SUM(I8:I107) | J108: =SUM(J8:J107)
A110: ⓘ Adjusted basis = Cost − §179 − Bonus. This is the amount the year-by-year MACRS schedule depreciates over the recovery period. If you elect §179 or bonus, the standard percentage tables apply only to the residual basis, not the full cost.

Sheet Schedule by Year
A2: =HYPERLINK("#'Asset Register'!A1", "← BACK") | D2: SCHEDULE BY YEAR | J2: =HYPERLINK("#'Current Year Summary'!A1", "NEXT →")
A4: Asset × Year matrix. Each cell = (Adjusted basis × MACRS Y_n %) from the Settings lookup table. Bottom row = portfolio total per year.
A7: Asset | B7: Class | C7: Adj. basis | D7: Year 1 | E7: Year 2 | F7: Year 3 | G7: Year 4 | H7: Year 5 | I7: Year 6 | J7: Year 7 | K7: Year 8 | L7: Year 9 | M7: Year 10 | N7: Year 11 | O7: Year 12 | P7: Year 13 | Q7: Year 14 | R7: Year 15 | S7: Year 16 | T7: Year 17 | U7: Year 18 | V7: Year 19 | W7: Year 20 | X7: Year 21 | Y7: Year 22 | Z7: Year 23 | AA7: Year 24 | AB7: Year 25 | AC7: Year 26 | AD7: Year 27
A8: ='Asset Register'!A8 | B8: ='Asset Register'!E8 | C8: ='Asset Register'!J8 | D8: =IF(OR($B8="",$B8="Land",$C8=""),"",IFERROR($C8*INDEX(Settings!$C$22:$AC$27,MATCH($B8,Settings!$A$22:$A$27,0),1),0)) | E8: =IF(OR($B8="",$B8="Land",$C8=""),"",IFERROR($C8*INDEX(Settings!$C$22:$AC$27,MATCH($B8,Settings!$A$22:$A$27,0),2),0)) | F8: =IF(OR($B8="",$B8="Land",$C8=""),"",IFERROR($C8*INDEX(Settings!$C$22:$AC$27,MATCH($B8,Settings!$A$22:$A$27,0),3),0)) | G8: =IF(OR($B8="",$B8="Land",$C8=""),"",IFERROR($C8*INDEX(Settings!$C$22:$AC$27,MATCH($B8,Settings!$A$22:$A$27,0),4),0)) | H8: =IF(OR($B8="",$B8="Land",$C8=""),"",IFERROR($C8*INDEX(Settings!$C$22:$AC$27,MATCH($B8,Settings!$A$22:$A$27,0),5),0)) | I8: =IF(OR($B8="",$B8="Land",$C8=""),"",IFERROR($C8*INDEX(Settings!$C$22:$AC$27,MATCH($B8,Settings!$A$22:$A$27,0),6),0)) | J8: =IF(OR($B8="",$B8="Land",$C8=""),"",IFERROR($C8*INDEX(Settings!$C$22:$AC$27,MATCH($B8,Settings!$A$22:$A$27,0),7),0)) | K8: =IF(OR($B8="",$B8="Land",$C8=""),"",IFERROR($C8*INDEX(Settings!$C$22:$AC$27,MATCH($B8,Settings!$A$22:$A$27,0),8),0)) | L8: =IF(OR($B8="",$B8="Land",$C8=""),"",IFERROR($C8*INDEX(Settings!$C$22:$AC$27,MATCH($B8,Settings!$A$22:$A$27,0),9),0)) | M8: =IF(OR($B8="",$B8="Land",$C8=""),"",IFERROR($C8*INDEX(Settings!$C$22:$AC$27,MATCH($B8,Settings!$A$22:$A$27,0),10),0)) | N8: =IF(OR($B8="",$B8="Land",$C8=""),"",IFERROR($C8*INDEX(Settings!$C$22:$AC$27,MATCH($B8,Settings!$A$22:$A$27,0),11),0)) | O8: =IF(OR($B8="",$B8="Land",$C8=""),"",IFERROR($C8*INDEX(Settings!$C$22:$AC$27,MATCH($B8,Settings!$A$22:$A$27,0),12),0)) | P8: =IF(OR($B8="",$B8="Land",$C8=""),"",IFERROR($C8*INDEX(Settings!$C$22:$AC$27,MATCH($B8,Settings!$A$22:$A$27,0),13),0)) | Q8: =IF(OR($B8="",$B8="Land",$C8=""),"",IFERROR($C8*INDEX(Settings!$C$22:$AC$27,MATCH($B8,Settings!$A$22:$A$27,0),14),0)) | R8: =IF(OR($B8="",$B8="Land",$C8=""),"",IFERROR($C8*INDEX(Settings!$C$22:$AC$27,MATCH($B8,Settings!$A$22:$A$27,0),15),0)) | S8: =IF(OR($B8="",$B8="Land",$C8=""),"",IFERROR($C8*INDEX(Settings!$C$22:$AC$27,MATCH($B8,Settings!$A$22:$A$27,0),16),0)) | T8: =IF(OR($B8="",$B8="Land",$C8=""),"",IFERROR($C8*INDEX(Settings!$C$22:$AC$27,MATCH($B8,Settings!$A$22:$A$27,0),17),0)) | U8: =IF(OR($B8="",$B8="Land",$C8=""),"",IFERROR($C8*INDEX(Settings!$C$22:$AC$27,MATCH($B8,Settings!$A$22:$A$27,0),18),0)) | V8: =IF(OR($B8="",$B8="Land",$C8=""),"",IFERROR($C8*INDEX(Settings!$C$22:$AC$27,MATCH($B8,Settings!$A$22:$A$27,0),19),0)) | W8: =IF(OR($B8="",$B8="Land",$C8=""),"",IFERROR($C8*INDEX(Settings!$C$22:$AC$27,MATCH($B8,Settings!$A$22:$A$27,0),20),0)) | X8: =IF(OR($B8="",$B8="Land",$C8=""),"",IFERROR($C8*INDEX(Settings!$C$22:$AC$27,MATCH($B8,Settings!$A$22:$A$27,0),21),0)) | Y8: =IF(OR($B8="",$B8="Land",$C8=""),"",IFERROR($C8*INDEX(Settings!$C$22:$AC$27,MATCH($B8,Settings!$A$22:$A$27,0),22),0)) | Z8: =IF(OR($B8="",$B8="Land",$C8=""),"",IFERROR($C8*INDEX(Settings!$C$22:$AC$27,MATCH($B8,Settings!$A$22:$A$27,0),23),0)) | AA8: =IF(OR($B8="",$B8="Land",$C8=""),"",IFERROR($C8*INDEX(Settings!$C$22:$AC$27,MATCH($B8,Settings!$A$22:$A$27,0),24),0)) | AB8: =IF(OR($B8="",$B8="Land",$C8=""),"",IFERROR($C8*INDEX(Settings!$C$22:$AC$27,MATCH($B8,Settings!$A$22:$A$27,0),25),0)) | AC8: =IF(OR($B8="",$B8="Land",$C8=""),"",IFERROR($C8*INDEX(Settings!$C$22:$AC$27,MATCH($B8,Settings!$A$22:$A$27,0),26),0)) | AD8: =IF(OR($B8="",$B8="Land",$C8=""),"",IFERROR($C8*INDEX(Settings!$C$22:$AC$27,MATCH($B8,Settings!$A$22:$A$27,0),27),0))
A9: ='Asset Register'!A9 | B9: ='Asset Register'!E9 | C9: ='Asset Register'!J9 | D9: =IF(OR($B9="",$B9="Land",$C9=""),"",IFERROR($C9*INDEX(Settings!$C$22:$AC$27,MATCH($B9,Settings!$A$22:$A$27,0),1),0)) | E9: =IF(OR($B9="",$B9="Land",$C9=""),"",IFERROR($C9*INDEX(Settings!$C$22:$AC$27,MATCH($B9,Settings!$A$22:$A$27,0),2),0)) | F9: =IF(OR($B9="",$B9="Land",$C9=""),"",IFERROR($C9*INDEX(Settings!$C$22:$AC$27,MATCH($B9,Settings!$A$22:$A$27,0),3),0)) | G9: =IF(OR($B9="",$B9="Land",$C9=""),"",IFERROR($C9*INDEX(Settings!$C$22:$AC$27,MATCH($B9,Settings!$A$22:$A$27,0),4),0)) | H9: =IF(OR($B9="",$B9="Land",$C9=""),"",IFERROR($C9*INDEX(Settings!$C$22:$AC$27,MATCH($B9,Settings!$A$22:$A$27,0),5),0)) | I9: =IF(OR($B9="",$B9="Land",$C9=""),"",IFERROR($C9*INDEX(Settings!$C$22:$AC$27,MATCH($B9,Settings!$A$22:$A$27,0),6),0)) | J9: =IF(OR($B9="",$B9="Land",$C9=""),"",IFERROR($C9*INDEX(Settings!$C$22:$AC$27,MATCH($B9,Settings!$A$22:$A$27,0),7),0)) | K9: =IF(OR($B9="",$B9="Land",$C9=""),"",IFERROR($C9*INDEX(Settings!$C$22:$AC$27,MATCH($B9,Settings!$A$22:$A$27,0),8),0)) | L9: =IF(OR($B9="",$B9="Land",$C9=""),"",IFERROR($C9*INDEX(Settings!$C$22:$AC$27,MATCH($B9,Settings!$A$22:$A$27,0),9),0)) | M9: =IF(OR($B9="",$B9="Land",$C9=""),"",IFERROR($C9*INDEX(Settings!$C$22:$AC$27,MATCH($B9,Settings!$A$22:$A$27,0),10),0)) | N9: =IF(OR($B9="",$B9="Land",$C9=""),"",IFERROR($C9*INDEX(Settings!$C$22:$AC$27,MATCH($B9,Settings!$A$22:$A$27,0),11),0)) | O9: =IF(OR($B9="",$B9="Land",$C9=""),"",IFERROR($C9*INDEX(Settings!$C$22:$AC$27,MATCH($B9,Settings!$A$22:$A$27,0),12),0)) | P9: =IF(OR($B9="",$B9="Land",$C9=""),"",IFERROR($C9*INDEX(Settings!$C$22:$AC$27,MATCH($B9,Settings!$A$22:$A$27,0),13),0)) | Q9: =IF(OR($B9="",$B9="Land",$C9=""),"",IFERROR($C9*INDEX(Settings!$C$22:$AC$27,MATCH($B9,Settings!$A$22:$A$27,0),14),0)) | R9: =IF(OR($B9="",$B9="Land",$C9=""),"",IFERROR($C9*INDEX(Settings!$C$22:$AC$27,MATCH($B9,Settings!$A$22:$A$27,0),15),0)) | S9: =IF(OR($B9="",$B9="Land",$C9=""),"",IFERROR($C9*INDEX(Settings!$C$22:$AC$27,MATCH($B9,Settings!$A$22:$A$27,0),16),0)) | T9: =IF(OR($B9="",$B9="Land",$C9=""),"",IFERROR($C9*INDEX(Settings!$C$22:$AC$27,MATCH($B9,Settings!$A$22:$A$27,0),17),0)) | U9: =IF(OR($B9="",$B9="Land",$C9=""),"",IFERROR($C9*INDEX(Settings!$C$22:$AC$27,MATCH($B9,Settings!$A$22:$A$27,0),18),0)) | V9: =IF(OR($B9="",$B9="Land",$C9=""),"",IFERROR($C9*INDEX(Settings!$C$22:$AC$27,MATCH($B9,Settings!$A$22:$A$27,0),19),0)) | W9: =IF(OR($B9="",$B9="Land",$C9=""),"",IFERROR($C9*INDEX(Settings!$C$22:$AC$27,MATCH($B9,Settings!$A$22:$A$27,0),20),0)) | X9: =IF(OR($B9="",$B9="Land",$C9=""),"",IFERROR($C9*INDEX(Settings!$C$22:$AC$27,MATCH($B9,Settings!$A$22:$A$27,0),21),0)) | Y9: =IF(OR($B9="",$B9="Land",$C9=""),"",IFERROR($C9*INDEX(Settings!$C$22:$AC$27,MATCH($B9,Settings!$A$22:$A$27,0),22),0)) | Z9: =IF(OR($B9="",$B9="Land",$C9=""),"",IFERROR($C9*INDEX(Settings!$C$22:$AC$27,MATCH($B9,Settings!$A$22:$A$27,0),23),0)) | AA9: =IF(OR($B9="",$B9="Land",$C9=""),"",IFERROR($C9*INDEX(Settings!$C$22:$AC$27,MATCH($B9,Settings!$A$22:$A$27,0),24),0)) | AB9: =IF(OR($B9="",$B9="Land",$C9=""),"",IFERROR($C9*INDEX(Settings!$C$22:$AC$27,MATCH($B9,Settings!$A$22:$A$27,0),25),0)) | AC9: =IF(OR($B9="",$B9="Land",$C9=""),"",IFERROR($C9*INDEX(Settings!$C$22:$AC$27,MATCH($B9,Settings!$A$22:$A$27,0),26),0)) | AD9: =IF(OR($B9="",$B9="Land",$C9=""),"",IFERROR($C9*INDEX(Settings!$C$22:$AC$27,MATCH($B9,Settings!$A$22:$A$27,0),27),0))
A10: ='Asset Register'!A10 | B10: ='Asset Register'!E10 | C10: ='Asset Register'!J10 | D10: =IF(OR($B10="",$B10="Land",$C10=""),"",IFERROR($C10*INDEX(Settings!$C$22:$AC$27,MATCH($B10,Settings!$A$22:$A$27,0),1),0)) | E10: =IF(OR($B10="",$B10="Land",$C10=""),"",IFERROR($C10*INDEX(Settings!$C$22:$AC$27,MATCH($B10,Settings!$A$22:$A$27,0),2),0)) | F10: =IF(OR($B10="",$B10="Land",$C10=""),"",IFERROR($C10*INDEX(Settings!$C$22:$AC$27,MATCH($B10,Settings!$A$22:$A$27,0),3),0)) | G10: =IF(OR($B10="",$B10="Land",$C10=""),"",IFERROR($C10*INDEX(Settings!$C$22:$AC$27,MATCH($B10,Settings!$A$22:$A$27,0),4),0)) | H10: =IF(OR($B10="",$B10="Land",$C10=""),"",IFERROR($C10*INDEX(Settings!$C$22:$AC$27,MATCH($B10,Settings!$A$22:$A$27,0),5),0)) | I10: =IF(OR($B10="",$B10="Land",$C10=""),"",IFERROR($C10*INDEX(Settings!$C$22:$AC$27,MATCH($B10,Settings!$A$22:$A$27,0),6),0)) | J10: =IF(OR($B10="",$B10="Land",$C10=""),"",IFERROR($C10*INDEX(Settings!$C$22:$AC$27,MATCH($B10,Settings!$A$22:$A$27,0),7),0)) | K10: =IF(OR($B10="",$B10="Land",$C10=""),"",IFERROR($C10*INDEX(Settings!$C$22:$AC$27,MATCH($B10,Settings!$A$22:$A$27,0),8),0)) | L10: =IF(OR($B10="",$B10="Land",$C10=""),"",IFERROR($C10*INDEX(Settings!$C$22:$AC$27,MATCH($B10,Settings!$A$22:$A$27,0),9),0)) | M10: =IF(OR($B10="",$B10="Land",$C10=""),"",IFERROR($C10*INDEX(Settings!$C$22:$AC$27,MATCH($B10,Settings!$A$22:$A$27,0),10),0)) | N10: =IF(OR($B10="",$B10="Land",$C10=""),"",IFERROR($C10*INDEX(Settings!$C$22:$AC$27,MATCH($B10,Settings!$A$22:$A$27,0),11),0)) | O10: =IF(OR($B10="",$B10="Land",$C10=""),"",IFERROR($C10*INDEX(Settings!$C$22:$AC$27,MATCH($B10,Settings!$A$22:$A$27,0),12),0)) | P10: =IF(OR($B10="",$B10="Land",$C10=""),"",IFERROR($C10*INDEX(Settings!$C$22:$AC$27,MATCH($B10,Settings!$A$22:$A$27,0),13),0)) | Q10: =IF(OR($B10="",$B10="Land",$C10=""),"",IFERROR($C10*INDEX(Settings!$C$22:$AC$27,MATCH($B10,Settings!$A$22:$A$27,0),14),0)) | R10: =IF(OR($B10="",$B10="Land",$C10=""),"",IFERROR($C10*INDEX(Settings!$C$22:$AC$27,MATCH($B10,Settings!$A$22:$A$27,0),15),0)) | S10: =IF(OR($B10="",$B10="Land",$C10=""),"",IFERROR($C10*INDEX(Settings!$C$22:$AC$27,MATCH($B10,Settings!$A$22:$A$27,0),16),0)) | T10: =IF(OR($B10="",$B10="Land",$C10=""),"",IFERROR($C10*INDEX(Settings!$C$22:$AC$27,MATCH($B10,Settings!$A$22:$A$27,0),17),0)) | U10: =IF(OR($B10="",$B10="Land",$C10=""),"",IFERROR($C10*INDEX(Settings!$C$22:$AC$27,MATCH($B10,Settings!$A$22:$A$27,0),18),0)) | V10: =IF(OR($B10="",$B10="Land",$C10=""),"",IFERROR($C10*INDEX(Settings!$C$22:$AC$27,MATCH($B10,Settings!$A$22:$A$27,0),19),0)) | W10: =IF(OR($B10="",$B10="Land",$C10=""),"",IFERROR($C10*INDEX(Settings!$C$22:$AC$27,MATCH($B10,Settings!$A$22:$A$27,0),20),0)) | X10: =IF(OR($B10="",$B10="Land",$C10=""),"",IFERROR($C10*INDEX(Settings!$C$22:$AC$27,MATCH($B10,Settings!$A$22:$A$27,0),21),0)) | Y10: =IF(OR($B10="",$B10="Land",$C10=""),"",IFERROR($C10*INDEX(Settings!$C$22:$AC$27,MATCH($B10,Settings!$A$22:$A$27,0),22),0)) | Z10: =IF(OR($B10="",$B10="Land",$C10=""),"",IFERROR($C10*INDEX(Settings!$C$22:$AC$27,MATCH($B10,Settings!$A$22:$A$27,0),23),0)) | AA10: =IF(OR($B10="",$B10="Land",$C10=""),"",IFERROR($C10*INDEX(Settings!$C$22:$AC$27,MATCH($B10,Settings!$A$22:$A$27,0),24),0)) | AB10: =IF(OR($B10="",$B10="Land",$C10=""),"",IFERROR($C10*INDEX(Settings!$C$22:$AC$27,MATCH($B10,Settings!$A$22:$A$27,0),25),0)) | AC10: =IF(OR($B10="",$B10="Land",$C10=""),"",IFERROR($C10*INDEX(Settings!$C$22:$AC$27,MATCH($B10,Settings!$A$22:$A$27,0),26),0)) | AD10: =IF(OR($B10="",$B10="Land",$C10=""),"",IFERROR($C10*INDEX(Settings!$C$22:$AC$27,MATCH($B10,Settings!$A$22:$A$27,0),27),0))
A11: ='Asset Register'!A11 | B11: ='Asset Register'!E11 | C11: ='Asset Register'!J11 | D11: =IF(OR($B11="",$B11="Land",$C11=""),"",IFERROR($C11*INDEX(Settings!$C$22:$AC$27,MATCH($B11,Settings!$A$22:$A$27,0),1),0)) | E11: =IF(OR($B11="",$B11="Land",$C11=""),"",IFERROR($C11*INDEX(Settings!$C$22:$AC$27,MATCH($B11,Settings!$A$22:$A$27,0),2),0)) | F11: =IF(OR($B11="",$B11="Land",$C11=""),"",IFERROR($C11*INDEX(Settings!$C$22:$AC$27,MATCH($B11,Settings!$A$22:$A$27,0),3),0)) | G11: =IF(OR($B11="",$B11="Land",$C11=""),"",IFERROR($C11*INDEX(Settings!$C$22:$AC$27,MATCH($B11,Settings!$A$22:$A$27,0),4),0)) | H11: =IF(OR($B11="",$B11="Land",$C11=""),"",IFERROR($C11*INDEX(Settings!$C$22:$AC$27,MATCH($B11,Settings!$A$22:$A$27,0),5),0)) | I11: =IF(OR($B11="",$B11="Land",$C11=""),"",IFERROR($C11*INDEX(Settings!$C$22:$AC$27,MATCH($B11,Settings!$A$22:$A$27,0),6),0)) | J11: =IF(OR($B11="",$B11="Land",$C11=""),"",IFERROR($C11*INDEX(Settings!$C$22:$AC$27,MATCH($B11,Settings!$A$22:$A$27,0),7),0)) | K11: =IF(OR($B11="",$B11="Land",$C11=""),"",IFERROR($C11*INDEX(Settings!$C$22:$AC$27,MATCH($B11,Settings!$A$22:$A$27,0),8),0)) | L11: =IF(OR($B11="",$B11="Land",$C11=""),"",IFERROR($C11*INDEX(Settings!$C$22:$AC$27,MATCH($B11,Settings!$A$22:$A$27,0),9),0)) | M11: =IF(OR($B11="",$B11="Land",$C11=""),"",IFERROR($C11*INDEX(Settings!$C$22:$AC$27,MATCH($B11,Settings!$A$22:$A$27,0),10),0)) | N11: =IF(OR($B11="",$B11="Land",$C11=""),"",IFERROR($C11*INDEX(Settings!$C$22:$AC$27,MATCH($B11,Settings!$A$22:$A$27,0),11),0)) | O11: =IF(OR($B11="",$B11="Land",$C11=""),"",IFERROR($C11*INDEX(Settings!$C$22:$AC$27,MATCH($B11,Settings!$A$22:$A$27,0),12),0)) | P11: =IF(OR($B11="",$B11="Land",$C11=""),"",IFERROR($C11*INDEX(Settings!$C$22:$AC$27,MATCH($B11,Settings!$A$22:$A$27,0),13),0)) | Q11: =IF(OR($B11="",$B11="Land",$C11=""),"",IFERROR($C11*INDEX(Settings!$C$22:$AC$27,MATCH($B11,Settings!$A$22:$A$27,0),14),0)) | R11: =IF(OR($B11="",$B11="Land",$C11=""),"",IFERROR($C11*INDEX(Settings!$C$22:$AC$27,MATCH($B11,Settings!$A$22:$A$27,0),15),0)) | S11: =IF(OR($B11="",$B11="Land",$C11=""),"",IFERROR($C11*INDEX(Settings!$C$22:$AC$27,MATCH($B11,Settings!$A$22:$A$27,0),16),0)) | T11: =IF(OR($B11="",$B11="Land",$C11=""),"",IFERROR($C11*INDEX(Settings!$C$22:$AC$27,MATCH($B11,Settings!$A$22:$A$27,0),17),0)) | U11: =IF(OR($B11="",$B11="Land",$C11=""),"",IFERROR($C11*INDEX(Settings!$C$22:$AC$27,MATCH($B11,Settings!$A$22:$A$27,0),18),0)) | V11: =IF(OR($B11="",$B11="Land",$C11=""),"",IFERROR($C11*INDEX(Settings!$C$22:$AC$27,MATCH($B11,Settings!$A$22:$A$27,0),19),0)) | W11: =IF(OR($B11="",$B11="Land",$C11=""),"",IFERROR($C11*INDEX(Settings!$C$22:$AC$27,MATCH($B11,Settings!$A$22:$A$27,0),20),0)) | X11: =IF(OR($B11="",$B11="Land",$C11=""),"",IFERROR($C11*INDEX(Settings!$C$22:$AC$27,MATCH($B11,Settings!$A$22:$A$27,0),21),0)) | Y11: =IF(OR($B11="",$B11="Land",$C11=""),"",IFERROR($C11*INDEX(Settings!$C$22:$AC$27,MATCH($B11,Settings!$A$22:$A$27,0),22),0)) | Z11: =IF(OR($B11="",$B11="Land",$C11=""),"",IFERROR($C11*INDEX(Settings!$C$22:$AC$27,MATCH($B11,Settings!$A$22:$A$27,0),23),0)) | AA11: =IF(OR($B11="",$B11="Land",$C11=""),"",IFERROR($C11*INDEX(Settings!$C$22:$AC$27,MATCH($B11,Settings!$A$22:$A$27,0),24),0)) | AB11: =IF(OR($B11="",$B11="Land",$C11=""),"",IFERROR($C11*INDEX(Settings!$C$22:$AC$27,MATCH($B11,Settings!$A$22:$A$27,0),25),0)) | AC11: =IF(OR($B11="",$B11="Land",$C11=""),"",IFERROR($C11*INDEX(Settings!$C$22:$AC$27,MATCH($B11,Settings!$A$22:$A$27,0),26),0)) | AD11: =IF(OR($B11="",$B11="Land",$C11=""),"",IFERROR($C11*INDEX(Settings!$C$22:$AC$27,MATCH($B11,Settings!$A$22:$A$27,0),27),0))
A12: ='Asset Register'!A12 | B12: ='Asset Register'!E12 | C12: ='Asset Register'!J12 | D12: =IF(OR($B12="",$B12="Land",$C12=""),"",IFERROR($C12*INDEX(Settings!$C$22:$AC$27,MATCH($B12,Settings!$A$22:$A$27,0),1),0)) | E12: =IF(OR($B12="",$B12="Land",$C12=""),"",IFERROR($C12*INDEX(Settings!$C$22:$AC$27,MATCH($B12,Settings!$A$22:$A$27,0),2),0)) | F12: =IF(OR($B12="",$B12="Land",$C12=""),"",IFERROR($C12*INDEX(Settings!$C$22:$AC$27,MATCH($B12,Settings!$A$22:$A$27,0),3),0)) | G12: =IF(OR($B12="",$B12="Land",$C12=""),"",IFERROR($C12*INDEX(Settings!$C$22:$AC$27,MATCH($B12,Settings!$A$22:$A$27,0),4),0)) | H12: =IF(OR($B12="",$B12="Land",$C12=""),"",IFERROR($C12*INDEX(Settings!$C$22:$AC$27,MATCH($B12,Settings!$A$22:$A$27,0),5),0)) | I12: =IF(OR($B12="",$B12="Land",$C12=""),"",IFERROR($C12*INDEX(Settings!$C$22:$AC$27,MATCH($B12,Settings!$A$22:$A$27,0),6),0)) | J12: =IF(OR($B12="",$B12="Land",$C12=""),"",IFERROR($C12*INDEX(Settings!$C$22:$AC$27,MATCH($B12,Settings!$A$22:$A$27,0),7),0)) | K12: =IF(OR($B12="",$B12="Land",$C12=""),"",IFERROR($C12*INDEX(Settings!$C$22:$AC$27,MATCH($B12,Settings!$A$22:$A$27,0),8),0)) | L12: =IF(OR($B12="",$B12="Land",$C12=""),"",IFERROR($C12*INDEX(Settings!$C$22:$AC$27,MATCH($B12,Settings!$A$22:$A$27,0),9),0)) | M12: =IF(OR($B12="",$B12="Land",$C12=""),"",IFERROR($C12*INDEX(Settings!$C$22:$AC$27,MATCH($B12,Settings!$A$22:$A$27,0),10),0)) | N12: =IF(OR($B12="",$B12="Land",$C12=""),"",IFERROR($C12*INDEX(Settings!$C$22:$AC$27,MATCH($B12,Settings!$A$22:$A$27,0),11),0)) | O12: =IF(OR($B12="",$B12="Land",$C12=""),"",IFERROR($C12*INDEX(Settings!$C$22:$AC$27,MATCH($B12,Settings!$A$22:$A$27,0),12),0)) | P12: =IF(OR($B12="",$B12="Land",$C12=""),"",IFERROR($C12*INDEX(Settings!$C$22:$AC$27,MATCH($B12,Settings!$A$22:$A$27,0),13),0)) | Q12: =IF(OR($B12="",$B12="Land",$C12=""),"",IFERROR($C12*INDEX(Settings!$C$22:$AC$27,MATCH($B12,Settings!$A$22:$A$27,0),14),0)) | R12: =IF(OR($B12="",$B12="Land",$C12=""),"",IFERROR($C12*INDEX(Settings!$C$22:$AC$27,MATCH($B12,Settings!$A$22:$A$27,0),15),0)) | S12: =IF(OR($B12="",$B12="Land",$C12=""),"",IFERROR($C12*INDEX(Settings!$C$22:$AC$27,MATCH($B12,Settings!$A$22:$A$27,0),16),0)) | T12: =IF(OR($B12="",$B12="Land",$C12=""),"",IFERROR($C12*INDEX(Settings!$C$22:$AC$27,MATCH($B12,Settings!$A$22:$A$27,0),17),0)) | U12: =IF(OR($B12="",$B12="Land",$C12=""),"",IFERROR($C12*INDEX(Settings!$C$22:$AC$27,MATCH($B12,Settings!$A$22:$A$27,0),18),0)) | V12: =IF(OR($B12="",$B12="Land",$C12=""),"",IFERROR($C12*INDEX(Settings!$C$22:$AC$27,MATCH($B12,Settings!$A$22:$A$27,0),19),0)) | W12: =IF(OR($B12="",$B12="Land",$C12=""),"",IFERROR($C12*INDEX(Settings!$C$22:$AC$27,MATCH($B12,Settings!$A$22:$A$27,0),20),0)) | X12: =IF(OR($B12="",$B12="Land",$C12=""),"",IFERROR($C12*INDEX(Settings!$C$22:$AC$27,MATCH($B12,Settings!$A$22:$A$27,0),21),0)) | Y12: =IF(OR($B12="",$B12="Land",$C12=""),"",IFERROR($C12*INDEX(Settings!$C$22:$AC$27,MATCH($B12,Settings!$A$22:$A$27,0),22),0)) | Z12: =IF(OR($B12="",$B12="Land",$C12=""),"",IFERROR($C12*INDEX(Settings!$C$22:$AC$27,MATCH($B12,Settings!$A$22:$A$27,0),23),0)) | AA12: =IF(OR($B12="",$B12="Land",$C12=""),"",IFERROR($C12*INDEX(Settings!$C$22:$AC$27,MATCH($B12,Settings!$A$22:$A$27,0),24),0)) | AB12: =IF(OR($B12="",$B12="Land",$C12=""),"",IFERROR($C12*INDEX(Settings!$C$22:$AC$27,MATCH($B12,Settings!$A$22:$A$27,0),25),0)) | AC12: =IF(OR($B12="",$B12="Land",$C12=""),"",IFERROR($C12*INDEX(Settings!$C$22:$AC$27,MATCH($B12,Settings!$A$22:$A$27,0),26),0)) | AD12: =IF(OR($B12="",$B12="Land",$C12=""),"",IFERROR($C12*INDEX(Settings!$C$22:$AC$27,MATCH($B12,Settings!$A$22:$A$27,0),27),0))
A13: ='Asset Register'!A13 | B13: ='Asset Register'!E13 | C13: ='Asset Register'!J13 | D13: =IF(OR($B13="",$B13="Land",$C13=""),"",IFERROR($C13*INDEX(Settings!$C$22:$AC$27,MATCH($B13,Settings!$A$22:$A$27,0),1),0)) | E13: =IF(OR($B13="",$B13="Land",$C13=""),"",IFERROR($C13*INDEX(Settings!$C$22:$AC$27,MATCH($B13,Settings!$A$22:$A$27,0),2),0)) | F13: =IF(OR($B13="",$B13="Land",$C13=""),"",IFERROR($C13*INDEX(Settings!$C$22:$AC$27,MATCH($B13,Settings!$A$22:$A$27,0),3),0)) | G13: =IF(OR($B13="",$B13="Land",$C13=""),"",IFERROR($C13*INDEX(Settings!$C$22:$AC$27,MATCH($B13,Settings!$A$22:$A$27,0),4),0)) | H13: =IF(OR($B13="",$B13="Land",$C13=""),"",IFERROR($C13*INDEX(Settings!$C$22:$AC$27,MATCH($B13,Settings!$A$22:$A$27,0),5),0)) | I13: =IF(OR($B13="",$B13="Land",$C13=""),"",IFERROR($C13*INDEX(Settings!$C$22:$AC$27,MATCH($B13,Settings!$A$22:$A$27,0),6),0)) | J13: =IF(OR($B13="",$B13="Land",$C13=""),"",IFERROR($C13*INDEX(Settings!$C$22:$AC$27,MATCH($B13,Settings!$A$22:$A$27,0),7),0)) | K13: =IF(OR($B13="",$B13="Land",$C13=""),"",IFERROR($C13*INDEX(Settings!$C$22:$AC$27,MATCH($B13,Settings!$A$22:$A$27,0),8),0)) | L13: =IF(OR($B13="",$B13="Land",$C13=""),"",IFERROR($C13*INDEX(Settings!$C$22:$AC$27,MATCH($B13,Settings!$A$22:$A$27,0),9),0)) | M13: =IF(OR($B13="",$B13="Land",$C13=""),"",IFERROR($C13*INDEX(Settings!$C$22:$AC$27,MATCH($B13,Settings!$A$22:$A$27,0),10),0)) | N13: =IF(OR($B13="",$B13="Land",$C13=""),"",IFERROR($C13*INDEX(Settings!$C$22:$AC$27,MATCH($B13,Settings!$A$22:$A$27,0),11),0)) | O13: =IF(OR($B13="",$B13="Land",$C13=""),"",IFERROR($C13*INDEX(Settings!$C$22:$AC$27,MATCH($B13,Settings!$A$22:$A$27,0),12),0)) | P13: =IF(OR($B13="",$B13="Land",$C13=""),"",IFERROR($C13*INDEX(Settings!$C$22:$AC$27,MATCH($B13,Settings!$A$22:$A$27,0),13),0)) | Q13: =IF(OR($B13="",$B13="Land",$C13=""),"",IFERROR($C13*INDEX(Settings!$C$22:$AC$27,MATCH($B13,Settings!$A$22:$A$27,0),14),0)) | R13: =IF(OR($B13="",$B13="Land",$C13=""),"",IFERROR($C13*INDEX(Settings!$C$22:$AC$27,MATCH($B13,Settings!$A$22:$A$27,0),15),0)) | S13: =IF(OR($B13="",$B13="Land",$C13=""),"",IFERROR($C13*INDEX(Settings!$C$22:$AC$27,MATCH($B13,Settings!$A$22:$A$27,0),16),0)) | T13: =IF(OR($B13="",$B13="Land",$C13=""),"",IFERROR($C13*INDEX(Settings!$C$22:$AC$27,MATCH($B13,Settings!$A$22:$A$27,0),17),0)) | U13: =IF(OR($B13="",$B13="Land",$C13=""),"",IFERROR($C13*INDEX(Settings!$C$22:$AC$27,MATCH($B13,Settings!$A$22:$A$27,0),18),0)) | V13: =IF(OR($B13="",$B13="Land",$C13=""),"",IFERROR($C13*INDEX(Settings!$C$22:$AC$27,MATCH($B13,Settings!$A$22:$A$27,0),19),0)) | W13: =IF(OR($B13="",$B13="Land",$C13=""),"",IFERROR($C13*INDEX(Settings!$C$22:$AC$27,MATCH($B13,Settings!$A$22:$A$27,0),20),0)) | X13: =IF(OR($B13="",$B13="Land",$C13=""),"",IFERROR($C13*INDEX(Settings!$C$22:$AC$27,MATCH($B13,Settings!$A$22:$A$27,0),21),0)) | Y13: =IF(OR($B13="",$B13="Land",$C13=""),"",IFERROR($C13*INDEX(Settings!$C$22:$AC$27,MATCH($B13,Settings!$A$22:$A$27,0),22),0)) | Z13: =IF(OR($B13="",$B13="Land",$C13=""),"",IFERROR($C13*INDEX(Settings!$C$22:$AC$27,MATCH($B13,Settings!$A$22:$A$27,0),23),0)) | AA13: =IF(OR($B13="",$B13="Land",$C13=""),"",IFERROR($C13*INDEX(Settings!$C$22:$AC$27,MATCH($B13,Settings!$A$22:$A$27,0),24),0)) | AB13: =IF(OR($B13="",$B13="Land",$C13=""),"",IFERROR($C13*INDEX(Settings!$C$22:$AC$27,MATCH($B13,Settings!$A$22:$A$27,0),25),0)) | AC13: =IF(OR($B13="",$B13="Land",$C13=""),"",IFERROR($C13*INDEX(Settings!$C$22:$AC$27,MATCH($B13,Settings!$A$22:$A$27,0),26),0)) | AD13: =IF(OR($B13="",$B13="Land",$C13=""),"",IFERROR($C13*INDEX(Settings!$C$22:$AC$27,MATCH($B13,Settings!$A$22:$A$27,0),27),0))
A14: ='Asset Register'!A14 | B14: ='Asset Register'!E14 | C14: ='Asset Register'!J14 | D14: =IF(OR($B14="",$B14="Land",$C14=""),"",IFERROR($C14*INDEX(Settings!$C$22:$AC$27,MATCH($B14,Settings!$A$22:$A$27,0),1),0)) | E14: =IF(OR($B14="",$B14="Land",$C14=""),"",IFERROR($C14*INDEX(Settings!$C$22:$AC$27,MATCH($B14,Settings!$A$22:$A$27,0),2),0)) | F14: =IF(OR($B14="",$B14="Land",$C14=""),"",IFERROR($C14*INDEX(Settings!$C$22:$AC$27,MATCH($B14,Settings!$A$22:$A$27,0),3),0)) | G14: =IF(OR($B14="",$B14="Land",$C14=""),"",IFERROR($C14*INDEX(Settings!$C$22:$AC$27,MATCH($B14,Settings!$A$22:$A$27,0),4),0)) | H14: =IF(OR($B14="",$B14="Land",$C14=""),"",IFERROR($C14*INDEX(Settings!$C$22:$AC$27,MATCH($B14,Settings!$A$22:$A$27,0),5),0)) | I14: =IF(OR($B14="",$B14="Land",$C14=""),"",IFERROR($C14*INDEX(Settings!$C$22:$AC$27,MATCH($B14,Settings!$A$22:$A$27,0),6),0)) | J14: =IF(OR($B14="",$B14="Land",$C14=""),"",IFERROR($C14*INDEX(Settings!$C$22:$AC$27,MATCH($B14,Settings!$A$22:$A$27,0),7),0)) | K14: =IF(OR($B14="",$B14="Land",$C14=""),"",IFERROR($C14*INDEX(Settings!$C$22:$AC$27,MATCH($B14,Settings!$A$22:$A$27,0),8),0)) | L14: =IF(OR($B14="",$B14="Land",$C14=""),"",IFERROR($C14*INDEX(Settings!$C$22:$AC$27,MATCH($B14,Settings!$A$22:$A$27,0),9),0)) | M14: =IF(OR($B14="",$B14="Land",$C14=""),"",IFERROR($C14*INDEX(Settings!$C$22:$AC$27,MATCH($B14,Settings!$A$22:$A$27,0),10),0)) | N14: =IF(OR($B14="",$B14="Land",$C14=""),"",IFERROR($C14*INDEX(Settings!$C$22:$AC$27,MATCH($B14,Settings!$A$22:$A$27,0),11),0)) | O14: =IF(OR($B14="",$B14="Land",$C14=""),"",IFERROR($C14*INDEX(Settings!$C$22:$AC$27,MATCH($B14,Settings!$A$22:$A$27,0),12),0)) | P14: =IF(OR($B14="",$B14="Land",$C14=""),"",IFERROR($C14*INDEX(Settings!$C$22:$AC$27,MATCH($B14,Settings!$A$22:$A$27,0),13),0)) | Q14: =IF(OR($B14="",$B14="Land",$C14=""),"",IFERROR($C14*INDEX(Settings!$C$22:$AC$27,MATCH($B14,Settings!$A$22:$A$27,0),14),0)) | R14: =IF(OR($B14="",$B14="Land",$C14=""),"",IFERROR($C14*INDEX(Settings!$C$22:$AC$27,MATCH($B14,Settings!$A$22:$A$27,0),15),0)) | S14: =IF(OR($B14="",$B14="Land",$C14=""),"",IFERROR($C14*INDEX(Settings!$C$22:$AC$27,MATCH($B14,Settings!$A$22:$A$27,0),16),0)) | T14: =IF(OR($B14="",$B14="Land",$C14=""),"",IFERROR($C14*INDEX(Settings!$C$22:$AC$27,MATCH($B14,Settings!$A$22:$A$27,0),17),0)) | U14: =IF(OR($B14="",$B14="Land",$C14=""),"",IFERROR($C14*INDEX(Settings!$C$22:$AC$27,MATCH($B14,Settings!$A$22:$A$27,0),18),0)) | V14: =IF(OR($B14="",$B14="Land",$C14=""),"",IFERROR($C14*INDEX(Settings!$C$22:$AC$27,MATCH($B14,Settings!$A$22:$A$27,0),19),0)) | W14: =IF(OR($B14="",$B14="Land",$C14=""),"",IFERROR($C14*INDEX(Settings!$C$22:$AC$27,MATCH($B14,Settings!$A$22:$A$27,0),20),0)) | X14: =IF(OR($B14="",$B14="Land",$C14=""),"",IFERROR($C14*INDEX(Settings!$C$22:$AC$27,MATCH($B14,Settings!$A$22:$A$27,0),21),0)) | Y14: =IF(OR($B14="",$B14="Land",$C14=""),"",IFERROR($C14*INDEX(Settings!$C$22:$AC$27,MATCH($B14,Settings!$A$22:$A$27,0),22),0)) | Z14: =IF(OR($B14="",$B14="Land",$C14=""),"",IFERROR($C14*INDEX(Settings!$C$22:$AC$27,MATCH($B14,Settings!$A$22:$A$27,0),23),0)) | AA14: =IF(OR($B14="",$B14="Land",$C14=""),"",IFERROR($C14*INDEX(Settings!$C$22:$AC$27,MATCH($B14,Settings!$A$22:$A$27,0),24),0)) | AB14: =IF(OR($B14="",$B14="Land",$C14=""),"",IFERROR($C14*INDEX(Settings!$C$22:$AC$27,MATCH($B14,Settings!$A$22:$A$27,0),25),0)) | AC14: =IF(OR($B14="",$B14="Land",$C14=""),"",IFERROR($C14*INDEX(Settings!$C$22:$AC$27,MATCH($B14,Settings!$A$22:$A$27,0),26),0)) | AD14: =IF(OR($B14="",$B14="Land",$C14=""),"",IFERROR($C14*INDEX(Settings!$C$22:$AC$27,MATCH($B14,Settings!$A$22:$A$27,0),27),0))
A15: ='Asset Register'!A15 | B15: ='Asset Register'!E15 | C15: ='Asset Register'!J15 | D15: =IF(OR($B15="",$B15="Land",$C15=""),"",IFERROR($C15*INDEX(Settings!$C$22:$AC$27,MATCH($B15,Settings!$A$22:$A$27,0),1),0)) | E15: =IF(OR($B15="",$B15="Land",$C15=""),"",IFERROR($C15*INDEX(Settings!$C$22:$AC$27,MATCH($B15,Settings!$A$22:$A$27,0),2),0)) | F15: =IF(OR($B15="",$B15="Land",$C15=""),"",IFERROR($C15*INDEX(Settings!$C$22:$AC$27,MATCH($B15,Settings!$A$22:$A$27,0),3),0)) | G15: =IF(OR($B15="",$B15="Land",$C15=""),"",IFERROR($C15*INDEX(Settings!$C$22:$AC$27,MATCH($B15,Settings!$A$22:$A$27,0),4),0)) | H15: =IF(OR($B15="",$B15="Land",$C15=""),"",IFERROR($C15*INDEX(Settings!$C$22:$AC$27,MATCH($B15,Settings!$A$22:$A$27,0),5),0)) | I15: =IF(OR($B15="",$B15="Land",$C15=""),"",IFERROR($C15*INDEX(Settings!$C$22:$AC$27,MATCH($B15,Settings!$A$22:$A$27,0),6),0)) | J15: =IF(OR($B15="",$B15="Land",$C15=""),"",IFERROR($C15*INDEX(Settings!$C$22:$AC$27,MATCH($B15,Settings!$A$22:$A$27,0),7),0)) | K15: =IF(OR($B15="",$B15="Land",$C15=""),"",IFERROR($C15*INDEX(Settings!$C$22:$AC$27,MATCH($B15,Settings!$A$22:$A$27,0),8),0)) | L15: =IF(OR($B15="",$B15="Land",$C15=""),"",IFERROR($C15*INDEX(Settings!$C$22:$AC$27,MATCH($B15,Settings!$A$22:$A$27,0),9),0)) | M15: =IF(OR($B15="",$B15="Land",$C15=""),"",IFERROR($C15*INDEX(Settings!$C$22:$AC$27,MATCH($B15,Settings!$A$22:$A$27,0),10),0)) | N15: =IF(OR($B15="",$B15="Land",$C15=""),"",IFERROR($C15*INDEX(Settings!$C$22:$AC$27,MATCH($B15,Settings!$A$22:$A$27,0),11),0)) | O15: =IF(OR($B15="",$B15="Land",$C15=""),"",IFERROR($C15*INDEX(Settings!$C$22:$AC$27,MATCH($B15,Settings!$A$22:$A$27,0),12),0)) | P15: =IF(OR($B15="",$B15="Land",$C15=""),"",IFERROR($C15*INDEX(Settings!$C$22:$AC$27,MATCH($B15,Settings!$A$22:$A$27,0),13),0)) | Q15: =IF(OR($B15="",$B15="Land",$C15=""),"",IFERROR($C15*INDEX(Settings!$C$22:$AC$27,MATCH($B15,Settings!$A$22:$A$27,0),14),0)) | R15: =IF(OR($B15="",$B15="Land",$C15=""),"",IFERROR($C15*INDEX(Settings!$C$22:$AC$27,MATCH($B15,Settings!$A$22:$A$27,0),15),0)) | S15: =IF(OR($B15="",$B15="Land",$C15=""),"",IFERROR($C15*INDEX(Settings!$C$22:$AC$27,MATCH($B15,Settings!$A$22:$A$27,0),16),0)) | T15: =IF(OR($B15="",$B15="Land",$C15=""),"",IFERROR($C15*INDEX(Settings!$C$22:$AC$27,MATCH($B15,Settings!$A$22:$A$27,0),17),0)) | U15: =IF(OR($B15="",$B15="Land",$C15=""),"",IFERROR($C15*INDEX(Settings!$C$22:$AC$27,MATCH($B15,Settings!$A$22:$A$27,0),18),0)) | V15: =IF(OR($B15="",$B15="Land",$C15=""),"",IFERROR($C15*INDEX(Settings!$C$22:$AC$27,MATCH($B15,Settings!$A$22:$A$27,0),19),0)) | W15: =IF(OR($B15="",$B15="Land",$C15=""),"",IFERROR($C15*INDEX(Settings!$C$22:$AC$27,MATCH($B15,Settings!$A$22:$A$27,0),20),0)) | X15: =IF(OR($B15="",$B15="Land",$C15=""),"",IFERROR($C15*INDEX(Settings!$C$22:$AC$27,MATCH($B15,Settings!$A$22:$A$27,0),21),0)) | Y15: =IF(OR($B15="",$B15="Land",$C15=""),"",IFERROR($C15*INDEX(Settings!$C$22:$AC$27,MATCH($B15,Settings!$A$22:$A$27,0),22),0)) | Z15: =IF(OR($B15="",$B15="Land",$C15=""),"",IFERROR($C15*INDEX(Settings!$C$22:$AC$27,MATCH($B15,Settings!$A$22:$A$27,0),23),0)) | AA15: =IF(OR($B15="",$B15="Land",$C15=""),"",IFERROR($C15*INDEX(Settings!$C$22:$AC$27,MATCH($B15,Settings!$A$22:$A$27,0),24),0)) | AB15: =IF(OR($B15="",$B15="Land",$C15=""),"",IFERROR($C15*INDEX(Settings!$C$22:$AC$27,MATCH($B15,Settings!$A$22:$A$27,0),25),0)) | AC15: =IF(OR($B15="",$B15="Land",$C15=""),"",IFERROR($C15*INDEX(Settings!$C$22:$AC$27,MATCH($B15,Settings!$A$22:$A$27,0),26),0)) | AD15: =IF(OR($B15="",$B15="Land",$C15=""),"",IFERROR($C15*INDEX(Settings!$C$22:$AC$27,MATCH($B15,Settings!$A$22:$A$27,0),27),0))
A16: ='Asset Register'!A16 | B16: ='Asset Register'!E16 | C16: ='Asset Register'!J16 | D16: =IF(OR($B16="",$B16="Land",$C16=""),"",IFERROR($C16*INDEX(Settings!$C$22:$AC$27,MATCH($B16,Settings!$A$22:$A$27,0),1),0)) | E16: =IF(OR($B16="",$B16="Land",$C16=""),"",IFERROR($C16*INDEX(Settings!$C$22:$AC$27,MATCH($B16,Settings!$A$22:$A$27,0),2),0)) | F16: =IF(OR($B16="",$B16="Land",$C16=""),"",IFERROR($C16*INDEX(Settings!$C$22:$AC$27,MATCH($B16,Settings!$A$22:$A$27,0),3),0)) | G16: =IF(OR($B16="",$B16="Land",$C16=""),"",IFERROR($C16*INDEX(Settings!$C$22:$AC$27,MATCH($B16,Settings!$A$22:$A$27,0),4),0)) | H16: =IF(OR($B16="",$B16="Land",$C16=""),"",IFERROR($C16*INDEX(Settings!$C$22:$AC$27,MATCH($B16,Settings!$A$22:$A$27,0),5),0)) | I16: =IF(OR($B16="",$B16="Land",$C16=""),"",IFERROR($C16*INDEX(Settings!$C$22:$AC$27,MATCH($B16,Settings!$A$22:$A$27,0),6),0)) | J16: =IF(OR($B16="",$B16="Land",$C16=""),"",IFERROR($C16*INDEX(Settings!$C$22:$AC$27,MATCH($B16,Settings!$A$22:$A$27,0),7),0)) | K16: =IF(OR($B16="",$B16="Land",$C16=""),"",IFERROR($C16*INDEX(Settings!$C$22:$AC$27,MATCH($B16,Settings!$A$22:$A$27,0),8),0)) | L16: =IF(OR($B16="",$B16="Land",$C16=""),"",IFERROR($C16*INDEX(Settings!$C$22:$AC$27,MATCH($B16,Settings!$A$22:$A$27,0),9),0)) | M16: =IF(OR($B16="",$B16="Land",$C16=""),"",IFERROR($C16*INDEX(Settings!$C$22:$AC$27,MATCH($B16,Settings!$A$22:$A$27,0),10),0)) | N16: =IF(OR($B16="",$B16="Land",$C16=""),"",IFERROR($C16*INDEX(Settings!$C$22:$AC$27,MATCH($B16,Settings!$A$22:$A$27,0),11),0)) | O16: =IF(OR($B16="",$B16="Land",$C16=""),"",IFERROR($C16*INDEX(Settings!$C$22:$AC$27,MATCH($B16,Settings!$A$22:$A$27,0),12),0)) | P16: =IF(OR($B16="",$B16="Land",$C16=""),"",IFERROR($C16*INDEX(Settings!$C$22:$AC$27,MATCH($B16,Settings!$A$22:$A$27,0),13),0)) | Q16: =IF(OR($B16="",$B16="Land",$C16=""),"",IFERROR($C16*INDEX(Settings!$C$22:$AC$27,MATCH($B16,Settings!$A$22:$A$27,0),14),0)) | R16: =IF(OR($B16="",$B16="Land",$C16=""),"",IFERROR($C16*INDEX(Settings!$C$22:$AC$27,MATCH($B16,Settings!$A$22:$A$27,0),15),0)) | S16: =IF(OR($B16="",$B16="Land",$C16=""),"",IFERROR($C16*INDEX(Settings!$C$22:$AC$27,MATCH($B16,Settings!$A$22:$A$27,0),16),0)) | T16: =IF(OR($B16="",$B16="Land",$C16=""),"",IFERROR($C16*INDEX(Settings!$C$22:$AC$27,MATCH($B16,Settings!$A$22:$A$27,0),17),0)) | U16: =IF(OR($B16="",$B16="Land",$C16=""),"",IFERROR($C16*INDEX(Settings!$C$22:$AC$27,MATCH($B16,Settings!$A$22:$A$27,0),18),0)) | V16: =IF(OR($B16="",$B16="Land",$C16=""),"",IFERROR($C16*INDEX(Settings!$C$22:$AC$27,MATCH($B16,Settings!$A$22:$A$27,0),19),0)) | W16: =IF(OR($B16="",$B16="Land",$C16=""),"",IFERROR($C16*INDEX(Settings!$C$22:$AC$27,MATCH($B16,Settings!$A$22:$A$27,0),20),0)) | X16: =IF(OR($B16="",$B16="Land",$C16=""),"",IFERROR($C16*INDEX(Settings!$C$22:$AC$27,MATCH($B16,Settings!$A$22:$A$27,0),21),0)) | Y16: =IF(OR($B16="",$B16="Land",$C16=""),"",IFERROR($C16*INDEX(Settings!$C$22:$AC$27,MATCH($B16,Settings!$A$22:$A$27,0),22),0)) | Z16: =IF(OR($B16="",$B16="Land",$C16=""),"",IFERROR($C16*INDEX(Settings!$C$22:$AC$27,MATCH($B16,Settings!$A$22:$A$27,0),23),0)) | AA16: =IF(OR($B16="",$B16="Land",$C16=""),"",IFERROR($C16*INDEX(Settings!$C$22:$AC$27,MATCH($B16,Settings!$A$22:$A$27,0),24),0)) | AB16: =IF(OR($B16="",$B16="Land",$C16=""),"",IFERROR($C16*INDEX(Settings!$C$22:$AC$27,MATCH($B16,Settings!$A$22:$A$27,0),25),0)) | AC16: =IF(OR($B16="",$B16="Land",$C16=""),"",IFERROR($C16*INDEX(Settings!$C$22:$AC$27,MATCH($B16,Settings!$A$22:$A$27,0),26),0)) | AD16: =IF(OR($B16="",$B16="Land",$C16=""),"",IFERROR($C16*INDEX(Settings!$C$22:$AC$27,MATCH($B16,Settings!$A$22:$A$27,0),27),0))
A17: ='Asset Register'!A17 | B17: ='Asset Register'!E17 | C17: ='Asset Register'!J17 | D17: =IF(OR($B17="",$B17="Land",$C17=""),"",IFERROR($C17*INDEX(Settings!$C$22:$AC$27,MATCH($B17,Settings!$A$22:$A$27,0),1),0)) | E17: =IF(OR($B17="",$B17="Land",$C17=""),"",IFERROR($C17*INDEX(Settings!$C$22:$AC$27,MATCH($B17,Settings!$A$22:$A$27,0),2),0)) | F17: =IF(OR($B17="",$B17="Land",$C17=""),"",IFERROR($C17*INDEX(Settings!$C$22:$AC$27,MATCH($B17,Settings!$A$22:$A$27,0),3),0)) | G17: =IF(OR($B17="",$B17="Land",$C17=""),"",IFERROR($C17*INDEX(Settings!$C$22:$AC$27,MATCH($B17,Settings!$A$22:$A$27,0),4),0)) | H17: =IF(OR($B17="",$B17="Land",$C17=""),"",IFERROR($C17*INDEX(Settings!$C$22:$AC$27,MATCH($B17,Settings!$A$22:$A$27,0),5),0)) | I17: =IF(OR($B17="",$B17="Land",$C17=""),"",IFERROR($C17*INDEX(Settings!$C$22:$AC$27,MATCH($B17,Settings!$A$22:$A$27,0),6),0)) | J17: =IF(OR($B17="",$B17="Land",$C17=""),"",IFERROR($C17*INDEX(Settings!$C$22:$AC$27,MATCH($B17,Settings!$A$22:$A$27,0),7),0)) | K17: =IF(OR($B17="",$B17="Land",$C17=""),"",IFERROR($C17*INDEX(Settings!$C$22:$AC$27,MATCH($B17,Settings!$A$22:$A$27,0),8),0)) | L17: =IF(OR($B17="",$B17="Land",$C17=""),"",IFERROR($C17*INDEX(Settings!$C$22:$AC$27,MATCH($B17,Settings!$A$22:$A$27,0),9),0)) | M17: =IF(OR($B17="",$B17="Land",$C17=""),"",IFERROR($C17*INDEX(Settings!$C$22:$AC$27,MATCH($B17,Settings!$A$22:$A$27,0),10),0)) | N17: =IF(OR($B17="",$B17="Land",$C17=""),"",IFERROR($C17*INDEX(Settings!$C$22:$AC$27,MATCH($B17,Settings!$A$22:$A$27,0),11),0)) | O17: =IF(OR($B17="",$B17="Land",$C17=""),"",IFERROR($C17*INDEX(Settings!$C$22:$AC$27,MATCH($B17,Settings!$A$22:$A$27,0),12),0)) | P17: =IF(OR($B17="",$B17="Land",$C17=""),"",IFERROR($C17*INDEX(Settings!$C$22:$AC$27,MATCH($B17,Settings!$A$22:$A$27,0),13),0)) | Q17: =IF(OR($B17="",$B17="Land",$C17=""),"",IFERROR($C17*INDEX(Settings!$C$22:$AC$27,MATCH($B17,Settings!$A$22:$A$27,0),14),0)) | R17: =IF(OR($B17="",$B17="Land",$C17=""),"",IFERROR($C17*INDEX(Settings!$C$22:$AC$27,MATCH($B17,Settings!$A$22:$A$27,0),15),0)) | S17: =IF(OR($B17="",$B17="Land",$C17=""),"",IFERROR($C17*INDEX(Settings!$C$22:$AC$27,MATCH($B17,Settings!$A$22:$A$27,0),16),0)) | T17: =IF(OR($B17="",$B17="Land",$C17=""),"",IFERROR($C17*INDEX(Settings!$C$22:$AC$27,MATCH($B17,Settings!$A$22:$A$27,0),17),0)) | U17: =IF(OR($B17="",$B17="Land",$C17=""),"",IFERROR($C17*INDEX(Settings!$C$22:$AC$27,MATCH($B17,Settings!$A$22:$A$27,0),18),0)) | V17: =IF(OR($B17="",$B17="Land",$C17=""),"",IFERROR($C17*INDEX(Settings!$C$22:$AC$27,MATCH($B17,Settings!$A$22:$A$27,0),19),0)) | W17: =IF(OR($B17="",$B17="Land",$C17=""),"",IFERROR($C17*INDEX(Settings!$C$22:$AC$27,MATCH($B17,Settings!$A$22:$A$27,0),20),0)) | X17: =IF(OR($B17="",$B17="Land",$C17=""),"",IFERROR($C17*INDEX(Settings!$C$22:$AC$27,MATCH($B17,Settings!$A$22:$A$27,0),21),0)) | Y17: =IF(OR($B17="",$B17="Land",$C17=""),"",IFERROR($C17*INDEX(Settings!$C$22:$AC$27,MATCH($B17,Settings!$A$22:$A$27,0),22),0)) | Z17: =IF(OR($B17="",$B17="Land",$C17=""),"",IFERROR($C17*INDEX(Settings!$C$22:$AC$27,MATCH($B17,Settings!$A$22:$A$27,0),23),0)) | AA17: =IF(OR($B17="",$B17="Land",$C17=""),"",IFERROR($C17*INDEX(Settings!$C$22:$AC$27,MATCH($B17,Settings!$A$22:$A$27,0),24),0)) | AB17: =IF(OR($B17="",$B17="Land",$C17=""),"",IFERROR($C17*INDEX(Settings!$C$22:$AC$27,MATCH($B17,Settings!$A$22:$A$27,0),25),0)) | AC17: =IF(OR($B17="",$B17="Land",$C17=""),"",IFERROR($C17*INDEX(Settings!$C$22:$AC$27,MATCH($B17,Settings!$A$22:$A$27,0),26),0)) | AD17: =IF(OR($B17="",$B17="Land",$C17=""),"",IFERROR($C17*INDEX(Settings!$C$22:$AC$27,MATCH($B17,Settings!$A$22:$A$27,0),27),0))
A18: ='Asset Register'!A18 | B18: ='Asset Register'!E18 | C18: ='Asset Register'!J18 | D18: =IF(OR($B18="",$B18="Land",$C18=""),"",IFERROR($C18*INDEX(Settings!$C$22:$AC$27,MATCH($B18,Settings!$A$22:$A$27,0),1),0)) | E18: =IF(OR($B18="",$B18="Land",$C18=""),"",IFERROR($C18*INDEX(Settings!$C$22:$AC$27,MATCH($B18,Settings!$A$22:$A$27,0),2),0)) | F18: =IF(OR($B18="",$B18="Land",$C18=""),"",IFERROR($C18*INDEX(Settings!$C$22:$AC$27,MATCH($B18,Settings!$A$22:$A$27,0),3),0)) | G18: =IF(OR($B18="",$B18="Land",$C18=""),"",IFERROR($C18*INDEX(Settings!$C$22:$AC$27,MATCH($B18,Settings!$A$22:$A$27,0),4),0)) | H18: =IF(OR($B18="",$B18="Land",$C18=""),"",IFERROR($C18*INDEX(Settings!$C$22:$AC$27,MATCH($B18,Settings!$A$22:$A$27,0),5),0)) | I18: =IF(OR($B18="",$B18="Land",$C18=""),"",IFERROR($C18*INDEX(Settings!$C$22:$AC$27,MATCH($B18,Settings!$A$22:$A$27,0),6),0)) | J18: =IF(OR($B18="",$B18="Land",$C18=""),"",IFERROR($C18*INDEX(Settings!$C$22:$AC$27,MATCH($B18,Settings!$A$22:$A$27,0),7),0)) | K18: =IF(OR($B18="",$B18="Land",$C18=""),"",IFERROR($C18*INDEX(Settings!$C$22:$AC$27,MATCH($B18,Settings!$A$22:$A$27,0),8),0)) | L18: =IF(OR($B18="",$B18="Land",$C18=""),"",IFERROR($C18*INDEX(Settings!$C$22:$AC$27,MATCH($B18,Settings!$A$22:$A$27,0),9),0)) | M18: =IF(OR($B18="",$B18="Land",$C18=""),"",IFERROR($C18*INDEX(Settings!$C$22:$AC$27,MATCH($B18,Settings!$A$22:$A$27,0),10),0)) | N18: =IF(OR($B18="",$B18="Land",$C18=""),"",IFERROR($C18*INDEX(Settings!$C$22:$AC$27,MATCH($B18,Settings!$A$22:$A$27,0),11),0)) | O18: =IF(OR($B18="",$B18="Land",$C18=""),"",IFERROR($C18*INDEX(Settings!$C$22:$AC$27,MATCH($B18,Settings!$A$22:$A$27,0),12),0)) | P18: =IF(OR($B18="",$B18="Land",$C18=""),"",IFERROR($C18*INDEX(Settings!$C$22:$AC$27,MATCH($B18,Settings!$A$22:$A$27,0),13),0)) | Q18: =IF(OR($B18="",$B18="Land",$C18=""),"",IFERROR($C18*INDEX(Settings!$C$22:$AC$27,MATCH($B18,Settings!$A$22:$A$27,0),14),0)) | R18: =IF(OR($B18="",$B18="Land",$C18=""),"",IFERROR($C18*INDEX(Settings!$C$22:$AC$27,MATCH($B18,Settings!$A$22:$A$27,0),15),0)) | S18: =IF(OR($B18="",$B18="Land",$C18=""),"",IFERROR($C18*INDEX(Settings!$C$22:$AC$27,MATCH($B18,Settings!$A$22:$A$27,0),16),0)) | T18: =IF(OR($B18="",$B18="Land",$C18=""),"",IFERROR($C18*INDEX(Settings!$C$22:$AC$27,MATCH($B18,Settings!$A$22:$A$27,0),17),0)) | U18: =IF(OR($B18="",$B18="Land",$C18=""),"",IFERROR($C18*INDEX(Settings!$C$22:$AC$27,MATCH($B18,Settings!$A$22:$A$27,0),18),0)) | V18: =IF(OR($B18="",$B18="Land",$C18=""),"",IFERROR($C18*INDEX(Settings!$C$22:$AC$27,MATCH($B18,Settings!$A$22:$A$27,0),19),0)) | W18: =IF(OR($B18="",$B18="Land",$C18=""),"",IFERROR($C18*INDEX(Settings!$C$22:$AC$27,MATCH($B18,Settings!$A$22:$A$27,0),20),0)) | X18: =IF(OR($B18="",$B18="Land",$C18=""),"",IFERROR($C18*INDEX(Settings!$C$22:$AC$27,MATCH($B18,Settings!$A$22:$A$27,0),21),0)) | Y18: =IF(OR($B18="",$B18="Land",$C18=""),"",IFERROR($C18*INDEX(Settings!$C$22:$AC$27,MATCH($B18,Settings!$A$22:$A$27,0),22),0)) | Z18: =IF(OR($B18="",$B18="Land",$C18=""),"",IFERROR($C18*INDEX(Settings!$C$22:$AC$27,MATCH($B18,Settings!$A$22:$A$27,0),23),0)) | AA18: =IF(OR($B18="",$B18="Land",$C18=""),"",IFERROR($C18*INDEX(Settings!$C$22:$AC$27,MATCH($B18,Settings!$A$22:$A$27,0),24),0)) | AB18: =IF(OR($B18="",$B18="Land",$C18=""),"",IFERROR($C18*INDEX(Settings!$C$22:$AC$27,MATCH($B18,Settings!$A$22:$A$27,0),25),0)) | AC18: =IF(OR($B18="",$B18="Land",$C18=""),"",IFERROR($C18*INDEX(Settings!$C$22:$AC$27,MATCH($B18,Settings!$A$22:$A$27,0),26),0)) | AD18: =IF(OR($B18="",$B18="Land",$C18=""),"",IFERROR($C18*INDEX(Settings!$C$22:$AC$27,MATCH($B18,Settings!$A$22:$A$27,0),27),0))
A19: ='Asset Register'!A19 | B19: ='Asset Register'!E19 | C19: ='Asset Register'!J19 | D19: =IF(OR($B19="",$B19="Land",$C19=""),"",IFERROR($C19*INDEX(Settings!$C$22:$AC$27,MATCH($B19,Settings!$A$22:$A$27,0),1),0)) | E19: =IF(OR($B19="",$B19="Land",$C19=""),"",IFERROR($C19*INDEX(Settings!$C$22:$AC$27,MATCH($B19,Settings!$A$22:$A$27,0),2),0)) | F19: =IF(OR($B19="",$B19="Land",$C19=""),"",IFERROR($C19*INDEX(Settings!$C$22:$AC$27,MATCH($B19,Settings!$A$22:$A$27,0),3),0)) | G19: =IF(OR($B19="",$B19="Land",$C19=""),"",IFERROR($C19*INDEX(Settings!$C$22:$AC$27,MATCH($B19,Settings!$A$22:$A$27,0),4),0)) | H19: =IF(OR($B19="",$B19="Land",$C19=""),"",IFERROR($C19*INDEX(Settings!$C$22:$AC$27,MATCH($B19,Settings!$A$22:$A$27,0),5),0)) | I19: =IF(OR($B19="",$B19="Land",$C19=""),"",IFERROR($C19*INDEX(Settings!$C$22:$AC$27,MATCH($B19,Settings!$A$22:$A$27,0),6),0)) | J19: =IF(OR($B19="",$B19="Land",$C19=""),"",IFERROR($C19*INDEX(Settings!$C$22:$AC$27,MATCH($B19,Settings!$A$22:$A$27,0),7),0)) | K19: =IF(OR($B19="",$B19="Land",$C19=""),"",IFERROR($C19*INDEX(Settings!$C$22:$AC$27,MATCH($B19,Settings!$A$22:$A$27,0),8),0)) | L19: =IF(OR($B19="",$B19="Land",$C19=""),"",IFERROR($C19*INDEX(Settings!$C$22:$AC$27,MATCH($B19,Settings!$A$22:$A$27,0),9),0)) | M19: =IF(OR($B19="",$B19="Land",$C19=""),"",IFERROR($C19*INDEX(Settings!$C$22:$AC$27,MATCH($B19,Settings!$A$22:$A$27,0),10),0)) | N19: =IF(OR($B19="",$B19="Land",$C19=""),"",IFERROR($C19*INDEX(Settings!$C$22:$AC$27,MATCH($B19,Settings!$A$22:$A$27,0),11),0)) | O19: =IF(OR($B19="",$B19="Land",$C19=""),"",IFERROR($C19*INDEX(Settings!$C$22:$AC$27,MATCH($B19,Settings!$A$22:$A$27,0),12),0)) | P19: =IF(OR($B19="",$B19="Land",$C19=""),"",IFERROR($C19*INDEX(Settings!$C$22:$AC$27,MATCH($B19,Settings!$A$22:$A$27,0),13),0)) | Q19: =IF(OR($B19="",$B19="Land",$C19=""),"",IFERROR($C19*INDEX(Settings!$C$22:$AC$27,MATCH($B19,Settings!$A$22:$A$27,0),14),0)) | R19: =IF(OR($B19="",$B19="Land",$C19=""),"",IFERROR($C19*INDEX(Settings!$C$22:$AC$27,MATCH($B19,Settings!$A$22:$A$27,0),15),0)) | S19: =IF(OR($B19="",$B19="Land",$C19=""),"",IFERROR($C19*INDEX(Settings!$C$22:$AC$27,MATCH($B19,Settings!$A$22:$A$27,0),16),0)) | T19: =IF(OR($B19="",$B19="Land",$C19=""),"",IFERROR($C19*INDEX(Settings!$C$22:$AC$27,MATCH($B19,Settings!$A$22:$A$27,0),17),0)) | U19: =IF(OR($B19="",$B19="Land",$C19=""),"",IFERROR($C19*INDEX(Settings!$C$22:$AC$27,MATCH($B19,Settings!$A$22:$A$27,0),18),0)) | V19: =IF(OR($B19="",$B19="Land",$C19=""),"",IFERROR($C19*INDEX(Settings!$C$22:$AC$27,MATCH($B19,Settings!$A$22:$A$27,0),19),0)) | W19: =IF(OR($B19="",$B19="Land",$C19=""),"",IFERROR($C19*INDEX(Settings!$C$22:$AC$27,MATCH($B19,Settings!$A$22:$A$27,0),20),0)) | X19: =IF(OR($B19="",$B19="Land",$C19=""),"",IFERROR($C19*INDEX(Settings!$C$22:$AC$27,MATCH($B19,Settings!$A$22:$A$27,0),21),0)) | Y19: =IF(OR($B19="",$B19="Land",$C19=""),"",IFERROR($C19*INDEX(Settings!$C$22:$AC$27,MATCH($B19,Settings!$A$22:$A$27,0),22),0)) | Z19: =IF(OR($B19="",$B19="Land",$C19=""),"",IFERROR($C19*INDEX(Settings!$C$22:$AC$27,MATCH($B19,Settings!$A$22:$A$27,0),23),0)) | AA19: =IF(OR($B19="",$B19="Land",$C19=""),"",IFERROR($C19*INDEX(Settings!$C$22:$AC$27,MATCH($B19,Settings!$A$22:$A$27,0),24),0)) | AB19: =IF(OR($B19="",$B19="Land",$C19=""),"",IFERROR($C19*INDEX(Settings!$C$22:$AC$27,MATCH($B19,Settings!$A$22:$A$27,0),25),0)) | AC19: =IF(OR($B19="",$B19="Land",$C19=""),"",IFERROR($C19*INDEX(Settings!$C$22:$AC$27,MATCH($B19,Settings!$A$22:$A$27,0),26),0)) | AD19: =IF(OR($B19="",$B19="Land",$C19=""),"",IFERROR($C19*INDEX(Settings!$C$22:$AC$27,MATCH($B19,Settings!$A$22:$A$27,0),27),0))
... A107: ='Asset Register'!A107 | B107: ='Asset Register'!E107 | C107: ='Asset Register'!J107 | D107: =IF(OR($B107="",$B107="Land",$C107=""),"",IFERROR($C107*INDEX(Settings!$C$22:$AC$27,MATCH($B107,Settings!$A$22:$A$27,0),1),0)) | E107: =IF(OR($B107="",$B107="Land",$C107=""),"",IFERROR($C107*INDEX(Settings!$C$22:$AC$27,MATCH($B107,Settings!$A$22:$A$27,0),2),0)) | F107: =IF(OR($B107="",$B107="Land",$C107=""),"",IFERROR($C107*INDEX(Settings!$C$22:$AC$27,MATCH($B107,Settings!$A$22:$A$27,0),3),0)) | G107: =IF(OR($B107="",$B107="Land",$C107=""),"",IFERROR($C107*INDEX(Settings!$C$22:$AC$27,MATCH($B107,Settings!$A$22:$A$27,0),4),0)) | H107: =IF(OR($B107="",$B107="Land",$C107=""),"",IFERROR($C107*INDEX(Settings!$C$22:$AC$27,MATCH($B107,Settings!$A$22:$A$27,0),5),0)) | I107: =IF(OR($B107="",$B107="Land",$C107=""),"",IFERROR($C107*INDEX(Settings!$C$22:$AC$27,MATCH($B107,Settings!$A$22:$A$27,0),6),0)) | J107: =IF(OR($B107="",$B107="Land",$C107=""),"",IFERROR($C107*INDEX(Settings!$C$22:$AC$27,MATCH($B107,Settings!$A$22:$A$27,0),7),0)) | K107: =IF(OR($B107="",$B107="Land",$C107=""),"",IFERROR($C107*INDEX(Settings!$C$22:$AC$27,MATCH($B107,Settings!$A$22:$A$27,0),8),0)) | L107: =IF(OR($B107="",$B107="Land",$C107=""),"",IFERROR($C107*INDEX(Settings!$C$22:$AC$27,MATCH($B107,Settings!$A$22:$A$27,0),9),0)) | M107: =IF(OR($B107="",$B107="Land",$C107=""),"",IFERROR($C107*INDEX(Settings!$C$22:$AC$27,MATCH($B107,Settings!$A$22:$A$27,0),10),0)) | N107: =IF(OR($B107="",$B107="Land",$C107=""),"",IFERROR($C107*INDEX(Settings!$C$22:$AC$27,MATCH($B107,Settings!$A$22:$A$27,0),11),0)) | O107: =IF(OR($B107="",$B107="Land",$C107=""),"",IFERROR($C107*INDEX(Settings!$C$22:$AC$27,MATCH($B107,Settings!$A$22:$A$27,0),12),0)) | P107: =IF(OR($B107="",$B107="Land",$C107=""),"",IFERROR($C107*INDEX(Settings!$C$22:$AC$27,MATCH($B107,Settings!$A$22:$A$27,0),13),0)) | Q107: =IF(OR($B107="",$B107="Land",$C107=""),"",IFERROR($C107*INDEX(Settings!$C$22:$AC$27,MATCH($B107,Settings!$A$22:$A$27,0),14),0)) | R107: =IF(OR($B107="",$B107="Land",$C107=""),"",IFERROR($C107*INDEX(Settings!$C$22:$AC$27,MATCH($B107,Settings!$A$22:$A$27,0),15),0)) | S107: =IF(OR($B107="",$B107="Land",$C107=""),"",IFERROR($C107*INDEX(Settings!$C$22:$AC$27,MATCH($B107,Settings!$A$22:$A$27,0),16),0)) | T107: =IF(OR($B107="",$B107="Land",$C107=""),"",IFERROR($C107*INDEX(Settings!$C$22:$AC$27,MATCH($B107,Settings!$A$22:$A$27,0),17),0)) | U107: =IF(OR($B107="",$B107="Land",$C107=""),"",IFERROR($C107*INDEX(Settings!$C$22:$AC$27,MATCH($B107,Settings!$A$22:$A$27,0),18),0)) | V107: =IF(OR($B107="",$B107="Land",$C107=""),"",IFERROR($C107*INDEX(Settings!$C$22:$AC$27,MATCH($B107,Settings!$A$22:$A$27,0),19),0)) | W107: =IF(OR($B107="",$B107="Land",$C107=""),"",IFERROR($C107*INDEX(Settings!$C$22:$AC$27,MATCH($B107,Settings!$A$22:$A$27,0),20),0)) | X107: =IF(OR($B107="",$B107="Land",$C107=""),"",IFERROR($C107*INDEX(Settings!$C$22:$AC$27,MATCH($B107,Settings!$A$22:$A$27,0),21),0)) | Y107: =IF(OR($B107="",$B107="Land",$C107=""),"",IFERROR($C107*INDEX(Settings!$C$22:$AC$27,MATCH($B107,Settings!$A$22:$A$27,0),22),0)) | Z107: =IF(OR($B107="",$B107="Land",$C107=""),"",IFERROR($C107*INDEX(Settings!$C$22:$AC$27,MATCH($B107,Settings!$A$22:$A$27,0),23),0)) | AA107: =IF(OR($B107="",$B107="Land",$C107=""),"",IFERROR($C107*INDEX(Settings!$C$22:$AC$27,MATCH($B107,Settings!$A$22:$A$27,0),24),0)) | AB107: =IF(OR($B107="",$B107="Land",$C107=""),"",IFERROR($C107*INDEX(Settings!$C$22:$AC$27,MATCH($B107,Settings!$A$22:$A$27,0),25),0)) | AC107: =IF(OR($B107="",$B107="Land",$C107=""),"",IFERROR($C107*INDEX(Settings!$C$22:$AC$27,MATCH($B107,Settings!$A$22:$A$27,0),26),0)) | AD107: =IF(OR($B107="",$B107="Land",$C107=""),"",IFERROR($C107*INDEX(Settings!$C$22:$AC$27,MATCH($B107,Settings!$A$22:$A$27,0),27),0))
A108: Portfolio total / year: | D108: =SUM(D8:D107) | E108: =SUM(E8:E107) | F108: =SUM(F8:F107) | G108: =SUM(G8:G107) | H108: =SUM(H8:H107) | I108: =SUM(I8:I107) | J108: =SUM(J8:J107) | K108: =SUM(K8:K107) | ... AD108: =SUM(AD8:AD107)
A110: ⓘ Year columns reflect the IRS half-year (HY) and mid-month (MM) percentage tables loaded in Settings. For mid-quarter (MQ) convention or short tax years, adjust manually — this ledger uses the standard tables.

Sheet Current Year Summary
A2: =HYPERLINK("#'Schedule by Year'!A1", "← BACK") | D2: CURRENT YEAR SUMMARY | J2: =HYPERLINK("#'Form 4562 Worksheet'!A1", "NEXT →")
A4: Current-year deduction per asset. Total flows to Schedule C line 13 (active business) or Schedule E line 18 (passive rental).
A7: Asset | B7: Class | C7: Placed in svc | D7: Original basis | E7: Adj. basis | F7: Current-year deprec. | G7: Accum. through prior yr | H7: Schedule line
A8: ='Asset Register'!A8 | B8: ='Asset Register'!E8 | C8: ='Asset Register'!C8 | D8: ='Asset Register'!D8 | E8: ='Asset Register'!J8 | F8: =IFERROR(IF(IF('Asset Register'!C8="",0,MAX(MIN(Settings!$B$5-YEAR('Asset Register'!C8)+1,27),0))<1,0,IF(AND('Asset Register'!M8<>"",YEAR('Asset Register'!M8)<Settings!$B$5),0,INDEX('Schedule by Year'!$D8:$AD8,1,IF('Asset Register'!C8="",0,MAX(MIN(Settings!$B$5-YEAR('Asset Register'!C8)+1,27),0))))),0) | G8: =IFERROR(IF(IF('Asset Register'!C8="",0,MAX(MIN(Settings!$B$5-YEAR('Asset Register'!C8)+1,27),0))<=1,0,SUM(OFFSET('Schedule by Year'!$D8,0,0,1,IF('Asset Register'!C8="",0,MAX(MIN(Settings!$B$5-YEAR('Asset Register'!C8)+1,27),0))-1))),0) | H8: =IF(Settings!$B$6="Schedule C (active)","Sch C, line 13",IF(Settings!$B$6="Schedule E (passive)","Sch E, line 18","Ask CPA"))
A9: ='Asset Register'!A9 | B9: ='Asset Register'!E9 | C9: ='Asset Register'!C9 | D9: ='Asset Register'!D9 | E9: ='Asset Register'!J9 | F9: =IFERROR(IF(IF('Asset Register'!C9="",0,MAX(MIN(Settings!$B$5-YEAR('Asset Register'!C9)+1,27),0))<1,0,IF(AND('Asset Register'!M9<>"",YEAR('Asset Register'!M9)<Settings!$B$5),0,INDEX('Schedule by Year'!$D9:$AD9,1,IF('Asset Register'!C9="",0,MAX(MIN(Settings!$B$5-YEAR('Asset Register'!C9)+1,27),0))))),0) | G9: =IFERROR(IF(IF('Asset Register'!C9="",0,MAX(MIN(Settings!$B$5-YEAR('Asset Register'!C9)+1,27),0))<=1,0,SUM(OFFSET('Schedule by Year'!$D9,0,0,1,IF('Asset Register'!C9="",0,MAX(MIN(Settings!$B$5-YEAR('Asset Register'!C9)+1,27),0))-1))),0) | H9: =IF(Settings!$B$6="Schedule C (active)","Sch C, line 13",IF(Settings!$B$6="Schedule E (passive)","Sch E, line 18","Ask CPA"))
A10: ='Asset Register'!A10 | B10: ='Asset Register'!E10 | C10: ='Asset Register'!C10 | D10: ='Asset Register'!D10 | E10: ='Asset Register'!J10 | F10: =IFERROR(IF(IF('Asset Register'!C10="",0,MAX(MIN(Settings!$B$5-YEAR('Asset Register'!C10)+1,27),0))<1,0,IF(AND('Asset Register'!M10<>"",YEAR('Asset Register'!M10)<Settings!$B$5),0,INDEX('Schedule by Year'!$D10:$AD10,1,IF('Asset Register'!C10="",0,MAX(MIN(Settings!$B$5-YEAR('Asset Register'!C10)+1,27),0))))),0) | G10: =IFERROR(IF(IF('Asset Register'!C10="",0,MAX(MIN(Settings!$B$5-YEAR('Asset Register'!C10)+1,27),0))<=1,0,SUM(OFFSET('Schedule by Year'!$D10,0,0,1,IF('Asset Register'!C10="",0,MAX(MIN(Settings!$B$5-YEAR('Asset Register'!C10)+1,27),0))-1))),0) | H10: =IF(Settings!$B$6="Schedule C (active)","Sch C, line 13",IF(Settings!$B$6="Schedule E (passive)","Sch E, line 18","Ask CPA"))
A11: ='Asset Register'!A11 | B11: ='Asset Register'!E11 | C11: ='Asset Register'!C11 | D11: ='Asset Register'!D11 | E11: ='Asset Register'!J11 | F11: =IFERROR(IF(IF('Asset Register'!C11="",0,MAX(MIN(Settings!$B$5-YEAR('Asset Register'!C11)+1,27),0))<1,0,IF(AND('Asset Register'!M11<>"",YEAR('Asset Register'!M11)<Settings!$B$5),0,INDEX('Schedule by Year'!$D11:$AD11,1,IF('Asset Register'!C11="",0,MAX(MIN(Settings!$B$5-YEAR('Asset Register'!C11)+1,27),0))))),0) | G11: =IFERROR(IF(IF('Asset Register'!C11="",0,MAX(MIN(Settings!$B$5-YEAR('Asset Register'!C11)+1,27),0))<=1,0,SUM(OFFSET('Schedule by Year'!$D11,0,0,1,IF('Asset Register'!C11="",0,MAX(MIN(Settings!$B$5-YEAR('Asset Register'!C11)+1,27),0))-1))),0) | H11: =IF(Settings!$B$6="Schedule C (active)","Sch C, line 13",IF(Settings!$B$6="Schedule E (passive)","Sch E, line 18","Ask CPA"))
A12: ='Asset Register'!A12 | B12: ='Asset Register'!E12 | C12: ='Asset Register'!C12 | D12: ='Asset Register'!D12 | E12: ='Asset Register'!J12 | F12: =IFERROR(IF(IF('Asset Register'!C12="",0,MAX(MIN(Settings!$B$5-YEAR('Asset Register'!C12)+1,27),0))<1,0,IF(AND('Asset Register'!M12<>"",YEAR('Asset Register'!M12)<Settings!$B$5),0,INDEX('Schedule by Year'!$D12:$AD12,1,IF('Asset Register'!C12="",0,MAX(MIN(Settings!$B$5-YEAR('Asset Register'!C12)+1,27),0))))),0) | G12: =IFERROR(IF(IF('Asset Register'!C12="",0,MAX(MIN(Settings!$B$5-YEAR('Asset Register'!C12)+1,27),0))<=1,0,SUM(OFFSET('Schedule by Year'!$D12,0,0,1,IF('Asset Register'!C12="",0,MAX(MIN(Settings!$B$5-YEAR('Asset Register'!C12)+1,27),0))-1))),0) | H12: =IF(Settings!$B$6="Schedule C (active)","Sch C, line 13",IF(Settings!$B$6="Schedule E (passive)","Sch E, line 18","Ask CPA"))
A13: ='Asset Register'!A13 | B13: ='Asset Register'!E13 | C13: ='Asset Register'!C13 | D13: ='Asset Register'!D13 | E13: ='Asset Register'!J13 | F13: =IFERROR(IF(IF('Asset Register'!C13="",0,MAX(MIN(Settings!$B$5-YEAR('Asset Register'!C13)+1,27),0))<1,0,IF(AND('Asset Register'!M13<>"",YEAR('Asset Register'!M13)<Settings!$B$5),0,INDEX('Schedule by Year'!$D13:$AD13,1,IF('Asset Register'!C13="",0,MAX(MIN(Settings!$B$5-YEAR('Asset Register'!C13)+1,27),0))))),0) | G13: =IFERROR(IF(IF('Asset Register'!C13="",0,MAX(MIN(Settings!$B$5-YEAR('Asset Register'!C13)+1,27),0))<=1,0,SUM(OFFSET('Schedule by Year'!$D13,0,0,1,IF('Asset Register'!C13="",0,MAX(MIN(Settings!$B$5-YEAR('Asset Register'!C13)+1,27),0))-1))),0) | H13: =IF(Settings!$B$6="Schedule C (active)","Sch C, line 13",IF(Settings!$B$6="Schedule E (passive)","Sch E, line 18","Ask CPA"))
A14: ='Asset Register'!A14 | B14: ='Asset Register'!E14 | C14: ='Asset Register'!C14 | D14: ='Asset Register'!D14 | E14: ='Asset Register'!J14 | F14: =IFERROR(IF(IF('Asset Register'!C14="",0,MAX(MIN(Settings!$B$5-YEAR('Asset Register'!C14)+1,27),0))<1,0,IF(AND('Asset Register'!M14<>"",YEAR('Asset Register'!M14)<Settings!$B$5),0,INDEX('Schedule by Year'!$D14:$AD14,1,IF('Asset Register'!C14="",0,MAX(MIN(Settings!$B$5-YEAR('Asset Register'!C14)+1,27),0))))),0) | G14: =IFERROR(IF(IF('Asset Register'!C14="",0,MAX(MIN(Settings!$B$5-YEAR('Asset Register'!C14)+1,27),0))<=1,0,SUM(OFFSET('Schedule by Year'!$D14,0,0,1,IF('Asset Register'!C14="",0,MAX(MIN(Settings!$B$5-YEAR('Asset Register'!C14)+1,27),0))-1))),0) | H14: =IF(Settings!$B$6="Schedule C (active)","Sch C, line 13",IF(Settings!$B$6="Schedule E (passive)","Sch E, line 18","Ask CPA"))
A15: ='Asset Register'!A15 | B15: ='Asset Register'!E15 | C15: ='Asset Register'!C15 | D15: ='Asset Register'!D15 | E15: ='Asset Register'!J15 | F15: =IFERROR(IF(IF('Asset Register'!C15="",0,MAX(MIN(Settings!$B$5-YEAR('Asset Register'!C15)+1,27),0))<1,0,IF(AND('Asset Register'!M15<>"",YEAR('Asset Register'!M15)<Settings!$B$5),0,INDEX('Schedule by Year'!$D15:$AD15,1,IF('Asset Register'!C15="",0,MAX(MIN(Settings!$B$5-YEAR('Asset Register'!C15)+1,27),0))))),0) | G15: =IFERROR(IF(IF('Asset Register'!C15="",0,MAX(MIN(Settings!$B$5-YEAR('Asset Register'!C15)+1,27),0))<=1,0,SUM(OFFSET('Schedule by Year'!$D15,0,0,1,IF('Asset Register'!C15="",0,MAX(MIN(Settings!$B$5-YEAR('Asset Register'!C15)+1,27),0))-1))),0) | H15: =IF(Settings!$B$6="Schedule C (active)","Sch C, line 13",IF(Settings!$B$6="Schedule E (passive)","Sch E, line 18","Ask CPA"))
A16: ='Asset Register'!A16 | B16: ='Asset Register'!E16 | C16: ='Asset Register'!C16 | D16: ='Asset Register'!D16 | E16: ='Asset Register'!J16 | F16: =IFERROR(IF(IF('Asset Register'!C16="",0,MAX(MIN(Settings!$B$5-YEAR('Asset Register'!C16)+1,27),0))<1,0,IF(AND('Asset Register'!M16<>"",YEAR('Asset Register'!M16)<Settings!$B$5),0,INDEX('Schedule by Year'!$D16:$AD16,1,IF('Asset Register'!C16="",0,MAX(MIN(Settings!$B$5-YEAR('Asset Register'!C16)+1,27),0))))),0) | G16: =IFERROR(IF(IF('Asset Register'!C16="",0,MAX(MIN(Settings!$B$5-YEAR('Asset Register'!C16)+1,27),0))<=1,0,SUM(OFFSET('Schedule by Year'!$D16,0,0,1,IF('Asset Register'!C16="",0,MAX(MIN(Settings!$B$5-YEAR('Asset Register'!C16)+1,27),0))-1))),0) | H16: =IF(Settings!$B$6="Schedule C (active)","Sch C, line 13",IF(Settings!$B$6="Schedule E (passive)","Sch E, line 18","Ask CPA"))
A17: ='Asset Register'!A17 | B17: ='Asset Register'!E17 | C17: ='Asset Register'!C17 | D17: ='Asset Register'!D17 | E17: ='Asset Register'!J17 | F17: =IFERROR(IF(IF('Asset Register'!C17="",0,MAX(MIN(Settings!$B$5-YEAR('Asset Register'!C17)+1,27),0))<1,0,IF(AND('Asset Register'!M17<>"",YEAR('Asset Register'!M17)<Settings!$B$5),0,INDEX('Schedule by Year'!$D17:$AD17,1,IF('Asset Register'!C17="",0,MAX(MIN(Settings!$B$5-YEAR('Asset Register'!C17)+1,27),0))))),0) | G17: =IFERROR(IF(IF('Asset Register'!C17="",0,MAX(MIN(Settings!$B$5-YEAR('Asset Register'!C17)+1,27),0))<=1,0,SUM(OFFSET('Schedule by Year'!$D17,0,0,1,IF('Asset Register'!C17="",0,MAX(MIN(Settings!$B$5-YEAR('Asset Register'!C17)+1,27),0))-1))),0) | H17: =IF(Settings!$B$6="Schedule C (active)","Sch C, line 13",IF(Settings!$B$6="Schedule E (passive)","Sch E, line 18","Ask CPA"))
A18: ='Asset Register'!A18 | B18: ='Asset Register'!E18 | C18: ='Asset Register'!C18 | D18: ='Asset Register'!D18 | E18: ='Asset Register'!J18 | F18: =IFERROR(IF(IF('Asset Register'!C18="",0,MAX(MIN(Settings!$B$5-YEAR('Asset Register'!C18)+1,27),0))<1,0,IF(AND('Asset Register'!M18<>"",YEAR('Asset Register'!M18)<Settings!$B$5),0,INDEX('Schedule by Year'!$D18:$AD18,1,IF('Asset Register'!C18="",0,MAX(MIN(Settings!$B$5-YEAR('Asset Register'!C18)+1,27),0))))),0) | G18: =IFERROR(IF(IF('Asset Register'!C18="",0,MAX(MIN(Settings!$B$5-YEAR('Asset Register'!C18)+1,27),0))<=1,0,SUM(OFFSET('Schedule by Year'!$D18,0,0,1,IF('Asset Register'!C18="",0,MAX(MIN(Settings!$B$5-YEAR('Asset Register'!C18)+1,27),0))-1))),0) | H18: =IF(Settings!$B$6="Schedule C (active)","Sch C, line 13",IF(Settings!$B$6="Schedule E (passive)","Sch E, line 18","Ask CPA"))
A19: ='Asset Register'!A19 | B19: ='Asset Register'!E19 | C19: ='Asset Register'!C19 | D19: ='Asset Register'!D19 | E19: ='Asset Register'!J19 | F19: =IFERROR(IF(IF('Asset Register'!C19="",0,MAX(MIN(Settings!$B$5-YEAR('Asset Register'!C19)+1,27),0))<1,0,IF(AND('Asset Register'!M19<>"",YEAR('Asset Register'!M19)<Settings!$B$5),0,INDEX('Schedule by Year'!$D19:$AD19,1,IF('Asset Register'!C19="",0,MAX(MIN(Settings!$B$5-YEAR('Asset Register'!C19)+1,27),0))))),0) | G19: =IFERROR(IF(IF('Asset Register'!C19="",0,MAX(MIN(Settings!$B$5-YEAR('Asset Register'!C19)+1,27),0))<=1,0,SUM(OFFSET('Schedule by Year'!$D19,0,0,1,IF('Asset Register'!C19="",0,MAX(MIN(Settings!$B$5-YEAR('Asset Register'!C19)+1,27),0))-1))),0) | H19: =IF(Settings!$B$6="Schedule C (active)","Sch C, line 13",IF(Settings!$B$6="Schedule E (passive)","Sch E, line 18","Ask CPA"))
... A107: ='Asset Register'!A107 | B107: ='Asset Register'!E107 | C107: ='Asset Register'!C107 | D107: ='Asset Register'!D107 | E107: ='Asset Register'!J107 | F107: =IFERROR(IF(IF('Asset Register'!C107="",0,MAX(MIN(Settings!$B$5-YEAR('Asset Register'!C107)+1,27),0))<1,0,IF(AND('Asset Register'!M107<>"",YEAR('Asset Register'!M107)<Settings!$B$5),0,INDEX('Schedule by Year'!$D107:$AD107,1,IF('Asset Register'!C107="",0,MAX(MIN(Settings!$B$5-YEAR('Asset Register'!C107)+1,27),0))))),0) | G107: =IFERROR(IF(IF('Asset Register'!C107="",0,MAX(MIN(Settings!$B$5-YEAR('Asset Register'!C107)+1,27),0))<=1,0,SUM(OFFSET('Schedule by Year'!$D107,0,0,1,IF('Asset Register'!C107="",0,MAX(MIN(Settings!$B$5-YEAR('Asset Register'!C107)+1,27),0))-1))),0) | H107: =IF(Settings!$B$6="Schedule C (active)","Sch C, line 13",IF(Settings!$B$6="Schedule E (passive)","Sch E, line 18","Ask CPA"))
A108: Portfolio total → | F108: =SUM(F8:F107) | G108: =SUM(G8:G107) | H108: ↓ drop on form
A110: ⓘ Schedule line mapping reads from Settings!B6. Active business hosts (substantial services — daily cleaning, meals, concierge) file Schedule C; most STR landlords file Schedule E. When in doubt, ask your CPA — the choice drives whether self-employment tax (15.3%) applies.

Sheet Form 4562 Worksheet
A2: =HYPERLINK("#'Current Year Summary'!A1", "← BACK") | D2: FORM 4562 WORKSHEET | J2: =HYPERLINK("#'Settings'!A1", "NEXT →")
A4: Mirror of IRS Form 4562 — Parts I (§179), II (Bonus), III (MACRS), and Part V (Listed Property — vehicles). Print + hand to your CPA.
A6: PART I — §179 ELECTION TO EXPENSE
A7: 1 | B7: Total §179 elected (sum from Asset Register col H): | C7: =SUM('Asset Register'!H8:H107)
A9: PART II — SPECIAL DEPRECIATION (BONUS)
A10: 14 | B10: Total Bonus depreciation (sum from Asset Register col I): | C10: =SUM('Asset Register'!I8:I107)
A12: PART III — MACRS DEPRECIATION (current year)
A13: 17 | B13: MACRS deduction for assets placed in service prior years: | C13: ='Current Year Summary'!F109
A14: 19a-i | B14: MACRS deduction for current-year placements (subset of 17): | C14: =SUMIFS('Current Year Summary'!F8:F107,'Asset Register'!C8:C107,">="&DATE(Settings!$B$5,1,1))
A15: TOT | B15: GRAND TOTAL CURRENT-YEAR DEPRECIATION: | C15: ='Current Year Summary'!F109+SUM('Asset Register'!I8:I107)
A17: PART V — LISTED PROPERTY (VEHICLES) — §280F
B19: Vehicle (Asset name) | C19: Date placed in service | D19: Total miles (Y) | E19: Business miles (Y) | F19: Commuting miles (Y) | G19: Other personal (Y) | H19: Business-use % | I19: Evidence kept?
B20: Ford F-150 (heavy truck >6,000lb) | C20: 45306 | D20: 12500 | E20: 9750 | F20: 1500 | G20: 1250 | H20: 0.78 | I20: Y
A26: ⓘ Listed-property §280F rule: vehicles must be used > 50% for qualified business use to claim §179 or bonus depreciation in Year 1. If business-use % drops to ≤ 50% in a later year, prior accelerated depreciation can be recaptured as ordinary income. Investment use (e.g., bank trips for STR deposits) is deductible but does NOT count toward the 50% test.
A28: ⓘ Pull total / business / commuting miles from your TAX-001 Mileage Log if you maintain one. Otherwise enter manual year-end totals. Evidence-kept = log, calendar entries, receipts, contractor agreements supporting the business-use percentage.

Sheet Settings
A2: =HYPERLINK("#'Form 4562 Worksheet'!A1", "← BACK") | D2: SETTINGS
A4: Active tax year · property list · Schedule C/E classification · MACRS percentage table (IRS Pub 946 Tables A-1 / A-6).
A5: Active tax year: | B5: 2026
A6: Schedule classification: | B6: Schedule E (passive)
A7: Property list: | B7: Smokies Ridge Cabin
B8: Creek Side Lodge
B9: Lakehouse A
A18: 📅 MACRS percentage tables current as of IRS Pub 946 (2024 rev). Tables A-1 / A-6 — half-year + mid-month conventions. Update if IRS revises.
A20: MACRS Percentage Table
A21: Class | B21: Recovery (yr) | C21: Y1 | D21: Y2 | E21: Y3 | F21: Y4 | G21: Y5 | H21: Y6 | I21: Y7 | J21: Y8 | K21: Y9 | L21: Y10 | M21: Y11 | N21: Y12 | O21: Y13 | P21: Y14 | Q21: Y15 | R21: Y16 | S21: Y17 | T21: Y18 | U21: Y19 | V21: Y20 | W21: Y21 | X21: Y22 | Y21: Y23 | Z21: Y24 | AA21: Y25 | AB21: Y26 | AC21: Y27
A22: 5 | B22: 5 | C22: 0.2 | D22: 0.32 | E22: 0.192 | F22: 0.1152 | G22: 0.1152 | H22: 0.0576 | I22: 0 | J22: 0 | K22: 0 | L22: 0 | M22: 0 | N22: 0 | O22: 0 | P22: 0 | Q22: 0 | R22: 0 | S22: 0 | T22: 0 | U22: 0 | V22: 0 | W22: 0 | X22: 0 | Y22: 0 | Z22: 0 | AA22: 0 | AB22: 0 | AC22: 0
A23: 7 | B23: 7 | C23: 0.1429 | D23: 0.2449 | E23: 0.1749 | F23: 0.1249 | G23: 0.0893 | H23: 0.0892 | I23: 0.0893 | J23: 0.0446 | K23: 0 | L23: 0 | M23: 0 | N23: 0 | O23: 0 | P23: 0 | Q23: 0 | R23: 0 | S23: 0 | T23: 0 | U23: 0 | V23: 0 | W23: 0 | X23: 0 | Y23: 0 | Z23: 0 | AA23: 0 | AB23: 0 | AC23: 0
A24: 15 | B24: 15 | C24: 0.05 | D24: 0.095 | E24: 0.0855 | F24: 0.077 | G24: 0.0693 | H24: 0.0623 | I24: 0.059 | J24: 0.059 | K24: 0.0591 | L24: 0.059 | M24: 0.0591 | N24: 0.059 | O24: 0.0591 | P24: 0.059 | Q24: 0.0591 | R24: 0.0295 | S24: 0 | T24: 0 | U24: 0 | V24: 0 | W24: 0 | X24: 0 | Y24: 0 | Z24: 0 | AA24: 0 | AB24: 0 | AC24: 0
A25: 27.5 | B25: 27.5 | C25: 0.03485 | D25: 0.03636 | E25: 0.03636 | F25: 0.03636 | G25: 0.03636 | H25: 0.03636 | I25: 0.03636 | J25: 0.03636 | K25: 0.03636 | L25: 0.03636 | M25: 0.03636 | N25: 0.03636 | O25: 0.03636 | P25: 0.03636 | Q25: 0.03636 | R25: 0.03636 | S25: 0.03636 | T25: 0.03636 | U25: 0.03636 | V25: 0.03636 | W25: 0.03636 | X25: 0.03636 | Y25: 0.03636 | Z25: 0.03636 | AA25: 0.03636 | AB25: 0.03636 | AC25: 0.03636
A26: 39 | B26: 39 | C26: 0.02461 | D26: 0.02564 | E26: 0.02564 | F26: 0.02564 | G26: 0.02564 | H26: 0.02564 | I26: 0.02564 | J26: 0.02564 | K26: 0.02564 | L26: 0.02564 | M26: 0.02564 | N26: 0.02564 | O26: 0.02564 | P26: 0.02564 | Q26: 0.02564 | R26: 0.02564 | S26: 0.02564 | T26: 0.02564 | U26: 0.02564 | V26: 0.02564 | W26: 0.02564 | X26: 0.02564 | Y26: 0.02564 | Z26: 0.02564 | AA26: 0.02564 | AB26: 0.02564 | AC26: 0.02564
A27: Land | B27: n/a | C27: 0 | D27: 0 | E27: 0 | F27: 0 | G27: 0 | H27: 0 | I27: 0 | J27: 0 | K27: 0 | L27: 0 | M27: 0 | N27: 0 | O27: 0 | P27: 0 | Q27: 0 | R27: 0 | S27: 0 | T27: 0 | U27: 0 | V27: 0 | W27: 0 | X27: 0 | Y27: 0 | Z27: 0 | AA27: 0 | AB27: 0 | AC27: 0
A30: Year-end Archive
A31: Year | B31: Assets tracked | C31: Current-year deprec. | D31: Accumulated | E31: §179 used | F31: Bonus used
A32: 2024
A33: 2025
A34: 2026
A35: 2027
A36: 2028
A37: 2029
A38: 2030
A42: Questions? hello@thestrledger.com
A43: TAX-013 · v2.3 · Free updates forever
