Workbook

Sheet Start
A2: The STR Ledger
A4: SE Tax Calculator
A5: Compute your 15.3% SE tax. Know what you owe.
A6: =IF(IFERROR('SE Tax Calc'!B17,0)>0,"⚠ SE tax due = "&TEXT('SE Tax Calc'!B17,"$#,##0")&" · ½ deductible = "&TEXT('SE Tax Calc'!B18,"$#,##0"),"📊 Enter your Net SE Income to see your SE tax.")
A7: TAX-008 · v2.3 · BLANK
A11: What you'll get
A13: 💰 SE TAX $ | E13: 📉 ½ ADJUSTMENT | I13: 📄 SCHEDULE SE
A14: Your total Schedule SE Line 12 with SS + Medicare + Addl Medicare. | E14: Schedule 1 Line 15 — 50% of SE tax deductible above the line. | I14: Print-ready Schedule SE Part I + Part II mirror for your CPA.
A23: Quick Start — be done in 5 minutes
B24: ① Net SE income (Schedule C / F / K-1) | H24: ④ Review SE Tax Calc — auto-computed
B25: ② W-2 wages this year (yours + spouse if MFJ) | H25: ⑤ Print Schedule SE Map for your CPA
B26: ③ Filing status (drives Additional Medicare threshold)
A30: =HYPERLINK("#'Net SE Income'!A5", "GET STARTED — ENTER NET SE INCOME →")
A36: Progress: | G36: =TEXT((COUNTA('Net SE Income'!B8:B10) + COUNTA('Wage Base & W-2'!B8:B9) + COUNTA('Adjustments'!B8))/6,"0%") & " complete"
A38: ① Net SE Income | G38: =IF(COUNTA('Net SE Income'!B8:B10)=3,"✅ Done",IF(COUNTA('Net SE Income'!B8:B10)=0,"⏳ Empty","⏳ "&COUNTA('Net SE Income'!B8:B10)&" of 3")) | K38: =HYPERLINK("#'Net SE Income'!A5","→ go")
A39: ② Wage Base & W-2 | G39: =IF(COUNTA('Wage Base & W-2'!B8:B9)=2,"✅ Done",IF(COUNTA('Wage Base & W-2'!B8:B9)=0,"⏳ Empty","⏳ "&COUNTA('Wage Base & W-2'!B8:B9)&" of 2")) | K39: =HYPERLINK("#'Wage Base & W-2'!A5","→ go")
A40: ③ Adjustments | G40: =IF(COUNTA('Adjustments'!B8)=1,"✅ Done",IF(COUNTA('Adjustments'!B8)=0,"⏳ Empty","⏳ "&COUNTA('Adjustments'!B8)&" of 1")) | K40: =HYPERLINK("#'Adjustments'!A5","→ go")
A46: Questions? hello@thestrledger.com
A47: TAX-008 · v2.2 · Free updates forever

Sheet Net SE Income
A2: =HYPERLINK("#'Start'!A1", "← START") | D2: SECTION 1 OF 3 | J2: =HYPERLINK("#'Wage Base & W-2'!A5", "NEXT →")
A4: Net SE Income
A5: Schedule C / F / K-1 — IRS Schedule SE Lines 1a, 1b, 2.
A6: Fill the highlighted fields below.
A7: NET SE INCOME
A8: Schedule C net profit ($):
A9: Schedule F net farm profit ($):
A10: Partnership SE income (K-1 Box 14A):
A12: Total net SE income (Line 3): | B12: =SUM(B8:B10)
A14: ⓘ De minimis exception (IRC §1402(a)): if total Net SE Income is < $400, no SE tax owed. Schedule E rental income is NOT subject to SE tax — only Schedule C (active business) and Schedule F (farm) income.
A16: =HYPERLINK("#'Start'!A1", "← Back: Start") | G16: =HYPERLINK("#'Wage Base & W-2'!A5", "Next: Wage Base & W-2 →")

Sheet Wage Base & W-2
A2: =HYPERLINK("#'Net SE Income'!A5", "← BACK") | D2: SECTION 2 OF 3 | J2: =HYPERLINK("#'Adjustments'!A5", "NEXT →")
A4: Wage Base & W-2
A5: W-2 wages count toward the SS wage base — Schedule SE Line 8a.
A6: Fill the highlighted fields below.
A7: WAGE BASE & W-2
A8: Your W-2 wages this year ($):
A9: Spouse W-2 wages this year ($, MFJ):
A11: Social Security wage base (Settings): | B11: =Settings!B6
A13: ⓘ The Social Security portion of SE tax (12.4%) only applies to income up to the wage base. Your W-2 wages this year fill that base first; SE income above what's left of the base owes only the 2.9% Medicare portion. If you've already maxed your W-2 above the wage base, NO SS portion of SE tax applies.
A15: =HYPERLINK("#'Net SE Income'!A5", "← Back: Net SE Income") | G15: =HYPERLINK("#'Adjustments'!A5", "Next: Adjustments →")

Sheet Adjustments
A2: =HYPERLINK("#'Wage Base & W-2'!A5", "← BACK") | D2: SECTION 3 OF 3 | J2: =HYPERLINK("#'SE Tax Calc'!A5", "NEXT →")
A4: Adjustments
A5: Filing status — drives Additional Medicare 0.9% threshold.
A6: Fill the highlighted fields below.
A7: ADJUSTMENTS
A8: Filing status:
A10: Additional Medicare 0.9% threshold: | B10: =IF(B8="MFJ",250000,IF(B8="MFS",125000,200000))
A12: ⓘ Additional Medicare tax (IRC §1401(b)(2)): 0.9% applies to Medicare wages + SE income above $200K (Single/HoH), $250K (MFJ), or $125K (MFS). Combined with the regular 2.9% Medicare, this stacks to 3.8% on income above the threshold.
A14: =HYPERLINK("#'Wage Base & W-2'!A5", "← Back: Wage Base & W-2") | G14: =HYPERLINK("#'SE Tax Calc'!A5", "Next: SE Tax Calc →")

Sheet SE Tax Calc
A2: =HYPERLINK("#'Adjustments'!A1", "← BACK") | D2: SE TAX CALC | J2: =HYPERLINK("#'Schedule SE Map'!A1", "NEXT →")
A4: Step-by-step SE tax computation — Schedule SE Lines 3-12.
A5: Net SE income (from Net SE Income tab): | B5: ='Net SE Income'!B12
A6: × 92.35% (employer-equivalent factor): | B6: =B5*0.9235
A7: Net Earnings from SE (NESE) — Line 4a: | B7: =B6
A8: Your W-2 wages this year: | B8: ='Wage Base & W-2'!B8
A9: Social Security wage base (Settings): | B9: =Settings!B6
A10: Wage-base headroom (= base − W-2): | B10: =MAX(B9-B8,0)
A11: SS-portion subject to 12.4%: | B11: =MIN(B7,B10)
A12: Social Security tax (Line 10): | B12: =B11*0.124
A13: Medicare tax (Line 11) — 2.9% × NESE: | B13: =B7*0.029
A14: Combined NESE + W-2 (for Addl Medicare check): | B14: =B7+B8+'Wage Base & W-2'!B9
A15: Additional Medicare threshold (filing-status): | B15: =IF('Adjustments'!B8="MFJ",250000,IF('Adjustments'!B8="MFS",125000,200000))
A16: Additional Medicare tax (0.9% × excess): | B16: =MAX(B14-B15,0)*0.009
A17: TOTAL SE TAX (Line 12) — to Sched 2 Line 4: | B17: =B12+B13+B16
A18: ½ SE tax adjustment (Sched 1 Line 15): | B18: =B17/2
A20: ⓘ Half-SE-tax adjustment is deductible above the line on Schedule 1 Line 15 — it reduces AGI directly. The other half is what you actually pay. If you have a spouse with separate SE income (MFJ), each spouse computes their own SE tax separately — they DO NOT combine.
A22: =HYPERLINK("#'Adjustments'!A5", "← Back: Adjustments") | G22: =HYPERLINK("#'Schedule SE Map'!A1", "Next: Schedule SE Map →")

Sheet Schedule SE Map
A2: =HYPERLINK("#'SE Tax Calc'!A1", "← BACK") | D2: SCHEDULE SE MAP | J2: =HYPERLINK("#'Launch'!A1", "NEXT →")
A4: Print this — IRS Schedule SE Part I + Part II mirror.
A5: Line | B5: Description | C5: Amount
A6: PART I — PART I — SELF-EMPLOYMENT TAX
A7: 1a | B7: Net farm profit | C7: ='Net SE Income'!B9
A8: 2 | B8: Net Schedule C profit | C8: ='Net SE Income'!B8
B9: Partnership SE (K-1 Box 14A) | C9: ='Net SE Income'!B10
A10: 3 | B10: Combined (sum) | C10: =C7+C8+C9
A11: 4a | B11: Multiply Line 3 by 92.35% | C11: =C10*0.9235
A12: 8a | B12: Total SS wages this year (W-2) | C12: ='Wage Base & W-2'!B8
A13: 8d | B13: Subtotal (W-2 entered for wage base): | C13: =C12
A14: 9 | B14: Subtract: SS wage base − W-2: | C14: =MAX(Settings!B6-C12,0)
A15: 10 | B15: SS portion (smaller of 4a or 9 × 12.4%): | C15: =MIN(C11,C14)*0.124
A16: 11 | B16: Medicare portion (Line 4a × 2.9%): | C16: =C11*0.029
A17: 12 | B17: Total SE tax (Line 10 + 11) | C17: =C15+C16
A18: 13 | B18: ½ SE tax adjustment | C18: =C17/2
A19: PART II — PART II — OPTIONAL METHODS
B20: (Not commonly used — see Sched SE for farm/non-farm methods) | C20: ""

Sheet Launch
A2: =HYPERLINK("#'Schedule SE Map'!A1", "← BACK") | D2: LAUNCH
A4: Your SE tax for the year
A5: Schedule 2 Line 4 + Schedule 1 Line 15.
A9: TOTAL SE TAX | E9: ½ ADJUSTMENT | I9: NESE (Line 4a)
A10: ='SE Tax Calc'!B17 | E10: ='SE Tax Calc'!B18 | I10: ='SE Tax Calc'!B7
A12: to Schedule 2 Line 4 | E12: to Schedule 1 Line 15 | I12: net earnings from SE
A16: =HYPERLINK("#'Schedule SE Map'!A1", "📄 PRINT SCHEDULE SE MAP →")
A23: 💡 Upgrade to the Tax Season Bundle ($147).
A26: Questions? hello@thestrledger.com
A27: TAX-008 · v2.2 · Free updates forever

Sheet Settings
A2: =HYPERLINK("#'Launch'!A1", "← BACK") | D2: SETTINGS
A4: Active tax year · SS wage base · rates.
A5: Active tax year: | B5: 2026
A6: SS wage base ($): | B6: 176100
A7: SS rate (12.4%): | B7: 0.124
A8: Medicare rate (2.9%): | B8: 0.029
A9: Additional Medicare rate (0.9%): | B9: 0.009
A10: NESE factor (92.35%): | B10: 0.9235
A12: Historical wage bases:
A13: 2023: | B13: 160200
A14: 2024: | B14: 168600
A15: 2025: | B15: 176100
A17: Year-end Archive
A18: Year | B18: NESE | C18: SE Tax | D18: ½ Adjustment
A19: 2024
A20: 2025
A21: 2026
A22: 2027
A23: 2028
A24: 2029
A25: 2030
