Workbook

Sheet Start
A2: The STR Ledger
A4: Section 179 Planner
A5: Front-load this year's depreciation. Legally.
A6: =IF(IFERROR('Income Limitation'!B17,0)>0,"✅ Year-1 deduction = "&TEXT('Income Limitation'!B17,"$#,##0")&" · §179 used = "&TEXT('Income Limitation'!B14,"$#,##0"),"📊 Add an asset on Asset List to see your deduction.")
A7: TAX-009 · v2.3 · BLANK
A11: What you'll get
A13: ⚡ §179 ELECTION | E13: 📅 BONUS DEPR | I13: 📄 FORM 4562
A14: Up to $1,250,000 expensed this year (2026 cap), per-asset choice. | E14: 40% bonus depreciation in 2026 — phasing down to 0% by 2028. | I14: Print-ready Form 4562 Part I (§179) + Part II (bonus) mirror.
A23: Quick Start — be done in 15 minutes
B24: ① Eligibility: active biz, schedule, listed-property check | H24: ④ Income limit: net biz income for §179 cap
B25: ② Asset List: cost, MACRS class, date, business % | H25: ⑤ Print Form 4562 Map for your CPA
B26: ③ Per-asset method: §179 / Bonus / MACRS
A30: =HYPERLINK("#'Eligibility'!A5", "GET STARTED — CHECK ELIGIBILITY →")
A36: Progress: | G36: =TEXT((COUNTA('Eligibility'!B8:B10) + COUNTA('Asset List'!B8:F22) + COUNTA('Election Per Asset'!B8:B22) + COUNTA('Income Limitation'!B8))/54,"0%") & " complete"
A38: ① Eligibility | G38: =IF(COUNTA('Eligibility'!B8:B10)>=3,"✅ Done",IF(COUNTA('Eligibility'!B8:B10)=0,"⏳ Empty","⏳ "&COUNTA('Eligibility'!B8:B10)&" of 3")) | K38: =HYPERLINK("#'Eligibility'!A5","→ go")
A39: ② Asset List | G39: =IF(COUNTA('Asset List'!B8:F22)>=45,"✅ Done",IF(COUNTA('Asset List'!B8:F22)=0,"⏳ Empty","⏳ "&COUNTA('Asset List'!B8:F22)&" of 45")) | K39: =HYPERLINK("#'Asset List'!A5","→ go")
A40: ③ Election Per Asset | G40: =IF(COUNTA('Election Per Asset'!B8:B22)>=5,"✅ Done",IF(COUNTA('Election Per Asset'!B8:B22)=0,"⏳ Empty","⏳ "&COUNTA('Election Per Asset'!B8:B22)&" of 5")) | K40: =HYPERLINK("#'Election Per Asset'!A5","→ go")
A41: ④ Income Limitation | G41: =IF(COUNTA('Income Limitation'!B8)>=1,"✅ Done",IF(COUNTA('Income Limitation'!B8)=0,"⏳ Empty","⏳ "&COUNTA('Income Limitation'!B8)&" of 1")) | K41: =HYPERLINK("#'Income Limitation'!A5","→ go")
A46: Questions? hello@thestrledger.com
A47: TAX-009 · v2.2 · Free updates forever

Sheet Eligibility
A2: =HYPERLINK("#'Start'!A1", "← START") | D2: SECTION 1 OF 4 | J2: =HYPERLINK("#'Asset List'!A5", "NEXT →")
A4: Eligibility
A5: Active business test, classification, listed-property check.
A6: Fill the highlighted fields below.
A7: ELIGIBILITY
A8: Active trade/business? (Y/N)
A9: Schedule classification:
A10: Listed property used > 50% for business? (vehicles/computers)
A12: Verdict: | B12: =IF(B8="N","NOT ELIGIBLE — §179 requires an active trade/business.",IF(B9="Schedule E (passive)","PARTIAL — Schedule E real estate is NOT eligible, but personal-property assets used in the rental are.","ELIGIBLE — proceed to Asset List."))
A14: ⓘ §179 is NOT allowed for residential rental REAL ESTATE itself, but IS allowed for personal-property assets used in an active rental business (appliances, furniture, hot tubs, vehicles). Listed property (vehicles, historically computers) requires > 50% business use to qualify for §179.
A16: =HYPERLINK("#'Start'!A1", "← Back: Start") | G16: =HYPERLINK("#'Asset List'!A5", "Next: Asset List →")

Sheet Asset List
A2: =HYPERLINK("#'Eligibility'!A5", "← BACK") | D2: SECTION 2 OF 4 | J2: =HYPERLINK("#'Election Per Asset'!A5", "NEXT →")
A4: Asset List
A5: Up to 15 assets. Cost, class, date, business %.
A6: MACRS classes: 5-yr (computers, vehicles), 7-yr (furniture/equipment), 15-yr (land improvements).
A7: # | B7: Asset description | C7: MACRS yr | D7: Cost ($) | E7: Date placed in service | F7: Biz % | G7: Vehicle?
A8: 1
A9: 2
A10: 3
A11: 4
A12: 5
A13: 6
A14: 7
A15: 8
A16: 9
A17: 10
A18: 11
A19: 12
... A22: 15
B23: Total cost: | D23: =SUM(D8:D22)
B24: =IF(D23>3130000,"⚠ Phase-out applies — §179 cap reduced $-for-$ over $3,130,000.","OK — under §179 phase-out threshold ($3,130,000).")
A26: ⓘ MACRS recovery period drives the per-year deduction floor. STR personal property is most often 5-yr (carpets, appliances, technology) or 7-yr (furniture, kitchen equipment). Land improvements (fences, sidewalks) = 15-yr. Buildings themselves = 27.5/39-yr (use the Schedule E Workbook + Home Office Allocator for those).
A28: =HYPERLINK("#'Eligibility'!A5", "← Back: Eligibility") | G28: =HYPERLINK("#'Election Per Asset'!A5", "Next: Election Per Asset →")

Sheet Election Per Asset
A2: =HYPERLINK("#'Asset List'!A5", "← BACK") | D2: SECTION 3 OF 4 | J2: =HYPERLINK("#'Income Limitation'!A5", "NEXT →")
A4: Election Per Asset
A5: Choose §179 / Bonus / MACRS for each asset.
A6: §179 (full this year) / Bonus (40% this year) / MACRS (over recovery period).
A7: # | B7: Asset (from Asset List) | C7: Method | D7: §179 deduction | E7: Bonus deduction | F7: Y1 MACRS deduction | G7: Total Y1
A8: ='Asset List'!A8 | B8: ='Asset List'!B8 | D8: =IF(C8="§179",IF('Asset List'!G8="Y",MIN('Asset List'!D8*'Asset List'!F8,30500*'Asset List'!F8),'Asset List'!D8*'Asset List'!F8),0) | E8: =IF(C8="Bonus",'Asset List'!D8*'Asset List'!F8*0.4,0) | F8: =IF(C8="MACRS",IFERROR(('Asset List'!D8*'Asset List'!F8)/'Asset List'!C8*0.5,0),0) | G8: =D8+E8+F8
A9: ='Asset List'!A9 | B9: ='Asset List'!B9 | D9: =IF(C9="§179",IF('Asset List'!G9="Y",MIN('Asset List'!D9*'Asset List'!F9,30500*'Asset List'!F9),'Asset List'!D9*'Asset List'!F9),0) | E9: =IF(C9="Bonus",'Asset List'!D9*'Asset List'!F9*0.4,0) | F9: =IF(C9="MACRS",IFERROR(('Asset List'!D9*'Asset List'!F9)/'Asset List'!C9*0.5,0),0) | G9: =D9+E9+F9
A10: ='Asset List'!A10 | B10: ='Asset List'!B10 | D10: =IF(C10="§179",IF('Asset List'!G10="Y",MIN('Asset List'!D10*'Asset List'!F10,30500*'Asset List'!F10),'Asset List'!D10*'Asset List'!F10),0) | E10: =IF(C10="Bonus",'Asset List'!D10*'Asset List'!F10*0.4,0) | F10: =IF(C10="MACRS",IFERROR(('Asset List'!D10*'Asset List'!F10)/'Asset List'!C10*0.5,0),0) | G10: =D10+E10+F10
A11: ='Asset List'!A11 | B11: ='Asset List'!B11 | D11: =IF(C11="§179",IF('Asset List'!G11="Y",MIN('Asset List'!D11*'Asset List'!F11,30500*'Asset List'!F11),'Asset List'!D11*'Asset List'!F11),0) | E11: =IF(C11="Bonus",'Asset List'!D11*'Asset List'!F11*0.4,0) | F11: =IF(C11="MACRS",IFERROR(('Asset List'!D11*'Asset List'!F11)/'Asset List'!C11*0.5,0),0) | G11: =D11+E11+F11
A12: ='Asset List'!A12 | B12: ='Asset List'!B12 | D12: =IF(C12="§179",IF('Asset List'!G12="Y",MIN('Asset List'!D12*'Asset List'!F12,30500*'Asset List'!F12),'Asset List'!D12*'Asset List'!F12),0) | E12: =IF(C12="Bonus",'Asset List'!D12*'Asset List'!F12*0.4,0) | F12: =IF(C12="MACRS",IFERROR(('Asset List'!D12*'Asset List'!F12)/'Asset List'!C12*0.5,0),0) | G12: =D12+E12+F12
A13: ='Asset List'!A13 | B13: ='Asset List'!B13 | D13: =IF(C13="§179",IF('Asset List'!G13="Y",MIN('Asset List'!D13*'Asset List'!F13,30500*'Asset List'!F13),'Asset List'!D13*'Asset List'!F13),0) | E13: =IF(C13="Bonus",'Asset List'!D13*'Asset List'!F13*0.4,0) | F13: =IF(C13="MACRS",IFERROR(('Asset List'!D13*'Asset List'!F13)/'Asset List'!C13*0.5,0),0) | G13: =D13+E13+F13
A14: ='Asset List'!A14 | B14: ='Asset List'!B14 | D14: =IF(C14="§179",IF('Asset List'!G14="Y",MIN('Asset List'!D14*'Asset List'!F14,30500*'Asset List'!F14),'Asset List'!D14*'Asset List'!F14),0) | E14: =IF(C14="Bonus",'Asset List'!D14*'Asset List'!F14*0.4,0) | F14: =IF(C14="MACRS",IFERROR(('Asset List'!D14*'Asset List'!F14)/'Asset List'!C14*0.5,0),0) | G14: =D14+E14+F14
A15: ='Asset List'!A15 | B15: ='Asset List'!B15 | D15: =IF(C15="§179",IF('Asset List'!G15="Y",MIN('Asset List'!D15*'Asset List'!F15,30500*'Asset List'!F15),'Asset List'!D15*'Asset List'!F15),0) | E15: =IF(C15="Bonus",'Asset List'!D15*'Asset List'!F15*0.4,0) | F15: =IF(C15="MACRS",IFERROR(('Asset List'!D15*'Asset List'!F15)/'Asset List'!C15*0.5,0),0) | G15: =D15+E15+F15
A16: ='Asset List'!A16 | B16: ='Asset List'!B16 | D16: =IF(C16="§179",IF('Asset List'!G16="Y",MIN('Asset List'!D16*'Asset List'!F16,30500*'Asset List'!F16),'Asset List'!D16*'Asset List'!F16),0) | E16: =IF(C16="Bonus",'Asset List'!D16*'Asset List'!F16*0.4,0) | F16: =IF(C16="MACRS",IFERROR(('Asset List'!D16*'Asset List'!F16)/'Asset List'!C16*0.5,0),0) | G16: =D16+E16+F16
A17: ='Asset List'!A17 | B17: ='Asset List'!B17 | D17: =IF(C17="§179",IF('Asset List'!G17="Y",MIN('Asset List'!D17*'Asset List'!F17,30500*'Asset List'!F17),'Asset List'!D17*'Asset List'!F17),0) | E17: =IF(C17="Bonus",'Asset List'!D17*'Asset List'!F17*0.4,0) | F17: =IF(C17="MACRS",IFERROR(('Asset List'!D17*'Asset List'!F17)/'Asset List'!C17*0.5,0),0) | G17: =D17+E17+F17
A18: ='Asset List'!A18 | B18: ='Asset List'!B18 | D18: =IF(C18="§179",IF('Asset List'!G18="Y",MIN('Asset List'!D18*'Asset List'!F18,30500*'Asset List'!F18),'Asset List'!D18*'Asset List'!F18),0) | E18: =IF(C18="Bonus",'Asset List'!D18*'Asset List'!F18*0.4,0) | F18: =IF(C18="MACRS",IFERROR(('Asset List'!D18*'Asset List'!F18)/'Asset List'!C18*0.5,0),0) | G18: =D18+E18+F18
A19: ='Asset List'!A19 | B19: ='Asset List'!B19 | D19: =IF(C19="§179",IF('Asset List'!G19="Y",MIN('Asset List'!D19*'Asset List'!F19,30500*'Asset List'!F19),'Asset List'!D19*'Asset List'!F19),0) | E19: =IF(C19="Bonus",'Asset List'!D19*'Asset List'!F19*0.4,0) | F19: =IF(C19="MACRS",IFERROR(('Asset List'!D19*'Asset List'!F19)/'Asset List'!C19*0.5,0),0) | G19: =D19+E19+F19
... A22: ='Asset List'!A22 | B22: ='Asset List'!B22 | D22: =IF(C22="§179",IF('Asset List'!G22="Y",MIN('Asset List'!D22*'Asset List'!F22,30500*'Asset List'!F22),'Asset List'!D22*'Asset List'!F22),0) | E22: =IF(C22="Bonus",'Asset List'!D22*'Asset List'!F22*0.4,0) | F22: =IF(C22="MACRS",IFERROR(('Asset List'!D22*'Asset List'!F22)/'Asset List'!C22*0.5,0),0) | G22: =D22+E22+F22
B23: Totals: | D23: =SUM(D8:D22) | E23: =SUM(E8:E22) | F23: =SUM(F8:F22) | G23: =SUM(G8:G22)
A25: ⓘ §179 capped per-year (currently $1.25M for 2026) AND limited by your business income (next tab). Bonus depreciation has NO income limit but the rate is phasing down (40% → 20% → 0% by 2028). MACRS spreads the deduction over the recovery period — slowest, but no Y1 limitation.
A27: =HYPERLINK("#'Asset List'!A5", "← Back: Asset List") | G27: =HYPERLINK("#'Income Limitation'!A5", "Next: Income Limitation →")

Sheet Income Limitation
A2: =HYPERLINK("#'Election Per Asset'!A5", "← BACK") | D2: SECTION 4 OF 4 | J2: =HYPERLINK("#'Form 4562 Map'!A5", "NEXT →")
A4: Income Limitation
A5: §179 deduction ≤ aggregate net business income.
A6: §179 cannot exceed aggregate net biz income — excess carries forward.
A7: INCOME LIMITATION
A8: Aggregate net business income (before §179):
A10: §179 elected (from Election Per Asset): | B10: ='Election Per Asset'!D23
A11: §179 cap (Settings): | B11: =Settings!B6
A12: Phase-out reduction (cost over threshold): | B12: =MAX('Asset List'!D23-Settings!B7,0)
A13: Adjusted §179 cap (after phase-out): | B13: =MAX(B11-B12,0)
A14: Allowed §179 (≤ adjusted cap AND ≤ biz income): | B14: =MIN(B10,B13,B8)
A15: Bonus depreciation (no income limit): | B15: ='Election Per Asset'!E23
A16: Y1 MACRS: | B16: ='Election Per Asset'!F23
A17: TOTAL Y1 DEDUCTION: | B17: =B14+B15+B16
A18: §179 carryover (excess deferred to next year): | B18: =MAX(B10-B14,0)
A20: ⓘ §179 carryover has no expiration — it stays on the books indefinitely until offset by future business income. Bonus depreciation does NOT carry over (it's used in full in Y1 regardless of business income). For STR hosts: aggregate biz income includes Schedule C net profit + W-2 wages from any active employment + spouse W-2 (MFJ filers).
A22: =HYPERLINK("#'Election Per Asset'!A5", "← Back: Election Per Asset") | G22: =HYPERLINK("#'Form 4562 Map'!A5", "Next: Form 4562 Map →")

Sheet Form 4562 Map
A2: =HYPERLINK("#'Income Limitation'!A1", "← BACK") | D2: FORM 4562 MAP | J2: =HYPERLINK("#'Launch'!A1", "NEXT →")
A4: IRS Form 4562 — Part I (§179) and Part II (Bonus) mirror.
A5: Line | B5: Description | C5: Amount
A6: Part I — PART I — §179 ELECTION TO EXPENSE
A7: 1 | B7: Maximum amount (Settings cap): | C7: =Settings!B6
A8: 2 | B8: Total cost of §179 property placed in service this year: | C8: ='Asset List'!D23
A9: 3 | B9: Threshold cost ($-for-$ phase-out start): | C9: =Settings!B7
A10: 4 | B10: Reduction in cap (Line 2 − Line 3, if positive): | C10: =MAX(C8-C9,0)
A11: 5 | B11: Adjusted cap (Line 1 − Line 4): | C11: =MAX(C7-C10,0)
A12: 8 | B12: Total §179 elected (sum of asset elections): | C12: ='Election Per Asset'!D23
A13: 9 | B13: Tentative deduction (smaller of Line 5 or Line 8): | C13: =MIN(C11,C13)
A14: 11 | B14: Business income limitation: | C14: ='Income Limitation'!B8
A15: 12 | B15: §179 deduction allowed (smallest of 9, 11): | C15: =MIN(C14,C15)
A16: 13 | B16: Carryover to 2027 (Line 8 − Line 12): | C16: =MAX(C13-C16,0)
A17: Part II — PART II — SPECIAL DEPRECIATION (BONUS)
A18: 14 | B18: Bonus depreciation (40% × cost × biz %): | C18: ='Election Per Asset'!E23
A19: Part III — PART III — MACRS (regular depreciation)
A20: 19a-i | B20: Y1 MACRS deduction (varies by class life): | C20: ='Election Per Asset'!F23
A21: Total | B21: GRAND TOTAL Y1 DEDUCTION: | C21: =C16+C19+C21

Sheet Launch
A2: =HYPERLINK("#'Form 4562 Map'!A1", "← BACK") | D2: LAUNCH
A4: Your Section 179 deduction
A5: Print Form 4562 Map and attach to Schedule C / E.
A9: TOTAL Y1 DEDUCTION | E9: §179 ALLOWED | I9: CARRYOVER
A10: ='Income Limitation'!B17 | E10: ='Income Limitation'!B14 | I10: ='Income Limitation'!B18
A12: §179 + Bonus + Y1 MACRS | E12: after income + cap limits | I12: deferred to next year
A16: =HYPERLINK("#'Form 4562 Map'!A1", "📄 PRINT FORM 4562 MAP →")
A23: 💡 Upgrade to the Tax Season Bundle ($147).
A26: Questions? hello@thestrledger.com
A27: TAX-009 · v2.2 · Free updates forever

Sheet Settings
A2: =HYPERLINK("#'Launch'!A1", "← BACK") | D2: SETTINGS
A4: Active tax year · §179 cap · phase-out · bonus % · vehicle cap.
A5: Active tax year: | B5: 2026
A6: §179 maximum deduction (cap): | B6: 1250000
A7: §179 phase-out threshold: | B7: 3130000
A8: Bonus depreciation % (placed in service Y1): | B8: 0.4
A9: Heavy SUV/truck §179 cap (>6,000 lb GVWR): | B9: 30500
A10: 📅 §179 cap, phase-out + bonus % as of 2026-01-01 — IRS adjusts the cap each Nov; bonus is statutory and phases to 0% by 2028.
A11: Historical reference (bonus depr %):
A12: 2023: | B12: 0.8
A13: 2024: | B13: 0.6
A14: 2025: | B14: 0.5
A15: 2026: | B15: 0.4
A16: 2027: | B16: 0.2
A17: 2028: | B17: 0
A19: Year-end Archive
A20: Year | B20: §179 elected | C20: §179 allowed | D20: Bonus | E20: Y1 MACRS | F20: Carryover
A21: 2024
A22: 2025
A23: 2026
A24: 2027
A25: 2028
A26: 2029
A27: 2030
